Workbook
Name chtB: OFFSET('组合净值（模拟）'!$B$6,0,0,COUNT('组合净值（模拟）'!$B$6:$B$2000),1)
Name chtDate: OFFSET('组合净值（模拟）'!$A$6,0,0,COUNT('组合净值（模拟）'!$B$6:$B$2000),1)
Name chtE: OFFSET('组合净值（模拟）'!$E$6,0,0,COUNT('组合净值（模拟）'!$E$6:$E$2000),1)
Name chtH: OFFSET('组合净值（模拟）'!$H$6,0,0,COUNT('组合净值（模拟）'!$H$6:$H$2000),1)
Name chtK: OFFSET('组合净值（模拟）'!$K$6,0,0,COUNT('组合净值（模拟）'!$K$6:$K$2000),1)

Sheet 持仓配置
A1: 持仓配置（初始权重）
A2: 基金简称 | B2: 宏利复兴混合A | C2: 信澳业绩驱动A | D2: 嘉实信息产业A | E2: 银华集成电路混合A | F2: 中欧中证500指增A | G2: 天弘中证1000指增A | H2: 华泰柏瑞中证2000指增A | I2: 博道沪深300指增A | J2: 易方达中债新综指LOFA | K2: 华安黄金ETF联接A | L2: 国泰半导体材料设备ETF联接A | M2: 国泰通信设备ETF联接A | N2: 嘉实快线货币A | O2: 合计 | P2: 年化费率(年)
A3: 基金代码 | B3: 001170.OF | C3: 016370.OF | D3: 017488.OF | E3: 013840.OF | F3: 015453.OF | G3: 014201.OF | H3: 019923.OF | I3: 007044.OF | J3: 161119.OF | K3: 000216.OF | L3: 019632.OF | M3: 007817.OF | N3: 000917.OF
A4: 10-90 权重 | B4: 0.01 | C4: 0.01 | D4: 0.01 | E4: 0.01 | F4: 0.0125 | G4: 0.0125 | H4: 0.0125 | I4: 0.0125 | J4: 0.83 | K4: 0.05 | L4: 0.005 | M4: 0.005 | N4: 0.02 | O4: =SUM(B4:N4) -> 1 | P4: 0.005
A5: 20-80 权重 | B5: 0.02 | C5: 0.02 | D5: 0.02 | E5: 0.02 | F5: 0.025 | G5: 0.025 | H5: 0.025 | I5: 0.025 | J5: 0.73 | K5: 0.05 | L5: 0.01 | M5: 0.01 | N5: 0.02 | O5: =SUM(B5:N5) -> 1 | P5: 0.01
A6: 30-70 权重 | B6: 0.03 | C6: 0.03 | D6: 0.03 | E6: 0.03 | F6: 0.0375 | G6: 0.0375 | H6: 0.0375 | I6: 0.0375 | J6: 0.58 | K6: 0.1 | L6: 0.015 | M6: 0.015 | N6: 0.02 | O6: =SUM(B6:N6) -> 1 | P6: 0.012
A7: 增值 权重 | B7: 0.19 | C7: 0.19 | D7: 0.19 | E7: 0.19 | F7: 0 | G7: 0 | H7: 0 | I7: 0 | J7: 0 | K7: 0 | L7: 0.11 | M7: 0.11 | N7: 0.02 | O7: =SUM(B7:N7) -> 1 | P7: 0.012
A8: 基准指数(参考，不计入组合)
A9: 科创创业50等权 | B9: 932381.CSI
A10: 中证800 | B10: 000906.SH
A11: 沪深300 | B11: 000300.SH
A12: 中证500 | B12: 000905.SH
A13: 中证1000 | B13: 000852.SH
A14: 中证2000 | B14: 932000.CSI
A16: 权重为蓝色输入；P列为各组合年化费率(蓝色输入，已折每日扣减)。下游净值与看板自动重算。

Sheet 净值数据(iFinD公式)
A1: 净值数据 · iFinD 实时拉取（复权单位净值）
A2: =TODAY()-1 -> 46210
A3: 基金代码→ | B3: =持仓配置!B3 -> 001170.OF | C3: =持仓配置!C3 -> 016370.OF | D3: =持仓配置!D3 -> 017488.OF | E3: =持仓配置!E3 -> 013840.OF | F3: =持仓配置!F3 -> 015453.OF | G3: =持仓配置!G3 -> 014201.OF | H3: =持仓配置!H3 -> 019923.OF | I3: =持仓配置!I3 -> 007044.OF | ... N3: =持仓配置!N3 -> 000917.OF
A4: =[1]!HX_AutoDate(1,"2026-05-29",A2,-1,-1,0,0,0,0,0,"SSE",27,0) -> 日期 | B4: 宏利复兴混合A | C4: 信澳业绩驱动A | D4: 嘉实信息产业A | E4: 银华集成电路混合A | F4: 中欧中证500指增A | G4: 天弘中证1000指增A | H4: 华泰柏瑞中证2000指增A | I4: 博道沪深300指增A | J4: 易方达中债新综指LOFA | K4: 华安黄金ETF联接A | L4: 国泰半导体材料设备ETF联接A | M4: 国泰通信设备ETF联接A | N4: 嘉实快线货币A
A5: 46171 | B5: =IF($A5="","",[1]!thsiFinD("ths_adjustment_nv_fund",B$3,$A5)) -> 4.925 | C5: =IF($A5="","",[1]!thsiFinD("ths_adjustment_nv_fund",C$3,$A5)) -> 3.1015 | D5: =IF($A5="","",[1]!thsiFinD("ths_adjustment_nv_fund",D$3,$A5)) -> 3.892 | E5: =IF($A5="","",[1]!thsiFinD("ths_adjustment_nv_fund",E$3,$A5)) -> 2.6235 | F5: =IF($A5="","",[1]!thsiFinD("ths_adjustment_nv_fund",F$3,$A5)) -> 1.5841 | G5: =IF($A5="","",[1]!thsiFinD("ths_adjustment_nv_fund",G$3,$A5)) -> 1.6332 | H5: =IF($A5="","",[1]!thsiFinD("ths_adjustment_nv_fund",H$3,$A5)) -> 2.066 | I5: =IF($A5="","",[1]!thsiFinD("ths_adjustment_nv_fund",I$3,$A5)) -> 1.9417 | ... N5: =IF($A5="","",[1]!thsiFinD("ths_adjustment_nv_fund",N$3,$A5)) -> 1.3163422
A6: 46174 | B6: =IF($A6="","",[1]!thsiFinD("ths_adjustment_nv_fund",B$3,$A6)) -> 4.698 | C6: =IF($A6="","",[1]!thsiFinD("ths_adjustment_nv_fund",C$3,$A6)) -> 2.9096 | D6: =IF($A6="","",[1]!thsiFinD("ths_adjustment_nv_fund",D$3,$A6)) -> 3.687 | E6: =IF($A6="","",[1]!thsiFinD("ths_adjustment_nv_fund",E$3,$A6)) -> 2.4715 | F6: =IF($A6="","",[1]!thsiFinD("ths_adjustment_nv_fund",F$3,$A6)) -> 1.578 | G6: =IF($A6="","",[1]!thsiFinD("ths_adjustment_nv_fund",G$3,$A6)) -> 1.6247 | H6: =IF($A6="","",[1]!thsiFinD("ths_adjustment_nv_fund",H$3,$A6)) -> 2.0661 | I6: =IF($A6="","",[1]!thsiFinD("ths_adjustment_nv_fund",I$3,$A6)) -> 1.9205 | ... N6: =IF($A6="","",[1]!thsiFinD("ths_adjustment_nv_fund",N$3,$A6)) -> 1.3164814
A7: 46175 | B7: =IF($A7="","",[1]!thsiFinD("ths_adjustment_nv_fund",B$3,$A7)) -> 4.97 | C7: =IF($A7="","",[1]!thsiFinD("ths_adjustment_nv_fund",C$3,$A7)) -> 3.1175 | D7: =IF($A7="","",[1]!thsiFinD("ths_adjustment_nv_fund",D$3,$A7)) -> 3.9251 | E7: =IF($A7="","",[1]!thsiFinD("ths_adjustment_nv_fund",E$3,$A7)) -> 2.5108 | F7: =IF($A7="","",[1]!thsiFinD("ths_adjustment_nv_fund",F$3,$A7)) -> 1.5838 | G7: =IF($A7="","",[1]!thsiFinD("ths_adjustment_nv_fund",G$3,$A7)) -> 1.6241 | H7: =IF($A7="","",[1]!thsiFinD("ths_adjustment_nv_fund",H$3,$A7)) -> 2.0552 | I7: =IF($A7="","",[1]!thsiFinD("ths_adjustment_nv_fund",I$3,$A7)) -> 1.9491 | ... N7: =IF($A7="","",[1]!thsiFinD("ths_adjustment_nv_fund",N$3,$A7)) -> 1.316531
A8: 46176 | B8: =IF($A8="","",[1]!thsiFinD("ths_adjustment_nv_fund",B$3,$A8)) -> 5.215 | C8: =IF($A8="","",[1]!thsiFinD("ths_adjustment_nv_fund",C$3,$A8)) -> 3.3028 | D8: =IF($A8="","",[1]!thsiFinD("ths_adjustment_nv_fund",D$3,$A8)) -> 4.1267 | E8: =IF($A8="","",[1]!thsiFinD("ths_adjustment_nv_fund",E$3,$A8)) -> 2.5747 | F8: =IF($A8="","",[1]!thsiFinD("ths_adjustment_nv_fund",F$3,$A8)) -> 1.5894 | G8: =IF($A8="","",[1]!thsiFinD("ths_adjustment_nv_fund",G$3,$A8)) -> 1.6348 | H8: =IF($A8="","",[1]!thsiFinD("ths_adjustment_nv_fund",H$3,$A8)) -> 2.0617 | I8: =IF($A8="","",[1]!thsiFinD("ths_adjustment_nv_fund",I$3,$A8)) -> 1.9628 | ... N8: =IF($A8="","",[1]!thsiFinD("ths_adjustment_nv_fund",N$3,$A8)) -> 1.3165753
A9: 46177 | B9: =IF($A9="","",[1]!thsiFinD("ths_adjustment_nv_fund",B$3,$A9)) -> 5.262 | C9: =IF($A9="","",[1]!thsiFinD("ths_adjustment_nv_fund",C$3,$A9)) -> 3.2991 | D9: =IF($A9="","",[1]!thsiFinD("ths_adjustment_nv_fund",D$3,$A9)) -> 4.113 | E9: =IF($A9="","",[1]!thsiFinD("ths_adjustment_nv_fund",E$3,$A9)) -> 2.6434 | F9: =IF($A9="","",[1]!thsiFinD("ths_adjustment_nv_fund",F$3,$A9)) -> 1.5815 | G9: =IF($A9="","",[1]!thsiFinD("ths_adjustment_nv_fund",G$3,$A9)) -> 1.6266 | H9: =IF($A9="","",[1]!thsiFinD("ths_adjustment_nv_fund",H$3,$A9)) -> 2.0603 | I9: =IF($A9="","",[1]!thsiFinD("ths_adjustment_nv_fund",I$3,$A9)) -> 1.9539 | ... N9: =IF($A9="","",[1]!thsiFinD("ths_adjustment_nv_fund",N$3,$A9)) -> 1.3166246
A10: 46178 | B10: =IF($A10="","",[1]!thsiFinD("ths_adjustment_nv_fund",B$3,$A10)) -> 5.099 | C10: =IF($A10="","",[1]!thsiFinD("ths_adjustment_nv_fund",C$3,$A10)) -> 3.1932 | D10: =IF($A10="","",[1]!thsiFinD("ths_adjustment_nv_fund",D$3,$A10)) -> 3.9333 | E10: =IF($A10="","",[1]!thsiFinD("ths_adjustment_nv_fund",E$3,$A10)) -> 2.5176 | F10: =IF($A10="","",[1]!thsiFinD("ths_adjustment_nv_fund",F$3,$A10)) -> 1.5605 | G10: =IF($A10="","",[1]!thsiFinD("ths_adjustment_nv_fund",G$3,$A10)) -> 1.608 | H10: =IF($A10="","",[1]!thsiFinD("ths_adjustment_nv_fund",H$3,$A10)) -> 2.0581 | I10: =IF($A10="","",[1]!thsiFinD("ths_adjustment_nv_fund",I$3,$A10)) -> 1.9209 | ... N10: =IF($A10="","",[1]!thsiFinD("ths_adjustment_nv_fund",N$3,$A10)) -> 1.316669
A11: 46181 | B11: =IF($A11="","",[1]!thsiFinD("ths_adjustment_nv_fund",B$3,$A11)) -> 5.009 | C11: =IF($A11="","",[1]!thsiFinD("ths_adjustment_nv_fund",C$3,$A11)) -> 3.0775 | D11: =IF($A11="","",[1]!thsiFinD("ths_adjustment_nv_fund",D$3,$A11)) -> 3.8208 | E11: =IF($A11="","",[1]!thsiFinD("ths_adjustment_nv_fund",E$3,$A11)) -> 2.4054 | F11: =IF($A11="","",[1]!thsiFinD("ths_adjustment_nv_fund",F$3,$A11)) -> 1.506 | G11: =IF($A11="","",[1]!thsiFinD("ths_adjustment_nv_fund",G$3,$A11)) -> 1.5555 | H11: =IF($A11="","",[1]!thsiFinD("ths_adjustment_nv_fund",H$3,$A11)) -> 1.9891 | I11: =IF($A11="","",[1]!thsiFinD("ths_adjustment_nv_fund",I$3,$A11)) -> 1.8813 | ... N11: =IF($A11="","",[1]!thsiFinD("ths_adjustment_nv_fund",N$3,$A11)) -> 1.316808
A12: 46182 | B12: =IF($A12="","",[1]!thsiFinD("ths_adjustment_nv_fund",B$3,$A12)) -> 5.303 | C12: =IF($A12="","",[1]!thsiFinD("ths_adjustment_nv_fund",C$3,$A12)) -> 3.2503 | D12: =IF($A12="","",[1]!thsiFinD("ths_adjustment_nv_fund",D$3,$A12)) -> 4.0078 | E12: =IF($A12="","",[1]!thsiFinD("ths_adjustment_nv_fund",E$3,$A12)) -> 2.5471 | F12: =IF($A12="","",[1]!thsiFinD("ths_adjustment_nv_fund",F$3,$A12)) -> 1.541 | G12: =IF($A12="","",[1]!thsiFinD("ths_adjustment_nv_fund",G$3,$A12)) -> 1.6001 | H12: =IF($A12="","",[1]!thsiFinD("ths_adjustment_nv_fund",H$3,$A12)) -> 2.0379 | I12: =IF($A12="","",[1]!thsiFinD("ths_adjustment_nv_fund",I$3,$A12)) -> 1.9145 | ... N12: =IF($A12="","",[1]!thsiFinD("ths_adjustment_nv_fund",N$3,$A12)) -> 1.3168572
A13: 46183 | B13: =IF($A13="","",[1]!thsiFinD("ths_adjustment_nv_fund",B$3,$A13)) -> 5.184 | C13: =IF($A13="","",[1]!thsiFinD("ths_adjustment_nv_fund",C$3,$A13)) -> 3.1173 | D13: =IF($A13="","",[1]!thsiFinD("ths_adjustment_nv_fund",D$3,$A13)) -> 3.867 | E13: =IF($A13="","",[1]!thsiFinD("ths_adjustment_nv_fund",E$3,$A13)) -> 2.5436 | F13: =IF($A13="","",[1]!thsiFinD("ths_adjustment_nv_fund",F$3,$A13)) -> 1.5274 | G13: =IF($A13="","",[1]!thsiFinD("ths_adjustment_nv_fund",G$3,$A13)) -> 1.5778 | H13: =IF($A13="","",[1]!thsiFinD("ths_adjustment_nv_fund",H$3,$A13)) -> 2.008 | I13: =IF($A13="","",[1]!thsiFinD("ths_adjustment_nv_fund",I$3,$A13)) -> 1.8953 | ... N13: =IF($A13="","",[1]!thsiFinD("ths_adjustment_nv_fund",N$3,$A13)) -> 1.3169026
A14: 46184 | B14: =IF($A14="","",[1]!thsiFinD("ths_adjustment_nv_fund",B$3,$A14)) -> 5.168 | C14: =IF($A14="","",[1]!thsiFinD("ths_adjustment_nv_fund",C$3,$A14)) -> 3.125 | D14: =IF($A14="","",[1]!thsiFinD("ths_adjustment_nv_fund",D$3,$A14)) -> 3.8191 | E14: =IF($A14="","",[1]!thsiFinD("ths_adjustment_nv_fund",E$3,$A14)) -> 2.6281 | F14: =IF($A14="","",[1]!thsiFinD("ths_adjustment_nv_fund",F$3,$A14)) -> 1.5225 | G14: =IF($A14="","",[1]!thsiFinD("ths_adjustment_nv_fund",G$3,$A14)) -> 1.5741 | H14: =IF($A14="","",[1]!thsiFinD("ths_adjustment_nv_fund",H$3,$A14)) -> 2.0013 | I14: =IF($A14="","",[1]!thsiFinD("ths_adjustment_nv_fund",I$3,$A14)) -> 1.8852 | ... N14: =IF($A14="","",[1]!thsiFinD("ths_adjustment_nv_fund",N$3,$A14)) -> 1.3169519
A15: 46185 | B15: =IF($A15="","",[1]!thsiFinD("ths_adjustment_nv_fund",B$3,$A15)) -> 5.147 | C15: =IF($A15="","",[1]!thsiFinD("ths_adjustment_nv_fund",C$3,$A15)) -> 3.0912 | D15: =IF($A15="","",[1]!thsiFinD("ths_adjustment_nv_fund",D$3,$A15)) -> 3.7906 | E15: =IF($A15="","",[1]!thsiFinD("ths_adjustment_nv_fund",E$3,$A15)) -> 2.6555 | F15: =IF($A15="","",[1]!thsiFinD("ths_adjustment_nv_fund",F$3,$A15)) -> 1.5447 | G15: =IF($A15="","",[1]!thsiFinD("ths_adjustment_nv_fund",G$3,$A15)) -> 1.588 | H15: =IF($A15="","",[1]!thsiFinD("ths_adjustment_nv_fund",H$3,$A15)) -> 2.0092 | I15: =IF($A15="","",[1]!thsiFinD("ths_adjustment_nv_fund",I$3,$A15)) -> 1.91 | ... N15: =IF($A15="","",[1]!thsiFinD("ths_adjustment_nv_fund",N$3,$A15)) -> 1.3169953
A16: 46188 | B16: =IF($A16="","",[1]!thsiFinD("ths_adjustment_nv_fund",B$3,$A16)) -> 5.55 | C16: =IF($A16="","",[1]!thsiFinD("ths_adjustment_nv_fund",C$3,$A16)) -> 3.3568 | D16: =IF($A16="","",[1]!thsiFinD("ths_adjustment_nv_fund",D$3,$A16)) -> 4.0604 | E16: =IF($A16="","",[1]!thsiFinD("ths_adjustment_nv_fund",E$3,$A16)) -> 2.7901 | F16: =IF($A16="","",[1]!thsiFinD("ths_adjustment_nv_fund",F$3,$A16)) -> 1.5955 | G16: =IF($A16="","",[1]!thsiFinD("ths_adjustment_nv_fund",G$3,$A16)) -> 1.6477 | H16: =IF($A16="","",[1]!thsiFinD("ths_adjustment_nv_fund",H$3,$A16)) -> 2.0804 | I16: =IF($A16="","",[1]!thsiFinD("ths_adjustment_nv_fund",I$3,$A16)) -> 1.9591 | ... N16: =IF($A16="","",[1]!thsiFinD("ths_adjustment_nv_fund",N$3,$A16)) -> 1.3171341
... A31: 46210 | B31: =IF($A31="","",[1]!thsiFinD("ths_adjustment_nv_fund",B$3,$A31)) -> 5.26 | C31: =IF($A31="","",[1]!thsiFinD("ths_adjustment_nv_fund",C$3,$A31)) -> 3.0265 | D31: =IF($A31="","",[1]!thsiFinD("ths_adjustment_nv_fund",D$3,$A31)) -> 3.8613 | E31: =IF($A31="","",[1]!thsiFinD("ths_adjustment_nv_fund",E$3,$A31)) -> 3.5808 | F31: =IF($A31="","",[1]!thsiFinD("ths_adjustment_nv_fund",F$3,$A31)) -> 1.6017 | G31: =IF($A31="","",[1]!thsiFinD("ths_adjustment_nv_fund",G$3,$A31)) -> 1.6538 | H31: =IF($A31="","",[1]!thsiFinD("ths_adjustment_nv_fund",H$3,$A31)) -> 2.0247 | I31: =IF($A31="","",[1]!thsiFinD("ths_adjustment_nv_fund",I$3,$A31)) -> 1.9216 | ... N31: =IF($A31="","",[1]!thsiFinD("ths_adjustment_nv_fund",N$3,$A31)) -> 1.3181508
B32: =IF($A32="","",[1]!thsiFinD("ths_adjustment_nv_fund",B$3,$A32)) | C32: =IF($A32="","",[1]!thsiFinD("ths_adjustment_nv_fund",C$3,$A32)) | D32: =IF($A32="","",[1]!thsiFinD("ths_adjustment_nv_fund",D$3,$A32)) | E32: =IF($A32="","",[1]!thsiFinD("ths_adjustment_nv_fund",E$3,$A32)) | F32: =IF($A32="","",[1]!thsiFinD("ths_adjustment_nv_fund",F$3,$A32)) | G32: =IF($A32="","",[1]!thsiFinD("ths_adjustment_nv_fund",G$3,$A32)) | H32: =IF($A32="","",[1]!thsiFinD("ths_adjustment_nv_fund",H$3,$A32)) | I32: =IF($A32="","",[1]!thsiFinD("ths_adjustment_nv_fund",I$3,$A32)) | ... N32: =IF($A32="","",[1]!thsiFinD("ths_adjustment_nv_fund",N$3,$A32))
B33: =IF($A33="","",[1]!thsiFinD("ths_adjustment_nv_fund",B$3,$A33)) | C33: =IF($A33="","",[1]!thsiFinD("ths_adjustment_nv_fund",C$3,$A33)) | D33: =IF($A33="","",[1]!thsiFinD("ths_adjustment_nv_fund",D$3,$A33)) | E33: =IF($A33="","",[1]!thsiFinD("ths_adjustment_nv_fund",E$3,$A33)) | F33: =IF($A33="","",[1]!thsiFinD("ths_adjustment_nv_fund",F$3,$A33)) | G33: =IF($A33="","",[1]!thsiFinD("ths_adjustment_nv_fund",G$3,$A33)) | H33: =IF($A33="","",[1]!thsiFinD("ths_adjustment_nv_fund",H$3,$A33)) | I33: =IF($A33="","",[1]!thsiFinD("ths_adjustment_nv_fund",I$3,$A33)) | ... N33: =IF($A33="","",[1]!thsiFinD("ths_adjustment_nv_fund",N$3,$A33))
B34: =IF($A34="","",[1]!thsiFinD("ths_adjustment_nv_fund",B$3,$A34)) | C34: =IF($A34="","",[1]!thsiFinD("ths_adjustment_nv_fund",C$3,$A34)) | D34: =IF($A34="","",[1]!thsiFinD("ths_adjustment_nv_fund",D$3,$A34)) | E34: =IF($A34="","",[1]!thsiFinD("ths_adjustment_nv_fund",E$3,$A34)) | F34: =IF($A34="","",[1]!thsiFinD("ths_adjustment_nv_fund",F$3,$A34)) | G34: =IF($A34="","",[1]!thsiFinD("ths_adjustment_nv_fund",G$3,$A34)) | H34: =IF($A34="","",[1]!thsiFinD("ths_adjustment_nv_fund",H$3,$A34)) | I34: =IF($A34="","",[1]!thsiFinD("ths_adjustment_nv_fund",I$3,$A34)) | ... N34: =IF($A34="","",[1]!thsiFinD("ths_adjustment_nv_fund",N$3,$A34))
B35: =IF($A35="","",[1]!thsiFinD("ths_adjustment_nv_fund",B$3,$A35)) | C35: =IF($A35="","",[1]!thsiFinD("ths_adjustment_nv_fund",C$3,$A35)) | D35: =IF($A35="","",[1]!thsiFinD("ths_adjustment_nv_fund",D$3,$A35)) | E35: =IF($A35="","",[1]!thsiFinD("ths_adjustment_nv_fund",E$3,$A35)) | F35: =IF($A35="","",[1]!thsiFinD("ths_adjustment_nv_fund",F$3,$A35)) | G35: =IF($A35="","",[1]!thsiFinD("ths_adjustment_nv_fund",G$3,$A35)) | H35: =IF($A35="","",[1]!thsiFinD("ths_adjustment_nv_fund",H$3,$A35)) | I35: =IF($A35="","",[1]!thsiFinD("ths_adjustment_nv_fund",I$3,$A35)) | ... N35: =IF($A35="","",[1]!thsiFinD("ths_adjustment_nv_fund",N$3,$A35))
B36: =IF($A36="","",[1]!thsiFinD("ths_adjustment_nv_fund",B$3,$A36)) | C36: =IF($A36="","",[1]!thsiFinD("ths_adjustment_nv_fund",C$3,$A36)) | D36: =IF($A36="","",[1]!thsiFinD("ths_adjustment_nv_fund",D$3,$A36)) | E36: =IF($A36="","",[1]!thsiFinD("ths_adjustment_nv_fund",E$3,$A36)) | F36: =IF($A36="","",[1]!thsiFinD("ths_adjustment_nv_fund",F$3,$A36)) | G36: =IF($A36="","",[1]!thsiFinD("ths_adjustment_nv_fund",G$3,$A36)) | H36: =IF($A36="","",[1]!thsiFinD("ths_adjustment_nv_fund",H$3,$A36)) | I36: =IF($A36="","",[1]!thsiFinD("ths_adjustment_nv_fund",I$3,$A36)) | ... N36: =IF($A36="","",[1]!thsiFinD("ths_adjustment_nv_fund",N$3,$A36))
B37: =IF($A37="","",[1]!thsiFinD("ths_adjustment_nv_fund",B$3,$A37)) | C37: =IF($A37="","",[1]!thsiFinD("ths_adjustment_nv_fund",C$3,$A37)) | D37: =IF($A37="","",[1]!thsiFinD("ths_adjustment_nv_fund",D$3,$A37)) | E37: =IF($A37="","",[1]!thsiFinD("ths_adjustment_nv_fund",E$3,$A37)) | F37: =IF($A37="","",[1]!thsiFinD("ths_adjustment_nv_fund",F$3,$A37)) | G37: =IF($A37="","",[1]!thsiFinD("ths_adjustment_nv_fund",G$3,$A37)) | H37: =IF($A37="","",[1]!thsiFinD("ths_adjustment_nv_fund",H$3,$A37)) | I37: =IF($A37="","",[1]!thsiFinD("ths_adjustment_nv_fund",I$3,$A37)) | ... N37: =IF($A37="","",[1]!thsiFinD("ths_adjustment_nv_fund",N$3,$A37))
B38: =IF($A38="","",[1]!thsiFinD("ths_adjustment_nv_fund",B$3,$A38)) | C38: =IF($A38="","",[1]!thsiFinD("ths_adjustment_nv_fund",C$3,$A38)) | D38: =IF($A38="","",[1]!thsiFinD("ths_adjustment_nv_fund",D$3,$A38)) | E38: =IF($A38="","",[1]!thsiFinD("ths_adjustment_nv_fund",E$3,$A38)) | F38: =IF($A38="","",[1]!thsiFinD("ths_adjustment_nv_fund",F$3,$A38)) | G38: =IF($A38="","",[1]!thsiFinD("ths_adjustment_nv_fund",G$3,$A38)) | H38: =IF($A38="","",[1]!thsiFinD("ths_adjustment_nv_fund",H$3,$A38)) | I38: =IF($A38="","",[1]!thsiFinD("ths_adjustment_nv_fund",I$3,$A38)) | ... N38: =IF($A38="","",[1]!thsiFinD("ths_adjustment_nv_fund",N$3,$A38))
B39: =IF($A39="","",[1]!thsiFinD("ths_adjustment_nv_fund",B$3,$A39)) | C39: =IF($A39="","",[1]!thsiFinD("ths_adjustment_nv_fund",C$3,$A39)) | D39: =IF($A39="","",[1]!thsiFinD("ths_adjustment_nv_fund",D$3,$A39)) | E39: =IF($A39="","",[1]!thsiFinD("ths_adjustment_nv_fund",E$3,$A39)) | F39: =IF($A39="","",[1]!thsiFinD("ths_adjustment_nv_fund",F$3,$A39)) | G39: =IF($A39="","",[1]!thsiFinD("ths_adjustment_nv_fund",G$3,$A39)) | H39: =IF($A39="","",[1]!thsiFinD("ths_adjustment_nv_fund",H$3,$A39)) | I39: =IF($A39="","",[1]!thsiFinD("ths_adjustment_nv_fund",I$3,$A39)) | ... N39: =IF($A39="","",[1]!thsiFinD("ths_adjustment_nv_fund",N$3,$A39))
B40: =IF($A40="","",[1]!thsiFinD("ths_adjustment_nv_fund",B$3,$A40)) | C40: =IF($A40="","",[1]!thsiFinD("ths_adjustment_nv_fund",C$3,$A40)) | D40: =IF($A40="","",[1]!thsiFinD("ths_adjustment_nv_fund",D$3,$A40)) | E40: =IF($A40="","",[1]!thsiFinD("ths_adjustment_nv_fund",E$3,$A40)) | F40: =IF($A40="","",[1]!thsiFinD("ths_adjustment_nv_fund",F$3,$A40)) | G40: =IF($A40="","",[1]!thsiFinD("ths_adjustment_nv_fund",G$3,$A40)) | H40: =IF($A40="","",[1]!thsiFinD("ths_adjustment_nv_fund",H$3,$A40)) | I40: =IF($A40="","",[1]!thsiFinD("ths_adjustment_nv_fund",I$3,$A40)) | ... N40: =IF($A40="","",[1]!thsiFinD("ths_adjustment_nv_fund",N$3,$A40))
B41: =IF($A41="","",[1]!thsiFinD("ths_adjustment_nv_fund",B$3,$A41)) | C41: =IF($A41="","",[1]!thsiFinD("ths_adjustment_nv_fund",C$3,$A41)) | D41: =IF($A41="","",[1]!thsiFinD("ths_adjustment_nv_fund",D$3,$A41)) | E41: =IF($A41="","",[1]!thsiFinD("ths_adjustment_nv_fund",E$3,$A41)) | F41: =IF($A41="","",[1]!thsiFinD("ths_adjustment_nv_fund",F$3,$A41)) | G41: =IF($A41="","",[1]!thsiFinD("ths_adjustment_nv_fund",G$3,$A41)) | H41: =IF($A41="","",[1]!thsiFinD("ths_adjustment_nv_fund",H$3,$A41)) | I41: =IF($A41="","",[1]!thsiFinD("ths_adjustment_nv_fund",I$3,$A41)) | ... N41: =IF($A41="","",[1]!thsiFinD("ths_adjustment_nv_fund",N$3,$A41))
B42: =IF($A42="","",[1]!thsiFinD("ths_adjustment_nv_fund",B$3,$A42)) | C42: =IF($A42="","",[1]!thsiFinD("ths_adjustment_nv_fund",C$3,$A42)) | D42: =IF($A42="","",[1]!thsiFinD("ths_adjustment_nv_fund",D$3,$A42)) | E42: =IF($A42="","",[1]!thsiFinD("ths_adjustment_nv_fund",E$3,$A42)) | F42: =IF($A42="","",[1]!thsiFinD("ths_adjustment_nv_fund",F$3,$A42)) | G42: =IF($A42="","",[1]!thsiFinD("ths_adjustment_nv_fund",G$3,$A42)) | H42: =IF($A42="","",[1]!thsiFinD("ths_adjustment_nv_fund",H$3,$A42)) | I42: =IF($A42="","",[1]!thsiFinD("ths_adjustment_nv_fund",I$3,$A42)) | ... N42: =IF($A42="","",[1]!thsiFinD("ths_adjustment_nv_fund",N$3,$A42))
B43: =IF($A43="","",[1]!thsiFinD("ths_adjustment_nv_fund",B$3,$A43)) | C43: =IF($A43="","",[1]!thsiFinD("ths_adjustment_nv_fund",C$3,$A43)) | D43: =IF($A43="","",[1]!thsiFinD("ths_adjustment_nv_fund",D$3,$A43)) | E43: =IF($A43="","",[1]!thsiFinD("ths_adjustment_nv_fund",E$3,$A43)) | F43: =IF($A43="","",[1]!thsiFinD("ths_adjustment_nv_fund",F$3,$A43)) | G43: =IF($A43="","",[1]!thsiFinD("ths_adjustment_nv_fund",G$3,$A43)) | H43: =IF($A43="","",[1]!thsiFinD("ths_adjustment_nv_fund",H$3,$A43)) | I43: =IF($A43="","",[1]!thsiFinD("ths_adjustment_nv_fund",I$3,$A43)) | ... N43: =IF($A43="","",[1]!thsiFinD("ths_adjustment_nv_fund",N$3,$A43))
... B59: =IF($A59="","",[1]!thsiFinD("ths_adjustment_nv_fund",B$3,$A59)) | C59: =IF($A59="","",[1]!thsiFinD("ths_adjustment_nv_fund",C$3,$A59)) | D59: =IF($A59="","",[1]!thsiFinD("ths_adjustment_nv_fund",D$3,$A59)) | E59: =IF($A59="","",[1]!thsiFinD("ths_adjustment_nv_fund",E$3,$A59)) | F59: =IF($A59="","",[1]!thsiFinD("ths_adjustment_nv_fund",F$3,$A59)) | G59: =IF($A59="","",[1]!thsiFinD("ths_adjustment_nv_fund",G$3,$A59)) | H59: =IF($A59="","",[1]!thsiFinD("ths_adjustment_nv_fund",H$3,$A59)) | I59: =IF($A59="","",[1]!thsiFinD("ths_adjustment_nv_fund",I$3,$A59)) | ... N59: =IF($A59="","",[1]!thsiFinD("ths_adjustment_nv_fund",N$3,$A59))

Sheet 组合净值（模拟）
A1: 组合净值 · 买入持有逐日计算
B4: 组合 10-90 | E4: 组合 20-80 | H4: 组合 30-70 | K4: 组合 增值
A5: 日期 | B5: 净值 | C5: 日收益 | D5: 回撤 | E5: 净值 | F5: 日收益 | G5: 回撤 | H5: 净值 | I5: 日收益 | J5: 回撤 | K5: 净值 | L5: 日收益 | M5: 回撤
A6: =IF('净值数据(iFinD公式)'!A5="","",'净值数据(iFinD公式)'!A5) -> 46171 | B6: =IF(OR('净值数据(iFinD公式)'!$A5="",'净值数据(iFinD公式)'!$B5=""),"",SUMPRODUCT(持仓配置!$B$4:$N$4,'净值数据(iFinD公式)'!$B5:$N5/'净值数据(iFinD公式)'!$B$5:$N$5)*(1-持仓配置!$P$4)^((ROW()-6)/说明!$C$17)) -> 1 | D6: =IF(B6="","",B6/MAX(B$6:B6)-1) -> 0 | E6: =IF(OR('净值数据(iFinD公式)'!$A5="",'净值数据(iFinD公式)'!$B5=""),"",SUMPRODUCT(持仓配置!$B$5:$N$5,'净值数据(iFinD公式)'!$B5:$N5/'净值数据(iFinD公式)'!$B$5:$N$5)*(1-持仓配置!$P$5)^((ROW()-6)/说明!$C$17)) -> 1 | G6: =IF(E6="","",E6/MAX(E$6:E6)-1) -> 0 | H6: =IF(OR('净值数据(iFinD公式)'!$A5="",'净值数据(iFinD公式)'!$B5=""),"",SUMPRODUCT(持仓配置!$B$6:$N$6,'净值数据(iFinD公式)'!$B5:$N5/'净值数据(iFinD公式)'!$B$5:$N$5)*(1-持仓配置!$P$6)^((ROW()-6)/说明!$C$17)) -> 1 | J6: =IF(H6="","",H6/MAX(H$6:H6)-1) -> 0 | K6: =IF(OR('净值数据(iFinD公式)'!$A5="",'净值数据(iFinD公式)'!$B5=""),"",SUMPRODUCT(持仓配置!$B$7:$N$7,'净值数据(iFinD公式)'!$B5:$N5/'净值数据(iFinD公式)'!$B$5:$N$5)*(1-持仓配置!$P$7)^((ROW()-6)/说明!$C$17)) -> 1 | M6: =IF(K6="","",K6/MAX(K$6:K6)-1) -> 0
A7: =IF('净值数据(iFinD公式)'!A6="","",'净值数据(iFinD公式)'!A6) -> 46174 | B7: =IF(OR('净值数据(iFinD公式)'!$A6="",'净值数据(iFinD公式)'!$B6=""),"",SUMPRODUCT(持仓配置!$B$4:$N$4,'净值数据(iFinD公式)'!$B6:$N6/'净值数据(iFinD公式)'!$B$5:$N$5)*(1-持仓配置!$P$4)^((ROW()-6)/说明!$C$17)) -> 0.99765643 | C7: =IF(OR(B7="",B6=""),"",B7/B6-1) -> -0.0023435666 | D7: =IF(B7="","",B7/MAX(B$6:B7)-1) -> -0.0023435666 | E7: =IF(OR('净值数据(iFinD公式)'!$A6="",'净值数据(iFinD公式)'!$B6=""),"",SUMPRODUCT(持仓配置!$B$5:$N$5,'净值数据(iFinD公式)'!$B6:$N6/'净值数据(iFinD公式)'!$B$5:$N$5)*(1-持仓配置!$P$5)^((ROW()-6)/说明!$C$17)) -> 0.99470984 | F7: =IF(OR(E7="",E6=""),"",E7/E6-1) -> -0.0052901552 | G7: =IF(E7="","",E7/MAX(E$6:E7)-1) -> -0.0052901552 | H7: =IF(OR('净值数据(iFinD公式)'!$A6="",'净值数据(iFinD公式)'!$B6=""),"",SUMPRODUCT(持仓配置!$B$6:$N$6,'净值数据(iFinD公式)'!$B6:$N6/'净值数据(iFinD公式)'!$B$5:$N$5)*(1-持仓配置!$P$6)^((ROW()-6)/说明!$C$17)) -> 0.99155316 | I7: =IF(OR(H7="",H6=""),"",H7/H6-1) -> -0.0084468409 | J7: =IF(H7="","",H7/MAX(H$6:H7)-1) -> -0.0084468409 | K7: =IF(OR('净值数据(iFinD公式)'!$A6="",'净值数据(iFinD公式)'!$B6=""),"",SUMPRODUCT(持仓配置!$B$7:$N$7,'净值数据(iFinD公式)'!$B6:$N6/'净值数据(iFinD公式)'!$B$5:$N$5)*(1-持仓配置!$P$7)^((ROW()-6)/说明!$C$17)) -> 0.94945547 | L7: =IF(OR(K7="",K6=""),"",K7/K6-1) -> -0.050544531 | M7: =IF(K7="","",K7/MAX(K$6:K7)-1) -> -0.050544531
A8: =IF('净值数据(iFinD公式)'!A7="","",'净值数据(iFinD公式)'!A7) -> 46175 | B8: =IF(OR('净值数据(iFinD公式)'!$A7="",'净值数据(iFinD公式)'!$B7=""),"",SUMPRODUCT(持仓配置!$B$4:$N$4,'净值数据(iFinD公式)'!$B7:$N7/'净值数据(iFinD公式)'!$B$5:$N$5)*(1-持仓配置!$P$4)^((ROW()-6)/说明!$C$17)) -> 1.0004874 | C8: =IF(OR(B8="",B7=""),"",B8/B7-1) -> 0.0028376156 | D8: =IF(B8="","",B8/MAX(B$6:B8)-1) -> 0 | E8: =IF(OR('净值数据(iFinD公式)'!$A7="",'净值数据(iFinD公式)'!$B7=""),"",SUMPRODUCT(持仓配置!$B$5:$N$5,'净值数据(iFinD公式)'!$B7:$N7/'净值数据(iFinD公式)'!$B$5:$N$5)*(1-持仓配置!$P$5)^((ROW()-6)/说明!$C$17)) -> 1.0000346 | F8: =IF(OR(E8="",E7=""),"",E8/E7-1) -> 0.0053530279 | G8: =IF(E8="","",E8/MAX(E$6:E8)-1) -> 0 | H8: =IF(OR('净值数据(iFinD公式)'!$A7="",'净值数据(iFinD公式)'!$B7=""),"",SUMPRODUCT(持仓配置!$B$6:$N$6,'净值数据(iFinD公式)'!$B7:$N7/'净值数据(iFinD公式)'!$B$5:$N$5)*(1-持仓配置!$P$6)^((ROW()-6)/说明!$C$17)) -> 0.99966507 | I8: =IF(OR(H8="",H7=""),"",H8/H7-1) -> 0.008181017 | J8: =IF(H8="","",H8/MAX(H$6:H8)-1) -> -0.00033492765 | K8: =IF(OR('净值数据(iFinD公式)'!$A7="",'净值数据(iFinD公式)'!$B7=""),"",SUMPRODUCT(持仓配置!$B$7:$N$7,'净值数据(iFinD公式)'!$B7:$N7/'净值数据(iFinD公式)'!$B$5:$N$5)*(1-持仓配置!$P$7)^((ROW()-6)/说明!$C$17)) -> 0.99538006 | L8: =IF(OR(K8="",K7=""),"",K8/K7-1) -> 0.048369402 | M8: =IF(K8="","",K8/MAX(K$6:K8)-1) -> -0.0046199376
A9: =IF('净值数据(iFinD公式)'!A8="","",'净值数据(iFinD公式)'!A8) -> 46176 | B9: =IF(OR('净值数据(iFinD公式)'!$A8="",'净值数据(iFinD公式)'!$B8=""),"",SUMPRODUCT(持仓配置!$B$4:$N$4,'净值数据(iFinD公式)'!$B8:$N8/'净值数据(iFinD公式)'!$B$5:$N$5)*(1-持仓配置!$P$4)^((ROW()-6)/说明!$C$17)) -> 1.0019149 | C9: =IF(OR(B9="",B8=""),"",B9/B8-1) -> 0.001426845 | D9: =IF(B9="","",B9/MAX(B$6:B9)-1) -> 0 | E9: =IF(OR('净值数据(iFinD公式)'!$A8="",'净值数据(iFinD公式)'!$B8=""),"",SUMPRODUCT(持仓配置!$B$5:$N$5,'净值数据(iFinD公式)'!$B8:$N8/'净值数据(iFinD公式)'!$B$5:$N$5)*(1-持仓配置!$P$5)^((ROW()-6)/说明!$C$17)) -> 1.003949 | F9: =IF(OR(E9="",E8=""),"",E9/E8-1) -> 0.0039142782 | G9: =IF(E9="","",E9/MAX(E$6:E9)-1) -> 0 | H9: =IF(OR('净值数据(iFinD公式)'!$A8="",'净值数据(iFinD公式)'!$B8=""),"",SUMPRODUCT(持仓配置!$B$6:$N$6,'净值数据(iFinD公式)'!$B8:$N8/'净值数据(iFinD公式)'!$B$5:$N$5)*(1-持仓配置!$P$6)^((ROW()-6)/说明!$C$17)) -> 1.0054022 | I9: =IF(OR(H9="",H8=""),"",H9/H8-1) -> 0.0057390377 | J9: =IF(H9="","",H9/MAX(H$6:H9)-1) -> 0 | K9: =IF(OR('净值数据(iFinD公式)'!$A8="",'净值数据(iFinD公式)'!$B8=""),"",SUMPRODUCT(持仓配置!$B$7:$N$7,'净值数据(iFinD公式)'!$B8:$N8/'净值数据(iFinD公式)'!$B$5:$N$5)*(1-持仓配置!$P$7)^((ROW()-6)/说明!$C$17)) -> 1.0384783 | L9: =IF(OR(K9="",K8=""),"",K9/K8-1) -> 0.043298242 | M9: =IF(K9="","",K9/MAX(K$6:K9)-1) -> 0
A10: =IF('净值数据(iFinD公式)'!A9="","",'净值数据(iFinD公式)'!A9) -> 46177 | B10: =IF(OR('净值数据(iFinD公式)'!$A9="",'净值数据(iFinD公式)'!$B9=""),"",SUMPRODUCT(持仓配置!$B$4:$N$4,'净值数据(iFinD公式)'!$B9:$N9/'净值数据(iFinD公式)'!$B$5:$N$5)*(1-持仓配置!$P$4)^((ROW()-6)/说明!$C$17)) -> 1.0027653 | C10: =IF(OR(B10="",B9=""),"",B10/B9-1) -> 0.00084874508 | D10: =IF(B10="","",B10/MAX(B$6:B10)-1) -> 0 | E10: =IF(OR('净值数据(iFinD公式)'!$A9="",'净值数据(iFinD公式)'!$B9=""),"",SUMPRODUCT(持仓配置!$B$5:$N$5,'净值数据(iFinD公式)'!$B9:$N9/'净值数据(iFinD公式)'!$B$5:$N$5)*(1-持仓配置!$P$5)^((ROW()-6)/说明!$C$17)) -> 1.0050041 | F10: =IF(OR(E10="",E9=""),"",E10/E9-1) -> 0.0010510185 | G10: =IF(E10="","",E10/MAX(E$6:E10)-1) -> 0 | H10: =IF(OR('净值数据(iFinD公式)'!$A9="",'净值数据(iFinD公式)'!$B9=""),"",SUMPRODUCT(持仓配置!$B$6:$N$6,'净值数据(iFinD公式)'!$B9:$N9/'净值数据(iFinD公式)'!$B$5:$N$5)*(1-持仓配置!$P$6)^((ROW()-6)/说明!$C$17)) -> 1.0067152 | I10: =IF(OR(H10="",H9=""),"",H10/H9-1) -> 0.0013059995 | J10: =IF(H10="","",H10/MAX(H$6:H10)-1) -> 0 | K10: =IF(OR('净值数据(iFinD公式)'!$A9="",'净值数据(iFinD公式)'!$B9=""),"",SUMPRODUCT(持仓配置!$B$7:$N$7,'净值数据(iFinD公式)'!$B9:$N9/'净值数据(iFinD公式)'!$B$5:$N$5)*(1-持仓配置!$P$7)^((ROW()-6)/说明!$C$17)) -> 1.0480045 | L10: =IF(OR(K10="",K9=""),"",K10/K9-1) -> 0.0091732227 | M10: =IF(K10="","",K10/MAX(K$6:K10)-1) -> 0
A11: =IF('净值数据(iFinD公式)'!A10="","",'净值数据(iFinD公式)'!A10) -> 46178 | B11: =IF(OR('净值数据(iFinD公式)'!$A10="",'净值数据(iFinD公式)'!$B10=""),"",SUMPRODUCT(持仓配置!$B$4:$N$4,'净值数据(iFinD公式)'!$B10:$N10/'净值数据(iFinD公式)'!$B$5:$N$5)*(1-持仓配置!$P$4)^((ROW()-6)/说明!$C$17)) -> 0.9997837 | C11: =IF(OR(B11="",B10=""),"",B11/B10-1) -> -0.0029733862 | D11: =IF(B11="","",B11/MAX(B$6:B11)-1) -> -0.0029733862 | E11: =IF(OR('净值数据(iFinD公式)'!$A10="",'净值数据(iFinD公式)'!$B10=""),"",SUMPRODUCT(持仓配置!$B$5:$N$5,'净值数据(iFinD公式)'!$B10:$N10/'净值数据(iFinD公式)'!$B$5:$N$5)*(1-持仓配置!$P$5)^((ROW()-6)/说明!$C$17)) -> 0.99963093 | F11: =IF(OR(E11="",E10=""),"",E11/E10-1) -> -0.0053464509 | G11: =IF(E11="","",E11/MAX(E$6:E11)-1) -> -0.0053464509 | H11: =IF(OR('净值数据(iFinD公式)'!$A10="",'净值数据(iFinD公式)'!$B10=""),"",SUMPRODUCT(持仓配置!$B$6:$N$6,'净值数据(iFinD公式)'!$B10:$N10/'净值数据(iFinD公式)'!$B$5:$N$5)*(1-持仓配置!$P$6)^((ROW()-6)/说明!$C$17)) -> 0.99897575 | I11: =IF(OR(H11="",H10=""),"",H11/H10-1) -> -0.0076878646 | J11: =IF(H11="","",H11/MAX(H$6:H11)-1) -> -0.0076878646 | K11: =IF(OR('净值数据(iFinD公式)'!$A10="",'净值数据(iFinD公式)'!$B10=""),"",SUMPRODUCT(持仓配置!$B$7:$N$7,'净值数据(iFinD公式)'!$B10:$N10/'净值数据(iFinD公式)'!$B$5:$N$5)*(1-持仓配置!$P$7)^((ROW()-6)/说明!$C$17)) -> 1.0110077 | L11: =IF(OR(K11="",K10=""),"",K11/K10-1) -> -0.035302084 | M11: =IF(K11="","",K11/MAX(K$6:K11)-1) -> -0.035302084
A12: =IF('净值数据(iFinD公式)'!A11="","",'净值数据(iFinD公式)'!A11) -> 46181 | B12: =IF(OR('净值数据(iFinD公式)'!$A11="",'净值数据(iFinD公式)'!$B11=""),"",SUMPRODUCT(持仓配置!$B$4:$N$4,'净值数据(iFinD公式)'!$B11:$N11/'净值数据(iFinD公式)'!$B$5:$N$5)*(1-持仓配置!$P$4)^((ROW()-6)/说明!$C$17)) -> 0.99463804 | C12: =IF(OR(B12="",B11=""),"",B12/B11-1) -> -0.0051467771 | D12: =IF(B12="","",B12/MAX(B$6:B12)-1) -> -0.00810486 | E12: =IF(OR('净值数据(iFinD公式)'!$A11="",'净值数据(iFinD公式)'!$B11=""),"",SUMPRODUCT(持仓配置!$B$5:$N$5,'净值数据(iFinD公式)'!$B11:$N11/'净值数据(iFinD公式)'!$B$5:$N$5)*(1-持仓配置!$P$5)^((ROW()-6)/说明!$C$17)) -> 0.99141603 | F12: =IF(OR(E12="",E11=""),"",E12/E11-1) -> -0.0082179367 | G12: =IF(E12="","",E12/MAX(E$6:E12)-1) -> -0.013520451 | H12: =IF(OR('净值数据(iFinD公式)'!$A11="",'净值数据(iFinD公式)'!$B11=""),"",SUMPRODUCT(持仓配置!$B$6:$N$6,'净值数据(iFinD公式)'!$B11:$N11/'净值数据(iFinD公式)'!$B$5:$N$5)*(1-持仓配置!$P$6)^((ROW()-6)/说明!$C$17)) -> 0.9860652 | I12: =IF(OR(H12="",H11=""),"",H12/H11-1) -> -0.012923792 | J12: =IF(H12="","",H12/MAX(H$6:H12)-1) -> -0.0205123 | K12: =IF(OR('净值数据(iFinD公式)'!$A11="",'净值数据(iFinD公式)'!$B11=""),"",SUMPRODUCT(持仓配置!$B$7:$N$7,'净值数据(iFinD公式)'!$B11:$N11/'净值数据(iFinD公式)'!$B$5:$N$5)*(1-持仓配置!$P$7)^((ROW()-6)/说明!$C$17)) -> 0.97978619 | L12: =IF(OR(K12="",K11=""),"",K12/K11-1) -> -0.030881592 | M12: =IF(K12="","",K12/MAX(K$6:K12)-1) -> -0.065093491
A13: =IF('净值数据(iFinD公式)'!A12="","",'净值数据(iFinD公式)'!A12) -> 46182 | B13: =IF(OR('净值数据(iFinD公式)'!$A12="",'净值数据(iFinD公式)'!$B12=""),"",SUMPRODUCT(持仓配置!$B$4:$N$4,'净值数据(iFinD公式)'!$B12:$N12/'净值数据(iFinD公式)'!$B$5:$N$5)*(1-持仓配置!$P$4)^((ROW()-6)/说明!$C$17)) -> 0.9981093 | C13: =IF(OR(B13="",B12=""),"",B13/B12-1) -> 0.0034899767 | D13: =IF(B13="","",B13/MAX(B$6:B13)-1) -> -0.004643169 | E13: =IF(OR('净值数据(iFinD公式)'!$A12="",'净值数据(iFinD公式)'!$B12=""),"",SUMPRODUCT(持仓配置!$B$5:$N$5,'净值数据(iFinD公式)'!$B12:$N12/'净值数据(iFinD公式)'!$B$5:$N$5)*(1-持仓配置!$P$5)^((ROW()-6)/说明!$C$17)) -> 0.99885349 | F13: =IF(OR(E13="",E12=""),"",E13/E12-1) -> 0.0075018579 | G13: =IF(E13="","",E13/MAX(E$6:E13)-1) -> -0.0061200214 | H13: =IF(OR('净值数据(iFinD公式)'!$A12="",'净值数据(iFinD公式)'!$B12=""),"",SUMPRODUCT(持仓配置!$B$6:$N$6,'净值数据(iFinD公式)'!$B12:$N12/'净值数据(iFinD公式)'!$B$5:$N$5)*(1-持仓配置!$P$6)^((ROW()-6)/说明!$C$17)) -> 0.99769737 | I13: =IF(OR(H13="",H12=""),"",H13/H12-1) -> 0.011796555 | J13: =IF(H13="","",H13/MAX(H$6:H13)-1) -> -0.0089577195 | K13: =IF(OR('净值数据(iFinD公式)'!$A12="",'净值数据(iFinD公式)'!$B12=""),"",SUMPRODUCT(持仓配置!$B$7:$N$7,'净值数据(iFinD公式)'!$B12:$N12/'净值数据(iFinD公式)'!$B$5:$N$5)*(1-持仓配置!$P$7)^((ROW()-6)/说明!$C$17)) -> 1.034542 | L13: =IF(OR(K13="",K12=""),"",K13/K12-1) -> 0.055885507 | M13: =IF(K13="","",K13/MAX(K$6:K13)-1) -> -0.012845767
A14: =IF('净值数据(iFinD公式)'!A13="","",'净值数据(iFinD公式)'!A13) -> 46183 | B14: =IF(OR('净值数据(iFinD公式)'!$A13="",'净值数据(iFinD公式)'!$B13=""),"",SUMPRODUCT(持仓配置!$B$4:$N$4,'净值数据(iFinD公式)'!$B13:$N13/'净值数据(iFinD公式)'!$B$5:$N$5)*(1-持仓配置!$P$4)^((ROW()-6)/说明!$C$17)) -> 0.99416737 | C14: =IF(OR(B14="",B13=""),"",B14/B13-1) -> -0.0039494012 | D14: =IF(B14="","",B14/MAX(B$6:B14)-1) -> -0.0085742325 | E14: =IF(OR('净值数据(iFinD公式)'!$A13="",'净值数据(iFinD公式)'!$B13=""),"",SUMPRODUCT(持仓配置!$B$5:$N$5,'净值数据(iFinD公式)'!$B13:$N13/'净值数据(iFinD公式)'!$B$5:$N$5)*(1-持仓配置!$P$5)^((ROW()-6)/说明!$C$17)) -> 0.99329826 | F14: =IF(OR(E14="",E13=""),"",E14/E13-1) -> -0.0055616046 | G14: =IF(E14="","",E14/MAX(E$6:E14)-1) -> -0.011647589 | H14: =IF(OR('净值数据(iFinD公式)'!$A13="",'净值数据(iFinD公式)'!$B13=""),"",SUMPRODUCT(持仓配置!$B$6:$N$6,'净值数据(iFinD公式)'!$B13:$N13/'净值数据(iFinD公式)'!$B$5:$N$5)*(1-持仓配置!$P$6)^((ROW()-6)/说明!$C$17)) -> 0.9890904 | I14: =IF(OR(H14="",H13=""),"",H14/H13-1) -> -0.0086268357 | J14: =IF(H14="","",H14/MAX(H$6:H14)-1) -> -0.017507278 | K14: =IF(OR('净值数据(iFinD公式)'!$A13="",'净值数据(iFinD公式)'!$B13=""),"",SUMPRODUCT(持仓配置!$B$7:$N$7,'净值数据(iFinD公式)'!$B13:$N13/'净值数据(iFinD公式)'!$B$5:$N$5)*(1-持仓配置!$P$7)^((ROW()-6)/说明!$C$17)) -> 1.0134071 | L14: =IF(OR(K14="",K13=""),"",K14/K13-1) -> -0.020429257 | M14: =IF(K14="","",K14/MAX(K$6:K14)-1) -> -0.033012594
A15: =IF('净值数据(iFinD公式)'!A14="","",'净值数据(iFinD公式)'!A14) -> 46184 | B15: =IF(OR('净值数据(iFinD公式)'!$A14="",'净值数据(iFinD公式)'!$B14=""),"",SUMPRODUCT(持仓配置!$B$4:$N$4,'净值数据(iFinD公式)'!$B14:$N14/'净值数据(iFinD公式)'!$B$5:$N$5)*(1-持仓配置!$P$4)^((ROW()-6)/说明!$C$17)) -> 0.99283271 | C15: =IF(OR(B15="",B14=""),"",B15/B14-1) -> -0.001342484 | D15: =IF(B15="","",B15/MAX(B$6:B15)-1) -> -0.0099052057 | E15: =IF(OR('净值数据(iFinD公式)'!$A14="",'净值数据(iFinD公式)'!$B14=""),"",SUMPRODUCT(持仓配置!$B$5:$N$5,'净值数据(iFinD公式)'!$B14:$N14/'净值数据(iFinD公式)'!$B$5:$N$5)*(1-持仓配置!$P$5)^((ROW()-6)/说明!$C$17)) -> 0.99221024 | F15: =IF(OR(E15="",E14=""),"",E15/E14-1) -> -0.0010953616 | G15: =IF(E15="","",E15/MAX(E$6:E15)-1) -> -0.012730192 | H15: =IF(OR('净值数据(iFinD公式)'!$A14="",'净值数据(iFinD公式)'!$B14=""),"",SUMPRODUCT(持仓配置!$B$6:$N$6,'净值数据(iFinD公式)'!$B14:$N14/'净值数据(iFinD公式)'!$B$5:$N$5)*(1-持仓配置!$P$6)^((ROW()-6)/说明!$C$17)) -> 0.98728284 | I15: =IF(OR(H15="",H14=""),"",H15/H14-1) -> -0.0018274936 | J15: =IF(H15="","",H15/MAX(H$6:H15)-1) -> -0.019302778 | K15: =IF(OR('净值数据(iFinD公式)'!$A14="",'净值数据(iFinD公式)'!$B14=""),"",SUMPRODUCT(持仓配置!$B$7:$N$7,'净值数据(iFinD公式)'!$B14:$N14/'净值数据(iFinD公式)'!$B$5:$N$5)*(1-持仓配置!$P$7)^((ROW()-6)/说明!$C$17)) -> 1.0210851 | L15: =IF(OR(K15="",K14=""),"",K15/K14-1) -> 0.007576428 | M15: =IF(K15="","",K15/MAX(K$6:K15)-1) -> -0.025686284
A16: =IF('净值数据(iFinD公式)'!A15="","",'净值数据(iFinD公式)'!A15) -> 46185 | B16: =IF(OR('净值数据(iFinD公式)'!$A15="",'净值数据(iFinD公式)'!$B15=""),"",SUMPRODUCT(持仓配置!$B$4:$N$4,'净值数据(iFinD公式)'!$B15:$N15/'净值数据(iFinD公式)'!$B$5:$N$5)*(1-持仓配置!$P$4)^((ROW()-6)/说明!$C$17)) -> 0.99406258 | C16: =IF(OR(B16="",B15=""),"",B16/B15-1) -> 0.0012387484 | D16: =IF(B16="","",B16/MAX(B$6:B16)-1) -> -0.0086787273 | E16: =IF(OR('净值数据(iFinD公式)'!$A15="",'净值数据(iFinD公式)'!$B15=""),"",SUMPRODUCT(持仓配置!$B$5:$N$5,'净值数据(iFinD公式)'!$B15:$N15/'净值数据(iFinD公式)'!$B$5:$N$5)*(1-持仓配置!$P$5)^((ROW()-6)/说明!$C$17)) -> 0.9935522 | F16: =IF(OR(E16="",E15=""),"",E16/E15-1) -> 0.0013524923 | G16: =IF(E16="","",E16/MAX(E$6:E16)-1) -> -0.011394917 | H16: =IF(OR('净值数据(iFinD公式)'!$A15="",'净值数据(iFinD公式)'!$B15=""),"",SUMPRODUCT(持仓配置!$B$6:$N$6,'净值数据(iFinD公式)'!$B15:$N15/'净值数据(iFinD公式)'!$B$5:$N$5)*(1-持仓配置!$P$6)^((ROW()-6)/说明!$C$17)) -> 0.98931719 | I16: =IF(OR(H16="",H15=""),"",H16/H15-1) -> 0.0020605487 | J16: =IF(H16="","",H16/MAX(H$6:H16)-1) -> -0.017282003 | K16: =IF(OR('净值数据(iFinD公式)'!$A15="",'净值数据(iFinD公式)'!$B15=""),"",SUMPRODUCT(持仓配置!$B$7:$N$7,'净值数据(iFinD公式)'!$B15:$N15/'净值数据(iFinD公式)'!$B$5:$N$5)*(1-持仓配置!$P$7)^((ROW()-6)/说明!$C$17)) -> 1.0147864 | L16: =IF(OR(K16="",K15=""),"",K16/K15-1) -> -0.006168628 | M16: =IF(K16="","",K16/MAX(K$6:K16)-1) -> -0.031696463
A17: =IF('净值数据(iFinD公式)'!A16="","",'净值数据(iFinD公式)'!A16) -> 46188 | B17: =IF(OR('净值数据(iFinD公式)'!$A16="",'净值数据(iFinD公式)'!$B16=""),"",SUMPRODUCT(持仓配置!$B$4:$N$4,'净值数据(iFinD公式)'!$B16:$N16/'净值数据(iFinD公式)'!$B$5:$N$5)*(1-持仓配置!$P$4)^((ROW()-6)/说明!$C$17)) -> 1.0008242 | C17: =IF(OR(B17="",B16=""),"",B17/B16-1) -> 0.0068020094 | D17: =IF(B17="","",B17/MAX(B$6:B17)-1) -> -0.0019357507 | E17: =IF(OR('净值数据(iFinD公式)'!$A16="",'净值数据(iFinD公式)'!$B16=""),"",SUMPRODUCT(持仓配置!$B$5:$N$5,'净值数据(iFinD公式)'!$B16:$N16/'净值数据(iFinD公式)'!$B$5:$N$5)*(1-持仓配置!$P$5)^((ROW()-6)/说明!$C$17)) -> 1.0052614 | F17: =IF(OR(E17="",E16=""),"",E17/E16-1) -> 0.011785176 | G17: =IF(E17="","",E17/MAX(E$6:E17)-1) -> 0 | H17: =IF(OR('净值数据(iFinD公式)'!$A16="",'净值数据(iFinD公式)'!$B16=""),"",SUMPRODUCT(持仓配置!$B$6:$N$6,'净值数据(iFinD公式)'!$B16:$N16/'净值数据(iFinD公式)'!$B$5:$N$5)*(1-持仓配置!$P$6)^((ROW()-6)/说明!$C$17)) -> 1.0074658 | I17: =IF(OR(H17="",H16=""),"",H17/H16-1) -> 0.01834455 | J17: =IF(H17="","",H17/MAX(H$6:H17)-1) -> 0 | K17: =IF(OR('净值数据(iFinD公式)'!$A16="",'净值数据(iFinD公式)'!$B16=""),"",SUMPRODUCT(持仓配置!$B$7:$N$7,'净值数据(iFinD公式)'!$B16:$N16/'净值数据(iFinD公式)'!$B$5:$N$5)*(1-持仓配置!$P$7)^((ROW()-6)/说明!$C$17)) -> 1.0808664 | L17: =IF(OR(K17="",K16=""),"",K17/K16-1) -> 0.065117147 | M17: =IF(K17="","",K17/MAX(K$6:K17)-1) -> 0
A18: =IF('净值数据(iFinD公式)'!A17="","",'净值数据(iFinD公式)'!A17) -> 46189 | B18: =IF(OR('净值数据(iFinD公式)'!$A17="",'净值数据(iFinD公式)'!$B17=""),"",SUMPRODUCT(持仓配置!$B$4:$N$4,'净值数据(iFinD公式)'!$B17:$N17/'净值数据(iFinD公式)'!$B$5:$N$5)*(1-持仓配置!$P$4)^((ROW()-6)/说明!$C$17)) -> 1.003562 | C18: =IF(OR(B18="",B17=""),"",B18/B17-1) -> 0.0027355394 | D18: =IF(B18="","",B18/MAX(B$6:B18)-1) -> 0 | E18: =IF(OR('净值数据(iFinD公式)'!$A17="",'净值数据(iFinD公式)'!$B17=""),"",SUMPRODUCT(持仓配置!$B$5:$N$5,'净值数据(iFinD公式)'!$B17:$N17/'净值数据(iFinD公式)'!$B$5:$N$5)*(1-持仓配置!$P$5)^((ROW()-6)/说明!$C$17)) -> 1.0097217 | F18: =IF(OR(E18="",E17=""),"",E18/E17-1) -> 0.0044369691 | G18: =IF(E18="","",E18/MAX(E$6:E18)-1) -> 0 | H18: =IF(OR('净值数据(iFinD公式)'!$A17="",'净值数据(iFinD公式)'!$B17=""),"",SUMPRODUCT(持仓配置!$B$6:$N$6,'净值数据(iFinD公式)'!$B17:$N17/'净值数据(iFinD公式)'!$B$5:$N$5)*(1-持仓配置!$P$6)^((ROW()-6)/说明!$C$17)) -> 1.0137961 | I18: =IF(OR(H18="",H17=""),"",H18/H17-1) -> 0.0062834111 | J18: =IF(H18="","",H18/MAX(H$6:H18)-1) -> 0 | K18: =IF(OR('净值数据(iFinD公式)'!$A17="",'净值数据(iFinD公式)'!$B17=""),"",SUMPRODUCT(持仓配置!$B$7:$N$7,'净值数据(iFinD公式)'!$B17:$N17/'净值数据(iFinD公式)'!$B$5:$N$5)*(1-持仓配置!$P$7)^((ROW()-6)/说明!$C$17)) -> 1.1061052 | L18: =IF(OR(K18="",K17=""),"",K18/K17-1) -> 0.023350539 | M18: =IF(K18="","",K18/MAX(K$6:K18)-1) -> 0
... A26: =IF('净值数据(iFinD公式)'!A25="","",'净值数据(iFinD公式)'!A25) -> 46202 | B26: =IF(OR('净值数据(iFinD公式)'!$A25="",'净值数据(iFinD公式)'!$B25=""),"",SUMPRODUCT(持仓配置!$B$4:$N$4,'净值数据(iFinD公式)'!$B25:$N25/'净值数据(iFinD公式)'!$B$5:$N$5)*(1-持仓配置!$P$4)^((ROW()-6)/说明!$C$17)) -> 1.0092716 | C26: =IF(OR(B26="",B25=""),"",B26/B25-1) -> 0.0016853386 | D26: =IF(B26="","",B26/MAX(B$6:B26)-1) -> -0.00097520704 | E26: =IF(OR('净值数据(iFinD公式)'!$A25="",'净值数据(iFinD公式)'!$B25=""),"",SUMPRODUCT(持仓配置!$B$5:$N$5,'净值数据(iFinD公式)'!$B25:$N25/'净值数据(iFinD公式)'!$B$5:$N$5)*(1-持仓配置!$P$5)^((ROW()-6)/说明!$C$17)) -> 1.0215215 | F26: =IF(OR(E26="",E25=""),"",E26/E25-1) -> 0.0022807927 | G26: =IF(E26="","",E26/MAX(E$6:E26)-1) -> -0.0036329055 | H26: =IF(OR('净值数据(iFinD公式)'!$A25="",'净值数据(iFinD公式)'!$B25=""),"",SUMPRODUCT(持仓配置!$B$6:$N$6,'净值数据(iFinD公式)'!$B25:$N25/'净值数据(iFinD公式)'!$B$5:$N$5)*(1-持仓配置!$P$6)^((ROW()-6)/说明!$C$17)) -> 1.028918 | I26: =IF(OR(H26="",H25=""),"",H26/H25-1) -> 0.003020864 | J26: =IF(H26="","",H26/MAX(H$6:H26)-1) -> -0.0056962923 | K26: =IF(OR('净值数据(iFinD公式)'!$A25="",'净值数据(iFinD公式)'!$B25=""),"",SUMPRODUCT(持仓配置!$B$7:$N$7,'净值数据(iFinD公式)'!$B25:$N25/'净值数据(iFinD公式)'!$B$5:$N$5)*(1-持仓配置!$P$7)^((ROW()-6)/说明!$C$17)) -> 1.2352096 | L26: =IF(OR(K26="",K25=""),"",K26/K25-1) -> 0.0099522555 | M26: =IF(K26="","",K26/MAX(K$6:K26)-1) -> -0.018751931
A27: =IF('净值数据(iFinD公式)'!A26="","",'净值数据(iFinD公式)'!A26) -> 46203 | B27: =IF(OR('净值数据(iFinD公式)'!$A26="",'净值数据(iFinD公式)'!$B26=""),"",SUMPRODUCT(持仓配置!$B$4:$N$4,'净值数据(iFinD公式)'!$B26:$N26/'净值数据(iFinD公式)'!$B$5:$N$5)*(1-持仓配置!$P$4)^((ROW()-6)/说明!$C$17)) -> 1.0119135 | C27: =IF(OR(B27="",B26=""),"",B27/B26-1) -> 0.0026176935 | D27: =IF(B27="","",B27/MAX(B$6:B27)-1) -> 0 | E27: =IF(OR('净值数据(iFinD公式)'!$A26="",'净值数据(iFinD公式)'!$B26=""),"",SUMPRODUCT(持仓配置!$B$5:$N$5,'净值数据(iFinD公式)'!$B26:$N26/'净值数据(iFinD公式)'!$B$5:$N$5)*(1-持仓配置!$P$5)^((ROW()-6)/说明!$C$17)) -> 1.0280127 | F27: =IF(OR(E27="",E26=""),"",E27/E26-1) -> 0.0063545029 | G27: =IF(E27="","",E27/MAX(E$6:E27)-1) -> 0 | H27: =IF(OR('净值数据(iFinD公式)'!$A26="",'净值数据(iFinD公式)'!$B26=""),"",SUMPRODUCT(持仓配置!$B$6:$N$6,'净值数据(iFinD公式)'!$B26:$N26/'净值数据(iFinD公式)'!$B$5:$N$5)*(1-持仓配置!$P$6)^((ROW()-6)/说明!$C$17)) -> 1.0388818 | I27: =IF(OR(H27="",H26=""),"",H27/H26-1) -> 0.0096837753 | J27: =IF(H27="","",H27/MAX(H$6:H27)-1) -> 0 | K27: =IF(OR('净值数据(iFinD公式)'!$A26="",'净值数据(iFinD公式)'!$B26=""),"",SUMPRODUCT(持仓配置!$B$7:$N$7,'净值数据(iFinD公式)'!$B26:$N26/'净值数据(iFinD公式)'!$B$5:$N$5)*(1-持仓配置!$P$7)^((ROW()-6)/说明!$C$17)) -> 1.2895492 | L27: =IF(OR(K27="",K26=""),"",K27/K26-1) -> 0.0439922 | M27: =IF(K27="","",K27/MAX(K$6:K27)-1) -> 0 | O27: =B25/B6-1 -> 0.0075734673
A28: =IF('净值数据(iFinD公式)'!A27="","",'净值数据(iFinD公式)'!A27) -> 46204 | B28: =IF(OR('净值数据(iFinD公式)'!$A27="",'净值数据(iFinD公式)'!$B27=""),"",SUMPRODUCT(持仓配置!$B$4:$N$4,'净值数据(iFinD公式)'!$B27:$N27/'净值数据(iFinD公式)'!$B$5:$N$5)*(1-持仓配置!$P$4)^((ROW()-6)/说明!$C$17)) -> 1.0089265 | C28: =IF(OR(B28="",B27=""),"",B28/B27-1) -> -0.0029519081 | D28: =IF(B28="","",B28/MAX(B$6:B28)-1) -> -0.0029519081 | E28: =IF(OR('净值数据(iFinD公式)'!$A27="",'净值数据(iFinD公式)'!$B27=""),"",SUMPRODUCT(持仓配置!$B$5:$N$5,'净值数据(iFinD公式)'!$B27:$N27/'净值数据(iFinD公式)'!$B$5:$N$5)*(1-持仓配置!$P$5)^((ROW()-6)/说明!$C$17)) -> 1.0234029 | F28: =IF(OR(E28="",E27=""),"",E28/E27-1) -> -0.0044842236 | G28: =IF(E28="","",E28/MAX(E$6:E28)-1) -> -0.0044842236 | H28: =IF(OR('净值数据(iFinD公式)'!$A27="",'净值数据(iFinD公式)'!$B27=""),"",SUMPRODUCT(持仓配置!$B$6:$N$6,'净值数据(iFinD公式)'!$B27:$N27/'净值数据(iFinD公式)'!$B$5:$N$5)*(1-持仓配置!$P$6)^((ROW()-6)/说明!$C$17)) -> 1.0322302 | I28: =IF(OR(H28="",H27=""),"",H28/H27-1) -> -0.0064026708 | J28: =IF(H28="","",H28/MAX(H$6:H28)-1) -> -0.0064026708 | K28: =IF(OR('净值数据(iFinD公式)'!$A27="",'净值数据(iFinD公式)'!$B27=""),"",SUMPRODUCT(持仓配置!$B$7:$N$7,'净值数据(iFinD公式)'!$B27:$N27/'净值数据(iFinD公式)'!$B$5:$N$5)*(1-持仓配置!$P$7)^((ROW()-6)/说明!$C$17)) -> 1.249937 | L28: =IF(OR(K28="",K27=""),"",K28/K27-1) -> -0.030717848 | M28: =IF(K28="","",K28/MAX(K$6:K28)-1) -> -0.030717848
A29: =IF('净值数据(iFinD公式)'!A28="","",'净值数据(iFinD公式)'!A28) -> 46205 | B29: =IF(OR('净值数据(iFinD公式)'!$A28="",'净值数据(iFinD公式)'!$B28=""),"",SUMPRODUCT(持仓配置!$B$4:$N$4,'净值数据(iFinD公式)'!$B28:$N28/'净值数据(iFinD公式)'!$B$5:$N$5)*(1-持仓配置!$P$4)^((ROW()-6)/说明!$C$17)) -> 1.003031 | C29: =IF(OR(B29="",B28=""),"",B29/B28-1) -> -0.005843289 | D29: =IF(B29="","",B29/MAX(B$6:B29)-1) -> -0.0087779482 | E29: =IF(OR('净值数据(iFinD公式)'!$A28="",'净值数据(iFinD公式)'!$B28=""),"",SUMPRODUCT(持仓配置!$B$5:$N$5,'净值数据(iFinD公式)'!$B28:$N28/'净值数据(iFinD公式)'!$B$5:$N$5)*(1-持仓配置!$P$5)^((ROW()-6)/说明!$C$17)) -> 1.0105958 | F29: =IF(OR(E29="",E28=""),"",E29/E28-1) -> -0.012514236 | G29: =IF(E29="","",E29/MAX(E$6:E29)-1) -> -0.016942343 | H29: =IF(OR('净值数据(iFinD公式)'!$A28="",'净值数据(iFinD公式)'!$B28=""),"",SUMPRODUCT(持仓配置!$B$6:$N$6,'净值数据(iFinD公式)'!$B28:$N28/'净值数据(iFinD公式)'!$B$5:$N$5)*(1-持仓配置!$P$6)^((ROW()-6)/说明!$C$17)) -> 1.0134351 | I29: =IF(OR(H29="",H28=""),"",H29/H28-1) -> -0.01820829 | J29: =IF(H29="","",H29/MAX(H$6:H29)-1) -> -0.024494379 | K29: =IF(OR('净值数据(iFinD公式)'!$A28="",'净值数据(iFinD公式)'!$B28=""),"",SUMPRODUCT(持仓配置!$B$7:$N$7,'净值数据(iFinD公式)'!$B28:$N28/'净值数据(iFinD公式)'!$B$5:$N$5)*(1-持仓配置!$P$7)^((ROW()-6)/说明!$C$17)) -> 1.1401462 | L29: =IF(OR(K29="",K28=""),"",K29/K28-1) -> -0.087837069 | M29: =IF(K29="","",K29/MAX(K$6:K29)-1) -> -0.11585675
A30: =IF('净值数据(iFinD公式)'!A29="","",'净值数据(iFinD公式)'!A29) -> 46206 | B30: =IF(OR('净值数据(iFinD公式)'!$A29="",'净值数据(iFinD公式)'!$B29=""),"",SUMPRODUCT(持仓配置!$B$4:$N$4,'净值数据(iFinD公式)'!$B29:$N29/'净值数据(iFinD公式)'!$B$5:$N$5)*(1-持仓配置!$P$4)^((ROW()-6)/说明!$C$17)) -> 1.0038981 | C30: =IF(OR(B30="",B29=""),"",B30/B29-1) -> 0.00086451351 | D30: =IF(B30="","",B30/MAX(B$6:B30)-1) -> -0.0079210234 | E30: =IF(OR('净值数据(iFinD公式)'!$A29="",'净值数据(iFinD公式)'!$B29=""),"",SUMPRODUCT(持仓配置!$B$5:$N$5,'净值数据(iFinD公式)'!$B29:$N29/'净值数据(iFinD公式)'!$B$5:$N$5)*(1-持仓配置!$P$5)^((ROW()-6)/说明!$C$17)) -> 1.0113375 | F30: =IF(OR(E30="",E29=""),"",E30/E29-1) -> 0.00073394516 | G30: =IF(E30="","",E30/MAX(E$6:E30)-1) -> -0.016220832 | H30: =IF(OR('净值数据(iFinD公式)'!$A29="",'净值数据(iFinD公式)'!$B29=""),"",SUMPRODUCT(持仓配置!$B$6:$N$6,'净值数据(iFinD公式)'!$B29:$N29/'净值数据(iFinD公式)'!$B$5:$N$5)*(1-持仓配置!$P$6)^((ROW()-6)/说明!$C$17)) -> 1.0152735 | I30: =IF(OR(H30="",H29=""),"",H30/H29-1) -> 0.0018140599 | J30: =IF(H30="","",H30/MAX(H$6:H30)-1) -> -0.022724753 | K30: =IF(OR('净值数据(iFinD公式)'!$A29="",'净值数据(iFinD公式)'!$B29=""),"",SUMPRODUCT(持仓配置!$B$7:$N$7,'净值数据(iFinD公式)'!$B29:$N29/'净值数据(iFinD公式)'!$B$5:$N$5)*(1-持仓配置!$P$7)^((ROW()-6)/说明!$C$17)) -> 1.1316225 | L30: =IF(OR(K30="",K29=""),"",K30/K29-1) -> -0.0074759634 | M30: =IF(K30="","",K30/MAX(K$6:K30)-1) -> -0.12246657
A31: =IF('净值数据(iFinD公式)'!A30="","",'净值数据(iFinD公式)'!A30) -> 46209 | B31: =IF(OR('净值数据(iFinD公式)'!$A30="",'净值数据(iFinD公式)'!$B30=""),"",SUMPRODUCT(持仓配置!$B$4:$N$4,'净值数据(iFinD公式)'!$B30:$N30/'净值数据(iFinD公式)'!$B$5:$N$5)*(1-持仓配置!$P$4)^((ROW()-6)/说明!$C$17)) -> 1.0027798 | C31: =IF(OR(B31="",B30=""),"",B31/B30-1) -> -0.00111401 | D31: =IF(B31="","",B31/MAX(B$6:B31)-1) -> -0.0090262092 | E31: =IF(OR('净值数据(iFinD公式)'!$A30="",'净值数据(iFinD公式)'!$B30=""),"",SUMPRODUCT(持仓配置!$B$5:$N$5,'净值数据(iFinD公式)'!$B30:$N30/'净值数据(iFinD公式)'!$B$5:$N$5)*(1-持仓配置!$P$5)^((ROW()-6)/说明!$C$17)) -> 1.0085651 | F31: =IF(OR(E31="",E30=""),"",E31/E30-1) -> -0.0027413421 | G31: =IF(E31="","",E31/MAX(E$6:E31)-1) -> -0.018917708 | H31: =IF(OR('净值数据(iFinD公式)'!$A30="",'净值数据(iFinD公式)'!$B30=""),"",SUMPRODUCT(持仓配置!$B$6:$N$6,'净值数据(iFinD公式)'!$B30:$N30/'净值数据(iFinD公式)'!$B$5:$N$5)*(1-持仓配置!$P$6)^((ROW()-6)/说明!$C$17)) -> 1.0106812 | I31: =IF(OR(H31="",H30=""),"",H31/H30-1) -> -0.0045232035 | J31: =IF(H31="","",H31/MAX(H$6:H31)-1) -> -0.027145168 | K31: =IF(OR('净值数据(iFinD公式)'!$A30="",'净值数据(iFinD公式)'!$B30=""),"",SUMPRODUCT(持仓配置!$B$7:$N$7,'净值数据(iFinD公式)'!$B30:$N30/'净值数据(iFinD公式)'!$B$5:$N$5)*(1-持仓配置!$P$7)^((ROW()-6)/说明!$C$17)) -> 1.1091831 | L31: =IF(OR(K31="",K30=""),"",K31/K30-1) -> -0.019829481 | M31: =IF(K31="","",K31/MAX(K$6:K31)-1) -> -0.13986761
A32: =IF('净值数据(iFinD公式)'!A31="","",'净值数据(iFinD公式)'!A31) -> 46210 | B32: =IF(OR('净值数据(iFinD公式)'!$A31="",'净值数据(iFinD公式)'!$B31=""),"",SUMPRODUCT(持仓配置!$B$4:$N$4,'净值数据(iFinD公式)'!$B31:$N31/'净值数据(iFinD公式)'!$B$5:$N$5)*(1-持仓配置!$P$4)^((ROW()-6)/说明!$C$17)) -> 1.0020308 | C32: =IF(OR(B32="",B31=""),"",B32/B31-1) -> -0.00074692569 | D32: =IF(B32="","",B32/MAX(B$6:B32)-1) -> -0.009766393 | E32: =IF(OR('净值数据(iFinD公式)'!$A31="",'净值数据(iFinD公式)'!$B31=""),"",SUMPRODUCT(持仓配置!$B$5:$N$5,'净值数据(iFinD公式)'!$B31:$N31/'净值数据(iFinD公式)'!$B$5:$N$5)*(1-持仓配置!$P$5)^((ROW()-6)/说明!$C$17)) -> 1.0072335 | F32: =IF(OR(E32="",E31=""),"",E32/E31-1) -> -0.0013202402 | G32: =IF(E32="","",E32/MAX(E$6:E32)-1) -> -0.020212972 | H32: =IF(OR('净值数据(iFinD公式)'!$A31="",'净值数据(iFinD公式)'!$B31=""),"",SUMPRODUCT(持仓配置!$B$6:$N$6,'净值数据(iFinD公式)'!$B31:$N31/'净值数据(iFinD公式)'!$B$5:$N$5)*(1-持仓配置!$P$6)^((ROW()-6)/说明!$C$17)) -> 1.008503 | I32: =IF(OR(H32="",H31=""),"",H32/H31-1) -> -0.0021551624 | J32: =IF(H32="","",H32/MAX(H$6:H32)-1) -> -0.029241828 | K32: =IF(OR('净值数据(iFinD公式)'!$A31="",'净值数据(iFinD公式)'!$B31=""),"",SUMPRODUCT(持仓配置!$B$7:$N$7,'净值数据(iFinD公式)'!$B31:$N31/'净值数据(iFinD公式)'!$B$5:$N$5)*(1-持仓配置!$P$7)^((ROW()-6)/说明!$C$17)) -> 1.1168983 | L32: =IF(OR(K32="",K31=""),"",K32/K31-1) -> 0.0069557665 | M32: =IF(K32="","",K32/MAX(K$6:K32)-1) -> -0.13388473
A33: =IF('净值数据(iFinD公式)'!A32="","",'净值数据(iFinD公式)'!A32) | B33: =IF(OR('净值数据(iFinD公式)'!$A32="",'净值数据(iFinD公式)'!$B32=""),"",SUMPRODUCT(持仓配置!$B$4:$N$4,'净值数据(iFinD公式)'!$B32:$N32/'净值数据(iFinD公式)'!$B$5:$N$5)*(1-持仓配置!$P$4)^((ROW()-6)/说明!$C$17)) | C33: =IF(OR(B33="",B32=""),"",B33/B32-1) | D33: =IF(B33="","",B33/MAX(B$6:B33)-1) | E33: =IF(OR('净值数据(iFinD公式)'!$A32="",'净值数据(iFinD公式)'!$B32=""),"",SUMPRODUCT(持仓配置!$B$5:$N$5,'净值数据(iFinD公式)'!$B32:$N32/'净值数据(iFinD公式)'!$B$5:$N$5)*(1-持仓配置!$P$5)^((ROW()-6)/说明!$C$17)) | F33: =IF(OR(E33="",E32=""),"",E33/E32-1) | G33: =IF(E33="","",E33/MAX(E$6:E33)-1) | H33: =IF(OR('净值数据(iFinD公式)'!$A32="",'净值数据(iFinD公式)'!$B32=""),"",SUMPRODUCT(持仓配置!$B$6:$N$6,'净值数据(iFinD公式)'!$B32:$N32/'净值数据(iFinD公式)'!$B$5:$N$5)*(1-持仓配置!$P$6)^((ROW()-6)/说明!$C$17)) | I33: =IF(OR(H33="",H32=""),"",H33/H32-1) | J33: =IF(H33="","",H33/MAX(H$6:H33)-1) | K33: =IF(OR('净值数据(iFinD公式)'!$A32="",'净值数据(iFinD公式)'!$B32=""),"",SUMPRODUCT(持仓配置!$B$7:$N$7,'净值数据(iFinD公式)'!$B32:$N32/'净值数据(iFinD公式)'!$B$5:$N$5)*(1-持仓配置!$P$7)^((ROW()-6)/说明!$C$17)) | L33: =IF(OR(K33="",K32=""),"",K33/K32-1) | M33: =IF(K33="","",K33/MAX(K$6:K33)-1)
A34: =IF('净值数据(iFinD公式)'!A33="","",'净值数据(iFinD公式)'!A33) | B34: =IF(OR('净值数据(iFinD公式)'!$A33="",'净值数据(iFinD公式)'!$B33=""),"",SUMPRODUCT(持仓配置!$B$4:$N$4,'净值数据(iFinD公式)'!$B33:$N33/'净值数据(iFinD公式)'!$B$5:$N$5)*(1-持仓配置!$P$4)^((ROW()-6)/说明!$C$17)) | C34: =IF(OR(B34="",B33=""),"",B34/B33-1) | D34: =IF(B34="","",B34/MAX(B$6:B34)-1) | E34: =IF(OR('净值数据(iFinD公式)'!$A33="",'净值数据(iFinD公式)'!$B33=""),"",SUMPRODUCT(持仓配置!$B$5:$N$5,'净值数据(iFinD公式)'!$B33:$N33/'净值数据(iFinD公式)'!$B$5:$N$5)*(1-持仓配置!$P$5)^((ROW()-6)/说明!$C$17)) | F34: =IF(OR(E34="",E33=""),"",E34/E33-1) | G34: =IF(E34="","",E34/MAX(E$6:E34)-1) | H34: =IF(OR('净值数据(iFinD公式)'!$A33="",'净值数据(iFinD公式)'!$B33=""),"",SUMPRODUCT(持仓配置!$B$6:$N$6,'净值数据(iFinD公式)'!$B33:$N33/'净值数据(iFinD公式)'!$B$5:$N$5)*(1-持仓配置!$P$6)^((ROW()-6)/说明!$C$17)) | I34: =IF(OR(H34="",H33=""),"",H34/H33-1) | J34: =IF(H34="","",H34/MAX(H$6:H34)-1) | K34: =IF(OR('净值数据(iFinD公式)'!$A33="",'净值数据(iFinD公式)'!$B33=""),"",SUMPRODUCT(持仓配置!$B$7:$N$7,'净值数据(iFinD公式)'!$B33:$N33/'净值数据(iFinD公式)'!$B$5:$N$5)*(1-持仓配置!$P$7)^((ROW()-6)/说明!$C$17)) | L34: =IF(OR(K34="",K33=""),"",K34/K33-1) | M34: =IF(K34="","",K34/MAX(K$6:K34)-1)
A35: =IF('净值数据(iFinD公式)'!A34="","",'净值数据(iFinD公式)'!A34) | B35: =IF(OR('净值数据(iFinD公式)'!$A34="",'净值数据(iFinD公式)'!$B34=""),"",SUMPRODUCT(持仓配置!$B$4:$N$4,'净值数据(iFinD公式)'!$B34:$N34/'净值数据(iFinD公式)'!$B$5:$N$5)*(1-持仓配置!$P$4)^((ROW()-6)/说明!$C$17)) | C35: =IF(OR(B35="",B34=""),"",B35/B34-1) | D35: =IF(B35="","",B35/MAX(B$6:B35)-1) | E35: =IF(OR('净值数据(iFinD公式)'!$A34="",'净值数据(iFinD公式)'!$B34=""),"",SUMPRODUCT(持仓配置!$B$5:$N$5,'净值数据(iFinD公式)'!$B34:$N34/'净值数据(iFinD公式)'!$B$5:$N$5)*(1-持仓配置!$P$5)^((ROW()-6)/说明!$C$17)) | F35: =IF(OR(E35="",E34=""),"",E35/E34-1) | G35: =IF(E35="","",E35/MAX(E$6:E35)-1) | H35: =IF(OR('净值数据(iFinD公式)'!$A34="",'净值数据(iFinD公式)'!$B34=""),"",SUMPRODUCT(持仓配置!$B$6:$N$6,'净值数据(iFinD公式)'!$B34:$N34/'净值数据(iFinD公式)'!$B$5:$N$5)*(1-持仓配置!$P$6)^((ROW()-6)/说明!$C$17)) | I35: =IF(OR(H35="",H34=""),"",H35/H34-1) | J35: =IF(H35="","",H35/MAX(H$6:H35)-1) | K35: =IF(OR('净值数据(iFinD公式)'!$A34="",'净值数据(iFinD公式)'!$B34=""),"",SUMPRODUCT(持仓配置!$B$7:$N$7,'净值数据(iFinD公式)'!$B34:$N34/'净值数据(iFinD公式)'!$B$5:$N$5)*(1-持仓配置!$P$7)^((ROW()-6)/说明!$C$17)) | L35: =IF(OR(K35="",K34=""),"",K35/K34-1) | M35: =IF(K35="","",K35/MAX(K$6:K35)-1)
A36: =IF('净值数据(iFinD公式)'!A35="","",'净值数据(iFinD公式)'!A35) | B36: =IF(OR('净值数据(iFinD公式)'!$A35="",'净值数据(iFinD公式)'!$B35=""),"",SUMPRODUCT(持仓配置!$B$4:$N$4,'净值数据(iFinD公式)'!$B35:$N35/'净值数据(iFinD公式)'!$B$5:$N$5)*(1-持仓配置!$P$4)^((ROW()-6)/说明!$C$17)) | C36: =IF(OR(B36="",B35=""),"",B36/B35-1) | D36: =IF(B36="","",B36/MAX(B$6:B36)-1) | E36: =IF(OR('净值数据(iFinD公式)'!$A35="",'净值数据(iFinD公式)'!$B35=""),"",SUMPRODUCT(持仓配置!$B$5:$N$5,'净值数据(iFinD公式)'!$B35:$N35/'净值数据(iFinD公式)'!$B$5:$N$5)*(1-持仓配置!$P$5)^((ROW()-6)/说明!$C$17)) | F36: =IF(OR(E36="",E35=""),"",E36/E35-1) | G36: =IF(E36="","",E36/MAX(E$6:E36)-1) | H36: =IF(OR('净值数据(iFinD公式)'!$A35="",'净值数据(iFinD公式)'!$B35=""),"",SUMPRODUCT(持仓配置!$B$6:$N$6,'净值数据(iFinD公式)'!$B35:$N35/'净值数据(iFinD公式)'!$B$5:$N$5)*(1-持仓配置!$P$6)^((ROW()-6)/说明!$C$17)) | I36: =IF(OR(H36="",H35=""),"",H36/H35-1) | J36: =IF(H36="","",H36/MAX(H$6:H36)-1) | K36: =IF(OR('净值数据(iFinD公式)'!$A35="",'净值数据(iFinD公式)'!$B35=""),"",SUMPRODUCT(持仓配置!$B$7:$N$7,'净值数据(iFinD公式)'!$B35:$N35/'净值数据(iFinD公式)'!$B$5:$N$5)*(1-持仓配置!$P$7)^((ROW()-6)/说明!$C$17)) | L36: =IF(OR(K36="",K35=""),"",K36/K35-1) | M36: =IF(K36="","",K36/MAX(K$6:K36)-1)
A37: =IF('净值数据(iFinD公式)'!A36="","",'净值数据(iFinD公式)'!A36) | B37: =IF(OR('净值数据(iFinD公式)'!$A36="",'净值数据(iFinD公式)'!$B36=""),"",SUMPRODUCT(持仓配置!$B$4:$N$4,'净值数据(iFinD公式)'!$B36:$N36/'净值数据(iFinD公式)'!$B$5:$N$5)*(1-持仓配置!$P$4)^((ROW()-6)/说明!$C$17)) | C37: =IF(OR(B37="",B36=""),"",B37/B36-1) | D37: =IF(B37="","",B37/MAX(B$6:B37)-1) | E37: =IF(OR('净值数据(iFinD公式)'!$A36="",'净值数据(iFinD公式)'!$B36=""),"",SUMPRODUCT(持仓配置!$B$5:$N$5,'净值数据(iFinD公式)'!$B36:$N36/'净值数据(iFinD公式)'!$B$5:$N$5)*(1-持仓配置!$P$5)^((ROW()-6)/说明!$C$17)) | F37: =IF(OR(E37="",E36=""),"",E37/E36-1) | G37: =IF(E37="","",E37/MAX(E$6:E37)-1) | H37: =IF(OR('净值数据(iFinD公式)'!$A36="",'净值数据(iFinD公式)'!$B36=""),"",SUMPRODUCT(持仓配置!$B$6:$N$6,'净值数据(iFinD公式)'!$B36:$N36/'净值数据(iFinD公式)'!$B$5:$N$5)*(1-持仓配置!$P$6)^((ROW()-6)/说明!$C$17)) | I37: =IF(OR(H37="",H36=""),"",H37/H36-1) | J37: =IF(H37="","",H37/MAX(H$6:H37)-1) | K37: =IF(OR('净值数据(iFinD公式)'!$A36="",'净值数据(iFinD公式)'!$B36=""),"",SUMPRODUCT(持仓配置!$B$7:$N$7,'净值数据(iFinD公式)'!$B36:$N36/'净值数据(iFinD公式)'!$B$5:$N$5)*(1-持仓配置!$P$7)^((ROW()-6)/说明!$C$17)) | L37: =IF(OR(K37="",K36=""),"",K37/K36-1) | M37: =IF(K37="","",K37/MAX(K$6:K37)-1)
A38: =IF('净值数据(iFinD公式)'!A37="","",'净值数据(iFinD公式)'!A37) | B38: =IF(OR('净值数据(iFinD公式)'!$A37="",'净值数据(iFinD公式)'!$B37=""),"",SUMPRODUCT(持仓配置!$B$4:$N$4,'净值数据(iFinD公式)'!$B37:$N37/'净值数据(iFinD公式)'!$B$5:$N$5)*(1-持仓配置!$P$4)^((ROW()-6)/说明!$C$17)) | C38: =IF(OR(B38="",B37=""),"",B38/B37-1) | D38: =IF(B38="","",B38/MAX(B$6:B38)-1) | E38: =IF(OR('净值数据(iFinD公式)'!$A37="",'净值数据(iFinD公式)'!$B37=""),"",SUMPRODUCT(持仓配置!$B$5:$N$5,'净值数据(iFinD公式)'!$B37:$N37/'净值数据(iFinD公式)'!$B$5:$N$5)*(1-持仓配置!$P$5)^((ROW()-6)/说明!$C$17)) | F38: =IF(OR(E38="",E37=""),"",E38/E37-1) | G38: =IF(E38="","",E38/MAX(E$6:E38)-1) | H38: =IF(OR('净值数据(iFinD公式)'!$A37="",'净值数据(iFinD公式)'!$B37=""),"",SUMPRODUCT(持仓配置!$B$6:$N$6,'净值数据(iFinD公式)'!$B37:$N37/'净值数据(iFinD公式)'!$B$5:$N$5)*(1-持仓配置!$P$6)^((ROW()-6)/说明!$C$17)) | I38: =IF(OR(H38="",H37=""),"",H38/H37-1) | J38: =IF(H38="","",H38/MAX(H$6:H38)-1) | K38: =IF(OR('净值数据(iFinD公式)'!$A37="",'净值数据(iFinD公式)'!$B37=""),"",SUMPRODUCT(持仓配置!$B$7:$N$7,'净值数据(iFinD公式)'!$B37:$N37/'净值数据(iFinD公式)'!$B$5:$N$5)*(1-持仓配置!$P$7)^((ROW()-6)/说明!$C$17)) | L38: =IF(OR(K38="",K37=""),"",K38/K37-1) | M38: =IF(K38="","",K38/MAX(K$6:K38)-1)
A39: =IF('净值数据(iFinD公式)'!A38="","",'净值数据(iFinD公式)'!A38) | B39: =IF(OR('净值数据(iFinD公式)'!$A38="",'净值数据(iFinD公式)'!$B38=""),"",SUMPRODUCT(持仓配置!$B$4:$N$4,'净值数据(iFinD公式)'!$B38:$N38/'净值数据(iFinD公式)'!$B$5:$N$5)*(1-持仓配置!$P$4)^((ROW()-6)/说明!$C$17)) | C39: =IF(OR(B39="",B38=""),"",B39/B38-1) | D39: =IF(B39="","",B39/MAX(B$6:B39)-1) | E39: =IF(OR('净值数据(iFinD公式)'!$A38="",'净值数据(iFinD公式)'!$B38=""),"",SUMPRODUCT(持仓配置!$B$5:$N$5,'净值数据(iFinD公式)'!$B38:$N38/'净值数据(iFinD公式)'!$B$5:$N$5)*(1-持仓配置!$P$5)^((ROW()-6)/说明!$C$17)) | F39: =IF(OR(E39="",E38=""),"",E39/E38-1) | G39: =IF(E39="","",E39/MAX(E$6:E39)-1) | H39: =IF(OR('净值数据(iFinD公式)'!$A38="",'净值数据(iFinD公式)'!$B38=""),"",SUMPRODUCT(持仓配置!$B$6:$N$6,'净值数据(iFinD公式)'!$B38:$N38/'净值数据(iFinD公式)'!$B$5:$N$5)*(1-持仓配置!$P$6)^((ROW()-6)/说明!$C$17)) | I39: =IF(OR(H39="",H38=""),"",H39/H38-1) | J39: =IF(H39="","",H39/MAX(H$6:H39)-1) | K39: =IF(OR('净值数据(iFinD公式)'!$A38="",'净值数据(iFinD公式)'!$B38=""),"",SUMPRODUCT(持仓配置!$B$7:$N$7,'净值数据(iFinD公式)'!$B38:$N38/'净值数据(iFinD公式)'!$B$5:$N$5)*(1-持仓配置!$P$7)^((ROW()-6)/说明!$C$17)) | L39: =IF(OR(K39="",K38=""),"",K39/K38-1) | M39: =IF(K39="","",K39/MAX(K$6:K39)-1)
... A60: =IF('净值数据(iFinD公式)'!A59="","",'净值数据(iFinD公式)'!A59) | B60: =IF(OR('净值数据(iFinD公式)'!$A59="",'净值数据(iFinD公式)'!$B59=""),"",SUMPRODUCT(持仓配置!$B$4:$N$4,'净值数据(iFinD公式)'!$B59:$N59/'净值数据(iFinD公式)'!$B$5:$N$5)*(1-持仓配置!$P$4)^((ROW()-6)/说明!$C$17)) | C60: =IF(OR(B60="",B59=""),"",B60/B59-1) | D60: =IF(B60="","",B60/MAX(B$6:B60)-1) | E60: =IF(OR('净值数据(iFinD公式)'!$A59="",'净值数据(iFinD公式)'!$B59=""),"",SUMPRODUCT(持仓配置!$B$5:$N$5,'净值数据(iFinD公式)'!$B59:$N59/'净值数据(iFinD公式)'!$B$5:$N$5)*(1-持仓配置!$P$5)^((ROW()-6)/说明!$C$17)) | F60: =IF(OR(E60="",E59=""),"",E60/E59-1) | G60: =IF(E60="","",E60/MAX(E$6:E60)-1) | H60: =IF(OR('净值数据(iFinD公式)'!$A59="",'净值数据(iFinD公式)'!$B59=""),"",SUMPRODUCT(持仓配置!$B$6:$N$6,'净值数据(iFinD公式)'!$B59:$N59/'净值数据(iFinD公式)'!$B$5:$N$5)*(1-持仓配置!$P$6)^((ROW()-6)/说明!$C$17)) | I60: =IF(OR(H60="",H59=""),"",H60/H59-1) | J60: =IF(H60="","",H60/MAX(H$6:H60)-1) | K60: =IF(OR('净值数据(iFinD公式)'!$A59="",'净值数据(iFinD公式)'!$B59=""),"",SUMPRODUCT(持仓配置!$B$7:$N$7,'净值数据(iFinD公式)'!$B59:$N59/'净值数据(iFinD公式)'!$B$5:$N$5)*(1-持仓配置!$P$7)^((ROW()-6)/说明!$C$17)) | L60: =IF(OR(K60="",K59=""),"",K60/K59-1) | M60: =IF(K60="","",K60/MAX(K$6:K60)-1)
A62: 组合净值起始=1.0000；买入持有，权重随涨跌漂移；净值已按年化费率折每日扣费。新增日期下拉填充。

Sheet 看板-10-90
B2: 样板间组合走势看板（10-90 账户）
B3: ="买入持有 · 已扣年化费率 "&TEXT(持仓配置!$M$4,"0.0%")&"（折每日计入净值）" -> 买入持有 · 已扣年化费率 0.5%（折每日计入净值） | E3: ="净值日期："&TEXT(LOOKUP(2,1/('组合净值（模拟）'!$B$6:$B$60<>""),'组合净值（模拟）'!$A$6:$A$60),"yyyy-mm-dd") -> 净值日期：2026-07-07
B5: 产品业绩表现（历史表现不代表未来收益承诺）
B6: 最新净值 | C6: 累计收益 | D6: 年化收益 | E6: 年化波动率 | F6: 最大回撤 | G6: 夏普比率
B7: =LOOKUP(2,1/('组合净值（模拟）'!$B$6:$B$60<>""),'组合净值（模拟）'!$B$6:$B$60) -> 1.0020308 | C7: =(LOOKUP(2,1/('组合净值（模拟）'!$B$6:$B$60<>""),'组合净值（模拟）'!$B$6:$B$60))/'组合净值（模拟）'!$B$6-1 -> 0.0020307881 | D7: =(LOOKUP(2,1/('组合净值（模拟）'!$B$6:$B$60<>""),'组合净值（模拟）'!$B$6:$B$60)/'组合净值（模拟）'!$B$6)^(说明!$C$17/MAX(COUNT('组合净值（模拟）'!$C$6:$C$60),1))-1 -> 0.019698513 | E7: =STDEV('组合净值（模拟）'!$C$6:$C$60)*SQRT(说明!$C$17) -> 0.047915986 | F7: =MIN('组合净值（模拟）'!$D$6:$D$60) -> -0.0099052057 | G7: =(((LOOKUP(2,1/('组合净值（模拟）'!$B$6:$B$60<>""),'组合净值（模拟）'!$B$6:$B$60)/'组合净值（模拟）'!$B$6)^(说明!$C$17/MAX(COUNT('组合净值（模拟）'!$C$6:$C$60),1))-1)-说明!$C$16)/IF((STDEV('组合净值（模拟）'!$C$6:$C$60)*SQRT(说明!$C$17))=0,"",(STDEV('组合净值（模拟）'!$C$6:$C$60)*SQRT(说明!$C$17))) -> 0.41110524
B9: 收益表现 | E9: 风险特征
B10: 区间 | C10: 累计收益 | D10: 年化收益 | E10: 指标 | G10: 数值
B11: 起始以来 | C11: =IFERROR((LOOKUP(2,1/('组合净值（模拟）'!$B$6:$B$60<>""),'组合净值（模拟）'!$B$6:$B$60))/('组合净值（模拟）'!$B$6)-1,"") -> 0.0020307881 | D11: =IFERROR((LOOKUP(2,1/('组合净值（模拟）'!$B$6:$B$60<>""),'组合净值（模拟）'!$B$6:$B$60)/('组合净值（模拟）'!$B$6))^(说明!$C$17/COUNT('组合净值（模拟）'!$C$6:$C$60))-1,"") -> 0.019698513 | E11: 最大回撤 | G11: =MIN('组合净值（模拟）'!$D$6:$D$60) -> -0.0099052057
B12: 2026YTD | C12: =IFERROR((LOOKUP(2,1/('组合净值（模拟）'!$B$6:$B$60<>""),'组合净值（模拟）'!$B$6:$B$60))/(IFERROR(LOOKUP(DATE(2026,1,1),'组合净值（模拟）'!$A$6:$A$60,'组合净值（模拟）'!$B$6:$B$60),'组合净值（模拟）'!$B$6))-1,"") -> 0.0020307881 | D12: =IFERROR((LOOKUP(2,1/('组合净值（模拟）'!$B$6:$B$60<>""),'组合净值（模拟）'!$B$6:$B$60)/(IFERROR(LOOKUP(DATE(2026,1,1),'组合净值（模拟）'!$A$6:$A$60,'组合净值（模拟）'!$B$6:$B$60),'组合净值（模拟）'!$B$6)))^(说明!$C$17/MAX(COUNTIF('组合净值（模拟）'!$A$6:$A$60,">="&(DATE(2026,1,1))),1))-1,"") -> 0.018962066 | E12: 回撤修复天数(未创新高) | G12: =IFERROR((LOOKUP(2,1/('组合净值（模拟）'!$B$6:$B$60<>""),ROW('组合净值（模拟）'!$B$6:$B$60)))-(LOOKUP(2,1/('组合净值（模拟）'!$D$6:$D$60=0),ROW('组合净值（模拟）'!$D$6:$D$60))),"") -> 5
B13: 近3个月 | C13: =IFERROR((LOOKUP(2,1/('组合净值（模拟）'!$B$6:$B$60<>""),'组合净值（模拟）'!$B$6:$B$60))/(IFERROR(LOOKUP(EDATE(LOOKUP(2,1/('组合净值（模拟）'!$B$6:$B$60<>""),'组合净值（模拟）'!$A$6:$A$60),-3),'组合净值（模拟）'!$A$6:$A$60,'组合净值（模拟）'!$B$6:$B$60),'组合净值（模拟）'!$B$6))-1,"") -> 0.0020307881 | D13: =IFERROR((LOOKUP(2,1/('组合净值（模拟）'!$B$6:$B$60<>""),'组合净值（模拟）'!$B$6:$B$60)/(IFERROR(LOOKUP(EDATE(LOOKUP(2,1/('组合净值（模拟）'!$B$6:$B$60<>""),'组合净值（模拟）'!$A$6:$A$60),-3),'组合净值（模拟）'!$A$6:$A$60,'组合净值（模拟）'!$B$6:$B$60),'组合净值（模拟）'!$B$6)))^(说明!$C$17/MAX(COUNTIF('组合净值（模拟）'!$A$6:$A$60,">="&(EDATE(LOOKUP(2,1/('组合净值（模拟）'!$B$6:$B$60<>""),'组合净值（模拟）'!$A$6:$A$60),-3))),1))-1,"") -> 0.018962066 | E13: 正收益占比 | G13: =COUNTIF('组合净值（模拟）'!$C$6:$C$60,">0")/MAX(COUNT('组合净值（模拟）'!$C$6:$C$60),1) -> 0.57692308
B14: 近6个月 | C14: =IFERROR((LOOKUP(2,1/('组合净值（模拟）'!$B$6:$B$60<>""),'组合净值（模拟）'!$B$6:$B$60))/(IFERROR(LOOKUP(EDATE(LOOKUP(2,1/('组合净值（模拟）'!$B$6:$B$60<>""),'组合净值（模拟）'!$A$6:$A$60),-6),'组合净值（模拟）'!$A$6:$A$60,'组合净值（模拟）'!$B$6:$B$60),'组合净值（模拟）'!$B$6))-1,"") -> 0.0020307881 | D14: =IFERROR((LOOKUP(2,1/('组合净值（模拟）'!$B$6:$B$60<>""),'组合净值（模拟）'!$B$6:$B$60)/(IFERROR(LOOKUP(EDATE(LOOKUP(2,1/('组合净值（模拟）'!$B$6:$B$60<>""),'组合净值（模拟）'!$A$6:$A$60),-6),'组合净值（模拟）'!$A$6:$A$60,'组合净值（模拟）'!$B$6:$B$60),'组合净值（模拟）'!$B$6)))^(说明!$C$17/MAX(COUNTIF('组合净值（模拟）'!$A$6:$A$60,">="&(EDATE(LOOKUP(2,1/('组合净值（模拟）'!$B$6:$B$60<>""),'组合净值（模拟）'!$A$6:$A$60),-6))),1))-1,"") -> 0.018962066 | E14: 年化波动率 | G14: =STDEV('组合净值（模拟）'!$C$6:$C$60)*SQRT(说明!$C$17) -> 0.047915986
B15: 近1年 | C15: =IFERROR((LOOKUP(2,1/('组合净值（模拟）'!$B$6:$B$60<>""),'组合净值（模拟）'!$B$6:$B$60))/(IFERROR(LOOKUP(EDATE(LOOKUP(2,1/('组合净值（模拟）'!$B$6:$B$60<>""),'组合净值（模拟）'!$A$6:$A$60),-12),'组合净值（模拟）'!$A$6:$A$60,'组合净值（模拟）'!$B$6:$B$60),'组合净值（模拟）'!$B$6))-1,"") -> 0.0020307881 | D15: =IFERROR((LOOKUP(2,1/('组合净值（模拟）'!$B$6:$B$60<>""),'组合净值（模拟）'!$B$6:$B$60)/(IFERROR(LOOKUP(EDATE(LOOKUP(2,1/('组合净值（模拟）'!$B$6:$B$60<>""),'组合净值（模拟）'!$A$6:$A$60),-12),'组合净值（模拟）'!$A$6:$A$60,'组合净值（模拟）'!$B$6:$B$60),'组合净值（模拟）'!$B$6)))^(说明!$C$17/MAX(COUNTIF('组合净值（模拟）'!$A$6:$A$60,">="&(EDATE(LOOKUP(2,1/('组合净值（模拟）'!$B$6:$B$60<>""),'组合净值（模拟）'!$A$6:$A$60),-12))),1))-1,"") -> 0.018962066 | E15: 夏普比率 | G15: =(((LOOKUP(2,1/('组合净值（模拟）'!$B$6:$B$60<>""),'组合净值（模拟）'!$B$6:$B$60)/'组合净值（模拟）'!$B$6)^(说明!$C$17/MAX(COUNT('组合净值（模拟）'!$C$6:$C$60),1))-1)-说明!$C$16)/IF((STDEV('组合净值（模拟）'!$C$6:$C$60)*SQRT(说明!$C$17))=0,"",(STDEV('组合净值（模拟）'!$C$6:$C$60)*SQRT(说明!$C$17))) -> 0.41110524
E16: 卡玛比率 | G16: =IFERROR(((LOOKUP(2,1/('组合净值（模拟）'!$B$6:$B$60<>""),'组合净值（模拟）'!$B$6:$B$60)/'组合净值（模拟）'!$B$6)^(说明!$C$17/MAX(COUNT('组合净值（模拟）'!$C$6:$C$60),1))-1)/ABS(MIN('组合净值（模拟）'!$D$6:$D$60)),"") -> 1.9887031
B18: 产品运作情况 · 组合净值曲线
B35: 统计区间自2026/6/1起；运作初期样本少，年化类指标仅供参考。新增交易日后请同步扩展本图数据区。

Sheet 看板-20-80
B2: 样板间组合走势看板（20-80 账户）
B3: ="买入持有 · 已扣年化费率 "&TEXT(持仓配置!$M$5,"0.0%")&"（折每日计入净值）" -> 买入持有 · 已扣年化费率 1.0%（折每日计入净值） | E3: ="净值日期："&TEXT(LOOKUP(2,1/('组合净值（模拟）'!$E$6:$E$60<>""),'组合净值（模拟）'!$A$6:$A$60),"yyyy-mm-dd") -> 净值日期：2026-07-07
B5: 产品业绩表现（历史表现不代表未来收益承诺）
B6: 最新净值 | C6: 累计收益 | D6: 年化收益 | E6: 年化波动率 | F6: 最大回撤 | G6: 夏普比率
B7: =LOOKUP(2,1/('组合净值（模拟）'!$E$6:$E$60<>""),'组合净值（模拟）'!$E$6:$E$60) -> 1.0072335 | C7: =(LOOKUP(2,1/('组合净值（模拟）'!$E$6:$E$60<>""),'组合净值（模拟）'!$E$6:$E$60))/'组合净值（模拟）'!$E$6-1 -> 0.0072335195 | D7: =(LOOKUP(2,1/('组合净值（模拟）'!$E$6:$E$60<>""),'组合净值（模拟）'!$E$6:$E$60)/'组合净值（模拟）'!$E$6)^(说明!$C$17/MAX(COUNT('组合净值（模拟）'!$F$6:$F$60),1))-1 -> 0.071760606 | E7: =STDEV('组合净值（模拟）'!$F$6:$F$60)*SQRT(说明!$C$17) -> 0.089212863 | F7: =MIN('组合净值（模拟）'!$G$6:$G$60) -> -0.020212972 | G7: =(((LOOKUP(2,1/('组合净值（模拟）'!$E$6:$E$60<>""),'组合净值（模拟）'!$E$6:$E$60)/'组合净值（模拟）'!$E$6)^(说明!$C$17/MAX(COUNT('组合净值（模拟）'!$F$6:$F$60),1))-1)-说明!$C$16)/IF((STDEV('组合净值（模拟）'!$F$6:$F$60)*SQRT(说明!$C$17))=0,"",(STDEV('组合净值（模拟）'!$F$6:$F$60)*SQRT(说明!$C$17))) -> 0.8043751
B9: 收益表现 | E9: 风险特征
B10: 区间 | C10: 累计收益 | D10: 年化收益 | E10: 指标 | G10: 数值
B11: 起始以来 | C11: =IFERROR((LOOKUP(2,1/('组合净值（模拟）'!$E$6:$E$60<>""),'组合净值（模拟）'!$E$6:$E$60))/('组合净值（模拟）'!$E$6)-1,"") -> 0.0072335195 | D11: =IFERROR((LOOKUP(2,1/('组合净值（模拟）'!$E$6:$E$60<>""),'组合净值（模拟）'!$E$6:$E$60)/('组合净值（模拟）'!$E$6))^(说明!$C$17/COUNT('组合净值（模拟）'!$F$6:$F$60))-1,"") -> 0.071760606 | E11: 最大回撤 | G11: =MIN('组合净值（模拟）'!$G$6:$G$60) -> -0.020212972
B12: 2026YTD | C12: =IFERROR((LOOKUP(2,1/('组合净值（模拟）'!$E$6:$E$60<>""),'组合净值（模拟）'!$E$6:$E$60))/(IFERROR(LOOKUP(DATE(2026,1,1),'组合净值（模拟）'!$A$6:$A$60,'组合净值（模拟）'!$E$6:$E$60),'组合净值（模拟）'!$E$6))-1,"") -> 0.0072335195 | D12: =IFERROR((LOOKUP(2,1/('组合净值（模拟）'!$E$6:$E$60<>""),'组合净值（模拟）'!$E$6:$E$60)/(IFERROR(LOOKUP(DATE(2026,1,1),'组合净值（模拟）'!$A$6:$A$60,'组合净值（模拟）'!$E$6:$E$60),'组合净值（模拟）'!$E$6)))^(说明!$C$17/MAX(COUNTIF('组合净值（模拟）'!$A$6:$A$60,">="&(DATE(2026,1,1))),1))-1,"") -> 0.069013173 | E12: 回撤修复天数(未创新高) | G12: =IFERROR((LOOKUP(2,1/('组合净值（模拟）'!$E$6:$E$60<>""),ROW('组合净值（模拟）'!$E$6:$E$60)))-(LOOKUP(2,1/('组合净值（模拟）'!$G$6:$G$60=0),ROW('组合净值（模拟）'!$G$6:$G$60))),"") -> 5
B13: 近3个月 | C13: =IFERROR((LOOKUP(2,1/('组合净值（模拟）'!$E$6:$E$60<>""),'组合净值（模拟）'!$E$6:$E$60))/(IFERROR(LOOKUP(EDATE(LOOKUP(2,1/('组合净值（模拟）'!$E$6:$E$60<>""),'组合净值（模拟）'!$A$6:$A$60),-3),'组合净值（模拟）'!$A$6:$A$60,'组合净值（模拟）'!$E$6:$E$60),'组合净值（模拟）'!$E$6))-1,"") -> 0.0072335195 | D13: =IFERROR((LOOKUP(2,1/('组合净值（模拟）'!$E$6:$E$60<>""),'组合净值（模拟）'!$E$6:$E$60)/(IFERROR(LOOKUP(EDATE(LOOKUP(2,1/('组合净值（模拟）'!$E$6:$E$60<>""),'组合净值（模拟）'!$A$6:$A$60),-3),'组合净值（模拟）'!$A$6:$A$60,'组合净值（模拟）'!$E$6:$E$60),'组合净值（模拟）'!$E$6)))^(说明!$C$17/MAX(COUNTIF('组合净值（模拟）'!$A$6:$A$60,">="&(EDATE(LOOKUP(2,1/('组合净值（模拟）'!$E$6:$E$60<>""),'组合净值（模拟）'!$A$6:$A$60),-3))),1))-1,"") -> 0.069013173 | E13: 正收益占比 | G13: =COUNTIF('组合净值（模拟）'!$F$6:$F$60,">0")/MAX(COUNT('组合净值（模拟）'!$F$6:$F$60),1) -> 0.57692308
B14: 近6个月 | C14: =IFERROR((LOOKUP(2,1/('组合净值（模拟）'!$E$6:$E$60<>""),'组合净值（模拟）'!$E$6:$E$60))/(IFERROR(LOOKUP(EDATE(LOOKUP(2,1/('组合净值（模拟）'!$E$6:$E$60<>""),'组合净值（模拟）'!$A$6:$A$60),-6),'组合净值（模拟）'!$A$6:$A$60,'组合净值（模拟）'!$E$6:$E$60),'组合净值（模拟）'!$E$6))-1,"") -> 0.0072335195 | D14: =IFERROR((LOOKUP(2,1/('组合净值（模拟）'!$E$6:$E$60<>""),'组合净值（模拟）'!$E$6:$E$60)/(IFERROR(LOOKUP(EDATE(LOOKUP(2,1/('组合净值（模拟）'!$E$6:$E$60<>""),'组合净值（模拟）'!$A$6:$A$60),-6),'组合净值（模拟）'!$A$6:$A$60,'组合净值（模拟）'!$E$6:$E$60),'组合净值（模拟）'!$E$6)))^(说明!$C$17/MAX(COUNTIF('组合净值（模拟）'!$A$6:$A$60,">="&(EDATE(LOOKUP(2,1/('组合净值（模拟）'!$E$6:$E$60<>""),'组合净值（模拟）'!$A$6:$A$60),-6))),1))-1,"") -> 0.069013173 | E14: 年化波动率 | G14: =STDEV('组合净值（模拟）'!$F$6:$F$60)*SQRT(说明!$C$17) -> 0.089212863
B15: 近1年 | C15: =IFERROR((LOOKUP(2,1/('组合净值（模拟）'!$E$6:$E$60<>""),'组合净值（模拟）'!$E$6:$E$60))/(IFERROR(LOOKUP(EDATE(LOOKUP(2,1/('组合净值（模拟）'!$E$6:$E$60<>""),'组合净值（模拟）'!$A$6:$A$60),-12),'组合净值（模拟）'!$A$6:$A$60,'组合净值（模拟）'!$E$6:$E$60),'组合净值（模拟）'!$E$6))-1,"") -> 0.0072335195 | D15: =IFERROR((LOOKUP(2,1/('组合净值（模拟）'!$E$6:$E$60<>""),'组合净值（模拟）'!$E$6:$E$60)/(IFERROR(LOOKUP(EDATE(LOOKUP(2,1/('组合净值（模拟）'!$E$6:$E$60<>""),'组合净值（模拟）'!$A$6:$A$60),-12),'组合净值（模拟）'!$A$6:$A$60,'组合净值（模拟）'!$E$6:$E$60),'组合净值（模拟）'!$E$6)))^(说明!$C$17/MAX(COUNTIF('组合净值（模拟）'!$A$6:$A$60,">="&(EDATE(LOOKUP(2,1/('组合净值（模拟）'!$E$6:$E$60<>""),'组合净值（模拟）'!$A$6:$A$60),-12))),1))-1,"") -> 0.069013173 | E15: 夏普比率 | G15: =(((LOOKUP(2,1/('组合净值（模拟）'!$E$6:$E$60<>""),'组合净值（模拟）'!$E$6:$E$60)/'组合净值（模拟）'!$E$6)^(说明!$C$17/MAX(COUNT('组合净值（模拟）'!$F$6:$F$60),1))-1)-说明!$C$16)/IF((STDEV('组合净值（模拟）'!$F$6:$F$60)*SQRT(说明!$C$17))=0,"",(STDEV('组合净值（模拟）'!$F$6:$F$60)*SQRT(说明!$C$17))) -> 0.8043751
E16: 卡玛比率 | G16: =IFERROR(((LOOKUP(2,1/('组合净值（模拟）'!$E$6:$E$60<>""),'组合净值（模拟）'!$E$6:$E$60)/'组合净值（模拟）'!$E$6)^(说明!$C$17/MAX(COUNT('组合净值（模拟）'!$F$6:$F$60),1))-1)/ABS(MIN('组合净值（模拟）'!$G$6:$G$60)),"") -> 3.5502254
B18: 产品运作情况 · 组合净值曲线
B35: 统计区间自2026/6/1起；运作初期样本少，年化类指标仅供参考。新增交易日后请同步扩展本图数据区。

Sheet 看板-30-70
B2: 样板间组合走势看板（30-70 账户）
B3: ="买入持有 · 已扣年化费率 "&TEXT(持仓配置!$M$6,"0.0%")&"（折每日计入净值）" -> 买入持有 · 已扣年化费率 1.5%（折每日计入净值） | E3: ="净值日期："&TEXT(LOOKUP(2,1/('组合净值（模拟）'!$H$6:$H$60<>""),'组合净值（模拟）'!$A$6:$A$60),"yyyy-mm-dd") -> 净值日期：2026-07-07
B5: 产品业绩表现（历史表现不代表未来收益承诺）
B6: 最新净值 | C6: 累计收益 | D6: 年化收益 | E6: 年化波动率 | F6: 最大回撤 | G6: 夏普比率
B7: =LOOKUP(2,1/('组合净值（模拟）'!$H$6:$H$60<>""),'组合净值（模拟）'!$H$6:$H$60) -> 1.008503 | C7: =(LOOKUP(2,1/('组合净值（模拟）'!$H$6:$H$60<>""),'组合净值（模拟）'!$H$6:$H$60))/'组合净值（模拟）'!$H$6-1 -> 0.0085030425 | D7: =(LOOKUP(2,1/('组合净值（模拟）'!$H$6:$H$60<>""),'组合净值（模拟）'!$H$6:$H$60)/'组合净值（模拟）'!$H$6)^(说明!$C$17/MAX(COUNT('组合净值（模拟）'!$I$6:$I$60),1))-1 -> 0.084820328 | E7: =STDEV('组合净值（模拟）'!$I$6:$I$60)*SQRT(说明!$C$17) -> 0.13425548 | F7: =MIN('组合净值（模拟）'!$J$6:$J$60) -> -0.029241828 | G7: =(((LOOKUP(2,1/('组合净值（模拟）'!$H$6:$H$60<>""),'组合净值（模拟）'!$H$6:$H$60)/'组合净值（模拟）'!$H$6)^(说明!$C$17/MAX(COUNT('组合净值（模拟）'!$I$6:$I$60),1))-1)-说明!$C$16)/IF((STDEV('组合净值（模拟）'!$I$6:$I$60)*SQRT(说明!$C$17))=0,"",(STDEV('组合净值（模拟）'!$I$6:$I$60)*SQRT(说明!$C$17))) -> 0.631783
B9: 收益表现 | E9: 风险特征
B10: 区间 | C10: 累计收益 | D10: 年化收益 | E10: 指标 | G10: 数值
B11: 起始以来 | C11: =IFERROR((LOOKUP(2,1/('组合净值（模拟）'!$H$6:$H$60<>""),'组合净值（模拟）'!$H$6:$H$60))/('组合净值（模拟）'!$H$6)-1,"") -> 0.0085030425 | D11: =IFERROR((LOOKUP(2,1/('组合净值（模拟）'!$H$6:$H$60<>""),'组合净值（模拟）'!$H$6:$H$60)/('组合净值（模拟）'!$H$6))^(说明!$C$17/COUNT('组合净值（模拟）'!$I$6:$I$60))-1,"") -> 0.084820328 | E11: 最大回撤 | G11: =MIN('组合净值（模拟）'!$J$6:$J$60) -> -0.029241828
B12: 2026YTD | C12: =IFERROR((LOOKUP(2,1/('组合净值（模拟）'!$H$6:$H$60<>""),'组合净值（模拟）'!$H$6:$H$60))/(IFERROR(LOOKUP(DATE(2026,1,1),'组合净值（模拟）'!$A$6:$A$60,'组合净值（模拟）'!$H$6:$H$60),'组合净值（模拟）'!$H$6))-1,"") -> 0.0085030425 | D12: =IFERROR((LOOKUP(2,1/('组合净值（模拟）'!$H$6:$H$60<>""),'组合净值（模拟）'!$H$6:$H$60)/(IFERROR(LOOKUP(DATE(2026,1,1),'组合净值（模拟）'!$A$6:$A$60,'组合净值（模拟）'!$H$6:$H$60),'组合净值（模拟）'!$H$6)))^(说明!$C$17/MAX(COUNTIF('组合净值（模拟）'!$A$6:$A$60,">="&(DATE(2026,1,1))),1))-1,"") -> 0.081554145 | E12: 回撤修复天数(未创新高) | G12: =IFERROR((LOOKUP(2,1/('组合净值（模拟）'!$H$6:$H$60<>""),ROW('组合净值（模拟）'!$H$6:$H$60)))-(LOOKUP(2,1/('组合净值（模拟）'!$J$6:$J$60=0),ROW('组合净值（模拟）'!$J$6:$J$60))),"") -> 5
B13: 近3个月 | C13: =IFERROR((LOOKUP(2,1/('组合净值（模拟）'!$H$6:$H$60<>""),'组合净值（模拟）'!$H$6:$H$60))/(IFERROR(LOOKUP(EDATE(LOOKUP(2,1/('组合净值（模拟）'!$H$6:$H$60<>""),'组合净值（模拟）'!$A$6:$A$60),-3),'组合净值（模拟）'!$A$6:$A$60,'组合净值（模拟）'!$H$6:$H$60),'组合净值（模拟）'!$H$6))-1,"") -> 0.0085030425 | D13: =IFERROR((LOOKUP(2,1/('组合净值（模拟）'!$H$6:$H$60<>""),'组合净值（模拟）'!$H$6:$H$60)/(IFERROR(LOOKUP(EDATE(LOOKUP(2,1/('组合净值（模拟）'!$H$6:$H$60<>""),'组合净值（模拟）'!$A$6:$A$60),-3),'组合净值（模拟）'!$A$6:$A$60,'组合净值（模拟）'!$H$6:$H$60),'组合净值（模拟）'!$H$6)))^(说明!$C$17/MAX(COUNTIF('组合净值（模拟）'!$A$6:$A$60,">="&(EDATE(LOOKUP(2,1/('组合净值（模拟）'!$H$6:$H$60<>""),'组合净值（模拟）'!$A$6:$A$60),-3))),1))-1,"") -> 0.081554145 | E13: 正收益占比 | G13: =COUNTIF('组合净值（模拟）'!$I$6:$I$60,">0")/MAX(COUNT('组合净值（模拟）'!$I$6:$I$60),1) -> 0.57692308
B14: 近6个月 | C14: =IFERROR((LOOKUP(2,1/('组合净值（模拟）'!$H$6:$H$60<>""),'组合净值（模拟）'!$H$6:$H$60))/(IFERROR(LOOKUP(EDATE(LOOKUP(2,1/('组合净值（模拟）'!$H$6:$H$60<>""),'组合净值（模拟）'!$A$6:$A$60),-6),'组合净值（模拟）'!$A$6:$A$60,'组合净值（模拟）'!$H$6:$H$60),'组合净值（模拟）'!$H$6))-1,"") -> 0.0085030425 | D14: =IFERROR((LOOKUP(2,1/('组合净值（模拟）'!$H$6:$H$60<>""),'组合净值（模拟）'!$H$6:$H$60)/(IFERROR(LOOKUP(EDATE(LOOKUP(2,1/('组合净值（模拟）'!$H$6:$H$60<>""),'组合净值（模拟）'!$A$6:$A$60),-6),'组合净值（模拟）'!$A$6:$A$60,'组合净值（模拟）'!$H$6:$H$60),'组合净值（模拟）'!$H$6)))^(说明!$C$17/MAX(COUNTIF('组合净值（模拟）'!$A$6:$A$60,">="&(EDATE(LOOKUP(2,1/('组合净值（模拟）'!$H$6:$H$60<>""),'组合净值（模拟）'!$A$6:$A$60),-6))),1))-1,"") -> 0.081554145 | E14: 年化波动率 | G14: =STDEV('组合净值（模拟）'!$I$6:$I$60)*SQRT(说明!$C$17) -> 0.13425548
B15: 近1年 | C15: =IFERROR((LOOKUP(2,1/('组合净值（模拟）'!$H$6:$H$60<>""),'组合净值（模拟）'!$H$6:$H$60))/(IFERROR(LOOKUP(EDATE(LOOKUP(2,1/('组合净值（模拟）'!$H$6:$H$60<>""),'组合净值（模拟）'!$A$6:$A$60),-12),'组合净值（模拟）'!$A$6:$A$60,'组合净值（模拟）'!$H$6:$H$60),'组合净值（模拟）'!$H$6))-1,"") -> 0.0085030425 | D15: =IFERROR((LOOKUP(2,1/('组合净值（模拟）'!$H$6:$H$60<>""),'组合净值（模拟）'!$H$6:$H$60)/(IFERROR(LOOKUP(EDATE(LOOKUP(2,1/('组合净值（模拟）'!$H$6:$H$60<>""),'组合净值（模拟）'!$A$6:$A$60),-12),'组合净值（模拟）'!$A$6:$A$60,'组合净值（模拟）'!$H$6:$H$60),'组合净值（模拟）'!$H$6)))^(说明!$C$17/MAX(COUNTIF('组合净值（模拟）'!$A$6:$A$60,">="&(EDATE(LOOKUP(2,1/('组合净值（模拟）'!$H$6:$H$60<>""),'组合净值（模拟）'!$A$6:$A$60),-12))),1))-1,"") -> 0.081554145 | E15: 夏普比率 | G15: =(((LOOKUP(2,1/('组合净值（模拟）'!$H$6:$H$60<>""),'组合净值（模拟）'!$H$6:$H$60)/'组合净值（模拟）'!$H$6)^(说明!$C$17/MAX(COUNT('组合净值（模拟）'!$I$6:$I$60),1))-1)-说明!$C$16)/IF((STDEV('组合净值（模拟）'!$I$6:$I$60)*SQRT(说明!$C$17))=0,"",(STDEV('组合净值（模拟）'!$I$6:$I$60)*SQRT(说明!$C$17))) -> 0.631783
E16: 卡玛比率 | G16: =IFERROR(((LOOKUP(2,1/('组合净值（模拟）'!$H$6:$H$60<>""),'组合净值（模拟）'!$H$6:$H$60)/'组合净值（模拟）'!$H$6)^(说明!$C$17/MAX(COUNT('组合净值（模拟）'!$I$6:$I$60),1))-1)/ABS(MIN('组合净值（模拟）'!$J$6:$J$60)),"") -> 2.9006507
B18: 产品运作情况 · 组合净值曲线
B35: 统计区间自2026/6/1起；运作初期样本少，年化类指标仅供参考。新增交易日后请同步扩展本图数据区。

Sheet 看板-增值
B2: 样板间组合走势看板（增值组合）
B3: ="买入持有 · 已扣年化费率 "&TEXT(持仓配置!$M$7,"0.0%")&"（折每日计入净值）" -> 买入持有 · 已扣年化费率 11.0%（折每日计入净值） | E3: ="净值日期："&TEXT(LOOKUP(2,1/('组合净值（模拟）'!$K$6:$K$60<>""),'组合净值（模拟）'!$A$6:$A$60),"yyyy-mm-dd") -> 净值日期：2026-07-07
B5: 产品业绩表现（历史表现不代表未来收益承诺）
B6: 最新净值 | C6: 累计收益 | D6: 年化收益 | E6: 年化波动率 | F6: 最大回撤 | G6: 夏普比率
B7: =LOOKUP(2,1/('组合净值（模拟）'!$K$6:$K$60<>""),'组合净值（模拟）'!$K$6:$K$60) -> 1.1168983 | C7: =(LOOKUP(2,1/('组合净值（模拟）'!$K$6:$K$60<>""),'组合净值（模拟）'!$K$6:$K$60))/'组合净值（模拟）'!$K$6-1 -> 0.11689827 | D7: =(LOOKUP(2,1/('组合净值（模拟）'!$K$6:$K$60<>""),'组合净值（模拟）'!$K$6:$K$60)/'组合净值（模拟）'!$K$6)^(说明!$C$17/MAX(COUNT('组合净值（模拟）'!$L$6:$L$60),1))-1 -> 1.895139 | E7: =STDEV('组合净值（模拟）'!$L$6:$L$60)*SQRT(说明!$C$17) -> 0.5825531 | F7: =MIN('组合净值（模拟）'!$M$6:$M$60) -> -0.13986761 | G7: =(((LOOKUP(2,1/('组合净值（模拟）'!$K$6:$K$60<>""),'组合净值（模拟）'!$K$6:$K$60)/'组合净值（模拟）'!$K$6)^(说明!$C$17/MAX(COUNT('组合净值（模拟）'!$L$6:$L$60),1))-1)-说明!$C$16)/IF((STDEV('组合净值（模拟）'!$L$6:$L$60)*SQRT(说明!$C$17))=0,"",(STDEV('组合净值（模拟）'!$L$6:$L$60)*SQRT(说明!$C$17))) -> 3.2531609
B9: 收益表现 | E9: 风险特征
B10: 区间 | C10: 累计收益 | D10: 年化收益 | E10: 指标 | G10: 数值
B11: 起始以来 | C11: =IFERROR((LOOKUP(2,1/('组合净值（模拟）'!$K$6:$K$60<>""),'组合净值（模拟）'!$K$6:$K$60))/('组合净值（模拟）'!$K$6)-1,"") -> 0.11689827 | D11: =IFERROR((LOOKUP(2,1/('组合净值（模拟）'!$K$6:$K$60<>""),'组合净值（模拟）'!$K$6:$K$60)/('组合净值（模拟）'!$K$6))^(说明!$C$17/COUNT('组合净值（模拟）'!$L$6:$L$60))-1,"") -> 1.895139 | E11: 最大回撤 | G11: =MIN('组合净值（模拟）'!$M$6:$M$60) -> -0.13986761
B12: 2026YTD | C12: =IFERROR((LOOKUP(2,1/('组合净值（模拟）'!$K$6:$K$60<>""),'组合净值（模拟）'!$K$6:$K$60))/(IFERROR(LOOKUP(DATE(2026,1,1),'组合净值（模拟）'!$A$6:$A$60,'组合净值（模拟）'!$K$6:$K$60),'组合净值（模拟）'!$K$6))-1,"") -> 0.11689827 | D12: =IFERROR((LOOKUP(2,1/('组合净值（模拟）'!$K$6:$K$60<>""),'组合净值（模拟）'!$K$6:$K$60)/(IFERROR(LOOKUP(DATE(2026,1,1),'组合净值（模拟）'!$A$6:$A$60,'组合净值（模拟）'!$K$6:$K$60),'组合净值（模拟）'!$K$6)))^(说明!$C$17/MAX(COUNTIF('组合净值（模拟）'!$A$6:$A$60,">="&(DATE(2026,1,1))),1))-1,"") -> 1.7833675 | E12: 回撤修复天数(未创新高) | G12: =IFERROR((LOOKUP(2,1/('组合净值（模拟）'!$K$6:$K$60<>""),ROW('组合净值（模拟）'!$K$6:$K$60)))-(LOOKUP(2,1/('组合净值（模拟）'!$M$6:$M$60=0),ROW('组合净值（模拟）'!$M$6:$M$60))),"") -> 5
B13: 近3个月 | C13: =IFERROR((LOOKUP(2,1/('组合净值（模拟）'!$K$6:$K$60<>""),'组合净值（模拟）'!$K$6:$K$60))/(IFERROR(LOOKUP(EDATE(LOOKUP(2,1/('组合净值（模拟）'!$K$6:$K$60<>""),'组合净值（模拟）'!$A$6:$A$60),-3),'组合净值（模拟）'!$A$6:$A$60,'组合净值（模拟）'!$K$6:$K$60),'组合净值（模拟）'!$K$6))-1,"") -> 0.11689827 | D13: =IFERROR((LOOKUP(2,1/('组合净值（模拟）'!$K$6:$K$60<>""),'组合净值（模拟）'!$K$6:$K$60)/(IFERROR(LOOKUP(EDATE(LOOKUP(2,1/('组合净值（模拟）'!$K$6:$K$60<>""),'组合净值（模拟）'!$A$6:$A$60),-3),'组合净值（模拟）'!$A$6:$A$60,'组合净值（模拟）'!$K$6:$K$60),'组合净值（模拟）'!$K$6)))^(说明!$C$17/MAX(COUNTIF('组合净值（模拟）'!$A$6:$A$60,">="&(EDATE(LOOKUP(2,1/('组合净值（模拟）'!$K$6:$K$60<>""),'组合净值（模拟）'!$A$6:$A$60),-3))),1))-1,"") -> 1.7833675 | E13: 正收益占比 | G13: =COUNTIF('组合净值（模拟）'!$L$6:$L$60,">0")/MAX(COUNT('组合净值（模拟）'!$L$6:$L$60),1) -> 0.57692308
B14: 近6个月 | C14: =IFERROR((LOOKUP(2,1/('组合净值（模拟）'!$K$6:$K$60<>""),'组合净值（模拟）'!$K$6:$K$60))/(IFERROR(LOOKUP(EDATE(LOOKUP(2,1/('组合净值（模拟）'!$K$6:$K$60<>""),'组合净值（模拟）'!$A$6:$A$60),-6),'组合净值（模拟）'!$A$6:$A$60,'组合净值（模拟）'!$K$6:$K$60),'组合净值（模拟）'!$K$6))-1,"") -> 0.11689827 | D14: =IFERROR((LOOKUP(2,1/('组合净值（模拟）'!$K$6:$K$60<>""),'组合净值（模拟）'!$K$6:$K$60)/(IFERROR(LOOKUP(EDATE(LOOKUP(2,1/('组合净值（模拟）'!$K$6:$K$60<>""),'组合净值（模拟）'!$A$6:$A$60),-6),'组合净值（模拟）'!$A$6:$A$60,'组合净值（模拟）'!$K$6:$K$60),'组合净值（模拟）'!$K$6)))^(说明!$C$17/MAX(COUNTIF('组合净值（模拟）'!$A$6:$A$60,">="&(EDATE(LOOKUP(2,1/('组合净值（模拟）'!$K$6:$K$60<>""),'组合净值（模拟）'!$A$6:$A$60),-6))),1))-1,"") -> 1.7833675 | E14: 年化波动率 | G14: =STDEV('组合净值（模拟）'!$L$6:$L$60)*SQRT(说明!$C$17) -> 0.5825531
B15: 近1年 | C15: =IFERROR((LOOKUP(2,1/('组合净值（模拟）'!$K$6:$K$60<>""),'组合净值（模拟）'!$K$6:$K$60))/(IFERROR(LOOKUP(EDATE(LOOKUP(2,1/('组合净值（模拟）'!$K$6:$K$60<>""),'组合净值（模拟）'!$A$6:$A$60),-12),'组合净值（模拟）'!$A$6:$A$60,'组合净值（模拟）'!$K$6:$K$60),'组合净值（模拟）'!$K$6))-1,"") -> 0.11689827 | D15: =IFERROR((LOOKUP(2,1/('组合净值（模拟）'!$K$6:$K$60<>""),'组合净值（模拟）'!$K$6:$K$60)/(IFERROR(LOOKUP(EDATE(LOOKUP(2,1/('组合净值（模拟）'!$K$6:$K$60<>""),'组合净值（模拟）'!$A$6:$A$60),-12),'组合净值（模拟）'!$A$6:$A$60,'组合净值（模拟）'!$K$6:$K$60),'组合净值（模拟）'!$K$6)))^(说明!$C$17/MAX(COUNTIF('组合净值（模拟）'!$A$6:$A$60,">="&(EDATE(LOOKUP(2,1/('组合净值（模拟）'!$K$6:$K$60<>""),'组合净值（模拟）'!$A$6:$A$60),-12))),1))-1,"") -> 1.7833675 | E15: 夏普比率 | G15: =(((LOOKUP(2,1/('组合净值（模拟）'!$K$6:$K$60<>""),'组合净值（模拟）'!$K$6:$K$60)/'组合净值（模拟）'!$K$6)^(说明!$C$17/MAX(COUNT('组合净值（模拟）'!$L$6:$L$60),1))-1)-说明!$C$16)/IF((STDEV('组合净值（模拟）'!$L$6:$L$60)*SQRT(说明!$C$17))=0,"",(STDEV('组合净值（模拟）'!$L$6:$L$60)*SQRT(说明!$C$17))) -> 3.2531609
E16: 卡玛比率 | G16: =IFERROR(((LOOKUP(2,1/('组合净值（模拟）'!$K$6:$K$60<>""),'组合净值（模拟）'!$K$6:$K$60)/'组合净值（模拟）'!$K$6)^(说明!$C$17/MAX(COUNT('组合净值（模拟）'!$L$6:$L$60),1))-1)/ABS(MIN('组合净值（模拟）'!$M$6:$M$60)),"") -> 13.54952
B18: 产品运作情况 · 组合净值曲线
B35: 统计区间自2026/6/1起；运作初期样本少，年化类指标仅供参考。新增交易日后请同步扩展本图数据区。

Sheet 说明
B2: 样板间投顾组合 · 净值监控模板
B3: 运作起始日 2026/6/1 ｜ 净值口径：复权单位净值(iFinD) ｜ 模拟：买入持有(权重漂移)
B5: 一、模板结构
B6: 持仓配置 | C6: 四组合(10-90/20-80/30-70/增值)成份基金、代码与初始权重，可直接编辑。
B7: 净值数据(iFinD公式) | C7: 同花顺公式拉取复权单位净值
B8: 组合净值 | C8: 按买入持有逐日计算四组合净值、日收益与回撤；净值已按年化费率折每日扣费(扣费后口径)。
B9: 看板-10/20/30/增值 | C9: 业绩表现KPI＋收益表现＋风险特征＋净值曲线。增值组合为8只权益基金、无债无黄金。
B11: 二、使用说明
B12: 每日更新 | C12: 在『净值数据』『组合净值』底部按日期顺序新增一行(公式可下拉)，看板自动刷新。
B13: iFinD指标 | C13: 复权净值指标代码集中在『净值数据』B2，与本地版本不符时只改此处。
B14: 买入持有口径 | C14: 起始日按初始权重买入后持有，权重随涨跌漂移；组合起始净值=1.0000。
B15: 扣费方式 | C15: 各组合年化费率见『持仓配置』M列(10-90=0.8%/20-80=1.0%/30-70=1.2%/增值=1.0%)；按 净值×(1-费率)^(已运作交易日数/年化交易日数) 折每日计入，看板均为扣费后口径。
B16: 参数：无风险利率(年化) | C16: 0
B17: 参数：年化交易日数 | C17: 250
B18: 净值曲线 | C18: 四看板曲线已改用动态命名区域(chtDate/chtB/chtE/chtH/chtK，OFFSET+COUNT)，新增交易日后自动延伸到最新，无需手动改图表数据区。
B19: 数据来源：同花顺 iFinD(复权单位净值)

Sheet vs招行
F1: 46191 | G1: 46171 | K1: 10-90
F2: 46195 | G2: 46174 | H2: 46174 | L2: =VLOOKUP(G1,'组合净值（模拟）'!A:M,2,0) -> 1 | M2: =VLOOKUP(F1,实盘组合净值!A:S,14,0) -> 1
F3: =G3 -> 46206 | G3: 46206 | H3: =G3 -> 46206 | L3: =VLOOKUP(G3,'组合净值（模拟）'!A:M,2,0) -> 1.0038981 | M3: =VLOOKUP(F3,'1090实盘净值'!A:C,2,0) -> 0.99491237
B4: FOF | C4: 权益中枢 | D4: 列2 | E4: 组合/基金 | F4: ="上线以来（截止"&TEXT($G$3,"m.d")&"）" -> 上线以来（截止7.3） | G4: ="6月以来（截止"&TEXT($G$3,"m.d")&"）" -> 6月以来（截止7.3） | H4: 最大回撤 | I4: 年化波动率 | J4: 夏普比率 | K4: 卡玛比率
B5: 嘉实财富样板间 | C5: 0.1 | E5: 10-90账户 | F5: =M3/M2-1 -> -0.00508763 | G5: =L3/L2-1 -> 0.0038981427 | H5: ='看板-10-90'!F7 -> -0.0099052057 | I5: ='看板-10-90'!E7 -> 0.047915986 | J5: ='看板-10-90'!G7 -> 0.41110524 | K5: =IFERROR('看板-10-90'!D7/ABS('看板-10-90'!F7),"") -> 1.9887031
B6: 招行长盈计划-安稳盈 | C6: ≤15% | D6: 016768.OF | E6: =[1]!thsiFinD("ths_fund_official_short_name_fund",D6) -> 华安盈瑞稳健优选6个月持有混合(FOF)A | F6: =[1]!thsiFinD("ths_adjustment_nvg_ratio_fund",$D6,F$2,F$3,101)/100 -> -0.0024139473 | G6: =[1]!thsiFinD("ths_adjustment_nvg_ratio_fund",$D6,G$2,G$3,101)/100 -> 0.0012562814 | H6: =-[1]!thsiFinD("ths_max_retrace_rate_all_fund",$D6,$H$2,$H$3)/100 -> -0.0050179211 | I6: =[1]!thsiFinD("ths_annual_volatility_fund",D6,$H$2,$H$3,100,101)/100 -> 0.025666682 | J6: =[1]!thsiFinD("ths_sharp_fund",D6,$H$2,$H$3,100,101,100) -> 0.0076886892 | K6: =[1]!thsiFinD("ths_calmar_ratio_fund",D6,$H$2,$H$3) -> 2.7866875
D7: 025218.OF | E7: =[1]!thsiFinD("ths_fund_official_short_name_fund",D7) -> 中欧盈欣稳健6个月持有混合(FOF)A | F7: =[1]!thsiFinD("ths_adjustment_nvg_ratio_fund",$D7,F$2,F$3,101)/100 -> -0.00019972039 | G7: =[1]!thsiFinD("ths_adjustment_nvg_ratio_fund",$D7,G$2,G$3,101)/100 -> -0.0035828025 | H7: =-[1]!thsiFinD("ths_max_retrace_rate_all_fund",$D7,$H$2,$H$3)/100 -> -0.0078497615 | I7: =[1]!thsiFinD("ths_annual_volatility_fund",D7,$H$2,$H$3,100,101)/100 -> 0.020908311 | J7: =[1]!thsiFinD("ths_sharp_fund",D7,$H$2,$H$3,100,101,100) -> -0.14353007 | K7: =[1]!thsiFinD("ths_calmar_ratio_fund",D7,$H$2,$H$3) -> -4.9582961
D8: 022978.OF | E8: =[1]!thsiFinD("ths_fund_official_short_name_fund",D8) -> 博时臻选楚汇三个月持有债券(FOF)B | F8: =[1]!thsiFinD("ths_adjustment_nvg_ratio_fund",$D8,F$2,F$3,101)/100 -> -0.00044907491 | G8: =[1]!thsiFinD("ths_adjustment_nvg_ratio_fund",$D8,G$2,G$3,101)/100 -> -0.0035813412 | H8: =-[1]!thsiFinD("ths_max_retrace_rate_all_fund",$D8,$H$2,$H$3)/100 -> -0.0088440236 | I8: =[1]!thsiFinD("ths_annual_volatility_fund",D8,$H$2,$H$3,100,101)/100 -> 0.022906381 | J8: =[1]!thsiFinD("ths_sharp_fund",D8,$H$2,$H$3,100,101,100) -> -0.13085215 | K8: =[1]!thsiFinD("ths_calmar_ratio_fund",D8,$H$2,$H$3) -> -4.3991122
D9: 017587.OF | E9: =[1]!thsiFinD("ths_fund_official_short_name_fund",D9) -> 中欧盈选稳健6个月持有混合发起(FOF)A | F9: =[1]!thsiFinD("ths_adjustment_nvg_ratio_fund",$D9,F$2,F$3,101)/100 -> 0 | G9: =[1]!thsiFinD("ths_adjustment_nvg_ratio_fund",$D9,G$2,G$3,101)/100 -> -0.0034498834 | H9: =-[1]!thsiFinD("ths_max_retrace_rate_all_fund",$D9,$H$2,$H$3)/100 -> -0.0080059579 | I9: =[1]!thsiFinD("ths_annual_volatility_fund",D9,$H$2,$H$3,100,101)/100 -> 0.020915346 | J9: =[1]!thsiFinD("ths_sharp_fund",D9,$H$2,$H$3,100,101,100) -> -0.13928047 | K9: =[1]!thsiFinD("ths_calmar_ratio_fund",D9,$H$2,$H$3) -> -4.6843195
D10: 026682.OF | E10: =[1]!thsiFinD("ths_fund_official_short_name_fund",D10) -> 博时盈泰臻选6个月持有期混合(FOF)A | F10: =[1]!thsiFinD("ths_adjustment_nvg_ratio_fund",$D10,F$2,F$3,101)/100 -> 0.00019984013 | G10: =[1]!thsiFinD("ths_adjustment_nvg_ratio_fund",$D10,G$2,G$3,101)/100 -> -0.00079856259 | H10: =-[1]!thsiFinD("ths_max_retrace_rate_all_fund",$D10,$H$2,$H$3)/100 -> -0.0062786526 | I10: =[1]!thsiFinD("ths_annual_volatility_fund",D10,$H$2,$H$3,100,101)/100 -> 0.018430341 | J10: =[1]!thsiFinD("ths_sharp_fund",D10,$H$2,$H$3,100,101,100) -> -0.063253701 | K10: =[1]!thsiFinD("ths_calmar_ratio_fund",D10,$H$2,$H$3) -> -1.4011272
B11: 招行长盈计划-安定盈 | C11: ≤25% | D11: 025822.OF | E11: =[1]!thsiFinD("ths_fund_official_short_name_fund",D11) -> 易方达如意盈安6个月持有混合发起式(FOF)A | F11: =[1]!thsiFinD("ths_adjustment_nvg_ratio_fund",$D11,F$2,F$3,101)/100 -> -0.0021541173 | G11: =[1]!thsiFinD("ths_adjustment_nvg_ratio_fund",$D11,G$2,G$3,101)/100 -> 0.001966375 | H11: =-[1]!thsiFinD("ths_max_retrace_rate_all_fund",$D11,$H$2,$H$3)/100 -> -0.010990089 | I11: =[1]!thsiFinD("ths_annual_volatility_fund",D11,$H$2,$H$3,100,101)/100 -> 0.055677162 | J11: =[1]!thsiFinD("ths_sharp_fund",D11,$H$2,$H$3,100,101,100) -> 0.013263802 | K11: =[1]!thsiFinD("ths_calmar_ratio_fund",D11,$H$2,$H$3) -> 1.9986839
D12: 018312.OF | E12: =[1]!thsiFinD("ths_fund_official_short_name_fund",D12) -> 易方达如意安诚六个月持有混合(FOF)A | F12: =[1]!thsiFinD("ths_adjustment_nvg_ratio_fund",$D12,F$2,F$3,101)/100 -> -0.0021763733 | G12: =[1]!thsiFinD("ths_adjustment_nvg_ratio_fund",$D12,G$2,G$3,101)/100 -> 0.00096061479 | H12: =-[1]!thsiFinD("ths_max_retrace_rate_all_fund",$D12,$H$2,$H$3)/100 -> -0.011072363 | I12: =[1]!thsiFinD("ths_annual_volatility_fund",D12,$H$2,$H$3,100,101)/100 -> 0.053773814 | J12: =[1]!thsiFinD("ths_sharp_fund",D12,$H$2,$H$3,100,101,100) -> 0.0013111096 | K12: =[1]!thsiFinD("ths_calmar_ratio_fund",D12,$H$2,$H$3) -> 0.96424523

Sheet vs固收+
F1: =vs招行!F1 -> 46191 | G1: =vs招行!G1 -> 46171
C2: 2026-03-31 | F2: =vs招行!F2 -> 46195 | G2: =vs招行!G2 -> 46174 | H2: =vs招行!H2 -> 46174 | M2: =VLOOKUP(G1,'组合净值（模拟）'!A:M,2,0) -> 1 | N2: 1
F3: =G3 -> 46210 | G3: 46210 | H3: =G3 -> 46210 | M3: =VLOOKUP(G3,'组合净值（模拟）'!A:M,2,0) -> 1.0020308 | N3: =VLOOKUP(H3,'1090实盘净值'!A:C,2,0) -> 0.99336489
B4: 固收+基金 | C4: 权益中枢 /股票仓位 | D4: 基金代码 | E4: 组合/基金 | F4: ="上线以来（截止"&TEXT($G$3,"m.d")&"）" -> 上线以来（截止7.7） | G4: ="6月以来（截止"&TEXT($G$3,"m.d")&"）" -> 6月以来（截止7.7） | H4: 最大回撤 | I4: 年化波动率 | J4: 夏普比率 | K4: 卡玛比率 | L4: 转债仓位(穿透)
B5: 嘉实财富样板间 | C5: 0.1 | E5: 10-90账户 | F5: =N3/N2-1 -> -0.00663511 | G5: =M3/M2-1 -> 0.0020307881 | H5: =vs招行!H5 -> -0.0099052057 | I5: =vs招行!I5 -> 0.047915986 | J5: =vs招行!J5 -> 0.41110524 | K5: =vs招行!K5 -> 1.9887031
B6: 固收+产品池 | C6: =[1]!thsiFinD("ths_stock_mv_to_fanv_fund",$D6,$C$2)/100 -> 0.11190982 | D6: 004010.OF | E6: =[1]!thsiFinD("ths_fund_official_short_name_fund",D6) -> 华泰柏瑞鼎利混合A | F6: =[1]!thsiFinD("ths_adjustment_nvg_ratio_fund",$D6,F$2,F$3,101)/100 -> -0.0058964556 | G6: =[1]!thsiFinD("ths_adjustment_nvg_ratio_fund",$D6,G$2,G$3,101)/100 -> -0.012487127 | H6: =-[1]!thsiFinD("ths_max_retrace_rate_all_fund",$D6,$H$2,$H$3)/100 -> -0.013511775 | I6: =[1]!thsiFinD("ths_annual_volatility_fund",D6,$H$2,$H$3,100,101)/100 -> 0.032082483 | J6: =[1]!thsiFinD("ths_sharp_fund",D6,$H$2,$H$3,100,101,100) -> -0.25740586 | K6: =[1]!thsiFinD("ths_calmar_ratio_fund",D6,$H$2,$H$3) -> -8.6283471 | L6: =[1]!thsiFinD("ths_cbb_to_bond_invest_mv_fund",$D6,$C$2)/100*[1]!thsiFinD("ths_bond_mv_to_fanv_fund",$D6,$C$2)/100 -> 0
C7: =[1]!thsiFinD("ths_stock_mv_to_fanv_fund",$D7,$C$2)/100 -> 0.15222139 | D7: 001316.OF | E7: =[1]!thsiFinD("ths_fund_official_short_name_fund",D7) -> 安信稳健增值混合A | F7: =[1]!thsiFinD("ths_adjustment_nvg_ratio_fund",$D7,F$2,F$3,101)/100 -> -0.0021679915 | G7: =[1]!thsiFinD("ths_adjustment_nvg_ratio_fund",$D7,G$2,G$3,101)/100 -> -0.011890345 | H7: =-[1]!thsiFinD("ths_max_retrace_rate_all_fund",$D7,$H$2,$H$3)/100 -> -0.020400329 | I7: =[1]!thsiFinD("ths_annual_volatility_fund",D7,$H$2,$H$3,100,101)/100 -> 0.031949941 | J7: =[1]!thsiFinD("ths_sharp_fund",D7,$H$2,$H$3,100,101,100) -> -0.24698901 | K7: =[1]!thsiFinD("ths_calmar_ratio_fund",D7,$H$2,$H$3) -> -5.4559691 | L7: =[1]!thsiFinD("ths_cbb_to_bond_invest_mv_fund",$D7,$C$2)/100*[1]!thsiFinD("ths_bond_mv_to_fanv_fund",$D7,$C$2)/100 -> 0
C8: =[1]!thsiFinD("ths_stock_mv_to_fanv_fund",$D8,$C$2)/100 -> 0.13282698 | D8: 009089.OF | E8: =[1]!thsiFinD("ths_fund_official_short_name_fund",D8) -> 嘉实稳固收益债券A | F8: =[1]!thsiFinD("ths_adjustment_nvg_ratio_fund",$D8,F$2,F$3,101)/100 -> 0.0031802984 | G8: =[1]!thsiFinD("ths_adjustment_nvg_ratio_fund",$D8,G$2,G$3,101)/100 -> 0.0028531833 | H8: =-[1]!thsiFinD("ths_max_retrace_rate_all_fund",$D8,$H$2,$H$3)/100 -> -0.013298523 | I8: =[1]!thsiFinD("ths_annual_volatility_fund",D8,$H$2,$H$3,100,101)/100 -> 0.055179471 | J8: =[1]!thsiFinD("ths_sharp_fund",D8,$H$2,$H$3,100,101,100) -> 0.021304774 | K8: =[1]!thsiFinD("ths_calmar_ratio_fund",D8,$H$2,$H$3) -> 2.1434633 | L8: =[1]!thsiFinD("ths_cbb_to_bond_invest_mv_fund",$D8,$C$2)/100*[1]!thsiFinD("ths_bond_mv_to_fanv_fund",$D8,$C$2)/100 -> 0
C9: =[1]!thsiFinD("ths_stock_mv_to_fanv_fund",$D9,$C$2)/100 -> 0.13829755 | D9: 002009.OF | E9: =[1]!thsiFinD("ths_fund_official_short_name_fund",D9) -> 中欧瑾通灵活配置混合A | F9: =[1]!thsiFinD("ths_adjustment_nvg_ratio_fund",$D9,F$2,F$3,101)/100 -> -0.0074819402 | G9: =[1]!thsiFinD("ths_adjustment_nvg_ratio_fund",$D9,G$2,G$3,101)/100 -> -0.004206303 | H9: =-[1]!thsiFinD("ths_max_retrace_rate_all_fund",$D9,$H$2,$H$3)/100 -> -0.011181082 | I9: =[1]!thsiFinD("ths_annual_volatility_fund",D9,$H$2,$H$3,100,101)/100 -> 0.037273857 | J9: =[1]!thsiFinD("ths_sharp_fund",D9,$H$2,$H$3,100,101,100) -> -0.085064152 | K9: =[1]!thsiFinD("ths_calmar_ratio_fund",D9,$H$2,$H$3) -> -3.6427108 | L9: =[1]!thsiFinD("ths_cbb_to_bond_invest_mv_fund",$D9,$C$2)/100*[1]!thsiFinD("ths_bond_mv_to_fanv_fund",$D9,$C$2)/100 -> 0
C10: =[1]!thsiFinD("ths_stock_mv_to_fanv_fund",$D10,$C$2)/100 -> 0.13282698 | D10: 009089.OF | E10: =[1]!thsiFinD("ths_fund_official_short_name_fund",D10) -> 嘉实稳固收益债券A | F10: =[1]!thsiFinD("ths_adjustment_nvg_ratio_fund",$D10,F$2,F$3,101)/100 -> 0.0031802984 | G10: =[1]!thsiFinD("ths_adjustment_nvg_ratio_fund",$D10,G$2,G$3,101)/100 -> 0.0028531833 | H10: =-[1]!thsiFinD("ths_max_retrace_rate_all_fund",$D10,$H$2,$H$3)/100 -> -0.013298523 | I10: =[1]!thsiFinD("ths_annual_volatility_fund",D10,$H$2,$H$3,100,101)/100 -> 0.055179471 | J10: =[1]!thsiFinD("ths_sharp_fund",D10,$H$2,$H$3,100,101,100) -> 0.021304774 | K10: =[1]!thsiFinD("ths_calmar_ratio_fund",D10,$H$2,$H$3) -> 2.1434633 | L10: =[1]!thsiFinD("ths_cbb_to_bond_invest_mv_fund",$D10,$C$2)/100*[1]!thsiFinD("ths_bond_mv_to_fanv_fund",$D10,$C$2)/100 -> 0
C11: =[1]!thsiFinD("ths_stock_mv_to_fanv_fund",$D11,$C$2)/100 -> 0.11452207 | D11: 675121.OF | E11: =[1]!thsiFinD("ths_fund_official_short_name_fund",D11) -> 西部利得汇逸债券A | F11: =[1]!thsiFinD("ths_adjustment_nvg_ratio_fund",$D11,F$2,F$3,101)/100 -> 0.0031320688 | G11: =[1]!thsiFinD("ths_adjustment_nvg_ratio_fund",$D11,G$2,G$3,101)/100 -> 0 | H11: =-[1]!thsiFinD("ths_max_retrace_rate_all_fund",$D11,$H$2,$H$3)/100 -> -0.0090121317 | I11: =[1]!thsiFinD("ths_annual_volatility_fund",D11,$H$2,$H$3,100,101)/100 -> 0.047573212 | J11: =[1]!thsiFinD("ths_sharp_fund",D11,$H$2,$H$3,100,101,100) -> -0.012211449 | K11: =[1]!thsiFinD("ths_calmar_ratio_fund",D11,$H$2,$H$3) -> 0 | L11: =[1]!thsiFinD("ths_cbb_to_bond_invest_mv_fund",$D11,$C$2)/100*[1]!thsiFinD("ths_bond_mv_to_fanv_fund",$D11,$C$2)/100 -> 0
C12: =[1]!thsiFinD("ths_stock_mv_to_fanv_fund",$D12,$C$2)/100 -> 0.17949274 | D12: 000171.OF | E12: =[1]!thsiFinD("ths_fund_official_short_name_fund",D12) -> 易方达裕丰回报债券A | F12: =[1]!thsiFinD("ths_adjustment_nvg_ratio_fund",$D12,F$2,F$3,101)/100 -> -0.0046403712 | G12: =[1]!thsiFinD("ths_adjustment_nvg_ratio_fund",$D12,G$2,G$3,101)/100 -> 0.025824964 | H12: =-[1]!thsiFinD("ths_max_retrace_rate_all_fund",$D12,$H$2,$H$3)/100 -> -0.020547945 | I12: =[1]!thsiFinD("ths_annual_volatility_fund",D12,$H$2,$H$3,100,101)/100 -> 0.1143056 | J12: =[1]!thsiFinD("ths_sharp_fund",D12,$H$2,$H$3,100,101,100) -> 0.13351081 | K12: =[1]!thsiFinD("ths_calmar_ratio_fund",D12,$H$2,$H$3) -> 13.917987 | L12: =[1]!thsiFinD("ths_cbb_to_bond_invest_mv_fund",$D12,$C$2)/100*[1]!thsiFinD("ths_bond_mv_to_fanv_fund",$D12,$C$2)/100 -> 0
C13: =[1]!thsiFinD("ths_stock_mv_to_fanv_fund",$D13,$C$2)/100 -> 0.18269629 | D13: 018595.OF | E13: =[1]!thsiFinD("ths_fund_official_short_name_fund",D13) -> 华商利欣回报债券A | F13: =[1]!thsiFinD("ths_adjustment_nvg_ratio_fund",$D13,F$2,F$3,101)/100 -> 0.0093502377 | G13: =[1]!thsiFinD("ths_adjustment_nvg_ratio_fund",$D13,G$2,G$3,101)/100 -> 0.02313253 | H13: =-[1]!thsiFinD("ths_max_retrace_rate_all_fund",$D13,$H$2,$H$3)/100 -> -0.012131437 | I13: =[1]!thsiFinD("ths_annual_volatility_fund",D13,$H$2,$H$3,100,101)/100 -> 0.070287628 | J13: =[1]!thsiFinD("ths_sharp_fund",D13,$H$2,$H$3,100,101,100) -> 0.19084196 | K13: =[1]!thsiFinD("ths_calmar_ratio_fund",D13,$H$2,$H$3) -> 20.861022 | L13: =[1]!thsiFinD("ths_cbb_to_bond_invest_mv_fund",$D13,$C$2)/100*[1]!thsiFinD("ths_bond_mv_to_fanv_fund",$D13,$C$2)/100 -> 0
C14: =[1]!thsiFinD("ths_stock_mv_to_fanv_fund",$D14,$C$2)/100 -> 0.19481447 | D14: 003504.OF | E14: =[1]!thsiFinD("ths_fund_official_short_name_fund",D14) -> 景顺长城景颐丰利债券A类 | F14: =[1]!thsiFinD("ths_adjustment_nvg_ratio_fund",$D14,F$2,F$3,101)/100 -> -0.019036496 | G14: =[1]!thsiFinD("ths_adjustment_nvg_ratio_fund",$D14,G$2,G$3,101)/100 -> 0.0082828161 | H14: =-[1]!thsiFinD("ths_max_retrace_rate_all_fund",$D14,$H$2,$H$3)/100 -> -0.025444406 | I14: =[1]!thsiFinD("ths_annual_volatility_fund",D14,$H$2,$H$3,100,101)/100 -> 0.11834019 | J14: =[1]!thsiFinD("ths_sharp_fund",D14,$H$2,$H$3,100,101,100) -> 0.040504126 | K14: =[1]!thsiFinD("ths_calmar_ratio_fund",D14,$H$2,$H$3) -> 3.3317624 | L14: =[1]!thsiFinD("ths_cbb_to_bond_invest_mv_fund",$D14,$C$2)/100*[1]!thsiFinD("ths_bond_mv_to_fanv_fund",$D14,$C$2)/100 -> 0
C15: =[1]!thsiFinD("ths_stock_mv_to_fanv_fund",$D15,$C$2)/100 -> 0.12892899 | D15: 020857.OF | E15: =[1]!thsiFinD("ths_fund_official_short_name_fund",D15) -> 嘉实多益债券A | F15: =[1]!thsiFinD("ths_adjustment_nvg_ratio_fund",$D15,F$2,F$3,101)/100 -> -0.024471545 | G15: =[1]!thsiFinD("ths_adjustment_nvg_ratio_fund",$D15,G$2,G$3,101)/100 -> 0.0036804684 | H15: =-[1]!thsiFinD("ths_max_retrace_rate_all_fund",$D15,$H$2,$H$3)/100 -> -0.038233408 | I15: =[1]!thsiFinD("ths_annual_volatility_fund",D15,$H$2,$H$3,100,101)/100 -> 0.13862277 | J15: =[1]!thsiFinD("ths_sharp_fund",D15,$H$2,$H$3,100,101,100) -> 0.015648482 | K15: =[1]!thsiFinD("ths_calmar_ratio_fund",D15,$H$2,$H$3) -> 0.96526503 | L15: =[1]!thsiFinD("ths_cbb_to_bond_invest_mv_fund",$D15,$C$2)/100*[1]!thsiFinD("ths_bond_mv_to_fanv_fund",$D15,$C$2)/100 -> 0
B16: 注：1090上线日为20260618，股票仓位＝最新季报期股票市值占基金资产净值比，最新季报期为2026-03-31

Sheet 1090实盘净值
B1: 1090账户基石投顾组合 | E1: =TODAY()-1 -> 46210
A2: =[1]!HX_AutoDate(1,"2026-06-18",E1,-1,-1,0,0,0,0,0,"SSE",13,0) -> 日期 | B2: 投资组合(扣除投顾费,申赎费) | C2: 业绩基准
A3: 46191 | B3: 1 | C3: 1
A4: 46195 | B4: 1.0008957 | C4: 1.0017327
A5: 46196 | B5: 0.99782281 | C5: 0.99848312
A6: 46197 | B6: 0.9997708 | C6: 0.99994096
A7: 46198 | B7: 1.0012783 | C7: 1.0012847
A8: 46199 | B8: 0.99893009 | C8: 0.99865014
A9: 46202 | B9: 1.0005215 | C9: 1.0012538
A10: 46203 | B10: 1.0027107 | C10: 1.0028215
A11: 46204 | B11: 0.99998488 | C11: 1.0016916
A12: 46205 | B12: 0.99402933 | C12: 0.99936768
A13: 46206 | B13: 0.99491237 | C13: 1.0007489
A14: 46209 | B14: 0.99396984 | C14: 0.99999342
A15: 46210 | B15: 0.99336489 | C15: 0.99843127

Sheet 实盘持仓配置
A1: 持仓配置（实盘·初始权重）
A2: 基金简称 | B2: 华安黄金ETF联接A | C2: 嘉实快线货币A | D2: 宏利复兴混合A | E2: 博道沪深300增强A | F2: 博道沪深300指增C | G2: 国泰通信设备ETF联接A | H2: 国泰通信设备C | I2: 嘉实前沿科技创新 | J2: 银华集成电路混合A | K2: 银华集成电路混合C | L2: 天弘中证1000指增A | M2: 天弘中证1000指增C | N2: 中欧中证500指增A | O2: 中欧中证500指增C | P2: 信澳业绩驱动A | Q2: 嘉实信息产业A | R2: 嘉实信息产业C | S2: 宏利复兴伟业C | T2: 国泰半导体材料设备ETF联接A | U2: 国泰半导体材料设备C | V2: 华泰柏瑞中证2000指增A | W2: 华泰柏瑞中证2000指增C | X2: 易方达中债新综指LOFA | Y2: 合计 | Z2: 年化费率 | AA2: 净值起始日
A3: 基金代码 | B3: 000216.OF | C3: 000917.OF | D3: 001170.OF | E3: 007044.OF | F3: 007045.OF | G3: 007817.OF | H3: 007818.OF | I3: 009993.OF | J3: 013840.OF | K3: 013841.OF | L3: 014201.OF | M3: 014202.OF | N3: 015453.OF | O3: 015454.OF | P3: 016370.OF | Q3: 017488.OF | R3: 017489.OF | S3: 017612.OF | T3: 019632.OF | U3: 019633.OF | V3: 019923.OF | W3: 019924.OF | X3: 161119.OF
A4: 产业趋势 权重 | B4: 0 | C4: 0.02 | D4: 0.19 | E4: 0 | F4: 0 | G4: 0.11 | H4: 0 | I4: 0 | J4: 0.19 | K4: 0 | L4: 0 | M4: 0 | N4: 0 | O4: 0 | P4: 0.19 | Q4: 0.19 | R4: 0 | S4: 0 | T4: 0.11 | U4: 0 | V4: 0 | W4: 0 | X4: 0 | Y4: =SUM(B4:X4) -> 1 | Z4: 0.015 | AA4: 46195
A5: 产业趋势基石 权重 | B5: 0 | C5: 0.02 | D5: 0.19 | E5: 0 | F5: 0 | G5: 0.11 | H5: 0 | I5: 0 | J5: 0.19 | K5: 0 | L5: 0 | M5: 0 | N5: 0 | O5: 0 | P5: 0.19 | Q5: 0.19 | R5: 0 | S5: 0 | T5: 0.11 | U5: 0 | V5: 0 | W5: 0 | X5: 0 | Y5: =SUM(B5:X5) -> 1 | Z5: 0.012 | AA5: 46191
A6: 产业趋势2号 权重 | B6: 0 | C6: 0.02 | D6: 0 | E6: 0 | F6: 0 | G6: 0 | H6: 0.11 | I6: 0.19 | J6: 0 | K6: 0.19 | L6: 0 | M6: 0 | N6: 0 | O6: 0 | P6: 0 | Q6: 0 | R6: 0.19 | S6: 0.19 | T6: 0 | U6: 0.11 | V6: 0 | W6: 0 | X6: 0 | Y6: =SUM(B6:X6) -> 1 | Z6: 0.015 | AA6: 46196
A7: 10-90 权重 | B7: 0.05 | C7: 0.02 | D7: 0 | E7: 0 | F7: 0.0125 | G7: 0 | H7: 0.005 | I7: 0.01 | J7: 0 | K7: 0.01 | L7: 0 | M7: 0.0125 | N7: 0 | O7: 0.0125 | P7: 0 | Q7: 0 | R7: 0.01 | S7: 0.01 | T7: 0 | U7: 0.005 | V7: 0 | W7: 0.0125 | X7: 0.83 | Y7: =SUM(B7:X7) -> 1 | Z7: 0.008 | AA7: 46197
A8: 10-90基石 权重 | B8: 0.05 | C8: 0.02 | D8: 0.01 | E8: 0.0125 | F8: 0 | G8: 0.005 | H8: 0 | I8: 0 | J8: 0.01 | K8: 0 | L8: 0.0125 | M8: 0 | N8: 0.0125 | O8: 0 | P8: 0.01 | Q8: 0.01 | R8: 0 | S8: 0 | T8: 0.005 | U8: 0 | V8: 0.0125 | W8: 0 | X8: 0.83 | Y8: =SUM(B8:X8) -> 1 | Z8: 0.005 | AA8: 46191
A9: 30-70 权重 | B9: 0.1 | C9: 0.02 | D9: 0 | E9: 0 | F9: 0.0375 | G9: 0 | H9: 0.015 | I9: 0.03 | J9: 0 | K9: 0.03 | L9: 0 | M9: 0.0375 | N9: 0 | O9: 0.0375 | P9: 0 | Q9: 0 | R9: 0.03 | S9: 0.03 | T9: 0 | U9: 0.015 | V9: 0 | W9: 0.0375 | X9: 0.58 | Y9: =SUM(B9:X9) -> 1 | Z9: 0.012 | AA9: 46197
A11: 权重蓝色输入；Z列为各组合年化费率、AA列为各组合净值起始日(当日净值=1)。新增交易日下拉填充，下游净值与看板自动重算。

Sheet 实盘净值数据(iFinD公式)
A1: 净值数据 * 实盘
A2: =TODAY() -> 46211
A3: 基金代码→ | B3: =实盘持仓配置!B3 -> 000216.OF | C3: =实盘持仓配置!C3 -> 000917.OF | D3: =实盘持仓配置!D3 -> 001170.OF | E3: =实盘持仓配置!E3 -> 007044.OF | F3: =实盘持仓配置!F3 -> 007045.OF | G3: =实盘持仓配置!G3 -> 007817.OF | H3: =实盘持仓配置!H3 -> 007818.OF | I3: =实盘持仓配置!I3 -> 009993.OF | ... X3: =实盘持仓配置!X3 -> 161119.OF
A4: =[1]!HX_AutoDate(1,"2026-06-18",A2,-1,-1,0,0,0,0,0,"SSE",14,0) -> 日期 | B4: 华安黄金ETF联接A | C4: 嘉实快线货币A | D4: 宏利复兴混合A | E4: 博道沪深300增强A | F4: 博道沪深300指增C | G4: 国泰通信设备ETF联接A | H4: 国泰通信设备C | I4: 嘉实前沿科技创新 | J4: 银华集成电路混合A | K4: 银华集成电路混合C | L4: 天弘中证1000指增A | M4: 天弘中证1000指增C | N4: 中欧中证500指增A | O4: 中欧中证500指增C | P4: 信澳业绩驱动A | Q4: 嘉实信息产业A | R4: 嘉实信息产业C | S4: 宏利复兴伟业C | T4: 国泰半导体材料设备ETF联接A | U4: 国泰半导体材料设备C | V4: 华泰柏瑞中证2000指增A | W4: 华泰柏瑞中证2000指增C | X4: 易方达中债新综指LOFA
A5: 46191 | B5: =IF($A5="","",[1]!thsiFinD("ths_adjustment_nv_fund",B$3,$A5)) -> 3.2441 | C5: =IF($A5="","",[1]!thsiFinD("ths_adjustment_nv_fund",C$3,$A5)) -> 1.3172785 | D5: =IF($A5="","",[1]!thsiFinD("ths_adjustment_nv_fund",D$3,$A5)) -> 6.062 | E5: =IF($A5="","",[1]!thsiFinD("ths_adjustment_nv_fund",E$3,$A5)) -> 1.9904 | F5: =IF($A5="","",[1]!thsiFinD("ths_adjustment_nv_fund",F$3,$A5)) -> 1.9344 | G5: =IF($A5="","",[1]!thsiFinD("ths_adjustment_nv_fund",G$3,$A5)) -> 5.0275 | H5: =IF($A5="","",[1]!thsiFinD("ths_adjustment_nv_fund",H$3,$A5)) -> 4.9215 | I5: =IF($A5="","",[1]!thsiFinD("ths_adjustment_nv_fund",I$3,$A5)) -> 2.9226 | ... X5: =IF($A5="","",[1]!thsiFinD("ths_adjustment_nv_fund",X$3,$A5)) -> 1.7869
A6: 46195 | B6: =IF($A6="","",[1]!thsiFinD("ths_adjustment_nv_fund",B$3,$A6)) -> 3.168 | C6: =IF($A6="","",[1]!thsiFinD("ths_adjustment_nv_fund",C$3,$A6)) -> 1.3174604 | D6: =IF($A6="","",[1]!thsiFinD("ths_adjustment_nv_fund",D$3,$A6)) -> 6.259 | E6: =IF($A6="","",[1]!thsiFinD("ths_adjustment_nv_fund",E$3,$A6)) -> 2.0345 | F6: =IF($A6="","",[1]!thsiFinD("ths_adjustment_nv_fund",F$3,$A6)) -> 1.9772 | G6: =IF($A6="","",[1]!thsiFinD("ths_adjustment_nv_fund",G$3,$A6)) -> 5.1121 | H6: =IF($A6="","",[1]!thsiFinD("ths_adjustment_nv_fund",H$3,$A6)) -> 5.0042 | I6: =IF($A6="","",[1]!thsiFinD("ths_adjustment_nv_fund",I$3,$A6)) -> 2.9905 | ... X6: =IF($A6="","",[1]!thsiFinD("ths_adjustment_nv_fund",X$3,$A6)) -> 1.7871
A7: 46196 | B7: =IF($A7="","",[1]!thsiFinD("ths_adjustment_nv_fund",B$3,$A7)) -> 3.116 | C7: =IF($A7="","",[1]!thsiFinD("ths_adjustment_nv_fund",C$3,$A7)) -> 1.3175125 | D7: =IF($A7="","",[1]!thsiFinD("ths_adjustment_nv_fund",D$3,$A7)) -> 5.996 | E7: =IF($A7="","",[1]!thsiFinD("ths_adjustment_nv_fund",E$3,$A7)) -> 1.9837 | F7: =IF($A7="","",[1]!thsiFinD("ths_adjustment_nv_fund",F$3,$A7)) -> 1.9278 | G7: =IF($A7="","",[1]!thsiFinD("ths_adjustment_nv_fund",G$3,$A7)) -> 4.9665 | H7: =IF($A7="","",[1]!thsiFinD("ths_adjustment_nv_fund",H$3,$A7)) -> 4.8616 | I7: =IF($A7="","",[1]!thsiFinD("ths_adjustment_nv_fund",I$3,$A7)) -> 2.9276 | ... X7: =IF($A7="","",[1]!thsiFinD("ths_adjustment_nv_fund",X$3,$A7)) -> 1.7863
A8: 46197 | B8: =IF($A8="","",[1]!thsiFinD("ths_adjustment_nv_fund",B$3,$A8)) -> 3.0984 | C8: =IF($A8="","",[1]!thsiFinD("ths_adjustment_nv_fund",C$3,$A8)) -> 1.3175573 | D8: =IF($A8="","",[1]!thsiFinD("ths_adjustment_nv_fund",D$3,$A8)) -> 6.113 | E8: =IF($A8="","",[1]!thsiFinD("ths_adjustment_nv_fund",E$3,$A8)) -> 1.9931 | F8: =IF($A8="","",[1]!thsiFinD("ths_adjustment_nv_fund",F$3,$A8)) -> 1.9369 | G8: =IF($A8="","",[1]!thsiFinD("ths_adjustment_nv_fund",G$3,$A8)) -> 5.0423 | H8: =IF($A8="","",[1]!thsiFinD("ths_adjustment_nv_fund",H$3,$A8)) -> 4.9357 | I8: =IF($A8="","",[1]!thsiFinD("ths_adjustment_nv_fund",I$3,$A8)) -> 3.0529 | ... X8: =IF($A8="","",[1]!thsiFinD("ths_adjustment_nv_fund",X$3,$A8)) -> 1.7862
A9: 46198 | B9: =IF($A9="","",[1]!thsiFinD("ths_adjustment_nv_fund",B$3,$A9)) -> 3.0309 | C9: =IF($A9="","",[1]!thsiFinD("ths_adjustment_nv_fund",C$3,$A9)) -> 1.3176051 | D9: =IF($A9="","",[1]!thsiFinD("ths_adjustment_nv_fund",D$3,$A9)) -> 6.312 | E9: =IF($A9="","",[1]!thsiFinD("ths_adjustment_nv_fund",E$3,$A9)) -> 2.0205 | F9: =IF($A9="","",[1]!thsiFinD("ths_adjustment_nv_fund",F$3,$A9)) -> 1.9635 | G9: =IF($A9="","",[1]!thsiFinD("ths_adjustment_nv_fund",G$3,$A9)) -> 5.1945 | H9: =IF($A9="","",[1]!thsiFinD("ths_adjustment_nv_fund",H$3,$A9)) -> 5.0848 | I9: =IF($A9="","",[1]!thsiFinD("ths_adjustment_nv_fund",I$3,$A9)) -> 3.1735 | ... X9: =IF($A9="","",[1]!thsiFinD("ths_adjustment_nv_fund",X$3,$A9)) -> 1.7875
A10: 46199 | B10: =IF($A10="","",[1]!thsiFinD("ths_adjustment_nv_fund",B$3,$A10)) -> 3.0598 | C10: =IF($A10="","",[1]!thsiFinD("ths_adjustment_nv_fund",C$3,$A10)) -> 1.3176497 | D10: =IF($A10="","",[1]!thsiFinD("ths_adjustment_nv_fund",D$3,$A10)) -> 5.99 | E10: =IF($A10="","",[1]!thsiFinD("ths_adjustment_nv_fund",E$3,$A10)) -> 1.9618 | F10: =IF($A10="","",[1]!thsiFinD("ths_adjustment_nv_fund",F$3,$A10)) -> 1.9065 | G10: =IF($A10="","",[1]!thsiFinD("ths_adjustment_nv_fund",G$3,$A10)) -> 4.8685 | H10: =IF($A10="","",[1]!thsiFinD("ths_adjustment_nv_fund",H$3,$A10)) -> 4.7655 | I10: =IF($A10="","",[1]!thsiFinD("ths_adjustment_nv_fund",I$3,$A10)) -> 3.0956 | ... X10: =IF($A10="","",[1]!thsiFinD("ths_adjustment_nv_fund",X$3,$A10)) -> 1.788
A11: 46202 | B11: =IF($A11="","",[1]!thsiFinD("ths_adjustment_nv_fund",B$3,$A11)) -> 3.0723 | C11: =IF($A11="","",[1]!thsiFinD("ths_adjustment_nv_fund",C$3,$A11)) -> 1.3177908 | D11: =IF($A11="","",[1]!thsiFinD("ths_adjustment_nv_fund",D$3,$A11)) -> 5.795 | E11: =IF($A11="","",[1]!thsiFinD("ths_adjustment_nv_fund",E$3,$A11)) -> 1.9811 | F11: =IF($A11="","",[1]!thsiFinD("ths_adjustment_nv_fund",F$3,$A11)) -> 1.9252 | G11: =IF($A11="","",[1]!thsiFinD("ths_adjustment_nv_fund",G$3,$A11)) -> 4.7592 | H11: =IF($A11="","",[1]!thsiFinD("ths_adjustment_nv_fund",H$3,$A11)) -> 4.6585 | I11: =IF($A11="","",[1]!thsiFinD("ths_adjustment_nv_fund",I$3,$A11)) -> 3.1442 | ... X11: =IF($A11="","",[1]!thsiFinD("ths_adjustment_nv_fund",X$3,$A11)) -> 1.7897
A12: 46203 | B12: =IF($A12="","",[1]!thsiFinD("ths_adjustment_nv_fund",B$3,$A12)) -> 3.0429 | C12: =IF($A12="","",[1]!thsiFinD("ths_adjustment_nv_fund",C$3,$A12)) -> 1.3178318 | D12: =IF($A12="","",[1]!thsiFinD("ths_adjustment_nv_fund",D$3,$A12)) -> 6.024 | E12: =IF($A12="","",[1]!thsiFinD("ths_adjustment_nv_fund",E$3,$A12)) -> 2.0032 | F12: =IF($A12="","",[1]!thsiFinD("ths_adjustment_nv_fund",F$3,$A12)) -> 1.9466 | G12: =IF($A12="","",[1]!thsiFinD("ths_adjustment_nv_fund",G$3,$A12)) -> 4.9737 | H12: =IF($A12="","",[1]!thsiFinD("ths_adjustment_nv_fund",H$3,$A12)) -> 4.8684 | I12: =IF($A12="","",[1]!thsiFinD("ths_adjustment_nv_fund",I$3,$A12)) -> 3.2499 | ... X12: =IF($A12="","",[1]!thsiFinD("ths_adjustment_nv_fund",X$3,$A12)) -> 1.7882
A13: 46204 | B13: =IF($A13="","",[1]!thsiFinD("ths_adjustment_nv_fund",B$3,$A13)) -> 3.0102 | C13: =IF($A13="","",[1]!thsiFinD("ths_adjustment_nv_fund",C$3,$A13)) -> 1.3178766 | D13: =IF($A13="","",[1]!thsiFinD("ths_adjustment_nv_fund",D$3,$A13)) -> 5.777 | E13: =IF($A13="","",[1]!thsiFinD("ths_adjustment_nv_fund",E$3,$A13)) -> 1.9953 | F13: =IF($A13="","",[1]!thsiFinD("ths_adjustment_nv_fund",F$3,$A13)) -> 1.9389 | G13: =IF($A13="","",[1]!thsiFinD("ths_adjustment_nv_fund",G$3,$A13)) -> 4.77 | H13: =IF($A13="","",[1]!thsiFinD("ths_adjustment_nv_fund",H$3,$A13)) -> 4.6689 | I13: =IF($A13="","",[1]!thsiFinD("ths_adjustment_nv_fund",I$3,$A13)) -> 3.1869 | ... X13: =IF($A13="","",[1]!thsiFinD("ths_adjustment_nv_fund",X$3,$A13)) -> 1.7865
A14: 46205 | B14: =IF($A14="","",[1]!thsiFinD("ths_adjustment_nv_fund",B$3,$A14)) -> 3.0728 | C14: =IF($A14="","",[1]!thsiFinD("ths_adjustment_nv_fund",C$3,$A14)) -> 1.3179215 | D14: =IF($A14="","",[1]!thsiFinD("ths_adjustment_nv_fund",D$3,$A14)) -> 5.363 | E14: =IF($A14="","",[1]!thsiFinD("ths_adjustment_nv_fund",E$3,$A14)) -> 1.9341 | F14: =IF($A14="","",[1]!thsiFinD("ths_adjustment_nv_fund",F$3,$A14)) -> 1.8795 | G14: =IF($A14="","",[1]!thsiFinD("ths_adjustment_nv_fund",G$3,$A14)) -> 4.4049 | H14: =IF($A14="","",[1]!thsiFinD("ths_adjustment_nv_fund",H$3,$A14)) -> 4.3115 | I14: =IF($A14="","",[1]!thsiFinD("ths_adjustment_nv_fund",I$3,$A14)) -> 2.9271 | ... X14: =IF($A14="","",[1]!thsiFinD("ths_adjustment_nv_fund",X$3,$A14)) -> 1.7867
A15: 46206 | B15: =IF($A15="","",[1]!thsiFinD("ths_adjustment_nv_fund",B$3,$A15)) -> 3.1547 | C15: =IF($A15="","",[1]!thsiFinD("ths_adjustment_nv_fund",C$3,$A15)) -> 1.3179685 | D15: =IF($A15="","",[1]!thsiFinD("ths_adjustment_nv_fund",D$3,$A15)) -> 5.405 | E15: =IF($A15="","",[1]!thsiFinD("ths_adjustment_nv_fund",E$3,$A15)) -> 1.9475 | F15: =IF($A15="","",[1]!thsiFinD("ths_adjustment_nv_fund",F$3,$A15)) -> 1.8924 | G15: =IF($A15="","",[1]!thsiFinD("ths_adjustment_nv_fund",G$3,$A15)) -> 4.4033 | H15: =IF($A15="","",[1]!thsiFinD("ths_adjustment_nv_fund",H$3,$A15)) -> 4.3099 | I15: =IF($A15="","",[1]!thsiFinD("ths_adjustment_nv_fund",I$3,$A15)) -> 2.9794 | ... X15: =IF($A15="","",[1]!thsiFinD("ths_adjustment_nv_fund",X$3,$A15)) -> 1.7863
A16: 46209 | B16: =IF($A16="","",[1]!thsiFinD("ths_adjustment_nv_fund",B$3,$A16)) -> 3.145 | C16: =IF($A16="","",[1]!thsiFinD("ths_adjustment_nv_fund",C$3,$A16)) -> 1.3181065 | D16: =IF($A16="","",[1]!thsiFinD("ths_adjustment_nv_fund",D$3,$A16)) -> 5.234 | E16: =IF($A16="","",[1]!thsiFinD("ths_adjustment_nv_fund",E$3,$A16)) -> 1.9455 | F16: =IF($A16="","",[1]!thsiFinD("ths_adjustment_nv_fund",F$3,$A16)) -> 1.8904 | G16: =IF($A16="","",[1]!thsiFinD("ths_adjustment_nv_fund",G$3,$A16)) -> 4.2539 | H16: =IF($A16="","",[1]!thsiFinD("ths_adjustment_nv_fund",H$3,$A16)) -> 4.1636 | I16: =IF($A16="","",[1]!thsiFinD("ths_adjustment_nv_fund",I$3,$A16)) -> 2.9168 | ... X16: =IF($A16="","",[1]!thsiFinD("ths_adjustment_nv_fund",X$3,$A16)) -> 1.7876
... A18: 46211 | B18: =IF($A18="","",[1]!thsiFinD("ths_adjustment_nv_fund",B$3,$A18)) -> 3.1265 | C18: =IF($A18="","",[1]!thsiFinD("ths_adjustment_nv_fund",C$3,$A18)) -> 1.3181508 | D18: =IF($A18="","",[1]!thsiFinD("ths_adjustment_nv_fund",D$3,$A18)) -> 5.26 | E18: =IF($A18="","",[1]!thsiFinD("ths_adjustment_nv_fund",E$3,$A18)) -> 1.9216 | F18: =IF($A18="","",[1]!thsiFinD("ths_adjustment_nv_fund",F$3,$A18)) -> 1.8671 | G18: =IF($A18="","",[1]!thsiFinD("ths_adjustment_nv_fund",G$3,$A18)) -> 4.2548 | H18: =IF($A18="","",[1]!thsiFinD("ths_adjustment_nv_fund",H$3,$A18)) -> 4.1645 | I18: =IF($A18="","",[1]!thsiFinD("ths_adjustment_nv_fund",I$3,$A18)) -> 2.873 | ... X18: =IF($A18="","",[1]!thsiFinD("ths_adjustment_nv_fund",X$3,$A18)) -> 1.7878
B19: =IF($A19="","",[1]!thsiFinD("ths_adjustment_nv_fund",B$3,$A19)) | C19: =IF($A19="","",[1]!thsiFinD("ths_adjustment_nv_fund",C$3,$A19)) | D19: =IF($A19="","",[1]!thsiFinD("ths_adjustment_nv_fund",D$3,$A19)) | E19: =IF($A19="","",[1]!thsiFinD("ths_adjustment_nv_fund",E$3,$A19)) | F19: =IF($A19="","",[1]!thsiFinD("ths_adjustment_nv_fund",F$3,$A19)) | G19: =IF($A19="","",[1]!thsiFinD("ths_adjustment_nv_fund",G$3,$A19)) | H19: =IF($A19="","",[1]!thsiFinD("ths_adjustment_nv_fund",H$3,$A19)) | I19: =IF($A19="","",[1]!thsiFinD("ths_adjustment_nv_fund",I$3,$A19)) | ... X19: =IF($A19="","",[1]!thsiFinD("ths_adjustment_nv_fund",X$3,$A19))
B20: =IF($A20="","",[1]!thsiFinD("ths_adjustment_nv_fund",B$3,$A20)) | C20: =IF($A20="","",[1]!thsiFinD("ths_adjustment_nv_fund",C$3,$A20)) | D20: =IF($A20="","",[1]!thsiFinD("ths_adjustment_nv_fund",D$3,$A20)) | E20: =IF($A20="","",[1]!thsiFinD("ths_adjustment_nv_fund",E$3,$A20)) | F20: =IF($A20="","",[1]!thsiFinD("ths_adjustment_nv_fund",F$3,$A20)) | G20: =IF($A20="","",[1]!thsiFinD("ths_adjustment_nv_fund",G$3,$A20)) | H20: =IF($A20="","",[1]!thsiFinD("ths_adjustment_nv_fund",H$3,$A20)) | I20: =IF($A20="","",[1]!thsiFinD("ths_adjustment_nv_fund",I$3,$A20)) | ... X20: =IF($A20="","",[1]!thsiFinD("ths_adjustment_nv_fund",X$3,$A20))
B21: =IF($A21="","",[1]!thsiFinD("ths_adjustment_nv_fund",B$3,$A21)) | C21: =IF($A21="","",[1]!thsiFinD("ths_adjustment_nv_fund",C$3,$A21)) | D21: =IF($A21="","",[1]!thsiFinD("ths_adjustment_nv_fund",D$3,$A21)) | E21: =IF($A21="","",[1]!thsiFinD("ths_adjustment_nv_fund",E$3,$A21)) | F21: =IF($A21="","",[1]!thsiFinD("ths_adjustment_nv_fund",F$3,$A21)) | G21: =IF($A21="","",[1]!thsiFinD("ths_adjustment_nv_fund",G$3,$A21)) | H21: =IF($A21="","",[1]!thsiFinD("ths_adjustment_nv_fund",H$3,$A21)) | I21: =IF($A21="","",[1]!thsiFinD("ths_adjustment_nv_fund",I$3,$A21)) | ... X21: =IF($A21="","",[1]!thsiFinD("ths_adjustment_nv_fund",X$3,$A21))
B22: =IF($A22="","",[1]!thsiFinD("ths_adjustment_nv_fund",B$3,$A22)) | C22: =IF($A22="","",[1]!thsiFinD("ths_adjustment_nv_fund",C$3,$A22)) | D22: =IF($A22="","",[1]!thsiFinD("ths_adjustment_nv_fund",D$3,$A22)) | E22: =IF($A22="","",[1]!thsiFinD("ths_adjustment_nv_fund",E$3,$A22)) | F22: =IF($A22="","",[1]!thsiFinD("ths_adjustment_nv_fund",F$3,$A22)) | G22: =IF($A22="","",[1]!thsiFinD("ths_adjustment_nv_fund",G$3,$A22)) | H22: =IF($A22="","",[1]!thsiFinD("ths_adjustment_nv_fund",H$3,$A22)) | I22: =IF($A22="","",[1]!thsiFinD("ths_adjustment_nv_fund",I$3,$A22)) | ... X22: =IF($A22="","",[1]!thsiFinD("ths_adjustment_nv_fund",X$3,$A22))
B23: =IF($A23="","",[1]!thsiFinD("ths_adjustment_nv_fund",B$3,$A23)) | C23: =IF($A23="","",[1]!thsiFinD("ths_adjustment_nv_fund",C$3,$A23)) | D23: =IF($A23="","",[1]!thsiFinD("ths_adjustment_nv_fund",D$3,$A23)) | E23: =IF($A23="","",[1]!thsiFinD("ths_adjustment_nv_fund",E$3,$A23)) | F23: =IF($A23="","",[1]!thsiFinD("ths_adjustment_nv_fund",F$3,$A23)) | G23: =IF($A23="","",[1]!thsiFinD("ths_adjustment_nv_fund",G$3,$A23)) | H23: =IF($A23="","",[1]!thsiFinD("ths_adjustment_nv_fund",H$3,$A23)) | I23: =IF($A23="","",[1]!thsiFinD("ths_adjustment_nv_fund",I$3,$A23)) | ... X23: =IF($A23="","",[1]!thsiFinD("ths_adjustment_nv_fund",X$3,$A23))
B24: =IF($A24="","",[1]!thsiFinD("ths_adjustment_nv_fund",B$3,$A24)) | C24: =IF($A24="","",[1]!thsiFinD("ths_adjustment_nv_fund",C$3,$A24)) | D24: =IF($A24="","",[1]!thsiFinD("ths_adjustment_nv_fund",D$3,$A24)) | E24: =IF($A24="","",[1]!thsiFinD("ths_adjustment_nv_fund",E$3,$A24)) | F24: =IF($A24="","",[1]!thsiFinD("ths_adjustment_nv_fund",F$3,$A24)) | G24: =IF($A24="","",[1]!thsiFinD("ths_adjustment_nv_fund",G$3,$A24)) | H24: =IF($A24="","",[1]!thsiFinD("ths_adjustment_nv_fund",H$3,$A24)) | I24: =IF($A24="","",[1]!thsiFinD("ths_adjustment_nv_fund",I$3,$A24)) | ... X24: =IF($A24="","",[1]!thsiFinD("ths_adjustment_nv_fund",X$3,$A24))
B25: =IF($A25="","",[1]!thsiFinD("ths_adjustment_nv_fund",B$3,$A25)) | C25: =IF($A25="","",[1]!thsiFinD("ths_adjustment_nv_fund",C$3,$A25)) | D25: =IF($A25="","",[1]!thsiFinD("ths_adjustment_nv_fund",D$3,$A25)) | E25: =IF($A25="","",[1]!thsiFinD("ths_adjustment_nv_fund",E$3,$A25)) | F25: =IF($A25="","",[1]!thsiFinD("ths_adjustment_nv_fund",F$3,$A25)) | G25: =IF($A25="","",[1]!thsiFinD("ths_adjustment_nv_fund",G$3,$A25)) | H25: =IF($A25="","",[1]!thsiFinD("ths_adjustment_nv_fund",H$3,$A25)) | I25: =IF($A25="","",[1]!thsiFinD("ths_adjustment_nv_fund",I$3,$A25)) | ... X25: =IF($A25="","",[1]!thsiFinD("ths_adjustment_nv_fund",X$3,$A25))
B26: =IF($A26="","",[1]!thsiFinD("ths_adjustment_nv_fund",B$3,$A26)) | C26: =IF($A26="","",[1]!thsiFinD("ths_adjustment_nv_fund",C$3,$A26)) | D26: =IF($A26="","",[1]!thsiFinD("ths_adjustment_nv_fund",D$3,$A26)) | E26: =IF($A26="","",[1]!thsiFinD("ths_adjustment_nv_fund",E$3,$A26)) | F26: =IF($A26="","",[1]!thsiFinD("ths_adjustment_nv_fund",F$3,$A26)) | G26: =IF($A26="","",[1]!thsiFinD("ths_adjustment_nv_fund",G$3,$A26)) | H26: =IF($A26="","",[1]!thsiFinD("ths_adjustment_nv_fund",H$3,$A26)) | I26: =IF($A26="","",[1]!thsiFinD("ths_adjustment_nv_fund",I$3,$A26)) | ... X26: =IF($A26="","",[1]!thsiFinD("ths_adjustment_nv_fund",X$3,$A26))
B27: =IF($A27="","",[1]!thsiFinD("ths_adjustment_nv_fund",B$3,$A27)) | C27: =IF($A27="","",[1]!thsiFinD("ths_adjustment_nv_fund",C$3,$A27)) | D27: =IF($A27="","",[1]!thsiFinD("ths_adjustment_nv_fund",D$3,$A27)) | E27: =IF($A27="","",[1]!thsiFinD("ths_adjustment_nv_fund",E$3,$A27)) | F27: =IF($A27="","",[1]!thsiFinD("ths_adjustment_nv_fund",F$3,$A27)) | G27: =IF($A27="","",[1]!thsiFinD("ths_adjustment_nv_fund",G$3,$A27)) | H27: =IF($A27="","",[1]!thsiFinD("ths_adjustment_nv_fund",H$3,$A27)) | I27: =IF($A27="","",[1]!thsiFinD("ths_adjustment_nv_fund",I$3,$A27)) | ... X27: =IF($A27="","",[1]!thsiFinD("ths_adjustment_nv_fund",X$3,$A27))
B28: =IF($A28="","",[1]!thsiFinD("ths_adjustment_nv_fund",B$3,$A28)) | C28: =IF($A28="","",[1]!thsiFinD("ths_adjustment_nv_fund",C$3,$A28)) | D28: =IF($A28="","",[1]!thsiFinD("ths_adjustment_nv_fund",D$3,$A28)) | E28: =IF($A28="","",[1]!thsiFinD("ths_adjustment_nv_fund",E$3,$A28)) | F28: =IF($A28="","",[1]!thsiFinD("ths_adjustment_nv_fund",F$3,$A28)) | G28: =IF($A28="","",[1]!thsiFinD("ths_adjustment_nv_fund",G$3,$A28)) | H28: =IF($A28="","",[1]!thsiFinD("ths_adjustment_nv_fund",H$3,$A28)) | I28: =IF($A28="","",[1]!thsiFinD("ths_adjustment_nv_fund",I$3,$A28)) | ... X28: =IF($A28="","",[1]!thsiFinD("ths_adjustment_nv_fund",X$3,$A28))
B29: =IF($A29="","",[1]!thsiFinD("ths_adjustment_nv_fund",B$3,$A29)) | C29: =IF($A29="","",[1]!thsiFinD("ths_adjustment_nv_fund",C$3,$A29)) | D29: =IF($A29="","",[1]!thsiFinD("ths_adjustment_nv_fund",D$3,$A29)) | E29: =IF($A29="","",[1]!thsiFinD("ths_adjustment_nv_fund",E$3,$A29)) | F29: =IF($A29="","",[1]!thsiFinD("ths_adjustment_nv_fund",F$3,$A29)) | G29: =IF($A29="","",[1]!thsiFinD("ths_adjustment_nv_fund",G$3,$A29)) | H29: =IF($A29="","",[1]!thsiFinD("ths_adjustment_nv_fund",H$3,$A29)) | I29: =IF($A29="","",[1]!thsiFinD("ths_adjustment_nv_fund",I$3,$A29)) | ... X29: =IF($A29="","",[1]!thsiFinD("ths_adjustment_nv_fund",X$3,$A29))
B30: =IF($A30="","",[1]!thsiFinD("ths_adjustment_nv_fund",B$3,$A30)) | C30: =IF($A30="","",[1]!thsiFinD("ths_adjustment_nv_fund",C$3,$A30)) | D30: =IF($A30="","",[1]!thsiFinD("ths_adjustment_nv_fund",D$3,$A30)) | E30: =IF($A30="","",[1]!thsiFinD("ths_adjustment_nv_fund",E$3,$A30)) | F30: =IF($A30="","",[1]!thsiFinD("ths_adjustment_nv_fund",F$3,$A30)) | G30: =IF($A30="","",[1]!thsiFinD("ths_adjustment_nv_fund",G$3,$A30)) | H30: =IF($A30="","",[1]!thsiFinD("ths_adjustment_nv_fund",H$3,$A30)) | I30: =IF($A30="","",[1]!thsiFinD("ths_adjustment_nv_fund",I$3,$A30)) | ... X30: =IF($A30="","",[1]!thsiFinD("ths_adjustment_nv_fund",X$3,$A30))
... B60: =IF($A60="","",[1]!thsiFinD("ths_adjustment_nv_fund",B$3,$A60)) | C60: =IF($A60="","",[1]!thsiFinD("ths_adjustment_nv_fund",C$3,$A60)) | D60: =IF($A60="","",[1]!thsiFinD("ths_adjustment_nv_fund",D$3,$A60)) | E60: =IF($A60="","",[1]!thsiFinD("ths_adjustment_nv_fund",E$3,$A60)) | F60: =IF($A60="","",[1]!thsiFinD("ths_adjustment_nv_fund",F$3,$A60)) | G60: =IF($A60="","",[1]!thsiFinD("ths_adjustment_nv_fund",G$3,$A60)) | H60: =IF($A60="","",[1]!thsiFinD("ths_adjustment_nv_fund",H$3,$A60)) | I60: =IF($A60="","",[1]!thsiFinD("ths_adjustment_nv_fund",I$3,$A60)) | ... X60: =IF($A60="","",[1]!thsiFinD("ths_adjustment_nv_fund",X$3,$A60))

Sheet 实盘组合净值
A1: 组合净值（实盘）· 各组合自起始日买入持有逐日计算
B3: 组合 产业趋势 | E3: 组合 产业趋势基石 | H3: 组合 产业趋势2号 | K3: 组合 10-90 | N3: 组合 10-90基石 | Q3: 组合 30-70
A4: 日期 | B4: 净值 | C4: 日收益 | D4: 回撤 | E4: 净值 | F4: 日收益 | G4: 回撤 | H4: 净值 | I4: 日收益 | J4: 回撤 | K4: 净值 | L4: 日收益 | M4: 回撤 | N4: 净值 | O4: 日收益 | P4: 回撤 | Q4: 净值 | R4: 日收益 | S4: 回撤
A5: =IF('实盘净值数据(iFinD公式)'!A5="","",'实盘净值数据(iFinD公式)'!A5) -> 46191 | B5: =IF(OR((ROW()-1)<6,'实盘净值数据(iFinD公式)'!$A5="",'实盘净值数据(iFinD公式)'!$B5=""),"",SUMPRODUCT(实盘持仓配置!$B$4:$X$4,'实盘净值数据(iFinD公式)'!$B5:$X5/'实盘净值数据(iFinD公式)'!$B$6:$X$6)*(1-实盘持仓配置!$Z$4)^(('实盘净值数据(iFinD公式)'!$A5-'实盘净值数据(iFinD公式)'!$A$6)/365)) | D5: =IF(B5="","",B5/MAX(B$5:B5)-1) | E5: 1 | G5: =IF(E5="","",E5/MAX(E$5:E5)-1) -> 0 | H5: =IF(OR((ROW()-1)<7,'实盘净值数据(iFinD公式)'!$A5="",'实盘净值数据(iFinD公式)'!$B5=""),"",SUMPRODUCT(实盘持仓配置!$B$6:$X$6,'实盘净值数据(iFinD公式)'!$B5:$X5/'实盘净值数据(iFinD公式)'!$B$7:$X$7)*(1-实盘持仓配置!$Z$6)^(('实盘净值数据(iFinD公式)'!$A5-'实盘净值数据(iFinD公式)'!$A$7)/365)) | J5: =IF(H5="","",H5/MAX(H$5:H5)-1) | K5: =IF(OR((ROW()-1)<8,'实盘净值数据(iFinD公式)'!$A5="",'实盘净值数据(iFinD公式)'!$B5=""),"",SUMPRODUCT(实盘持仓配置!$B$7:$X$7,'实盘净值数据(iFinD公式)'!$B5:$X5/'实盘净值数据(iFinD公式)'!$B$8:$X$8)*(1-实盘持仓配置!$Z$7)^(('实盘净值数据(iFinD公式)'!$A5-'实盘净值数据(iFinD公式)'!$A$8)/365)) | M5: =IF(K5="","",K5/MAX(K$5:K5)-1) | N5: 1 | P5: =IF(N5="","",N5/MAX(N$5:N5)-1) -> 0 | Q5: =IF(OR((ROW()-1)<8,'实盘净值数据(iFinD公式)'!$A5="",'实盘净值数据(iFinD公式)'!$B5=""),"",SUMPRODUCT(实盘持仓配置!$B$9:$X$9,'实盘净值数据(iFinD公式)'!$B5:$X5/'实盘净值数据(iFinD公式)'!$B$8:$X$8)*(1-实盘持仓配置!$Z$9)^(('实盘净值数据(iFinD公式)'!$A5-'实盘净值数据(iFinD公式)'!$A$8)/365)) | S5: =IF(Q5="","",Q5/MAX(Q$5:Q5)-1)
A6: =IF('实盘净值数据(iFinD公式)'!A6="","",'实盘净值数据(iFinD公式)'!A6) -> 46195 | B6: 1 | C6: =IF(OR(B5="",'实盘净值数据(iFinD公式)'!$A6="",'实盘净值数据(iFinD公式)'!$B6=""),"",(SUMPRODUCT(实盘持仓配置!$B$4:$X$4,'实盘净值数据(iFinD公式)'!$B5:$X5/'实盘净值数据(iFinD公式)'!$B$6:$X$6,'实盘净值数据(iFinD公式)'!$B6:$X6/'实盘净值数据(iFinD公式)'!$B5:$X5)/SUMPRODUCT(实盘持仓配置!$B$4:$X$4,'实盘净值数据(iFinD公式)'!$B5:$X5/'实盘净值数据(iFinD公式)'!$B$6:$X$6))*(1-实盘持仓配置!$Z$4)^(('实盘净值数据(iFinD公式)'!$A6-'实盘净值数据(iFinD公式)'!$A5)/365)-1) | D6: =IF(B6="","",B6/MAX(B$5:B6)-1) -> 0 | E6: =IF(OR((ROW()-1)<5,'实盘净值数据(iFinD公式)'!$A6="",'实盘净值数据(iFinD公式)'!$B6=""),"",SUMPRODUCT(实盘持仓配置!$B$5:$X$5,'实盘净值数据(iFinD公式)'!$B6:$X6/'实盘净值数据(iFinD公式)'!$B$5:$X$5)*(1-实盘持仓配置!$Z$5)^(('实盘净值数据(iFinD公式)'!$A6-'实盘净值数据(iFinD公式)'!$A$5)/365)) -> 1.0234375 | F6: =IF(OR(E5="",'实盘净值数据(iFinD公式)'!$A6="",'实盘净值数据(iFinD公式)'!$B6=""),"",(SUMPRODUCT(实盘持仓配置!$B$5:$X$5,'实盘净值数据(iFinD公式)'!$B5:$X5/'实盘净值数据(iFinD公式)'!$B$5:$X$5,'实盘净值数据(iFinD公式)'!$B6:$X6/'实盘净值数据(iFinD公式)'!$B5:$X5)/SUMPRODUCT(实盘持仓配置!$B$5:$X$5,'实盘净值数据(iFinD公式)'!$B5:$X5/'实盘净值数据(iFinD公式)'!$B$5:$X$5))*(1-实盘持仓配置!$Z$5)^(('实盘净值数据(iFinD公式)'!$A6-'实盘净值数据(iFinD公式)'!$A5)/365)-1) -> 0.023437473 | G6: =IF(E6="","",E6/MAX(E$5:E6)-1) -> 0 | H6: =IF(OR((ROW()-1)<7,'实盘净值数据(iFinD公式)'!$A6="",'实盘净值数据(iFinD公式)'!$B6=""),"",SUMPRODUCT(实盘持仓配置!$B$6:$X$6,'实盘净值数据(iFinD公式)'!$B6:$X6/'实盘净值数据(iFinD公式)'!$B$7:$X$7)*(1-实盘持仓配置!$Z$6)^(('实盘净值数据(iFinD公式)'!$A6-'实盘净值数据(iFinD公式)'!$A$7)/365)) | I6: =IF(OR(H5="",'实盘净值数据(iFinD公式)'!$A6="",'实盘净值数据(iFinD公式)'!$B6=""),"",(SUMPRODUCT(实盘持仓配置!$B$6:$X$6,'实盘净值数据(iFinD公式)'!$B5:$X5/'实盘净值数据(iFinD公式)'!$B$7:$X$7,'实盘净值数据(iFinD公式)'!$B6:$X6/'实盘净值数据(iFinD公式)'!$B5:$X5)/SUMPRODUCT(实盘持仓配置!$B$6:$X$6,'实盘净值数据(iFinD公式)'!$B5:$X5/'实盘净值数据(iFinD公式)'!$B$7:$X$7))*(1-实盘持仓配置!$Z$6)^(('实盘净值数据(iFinD公式)'!$A6-'实盘净值数据(iFinD公式)'!$A5)/365)-1) | J6: =IF(H6="","",H6/MAX(H$5:H6)-1) | K6: =IF(OR((ROW()-1)<8,'实盘净值数据(iFinD公式)'!$A6="",'实盘净值数据(iFinD公式)'!$B6=""),"",SUMPRODUCT(实盘持仓配置!$B$7:$X$7,'实盘净值数据(iFinD公式)'!$B6:$X6/'实盘净值数据(iFinD公式)'!$B$8:$X$8)*(1-实盘持仓配置!$Z$7)^(('实盘净值数据(iFinD公式)'!$A6-'实盘净值数据(iFinD公式)'!$A$8)/365)) | L6: =IF(OR(K5="",'实盘净值数据(iFinD公式)'!$A6="",'实盘净值数据(iFinD公式)'!$B6=""),"",(SUMPRODUCT(实盘持仓配置!$B$7:$X$7,'实盘净值数据(iFinD公式)'!$B5:$X5/'实盘净值数据(iFinD公式)'!$B$8:$X$8,'实盘净值数据(iFinD公式)'!$B6:$X6/'实盘净值数据(iFinD公式)'!$B5:$X5)/SUMPRODUCT(实盘持仓配置!$B$7:$X$7,'实盘净值数据(iFinD公式)'!$B5:$X5/'实盘净值数据(iFinD公式)'!$B$8:$X$8))*(1-实盘持仓配置!$Z$7)^(('实盘净值数据(iFinD公式)'!$A6-'实盘净值数据(iFinD公式)'!$A5)/365)-1) | M6: =IF(K6="","",K6/MAX(K$5:K6)-1) | N6: =IF(OR((ROW()-1)<5,'实盘净值数据(iFinD公式)'!$A6="",'实盘净值数据(iFinD公式)'!$B6=""),"",SUMPRODUCT(实盘持仓配置!$B$8:$X$8,'实盘净值数据(iFinD公式)'!$B6:$X6/'实盘净值数据(iFinD公式)'!$B$5:$X$5)*(1-实盘持仓配置!$Z$8)^(('实盘净值数据(iFinD公式)'!$A6-'实盘净值数据(iFinD公式)'!$A$5)/365)) -> 1.0008955 | O6: =IF(OR(N5="",'实盘净值数据(iFinD公式)'!$A6="",'实盘净值数据(iFinD公式)'!$B6=""),"",(SUMPRODUCT(实盘持仓配置!$B$8:$X$8,'实盘净值数据(iFinD公式)'!$B5:$X5/'实盘净值数据(iFinD公式)'!$B$5:$X$5,'实盘净值数据(iFinD公式)'!$B6:$X6/'实盘净值数据(iFinD公式)'!$B5:$X5)/SUMPRODUCT(实盘持仓配置!$B$8:$X$8,'实盘净值数据(iFinD公式)'!$B5:$X5/'实盘净值数据(iFinD公式)'!$B$5:$X$5))*(1-实盘持仓配置!$Z$8)^(('实盘净值数据(iFinD公式)'!$A6-'实盘净值数据(iFinD公式)'!$A5)/365)-1) -> 0.00089553164 | P6: =IF(N6="","",N6/MAX(N$5:N6)-1) -> 0 | Q6: =IF(OR((ROW()-1)<8,'实盘净值数据(iFinD公式)'!$A6="",'实盘净值数据(iFinD公式)'!$B6=""),"",SUMPRODUCT(实盘持仓配置!$B$9:$X$9,'实盘净值数据(iFinD公式)'!$B6:$X6/'实盘净值数据(iFinD公式)'!$B$8:$X$8)*(1-实盘持仓配置!$Z$9)^(('实盘净值数据(iFinD公式)'!$A6-'实盘净值数据(iFinD公式)'!$A$8)/365)) | R6: =IF(OR(Q5="",'实盘净值数据(iFinD公式)'!$A6="",'实盘净值数据(iFinD公式)'!$B6=""),"",(SUMPRODUCT(实盘持仓配置!$B$9:$X$9,'实盘净值数据(iFinD公式)'!$B5:$X5/'实盘净值数据(iFinD公式)'!$B$8:$X$8,'实盘净值数据(iFinD公式)'!$B6:$X6/'实盘净值数据(iFinD公式)'!$B5:$X5)/SUMPRODUCT(实盘持仓配置!$B$9:$X$9,'实盘净值数据(iFinD公式)'!$B5:$X5/'实盘净值数据(iFinD公式)'!$B$8:$X$8))*(1-实盘持仓配置!$Z$9)^(('实盘净值数据(iFinD公式)'!$A6-'实盘净值数据(iFinD公式)'!$A5)/365)-1) | S6: =IF(Q6="","",Q6/MAX(Q$5:Q6)-1)
A7: =IF('实盘净值数据(iFinD公式)'!A7="","",'实盘净值数据(iFinD公式)'!A7) -> 46196 | B7: =IF(OR((ROW()-1)<6,'实盘净值数据(iFinD公式)'!$A7="",'实盘净值数据(iFinD公式)'!$B7=""),"",SUMPRODUCT(实盘持仓配置!$B$4:$X$4,'实盘净值数据(iFinD公式)'!$B7:$X7/'实盘净值数据(iFinD公式)'!$B$6:$X$6)*(1-实盘持仓配置!$Z$4)^(('实盘净值数据(iFinD公式)'!$A7-'实盘净值数据(iFinD公式)'!$A$6)/365)) -> 0.98042319 | C7: =IF(OR(B6="",'实盘净值数据(iFinD公式)'!$A7="",'实盘净值数据(iFinD公式)'!$B7=""),"",(SUMPRODUCT(实盘持仓配置!$B$4:$X$4,'实盘净值数据(iFinD公式)'!$B6:$X6/'实盘净值数据(iFinD公式)'!$B$6:$X$6,'实盘净值数据(iFinD公式)'!$B7:$X7/'实盘净值数据(iFinD公式)'!$B6:$X6)/SUMPRODUCT(实盘持仓配置!$B$4:$X$4,'实盘净值数据(iFinD公式)'!$B6:$X6/'实盘净值数据(iFinD公式)'!$B$6:$X$6))*(1-实盘持仓配置!$Z$4)^(('实盘净值数据(iFinD公式)'!$A7-'实盘净值数据(iFinD公式)'!$A6)/365)-1) -> -0.019576812 | D7: =IF(B7="","",B7/MAX(B$5:B7)-1) -> -0.019576812 | E7: =IF(OR((ROW()-1)<5,'实盘净值数据(iFinD公式)'!$A7="",'实盘净值数据(iFinD公式)'!$B7=""),"",SUMPRODUCT(实盘持仓配置!$B$5:$X$5,'实盘净值数据(iFinD公式)'!$B7:$X7/'实盘净值数据(iFinD公式)'!$B$5:$X$5)*(1-实盘持仓配置!$Z$5)^(('实盘净值数据(iFinD公式)'!$A7-'实盘净值数据(iFinD公式)'!$A$5)/365)) -> 1.0033379 | F7: =IF(OR(E6="",'实盘净值数据(iFinD公式)'!$A7="",'实盘净值数据(iFinD公式)'!$B7=""),"",(SUMPRODUCT(实盘持仓配置!$B$5:$X$5,'实盘净值数据(iFinD公式)'!$B6:$X6/'实盘净值数据(iFinD公式)'!$B$5:$X$5,'实盘净值数据(iFinD公式)'!$B7:$X7/'实盘净值数据(iFinD公式)'!$B6:$X6)/SUMPRODUCT(实盘持仓配置!$B$5:$X$5,'实盘净值数据(iFinD公式)'!$B6:$X6/'实盘净值数据(iFinD公式)'!$B$5:$X$5))*(1-实盘持仓配置!$Z$5)^(('实盘净值数据(iFinD公式)'!$A7-'实盘净值数据(iFinD公式)'!$A6)/365)-1) -> -0.019639287 | G7: =IF(E7="","",E7/MAX(E$5:E7)-1) -> -0.019639287 | H7: 1 | I7: =IF(OR(H6="",'实盘净值数据(iFinD公式)'!$A7="",'实盘净值数据(iFinD公式)'!$B7=""),"",(SUMPRODUCT(实盘持仓配置!$B$6:$X$6,'实盘净值数据(iFinD公式)'!$B6:$X6/'实盘净值数据(iFinD公式)'!$B$7:$X$7,'实盘净值数据(iFinD公式)'!$B7:$X7/'实盘净值数据(iFinD公式)'!$B6:$X6)/SUMPRODUCT(实盘持仓配置!$B$6:$X$6,'实盘净值数据(iFinD公式)'!$B6:$X6/'实盘净值数据(iFinD公式)'!$B$7:$X$7))*(1-实盘持仓配置!$Z$6)^(('实盘净值数据(iFinD公式)'!$A7-'实盘净值数据(iFinD公式)'!$A6)/365)-1) | J7: =IF(H7="","",H7/MAX(H$5:H7)-1) -> 0 | K7: =IF(OR((ROW()-1)<8,'实盘净值数据(iFinD公式)'!$A7="",'实盘净值数据(iFinD公式)'!$B7=""),"",SUMPRODUCT(实盘持仓配置!$B$7:$X$7,'实盘净值数据(iFinD公式)'!$B7:$X7/'实盘净值数据(iFinD公式)'!$B$8:$X$8)*(1-实盘持仓配置!$Z$7)^(('实盘净值数据(iFinD公式)'!$A7-'实盘净值数据(iFinD公式)'!$A$8)/365)) | L7: =IF(OR(K6="",'实盘净值数据(iFinD公式)'!$A7="",'实盘净值数据(iFinD公式)'!$B7=""),"",(SUMPRODUCT(实盘持仓配置!$B$7:$X$7,'实盘净值数据(iFinD公式)'!$B6:$X6/'实盘净值数据(iFinD公式)'!$B$8:$X$8,'实盘净值数据(iFinD公式)'!$B7:$X7/'实盘净值数据(iFinD公式)'!$B6:$X6)/SUMPRODUCT(实盘持仓配置!$B$7:$X$7,'实盘净值数据(iFinD公式)'!$B6:$X6/'实盘净值数据(iFinD公式)'!$B$8:$X$8))*(1-实盘持仓配置!$Z$7)^(('实盘净值数据(iFinD公式)'!$A7-'实盘净值数据(iFinD公式)'!$A6)/365)-1) | M7: =IF(K7="","",K7/MAX(K$5:K7)-1) | N7: =IF(OR((ROW()-1)<5,'实盘净值数据(iFinD公式)'!$A7="",'实盘净值数据(iFinD公式)'!$B7=""),"",SUMPRODUCT(实盘持仓配置!$B$8:$X$8,'实盘净值数据(iFinD公式)'!$B7:$X7/'实盘净值数据(iFinD公式)'!$B$5:$X$5)*(1-实盘持仓配置!$Z$8)^(('实盘净值数据(iFinD公式)'!$A7-'实盘净值数据(iFinD公式)'!$A$5)/365)) -> 0.99782264 | O7: =IF(OR(N6="",'实盘净值数据(iFinD公式)'!$A7="",'实盘净值数据(iFinD公式)'!$B7=""),"",(SUMPRODUCT(实盘持仓配置!$B$8:$X$8,'实盘净值数据(iFinD公式)'!$B6:$X6/'实盘净值数据(iFinD公式)'!$B$5:$X$5,'实盘净值数据(iFinD公式)'!$B7:$X7/'实盘净值数据(iFinD公式)'!$B6:$X6)/SUMPRODUCT(实盘持仓配置!$B$8:$X$8,'实盘净值数据(iFinD公式)'!$B6:$X6/'实盘净值数据(iFinD公式)'!$B$5:$X$5))*(1-实盘持仓配置!$Z$8)^(('实盘净值数据(iFinD公式)'!$A7-'实盘净值数据(iFinD公式)'!$A6)/365)-1) -> -0.0030701438 | P7: =IF(N7="","",N7/MAX(N$5:N7)-1) -> -0.0030701438 | Q7: =IF(OR((ROW()-1)<8,'实盘净值数据(iFinD公式)'!$A7="",'实盘净值数据(iFinD公式)'!$B7=""),"",SUMPRODUCT(实盘持仓配置!$B$9:$X$9,'实盘净值数据(iFinD公式)'!$B7:$X7/'实盘净值数据(iFinD公式)'!$B$8:$X$8)*(1-实盘持仓配置!$Z$9)^(('实盘净值数据(iFinD公式)'!$A7-'实盘净值数据(iFinD公式)'!$A$8)/365)) | R7: =IF(OR(Q6="",'实盘净值数据(iFinD公式)'!$A7="",'实盘净值数据(iFinD公式)'!$B7=""),"",(SUMPRODUCT(实盘持仓配置!$B$9:$X$9,'实盘净值数据(iFinD公式)'!$B6:$X6/'实盘净值数据(iFinD公式)'!$B$8:$X$8,'实盘净值数据(iFinD公式)'!$B7:$X7/'实盘净值数据(iFinD公式)'!$B6:$X6)/SUMPRODUCT(实盘持仓配置!$B$9:$X$9,'实盘净值数据(iFinD公式)'!$B6:$X6/'实盘净值数据(iFinD公式)'!$B$8:$X$8))*(1-实盘持仓配置!$Z$9)^(('实盘净值数据(iFinD公式)'!$A7-'实盘净值数据(iFinD公式)'!$A6)/365)-1) | S7: =IF(Q7="","",Q7/MAX(Q$5:Q7)-1)
A8: =IF('实盘净值数据(iFinD公式)'!A8="","",'实盘净值数据(iFinD公式)'!A8) -> 46197 | B8: =IF(OR((ROW()-1)<6,'实盘净值数据(iFinD公式)'!$A8="",'实盘净值数据(iFinD公式)'!$B8=""),"",SUMPRODUCT(实盘持仓配置!$B$4:$X$4,'实盘净值数据(iFinD公式)'!$B8:$X8/'实盘净值数据(iFinD公式)'!$B$6:$X$6)*(1-实盘持仓配置!$Z$4)^(('实盘净值数据(iFinD公式)'!$A8-'实盘净值数据(iFinD公式)'!$A$6)/365)) -> 1.0160197 | C8: =IF(OR(B7="",'实盘净值数据(iFinD公式)'!$A8="",'实盘净值数据(iFinD公式)'!$B8=""),"",(SUMPRODUCT(实盘持仓配置!$B$4:$X$4,'实盘净值数据(iFinD公式)'!$B7:$X7/'实盘净值数据(iFinD公式)'!$B$6:$X$6,'实盘净值数据(iFinD公式)'!$B8:$X8/'实盘净值数据(iFinD公式)'!$B7:$X7)/SUMPRODUCT(实盘持仓配置!$B$4:$X$4,'实盘净值数据(iFinD公式)'!$B7:$X7/'实盘净值数据(iFinD公式)'!$B$6:$X$6))*(1-实盘持仓配置!$Z$4)^(('实盘净值数据(iFinD公式)'!$A8-'实盘净值数据(iFinD公式)'!$A7)/365)-1) -> 0.036307314 | D8: =IF(B8="","",B8/MAX(B$5:B8)-1) -> 0 | E8: =IF(OR((ROW()-1)<5,'实盘净值数据(iFinD公式)'!$A8="",'实盘净值数据(iFinD公式)'!$B8=""),"",SUMPRODUCT(实盘持仓配置!$B$5:$X$5,'实盘净值数据(iFinD公式)'!$B8:$X8/'实盘净值数据(iFinD公式)'!$B$5:$X$5)*(1-实盘持仓配置!$Z$5)^(('实盘净值数据(iFinD公式)'!$A8-'实盘净值数据(iFinD公式)'!$A$5)/365)) -> 1.0397127 | F8: =IF(OR(E7="",'实盘净值数据(iFinD公式)'!$A8="",'实盘净值数据(iFinD公式)'!$B8=""),"",(SUMPRODUCT(实盘持仓配置!$B$5:$X$5,'实盘净值数据(iFinD公式)'!$B7:$X7/'实盘净值数据(iFinD公式)'!$B$5:$X$5,'实盘净值数据(iFinD公式)'!$B8:$X8/'实盘净值数据(iFinD公式)'!$B7:$X7)/SUMPRODUCT(实盘持仓配置!$B$5:$X$5,'实盘净值数据(iFinD公式)'!$B7:$X7/'实盘净值数据(iFinD公式)'!$B$5:$X$5))*(1-实盘持仓配置!$Z$5)^(('实盘净值数据(iFinD公式)'!$A8-'实盘净值数据(iFinD公式)'!$A7)/365)-1) -> 0.036253775 | G8: =IF(E8="","",E8/MAX(E$5:E8)-1) -> 0 | H8: =IF(OR((ROW()-1)<7,'实盘净值数据(iFinD公式)'!$A8="",'实盘净值数据(iFinD公式)'!$B8=""),"",SUMPRODUCT(实盘持仓配置!$B$6:$X$6,'实盘净值数据(iFinD公式)'!$B8:$X8/'实盘净值数据(iFinD公式)'!$B$7:$X$7)*(1-实盘持仓配置!$Z$6)^(('实盘净值数据(iFinD公式)'!$A8-'实盘净值数据(iFinD公式)'!$A$7)/365)) -> 1.039203 | I8: =IF(OR(H7="",'实盘净值数据(iFinD公式)'!$A8="",'实盘净值数据(iFinD公式)'!$B8=""),"",(SUMPRODUCT(实盘持仓配置!$B$6:$X$6,'实盘净值数据(iFinD公式)'!$B7:$X7/'实盘净值数据(iFinD公式)'!$B$7:$X$7,'实盘净值数据(iFinD公式)'!$B8:$X8/'实盘净值数据(iFinD公式)'!$B7:$X7)/SUMPRODUCT(实盘持仓配置!$B$6:$X$6,'实盘净值数据(iFinD公式)'!$B7:$X7/'实盘净值数据(iFinD公式)'!$B$7:$X$7))*(1-实盘持仓配置!$Z$6)^(('实盘净值数据(iFinD公式)'!$A8-'实盘净值数据(iFinD公式)'!$A7)/365)-1) -> 0.039202963 | J8: =IF(H8="","",H8/MAX(H$5:H8)-1) -> 0 | K8: 1 | L8: =IF(OR(K7="",'实盘净值数据(iFinD公式)'!$A8="",'实盘净值数据(iFinD公式)'!$B8=""),"",(SUMPRODUCT(实盘持仓配置!$B$7:$X$7,'实盘净值数据(iFinD公式)'!$B7:$X7/'实盘净值数据(iFinD公式)'!$B$8:$X$8,'实盘净值数据(iFinD公式)'!$B8:$X8/'实盘净值数据(iFinD公式)'!$B7:$X7)/SUMPRODUCT(实盘持仓配置!$B$7:$X$7,'实盘净值数据(iFinD公式)'!$B7:$X7/'实盘净值数据(iFinD公式)'!$B$8:$X$8))*(1-实盘持仓配置!$Z$7)^(('实盘净值数据(iFinD公式)'!$A8-'实盘净值数据(iFinD公式)'!$A7)/365)-1) | M8: =IF(K8="","",K8/MAX(K$5:K8)-1) -> 0 | N8: =IF(OR((ROW()-1)<5,'实盘净值数据(iFinD公式)'!$A8="",'实盘净值数据(iFinD公式)'!$B8=""),"",SUMPRODUCT(实盘持仓配置!$B$8:$X$8,'实盘净值数据(iFinD公式)'!$B8:$X8/'实盘净值数据(iFinD公式)'!$B$5:$X$5)*(1-实盘持仓配置!$Z$8)^(('实盘净值数据(iFinD公式)'!$A8-'实盘净值数据(iFinD公式)'!$A$5)/365)) -> 0.99977057 | O8: =IF(OR(N7="",'实盘净值数据(iFinD公式)'!$A8="",'实盘净值数据(iFinD公式)'!$B8=""),"",(SUMPRODUCT(实盘持仓配置!$B$8:$X$8,'实盘净值数据(iFinD公式)'!$B7:$X7/'实盘净值数据(iFinD公式)'!$B$5:$X$5,'实盘净值数据(iFinD公式)'!$B8:$X8/'实盘净值数据(iFinD公式)'!$B7:$X7)/SUMPRODUCT(实盘持仓配置!$B$8:$X$8,'实盘净值数据(iFinD公式)'!$B7:$X7/'实盘净值数据(iFinD公式)'!$B$5:$X$5))*(1-实盘持仓配置!$Z$8)^(('实盘净值数据(iFinD公式)'!$A8-'实盘净值数据(iFinD公式)'!$A7)/365)-1) -> 0.001952181 | P8: =IF(N8="","",N8/MAX(N$5:N8)-1) -> -0.0011239563 | Q8: 1 | R8: =IF(OR(Q7="",'实盘净值数据(iFinD公式)'!$A8="",'实盘净值数据(iFinD公式)'!$B8=""),"",(SUMPRODUCT(实盘持仓配置!$B$9:$X$9,'实盘净值数据(iFinD公式)'!$B7:$X7/'实盘净值数据(iFinD公式)'!$B$8:$X$8,'实盘净值数据(iFinD公式)'!$B8:$X8/'实盘净值数据(iFinD公式)'!$B7:$X7)/SUMPRODUCT(实盘持仓配置!$B$9:$X$9,'实盘净值数据(iFinD公式)'!$B7:$X7/'实盘净值数据(iFinD公式)'!$B$8:$X$8))*(1-实盘持仓配置!$Z$9)^(('实盘净值数据(iFinD公式)'!$A8-'实盘净值数据(iFinD公式)'!$A7)/365)-1) | S8: =IF(Q8="","",Q8/MAX(Q$5:Q8)-1) -> 0
A9: =IF('实盘净值数据(iFinD公式)'!A9="","",'实盘净值数据(iFinD公式)'!A9) -> 46198 | B9: =IF(OR((ROW()-1)<6,'实盘净值数据(iFinD公式)'!$A9="",'实盘净值数据(iFinD公式)'!$B9=""),"",SUMPRODUCT(实盘持仓配置!$B$4:$X$4,'实盘净值数据(iFinD公式)'!$B9:$X9/'实盘净值数据(iFinD公式)'!$B$6:$X$6)*(1-实盘持仓配置!$Z$4)^(('实盘净值数据(iFinD公式)'!$A9-'实盘净值数据(iFinD公式)'!$A$6)/365)) -> 1.0494432 | C9: =IF(OR(B8="",'实盘净值数据(iFinD公式)'!$A9="",'实盘净值数据(iFinD公式)'!$B9=""),"",(SUMPRODUCT(实盘持仓配置!$B$4:$X$4,'实盘净值数据(iFinD公式)'!$B8:$X8/'实盘净值数据(iFinD公式)'!$B$6:$X$6,'实盘净值数据(iFinD公式)'!$B9:$X9/'实盘净值数据(iFinD公式)'!$B8:$X8)/SUMPRODUCT(实盘持仓配置!$B$4:$X$4,'实盘净值数据(iFinD公式)'!$B8:$X8/'实盘净值数据(iFinD公式)'!$B$6:$X$6))*(1-实盘持仓配置!$Z$4)^(('实盘净值数据(iFinD公式)'!$A9-'实盘净值数据(iFinD公式)'!$A8)/365)-1) -> 0.032896442 | D9: =IF(B9="","",B9/MAX(B$5:B9)-1) -> 0 | E9: =IF(OR((ROW()-1)<5,'实盘净值数据(iFinD公式)'!$A9="",'实盘净值数据(iFinD公式)'!$B9=""),"",SUMPRODUCT(实盘持仓配置!$B$5:$X$5,'实盘净值数据(iFinD公式)'!$B9:$X9/'实盘净值数据(iFinD公式)'!$B$5:$X$5)*(1-实盘持仓配置!$Z$5)^(('实盘净值数据(iFinD公式)'!$A9-'实盘净值数据(iFinD公式)'!$A$5)/365)) -> 1.0739445 | F9: =IF(OR(E8="",'实盘净值数据(iFinD公式)'!$A9="",'实盘净值数据(iFinD公式)'!$B9=""),"",(SUMPRODUCT(实盘持仓配置!$B$5:$X$5,'实盘净值数据(iFinD公式)'!$B8:$X8/'实盘净值数据(iFinD公式)'!$B$5:$X$5,'实盘净值数据(iFinD公式)'!$B9:$X9/'实盘净值数据(iFinD公式)'!$B8:$X8)/SUMPRODUCT(实盘持仓配置!$B$5:$X$5,'实盘净值数据(iFinD公式)'!$B8:$X8/'实盘净值数据(iFinD公式)'!$B$5:$X$5))*(1-实盘持仓配置!$Z$5)^(('实盘净值数据(iFinD公式)'!$A9-'实盘净值数据(iFinD公式)'!$A8)/365)-1) -> 0.032924343 | G9: =IF(E9="","",E9/MAX(E$5:E9)-1) -> 0 | H9: =IF(OR((ROW()-1)<7,'实盘净值数据(iFinD公式)'!$A9="",'实盘净值数据(iFinD公式)'!$B9=""),"",SUMPRODUCT(实盘持仓配置!$B$6:$X$6,'实盘净值数据(iFinD公式)'!$B9:$X9/'实盘净值数据(iFinD公式)'!$B$7:$X$7)*(1-实盘持仓配置!$Z$6)^(('实盘净值数据(iFinD公式)'!$A9-'实盘净值数据(iFinD公式)'!$A$7)/365)) -> 1.0741076 | I9: =IF(OR(H8="",'实盘净值数据(iFinD公式)'!$A9="",'实盘净值数据(iFinD公式)'!$B9=""),"",(SUMPRODUCT(实盘持仓配置!$B$6:$X$6,'实盘净值数据(iFinD公式)'!$B8:$X8/'实盘净值数据(iFinD公式)'!$B$7:$X$7,'实盘净值数据(iFinD公式)'!$B9:$X9/'实盘净值数据(iFinD公式)'!$B8:$X8)/SUMPRODUCT(实盘持仓配置!$B$6:$X$6,'实盘净值数据(iFinD公式)'!$B8:$X8/'实盘净值数据(iFinD公式)'!$B$7:$X$7))*(1-实盘持仓配置!$Z$6)^(('实盘净值数据(iFinD公式)'!$A9-'实盘净值数据(iFinD公式)'!$A8)/365)-1) -> 0.033587935 | J9: =IF(H9="","",H9/MAX(H$5:H9)-1) -> 0 | K9: =IF(OR((ROW()-1)<8,'实盘净值数据(iFinD公式)'!$A9="",'实盘净值数据(iFinD公式)'!$B9=""),"",SUMPRODUCT(实盘持仓配置!$B$7:$X$7,'实盘净值数据(iFinD公式)'!$B9:$X9/'实盘净值数据(iFinD公式)'!$B$8:$X$8)*(1-实盘持仓配置!$Z$7)^(('实盘净值数据(iFinD公式)'!$A9-'实盘净值数据(iFinD公式)'!$A$8)/365)) -> 1.0014142 | L9: =IF(OR(K8="",'实盘净值数据(iFinD公式)'!$A9="",'实盘净值数据(iFinD公式)'!$B9=""),"",(SUMPRODUCT(实盘持仓配置!$B$7:$X$7,'实盘净值数据(iFinD公式)'!$B8:$X8/'实盘净值数据(iFinD公式)'!$B$8:$X$8,'实盘净值数据(iFinD公式)'!$B9:$X9/'实盘净值数据(iFinD公式)'!$B8:$X8)/SUMPRODUCT(实盘持仓配置!$B$7:$X$7,'实盘净值数据(iFinD公式)'!$B8:$X8/'实盘净值数据(iFinD公式)'!$B$8:$X$8))*(1-实盘持仓配置!$Z$7)^(('实盘净值数据(iFinD公式)'!$A9-'实盘净值数据(iFinD公式)'!$A8)/365)-1) -> 0.0014141946 | M9: =IF(K9="","",K9/MAX(K$5:K9)-1) -> 0 | N9: =IF(OR((ROW()-1)<5,'实盘净值数据(iFinD公式)'!$A9="",'实盘净值数据(iFinD公式)'!$B9=""),"",SUMPRODUCT(实盘持仓配置!$B$8:$X$8,'实盘净值数据(iFinD公式)'!$B9:$X9/'实盘净值数据(iFinD公式)'!$B$5:$X$5)*(1-实盘持仓配置!$Z$8)^(('实盘净值数据(iFinD公式)'!$A9-'实盘净值数据(iFinD公式)'!$A$5)/365)) -> 1.001278 | O9: =IF(OR(N8="",'实盘净值数据(iFinD公式)'!$A9="",'实盘净值数据(iFinD公式)'!$B9=""),"",(SUMPRODUCT(实盘持仓配置!$B$8:$X$8,'实盘净值数据(iFinD公式)'!$B8:$X8/'实盘净值数据(iFinD公式)'!$B$5:$X$5,'实盘净值数据(iFinD公式)'!$B9:$X9/'实盘净值数据(iFinD公式)'!$B8:$X8)/SUMPRODUCT(实盘持仓配置!$B$8:$X$8,'实盘净值数据(iFinD公式)'!$B8:$X8/'实盘净值数据(iFinD公式)'!$B$5:$X$5))*(1-实盘持仓配置!$Z$8)^(('实盘净值数据(iFinD公式)'!$A9-'实盘净值数据(iFinD公式)'!$A8)/365)-1) -> 0.0015077592 | P9: =IF(N9="","",N9/MAX(N$5:N9)-1) -> 0 | Q9: =IF(OR((ROW()-1)<8,'实盘净值数据(iFinD公式)'!$A9="",'实盘净值数据(iFinD公式)'!$B9=""),"",SUMPRODUCT(实盘持仓配置!$B$9:$X$9,'实盘净值数据(iFinD公式)'!$B9:$X9/'实盘净值数据(iFinD公式)'!$B$8:$X$8)*(1-实盘持仓配置!$Z$9)^(('实盘净值数据(iFinD公式)'!$A9-'实盘净值数据(iFinD公式)'!$A$8)/365)) -> 1.0039732 | R9: =IF(OR(Q8="",'实盘净值数据(iFinD公式)'!$A9="",'实盘净值数据(iFinD公式)'!$B9=""),"",(SUMPRODUCT(实盘持仓配置!$B$9:$X$9,'实盘净值数据(iFinD公式)'!$B8:$X8/'实盘净值数据(iFinD公式)'!$B$8:$X$8,'实盘净值数据(iFinD公式)'!$B9:$X9/'实盘净值数据(iFinD公式)'!$B8:$X8)/SUMPRODUCT(实盘持仓配置!$B$9:$X$9,'实盘净值数据(iFinD公式)'!$B8:$X8/'实盘净值数据(iFinD公式)'!$B$8:$X$8))*(1-实盘持仓配置!$Z$9)^(('实盘净值数据(iFinD公式)'!$A9-'实盘净值数据(iFinD公式)'!$A8)/365)-1) -> 0.0039732082 | S9: =IF(Q9="","",Q9/MAX(Q$5:Q9)-1) -> 0
A10: =IF('实盘净值数据(iFinD公式)'!A10="","",'实盘净值数据(iFinD公式)'!A10) -> 46199 | B10: =IF(OR((ROW()-1)<6,'实盘净值数据(iFinD公式)'!$A10="",'实盘净值数据(iFinD公式)'!$B10=""),"",SUMPRODUCT(实盘持仓配置!$B$4:$X$4,'实盘净值数据(iFinD公式)'!$B10:$X10/'实盘净值数据(iFinD公式)'!$B$6:$X$6)*(1-实盘持仓配置!$Z$4)^(('实盘净值数据(iFinD公式)'!$A10-'实盘净值数据(iFinD公式)'!$A$6)/365)) -> 1.0194457 | C10: =IF(OR(B9="",'实盘净值数据(iFinD公式)'!$A10="",'实盘净值数据(iFinD公式)'!$B10=""),"",(SUMPRODUCT(实盘持仓配置!$B$4:$X$4,'实盘净值数据(iFinD公式)'!$B9:$X9/'实盘净值数据(iFinD公式)'!$B$6:$X$6,'实盘净值数据(iFinD公式)'!$B10:$X10/'实盘净值数据(iFinD公式)'!$B9:$X9)/SUMPRODUCT(实盘持仓配置!$B$4:$X$4,'实盘净值数据(iFinD公式)'!$B9:$X9/'实盘净值数据(iFinD公式)'!$B$6:$X$6))*(1-实盘持仓配置!$Z$4)^(('实盘净值数据(iFinD公式)'!$A10-'实盘净值数据(iFinD公式)'!$A9)/365)-1) -> -0.028584129 | D10: =IF(B10="","",B10/MAX(B$5:B10)-1) -> -0.028584129 | E10: =IF(OR((ROW()-1)<5,'实盘净值数据(iFinD公式)'!$A10="",'实盘净值数据(iFinD公式)'!$B10=""),"",SUMPRODUCT(实盘持仓配置!$B$5:$X$5,'实盘净值数据(iFinD公式)'!$B10:$X10/'实盘净值数据(iFinD公式)'!$B$5:$X$5)*(1-实盘持仓配置!$Z$5)^(('实盘净值数据(iFinD公式)'!$A10-'实盘净值数据(iFinD公式)'!$A$5)/365)) -> 1.0431452 | F10: =IF(OR(E9="",'实盘净值数据(iFinD公式)'!$A10="",'实盘净值数据(iFinD公式)'!$B10=""),"",(SUMPRODUCT(实盘持仓配置!$B$5:$X$5,'实盘净值数据(iFinD公式)'!$B9:$X9/'实盘净值数据(iFinD公式)'!$B$5:$X$5,'实盘净值数据(iFinD公式)'!$B10:$X10/'实盘净值数据(iFinD公式)'!$B9:$X9)/SUMPRODUCT(实盘持仓配置!$B$5:$X$5,'实盘净值数据(iFinD公式)'!$B9:$X9/'实盘净值数据(iFinD公式)'!$B$5:$X$5))*(1-实盘持仓配置!$Z$5)^(('实盘净值数据(iFinD公式)'!$A10-'实盘净值数据(iFinD公式)'!$A9)/365)-1) -> -0.028678715 | G10: =IF(E10="","",E10/MAX(E$5:E10)-1) -> -0.028678715 | H10: =IF(OR((ROW()-1)<7,'实盘净值数据(iFinD公式)'!$A10="",'实盘净值数据(iFinD公式)'!$B10=""),"",SUMPRODUCT(实盘持仓配置!$B$6:$X$6,'实盘净值数据(iFinD公式)'!$B10:$X10/'实盘净值数据(iFinD公式)'!$B$7:$X$7)*(1-实盘持仓配置!$Z$6)^(('实盘净值数据(iFinD公式)'!$A10-'实盘净值数据(iFinD公式)'!$A$7)/365)) -> 1.0506457 | I10: =IF(OR(H9="",'实盘净值数据(iFinD公式)'!$A10="",'实盘净值数据(iFinD公式)'!$B10=""),"",(SUMPRODUCT(实盘持仓配置!$B$6:$X$6,'实盘净值数据(iFinD公式)'!$B9:$X9/'实盘净值数据(iFinD公式)'!$B$7:$X$7,'实盘净值数据(iFinD公式)'!$B10:$X10/'实盘净值数据(iFinD公式)'!$B9:$X9)/SUMPRODUCT(实盘持仓配置!$B$6:$X$6,'实盘净值数据(iFinD公式)'!$B9:$X9/'实盘净值数据(iFinD公式)'!$B$7:$X$7))*(1-实盘持仓配置!$Z$6)^(('实盘净值数据(iFinD公式)'!$A10-'实盘净值数据(iFinD公式)'!$A9)/365)-1) -> -0.021843224 | J10: =IF(H10="","",H10/MAX(H$5:H10)-1) -> -0.021843224 | K10: =IF(OR((ROW()-1)<8,'实盘净值数据(iFinD公式)'!$A10="",'实盘净值数据(iFinD公式)'!$B10=""),"",SUMPRODUCT(实盘持仓配置!$B$7:$X$7,'实盘净值数据(iFinD公式)'!$B10:$X10/'实盘净值数据(iFinD公式)'!$B$8:$X$8)*(1-实盘持仓配置!$Z$7)^(('实盘净值数据(iFinD公式)'!$A10-'实盘净值数据(iFinD公式)'!$A$8)/365)) -> 0.99948223 | L10: =IF(OR(K9="",'实盘净值数据(iFinD公式)'!$A10="",'实盘净值数据(iFinD公式)'!$B10=""),"",(SUMPRODUCT(实盘持仓配置!$B$7:$X$7,'实盘净值数据(iFinD公式)'!$B9:$X9/'实盘净值数据(iFinD公式)'!$B$8:$X$8,'实盘净值数据(iFinD公式)'!$B10:$X10/'实盘净值数据(iFinD公式)'!$B9:$X9)/SUMPRODUCT(实盘持仓配置!$B$7:$X$7,'实盘净值数据(iFinD公式)'!$B9:$X9/'实盘净值数据(iFinD公式)'!$B$8:$X$8))*(1-实盘持仓配置!$Z$7)^(('实盘净值数据(iFinD公式)'!$A10-'实盘净值数据(iFinD公式)'!$A9)/365)-1) -> -0.0019292328 | M10: =IF(K10="","",K10/MAX(K$5:K10)-1) -> -0.0019292328 | N10: =IF(OR((ROW()-1)<5,'实盘净值数据(iFinD公式)'!$A10="",'实盘净值数据(iFinD公式)'!$B10=""),"",SUMPRODUCT(实盘持仓配置!$B$8:$X$8,'实盘净值数据(iFinD公式)'!$B10:$X10/'实盘净值数据(iFinD公式)'!$B$5:$X$5)*(1-实盘持仓配置!$Z$8)^(('实盘净值数据(iFinD公式)'!$A10-'实盘净值数据(iFinD公式)'!$A$5)/365)) -> 0.9989298 | O10: =IF(OR(N9="",'实盘净值数据(iFinD公式)'!$A10="",'实盘净值数据(iFinD公式)'!$B10=""),"",(SUMPRODUCT(实盘持仓配置!$B$8:$X$8,'实盘净值数据(iFinD公式)'!$B9:$X9/'实盘净值数据(iFinD公式)'!$B$5:$X$5,'实盘净值数据(iFinD公式)'!$B10:$X10/'实盘净值数据(iFinD公式)'!$B9:$X9)/SUMPRODUCT(实盘持仓配置!$B$8:$X$8,'实盘净值数据(iFinD公式)'!$B9:$X9/'实盘净值数据(iFinD公式)'!$B$5:$X$5))*(1-实盘持仓配置!$Z$8)^(('实盘净值数据(iFinD公式)'!$A10-'实盘净值数据(iFinD公式)'!$A9)/365)-1) -> -0.0023451843 | P10: =IF(N10="","",N10/MAX(N$5:N10)-1) -> -0.0023451843 | Q10: =IF(OR((ROW()-1)<8,'实盘净值数据(iFinD公式)'!$A10="",'实盘净值数据(iFinD公式)'!$B10=""),"",SUMPRODUCT(实盘持仓配置!$B$9:$X$9,'实盘净值数据(iFinD公式)'!$B10:$X10/'实盘净值数据(iFinD公式)'!$B$8:$X$8)*(1-实盘持仓配置!$Z$9)^(('实盘净值数据(iFinD公式)'!$A10-'实盘净值数据(iFinD公式)'!$A$8)/365)) -> 0.99720804 | R10: =IF(OR(Q9="",'实盘净值数据(iFinD公式)'!$A10="",'实盘净值数据(iFinD公式)'!$B10=""),"",(SUMPRODUCT(实盘持仓配置!$B$9:$X$9,'实盘净值数据(iFinD公式)'!$B9:$X9/'实盘净值数据(iFinD公式)'!$B$8:$X$8,'实盘净值数据(iFinD公式)'!$B10:$X10/'实盘净值数据(iFinD公式)'!$B9:$X9)/SUMPRODUCT(实盘持仓配置!$B$9:$X$9,'实盘净值数据(iFinD公式)'!$B9:$X9/'实盘净值数据(iFinD公式)'!$B$8:$X$8))*(1-实盘持仓配置!$Z$9)^(('实盘净值数据(iFinD公式)'!$A10-'实盘净值数据(iFinD公式)'!$A9)/365)-1) -> -0.0067383921 | S10: =IF(Q10="","",Q10/MAX(Q$5:Q10)-1) -> -0.0067383921
A11: =IF('实盘净值数据(iFinD公式)'!A11="","",'实盘净值数据(iFinD公式)'!A11) -> 46202 | B11: =IF(OR((ROW()-1)<6,'实盘净值数据(iFinD公式)'!$A11="",'实盘净值数据(iFinD公式)'!$B11=""),"",SUMPRODUCT(实盘持仓配置!$B$4:$X$4,'实盘净值数据(iFinD公式)'!$B11:$X11/'实盘净值数据(iFinD公式)'!$B$6:$X$6)*(1-实盘持仓配置!$Z$4)^(('实盘净值数据(iFinD公式)'!$A11-'实盘净值数据(iFinD公式)'!$A$6)/365)) -> 1.0294387 | C11: =IF(OR(B10="",'实盘净值数据(iFinD公式)'!$A11="",'实盘净值数据(iFinD公式)'!$B11=""),"",(SUMPRODUCT(实盘持仓配置!$B$4:$X$4,'实盘净值数据(iFinD公式)'!$B10:$X10/'实盘净值数据(iFinD公式)'!$B$6:$X$6,'实盘净值数据(iFinD公式)'!$B11:$X11/'实盘净值数据(iFinD公式)'!$B10:$X10)/SUMPRODUCT(实盘持仓配置!$B$4:$X$4,'实盘净值数据(iFinD公式)'!$B10:$X10/'实盘净值数据(iFinD公式)'!$B$6:$X$6))*(1-实盘持仓配置!$Z$4)^(('实盘净值数据(iFinD公式)'!$A11-'实盘净值数据(iFinD公式)'!$A10)/365)-1) -> 0.0098023153 | D11: =IF(B11="","",B11/MAX(B$5:B11)-1) -> -0.019062005 | E11: =IF(OR((ROW()-1)<5,'实盘净值数据(iFinD公式)'!$A11="",'实盘净值数据(iFinD公式)'!$B11=""),"",SUMPRODUCT(实盘持仓配置!$B$5:$X$5,'实盘净值数据(iFinD公式)'!$B11:$X11/'实盘净值数据(iFinD公式)'!$B$5:$X$5)*(1-实盘持仓配置!$Z$5)^(('实盘净值数据(iFinD公式)'!$A11-'实盘净值数据(iFinD公式)'!$A$5)/365)) -> 1.0532584 | F11: =IF(OR(E10="",'实盘净值数据(iFinD公式)'!$A11="",'实盘净值数据(iFinD公式)'!$B11=""),"",(SUMPRODUCT(实盘持仓配置!$B$5:$X$5,'实盘净值数据(iFinD公式)'!$B10:$X10/'实盘净值数据(iFinD公式)'!$B$5:$X$5,'实盘净值数据(iFinD公式)'!$B11:$X11/'实盘净值数据(iFinD公式)'!$B10:$X10)/SUMPRODUCT(实盘持仓配置!$B$5:$X$5,'实盘净值数据(iFinD公式)'!$B10:$X10/'实盘净值数据(iFinD公式)'!$B$5:$X$5))*(1-实盘持仓配置!$Z$5)^(('实盘净值数据(iFinD公式)'!$A11-'实盘净值数据(iFinD公式)'!$A10)/365)-1) -> 0.0096949189 | G11: =IF(E11="","",E11/MAX(E$5:E11)-1) -> -0.019261834 | H11: =IF(OR((ROW()-1)<7,'实盘净值数据(iFinD公式)'!$A11="",'实盘净值数据(iFinD公式)'!$B11=""),"",SUMPRODUCT(实盘持仓配置!$B$6:$X$6,'实盘净值数据(iFinD公式)'!$B11:$X11/'实盘净值数据(iFinD公式)'!$B$7:$X$7)*(1-实盘持仓配置!$Z$6)^(('实盘净值数据(iFinD公式)'!$A11-'实盘净值数据(iFinD公式)'!$A$7)/365)) -> 1.0685099 | I11: =IF(OR(H10="",'实盘净值数据(iFinD公式)'!$A11="",'实盘净值数据(iFinD公式)'!$B11=""),"",(SUMPRODUCT(实盘持仓配置!$B$6:$X$6,'实盘净值数据(iFinD公式)'!$B10:$X10/'实盘净值数据(iFinD公式)'!$B$7:$X$7,'实盘净值数据(iFinD公式)'!$B11:$X11/'实盘净值数据(iFinD公式)'!$B10:$X10)/SUMPRODUCT(实盘持仓配置!$B$6:$X$6,'实盘净值数据(iFinD公式)'!$B10:$X10/'实盘净值数据(iFinD公式)'!$B$7:$X$7))*(1-实盘持仓配置!$Z$6)^(('实盘净值数据(iFinD公式)'!$A11-'实盘净值数据(iFinD公式)'!$A10)/365)-1) -> 0.017003074 | J11: =IF(H11="","",H11/MAX(H$5:H11)-1) -> -0.0052115523 | K11: =IF(OR((ROW()-1)<8,'实盘净值数据(iFinD公式)'!$A11="",'实盘净值数据(iFinD公式)'!$B11=""),"",SUMPRODUCT(实盘持仓配置!$B$7:$X$7,'实盘净值数据(iFinD公式)'!$B11:$X11/'实盘净值数据(iFinD公式)'!$B$8:$X$8)*(1-实盘持仓配置!$Z$7)^(('实盘净值数据(iFinD公式)'!$A11-'实盘净值数据(iFinD公式)'!$A$8)/365)) -> 1.0013814 | L11: =IF(OR(K10="",'实盘净值数据(iFinD公式)'!$A11="",'实盘净值数据(iFinD公式)'!$B11=""),"",(SUMPRODUCT(实盘持仓配置!$B$7:$X$7,'实盘净值数据(iFinD公式)'!$B10:$X10/'实盘净值数据(iFinD公式)'!$B$8:$X$8,'实盘净值数据(iFinD公式)'!$B11:$X11/'实盘净值数据(iFinD公式)'!$B10:$X10)/SUMPRODUCT(实盘持仓配置!$B$7:$X$7,'实盘净值数据(iFinD公式)'!$B10:$X10/'实盘净值数据(iFinD公式)'!$B$8:$X$8))*(1-实盘持仓配置!$Z$7)^(('实盘净值数据(iFinD公式)'!$A11-'实盘净值数据(iFinD公式)'!$A10)/365)-1) -> 0.0019001106 | M11: =IF(K11="","",K11/MAX(K$5:K11)-1) -> -3.2787891e-05 | N11: =IF(OR((ROW()-1)<5,'实盘净值数据(iFinD公式)'!$A11="",'实盘净值数据(iFinD公式)'!$B11=""),"",SUMPRODUCT(实盘持仓配置!$B$8:$X$8,'实盘净值数据(iFinD公式)'!$B11:$X11/'实盘净值数据(iFinD公式)'!$B$5:$X$5)*(1-实盘持仓配置!$Z$8)^(('实盘净值数据(iFinD公式)'!$A11-'实盘净值数据(iFinD公式)'!$A$5)/365)) -> 1.000521 | O11: =IF(OR(N10="",'实盘净值数据(iFinD公式)'!$A11="",'实盘净值数据(iFinD公式)'!$B11=""),"",(SUMPRODUCT(实盘持仓配置!$B$8:$X$8,'实盘净值数据(iFinD公式)'!$B10:$X10/'实盘净值数据(iFinD公式)'!$B$5:$X$5,'实盘净值数据(iFinD公式)'!$B11:$X11/'实盘净值数据(iFinD公式)'!$B10:$X10)/SUMPRODUCT(实盘持仓配置!$B$8:$X$8,'实盘净值数据(iFinD公式)'!$B10:$X10/'实盘净值数据(iFinD公式)'!$B$5:$X$5))*(1-实盘持仓配置!$Z$8)^(('实盘净值数据(iFinD公式)'!$A11-'实盘净值数据(iFinD公式)'!$A10)/365)-1) -> 0.0015929539 | P11: =IF(N11="","",N11/MAX(N$5:N11)-1) -> -0.00075596623 | Q11: =IF(OR((ROW()-1)<8,'实盘净值数据(iFinD公式)'!$A11="",'实盘净值数据(iFinD公式)'!$B11=""),"",SUMPRODUCT(实盘持仓配置!$B$9:$X$9,'实盘净值数据(iFinD公式)'!$B11:$X11/'实盘净值数据(iFinD公式)'!$B$8:$X$8)*(1-实盘持仓配置!$Z$9)^(('实盘净值数据(iFinD公式)'!$A11-'实盘净值数据(iFinD公式)'!$A$8)/365)) -> 1.0009806 | R11: =IF(OR(Q10="",'实盘净值数据(iFinD公式)'!$A11="",'实盘净值数据(iFinD公式)'!$B11=""),"",(SUMPRODUCT(实盘持仓配置!$B$9:$X$9,'实盘净值数据(iFinD公式)'!$B10:$X10/'实盘净值数据(iFinD公式)'!$B$8:$X$8,'实盘净值数据(iFinD公式)'!$B11:$X11/'实盘净值数据(iFinD公式)'!$B10:$X10)/SUMPRODUCT(实盘持仓配置!$B$9:$X$9,'实盘净值数据(iFinD公式)'!$B10:$X10/'实盘净值数据(iFinD公式)'!$B$8:$X$8))*(1-实盘持仓配置!$Z$9)^(('实盘净值数据(iFinD公式)'!$A11-'实盘净值数据(iFinD公式)'!$A10)/365)-1) -> 0.0037831247 | S11: =IF(Q11="","",Q11/MAX(Q$5:Q11)-1) -> -0.0029807597
A12: =IF('实盘净值数据(iFinD公式)'!A12="","",'实盘净值数据(iFinD公式)'!A12) -> 46203 | B12: =IF(OR((ROW()-1)<6,'实盘净值数据(iFinD公式)'!$A12="",'实盘净值数据(iFinD公式)'!$B12=""),"",SUMPRODUCT(实盘持仓配置!$B$4:$X$4,'实盘净值数据(iFinD公式)'!$B12:$X12/'实盘净值数据(iFinD公式)'!$B$6:$X$6)*(1-实盘持仓配置!$Z$4)^(('实盘净值数据(iFinD公式)'!$A12-'实盘净值数据(iFinD公式)'!$A$6)/365)) -> 1.0748479 | C12: =IF(OR(B11="",'实盘净值数据(iFinD公式)'!$A12="",'实盘净值数据(iFinD公式)'!$B12=""),"",(SUMPRODUCT(实盘持仓配置!$B$4:$X$4,'实盘净值数据(iFinD公式)'!$B11:$X11/'实盘净值数据(iFinD公式)'!$B$6:$X$6,'实盘净值数据(iFinD公式)'!$B12:$X12/'实盘净值数据(iFinD公式)'!$B11:$X11)/SUMPRODUCT(实盘持仓配置!$B$4:$X$4,'实盘净值数据(iFinD公式)'!$B11:$X11/'实盘净值数据(iFinD公式)'!$B$6:$X$6))*(1-实盘持仓配置!$Z$4)^(('实盘净值数据(iFinD公式)'!$A12-'实盘净值数据(iFinD公式)'!$A11)/365)-1) -> 0.044110687 | D12: =IF(B12="","",B12/MAX(B$5:B12)-1) -> 0 | E12: =IF(OR((ROW()-1)<5,'实盘净值数据(iFinD公式)'!$A12="",'实盘净值数据(iFinD公式)'!$B12=""),"",SUMPRODUCT(实盘持仓配置!$B$5:$X$5,'实盘净值数据(iFinD公式)'!$B12:$X12/'实盘净值数据(iFinD公式)'!$B$5:$X$5)*(1-实盘持仓配置!$Z$5)^(('实盘净值数据(iFinD公式)'!$A12-'实盘净值数据(iFinD公式)'!$A$5)/365)) -> 1.0997369 | F12: =IF(OR(E11="",'实盘净值数据(iFinD公式)'!$A12="",'实盘净值数据(iFinD公式)'!$B12=""),"",(SUMPRODUCT(实盘持仓配置!$B$5:$X$5,'实盘净值数据(iFinD公式)'!$B11:$X11/'实盘净值数据(iFinD公式)'!$B$5:$X$5,'实盘净值数据(iFinD公式)'!$B12:$X12/'实盘净值数据(iFinD公式)'!$B11:$X11)/SUMPRODUCT(实盘持仓配置!$B$5:$X$5,'实盘净值数据(iFinD公式)'!$B11:$X11/'实盘净值数据(iFinD公式)'!$B$5:$X$5))*(1-实盘持仓配置!$Z$5)^(('实盘净值数据(iFinD公式)'!$A12-'实盘净值数据(iFinD公式)'!$A11)/365)-1) -> 0.044128278 | G12: =IF(E12="","",E12/MAX(E$5:E12)-1) -> 0 | H12: =IF(OR((ROW()-1)<7,'实盘净值数据(iFinD公式)'!$A12="",'实盘净值数据(iFinD公式)'!$B12=""),"",SUMPRODUCT(实盘持仓配置!$B$6:$X$6,'实盘净值数据(iFinD公式)'!$B12:$X12/'实盘净值数据(iFinD公式)'!$B$7:$X$7)*(1-实盘持仓配置!$Z$6)^(('实盘净值数据(iFinD公式)'!$A12-'实盘净值数据(iFinD公式)'!$A$7)/365)) -> 1.1117067 | I12: =IF(OR(H11="",'实盘净值数据(iFinD公式)'!$A12="",'实盘净值数据(iFinD公式)'!$B12=""),"",(SUMPRODUCT(实盘持仓配置!$B$6:$X$6,'实盘净值数据(iFinD公式)'!$B11:$X11/'实盘净值数据(iFinD公式)'!$B$7:$X$7,'实盘净值数据(iFinD公式)'!$B12:$X12/'实盘净值数据(iFinD公式)'!$B11:$X11)/SUMPRODUCT(实盘持仓配置!$B$6:$X$6,'实盘净值数据(iFinD公式)'!$B11:$X11/'实盘净值数据(iFinD公式)'!$B$7:$X$7))*(1-实盘持仓配置!$Z$6)^(('实盘净值数据(iFinD公式)'!$A12-'实盘净值数据(iFinD公式)'!$A11)/365)-1) -> 0.04042716 | J12: =IF(H12="","",H12/MAX(H$5:H12)-1) -> 0 | K12: =IF(OR((ROW()-1)<8,'实盘净值数据(iFinD公式)'!$A12="",'实盘净值数据(iFinD公式)'!$B12=""),"",SUMPRODUCT(实盘持仓配置!$B$7:$X$7,'实盘净值数据(iFinD公式)'!$B12:$X12/'实盘净值数据(iFinD公式)'!$B$8:$X$8)*(1-实盘持仓配置!$Z$7)^(('实盘净值数据(iFinD公式)'!$A12-'实盘净值数据(iFinD公式)'!$A$8)/365)) -> 1.003272 | L12: =IF(OR(K11="",'实盘净值数据(iFinD公式)'!$A12="",'实盘净值数据(iFinD公式)'!$B12=""),"",(SUMPRODUCT(实盘持仓配置!$B$7:$X$7,'实盘净值数据(iFinD公式)'!$B11:$X11/'实盘净值数据(iFinD公式)'!$B$8:$X$8,'实盘净值数据(iFinD公式)'!$B12:$X12/'实盘净值数据(iFinD公式)'!$B11:$X11)/SUMPRODUCT(实盘持仓配置!$B$7:$X$7,'实盘净值数据(iFinD公式)'!$B11:$X11/'实盘净值数据(iFinD公式)'!$B$8:$X$8))*(1-实盘持仓配置!$Z$7)^(('实盘净值数据(iFinD公式)'!$A12-'实盘净值数据(iFinD公式)'!$A11)/365)-1) -> 0.0018880252 | M12: =IF(K12="","",K12/MAX(K$5:K12)-1) -> 0 | N12: =IF(OR((ROW()-1)<5,'实盘净值数据(iFinD公式)'!$A12="",'实盘净值数据(iFinD公式)'!$B12=""),"",SUMPRODUCT(实盘持仓配置!$B$8:$X$8,'实盘净值数据(iFinD公式)'!$B12:$X12/'实盘净值数据(iFinD公式)'!$B$5:$X$5)*(1-实盘持仓配置!$Z$8)^(('实盘净值数据(iFinD公式)'!$A12-'实盘净值数据(iFinD公式)'!$A$5)/365)) -> 1.0027101 | O12: =IF(OR(N11="",'实盘净值数据(iFinD公式)'!$A12="",'实盘净值数据(iFinD公式)'!$B12=""),"",(SUMPRODUCT(实盘持仓配置!$B$8:$X$8,'实盘净值数据(iFinD公式)'!$B11:$X11/'实盘净值数据(iFinD公式)'!$B$5:$X$5,'实盘净值数据(iFinD公式)'!$B12:$X12/'实盘净值数据(iFinD公式)'!$B11:$X11)/SUMPRODUCT(实盘持仓配置!$B$8:$X$8,'实盘净值数据(iFinD公式)'!$B11:$X11/'实盘净值数据(iFinD公式)'!$B$5:$X$5))*(1-实盘持仓配置!$Z$8)^(('实盘净值数据(iFinD公式)'!$A12-'实盘净值数据(iFinD公式)'!$A11)/365)-1) -> 0.0021879494 | P12: =IF(N12="","",N12/MAX(N$5:N12)-1) -> 0 | Q12: =IF(OR((ROW()-1)<8,'实盘净值数据(iFinD公式)'!$A12="",'实盘净值数据(iFinD公式)'!$B12=""),"",SUMPRODUCT(实盘持仓配置!$B$9:$X$9,'实盘净值数据(iFinD公式)'!$B12:$X12/'实盘净值数据(iFinD公式)'!$B$8:$X$8)*(1-实盘持仓配置!$Z$9)^(('实盘净值数据(iFinD公式)'!$A12-'实盘净值数据(iFinD公式)'!$A$8)/365)) -> 1.0087619 | R12: =IF(OR(Q11="",'实盘净值数据(iFinD公式)'!$A12="",'实盘净值数据(iFinD公式)'!$B12=""),"",(SUMPRODUCT(实盘持仓配置!$B$9:$X$9,'实盘净值数据(iFinD公式)'!$B11:$X11/'实盘净值数据(iFinD公式)'!$B$8:$X$8,'实盘净值数据(iFinD公式)'!$B12:$X12/'实盘净值数据(iFinD公式)'!$B11:$X11)/SUMPRODUCT(实盘持仓配置!$B$9:$X$9,'实盘净值数据(iFinD公式)'!$B11:$X11/'实盘净值数据(iFinD公式)'!$B$8:$X$8))*(1-实盘持仓配置!$Z$9)^(('实盘净值数据(iFinD公式)'!$A12-'实盘净值数据(iFinD公式)'!$A11)/365)-1) -> 0.0077736429 | S12: =IF(Q12="","",Q12/MAX(Q$5:Q12)-1) -> 0
A13: =IF('实盘净值数据(iFinD公式)'!A13="","",'实盘净值数据(iFinD公式)'!A13) -> 46204 | B13: =IF(OR((ROW()-1)<6,'实盘净值数据(iFinD公式)'!$A13="",'实盘净值数据(iFinD公式)'!$B13=""),"",SUMPRODUCT(实盘持仓配置!$B$4:$X$4,'实盘净值数据(iFinD公式)'!$B13:$X13/'实盘净值数据(iFinD公式)'!$B$6:$X$6)*(1-实盘持仓配置!$Z$4)^(('实盘净值数据(iFinD公式)'!$A13-'实盘净值数据(iFinD公式)'!$A$6)/365)) -> 1.0416673 | C13: =IF(OR(B12="",'实盘净值数据(iFinD公式)'!$A13="",'实盘净值数据(iFinD公式)'!$B13=""),"",(SUMPRODUCT(实盘持仓配置!$B$4:$X$4,'实盘净值数据(iFinD公式)'!$B12:$X12/'实盘净值数据(iFinD公式)'!$B$6:$X$6,'实盘净值数据(iFinD公式)'!$B13:$X13/'实盘净值数据(iFinD公式)'!$B12:$X12)/SUMPRODUCT(实盘持仓配置!$B$4:$X$4,'实盘净值数据(iFinD公式)'!$B12:$X12/'实盘净值数据(iFinD公式)'!$B$6:$X$6))*(1-实盘持仓配置!$Z$4)^(('实盘净值数据(iFinD公式)'!$A13-'实盘净值数据(iFinD公式)'!$A12)/365)-1) -> -0.030870027 | D13: =IF(B13="","",B13/MAX(B$5:B13)-1) -> -0.030870027 | E13: =IF(OR((ROW()-1)<5,'实盘净值数据(iFinD公式)'!$A13="",'实盘净值数据(iFinD公式)'!$B13=""),"",SUMPRODUCT(实盘持仓配置!$B$5:$X$5,'实盘净值数据(iFinD公式)'!$B13:$X13/'实盘净值数据(iFinD公式)'!$B$5:$X$5)*(1-实盘持仓配置!$Z$5)^(('实盘净值数据(iFinD公式)'!$A13-'实盘净值数据(iFinD公式)'!$A$5)/365)) -> 1.0657543 | F13: =IF(OR(E12="",'实盘净值数据(iFinD公式)'!$A13="",'实盘净值数据(iFinD公式)'!$B13=""),"",(SUMPRODUCT(实盘持仓配置!$B$5:$X$5,'实盘净值数据(iFinD公式)'!$B12:$X12/'实盘净值数据(iFinD公式)'!$B$5:$X$5,'实盘净值数据(iFinD公式)'!$B13:$X13/'实盘净值数据(iFinD公式)'!$B12:$X12)/SUMPRODUCT(实盘持仓配置!$B$5:$X$5,'实盘净值数据(iFinD公式)'!$B12:$X12/'实盘净值数据(iFinD公式)'!$B$5:$X$5))*(1-实盘持仓配置!$Z$5)^(('实盘净值数据(iFinD公式)'!$A13-'实盘净值数据(iFinD公式)'!$A12)/365)-1) -> -0.030900613 | G13: =IF(E13="","",E13/MAX(E$5:E13)-1) -> -0.030900613 | H13: =IF(OR((ROW()-1)<7,'实盘净值数据(iFinD公式)'!$A13="",'实盘净值数据(iFinD公式)'!$B13=""),"",SUMPRODUCT(实盘持仓配置!$B$6:$X$6,'实盘净值数据(iFinD公式)'!$B13:$X13/'实盘净值数据(iFinD公式)'!$B$7:$X$7)*(1-实盘持仓配置!$Z$6)^(('实盘净值数据(iFinD公式)'!$A13-'实盘净值数据(iFinD公式)'!$A$7)/365)) -> 1.0836175 | I13: =IF(OR(H12="",'实盘净值数据(iFinD公式)'!$A13="",'实盘净值数据(iFinD公式)'!$B13=""),"",(SUMPRODUCT(实盘持仓配置!$B$6:$X$6,'实盘净值数据(iFinD公式)'!$B12:$X12/'实盘净值数据(iFinD公式)'!$B$7:$X$7,'实盘净值数据(iFinD公式)'!$B13:$X13/'实盘净值数据(iFinD公式)'!$B12:$X12)/SUMPRODUCT(实盘持仓配置!$B$6:$X$6,'实盘净值数据(iFinD公式)'!$B12:$X12/'实盘净值数据(iFinD公式)'!$B$7:$X$7))*(1-实盘持仓配置!$Z$6)^(('实盘净值数据(iFinD公式)'!$A13-'实盘净值数据(iFinD公式)'!$A12)/365)-1) -> -0.025266743 | J13: =IF(H13="","",H13/MAX(H$5:H13)-1) -> -0.025266743 | K13: =IF(OR((ROW()-1)<8,'实盘净值数据(iFinD公式)'!$A13="",'实盘净值数据(iFinD公式)'!$B13=""),"",SUMPRODUCT(实盘持仓配置!$B$7:$X$7,'实盘净值数据(iFinD公式)'!$B13:$X13/'实盘净值数据(iFinD公式)'!$B$8:$X$8)*(1-实盘持仓配置!$Z$7)^(('实盘净值数据(iFinD公式)'!$A13-'实盘净值数据(iFinD公式)'!$A$8)/365)) -> 1.0008642 | L13: =IF(OR(K12="",'实盘净值数据(iFinD公式)'!$A13="",'实盘净值数据(iFinD公式)'!$B13=""),"",(SUMPRODUCT(实盘持仓配置!$B$7:$X$7,'实盘净值数据(iFinD公式)'!$B12:$X12/'实盘净值数据(iFinD公式)'!$B$8:$X$8,'实盘净值数据(iFinD公式)'!$B13:$X13/'实盘净值数据(iFinD公式)'!$B12:$X12)/SUMPRODUCT(实盘持仓配置!$B$7:$X$7,'实盘净值数据(iFinD公式)'!$B12:$X12/'实盘净值数据(iFinD公式)'!$B$8:$X$8))*(1-实盘持仓配置!$Z$7)^(('实盘净值数据(iFinD公式)'!$A13-'实盘净值数据(iFinD公式)'!$A12)/365)-1) -> -0.0023999339 | M13: =IF(K13="","",K13/MAX(K$5:K13)-1) -> -0.0023999339 | N13: =IF(OR((ROW()-1)<5,'实盘净值数据(iFinD公式)'!$A13="",'实盘净值数据(iFinD公式)'!$B13=""),"",SUMPRODUCT(实盘持仓配置!$B$8:$X$8,'实盘净值数据(iFinD公式)'!$B13:$X13/'实盘净值数据(iFinD公式)'!$B$5:$X$5)*(1-实盘持仓配置!$Z$8)^(('实盘净值数据(iFinD公式)'!$A13-'实盘净值数据(iFinD公式)'!$A$5)/365)) -> 0.99998437 | O13: =IF(OR(N12="",'实盘净值数据(iFinD公式)'!$A13="",'实盘净值数据(iFinD公式)'!$B13=""),"",(SUMPRODUCT(实盘持仓配置!$B$8:$X$8,'实盘净值数据(iFinD公式)'!$B12:$X12/'实盘净值数据(iFinD公式)'!$B$5:$X$5,'实盘净值数据(iFinD公式)'!$B13:$X13/'实盘净值数据(iFinD公式)'!$B12:$X12)/SUMPRODUCT(实盘持仓配置!$B$8:$X$8,'实盘净值数据(iFinD公式)'!$B12:$X12/'实盘净值数据(iFinD公式)'!$B$5:$X$5))*(1-实盘持仓配置!$Z$8)^(('实盘净值数据(iFinD公式)'!$A13-'实盘净值数据(iFinD公式)'!$A12)/365)-1) -> -0.0027184046 | P13: =IF(N13="","",N13/MAX(N$5:N13)-1) -> -0.0027184046 | Q13: =IF(OR((ROW()-1)<8,'实盘净值数据(iFinD公式)'!$A13="",'实盘净值数据(iFinD公式)'!$B13=""),"",SUMPRODUCT(实盘持仓配置!$B$9:$X$9,'实盘净值数据(iFinD公式)'!$B13:$X13/'实盘净值数据(iFinD公式)'!$B$8:$X$8)*(1-实盘持仓配置!$Z$9)^(('实盘净值数据(iFinD公式)'!$A13-'实盘净值数据(iFinD公式)'!$A$8)/365)) -> 1.0039155 | R13: =IF(OR(Q12="",'实盘净值数据(iFinD公式)'!$A13="",'实盘净值数据(iFinD公式)'!$B13=""),"",(SUMPRODUCT(实盘持仓配置!$B$9:$X$9,'实盘净值数据(iFinD公式)'!$B12:$X12/'实盘净值数据(iFinD公式)'!$B$8:$X$8,'实盘净值数据(iFinD公式)'!$B13:$X13/'实盘净值数据(iFinD公式)'!$B12:$X12)/SUMPRODUCT(实盘持仓配置!$B$9:$X$9,'实盘净值数据(iFinD公式)'!$B12:$X12/'实盘净值数据(iFinD公式)'!$B$8:$X$8))*(1-实盘持仓配置!$Z$9)^(('实盘净值数据(iFinD公式)'!$A13-'实盘净值数据(iFinD公式)'!$A12)/365)-1) -> -0.0048042295 | S13: =IF(Q13="","",Q13/MAX(Q$5:Q13)-1) -> -0.0048042295
A14: =IF('实盘净值数据(iFinD公式)'!A14="","",'实盘净值数据(iFinD公式)'!A14) -> 46205 | B14: =IF(OR((ROW()-1)<6,'实盘净值数据(iFinD公式)'!$A14="",'实盘净值数据(iFinD公式)'!$B14=""),"",SUMPRODUCT(实盘持仓配置!$B$4:$X$4,'实盘净值数据(iFinD公式)'!$B14:$X14/'实盘净值数据(iFinD公式)'!$B$6:$X$6)*(1-实盘持仓配置!$Z$4)^(('实盘净值数据(iFinD公式)'!$A14-'实盘净值数据(iFinD公式)'!$A$6)/365)) -> 0.95024005 | C14: =IF(OR(B13="",'实盘净值数据(iFinD公式)'!$A14="",'实盘净值数据(iFinD公式)'!$B14=""),"",(SUMPRODUCT(实盘持仓配置!$B$4:$X$4,'实盘净值数据(iFinD公式)'!$B13:$X13/'实盘净值数据(iFinD公式)'!$B$6:$X$6,'实盘净值数据(iFinD公式)'!$B14:$X14/'实盘净值数据(iFinD公式)'!$B13:$X13)/SUMPRODUCT(实盘持仓配置!$B$4:$X$4,'实盘净值数据(iFinD公式)'!$B13:$X13/'实盘净值数据(iFinD公式)'!$B$6:$X$6))*(1-实盘持仓配置!$Z$4)^(('实盘净值数据(iFinD公式)'!$A14-'实盘净值数据(iFinD公式)'!$A13)/365)-1) -> -0.087770129 | D14: =IF(B14="","",B14/MAX(B$5:B14)-1) -> -0.11593069 | E14: =IF(OR((ROW()-1)<5,'实盘净值数据(iFinD公式)'!$A14="",'实盘净值数据(iFinD公式)'!$B14=""),"",SUMPRODUCT(实盘持仓配置!$B$5:$X$5,'实盘净值数据(iFinD公式)'!$B14:$X14/'实盘净值数据(iFinD公式)'!$B$5:$X$5)*(1-实盘持仓配置!$Z$5)^(('实盘净值数据(iFinD公式)'!$A14-'实盘净值数据(iFinD公式)'!$A$5)/365)) -> 0.97222777 | F14: =IF(OR(E13="",'实盘净值数据(iFinD公式)'!$A14="",'实盘净值数据(iFinD公式)'!$B14=""),"",(SUMPRODUCT(实盘持仓配置!$B$5:$X$5,'实盘净值数据(iFinD公式)'!$B13:$X13/'实盘净值数据(iFinD公式)'!$B$5:$X$5,'实盘净值数据(iFinD公式)'!$B14:$X14/'实盘净值数据(iFinD公式)'!$B13:$X13)/SUMPRODUCT(实盘持仓配置!$B$5:$X$5,'实盘净值数据(iFinD公式)'!$B13:$X13/'实盘净值数据(iFinD公式)'!$B$5:$X$5))*(1-实盘持仓配置!$Z$5)^(('实盘净值数据(iFinD公式)'!$A14-'实盘净值数据(iFinD公式)'!$A13)/365)-1) -> -0.087756207 | G14: =IF(E14="","",E14/MAX(E$5:E14)-1) -> -0.1159451 | H14: =IF(OR((ROW()-1)<7,'实盘净值数据(iFinD公式)'!$A14="",'实盘净值数据(iFinD公式)'!$B14=""),"",SUMPRODUCT(实盘持仓配置!$B$6:$X$6,'实盘净值数据(iFinD公式)'!$B14:$X14/'实盘净值数据(iFinD公式)'!$B$7:$X$7)*(1-实盘持仓配置!$Z$6)^(('实盘净值数据(iFinD公式)'!$A14-'实盘净值数据(iFinD公式)'!$A$7)/365)) -> 0.99175225 | I14: =IF(OR(H13="",'实盘净值数据(iFinD公式)'!$A14="",'实盘净值数据(iFinD公式)'!$B14=""),"",(SUMPRODUCT(实盘持仓配置!$B$6:$X$6,'实盘净值数据(iFinD公式)'!$B13:$X13/'实盘净值数据(iFinD公式)'!$B$7:$X$7,'实盘净值数据(iFinD公式)'!$B14:$X14/'实盘净值数据(iFinD公式)'!$B13:$X13)/SUMPRODUCT(实盘持仓配置!$B$6:$X$6,'实盘净值数据(iFinD公式)'!$B13:$X13/'实盘净值数据(iFinD公式)'!$B$7:$X$7))*(1-实盘持仓配置!$Z$6)^(('实盘净值数据(iFinD公式)'!$A14-'实盘净值数据(iFinD公式)'!$A13)/365)-1) -> -0.084776442 | J14: =IF(H14="","",H14/MAX(H$5:H14)-1) -> -0.10790116 | K14: =IF(OR((ROW()-1)<8,'实盘净值数据(iFinD公式)'!$A14="",'实盘净值数据(iFinD公式)'!$B14=""),"",SUMPRODUCT(实盘持仓配置!$B$7:$X$7,'实盘净值数据(iFinD公式)'!$B14:$X14/'实盘净值数据(iFinD公式)'!$B$8:$X$8)*(1-实盘持仓配置!$Z$7)^(('实盘净值数据(iFinD公式)'!$A14-'实盘净值数据(iFinD公式)'!$A$8)/365)) -> 0.99622662 | L14: =IF(OR(K13="",'实盘净值数据(iFinD公式)'!$A14="",'实盘净值数据(iFinD公式)'!$B14=""),"",(SUMPRODUCT(实盘持仓配置!$B$7:$X$7,'实盘净值数据(iFinD公式)'!$B13:$X13/'实盘净值数据(iFinD公式)'!$B$8:$X$8,'实盘净值数据(iFinD公式)'!$B14:$X14/'实盘净值数据(iFinD公式)'!$B13:$X13)/SUMPRODUCT(实盘持仓配置!$B$7:$X$7,'实盘净值数据(iFinD公式)'!$B13:$X13/'实盘净值数据(iFinD公式)'!$B$8:$X$8))*(1-实盘持仓配置!$Z$7)^(('实盘净值数据(iFinD公式)'!$A14-'实盘净值数据(iFinD公式)'!$A13)/365)-1) -> -0.0046335858 | M14: =IF(K14="","",K14/MAX(K$5:K14)-1) -> -0.0070223994 | N14: =IF(OR((ROW()-1)<5,'实盘净值数据(iFinD公式)'!$A14="",'实盘净值数据(iFinD公式)'!$B14=""),"",SUMPRODUCT(实盘持仓配置!$B$8:$X$8,'实盘净值数据(iFinD公式)'!$B14:$X14/'实盘净值数据(iFinD公式)'!$B$5:$X$5)*(1-实盘持仓配置!$Z$8)^(('实盘净值数据(iFinD公式)'!$A14-'实盘净值数据(iFinD公式)'!$A$5)/365)) -> 0.99500922 | O14: =IF(OR(N13="",'实盘净值数据(iFinD公式)'!$A14="",'实盘净值数据(iFinD公式)'!$B14=""),"",(SUMPRODUCT(实盘持仓配置!$B$8:$X$8,'实盘净值数据(iFinD公式)'!$B13:$X13/'实盘净值数据(iFinD公式)'!$B$5:$X$5,'实盘净值数据(iFinD公式)'!$B14:$X14/'实盘净值数据(iFinD公式)'!$B13:$X13)/SUMPRODUCT(实盘持仓配置!$B$8:$X$8,'实盘净值数据(iFinD公式)'!$B13:$X13/'实盘净值数据(iFinD公式)'!$B$5:$X$5))*(1-实盘持仓配置!$Z$8)^(('实盘净值数据(iFinD公式)'!$A14-'实盘净值数据(iFinD公式)'!$A13)/365)-1) -> -0.0049752255 | P14: =IF(N14="","",N14/MAX(N$5:N14)-1) -> -0.0076801054 | Q14: =IF(OR((ROW()-1)<8,'实盘净值数据(iFinD公式)'!$A14="",'实盘净值数据(iFinD公式)'!$B14=""),"",SUMPRODUCT(实盘持仓配置!$B$9:$X$9,'实盘净值数据(iFinD公式)'!$B14:$X14/'实盘净值数据(iFinD公式)'!$B$8:$X$8)*(1-实盘持仓配置!$Z$9)^(('实盘净值数据(iFinD公式)'!$A14-'实盘净值数据(iFinD公式)'!$A$8)/365)) -> 0.98881177 | R14: =IF(OR(Q13="",'实盘净值数据(iFinD公式)'!$A14="",'实盘净值数据(iFinD公式)'!$B14=""),"",(SUMPRODUCT(实盘持仓配置!$B$9:$X$9,'实盘净值数据(iFinD公式)'!$B13:$X13/'实盘净值数据(iFinD公式)'!$B$8:$X$8,'实盘净值数据(iFinD公式)'!$B14:$X14/'实盘净值数据(iFinD公式)'!$B13:$X13)/SUMPRODUCT(实盘持仓配置!$B$9:$X$9,'实盘净值数据(iFinD公式)'!$B13:$X13/'实盘净值数据(iFinD公式)'!$B$8:$X$8))*(1-实盘持仓配置!$Z$9)^(('实盘净值数据(iFinD公式)'!$A14-'实盘净值数据(iFinD公式)'!$A13)/365)-1) -> -0.015044865 | S14: =IF(Q14="","",Q14/MAX(Q$5:Q14)-1) -> -0.019776815
A15: =IF('实盘净值数据(iFinD公式)'!A15="","",'实盘净值数据(iFinD公式)'!A15) -> 46206 | B15: =IF(OR((ROW()-1)<6,'实盘净值数据(iFinD公式)'!$A15="",'实盘净值数据(iFinD公式)'!$B15=""),"",SUMPRODUCT(实盘持仓配置!$B$4:$X$4,'实盘净值数据(iFinD公式)'!$B15:$X15/'实盘净值数据(iFinD公式)'!$B$6:$X$6)*(1-实盘持仓配置!$Z$4)^(('实盘净值数据(iFinD公式)'!$A15-'实盘净值数据(iFinD公式)'!$A$6)/365)) -> 0.943219 | C15: =IF(OR(B14="",'实盘净值数据(iFinD公式)'!$A15="",'实盘净值数据(iFinD公式)'!$B15=""),"",(SUMPRODUCT(实盘持仓配置!$B$4:$X$4,'实盘净值数据(iFinD公式)'!$B14:$X14/'实盘净值数据(iFinD公式)'!$B$6:$X$6,'实盘净值数据(iFinD公式)'!$B15:$X15/'实盘净值数据(iFinD公式)'!$B14:$X14)/SUMPRODUCT(实盘持仓配置!$B$4:$X$4,'实盘净值数据(iFinD公式)'!$B14:$X14/'实盘净值数据(iFinD公式)'!$B$6:$X$6))*(1-实盘持仓配置!$Z$4)^(('实盘净值数据(iFinD公式)'!$A15-'实盘净值数据(iFinD公式)'!$A14)/365)-1) -> -0.0073887185 | D15: =IF(B15="","",B15/MAX(B$5:B15)-1) -> -0.12246283 | E15: =IF(OR((ROW()-1)<5,'实盘净值数据(iFinD公式)'!$A15="",'实盘净值数据(iFinD公式)'!$B15=""),"",SUMPRODUCT(实盘持仓配置!$B$5:$X$5,'实盘净值数据(iFinD公式)'!$B15:$X15/'实盘净值数据(iFinD公式)'!$B$5:$X$5)*(1-实盘持仓配置!$Z$5)^(('实盘净值数据(iFinD公式)'!$A15-'实盘净值数据(iFinD公式)'!$A$5)/365)) -> 0.96507649 | F15: =IF(OR(E14="",'实盘净值数据(iFinD公式)'!$A15="",'实盘净值数据(iFinD公式)'!$B15=""),"",(SUMPRODUCT(实盘持仓配置!$B$5:$X$5,'实盘净值数据(iFinD公式)'!$B14:$X14/'实盘净值数据(iFinD公式)'!$B$5:$X$5,'实盘净值数据(iFinD公式)'!$B15:$X15/'实盘净值数据(iFinD公式)'!$B14:$X14)/SUMPRODUCT(实盘持仓配置!$B$5:$X$5,'实盘净值数据(iFinD公式)'!$B14:$X14/'实盘净值数据(iFinD公式)'!$B$5:$X$5))*(1-实盘持仓配置!$Z$5)^(('实盘净值数据(iFinD公式)'!$A15-'实盘净值数据(iFinD公式)'!$A14)/365)-1) -> -0.007355563 | G15: =IF(E15="","",E15/MAX(E$5:E15)-1) -> -0.12244782 | H15: =IF(OR((ROW()-1)<7,'实盘净值数据(iFinD公式)'!$A15="",'实盘净值数据(iFinD公式)'!$B15=""),"",SUMPRODUCT(实盘持仓配置!$B$6:$X$6,'实盘净值数据(iFinD公式)'!$B15:$X15/'实盘净值数据(iFinD公式)'!$B$7:$X$7)*(1-实盘持仓配置!$Z$6)^(('实盘净值数据(iFinD公式)'!$A15-'实盘净值数据(iFinD公式)'!$A$7)/365)) -> 0.98876259 | I15: =IF(OR(H14="",'实盘净值数据(iFinD公式)'!$A15="",'实盘净值数据(iFinD公式)'!$B15=""),"",(SUMPRODUCT(实盘持仓配置!$B$6:$X$6,'实盘净值数据(iFinD公式)'!$B14:$X14/'实盘净值数据(iFinD公式)'!$B$7:$X$7,'实盘净值数据(iFinD公式)'!$B15:$X15/'实盘净值数据(iFinD公式)'!$B14:$X14)/SUMPRODUCT(实盘持仓配置!$B$6:$X$6,'实盘净值数据(iFinD公式)'!$B14:$X14/'实盘净值数据(iFinD公式)'!$B$7:$X$7))*(1-实盘持仓配置!$Z$6)^(('实盘净值数据(iFinD公式)'!$A15-'实盘净值数据(iFinD公式)'!$A14)/365)-1) -> -0.0030145263 | J15: =IF(H15="","",H15/MAX(H$5:H15)-1) -> -0.11059042 | K15: =IF(OR((ROW()-1)<8,'实盘净值数据(iFinD公式)'!$A15="",'实盘净值数据(iFinD公式)'!$B15=""),"",SUMPRODUCT(实盘持仓配置!$B$7:$X$7,'实盘净值数据(iFinD公式)'!$B15:$X15/'实盘净值数据(iFinD公式)'!$B$8:$X$8)*(1-实盘持仓配置!$Z$7)^(('实盘净值数据(iFinD公式)'!$A15-'实盘净值数据(iFinD公式)'!$A$8)/365)) -> 0.99750069 | L15: =IF(OR(K14="",'实盘净值数据(iFinD公式)'!$A15="",'实盘净值数据(iFinD公式)'!$B15=""),"",(SUMPRODUCT(实盘持仓配置!$B$7:$X$7,'实盘净值数据(iFinD公式)'!$B14:$X14/'实盘净值数据(iFinD公式)'!$B$8:$X$8,'实盘净值数据(iFinD公式)'!$B15:$X15/'实盘净值数据(iFinD公式)'!$B14:$X14)/SUMPRODUCT(实盘持仓配置!$B$7:$X$7,'实盘净值数据(iFinD公式)'!$B14:$X14/'实盘净值数据(iFinD公式)'!$B$8:$X$8))*(1-实盘持仓配置!$Z$7)^(('实盘净值数据(iFinD公式)'!$A15-'实盘净值数据(iFinD公式)'!$A14)/365)-1) -> 0.0012788991 | M15: =IF(K15="","",K15/MAX(K$5:K15)-1) -> -0.0057524813 | N15: =IF(OR((ROW()-1)<5,'实盘净值数据(iFinD公式)'!$A15="",'实盘净值数据(iFinD公式)'!$B15=""),"",SUMPRODUCT(实盘持仓配置!$B$8:$X$8,'实盘净值数据(iFinD公式)'!$B15:$X15/'实盘净值数据(iFinD公式)'!$B$5:$X$5)*(1-实盘持仓配置!$Z$8)^(('实盘净值数据(iFinD公式)'!$A15-'实盘净值数据(iFinD公式)'!$A$5)/365)) -> 0.99600193 | O15: =IF(OR(N14="",'实盘净值数据(iFinD公式)'!$A15="",'实盘净值数据(iFinD公式)'!$B15=""),"",(SUMPRODUCT(实盘持仓配置!$B$8:$X$8,'实盘净值数据(iFinD公式)'!$B14:$X14/'实盘净值数据(iFinD公式)'!$B$5:$X$5,'实盘净值数据(iFinD公式)'!$B15:$X15/'实盘净值数据(iFinD公式)'!$B14:$X14)/SUMPRODUCT(实盘持仓配置!$B$8:$X$8,'实盘净值数据(iFinD公式)'!$B14:$X14/'实盘净值数据(iFinD公式)'!$B$5:$X$5))*(1-实盘持仓配置!$Z$8)^(('实盘净值数据(iFinD公式)'!$A15-'实盘净值数据(iFinD公式)'!$A14)/365)-1) -> 0.00099768829 | P15: =IF(N15="","",N15/MAX(N$5:N15)-1) -> -0.0066900795 | Q15: =IF(OR((ROW()-1)<8,'实盘净值数据(iFinD公式)'!$A15="",'实盘净值数据(iFinD公式)'!$B15=""),"",SUMPRODUCT(实盘持仓配置!$B$9:$X$9,'实盘净值数据(iFinD公式)'!$B15:$X15/'实盘净值数据(iFinD公式)'!$B$8:$X$8)*(1-实盘持仓配置!$Z$9)^(('实盘净值数据(iFinD公式)'!$A15-'实盘净值数据(iFinD公式)'!$A$8)/365)) -> 0.99177158 | R15: =IF(OR(Q14="",'实盘净值数据(iFinD公式)'!$A15="",'实盘净值数据(iFinD公式)'!$B15=""),"",(SUMPRODUCT(实盘持仓配置!$B$9:$X$9,'实盘净值数据(iFinD公式)'!$B14:$X14/'实盘净值数据(iFinD公式)'!$B$8:$X$8,'实盘净值数据(iFinD公式)'!$B15:$X15/'实盘净值数据(iFinD公式)'!$B14:$X14)/SUMPRODUCT(实盘持仓配置!$B$9:$X$9,'实盘净值数据(iFinD公式)'!$B14:$X14/'实盘净值数据(iFinD公式)'!$B$8:$X$8))*(1-实盘持仓配置!$Z$9)^(('实盘净值数据(iFinD公式)'!$A15-'实盘净值数据(iFinD公式)'!$A14)/365)-1) -> 0.0029932992 | S15: =IF(Q15="","",Q15/MAX(Q$5:Q15)-1) -> -0.016842714
A16: =IF('实盘净值数据(iFinD公式)'!A16="","",'实盘净值数据(iFinD公式)'!A16) -> 46209 | B16: =IF(OR((ROW()-1)<6,'实盘净值数据(iFinD公式)'!$A16="",'实盘净值数据(iFinD公式)'!$B16=""),"",SUMPRODUCT(实盘持仓配置!$B$4:$X$4,'实盘净值数据(iFinD公式)'!$B16:$X16/'实盘净值数据(iFinD公式)'!$B$6:$X$6)*(1-实盘持仓配置!$Z$4)^(('实盘净值数据(iFinD公式)'!$A16-'实盘净值数据(iFinD公式)'!$A$6)/365)) -> 0.92459185 | C16: =IF(OR(B15="",'实盘净值数据(iFinD公式)'!$A16="",'实盘净值数据(iFinD公式)'!$B16=""),"",(SUMPRODUCT(实盘持仓配置!$B$4:$X$4,'实盘净值数据(iFinD公式)'!$B15:$X15/'实盘净值数据(iFinD公式)'!$B$6:$X$6,'实盘净值数据(iFinD公式)'!$B16:$X16/'实盘净值数据(iFinD公式)'!$B15:$X15)/SUMPRODUCT(实盘持仓配置!$B$4:$X$4,'实盘净值数据(iFinD公式)'!$B15:$X15/'实盘净值数据(iFinD公式)'!$B$6:$X$6))*(1-实盘持仓配置!$Z$4)^(('实盘净值数据(iFinD公式)'!$A16-'实盘净值数据(iFinD公式)'!$A15)/365)-1) -> -0.019748483 | D16: =IF(B16="","",B16/MAX(B$5:B16)-1) -> -0.13979286 | E16: =IF(OR((ROW()-1)<5,'实盘净值数据(iFinD公式)'!$A16="",'实盘净值数据(iFinD公式)'!$B16=""),"",SUMPRODUCT(实盘持仓配置!$B$5:$X$5,'实盘净值数据(iFinD公式)'!$B16:$X16/'实盘净值数据(iFinD公式)'!$B$5:$X$5)*(1-实盘持仓配置!$Z$5)^(('实盘净值数据(iFinD公式)'!$A16-'实盘净值数据(iFinD公式)'!$A$5)/365)) -> 0.94597776 | F16: =IF(OR(E15="",'实盘净值数据(iFinD公式)'!$A16="",'实盘净值数据(iFinD公式)'!$B16=""),"",(SUMPRODUCT(实盘持仓配置!$B$5:$X$5,'实盘净值数据(iFinD公式)'!$B15:$X15/'实盘净值数据(iFinD公式)'!$B$5:$X$5,'实盘净值数据(iFinD公式)'!$B16:$X16/'实盘净值数据(iFinD公式)'!$B15:$X15)/SUMPRODUCT(实盘持仓配置!$B$5:$X$5,'实盘净值数据(iFinD公式)'!$B15:$X15/'实盘净值数据(iFinD公式)'!$B$5:$X$5))*(1-实盘持仓配置!$Z$5)^(('实盘净值数据(iFinD公式)'!$A16-'实盘净值数据(iFinD公式)'!$A15)/365)-1) -> -0.019789862 | G16: =IF(E16="","",E16/MAX(E$5:E16)-1) -> -0.13981446 | H16: =IF(OR((ROW()-1)<7,'实盘净值数据(iFinD公式)'!$A16="",'实盘净值数据(iFinD公式)'!$B16=""),"",SUMPRODUCT(实盘持仓配置!$B$6:$X$6,'实盘净值数据(iFinD公式)'!$B16:$X16/'实盘净值数据(iFinD公式)'!$B$7:$X$7)*(1-实盘持仓配置!$Z$6)^(('实盘净值数据(iFinD公式)'!$A16-'实盘净值数据(iFinD公式)'!$A$7)/365)) -> 0.97195202 | I16: =IF(OR(H15="",'实盘净值数据(iFinD公式)'!$A16="",'实盘净值数据(iFinD公式)'!$B16=""),"",(SUMPRODUCT(实盘持仓配置!$B$6:$X$6,'实盘净值数据(iFinD公式)'!$B15:$X15/'实盘净值数据(iFinD公式)'!$B$7:$X$7,'实盘净值数据(iFinD公式)'!$B16:$X16/'实盘净值数据(iFinD公式)'!$B15:$X15)/SUMPRODUCT(实盘持仓配置!$B$6:$X$6,'实盘净值数据(iFinD公式)'!$B15:$X15/'实盘净值数据(iFinD公式)'!$B$7:$X$7))*(1-实盘持仓配置!$Z$6)^(('实盘净值数据(iFinD公式)'!$A16-'实盘净值数据(iFinD公式)'!$A15)/365)-1) -> -0.017001619 | J16: =IF(H16="","",H16/MAX(H$5:H16)-1) -> -0.12571182 | K16: =IF(OR((ROW()-1)<8,'实盘净值数据(iFinD公式)'!$A16="",'实盘净值数据(iFinD公式)'!$B16=""),"",SUMPRODUCT(实盘持仓配置!$B$7:$X$7,'实盘净值数据(iFinD公式)'!$B16:$X16/'实盘净值数据(iFinD公式)'!$B$8:$X$8)*(1-实盘持仓配置!$Z$7)^(('实盘净值数据(iFinD公式)'!$A16-'实盘净值数据(iFinD公式)'!$A$8)/365)) -> 0.99665018 | L16: =IF(OR(K15="",'实盘净值数据(iFinD公式)'!$A16="",'实盘净值数据(iFinD公式)'!$B16=""),"",(SUMPRODUCT(实盘持仓配置!$B$7:$X$7,'实盘净值数据(iFinD公式)'!$B15:$X15/'实盘净值数据(iFinD公式)'!$B$8:$X$8,'实盘净值数据(iFinD公式)'!$B16:$X16/'实盘净值数据(iFinD公式)'!$B15:$X15)/SUMPRODUCT(实盘持仓配置!$B$7:$X$7,'实盘净值数据(iFinD公式)'!$B15:$X15/'实盘净值数据(iFinD公式)'!$B$8:$X$8))*(1-实盘持仓配置!$Z$7)^(('实盘净值数据(iFinD公式)'!$A16-'实盘净值数据(iFinD公式)'!$A15)/365)-1) -> -0.0008526422 | M16: =IF(K16="","",K16/MAX(K$5:K16)-1) -> -0.0066002186 | N16: =IF(OR((ROW()-1)<5,'实盘净值数据(iFinD公式)'!$A16="",'实盘净值数据(iFinD公式)'!$B16=""),"",SUMPRODUCT(实盘持仓配置!$B$8:$X$8,'实盘净值数据(iFinD公式)'!$B16:$X16/'实盘净值数据(iFinD公式)'!$B$5:$X$5)*(1-实盘持仓配置!$Z$8)^(('实盘净值数据(iFinD公式)'!$A16-'实盘净值数据(iFinD公式)'!$A$5)/365)) -> 0.9950428 | O16: =IF(OR(N15="",'实盘净值数据(iFinD公式)'!$A16="",'实盘净值数据(iFinD公式)'!$B16=""),"",(SUMPRODUCT(实盘持仓配置!$B$8:$X$8,'实盘净值数据(iFinD公式)'!$B15:$X15/'实盘净值数据(iFinD公式)'!$B$5:$X$5,'实盘净值数据(iFinD公式)'!$B16:$X16/'实盘净值数据(iFinD公式)'!$B15:$X15)/SUMPRODUCT(实盘持仓配置!$B$8:$X$8,'实盘净值数据(iFinD公式)'!$B15:$X15/'实盘净值数据(iFinD公式)'!$B$5:$X$5))*(1-实盘持仓配置!$Z$8)^(('实盘净值数据(iFinD公式)'!$A16-'实盘净值数据(iFinD公式)'!$A15)/365)-1) -> -0.00096298173 | P16: =IF(N16="","",N16/MAX(N$5:N16)-1) -> -0.0076466188 | Q16: =IF(OR((ROW()-1)<8,'实盘净值数据(iFinD公式)'!$A16="",'实盘净值数据(iFinD公式)'!$B16=""),"",SUMPRODUCT(实盘持仓配置!$B$9:$X$9,'实盘净值数据(iFinD公式)'!$B16:$X16/'实盘净值数据(iFinD公式)'!$B$8:$X$8)*(1-实盘持仓配置!$Z$9)^(('实盘净值数据(iFinD公式)'!$A16-'实盘净值数据(iFinD公式)'!$A$8)/365)) -> 0.98808224 | R16: =IF(OR(Q15="",'实盘净值数据(iFinD公式)'!$A16="",'实盘净值数据(iFinD公式)'!$B16=""),"",(SUMPRODUCT(实盘持仓配置!$B$9:$X$9,'实盘净值数据(iFinD公式)'!$B15:$X15/'实盘净值数据(iFinD公式)'!$B$8:$X$8,'实盘净值数据(iFinD公式)'!$B16:$X16/'实盘净值数据(iFinD公式)'!$B15:$X15)/SUMPRODUCT(实盘持仓配置!$B$9:$X$9,'实盘净值数据(iFinD公式)'!$B15:$X15/'实盘净值数据(iFinD公式)'!$B$8:$X$8))*(1-实盘持仓配置!$Z$9)^(('实盘净值数据(iFinD公式)'!$A16-'实盘净值数据(iFinD公式)'!$A15)/365)-1) -> -0.0037199512 | S16: =IF(Q16="","",Q16/MAX(Q$5:Q16)-1) -> -0.020500011
A17: =IF('实盘净值数据(iFinD公式)'!A17="","",'实盘净值数据(iFinD公式)'!A17) -> 46210 | B17: =IF(OR((ROW()-1)<6,'实盘净值数据(iFinD公式)'!$A17="",'实盘净值数据(iFinD公式)'!$B17=""),"",SUMPRODUCT(实盘持仓配置!$B$4:$X$4,'实盘净值数据(iFinD公式)'!$B17:$X17/'实盘净值数据(iFinD公式)'!$B$6:$X$6)*(1-实盘持仓配置!$Z$4)^(('实盘净值数据(iFinD公式)'!$A17-'实盘净值数据(iFinD公式)'!$A$6)/365)) -> 0.93094052 | C17: =IF(OR(B16="",'实盘净值数据(iFinD公式)'!$A17="",'实盘净值数据(iFinD公式)'!$B17=""),"",(SUMPRODUCT(实盘持仓配置!$B$4:$X$4,'实盘净值数据(iFinD公式)'!$B16:$X16/'实盘净值数据(iFinD公式)'!$B$6:$X$6,'实盘净值数据(iFinD公式)'!$B17:$X17/'实盘净值数据(iFinD公式)'!$B16:$X16)/SUMPRODUCT(实盘持仓配置!$B$4:$X$4,'实盘净值数据(iFinD公式)'!$B16:$X16/'实盘净值数据(iFinD公式)'!$B$6:$X$6))*(1-实盘持仓配置!$Z$4)^(('实盘净值数据(iFinD公式)'!$A17-'实盘净值数据(iFinD公式)'!$A16)/365)-1) -> 0.0068664547 | D17: =IF(B17="","",B17/MAX(B$5:B17)-1) -> -0.13388628 | E17: =IF(OR((ROW()-1)<5,'实盘净值数据(iFinD公式)'!$A17="",'实盘净值数据(iFinD公式)'!$B17=""),"",SUMPRODUCT(实盘持仓配置!$B$5:$X$5,'实盘净值数据(iFinD公式)'!$B17:$X17/'实盘净值数据(iFinD公式)'!$B$5:$X$5)*(1-实盘持仓配置!$Z$5)^(('实盘净值数据(iFinD公式)'!$A17-'实盘净值数据(iFinD公式)'!$A$5)/365)) -> 0.95247543 | F17: =IF(OR(E16="",'实盘净值数据(iFinD公式)'!$A17="",'实盘净值数据(iFinD公式)'!$B17=""),"",(SUMPRODUCT(实盘持仓配置!$B$5:$X$5,'实盘净值数据(iFinD公式)'!$B16:$X16/'实盘净值数据(iFinD公式)'!$B$5:$X$5,'实盘净值数据(iFinD公式)'!$B17:$X17/'实盘净值数据(iFinD公式)'!$B16:$X16)/SUMPRODUCT(实盘持仓配置!$B$5:$X$5,'实盘净值数据(iFinD公式)'!$B16:$X16/'实盘净值数据(iFinD公式)'!$B$5:$X$5))*(1-实盘持仓配置!$Z$5)^(('实盘净值数据(iFinD公式)'!$A17-'实盘净值数据(iFinD公式)'!$A16)/365)-1) -> 0.0068687365 | G17: =IF(E17="","",E17/MAX(E$5:E17)-1) -> -0.13390607 | H17: =IF(OR((ROW()-1)<7,'实盘净值数据(iFinD公式)'!$A17="",'实盘净值数据(iFinD公式)'!$B17=""),"",SUMPRODUCT(实盘持仓配置!$B$6:$X$6,'实盘净值数据(iFinD公式)'!$B17:$X17/'实盘净值数据(iFinD公式)'!$B$7:$X$7)*(1-实盘持仓配置!$Z$6)^(('实盘净值数据(iFinD公式)'!$A17-'实盘净值数据(iFinD公式)'!$A$7)/365)) -> 0.97477427 | I17: =IF(OR(H16="",'实盘净值数据(iFinD公式)'!$A17="",'实盘净值数据(iFinD公式)'!$B17=""),"",(SUMPRODUCT(实盘持仓配置!$B$6:$X$6,'实盘净值数据(iFinD公式)'!$B16:$X16/'实盘净值数据(iFinD公式)'!$B$7:$X$7,'实盘净值数据(iFinD公式)'!$B17:$X17/'实盘净值数据(iFinD公式)'!$B16:$X16)/SUMPRODUCT(实盘持仓配置!$B$6:$X$6,'实盘净值数据(iFinD公式)'!$B16:$X16/'实盘净值数据(iFinD公式)'!$B$7:$X$7))*(1-实盘持仓配置!$Z$6)^(('实盘净值数据(iFinD公式)'!$A17-'实盘净值数据(iFinD公式)'!$A16)/365)-1) -> 0.002903689 | J17: =IF(H17="","",H17/MAX(H$5:H17)-1) -> -0.12317316 | K17: =IF(OR((ROW()-1)<8,'实盘净值数据(iFinD公式)'!$A17="",'实盘净值数据(iFinD公式)'!$B17=""),"",SUMPRODUCT(实盘持仓配置!$B$7:$X$7,'实盘净值数据(iFinD公式)'!$B17:$X17/'实盘净值数据(iFinD公式)'!$B$8:$X$8)*(1-实盘持仓配置!$Z$7)^(('实盘净值数据(iFinD公式)'!$A17-'实盘净值数据(iFinD公式)'!$A$8)/365)) -> 0.99564272 | L17: =IF(OR(K16="",'实盘净值数据(iFinD公式)'!$A17="",'实盘净值数据(iFinD公式)'!$B17=""),"",(SUMPRODUCT(实盘持仓配置!$B$7:$X$7,'实盘净值数据(iFinD公式)'!$B16:$X16/'实盘净值数据(iFinD公式)'!$B$8:$X$8,'实盘净值数据(iFinD公式)'!$B17:$X17/'实盘净值数据(iFinD公式)'!$B16:$X16)/SUMPRODUCT(实盘持仓配置!$B$7:$X$7,'实盘净值数据(iFinD公式)'!$B16:$X16/'实盘净值数据(iFinD公式)'!$B$8:$X$8))*(1-实盘持仓配置!$Z$7)^(('实盘净值数据(iFinD公式)'!$A17-'实盘净值数据(iFinD公式)'!$A16)/365)-1) -> -0.0010108462 | M17: =IF(K17="","",K17/MAX(K$5:K17)-1) -> -0.0076043931 | N17: =IF(OR((ROW()-1)<5,'实盘净值数据(iFinD公式)'!$A17="",'实盘净值数据(iFinD公式)'!$B17=""),"",SUMPRODUCT(实盘持仓配置!$B$8:$X$8,'实盘净值数据(iFinD公式)'!$B17:$X17/'实盘净值数据(iFinD公式)'!$B$5:$X$5)*(1-实盘持仓配置!$Z$8)^(('实盘净值数据(iFinD公式)'!$A17-'实盘净值数据(iFinD公式)'!$A$5)/365)) -> 0.99425421 | O17: =IF(OR(N16="",'实盘净值数据(iFinD公式)'!$A17="",'实盘净值数据(iFinD公式)'!$B17=""),"",(SUMPRODUCT(实盘持仓配置!$B$8:$X$8,'实盘净值数据(iFinD公式)'!$B16:$X16/'实盘净值数据(iFinD公式)'!$B$5:$X$5,'实盘净值数据(iFinD公式)'!$B17:$X17/'实盘净值数据(iFinD公式)'!$B16:$X16)/SUMPRODUCT(实盘持仓配置!$B$8:$X$8,'实盘净值数据(iFinD公式)'!$B16:$X16/'实盘净值数据(iFinD公式)'!$B$5:$X$5))*(1-实盘持仓配置!$Z$8)^(('实盘净值数据(iFinD公式)'!$A17-'实盘净值数据(iFinD公式)'!$A16)/365)-1) -> -0.00079251674 | P17: =IF(N17="","",N17/MAX(N$5:N17)-1) -> -0.0084330754 | Q17: =IF(OR((ROW()-1)<8,'实盘净值数据(iFinD公式)'!$A17="",'实盘净值数据(iFinD公式)'!$B17=""),"",SUMPRODUCT(实盘持仓配置!$B$9:$X$9,'实盘净值数据(iFinD公式)'!$B17:$X17/'实盘净值数据(iFinD公式)'!$B$8:$X$8)*(1-实盘持仓配置!$Z$9)^(('实盘净值数据(iFinD公式)'!$A17-'实盘净值数据(iFinD公式)'!$A$8)/365)) -> 0.9851767 | R17: =IF(OR(Q16="",'实盘净值数据(iFinD公式)'!$A17="",'实盘净值数据(iFinD公式)'!$B17=""),"",(SUMPRODUCT(实盘持仓配置!$B$9:$X$9,'实盘净值数据(iFinD公式)'!$B16:$X16/'实盘净值数据(iFinD公式)'!$B$8:$X$8,'实盘净值数据(iFinD公式)'!$B17:$X17/'实盘净值数据(iFinD公式)'!$B16:$X16)/SUMPRODUCT(实盘持仓配置!$B$9:$X$9,'实盘净值数据(iFinD公式)'!$B16:$X16/'实盘净值数据(iFinD公式)'!$B$8:$X$8))*(1-实盘持仓配置!$Z$9)^(('实盘净值数据(iFinD公式)'!$A17-'实盘净值数据(iFinD公式)'!$A16)/365)-1) -> -0.0029405883 | S17: =IF(Q17="","",Q17/MAX(Q$5:Q17)-1) -> -0.023380317
A18: =IF('实盘净值数据(iFinD公式)'!A18="","",'实盘净值数据(iFinD公式)'!A18) -> 46211 | B18: =IF(OR((ROW()-1)<6,'实盘净值数据(iFinD公式)'!$A18="",'实盘净值数据(iFinD公式)'!$B18=""),"",SUMPRODUCT(实盘持仓配置!$B$4:$X$4,'实盘净值数据(iFinD公式)'!$B18:$X18/'实盘净值数据(iFinD公式)'!$B$6:$X$6)*(1-实盘持仓配置!$Z$4)^(('实盘净值数据(iFinD公式)'!$A18-'实盘净值数据(iFinD公式)'!$A$6)/365)) -> 0.93090197 | C18: =IF(OR(B17="",'实盘净值数据(iFinD公式)'!$A18="",'实盘净值数据(iFinD公式)'!$B18=""),"",(SUMPRODUCT(实盘持仓配置!$B$4:$X$4,'实盘净值数据(iFinD公式)'!$B17:$X17/'实盘净值数据(iFinD公式)'!$B$6:$X$6,'实盘净值数据(iFinD公式)'!$B18:$X18/'实盘净值数据(iFinD公式)'!$B17:$X17)/SUMPRODUCT(实盘持仓配置!$B$4:$X$4,'实盘净值数据(iFinD公式)'!$B17:$X17/'实盘净值数据(iFinD公式)'!$B$6:$X$6))*(1-实盘持仓配置!$Z$4)^(('实盘净值数据(iFinD公式)'!$A18-'实盘净值数据(iFinD公式)'!$A17)/365)-1) -> -4.140637e-05 | D18: =IF(B18="","",B18/MAX(B$5:B18)-1) -> -0.13392215 | E18: =IF(OR((ROW()-1)<5,'实盘净值数据(iFinD公式)'!$A18="",'实盘净值数据(iFinD公式)'!$B18=""),"",SUMPRODUCT(实盘持仓配置!$B$5:$X$5,'实盘净值数据(iFinD公式)'!$B18:$X18/'实盘净值数据(iFinD公式)'!$B$5:$X$5)*(1-实盘持仓配置!$Z$5)^(('实盘净值数据(iFinD公式)'!$A18-'实盘净值数据(iFinD公式)'!$A$5)/365)) -> 0.95244393 | F18: =IF(OR(E17="",'实盘净值数据(iFinD公式)'!$A18="",'实盘净值数据(iFinD公式)'!$B18=""),"",(SUMPRODUCT(实盘持仓配置!$B$5:$X$5,'实盘净值数据(iFinD公式)'!$B17:$X17/'实盘净值数据(iFinD公式)'!$B$5:$X$5,'实盘净值数据(iFinD公式)'!$B18:$X18/'实盘净值数据(iFinD公式)'!$B17:$X17)/SUMPRODUCT(实盘持仓配置!$B$5:$X$5,'实盘净值数据(iFinD公式)'!$B17:$X17/'实盘净值数据(iFinD公式)'!$B$5:$X$5))*(1-实盘持仓配置!$Z$5)^(('实盘净值数据(iFinD公式)'!$A18-'实盘净值数据(iFinD公式)'!$A17)/365)-1) -> -3.3075018e-05 | G18: =IF(E18="","",E18/MAX(E$5:E18)-1) -> -0.13393472 | H18: =IF(OR((ROW()-1)<7,'实盘净值数据(iFinD公式)'!$A18="",'实盘净值数据(iFinD公式)'!$B18=""),"",SUMPRODUCT(实盘持仓配置!$B$6:$X$6,'实盘净值数据(iFinD公式)'!$B18:$X18/'实盘净值数据(iFinD公式)'!$B$7:$X$7)*(1-实盘持仓配置!$Z$6)^(('实盘净值数据(iFinD公式)'!$A18-'实盘净值数据(iFinD公式)'!$A$7)/365)) -> 0.97473391 | I18: =IF(OR(H17="",'实盘净值数据(iFinD公式)'!$A18="",'实盘净值数据(iFinD公式)'!$B18=""),"",(SUMPRODUCT(实盘持仓配置!$B$6:$X$6,'实盘净值数据(iFinD公式)'!$B17:$X17/'实盘净值数据(iFinD公式)'!$B$7:$X$7,'实盘净值数据(iFinD公式)'!$B18:$X18/'实盘净值数据(iFinD公式)'!$B17:$X17)/SUMPRODUCT(实盘持仓配置!$B$6:$X$6,'实盘净值数据(iFinD公式)'!$B17:$X17/'实盘净值数据(iFinD公式)'!$B$7:$X$7))*(1-实盘持仓配置!$Z$6)^(('实盘净值数据(iFinD公式)'!$A18-'实盘净值数据(iFinD公式)'!$A17)/365)-1) -> -4.140637e-05 | J18: =IF(H18="","",H18/MAX(H$5:H18)-1) -> -0.12320946 | K18: =IF(OR((ROW()-1)<8,'实盘净值数据(iFinD公式)'!$A18="",'实盘净值数据(iFinD公式)'!$B18=""),"",SUMPRODUCT(实盘持仓配置!$B$7:$X$7,'实盘净值数据(iFinD公式)'!$B18:$X18/'实盘净值数据(iFinD公式)'!$B$8:$X$8)*(1-实盘持仓配置!$Z$7)^(('实盘净值数据(iFinD公式)'!$A18-'实盘净值数据(iFinD公式)'!$A$8)/365)) -> 0.99562081 | L18: =IF(OR(K17="",'实盘净值数据(iFinD公式)'!$A18="",'实盘净值数据(iFinD公式)'!$B18=""),"",(SUMPRODUCT(实盘持仓配置!$B$7:$X$7,'实盘净值数据(iFinD公式)'!$B17:$X17/'实盘净值数据(iFinD公式)'!$B$8:$X$8,'实盘净值数据(iFinD公式)'!$B18:$X18/'实盘净值数据(iFinD公式)'!$B17:$X17)/SUMPRODUCT(实盘持仓配置!$B$7:$X$7,'实盘净值数据(iFinD公式)'!$B17:$X17/'实盘净值数据(iFinD公式)'!$B$8:$X$8))*(1-实盘持仓配置!$Z$7)^(('实盘净值数据(iFinD公式)'!$A18-'实盘净值数据(iFinD公式)'!$A17)/365)-1) -> -2.2005708e-05 | M18: =IF(K18="","",K18/MAX(K$5:K18)-1) -> -0.0076262314 | N18: =IF(OR((ROW()-1)<5,'实盘净值数据(iFinD公式)'!$A18="",'实盘净值数据(iFinD公式)'!$B18=""),"",SUMPRODUCT(实盘持仓配置!$B$8:$X$8,'实盘净值数据(iFinD公式)'!$B18:$X18/'实盘净值数据(iFinD公式)'!$B$5:$X$5)*(1-实盘持仓配置!$Z$8)^(('实盘净值数据(iFinD公式)'!$A18-'实盘净值数据(iFinD公式)'!$A$5)/365)) -> 0.99424055 | O18: =IF(OR(N17="",'实盘净值数据(iFinD公式)'!$A18="",'实盘净值数据(iFinD公式)'!$B18=""),"",(SUMPRODUCT(实盘持仓配置!$B$8:$X$8,'实盘净值数据(iFinD公式)'!$B17:$X17/'实盘净值数据(iFinD公式)'!$B$5:$X$5,'实盘净值数据(iFinD公式)'!$B18:$X18/'实盘净值数据(iFinD公式)'!$B17:$X17)/SUMPRODUCT(实盘持仓配置!$B$8:$X$8,'实盘净值数据(iFinD公式)'!$B17:$X17/'实盘净值数据(iFinD公式)'!$B$5:$X$5))*(1-实盘持仓配置!$Z$8)^(('实盘净值数据(iFinD公式)'!$A18-'实盘净值数据(iFinD公式)'!$A17)/365)-1) -> -1.3732897e-05 | P18: =IF(N18="","",N18/MAX(N$5:N18)-1) -> -0.0084466925 | Q18: =IF(OR((ROW()-1)<8,'实盘净值数据(iFinD公式)'!$A18="",'实盘净值数据(iFinD公式)'!$B18=""),"",SUMPRODUCT(实盘持仓配置!$B$9:$X$9,'实盘净值数据(iFinD公式)'!$B18:$X18/'实盘净值数据(iFinD公式)'!$B$8:$X$8)*(1-实盘持仓配置!$Z$9)^(('实盘净值数据(iFinD公式)'!$A18-'实盘净值数据(iFinD公式)'!$A$8)/365)) -> 0.98514411 | R18: =IF(OR(Q17="",'实盘净值数据(iFinD公式)'!$A18="",'实盘净值数据(iFinD公式)'!$B18=""),"",(SUMPRODUCT(实盘持仓配置!$B$9:$X$9,'实盘净值数据(iFinD公式)'!$B17:$X17/'实盘净值数据(iFinD公式)'!$B$8:$X$8,'实盘净值数据(iFinD公式)'!$B18:$X18/'实盘净值数据(iFinD公式)'!$B17:$X17)/SUMPRODUCT(实盘持仓配置!$B$9:$X$9,'实盘净值数据(iFinD公式)'!$B17:$X17/'实盘净值数据(iFinD公式)'!$B$8:$X$8))*(1-实盘持仓配置!$Z$9)^(('实盘净值数据(iFinD公式)'!$A18-'实盘净值数据(iFinD公式)'!$A17)/365)-1) -> -3.3075018e-05 | S18: =IF(Q18="","",Q18/MAX(Q$5:Q18)-1) -> -0.023412619
A19: =IF('实盘净值数据(iFinD公式)'!A19="","",'实盘净值数据(iFinD公式)'!A19) | B19: =IF(OR((ROW()-1)<6,'实盘净值数据(iFinD公式)'!$A19="",'实盘净值数据(iFinD公式)'!$B19=""),"",SUMPRODUCT(实盘持仓配置!$B$4:$X$4,'实盘净值数据(iFinD公式)'!$B19:$X19/'实盘净值数据(iFinD公式)'!$B$6:$X$6)*(1-实盘持仓配置!$Z$4)^(('实盘净值数据(iFinD公式)'!$A19-'实盘净值数据(iFinD公式)'!$A$6)/365)) | C19: =IF(OR(B18="",'实盘净值数据(iFinD公式)'!$A19="",'实盘净值数据(iFinD公式)'!$B19=""),"",(SUMPRODUCT(实盘持仓配置!$B$4:$X$4,'实盘净值数据(iFinD公式)'!$B18:$X18/'实盘净值数据(iFinD公式)'!$B$6:$X$6,'实盘净值数据(iFinD公式)'!$B19:$X19/'实盘净值数据(iFinD公式)'!$B18:$X18)/SUMPRODUCT(实盘持仓配置!$B$4:$X$4,'实盘净值数据(iFinD公式)'!$B18:$X18/'实盘净值数据(iFinD公式)'!$B$6:$X$6))*(1-实盘持仓配置!$Z$4)^(('实盘净值数据(iFinD公式)'!$A19-'实盘净值数据(iFinD公式)'!$A18)/365)-1) | D19: =IF(B19="","",B19/MAX(B$5:B19)-1) | E19: =IF(OR((ROW()-1)<5,'实盘净值数据(iFinD公式)'!$A19="",'实盘净值数据(iFinD公式)'!$B19=""),"",SUMPRODUCT(实盘持仓配置!$B$5:$X$5,'实盘净值数据(iFinD公式)'!$B19:$X19/'实盘净值数据(iFinD公式)'!$B$5:$X$5)*(1-实盘持仓配置!$Z$5)^(('实盘净值数据(iFinD公式)'!$A19-'实盘净值数据(iFinD公式)'!$A$5)/365)) | F19: =IF(OR(E18="",'实盘净值数据(iFinD公式)'!$A19="",'实盘净值数据(iFinD公式)'!$B19=""),"",(SUMPRODUCT(实盘持仓配置!$B$5:$X$5,'实盘净值数据(iFinD公式)'!$B18:$X18/'实盘净值数据(iFinD公式)'!$B$5:$X$5,'实盘净值数据(iFinD公式)'!$B19:$X19/'实盘净值数据(iFinD公式)'!$B18:$X18)/SUMPRODUCT(实盘持仓配置!$B$5:$X$5,'实盘净值数据(iFinD公式)'!$B18:$X18/'实盘净值数据(iFinD公式)'!$B$5:$X$5))*(1-实盘持仓配置!$Z$5)^(('实盘净值数据(iFinD公式)'!$A19-'实盘净值数据(iFinD公式)'!$A18)/365)-1) | G19: =IF(E19="","",E19/MAX(E$5:E19)-1) | H19: =IF(OR((ROW()-1)<7,'实盘净值数据(iFinD公式)'!$A19="",'实盘净值数据(iFinD公式)'!$B19=""),"",SUMPRODUCT(实盘持仓配置!$B$6:$X$6,'实盘净值数据(iFinD公式)'!$B19:$X19/'实盘净值数据(iFinD公式)'!$B$7:$X$7)*(1-实盘持仓配置!$Z$6)^(('实盘净值数据(iFinD公式)'!$A19-'实盘净值数据(iFinD公式)'!$A$7)/365)) | I19: =IF(OR(H18="",'实盘净值数据(iFinD公式)'!$A19="",'实盘净值数据(iFinD公式)'!$B19=""),"",(SUMPRODUCT(实盘持仓配置!$B$6:$X$6,'实盘净值数据(iFinD公式)'!$B18:$X18/'实盘净值数据(iFinD公式)'!$B$7:$X$7,'实盘净值数据(iFinD公式)'!$B19:$X19/'实盘净值数据(iFinD公式)'!$B18:$X18)/SUMPRODUCT(实盘持仓配置!$B$6:$X$6,'实盘净值数据(iFinD公式)'!$B18:$X18/'实盘净值数据(iFinD公式)'!$B$7:$X$7))*(1-实盘持仓配置!$Z$6)^(('实盘净值数据(iFinD公式)'!$A19-'实盘净值数据(iFinD公式)'!$A18)/365)-1) | J19: =IF(H19="","",H19/MAX(H$5:H19)-1) | K19: =IF(OR((ROW()-1)<8,'实盘净值数据(iFinD公式)'!$A19="",'实盘净值数据(iFinD公式)'!$B19=""),"",SUMPRODUCT(实盘持仓配置!$B$7:$X$7,'实盘净值数据(iFinD公式)'!$B19:$X19/'实盘净值数据(iFinD公式)'!$B$8:$X$8)*(1-实盘持仓配置!$Z$7)^(('实盘净值数据(iFinD公式)'!$A19-'实盘净值数据(iFinD公式)'!$A$8)/365)) | L19: =IF(OR(K18="",'实盘净值数据(iFinD公式)'!$A19="",'实盘净值数据(iFinD公式)'!$B19=""),"",(SUMPRODUCT(实盘持仓配置!$B$7:$X$7,'实盘净值数据(iFinD公式)'!$B18:$X18/'实盘净值数据(iFinD公式)'!$B$8:$X$8,'实盘净值数据(iFinD公式)'!$B19:$X19/'实盘净值数据(iFinD公式)'!$B18:$X18)/SUMPRODUCT(实盘持仓配置!$B$7:$X$7,'实盘净值数据(iFinD公式)'!$B18:$X18/'实盘净值数据(iFinD公式)'!$B$8:$X$8))*(1-实盘持仓配置!$Z$7)^(('实盘净值数据(iFinD公式)'!$A19-'实盘净值数据(iFinD公式)'!$A18)/365)-1) | M19: =IF(K19="","",K19/MAX(K$5:K19)-1) | N19: =IF(OR((ROW()-1)<5,'实盘净值数据(iFinD公式)'!$A19="",'实盘净值数据(iFinD公式)'!$B19=""),"",SUMPRODUCT(实盘持仓配置!$B$8:$X$8,'实盘净值数据(iFinD公式)'!$B19:$X19/'实盘净值数据(iFinD公式)'!$B$5:$X$5)*(1-实盘持仓配置!$Z$8)^(('实盘净值数据(iFinD公式)'!$A19-'实盘净值数据(iFinD公式)'!$A$5)/365)) | O19: =IF(OR(N18="",'实盘净值数据(iFinD公式)'!$A19="",'实盘净值数据(iFinD公式)'!$B19=""),"",(SUMPRODUCT(实盘持仓配置!$B$8:$X$8,'实盘净值数据(iFinD公式)'!$B18:$X18/'实盘净值数据(iFinD公式)'!$B$5:$X$5,'实盘净值数据(iFinD公式)'!$B19:$X19/'实盘净值数据(iFinD公式)'!$B18:$X18)/SUMPRODUCT(实盘持仓配置!$B$8:$X$8,'实盘净值数据(iFinD公式)'!$B18:$X18/'实盘净值数据(iFinD公式)'!$B$5:$X$5))*(1-实盘持仓配置!$Z$8)^(('实盘净值数据(iFinD公式)'!$A19-'实盘净值数据(iFinD公式)'!$A18)/365)-1) | P19: =IF(N19="","",N19/MAX(N$5:N19)-1) | Q19: =IF(OR((ROW()-1)<8,'实盘净值数据(iFinD公式)'!$A19="",'实盘净值数据(iFinD公式)'!$B19=""),"",SUMPRODUCT(实盘持仓配置!$B$9:$X$9,'实盘净值数据(iFinD公式)'!$B19:$X19/'实盘净值数据(iFinD公式)'!$B$8:$X$8)*(1-实盘持仓配置!$Z$9)^(('实盘净值数据(iFinD公式)'!$A19-'实盘净值数据(iFinD公式)'!$A$8)/365)) | R19: =IF(OR(Q18="",'实盘净值数据(iFinD公式)'!$A19="",'实盘净值数据(iFinD公式)'!$B19=""),"",(SUMPRODUCT(实盘持仓配置!$B$9:$X$9,'实盘净值数据(iFinD公式)'!$B18:$X18/'实盘净值数据(iFinD公式)'!$B$8:$X$8,'实盘净值数据(iFinD公式)'!$B19:$X19/'实盘净值数据(iFinD公式)'!$B18:$X18)/SUMPRODUCT(实盘持仓配置!$B$9:$X$9,'实盘净值数据(iFinD公式)'!$B18:$X18/'实盘净值数据(iFinD公式)'!$B$8:$X$8))*(1-实盘持仓配置!$Z$9)^(('实盘净值数据(iFinD公式)'!$A19-'实盘净值数据(iFinD公式)'!$A18)/365)-1) | S19: =IF(Q19="","",Q19/MAX(Q$5:Q19)-1)
A20: =IF('实盘净值数据(iFinD公式)'!A20="","",'实盘净值数据(iFinD公式)'!A20) | B20: =IF(OR((ROW()-1)<6,'实盘净值数据(iFinD公式)'!$A20="",'实盘净值数据(iFinD公式)'!$B20=""),"",SUMPRODUCT(实盘持仓配置!$B$4:$X$4,'实盘净值数据(iFinD公式)'!$B20:$X20/'实盘净值数据(iFinD公式)'!$B$6:$X$6)*(1-实盘持仓配置!$Z$4)^(('实盘净值数据(iFinD公式)'!$A20-'实盘净值数据(iFinD公式)'!$A$6)/365)) | C20: =IF(OR(B19="",'实盘净值数据(iFinD公式)'!$A20="",'实盘净值数据(iFinD公式)'!$B20=""),"",(SUMPRODUCT(实盘持仓配置!$B$4:$X$4,'实盘净值数据(iFinD公式)'!$B19:$X19/'实盘净值数据(iFinD公式)'!$B$6:$X$6,'实盘净值数据(iFinD公式)'!$B20:$X20/'实盘净值数据(iFinD公式)'!$B19:$X19)/SUMPRODUCT(实盘持仓配置!$B$4:$X$4,'实盘净值数据(iFinD公式)'!$B19:$X19/'实盘净值数据(iFinD公式)'!$B$6:$X$6))*(1-实盘持仓配置!$Z$4)^(('实盘净值数据(iFinD公式)'!$A20-'实盘净值数据(iFinD公式)'!$A19)/365)-1) | D20: =IF(B20="","",B20/MAX(B$5:B20)-1) | E20: =IF(OR((ROW()-1)<5,'实盘净值数据(iFinD公式)'!$A20="",'实盘净值数据(iFinD公式)'!$B20=""),"",SUMPRODUCT(实盘持仓配置!$B$5:$X$5,'实盘净值数据(iFinD公式)'!$B20:$X20/'实盘净值数据(iFinD公式)'!$B$5:$X$5)*(1-实盘持仓配置!$Z$5)^(('实盘净值数据(iFinD公式)'!$A20-'实盘净值数据(iFinD公式)'!$A$5)/365)) | F20: =IF(OR(E19="",'实盘净值数据(iFinD公式)'!$A20="",'实盘净值数据(iFinD公式)'!$B20=""),"",(SUMPRODUCT(实盘持仓配置!$B$5:$X$5,'实盘净值数据(iFinD公式)'!$B19:$X19/'实盘净值数据(iFinD公式)'!$B$5:$X$5,'实盘净值数据(iFinD公式)'!$B20:$X20/'实盘净值数据(iFinD公式)'!$B19:$X19)/SUMPRODUCT(实盘持仓配置!$B$5:$X$5,'实盘净值数据(iFinD公式)'!$B19:$X19/'实盘净值数据(iFinD公式)'!$B$5:$X$5))*(1-实盘持仓配置!$Z$5)^(('实盘净值数据(iFinD公式)'!$A20-'实盘净值数据(iFinD公式)'!$A19)/365)-1) | G20: =IF(E20="","",E20/MAX(E$5:E20)-1) | H20: =IF(OR((ROW()-1)<7,'实盘净值数据(iFinD公式)'!$A20="",'实盘净值数据(iFinD公式)'!$B20=""),"",SUMPRODUCT(实盘持仓配置!$B$6:$X$6,'实盘净值数据(iFinD公式)'!$B20:$X20/'实盘净值数据(iFinD公式)'!$B$7:$X$7)*(1-实盘持仓配置!$Z$6)^(('实盘净值数据(iFinD公式)'!$A20-'实盘净值数据(iFinD公式)'!$A$7)/365)) | I20: =IF(OR(H19="",'实盘净值数据(iFinD公式)'!$A20="",'实盘净值数据(iFinD公式)'!$B20=""),"",(SUMPRODUCT(实盘持仓配置!$B$6:$X$6,'实盘净值数据(iFinD公式)'!$B19:$X19/'实盘净值数据(iFinD公式)'!$B$7:$X$7,'实盘净值数据(iFinD公式)'!$B20:$X20/'实盘净值数据(iFinD公式)'!$B19:$X19)/SUMPRODUCT(实盘持仓配置!$B$6:$X$6,'实盘净值数据(iFinD公式)'!$B19:$X19/'实盘净值数据(iFinD公式)'!$B$7:$X$7))*(1-实盘持仓配置!$Z$6)^(('实盘净值数据(iFinD公式)'!$A20-'实盘净值数据(iFinD公式)'!$A19)/365)-1) | J20: =IF(H20="","",H20/MAX(H$5:H20)-1) | K20: =IF(OR((ROW()-1)<8,'实盘净值数据(iFinD公式)'!$A20="",'实盘净值数据(iFinD公式)'!$B20=""),"",SUMPRODUCT(实盘持仓配置!$B$7:$X$7,'实盘净值数据(iFinD公式)'!$B20:$X20/'实盘净值数据(iFinD公式)'!$B$8:$X$8)*(1-实盘持仓配置!$Z$7)^(('实盘净值数据(iFinD公式)'!$A20-'实盘净值数据(iFinD公式)'!$A$8)/365)) | L20: =IF(OR(K19="",'实盘净值数据(iFinD公式)'!$A20="",'实盘净值数据(iFinD公式)'!$B20=""),"",(SUMPRODUCT(实盘持仓配置!$B$7:$X$7,'实盘净值数据(iFinD公式)'!$B19:$X19/'实盘净值数据(iFinD公式)'!$B$8:$X$8,'实盘净值数据(iFinD公式)'!$B20:$X20/'实盘净值数据(iFinD公式)'!$B19:$X19)/SUMPRODUCT(实盘持仓配置!$B$7:$X$7,'实盘净值数据(iFinD公式)'!$B19:$X19/'实盘净值数据(iFinD公式)'!$B$8:$X$8))*(1-实盘持仓配置!$Z$7)^(('实盘净值数据(iFinD公式)'!$A20-'实盘净值数据(iFinD公式)'!$A19)/365)-1) | M20: =IF(K20="","",K20/MAX(K$5:K20)-1) | N20: =IF(OR((ROW()-1)<5,'实盘净值数据(iFinD公式)'!$A20="",'实盘净值数据(iFinD公式)'!$B20=""),"",SUMPRODUCT(实盘持仓配置!$B$8:$X$8,'实盘净值数据(iFinD公式)'!$B20:$X20/'实盘净值数据(iFinD公式)'!$B$5:$X$5)*(1-实盘持仓配置!$Z$8)^(('实盘净值数据(iFinD公式)'!$A20-'实盘净值数据(iFinD公式)'!$A$5)/365)) | O20: =IF(OR(N19="",'实盘净值数据(iFinD公式)'!$A20="",'实盘净值数据(iFinD公式)'!$B20=""),"",(SUMPRODUCT(实盘持仓配置!$B$8:$X$8,'实盘净值数据(iFinD公式)'!$B19:$X19/'实盘净值数据(iFinD公式)'!$B$5:$X$5,'实盘净值数据(iFinD公式)'!$B20:$X20/'实盘净值数据(iFinD公式)'!$B19:$X19)/SUMPRODUCT(实盘持仓配置!$B$8:$X$8,'实盘净值数据(iFinD公式)'!$B19:$X19/'实盘净值数据(iFinD公式)'!$B$5:$X$5))*(1-实盘持仓配置!$Z$8)^(('实盘净值数据(iFinD公式)'!$A20-'实盘净值数据(iFinD公式)'!$A19)/365)-1) | P20: =IF(N20="","",N20/MAX(N$5:N20)-1) | Q20: =IF(OR((ROW()-1)<8,'实盘净值数据(iFinD公式)'!$A20="",'实盘净值数据(iFinD公式)'!$B20=""),"",SUMPRODUCT(实盘持仓配置!$B$9:$X$9,'实盘净值数据(iFinD公式)'!$B20:$X20/'实盘净值数据(iFinD公式)'!$B$8:$X$8)*(1-实盘持仓配置!$Z$9)^(('实盘净值数据(iFinD公式)'!$A20-'实盘净值数据(iFinD公式)'!$A$8)/365)) | R20: =IF(OR(Q19="",'实盘净值数据(iFinD公式)'!$A20="",'实盘净值数据(iFinD公式)'!$B20=""),"",(SUMPRODUCT(实盘持仓配置!$B$9:$X$9,'实盘净值数据(iFinD公式)'!$B19:$X19/'实盘净值数据(iFinD公式)'!$B$8:$X$8,'实盘净值数据(iFinD公式)'!$B20:$X20/'实盘净值数据(iFinD公式)'!$B19:$X19)/SUMPRODUCT(实盘持仓配置!$B$9:$X$9,'实盘净值数据(iFinD公式)'!$B19:$X19/'实盘净值数据(iFinD公式)'!$B$8:$X$8))*(1-实盘持仓配置!$Z$9)^(('实盘净值数据(iFinD公式)'!$A20-'实盘净值数据(iFinD公式)'!$A19)/365)-1) | S20: =IF(Q20="","",Q20/MAX(Q$5:Q20)-1)
... A59: =IF('实盘净值数据(iFinD公式)'!A59="","",'实盘净值数据(iFinD公式)'!A59) | B59: =IF(OR((ROW()-1)<6,'实盘净值数据(iFinD公式)'!$A59="",'实盘净值数据(iFinD公式)'!$B59=""),"",SUMPRODUCT(实盘持仓配置!$B$4:$X$4,'实盘净值数据(iFinD公式)'!$B59:$X59/'实盘净值数据(iFinD公式)'!$B$6:$X$6)*(1-实盘持仓配置!$Z$4)^(('实盘净值数据(iFinD公式)'!$A59-'实盘净值数据(iFinD公式)'!$A$6)/365)) | C59: =IF(OR(B58="",'实盘净值数据(iFinD公式)'!$A59="",'实盘净值数据(iFinD公式)'!$B59=""),"",(SUMPRODUCT(实盘持仓配置!$B$4:$X$4,'实盘净值数据(iFinD公式)'!$B58:$X58/'实盘净值数据(iFinD公式)'!$B$6:$X$6,'实盘净值数据(iFinD公式)'!$B59:$X59/'实盘净值数据(iFinD公式)'!$B58:$X58)/SUMPRODUCT(实盘持仓配置!$B$4:$X$4,'实盘净值数据(iFinD公式)'!$B58:$X58/'实盘净值数据(iFinD公式)'!$B$6:$X$6))*(1-实盘持仓配置!$Z$4)^(('实盘净值数据(iFinD公式)'!$A59-'实盘净值数据(iFinD公式)'!$A58)/365)-1) | D59: =IF(B59="","",B59/MAX(B$5:B59)-1) | E59: =IF(OR((ROW()-1)<5,'实盘净值数据(iFinD公式)'!$A59="",'实盘净值数据(iFinD公式)'!$B59=""),"",SUMPRODUCT(实盘持仓配置!$B$5:$X$5,'实盘净值数据(iFinD公式)'!$B59:$X59/'实盘净值数据(iFinD公式)'!$B$5:$X$5)*(1-实盘持仓配置!$Z$5)^(('实盘净值数据(iFinD公式)'!$A59-'实盘净值数据(iFinD公式)'!$A$5)/365)) | F59: =IF(OR(E58="",'实盘净值数据(iFinD公式)'!$A59="",'实盘净值数据(iFinD公式)'!$B59=""),"",(SUMPRODUCT(实盘持仓配置!$B$5:$X$5,'实盘净值数据(iFinD公式)'!$B58:$X58/'实盘净值数据(iFinD公式)'!$B$5:$X$5,'实盘净值数据(iFinD公式)'!$B59:$X59/'实盘净值数据(iFinD公式)'!$B58:$X58)/SUMPRODUCT(实盘持仓配置!$B$5:$X$5,'实盘净值数据(iFinD公式)'!$B58:$X58/'实盘净值数据(iFinD公式)'!$B$5:$X$5))*(1-实盘持仓配置!$Z$5)^(('实盘净值数据(iFinD公式)'!$A59-'实盘净值数据(iFinD公式)'!$A58)/365)-1) | G59: =IF(E59="","",E59/MAX(E$5:E59)-1) | H59: =IF(OR((ROW()-1)<7,'实盘净值数据(iFinD公式)'!$A59="",'实盘净值数据(iFinD公式)'!$B59=""),"",SUMPRODUCT(实盘持仓配置!$B$6:$X$6,'实盘净值数据(iFinD公式)'!$B59:$X59/'实盘净值数据(iFinD公式)'!$B$7:$X$7)*(1-实盘持仓配置!$Z$6)^(('实盘净值数据(iFinD公式)'!$A59-'实盘净值数据(iFinD公式)'!$A$7)/365)) | I59: =IF(OR(H58="",'实盘净值数据(iFinD公式)'!$A59="",'实盘净值数据(iFinD公式)'!$B59=""),"",(SUMPRODUCT(实盘持仓配置!$B$6:$X$6,'实盘净值数据(iFinD公式)'!$B58:$X58/'实盘净值数据(iFinD公式)'!$B$7:$X$7,'实盘净值数据(iFinD公式)'!$B59:$X59/'实盘净值数据(iFinD公式)'!$B58:$X58)/SUMPRODUCT(实盘持仓配置!$B$6:$X$6,'实盘净值数据(iFinD公式)'!$B58:$X58/'实盘净值数据(iFinD公式)'!$B$7:$X$7))*(1-实盘持仓配置!$Z$6)^(('实盘净值数据(iFinD公式)'!$A59-'实盘净值数据(iFinD公式)'!$A58)/365)-1) | J59: =IF(H59="","",H59/MAX(H$5:H59)-1) | K59: =IF(OR((ROW()-1)<8,'实盘净值数据(iFinD公式)'!$A59="",'实盘净值数据(iFinD公式)'!$B59=""),"",SUMPRODUCT(实盘持仓配置!$B$7:$X$7,'实盘净值数据(iFinD公式)'!$B59:$X59/'实盘净值数据(iFinD公式)'!$B$8:$X$8)*(1-实盘持仓配置!$Z$7)^(('实盘净值数据(iFinD公式)'!$A59-'实盘净值数据(iFinD公式)'!$A$8)/365)) | L59: =IF(OR(K58="",'实盘净值数据(iFinD公式)'!$A59="",'实盘净值数据(iFinD公式)'!$B59=""),"",(SUMPRODUCT(实盘持仓配置!$B$7:$X$7,'实盘净值数据(iFinD公式)'!$B58:$X58/'实盘净值数据(iFinD公式)'!$B$8:$X$8,'实盘净值数据(iFinD公式)'!$B59:$X59/'实盘净值数据(iFinD公式)'!$B58:$X58)/SUMPRODUCT(实盘持仓配置!$B$7:$X$7,'实盘净值数据(iFinD公式)'!$B58:$X58/'实盘净值数据(iFinD公式)'!$B$8:$X$8))*(1-实盘持仓配置!$Z$7)^(('实盘净值数据(iFinD公式)'!$A59-'实盘净值数据(iFinD公式)'!$A58)/365)-1) | M59: =IF(K59="","",K59/MAX(K$5:K59)-1) | N59: =IF(OR((ROW()-1)<5,'实盘净值数据(iFinD公式)'!$A59="",'实盘净值数据(iFinD公式)'!$B59=""),"",SUMPRODUCT(实盘持仓配置!$B$8:$X$8,'实盘净值数据(iFinD公式)'!$B59:$X59/'实盘净值数据(iFinD公式)'!$B$5:$X$5)*(1-实盘持仓配置!$Z$8)^(('实盘净值数据(iFinD公式)'!$A59-'实盘净值数据(iFinD公式)'!$A$5)/365)) | O59: =IF(OR(N58="",'实盘净值数据(iFinD公式)'!$A59="",'实盘净值数据(iFinD公式)'!$B59=""),"",(SUMPRODUCT(实盘持仓配置!$B$8:$X$8,'实盘净值数据(iFinD公式)'!$B58:$X58/'实盘净值数据(iFinD公式)'!$B$5:$X$5,'实盘净值数据(iFinD公式)'!$B59:$X59/'实盘净值数据(iFinD公式)'!$B58:$X58)/SUMPRODUCT(实盘持仓配置!$B$8:$X$8,'实盘净值数据(iFinD公式)'!$B58:$X58/'实盘净值数据(iFinD公式)'!$B$5:$X$5))*(1-实盘持仓配置!$Z$8)^(('实盘净值数据(iFinD公式)'!$A59-'实盘净值数据(iFinD公式)'!$A58)/365)-1) | P59: =IF(N59="","",N59/MAX(N$5:N59)-1) | Q59: =IF(OR((ROW()-1)<8,'实盘净值数据(iFinD公式)'!$A59="",'实盘净值数据(iFinD公式)'!$B59=""),"",SUMPRODUCT(实盘持仓配置!$B$9:$X$9,'实盘净值数据(iFinD公式)'!$B59:$X59/'实盘净值数据(iFinD公式)'!$B$8:$X$8)*(1-实盘持仓配置!$Z$9)^(('实盘净值数据(iFinD公式)'!$A59-'实盘净值数据(iFinD公式)'!$A$8)/365)) | R59: =IF(OR(Q58="",'实盘净值数据(iFinD公式)'!$A59="",'实盘净值数据(iFinD公式)'!$B59=""),"",(SUMPRODUCT(实盘持仓配置!$B$9:$X$9,'实盘净值数据(iFinD公式)'!$B58:$X58/'实盘净值数据(iFinD公式)'!$B$8:$X$8,'实盘净值数据(iFinD公式)'!$B59:$X59/'实盘净值数据(iFinD公式)'!$B58:$X58)/SUMPRODUCT(实盘持仓配置!$B$9:$X$9,'实盘净值数据(iFinD公式)'!$B58:$X58/'实盘净值数据(iFinD公式)'!$B$8:$X$8))*(1-实盘持仓配置!$Z$9)^(('实盘净值数据(iFinD公式)'!$A59-'实盘净值数据(iFinD公式)'!$A58)/365)-1) | S59: =IF(Q59="","",Q59/MAX(Q$5:Q59)-1)
A61: 各组合自其净值起始日起=1.0000；买入持有，权重随涨跌漂移；净值已按各自年化费率折每日扣费。新增日期下拉填充。
