Workbook
Name chtB: OFFSET(组合净值!$B$6,0,0,COUNT(组合净值!$B$6:$B$2000),1)
Name chtDate: OFFSET(组合净值!$A$6,0,0,COUNT(组合净值!$B$6:$B$2000),1)
Name chtE: OFFSET(组合净值!$E$6,0,0,COUNT(组合净值!$E$6:$E$2000),1)
Name chtH: OFFSET(组合净值!$H$6,0,0,COUNT(组合净值!$H$6:$H$2000),1)
Name chtK: OFFSET(组合净值!$K$6,0,0,COUNT(组合净值!$K$6:$K$2000),1)

Sheet 持仓配置
A1: 持仓配置（初始权重）
A2: 基金简称 | B2: 宏利复兴混合A | C2: 信澳业绩驱动A | D2: 嘉实信息产业A | E2: 银华集成电路混合A | F2: 中欧中证500指增A | G2: 天弘中证1000指增A | H2: 华泰柏瑞中证2000指增A | I2: 博道沪深300指增A | J2: 易方达中债新综指LOFA | K2: 华安黄金ETF联接A | L2: 国泰半导体材料设备ETF联接A | M2: 国泰通信设备ETF联接A | N2: 嘉实快线货币A | O2: 合计 | P2: 年化费率(年)
A3: 基金代码 | B3: 001170.OF | C3: 016370.OF | D3: 017488.OF | E3: 013840.OF | F3: 015453.OF | G3: 014201.OF | H3: 019923.OF | I3: 007044.OF | J3: 161119.OF | K3: 000216.OF | L3: 019632.OF | M3: 007817.OF | N3: 000917.OF
A4: 10-90 权重 | B4: 0.01 | C4: 0.01 | D4: 0.01 | E4: 0.01 | F4: 0.0125 | G4: 0.0125 | H4: 0.0125 | I4: 0.0125 | J4: 0.83 | K4: 0.05 | L4: 0.005 | M4: 0.005 | N4: 0.02 | O4: =SUM(B4:N4) | P4: 0.005
A5: 20-80 权重 | B5: 0.02 | C5: 0.02 | D5: 0.02 | E5: 0.02 | F5: 0.025 | G5: 0.025 | H5: 0.025 | I5: 0.025 | J5: 0.73 | K5: 0.05 | L5: 0.01 | M5: 0.01 | N5: 0.02 | O5: =SUM(B5:N5) | P5: 0.01
A6: 30-70 权重 | B6: 0.03 | C6: 0.03 | D6: 0.03 | E6: 0.03 | F6: 0.0375 | G6: 0.0375 | H6: 0.0375 | I6: 0.0375 | J6: 0.58 | K6: 0.1 | L6: 0.015 | M6: 0.015 | N6: 0.02 | O6: =SUM(B6:N6) | P6: 0.012
A7: 增值 权重 | B7: 0.19 | C7: 0.19 | D7: 0.19 | E7: 0.19 | F7: 0 | G7: 0 | H7: 0 | I7: 0 | J7: 0 | K7: 0 | L7: 0.11 | M7: 0.11 | N7: 0.02 | O7: =SUM(B7:N7) | P7: 0.012
A8: 基准指数(参考，不计入组合)
A9: 科创创业50等权 | B9: 932381.CSI
A10: 中证800 | B10: 000906.SH
A11: 沪深300 | B11: 000300.SH
A12: 中证500 | B12: 000905.SH
A13: 中证1000 | B13: 000852.SH
A14: 中证2000 | B14: 932000.CSI
A16: 权重为蓝色输入；P列为各组合年化费率(蓝色输入，已折每日扣减)。下游净值与看板自动重算。

Sheet 净值数据(iFinD公式)
A1: 净值数据 · iFinD 实时拉取（复权单位净值）
A2: =TODAY()-1
A3: 基金代码→ | B3: =持仓配置!B3 | C3: =持仓配置!C3 | D3: =持仓配置!D3 | E3: =持仓配置!E3 | F3: =持仓配置!F3 | G3: =持仓配置!G3 | H3: =持仓配置!H3 | I3: =持仓配置!I3 | ... N3: =持仓配置!N3
A4: =[1]!HX_AutoDate(1,"2026-05-29",A2,-1,-1,0,0,0,0,0,"SSE",25,0) | B4: 宏利复兴混合A | C4: 信澳业绩驱动A | D4: 嘉实信息产业A | E4: 银华集成电路混合A | F4: 中欧中证500指增A | G4: 天弘中证1000指增A | H4: 华泰柏瑞中证2000指增A | I4: 博道沪深300指增A | J4: 易方达中债新综指LOFA | K4: 华安黄金ETF联接A | L4: 国泰半导体材料设备ETF联接A | M4: 国泰通信设备ETF联接A | N4: 嘉实快线货币A
A5: 46171 | B5: =IF($A5="","",[1]!thsiFinD("ths_adjustment_nv_fund",B$3,$A5)) | C5: =IF($A5="","",[1]!thsiFinD("ths_adjustment_nv_fund",C$3,$A5)) | D5: =IF($A5="","",[1]!thsiFinD("ths_adjustment_nv_fund",D$3,$A5)) | E5: =IF($A5="","",[1]!thsiFinD("ths_adjustment_nv_fund",E$3,$A5)) | F5: =IF($A5="","",[1]!thsiFinD("ths_adjustment_nv_fund",F$3,$A5)) | G5: =IF($A5="","",[1]!thsiFinD("ths_adjustment_nv_fund",G$3,$A5)) | H5: =IF($A5="","",[1]!thsiFinD("ths_adjustment_nv_fund",H$3,$A5)) | I5: =IF($A5="","",[1]!thsiFinD("ths_adjustment_nv_fund",I$3,$A5)) | ... N5: =IF($A5="","",[1]!thsiFinD("ths_adjustment_nv_fund",N$3,$A5))
A6: 46174 | B6: =IF($A6="","",[1]!thsiFinD("ths_adjustment_nv_fund",B$3,$A6)) | C6: =IF($A6="","",[1]!thsiFinD("ths_adjustment_nv_fund",C$3,$A6)) | D6: =IF($A6="","",[1]!thsiFinD("ths_adjustment_nv_fund",D$3,$A6)) | E6: =IF($A6="","",[1]!thsiFinD("ths_adjustment_nv_fund",E$3,$A6)) | F6: =IF($A6="","",[1]!thsiFinD("ths_adjustment_nv_fund",F$3,$A6)) | G6: =IF($A6="","",[1]!thsiFinD("ths_adjustment_nv_fund",G$3,$A6)) | H6: =IF($A6="","",[1]!thsiFinD("ths_adjustment_nv_fund",H$3,$A6)) | I6: =IF($A6="","",[1]!thsiFinD("ths_adjustment_nv_fund",I$3,$A6)) | ... N6: =IF($A6="","",[1]!thsiFinD("ths_adjustment_nv_fund",N$3,$A6))
A7: 46175 | B7: =IF($A7="","",[1]!thsiFinD("ths_adjustment_nv_fund",B$3,$A7)) | C7: =IF($A7="","",[1]!thsiFinD("ths_adjustment_nv_fund",C$3,$A7)) | D7: =IF($A7="","",[1]!thsiFinD("ths_adjustment_nv_fund",D$3,$A7)) | E7: =IF($A7="","",[1]!thsiFinD("ths_adjustment_nv_fund",E$3,$A7)) | F7: =IF($A7="","",[1]!thsiFinD("ths_adjustment_nv_fund",F$3,$A7)) | G7: =IF($A7="","",[1]!thsiFinD("ths_adjustment_nv_fund",G$3,$A7)) | H7: =IF($A7="","",[1]!thsiFinD("ths_adjustment_nv_fund",H$3,$A7)) | I7: =IF($A7="","",[1]!thsiFinD("ths_adjustment_nv_fund",I$3,$A7)) | ... N7: =IF($A7="","",[1]!thsiFinD("ths_adjustment_nv_fund",N$3,$A7))
A8: 46176 | B8: =IF($A8="","",[1]!thsiFinD("ths_adjustment_nv_fund",B$3,$A8)) | C8: =IF($A8="","",[1]!thsiFinD("ths_adjustment_nv_fund",C$3,$A8)) | D8: =IF($A8="","",[1]!thsiFinD("ths_adjustment_nv_fund",D$3,$A8)) | E8: =IF($A8="","",[1]!thsiFinD("ths_adjustment_nv_fund",E$3,$A8)) | F8: =IF($A8="","",[1]!thsiFinD("ths_adjustment_nv_fund",F$3,$A8)) | G8: =IF($A8="","",[1]!thsiFinD("ths_adjustment_nv_fund",G$3,$A8)) | H8: =IF($A8="","",[1]!thsiFinD("ths_adjustment_nv_fund",H$3,$A8)) | I8: =IF($A8="","",[1]!thsiFinD("ths_adjustment_nv_fund",I$3,$A8)) | ... N8: =IF($A8="","",[1]!thsiFinD("ths_adjustment_nv_fund",N$3,$A8))
A9: 46177 | B9: =IF($A9="","",[1]!thsiFinD("ths_adjustment_nv_fund",B$3,$A9)) | C9: =IF($A9="","",[1]!thsiFinD("ths_adjustment_nv_fund",C$3,$A9)) | D9: =IF($A9="","",[1]!thsiFinD("ths_adjustment_nv_fund",D$3,$A9)) | E9: =IF($A9="","",[1]!thsiFinD("ths_adjustment_nv_fund",E$3,$A9)) | F9: =IF($A9="","",[1]!thsiFinD("ths_adjustment_nv_fund",F$3,$A9)) | G9: =IF($A9="","",[1]!thsiFinD("ths_adjustment_nv_fund",G$3,$A9)) | H9: =IF($A9="","",[1]!thsiFinD("ths_adjustment_nv_fund",H$3,$A9)) | I9: =IF($A9="","",[1]!thsiFinD("ths_adjustment_nv_fund",I$3,$A9)) | ... N9: =IF($A9="","",[1]!thsiFinD("ths_adjustment_nv_fund",N$3,$A9))
A10: 46178 | B10: =IF($A10="","",[1]!thsiFinD("ths_adjustment_nv_fund",B$3,$A10)) | C10: =IF($A10="","",[1]!thsiFinD("ths_adjustment_nv_fund",C$3,$A10)) | D10: =IF($A10="","",[1]!thsiFinD("ths_adjustment_nv_fund",D$3,$A10)) | E10: =IF($A10="","",[1]!thsiFinD("ths_adjustment_nv_fund",E$3,$A10)) | F10: =IF($A10="","",[1]!thsiFinD("ths_adjustment_nv_fund",F$3,$A10)) | G10: =IF($A10="","",[1]!thsiFinD("ths_adjustment_nv_fund",G$3,$A10)) | H10: =IF($A10="","",[1]!thsiFinD("ths_adjustment_nv_fund",H$3,$A10)) | I10: =IF($A10="","",[1]!thsiFinD("ths_adjustment_nv_fund",I$3,$A10)) | ... N10: =IF($A10="","",[1]!thsiFinD("ths_adjustment_nv_fund",N$3,$A10))
A11: 46181 | B11: =IF($A11="","",[1]!thsiFinD("ths_adjustment_nv_fund",B$3,$A11)) | C11: =IF($A11="","",[1]!thsiFinD("ths_adjustment_nv_fund",C$3,$A11)) | D11: =IF($A11="","",[1]!thsiFinD("ths_adjustment_nv_fund",D$3,$A11)) | E11: =IF($A11="","",[1]!thsiFinD("ths_adjustment_nv_fund",E$3,$A11)) | F11: =IF($A11="","",[1]!thsiFinD("ths_adjustment_nv_fund",F$3,$A11)) | G11: =IF($A11="","",[1]!thsiFinD("ths_adjustment_nv_fund",G$3,$A11)) | H11: =IF($A11="","",[1]!thsiFinD("ths_adjustment_nv_fund",H$3,$A11)) | I11: =IF($A11="","",[1]!thsiFinD("ths_adjustment_nv_fund",I$3,$A11)) | ... N11: =IF($A11="","",[1]!thsiFinD("ths_adjustment_nv_fund",N$3,$A11))
A12: 46182 | B12: =IF($A12="","",[1]!thsiFinD("ths_adjustment_nv_fund",B$3,$A12)) | C12: =IF($A12="","",[1]!thsiFinD("ths_adjustment_nv_fund",C$3,$A12)) | D12: =IF($A12="","",[1]!thsiFinD("ths_adjustment_nv_fund",D$3,$A12)) | E12: =IF($A12="","",[1]!thsiFinD("ths_adjustment_nv_fund",E$3,$A12)) | F12: =IF($A12="","",[1]!thsiFinD("ths_adjustment_nv_fund",F$3,$A12)) | G12: =IF($A12="","",[1]!thsiFinD("ths_adjustment_nv_fund",G$3,$A12)) | H12: =IF($A12="","",[1]!thsiFinD("ths_adjustment_nv_fund",H$3,$A12)) | I12: =IF($A12="","",[1]!thsiFinD("ths_adjustment_nv_fund",I$3,$A12)) | ... N12: =IF($A12="","",[1]!thsiFinD("ths_adjustment_nv_fund",N$3,$A12))
A13: 46183 | B13: =IF($A13="","",[1]!thsiFinD("ths_adjustment_nv_fund",B$3,$A13)) | C13: =IF($A13="","",[1]!thsiFinD("ths_adjustment_nv_fund",C$3,$A13)) | D13: =IF($A13="","",[1]!thsiFinD("ths_adjustment_nv_fund",D$3,$A13)) | E13: =IF($A13="","",[1]!thsiFinD("ths_adjustment_nv_fund",E$3,$A13)) | F13: =IF($A13="","",[1]!thsiFinD("ths_adjustment_nv_fund",F$3,$A13)) | G13: =IF($A13="","",[1]!thsiFinD("ths_adjustment_nv_fund",G$3,$A13)) | H13: =IF($A13="","",[1]!thsiFinD("ths_adjustment_nv_fund",H$3,$A13)) | I13: =IF($A13="","",[1]!thsiFinD("ths_adjustment_nv_fund",I$3,$A13)) | ... N13: =IF($A13="","",[1]!thsiFinD("ths_adjustment_nv_fund",N$3,$A13))
A14: 46184 | B14: =IF($A14="","",[1]!thsiFinD("ths_adjustment_nv_fund",B$3,$A14)) | C14: =IF($A14="","",[1]!thsiFinD("ths_adjustment_nv_fund",C$3,$A14)) | D14: =IF($A14="","",[1]!thsiFinD("ths_adjustment_nv_fund",D$3,$A14)) | E14: =IF($A14="","",[1]!thsiFinD("ths_adjustment_nv_fund",E$3,$A14)) | F14: =IF($A14="","",[1]!thsiFinD("ths_adjustment_nv_fund",F$3,$A14)) | G14: =IF($A14="","",[1]!thsiFinD("ths_adjustment_nv_fund",G$3,$A14)) | H14: =IF($A14="","",[1]!thsiFinD("ths_adjustment_nv_fund",H$3,$A14)) | I14: =IF($A14="","",[1]!thsiFinD("ths_adjustment_nv_fund",I$3,$A14)) | ... N14: =IF($A14="","",[1]!thsiFinD("ths_adjustment_nv_fund",N$3,$A14))
A15: 46185 | B15: =IF($A15="","",[1]!thsiFinD("ths_adjustment_nv_fund",B$3,$A15)) | C15: =IF($A15="","",[1]!thsiFinD("ths_adjustment_nv_fund",C$3,$A15)) | D15: =IF($A15="","",[1]!thsiFinD("ths_adjustment_nv_fund",D$3,$A15)) | E15: =IF($A15="","",[1]!thsiFinD("ths_adjustment_nv_fund",E$3,$A15)) | F15: =IF($A15="","",[1]!thsiFinD("ths_adjustment_nv_fund",F$3,$A15)) | G15: =IF($A15="","",[1]!thsiFinD("ths_adjustment_nv_fund",G$3,$A15)) | H15: =IF($A15="","",[1]!thsiFinD("ths_adjustment_nv_fund",H$3,$A15)) | I15: =IF($A15="","",[1]!thsiFinD("ths_adjustment_nv_fund",I$3,$A15)) | ... N15: =IF($A15="","",[1]!thsiFinD("ths_adjustment_nv_fund",N$3,$A15))
A16: 46188 | B16: =IF($A16="","",[1]!thsiFinD("ths_adjustment_nv_fund",B$3,$A16)) | C16: =IF($A16="","",[1]!thsiFinD("ths_adjustment_nv_fund",C$3,$A16)) | D16: =IF($A16="","",[1]!thsiFinD("ths_adjustment_nv_fund",D$3,$A16)) | E16: =IF($A16="","",[1]!thsiFinD("ths_adjustment_nv_fund",E$3,$A16)) | F16: =IF($A16="","",[1]!thsiFinD("ths_adjustment_nv_fund",F$3,$A16)) | G16: =IF($A16="","",[1]!thsiFinD("ths_adjustment_nv_fund",G$3,$A16)) | H16: =IF($A16="","",[1]!thsiFinD("ths_adjustment_nv_fund",H$3,$A16)) | I16: =IF($A16="","",[1]!thsiFinD("ths_adjustment_nv_fund",I$3,$A16)) | ... N16: =IF($A16="","",[1]!thsiFinD("ths_adjustment_nv_fund",N$3,$A16))
... A29: 46206 | B29: =IF($A29="","",[1]!thsiFinD("ths_adjustment_nv_fund",B$3,$A29)) | C29: =IF($A29="","",[1]!thsiFinD("ths_adjustment_nv_fund",C$3,$A29)) | D29: =IF($A29="","",[1]!thsiFinD("ths_adjustment_nv_fund",D$3,$A29)) | E29: =IF($A29="","",[1]!thsiFinD("ths_adjustment_nv_fund",E$3,$A29)) | F29: =IF($A29="","",[1]!thsiFinD("ths_adjustment_nv_fund",F$3,$A29)) | G29: =IF($A29="","",[1]!thsiFinD("ths_adjustment_nv_fund",G$3,$A29)) | H29: =IF($A29="","",[1]!thsiFinD("ths_adjustment_nv_fund",H$3,$A29)) | I29: =IF($A29="","",[1]!thsiFinD("ths_adjustment_nv_fund",I$3,$A29)) | ... N29: =IF($A29="","",[1]!thsiFinD("ths_adjustment_nv_fund",N$3,$A29))
B30: =IF($A30="","",[1]!thsiFinD("ths_adjustment_nv_fund",B$3,$A30)) | C30: =IF($A30="","",[1]!thsiFinD("ths_adjustment_nv_fund",C$3,$A30)) | D30: =IF($A30="","",[1]!thsiFinD("ths_adjustment_nv_fund",D$3,$A30)) | E30: =IF($A30="","",[1]!thsiFinD("ths_adjustment_nv_fund",E$3,$A30)) | F30: =IF($A30="","",[1]!thsiFinD("ths_adjustment_nv_fund",F$3,$A30)) | G30: =IF($A30="","",[1]!thsiFinD("ths_adjustment_nv_fund",G$3,$A30)) | H30: =IF($A30="","",[1]!thsiFinD("ths_adjustment_nv_fund",H$3,$A30)) | I30: =IF($A30="","",[1]!thsiFinD("ths_adjustment_nv_fund",I$3,$A30)) | ... N30: =IF($A30="","",[1]!thsiFinD("ths_adjustment_nv_fund",N$3,$A30))
B31: =IF($A31="","",[1]!thsiFinD("ths_adjustment_nv_fund",B$3,$A31)) | C31: =IF($A31="","",[1]!thsiFinD("ths_adjustment_nv_fund",C$3,$A31)) | D31: =IF($A31="","",[1]!thsiFinD("ths_adjustment_nv_fund",D$3,$A31)) | E31: =IF($A31="","",[1]!thsiFinD("ths_adjustment_nv_fund",E$3,$A31)) | F31: =IF($A31="","",[1]!thsiFinD("ths_adjustment_nv_fund",F$3,$A31)) | G31: =IF($A31="","",[1]!thsiFinD("ths_adjustment_nv_fund",G$3,$A31)) | H31: =IF($A31="","",[1]!thsiFinD("ths_adjustment_nv_fund",H$3,$A31)) | I31: =IF($A31="","",[1]!thsiFinD("ths_adjustment_nv_fund",I$3,$A31)) | ... N31: =IF($A31="","",[1]!thsiFinD("ths_adjustment_nv_fund",N$3,$A31))
B32: =IF($A32="","",[1]!thsiFinD("ths_adjustment_nv_fund",B$3,$A32)) | C32: =IF($A32="","",[1]!thsiFinD("ths_adjustment_nv_fund",C$3,$A32)) | D32: =IF($A32="","",[1]!thsiFinD("ths_adjustment_nv_fund",D$3,$A32)) | E32: =IF($A32="","",[1]!thsiFinD("ths_adjustment_nv_fund",E$3,$A32)) | F32: =IF($A32="","",[1]!thsiFinD("ths_adjustment_nv_fund",F$3,$A32)) | G32: =IF($A32="","",[1]!thsiFinD("ths_adjustment_nv_fund",G$3,$A32)) | H32: =IF($A32="","",[1]!thsiFinD("ths_adjustment_nv_fund",H$3,$A32)) | I32: =IF($A32="","",[1]!thsiFinD("ths_adjustment_nv_fund",I$3,$A32)) | ... N32: =IF($A32="","",[1]!thsiFinD("ths_adjustment_nv_fund",N$3,$A32))
B33: =IF($A33="","",[1]!thsiFinD("ths_adjustment_nv_fund",B$3,$A33)) | C33: =IF($A33="","",[1]!thsiFinD("ths_adjustment_nv_fund",C$3,$A33)) | D33: =IF($A33="","",[1]!thsiFinD("ths_adjustment_nv_fund",D$3,$A33)) | E33: =IF($A33="","",[1]!thsiFinD("ths_adjustment_nv_fund",E$3,$A33)) | F33: =IF($A33="","",[1]!thsiFinD("ths_adjustment_nv_fund",F$3,$A33)) | G33: =IF($A33="","",[1]!thsiFinD("ths_adjustment_nv_fund",G$3,$A33)) | H33: =IF($A33="","",[1]!thsiFinD("ths_adjustment_nv_fund",H$3,$A33)) | I33: =IF($A33="","",[1]!thsiFinD("ths_adjustment_nv_fund",I$3,$A33)) | ... N33: =IF($A33="","",[1]!thsiFinD("ths_adjustment_nv_fund",N$3,$A33))
B34: =IF($A34="","",[1]!thsiFinD("ths_adjustment_nv_fund",B$3,$A34)) | C34: =IF($A34="","",[1]!thsiFinD("ths_adjustment_nv_fund",C$3,$A34)) | D34: =IF($A34="","",[1]!thsiFinD("ths_adjustment_nv_fund",D$3,$A34)) | E34: =IF($A34="","",[1]!thsiFinD("ths_adjustment_nv_fund",E$3,$A34)) | F34: =IF($A34="","",[1]!thsiFinD("ths_adjustment_nv_fund",F$3,$A34)) | G34: =IF($A34="","",[1]!thsiFinD("ths_adjustment_nv_fund",G$3,$A34)) | H34: =IF($A34="","",[1]!thsiFinD("ths_adjustment_nv_fund",H$3,$A34)) | I34: =IF($A34="","",[1]!thsiFinD("ths_adjustment_nv_fund",I$3,$A34)) | ... N34: =IF($A34="","",[1]!thsiFinD("ths_adjustment_nv_fund",N$3,$A34))
B35: =IF($A35="","",[1]!thsiFinD("ths_adjustment_nv_fund",B$3,$A35)) | C35: =IF($A35="","",[1]!thsiFinD("ths_adjustment_nv_fund",C$3,$A35)) | D35: =IF($A35="","",[1]!thsiFinD("ths_adjustment_nv_fund",D$3,$A35)) | E35: =IF($A35="","",[1]!thsiFinD("ths_adjustment_nv_fund",E$3,$A35)) | F35: =IF($A35="","",[1]!thsiFinD("ths_adjustment_nv_fund",F$3,$A35)) | G35: =IF($A35="","",[1]!thsiFinD("ths_adjustment_nv_fund",G$3,$A35)) | H35: =IF($A35="","",[1]!thsiFinD("ths_adjustment_nv_fund",H$3,$A35)) | I35: =IF($A35="","",[1]!thsiFinD("ths_adjustment_nv_fund",I$3,$A35)) | ... N35: =IF($A35="","",[1]!thsiFinD("ths_adjustment_nv_fund",N$3,$A35))
B36: =IF($A36="","",[1]!thsiFinD("ths_adjustment_nv_fund",B$3,$A36)) | C36: =IF($A36="","",[1]!thsiFinD("ths_adjustment_nv_fund",C$3,$A36)) | D36: =IF($A36="","",[1]!thsiFinD("ths_adjustment_nv_fund",D$3,$A36)) | E36: =IF($A36="","",[1]!thsiFinD("ths_adjustment_nv_fund",E$3,$A36)) | F36: =IF($A36="","",[1]!thsiFinD("ths_adjustment_nv_fund",F$3,$A36)) | G36: =IF($A36="","",[1]!thsiFinD("ths_adjustment_nv_fund",G$3,$A36)) | H36: =IF($A36="","",[1]!thsiFinD("ths_adjustment_nv_fund",H$3,$A36)) | I36: =IF($A36="","",[1]!thsiFinD("ths_adjustment_nv_fund",I$3,$A36)) | ... N36: =IF($A36="","",[1]!thsiFinD("ths_adjustment_nv_fund",N$3,$A36))
B37: =IF($A37="","",[1]!thsiFinD("ths_adjustment_nv_fund",B$3,$A37)) | C37: =IF($A37="","",[1]!thsiFinD("ths_adjustment_nv_fund",C$3,$A37)) | D37: =IF($A37="","",[1]!thsiFinD("ths_adjustment_nv_fund",D$3,$A37)) | E37: =IF($A37="","",[1]!thsiFinD("ths_adjustment_nv_fund",E$3,$A37)) | F37: =IF($A37="","",[1]!thsiFinD("ths_adjustment_nv_fund",F$3,$A37)) | G37: =IF($A37="","",[1]!thsiFinD("ths_adjustment_nv_fund",G$3,$A37)) | H37: =IF($A37="","",[1]!thsiFinD("ths_adjustment_nv_fund",H$3,$A37)) | I37: =IF($A37="","",[1]!thsiFinD("ths_adjustment_nv_fund",I$3,$A37)) | ... N37: =IF($A37="","",[1]!thsiFinD("ths_adjustment_nv_fund",N$3,$A37))
B38: =IF($A38="","",[1]!thsiFinD("ths_adjustment_nv_fund",B$3,$A38)) | C38: =IF($A38="","",[1]!thsiFinD("ths_adjustment_nv_fund",C$3,$A38)) | D38: =IF($A38="","",[1]!thsiFinD("ths_adjustment_nv_fund",D$3,$A38)) | E38: =IF($A38="","",[1]!thsiFinD("ths_adjustment_nv_fund",E$3,$A38)) | F38: =IF($A38="","",[1]!thsiFinD("ths_adjustment_nv_fund",F$3,$A38)) | G38: =IF($A38="","",[1]!thsiFinD("ths_adjustment_nv_fund",G$3,$A38)) | H38: =IF($A38="","",[1]!thsiFinD("ths_adjustment_nv_fund",H$3,$A38)) | I38: =IF($A38="","",[1]!thsiFinD("ths_adjustment_nv_fund",I$3,$A38)) | ... N38: =IF($A38="","",[1]!thsiFinD("ths_adjustment_nv_fund",N$3,$A38))
B39: =IF($A39="","",[1]!thsiFinD("ths_adjustment_nv_fund",B$3,$A39)) | C39: =IF($A39="","",[1]!thsiFinD("ths_adjustment_nv_fund",C$3,$A39)) | D39: =IF($A39="","",[1]!thsiFinD("ths_adjustment_nv_fund",D$3,$A39)) | E39: =IF($A39="","",[1]!thsiFinD("ths_adjustment_nv_fund",E$3,$A39)) | F39: =IF($A39="","",[1]!thsiFinD("ths_adjustment_nv_fund",F$3,$A39)) | G39: =IF($A39="","",[1]!thsiFinD("ths_adjustment_nv_fund",G$3,$A39)) | H39: =IF($A39="","",[1]!thsiFinD("ths_adjustment_nv_fund",H$3,$A39)) | I39: =IF($A39="","",[1]!thsiFinD("ths_adjustment_nv_fund",I$3,$A39)) | ... N39: =IF($A39="","",[1]!thsiFinD("ths_adjustment_nv_fund",N$3,$A39))
B40: =IF($A40="","",[1]!thsiFinD("ths_adjustment_nv_fund",B$3,$A40)) | C40: =IF($A40="","",[1]!thsiFinD("ths_adjustment_nv_fund",C$3,$A40)) | D40: =IF($A40="","",[1]!thsiFinD("ths_adjustment_nv_fund",D$3,$A40)) | E40: =IF($A40="","",[1]!thsiFinD("ths_adjustment_nv_fund",E$3,$A40)) | F40: =IF($A40="","",[1]!thsiFinD("ths_adjustment_nv_fund",F$3,$A40)) | G40: =IF($A40="","",[1]!thsiFinD("ths_adjustment_nv_fund",G$3,$A40)) | H40: =IF($A40="","",[1]!thsiFinD("ths_adjustment_nv_fund",H$3,$A40)) | I40: =IF($A40="","",[1]!thsiFinD("ths_adjustment_nv_fund",I$3,$A40)) | ... N40: =IF($A40="","",[1]!thsiFinD("ths_adjustment_nv_fund",N$3,$A40))
B41: =IF($A41="","",[1]!thsiFinD("ths_adjustment_nv_fund",B$3,$A41)) | C41: =IF($A41="","",[1]!thsiFinD("ths_adjustment_nv_fund",C$3,$A41)) | D41: =IF($A41="","",[1]!thsiFinD("ths_adjustment_nv_fund",D$3,$A41)) | E41: =IF($A41="","",[1]!thsiFinD("ths_adjustment_nv_fund",E$3,$A41)) | F41: =IF($A41="","",[1]!thsiFinD("ths_adjustment_nv_fund",F$3,$A41)) | G41: =IF($A41="","",[1]!thsiFinD("ths_adjustment_nv_fund",G$3,$A41)) | H41: =IF($A41="","",[1]!thsiFinD("ths_adjustment_nv_fund",H$3,$A41)) | I41: =IF($A41="","",[1]!thsiFinD("ths_adjustment_nv_fund",I$3,$A41)) | ... N41: =IF($A41="","",[1]!thsiFinD("ths_adjustment_nv_fund",N$3,$A41))
... B59: =IF($A59="","",[1]!thsiFinD("ths_adjustment_nv_fund",B$3,$A59)) | C59: =IF($A59="","",[1]!thsiFinD("ths_adjustment_nv_fund",C$3,$A59)) | D59: =IF($A59="","",[1]!thsiFinD("ths_adjustment_nv_fund",D$3,$A59)) | E59: =IF($A59="","",[1]!thsiFinD("ths_adjustment_nv_fund",E$3,$A59)) | F59: =IF($A59="","",[1]!thsiFinD("ths_adjustment_nv_fund",F$3,$A59)) | G59: =IF($A59="","",[1]!thsiFinD("ths_adjustment_nv_fund",G$3,$A59)) | H59: =IF($A59="","",[1]!thsiFinD("ths_adjustment_nv_fund",H$3,$A59)) | I59: =IF($A59="","",[1]!thsiFinD("ths_adjustment_nv_fund",I$3,$A59)) | ... N59: =IF($A59="","",[1]!thsiFinD("ths_adjustment_nv_fund",N$3,$A59))

Sheet 组合净值
A1: 组合净值 · 买入持有逐日计算
B4: 组合 10-90 | E4: 组合 20-80 | H4: 组合 30-70 | K4: 组合 增值
A5: 日期 | B5: 净值 | C5: 日收益 | D5: 回撤 | E5: 净值 | F5: 日收益 | G5: 回撤 | H5: 净值 | I5: 日收益 | J5: 回撤 | K5: 净值 | L5: 日收益 | M5: 回撤
A6: =IF('净值数据(iFinD公式)'!A5="","",'净值数据(iFinD公式)'!A5) | B6: =IF(OR('净值数据(iFinD公式)'!$A5="",'净值数据(iFinD公式)'!$B5=""),"",SUMPRODUCT(持仓配置!$B$4:$N$4,'净值数据(iFinD公式)'!$B5:$N5/'净值数据(iFinD公式)'!$B$5:$N$5)*(1-持仓配置!$P$4)^((ROW()-6)/说明!$C$17)) | D6: =IF(B6="","",B6/MAX(B$6:B6)-1) | E6: =IF(OR('净值数据(iFinD公式)'!$A5="",'净值数据(iFinD公式)'!$B5=""),"",SUMPRODUCT(持仓配置!$B$5:$N$5,'净值数据(iFinD公式)'!$B5:$N5/'净值数据(iFinD公式)'!$B$5:$N$5)*(1-持仓配置!$P$5)^((ROW()-6)/说明!$C$17)) | G6: =IF(E6="","",E6/MAX(E$6:E6)-1) | H6: =IF(OR('净值数据(iFinD公式)'!$A5="",'净值数据(iFinD公式)'!$B5=""),"",SUMPRODUCT(持仓配置!$B$6:$N$6,'净值数据(iFinD公式)'!$B5:$N5/'净值数据(iFinD公式)'!$B$5:$N$5)*(1-持仓配置!$P$6)^((ROW()-6)/说明!$C$17)) | J6: =IF(H6="","",H6/MAX(H$6:H6)-1) | K6: =IF(OR('净值数据(iFinD公式)'!$A5="",'净值数据(iFinD公式)'!$B5=""),"",SUMPRODUCT(持仓配置!$B$7:$N$7,'净值数据(iFinD公式)'!$B5:$N5/'净值数据(iFinD公式)'!$B$5:$N$5)*(1-持仓配置!$P$7)^((ROW()-6)/说明!$C$17)) | M6: =IF(K6="","",K6/MAX(K$6:K6)-1)
A7: =IF('净值数据(iFinD公式)'!A6="","",'净值数据(iFinD公式)'!A6) | B7: =IF(OR('净值数据(iFinD公式)'!$A6="",'净值数据(iFinD公式)'!$B6=""),"",SUMPRODUCT(持仓配置!$B$4:$N$4,'净值数据(iFinD公式)'!$B6:$N6/'净值数据(iFinD公式)'!$B$5:$N$5)*(1-持仓配置!$P$4)^((ROW()-6)/说明!$C$17)) | C7: =IF(OR(B7="",B6=""),"",B7/B6-1) | D7: =IF(B7="","",B7/MAX(B$6:B7)-1) | E7: =IF(OR('净值数据(iFinD公式)'!$A6="",'净值数据(iFinD公式)'!$B6=""),"",SUMPRODUCT(持仓配置!$B$5:$N$5,'净值数据(iFinD公式)'!$B6:$N6/'净值数据(iFinD公式)'!$B$5:$N$5)*(1-持仓配置!$P$5)^((ROW()-6)/说明!$C$17)) | F7: =IF(OR(E7="",E6=""),"",E7/E6-1) | G7: =IF(E7="","",E7/MAX(E$6:E7)-1) | H7: =IF(OR('净值数据(iFinD公式)'!$A6="",'净值数据(iFinD公式)'!$B6=""),"",SUMPRODUCT(持仓配置!$B$6:$N$6,'净值数据(iFinD公式)'!$B6:$N6/'净值数据(iFinD公式)'!$B$5:$N$5)*(1-持仓配置!$P$6)^((ROW()-6)/说明!$C$17)) | I7: =IF(OR(H7="",H6=""),"",H7/H6-1) | J7: =IF(H7="","",H7/MAX(H$6:H7)-1) | K7: =IF(OR('净值数据(iFinD公式)'!$A6="",'净值数据(iFinD公式)'!$B6=""),"",SUMPRODUCT(持仓配置!$B$7:$N$7,'净值数据(iFinD公式)'!$B6:$N6/'净值数据(iFinD公式)'!$B$5:$N$5)*(1-持仓配置!$P$7)^((ROW()-6)/说明!$C$17)) | L7: =IF(OR(K7="",K6=""),"",K7/K6-1) | M7: =IF(K7="","",K7/MAX(K$6:K7)-1)
A8: =IF('净值数据(iFinD公式)'!A7="","",'净值数据(iFinD公式)'!A7) | B8: =IF(OR('净值数据(iFinD公式)'!$A7="",'净值数据(iFinD公式)'!$B7=""),"",SUMPRODUCT(持仓配置!$B$4:$N$4,'净值数据(iFinD公式)'!$B7:$N7/'净值数据(iFinD公式)'!$B$5:$N$5)*(1-持仓配置!$P$4)^((ROW()-6)/说明!$C$17)) | C8: =IF(OR(B8="",B7=""),"",B8/B7-1) | D8: =IF(B8="","",B8/MAX(B$6:B8)-1) | E8: =IF(OR('净值数据(iFinD公式)'!$A7="",'净值数据(iFinD公式)'!$B7=""),"",SUMPRODUCT(持仓配置!$B$5:$N$5,'净值数据(iFinD公式)'!$B7:$N7/'净值数据(iFinD公式)'!$B$5:$N$5)*(1-持仓配置!$P$5)^((ROW()-6)/说明!$C$17)) | F8: =IF(OR(E8="",E7=""),"",E8/E7-1) | G8: =IF(E8="","",E8/MAX(E$6:E8)-1) | H8: =IF(OR('净值数据(iFinD公式)'!$A7="",'净值数据(iFinD公式)'!$B7=""),"",SUMPRODUCT(持仓配置!$B$6:$N$6,'净值数据(iFinD公式)'!$B7:$N7/'净值数据(iFinD公式)'!$B$5:$N$5)*(1-持仓配置!$P$6)^((ROW()-6)/说明!$C$17)) | I8: =IF(OR(H8="",H7=""),"",H8/H7-1) | J8: =IF(H8="","",H8/MAX(H$6:H8)-1) | K8: =IF(OR('净值数据(iFinD公式)'!$A7="",'净值数据(iFinD公式)'!$B7=""),"",SUMPRODUCT(持仓配置!$B$7:$N$7,'净值数据(iFinD公式)'!$B7:$N7/'净值数据(iFinD公式)'!$B$5:$N$5)*(1-持仓配置!$P$7)^((ROW()-6)/说明!$C$17)) | L8: =IF(OR(K8="",K7=""),"",K8/K7-1) | M8: =IF(K8="","",K8/MAX(K$6:K8)-1)
A9: =IF('净值数据(iFinD公式)'!A8="","",'净值数据(iFinD公式)'!A8) | B9: =IF(OR('净值数据(iFinD公式)'!$A8="",'净值数据(iFinD公式)'!$B8=""),"",SUMPRODUCT(持仓配置!$B$4:$N$4,'净值数据(iFinD公式)'!$B8:$N8/'净值数据(iFinD公式)'!$B$5:$N$5)*(1-持仓配置!$P$4)^((ROW()-6)/说明!$C$17)) | C9: =IF(OR(B9="",B8=""),"",B9/B8-1) | D9: =IF(B9="","",B9/MAX(B$6:B9)-1) | E9: =IF(OR('净值数据(iFinD公式)'!$A8="",'净值数据(iFinD公式)'!$B8=""),"",SUMPRODUCT(持仓配置!$B$5:$N$5,'净值数据(iFinD公式)'!$B8:$N8/'净值数据(iFinD公式)'!$B$5:$N$5)*(1-持仓配置!$P$5)^((ROW()-6)/说明!$C$17)) | F9: =IF(OR(E9="",E8=""),"",E9/E8-1) | G9: =IF(E9="","",E9/MAX(E$6:E9)-1) | H9: =IF(OR('净值数据(iFinD公式)'!$A8="",'净值数据(iFinD公式)'!$B8=""),"",SUMPRODUCT(持仓配置!$B$6:$N$6,'净值数据(iFinD公式)'!$B8:$N8/'净值数据(iFinD公式)'!$B$5:$N$5)*(1-持仓配置!$P$6)^((ROW()-6)/说明!$C$17)) | I9: =IF(OR(H9="",H8=""),"",H9/H8-1) | J9: =IF(H9="","",H9/MAX(H$6:H9)-1) | K9: =IF(OR('净值数据(iFinD公式)'!$A8="",'净值数据(iFinD公式)'!$B8=""),"",SUMPRODUCT(持仓配置!$B$7:$N$7,'净值数据(iFinD公式)'!$B8:$N8/'净值数据(iFinD公式)'!$B$5:$N$5)*(1-持仓配置!$P$7)^((ROW()-6)/说明!$C$17)) | L9: =IF(OR(K9="",K8=""),"",K9/K8-1) | M9: =IF(K9="","",K9/MAX(K$6:K9)-1)
A10: =IF('净值数据(iFinD公式)'!A9="","",'净值数据(iFinD公式)'!A9) | B10: =IF(OR('净值数据(iFinD公式)'!$A9="",'净值数据(iFinD公式)'!$B9=""),"",SUMPRODUCT(持仓配置!$B$4:$N$4,'净值数据(iFinD公式)'!$B9:$N9/'净值数据(iFinD公式)'!$B$5:$N$5)*(1-持仓配置!$P$4)^((ROW()-6)/说明!$C$17)) | C10: =IF(OR(B10="",B9=""),"",B10/B9-1) | D10: =IF(B10="","",B10/MAX(B$6:B10)-1) | E10: =IF(OR('净值数据(iFinD公式)'!$A9="",'净值数据(iFinD公式)'!$B9=""),"",SUMPRODUCT(持仓配置!$B$5:$N$5,'净值数据(iFinD公式)'!$B9:$N9/'净值数据(iFinD公式)'!$B$5:$N$5)*(1-持仓配置!$P$5)^((ROW()-6)/说明!$C$17)) | F10: =IF(OR(E10="",E9=""),"",E10/E9-1) | G10: =IF(E10="","",E10/MAX(E$6:E10)-1) | H10: =IF(OR('净值数据(iFinD公式)'!$A9="",'净值数据(iFinD公式)'!$B9=""),"",SUMPRODUCT(持仓配置!$B$6:$N$6,'净值数据(iFinD公式)'!$B9:$N9/'净值数据(iFinD公式)'!$B$5:$N$5)*(1-持仓配置!$P$6)^((ROW()-6)/说明!$C$17)) | I10: =IF(OR(H10="",H9=""),"",H10/H9-1) | J10: =IF(H10="","",H10/MAX(H$6:H10)-1) | K10: =IF(OR('净值数据(iFinD公式)'!$A9="",'净值数据(iFinD公式)'!$B9=""),"",SUMPRODUCT(持仓配置!$B$7:$N$7,'净值数据(iFinD公式)'!$B9:$N9/'净值数据(iFinD公式)'!$B$5:$N$5)*(1-持仓配置!$P$7)^((ROW()-6)/说明!$C$17)) | L10: =IF(OR(K10="",K9=""),"",K10/K9-1) | M10: =IF(K10="","",K10/MAX(K$6:K10)-1)
A11: =IF('净值数据(iFinD公式)'!A10="","",'净值数据(iFinD公式)'!A10) | B11: =IF(OR('净值数据(iFinD公式)'!$A10="",'净值数据(iFinD公式)'!$B10=""),"",SUMPRODUCT(持仓配置!$B$4:$N$4,'净值数据(iFinD公式)'!$B10:$N10/'净值数据(iFinD公式)'!$B$5:$N$5)*(1-持仓配置!$P$4)^((ROW()-6)/说明!$C$17)) | C11: =IF(OR(B11="",B10=""),"",B11/B10-1) | D11: =IF(B11="","",B11/MAX(B$6:B11)-1) | E11: =IF(OR('净值数据(iFinD公式)'!$A10="",'净值数据(iFinD公式)'!$B10=""),"",SUMPRODUCT(持仓配置!$B$5:$N$5,'净值数据(iFinD公式)'!$B10:$N10/'净值数据(iFinD公式)'!$B$5:$N$5)*(1-持仓配置!$P$5)^((ROW()-6)/说明!$C$17)) | F11: =IF(OR(E11="",E10=""),"",E11/E10-1) | G11: =IF(E11="","",E11/MAX(E$6:E11)-1) | H11: =IF(OR('净值数据(iFinD公式)'!$A10="",'净值数据(iFinD公式)'!$B10=""),"",SUMPRODUCT(持仓配置!$B$6:$N$6,'净值数据(iFinD公式)'!$B10:$N10/'净值数据(iFinD公式)'!$B$5:$N$5)*(1-持仓配置!$P$6)^((ROW()-6)/说明!$C$17)) | I11: =IF(OR(H11="",H10=""),"",H11/H10-1) | J11: =IF(H11="","",H11/MAX(H$6:H11)-1) | K11: =IF(OR('净值数据(iFinD公式)'!$A10="",'净值数据(iFinD公式)'!$B10=""),"",SUMPRODUCT(持仓配置!$B$7:$N$7,'净值数据(iFinD公式)'!$B10:$N10/'净值数据(iFinD公式)'!$B$5:$N$5)*(1-持仓配置!$P$7)^((ROW()-6)/说明!$C$17)) | L11: =IF(OR(K11="",K10=""),"",K11/K10-1) | M11: =IF(K11="","",K11/MAX(K$6:K11)-1)
A12: =IF('净值数据(iFinD公式)'!A11="","",'净值数据(iFinD公式)'!A11) | B12: =IF(OR('净值数据(iFinD公式)'!$A11="",'净值数据(iFinD公式)'!$B11=""),"",SUMPRODUCT(持仓配置!$B$4:$N$4,'净值数据(iFinD公式)'!$B11:$N11/'净值数据(iFinD公式)'!$B$5:$N$5)*(1-持仓配置!$P$4)^((ROW()-6)/说明!$C$17)) | C12: =IF(OR(B12="",B11=""),"",B12/B11-1) | D12: =IF(B12="","",B12/MAX(B$6:B12)-1) | E12: =IF(OR('净值数据(iFinD公式)'!$A11="",'净值数据(iFinD公式)'!$B11=""),"",SUMPRODUCT(持仓配置!$B$5:$N$5,'净值数据(iFinD公式)'!$B11:$N11/'净值数据(iFinD公式)'!$B$5:$N$5)*(1-持仓配置!$P$5)^((ROW()-6)/说明!$C$17)) | F12: =IF(OR(E12="",E11=""),"",E12/E11-1) | G12: =IF(E12="","",E12/MAX(E$6:E12)-1) | H12: =IF(OR('净值数据(iFinD公式)'!$A11="",'净值数据(iFinD公式)'!$B11=""),"",SUMPRODUCT(持仓配置!$B$6:$N$6,'净值数据(iFinD公式)'!$B11:$N11/'净值数据(iFinD公式)'!$B$5:$N$5)*(1-持仓配置!$P$6)^((ROW()-6)/说明!$C$17)) | I12: =IF(OR(H12="",H11=""),"",H12/H11-1) | J12: =IF(H12="","",H12/MAX(H$6:H12)-1) | K12: =IF(OR('净值数据(iFinD公式)'!$A11="",'净值数据(iFinD公式)'!$B11=""),"",SUMPRODUCT(持仓配置!$B$7:$N$7,'净值数据(iFinD公式)'!$B11:$N11/'净值数据(iFinD公式)'!$B$5:$N$5)*(1-持仓配置!$P$7)^((ROW()-6)/说明!$C$17)) | L12: =IF(OR(K12="",K11=""),"",K12/K11-1) | M12: =IF(K12="","",K12/MAX(K$6:K12)-1)
A13: =IF('净值数据(iFinD公式)'!A12="","",'净值数据(iFinD公式)'!A12) | B13: =IF(OR('净值数据(iFinD公式)'!$A12="",'净值数据(iFinD公式)'!$B12=""),"",SUMPRODUCT(持仓配置!$B$4:$N$4,'净值数据(iFinD公式)'!$B12:$N12/'净值数据(iFinD公式)'!$B$5:$N$5)*(1-持仓配置!$P$4)^((ROW()-6)/说明!$C$17)) | C13: =IF(OR(B13="",B12=""),"",B13/B12-1) | D13: =IF(B13="","",B13/MAX(B$6:B13)-1) | E13: =IF(OR('净值数据(iFinD公式)'!$A12="",'净值数据(iFinD公式)'!$B12=""),"",SUMPRODUCT(持仓配置!$B$5:$N$5,'净值数据(iFinD公式)'!$B12:$N12/'净值数据(iFinD公式)'!$B$5:$N$5)*(1-持仓配置!$P$5)^((ROW()-6)/说明!$C$17)) | F13: =IF(OR(E13="",E12=""),"",E13/E12-1) | G13: =IF(E13="","",E13/MAX(E$6:E13)-1) | H13: =IF(OR('净值数据(iFinD公式)'!$A12="",'净值数据(iFinD公式)'!$B12=""),"",SUMPRODUCT(持仓配置!$B$6:$N$6,'净值数据(iFinD公式)'!$B12:$N12/'净值数据(iFinD公式)'!$B$5:$N$5)*(1-持仓配置!$P$6)^((ROW()-6)/说明!$C$17)) | I13: =IF(OR(H13="",H12=""),"",H13/H12-1) | J13: =IF(H13="","",H13/MAX(H$6:H13)-1) | K13: =IF(OR('净值数据(iFinD公式)'!$A12="",'净值数据(iFinD公式)'!$B12=""),"",SUMPRODUCT(持仓配置!$B$7:$N$7,'净值数据(iFinD公式)'!$B12:$N12/'净值数据(iFinD公式)'!$B$5:$N$5)*(1-持仓配置!$P$7)^((ROW()-6)/说明!$C$17)) | L13: =IF(OR(K13="",K12=""),"",K13/K12-1) | M13: =IF(K13="","",K13/MAX(K$6:K13)-1)
A14: =IF('净值数据(iFinD公式)'!A13="","",'净值数据(iFinD公式)'!A13) | B14: =IF(OR('净值数据(iFinD公式)'!$A13="",'净值数据(iFinD公式)'!$B13=""),"",SUMPRODUCT(持仓配置!$B$4:$N$4,'净值数据(iFinD公式)'!$B13:$N13/'净值数据(iFinD公式)'!$B$5:$N$5)*(1-持仓配置!$P$4)^((ROW()-6)/说明!$C$17)) | C14: =IF(OR(B14="",B13=""),"",B14/B13-1) | D14: =IF(B14="","",B14/MAX(B$6:B14)-1) | E14: =IF(OR('净值数据(iFinD公式)'!$A13="",'净值数据(iFinD公式)'!$B13=""),"",SUMPRODUCT(持仓配置!$B$5:$N$5,'净值数据(iFinD公式)'!$B13:$N13/'净值数据(iFinD公式)'!$B$5:$N$5)*(1-持仓配置!$P$5)^((ROW()-6)/说明!$C$17)) | F14: =IF(OR(E14="",E13=""),"",E14/E13-1) | G14: =IF(E14="","",E14/MAX(E$6:E14)-1) | H14: =IF(OR('净值数据(iFinD公式)'!$A13="",'净值数据(iFinD公式)'!$B13=""),"",SUMPRODUCT(持仓配置!$B$6:$N$6,'净值数据(iFinD公式)'!$B13:$N13/'净值数据(iFinD公式)'!$B$5:$N$5)*(1-持仓配置!$P$6)^((ROW()-6)/说明!$C$17)) | I14: =IF(OR(H14="",H13=""),"",H14/H13-1) | J14: =IF(H14="","",H14/MAX(H$6:H14)-1) | K14: =IF(OR('净值数据(iFinD公式)'!$A13="",'净值数据(iFinD公式)'!$B13=""),"",SUMPRODUCT(持仓配置!$B$7:$N$7,'净值数据(iFinD公式)'!$B13:$N13/'净值数据(iFinD公式)'!$B$5:$N$5)*(1-持仓配置!$P$7)^((ROW()-6)/说明!$C$17)) | L14: =IF(OR(K14="",K13=""),"",K14/K13-1) | M14: =IF(K14="","",K14/MAX(K$6:K14)-1)
A15: =IF('净值数据(iFinD公式)'!A14="","",'净值数据(iFinD公式)'!A14) | B15: =IF(OR('净值数据(iFinD公式)'!$A14="",'净值数据(iFinD公式)'!$B14=""),"",SUMPRODUCT(持仓配置!$B$4:$N$4,'净值数据(iFinD公式)'!$B14:$N14/'净值数据(iFinD公式)'!$B$5:$N$5)*(1-持仓配置!$P$4)^((ROW()-6)/说明!$C$17)) | C15: =IF(OR(B15="",B14=""),"",B15/B14-1) | D15: =IF(B15="","",B15/MAX(B$6:B15)-1) | E15: =IF(OR('净值数据(iFinD公式)'!$A14="",'净值数据(iFinD公式)'!$B14=""),"",SUMPRODUCT(持仓配置!$B$5:$N$5,'净值数据(iFinD公式)'!$B14:$N14/'净值数据(iFinD公式)'!$B$5:$N$5)*(1-持仓配置!$P$5)^((ROW()-6)/说明!$C$17)) | F15: =IF(OR(E15="",E14=""),"",E15/E14-1) | G15: =IF(E15="","",E15/MAX(E$6:E15)-1) | H15: =IF(OR('净值数据(iFinD公式)'!$A14="",'净值数据(iFinD公式)'!$B14=""),"",SUMPRODUCT(持仓配置!$B$6:$N$6,'净值数据(iFinD公式)'!$B14:$N14/'净值数据(iFinD公式)'!$B$5:$N$5)*(1-持仓配置!$P$6)^((ROW()-6)/说明!$C$17)) | I15: =IF(OR(H15="",H14=""),"",H15/H14-1) | J15: =IF(H15="","",H15/MAX(H$6:H15)-1) | K15: =IF(OR('净值数据(iFinD公式)'!$A14="",'净值数据(iFinD公式)'!$B14=""),"",SUMPRODUCT(持仓配置!$B$7:$N$7,'净值数据(iFinD公式)'!$B14:$N14/'净值数据(iFinD公式)'!$B$5:$N$5)*(1-持仓配置!$P$7)^((ROW()-6)/说明!$C$17)) | L15: =IF(OR(K15="",K14=""),"",K15/K14-1) | M15: =IF(K15="","",K15/MAX(K$6:K15)-1)
A16: =IF('净值数据(iFinD公式)'!A15="","",'净值数据(iFinD公式)'!A15) | B16: =IF(OR('净值数据(iFinD公式)'!$A15="",'净值数据(iFinD公式)'!$B15=""),"",SUMPRODUCT(持仓配置!$B$4:$N$4,'净值数据(iFinD公式)'!$B15:$N15/'净值数据(iFinD公式)'!$B$5:$N$5)*(1-持仓配置!$P$4)^((ROW()-6)/说明!$C$17)) | C16: =IF(OR(B16="",B15=""),"",B16/B15-1) | D16: =IF(B16="","",B16/MAX(B$6:B16)-1) | E16: =IF(OR('净值数据(iFinD公式)'!$A15="",'净值数据(iFinD公式)'!$B15=""),"",SUMPRODUCT(持仓配置!$B$5:$N$5,'净值数据(iFinD公式)'!$B15:$N15/'净值数据(iFinD公式)'!$B$5:$N$5)*(1-持仓配置!$P$5)^((ROW()-6)/说明!$C$17)) | F16: =IF(OR(E16="",E15=""),"",E16/E15-1) | G16: =IF(E16="","",E16/MAX(E$6:E16)-1) | H16: =IF(OR('净值数据(iFinD公式)'!$A15="",'净值数据(iFinD公式)'!$B15=""),"",SUMPRODUCT(持仓配置!$B$6:$N$6,'净值数据(iFinD公式)'!$B15:$N15/'净值数据(iFinD公式)'!$B$5:$N$5)*(1-持仓配置!$P$6)^((ROW()-6)/说明!$C$17)) | I16: =IF(OR(H16="",H15=""),"",H16/H15-1) | J16: =IF(H16="","",H16/MAX(H$6:H16)-1) | K16: =IF(OR('净值数据(iFinD公式)'!$A15="",'净值数据(iFinD公式)'!$B15=""),"",SUMPRODUCT(持仓配置!$B$7:$N$7,'净值数据(iFinD公式)'!$B15:$N15/'净值数据(iFinD公式)'!$B$5:$N$5)*(1-持仓配置!$P$7)^((ROW()-6)/说明!$C$17)) | L16: =IF(OR(K16="",K15=""),"",K16/K15-1) | M16: =IF(K16="","",K16/MAX(K$6:K16)-1)
A17: =IF('净值数据(iFinD公式)'!A16="","",'净值数据(iFinD公式)'!A16) | B17: =IF(OR('净值数据(iFinD公式)'!$A16="",'净值数据(iFinD公式)'!$B16=""),"",SUMPRODUCT(持仓配置!$B$4:$N$4,'净值数据(iFinD公式)'!$B16:$N16/'净值数据(iFinD公式)'!$B$5:$N$5)*(1-持仓配置!$P$4)^((ROW()-6)/说明!$C$17)) | C17: =IF(OR(B17="",B16=""),"",B17/B16-1) | D17: =IF(B17="","",B17/MAX(B$6:B17)-1) | E17: =IF(OR('净值数据(iFinD公式)'!$A16="",'净值数据(iFinD公式)'!$B16=""),"",SUMPRODUCT(持仓配置!$B$5:$N$5,'净值数据(iFinD公式)'!$B16:$N16/'净值数据(iFinD公式)'!$B$5:$N$5)*(1-持仓配置!$P$5)^((ROW()-6)/说明!$C$17)) | F17: =IF(OR(E17="",E16=""),"",E17/E16-1) | G17: =IF(E17="","",E17/MAX(E$6:E17)-1) | H17: =IF(OR('净值数据(iFinD公式)'!$A16="",'净值数据(iFinD公式)'!$B16=""),"",SUMPRODUCT(持仓配置!$B$6:$N$6,'净值数据(iFinD公式)'!$B16:$N16/'净值数据(iFinD公式)'!$B$5:$N$5)*(1-持仓配置!$P$6)^((ROW()-6)/说明!$C$17)) | I17: =IF(OR(H17="",H16=""),"",H17/H16-1) | J17: =IF(H17="","",H17/MAX(H$6:H17)-1) | K17: =IF(OR('净值数据(iFinD公式)'!$A16="",'净值数据(iFinD公式)'!$B16=""),"",SUMPRODUCT(持仓配置!$B$7:$N$7,'净值数据(iFinD公式)'!$B16:$N16/'净值数据(iFinD公式)'!$B$5:$N$5)*(1-持仓配置!$P$7)^((ROW()-6)/说明!$C$17)) | L17: =IF(OR(K17="",K16=""),"",K17/K16-1) | M17: =IF(K17="","",K17/MAX(K$6:K17)-1)
A18: =IF('净值数据(iFinD公式)'!A17="","",'净值数据(iFinD公式)'!A17) | B18: =IF(OR('净值数据(iFinD公式)'!$A17="",'净值数据(iFinD公式)'!$B17=""),"",SUMPRODUCT(持仓配置!$B$4:$N$4,'净值数据(iFinD公式)'!$B17:$N17/'净值数据(iFinD公式)'!$B$5:$N$5)*(1-持仓配置!$P$4)^((ROW()-6)/说明!$C$17)) | C18: =IF(OR(B18="",B17=""),"",B18/B17-1) | D18: =IF(B18="","",B18/MAX(B$6:B18)-1) | E18: =IF(OR('净值数据(iFinD公式)'!$A17="",'净值数据(iFinD公式)'!$B17=""),"",SUMPRODUCT(持仓配置!$B$5:$N$5,'净值数据(iFinD公式)'!$B17:$N17/'净值数据(iFinD公式)'!$B$5:$N$5)*(1-持仓配置!$P$5)^((ROW()-6)/说明!$C$17)) | F18: =IF(OR(E18="",E17=""),"",E18/E17-1) | G18: =IF(E18="","",E18/MAX(E$6:E18)-1) | H18: =IF(OR('净值数据(iFinD公式)'!$A17="",'净值数据(iFinD公式)'!$B17=""),"",SUMPRODUCT(持仓配置!$B$6:$N$6,'净值数据(iFinD公式)'!$B17:$N17/'净值数据(iFinD公式)'!$B$5:$N$5)*(1-持仓配置!$P$6)^((ROW()-6)/说明!$C$17)) | I18: =IF(OR(H18="",H17=""),"",H18/H17-1) | J18: =IF(H18="","",H18/MAX(H$6:H18)-1) | K18: =IF(OR('净值数据(iFinD公式)'!$A17="",'净值数据(iFinD公式)'!$B17=""),"",SUMPRODUCT(持仓配置!$B$7:$N$7,'净值数据(iFinD公式)'!$B17:$N17/'净值数据(iFinD公式)'!$B$5:$N$5)*(1-持仓配置!$P$7)^((ROW()-6)/说明!$C$17)) | L18: =IF(OR(K18="",K17=""),"",K18/K17-1) | M18: =IF(K18="","",K18/MAX(K$6:K18)-1)
... A26: =IF('净值数据(iFinD公式)'!A25="","",'净值数据(iFinD公式)'!A25) | B26: =IF(OR('净值数据(iFinD公式)'!$A25="",'净值数据(iFinD公式)'!$B25=""),"",SUMPRODUCT(持仓配置!$B$4:$N$4,'净值数据(iFinD公式)'!$B25:$N25/'净值数据(iFinD公式)'!$B$5:$N$5)*(1-持仓配置!$P$4)^((ROW()-6)/说明!$C$17)) | C26: =IF(OR(B26="",B25=""),"",B26/B25-1) | D26: =IF(B26="","",B26/MAX(B$6:B26)-1) | E26: =IF(OR('净值数据(iFinD公式)'!$A25="",'净值数据(iFinD公式)'!$B25=""),"",SUMPRODUCT(持仓配置!$B$5:$N$5,'净值数据(iFinD公式)'!$B25:$N25/'净值数据(iFinD公式)'!$B$5:$N$5)*(1-持仓配置!$P$5)^((ROW()-6)/说明!$C$17)) | F26: =IF(OR(E26="",E25=""),"",E26/E25-1) | G26: =IF(E26="","",E26/MAX(E$6:E26)-1) | H26: =IF(OR('净值数据(iFinD公式)'!$A25="",'净值数据(iFinD公式)'!$B25=""),"",SUMPRODUCT(持仓配置!$B$6:$N$6,'净值数据(iFinD公式)'!$B25:$N25/'净值数据(iFinD公式)'!$B$5:$N$5)*(1-持仓配置!$P$6)^((ROW()-6)/说明!$C$17)) | I26: =IF(OR(H26="",H25=""),"",H26/H25-1) | J26: =IF(H26="","",H26/MAX(H$6:H26)-1) | K26: =IF(OR('净值数据(iFinD公式)'!$A25="",'净值数据(iFinD公式)'!$B25=""),"",SUMPRODUCT(持仓配置!$B$7:$N$7,'净值数据(iFinD公式)'!$B25:$N25/'净值数据(iFinD公式)'!$B$5:$N$5)*(1-持仓配置!$P$7)^((ROW()-6)/说明!$C$17)) | L26: =IF(OR(K26="",K25=""),"",K26/K25-1) | M26: =IF(K26="","",K26/MAX(K$6:K26)-1)
A27: =IF('净值数据(iFinD公式)'!A26="","",'净值数据(iFinD公式)'!A26) | B27: =IF(OR('净值数据(iFinD公式)'!$A26="",'净值数据(iFinD公式)'!$B26=""),"",SUMPRODUCT(持仓配置!$B$4:$N$4,'净值数据(iFinD公式)'!$B26:$N26/'净值数据(iFinD公式)'!$B$5:$N$5)*(1-持仓配置!$P$4)^((ROW()-6)/说明!$C$17)) | C27: =IF(OR(B27="",B26=""),"",B27/B26-1) | D27: =IF(B27="","",B27/MAX(B$6:B27)-1) | E27: =IF(OR('净值数据(iFinD公式)'!$A26="",'净值数据(iFinD公式)'!$B26=""),"",SUMPRODUCT(持仓配置!$B$5:$N$5,'净值数据(iFinD公式)'!$B26:$N26/'净值数据(iFinD公式)'!$B$5:$N$5)*(1-持仓配置!$P$5)^((ROW()-6)/说明!$C$17)) | F27: =IF(OR(E27="",E26=""),"",E27/E26-1) | G27: =IF(E27="","",E27/MAX(E$6:E27)-1) | H27: =IF(OR('净值数据(iFinD公式)'!$A26="",'净值数据(iFinD公式)'!$B26=""),"",SUMPRODUCT(持仓配置!$B$6:$N$6,'净值数据(iFinD公式)'!$B26:$N26/'净值数据(iFinD公式)'!$B$5:$N$5)*(1-持仓配置!$P$6)^((ROW()-6)/说明!$C$17)) | I27: =IF(OR(H27="",H26=""),"",H27/H26-1) | J27: =IF(H27="","",H27/MAX(H$6:H27)-1) | K27: =IF(OR('净值数据(iFinD公式)'!$A26="",'净值数据(iFinD公式)'!$B26=""),"",SUMPRODUCT(持仓配置!$B$7:$N$7,'净值数据(iFinD公式)'!$B26:$N26/'净值数据(iFinD公式)'!$B$5:$N$5)*(1-持仓配置!$P$7)^((ROW()-6)/说明!$C$17)) | L27: =IF(OR(K27="",K26=""),"",K27/K26-1) | M27: =IF(K27="","",K27/MAX(K$6:K27)-1) | O27: =B25/B6-1
A28: =IF('净值数据(iFinD公式)'!A27="","",'净值数据(iFinD公式)'!A27) | B28: =IF(OR('净值数据(iFinD公式)'!$A27="",'净值数据(iFinD公式)'!$B27=""),"",SUMPRODUCT(持仓配置!$B$4:$N$4,'净值数据(iFinD公式)'!$B27:$N27/'净值数据(iFinD公式)'!$B$5:$N$5)*(1-持仓配置!$P$4)^((ROW()-6)/说明!$C$17)) | C28: =IF(OR(B28="",B27=""),"",B28/B27-1) | D28: =IF(B28="","",B28/MAX(B$6:B28)-1) | E28: =IF(OR('净值数据(iFinD公式)'!$A27="",'净值数据(iFinD公式)'!$B27=""),"",SUMPRODUCT(持仓配置!$B$5:$N$5,'净值数据(iFinD公式)'!$B27:$N27/'净值数据(iFinD公式)'!$B$5:$N$5)*(1-持仓配置!$P$5)^((ROW()-6)/说明!$C$17)) | F28: =IF(OR(E28="",E27=""),"",E28/E27-1) | G28: =IF(E28="","",E28/MAX(E$6:E28)-1) | H28: =IF(OR('净值数据(iFinD公式)'!$A27="",'净值数据(iFinD公式)'!$B27=""),"",SUMPRODUCT(持仓配置!$B$6:$N$6,'净值数据(iFinD公式)'!$B27:$N27/'净值数据(iFinD公式)'!$B$5:$N$5)*(1-持仓配置!$P$6)^((ROW()-6)/说明!$C$17)) | I28: =IF(OR(H28="",H27=""),"",H28/H27-1) | J28: =IF(H28="","",H28/MAX(H$6:H28)-1) | K28: =IF(OR('净值数据(iFinD公式)'!$A27="",'净值数据(iFinD公式)'!$B27=""),"",SUMPRODUCT(持仓配置!$B$7:$N$7,'净值数据(iFinD公式)'!$B27:$N27/'净值数据(iFinD公式)'!$B$5:$N$5)*(1-持仓配置!$P$7)^((ROW()-6)/说明!$C$17)) | L28: =IF(OR(K28="",K27=""),"",K28/K27-1) | M28: =IF(K28="","",K28/MAX(K$6:K28)-1)
A29: =IF('净值数据(iFinD公式)'!A28="","",'净值数据(iFinD公式)'!A28) | B29: =IF(OR('净值数据(iFinD公式)'!$A28="",'净值数据(iFinD公式)'!$B28=""),"",SUMPRODUCT(持仓配置!$B$4:$N$4,'净值数据(iFinD公式)'!$B28:$N28/'净值数据(iFinD公式)'!$B$5:$N$5)*(1-持仓配置!$P$4)^((ROW()-6)/说明!$C$17)) | C29: =IF(OR(B29="",B28=""),"",B29/B28-1) | D29: =IF(B29="","",B29/MAX(B$6:B29)-1) | E29: =IF(OR('净值数据(iFinD公式)'!$A28="",'净值数据(iFinD公式)'!$B28=""),"",SUMPRODUCT(持仓配置!$B$5:$N$5,'净值数据(iFinD公式)'!$B28:$N28/'净值数据(iFinD公式)'!$B$5:$N$5)*(1-持仓配置!$P$5)^((ROW()-6)/说明!$C$17)) | F29: =IF(OR(E29="",E28=""),"",E29/E28-1) | G29: =IF(E29="","",E29/MAX(E$6:E29)-1) | H29: =IF(OR('净值数据(iFinD公式)'!$A28="",'净值数据(iFinD公式)'!$B28=""),"",SUMPRODUCT(持仓配置!$B$6:$N$6,'净值数据(iFinD公式)'!$B28:$N28/'净值数据(iFinD公式)'!$B$5:$N$5)*(1-持仓配置!$P$6)^((ROW()-6)/说明!$C$17)) | I29: =IF(OR(H29="",H28=""),"",H29/H28-1) | J29: =IF(H29="","",H29/MAX(H$6:H29)-1) | K29: =IF(OR('净值数据(iFinD公式)'!$A28="",'净值数据(iFinD公式)'!$B28=""),"",SUMPRODUCT(持仓配置!$B$7:$N$7,'净值数据(iFinD公式)'!$B28:$N28/'净值数据(iFinD公式)'!$B$5:$N$5)*(1-持仓配置!$P$7)^((ROW()-6)/说明!$C$17)) | L29: =IF(OR(K29="",K28=""),"",K29/K28-1) | M29: =IF(K29="","",K29/MAX(K$6:K29)-1)
A30: =IF('净值数据(iFinD公式)'!A29="","",'净值数据(iFinD公式)'!A29) | B30: =IF(OR('净值数据(iFinD公式)'!$A29="",'净值数据(iFinD公式)'!$B29=""),"",SUMPRODUCT(持仓配置!$B$4:$N$4,'净值数据(iFinD公式)'!$B29:$N29/'净值数据(iFinD公式)'!$B$5:$N$5)*(1-持仓配置!$P$4)^((ROW()-6)/说明!$C$17)) | C30: =IF(OR(B30="",B29=""),"",B30/B29-1) | D30: =IF(B30="","",B30/MAX(B$6:B30)-1) | E30: =IF(OR('净值数据(iFinD公式)'!$A29="",'净值数据(iFinD公式)'!$B29=""),"",SUMPRODUCT(持仓配置!$B$5:$N$5,'净值数据(iFinD公式)'!$B29:$N29/'净值数据(iFinD公式)'!$B$5:$N$5)*(1-持仓配置!$P$5)^((ROW()-6)/说明!$C$17)) | F30: =IF(OR(E30="",E29=""),"",E30/E29-1) | G30: =IF(E30="","",E30/MAX(E$6:E30)-1) | H30: =IF(OR('净值数据(iFinD公式)'!$A29="",'净值数据(iFinD公式)'!$B29=""),"",SUMPRODUCT(持仓配置!$B$6:$N$6,'净值数据(iFinD公式)'!$B29:$N29/'净值数据(iFinD公式)'!$B$5:$N$5)*(1-持仓配置!$P$6)^((ROW()-6)/说明!$C$17)) | I30: =IF(OR(H30="",H29=""),"",H30/H29-1) | J30: =IF(H30="","",H30/MAX(H$6:H30)-1) | K30: =IF(OR('净值数据(iFinD公式)'!$A29="",'净值数据(iFinD公式)'!$B29=""),"",SUMPRODUCT(持仓配置!$B$7:$N$7,'净值数据(iFinD公式)'!$B29:$N29/'净值数据(iFinD公式)'!$B$5:$N$5)*(1-持仓配置!$P$7)^((ROW()-6)/说明!$C$17)) | L30: =IF(OR(K30="",K29=""),"",K30/K29-1) | M30: =IF(K30="","",K30/MAX(K$6:K30)-1)
A31: =IF('净值数据(iFinD公式)'!A30="","",'净值数据(iFinD公式)'!A30) | B31: =IF(OR('净值数据(iFinD公式)'!$A30="",'净值数据(iFinD公式)'!$B30=""),"",SUMPRODUCT(持仓配置!$B$4:$N$4,'净值数据(iFinD公式)'!$B30:$N30/'净值数据(iFinD公式)'!$B$5:$N$5)*(1-持仓配置!$P$4)^((ROW()-6)/说明!$C$17)) | C31: =IF(OR(B31="",B30=""),"",B31/B30-1) | D31: =IF(B31="","",B31/MAX(B$6:B31)-1) | E31: =IF(OR('净值数据(iFinD公式)'!$A30="",'净值数据(iFinD公式)'!$B30=""),"",SUMPRODUCT(持仓配置!$B$5:$N$5,'净值数据(iFinD公式)'!$B30:$N30/'净值数据(iFinD公式)'!$B$5:$N$5)*(1-持仓配置!$P$5)^((ROW()-6)/说明!$C$17)) | F31: =IF(OR(E31="",E30=""),"",E31/E30-1) | G31: =IF(E31="","",E31/MAX(E$6:E31)-1) | H31: =IF(OR('净值数据(iFinD公式)'!$A30="",'净值数据(iFinD公式)'!$B30=""),"",SUMPRODUCT(持仓配置!$B$6:$N$6,'净值数据(iFinD公式)'!$B30:$N30/'净值数据(iFinD公式)'!$B$5:$N$5)*(1-持仓配置!$P$6)^((ROW()-6)/说明!$C$17)) | I31: =IF(OR(H31="",H30=""),"",H31/H30-1) | J31: =IF(H31="","",H31/MAX(H$6:H31)-1) | K31: =IF(OR('净值数据(iFinD公式)'!$A30="",'净值数据(iFinD公式)'!$B30=""),"",SUMPRODUCT(持仓配置!$B$7:$N$7,'净值数据(iFinD公式)'!$B30:$N30/'净值数据(iFinD公式)'!$B$5:$N$5)*(1-持仓配置!$P$7)^((ROW()-6)/说明!$C$17)) | L31: =IF(OR(K31="",K30=""),"",K31/K30-1) | M31: =IF(K31="","",K31/MAX(K$6:K31)-1)
A32: =IF('净值数据(iFinD公式)'!A31="","",'净值数据(iFinD公式)'!A31) | B32: =IF(OR('净值数据(iFinD公式)'!$A31="",'净值数据(iFinD公式)'!$B31=""),"",SUMPRODUCT(持仓配置!$B$4:$N$4,'净值数据(iFinD公式)'!$B31:$N31/'净值数据(iFinD公式)'!$B$5:$N$5)*(1-持仓配置!$P$4)^((ROW()-6)/说明!$C$17)) | C32: =IF(OR(B32="",B31=""),"",B32/B31-1) | D32: =IF(B32="","",B32/MAX(B$6:B32)-1) | E32: =IF(OR('净值数据(iFinD公式)'!$A31="",'净值数据(iFinD公式)'!$B31=""),"",SUMPRODUCT(持仓配置!$B$5:$N$5,'净值数据(iFinD公式)'!$B31:$N31/'净值数据(iFinD公式)'!$B$5:$N$5)*(1-持仓配置!$P$5)^((ROW()-6)/说明!$C$17)) | F32: =IF(OR(E32="",E31=""),"",E32/E31-1) | G32: =IF(E32="","",E32/MAX(E$6:E32)-1) | H32: =IF(OR('净值数据(iFinD公式)'!$A31="",'净值数据(iFinD公式)'!$B31=""),"",SUMPRODUCT(持仓配置!$B$6:$N$6,'净值数据(iFinD公式)'!$B31:$N31/'净值数据(iFinD公式)'!$B$5:$N$5)*(1-持仓配置!$P$6)^((ROW()-6)/说明!$C$17)) | I32: =IF(OR(H32="",H31=""),"",H32/H31-1) | J32: =IF(H32="","",H32/MAX(H$6:H32)-1) | K32: =IF(OR('净值数据(iFinD公式)'!$A31="",'净值数据(iFinD公式)'!$B31=""),"",SUMPRODUCT(持仓配置!$B$7:$N$7,'净值数据(iFinD公式)'!$B31:$N31/'净值数据(iFinD公式)'!$B$5:$N$5)*(1-持仓配置!$P$7)^((ROW()-6)/说明!$C$17)) | L32: =IF(OR(K32="",K31=""),"",K32/K31-1) | M32: =IF(K32="","",K32/MAX(K$6:K32)-1)
A33: =IF('净值数据(iFinD公式)'!A32="","",'净值数据(iFinD公式)'!A32) | B33: =IF(OR('净值数据(iFinD公式)'!$A32="",'净值数据(iFinD公式)'!$B32=""),"",SUMPRODUCT(持仓配置!$B$4:$N$4,'净值数据(iFinD公式)'!$B32:$N32/'净值数据(iFinD公式)'!$B$5:$N$5)*(1-持仓配置!$P$4)^((ROW()-6)/说明!$C$17)) | C33: =IF(OR(B33="",B32=""),"",B33/B32-1) | D33: =IF(B33="","",B33/MAX(B$6:B33)-1) | E33: =IF(OR('净值数据(iFinD公式)'!$A32="",'净值数据(iFinD公式)'!$B32=""),"",SUMPRODUCT(持仓配置!$B$5:$N$5,'净值数据(iFinD公式)'!$B32:$N32/'净值数据(iFinD公式)'!$B$5:$N$5)*(1-持仓配置!$P$5)^((ROW()-6)/说明!$C$17)) | F33: =IF(OR(E33="",E32=""),"",E33/E32-1) | G33: =IF(E33="","",E33/MAX(E$6:E33)-1) | H33: =IF(OR('净值数据(iFinD公式)'!$A32="",'净值数据(iFinD公式)'!$B32=""),"",SUMPRODUCT(持仓配置!$B$6:$N$6,'净值数据(iFinD公式)'!$B32:$N32/'净值数据(iFinD公式)'!$B$5:$N$5)*(1-持仓配置!$P$6)^((ROW()-6)/说明!$C$17)) | I33: =IF(OR(H33="",H32=""),"",H33/H32-1) | J33: =IF(H33="","",H33/MAX(H$6:H33)-1) | K33: =IF(OR('净值数据(iFinD公式)'!$A32="",'净值数据(iFinD公式)'!$B32=""),"",SUMPRODUCT(持仓配置!$B$7:$N$7,'净值数据(iFinD公式)'!$B32:$N32/'净值数据(iFinD公式)'!$B$5:$N$5)*(1-持仓配置!$P$7)^((ROW()-6)/说明!$C$17)) | L33: =IF(OR(K33="",K32=""),"",K33/K32-1) | M33: =IF(K33="","",K33/MAX(K$6:K33)-1)
A34: =IF('净值数据(iFinD公式)'!A33="","",'净值数据(iFinD公式)'!A33) | B34: =IF(OR('净值数据(iFinD公式)'!$A33="",'净值数据(iFinD公式)'!$B33=""),"",SUMPRODUCT(持仓配置!$B$4:$N$4,'净值数据(iFinD公式)'!$B33:$N33/'净值数据(iFinD公式)'!$B$5:$N$5)*(1-持仓配置!$P$4)^((ROW()-6)/说明!$C$17)) | C34: =IF(OR(B34="",B33=""),"",B34/B33-1) | D34: =IF(B34="","",B34/MAX(B$6:B34)-1) | E34: =IF(OR('净值数据(iFinD公式)'!$A33="",'净值数据(iFinD公式)'!$B33=""),"",SUMPRODUCT(持仓配置!$B$5:$N$5,'净值数据(iFinD公式)'!$B33:$N33/'净值数据(iFinD公式)'!$B$5:$N$5)*(1-持仓配置!$P$5)^((ROW()-6)/说明!$C$17)) | F34: =IF(OR(E34="",E33=""),"",E34/E33-1) | G34: =IF(E34="","",E34/MAX(E$6:E34)-1) | H34: =IF(OR('净值数据(iFinD公式)'!$A33="",'净值数据(iFinD公式)'!$B33=""),"",SUMPRODUCT(持仓配置!$B$6:$N$6,'净值数据(iFinD公式)'!$B33:$N33/'净值数据(iFinD公式)'!$B$5:$N$5)*(1-持仓配置!$P$6)^((ROW()-6)/说明!$C$17)) | I34: =IF(OR(H34="",H33=""),"",H34/H33-1) | J34: =IF(H34="","",H34/MAX(H$6:H34)-1) | K34: =IF(OR('净值数据(iFinD公式)'!$A33="",'净值数据(iFinD公式)'!$B33=""),"",SUMPRODUCT(持仓配置!$B$7:$N$7,'净值数据(iFinD公式)'!$B33:$N33/'净值数据(iFinD公式)'!$B$5:$N$5)*(1-持仓配置!$P$7)^((ROW()-6)/说明!$C$17)) | L34: =IF(OR(K34="",K33=""),"",K34/K33-1) | M34: =IF(K34="","",K34/MAX(K$6:K34)-1)
A35: =IF('净值数据(iFinD公式)'!A34="","",'净值数据(iFinD公式)'!A34) | B35: =IF(OR('净值数据(iFinD公式)'!$A34="",'净值数据(iFinD公式)'!$B34=""),"",SUMPRODUCT(持仓配置!$B$4:$N$4,'净值数据(iFinD公式)'!$B34:$N34/'净值数据(iFinD公式)'!$B$5:$N$5)*(1-持仓配置!$P$4)^((ROW()-6)/说明!$C$17)) | C35: =IF(OR(B35="",B34=""),"",B35/B34-1) | D35: =IF(B35="","",B35/MAX(B$6:B35)-1) | E35: =IF(OR('净值数据(iFinD公式)'!$A34="",'净值数据(iFinD公式)'!$B34=""),"",SUMPRODUCT(持仓配置!$B$5:$N$5,'净值数据(iFinD公式)'!$B34:$N34/'净值数据(iFinD公式)'!$B$5:$N$5)*(1-持仓配置!$P$5)^((ROW()-6)/说明!$C$17)) | F35: =IF(OR(E35="",E34=""),"",E35/E34-1) | G35: =IF(E35="","",E35/MAX(E$6:E35)-1) | H35: =IF(OR('净值数据(iFinD公式)'!$A34="",'净值数据(iFinD公式)'!$B34=""),"",SUMPRODUCT(持仓配置!$B$6:$N$6,'净值数据(iFinD公式)'!$B34:$N34/'净值数据(iFinD公式)'!$B$5:$N$5)*(1-持仓配置!$P$6)^((ROW()-6)/说明!$C$17)) | I35: =IF(OR(H35="",H34=""),"",H35/H34-1) | J35: =IF(H35="","",H35/MAX(H$6:H35)-1) | K35: =IF(OR('净值数据(iFinD公式)'!$A34="",'净值数据(iFinD公式)'!$B34=""),"",SUMPRODUCT(持仓配置!$B$7:$N$7,'净值数据(iFinD公式)'!$B34:$N34/'净值数据(iFinD公式)'!$B$5:$N$5)*(1-持仓配置!$P$7)^((ROW()-6)/说明!$C$17)) | L35: =IF(OR(K35="",K34=""),"",K35/K34-1) | M35: =IF(K35="","",K35/MAX(K$6:K35)-1)
A36: =IF('净值数据(iFinD公式)'!A35="","",'净值数据(iFinD公式)'!A35) | B36: =IF(OR('净值数据(iFinD公式)'!$A35="",'净值数据(iFinD公式)'!$B35=""),"",SUMPRODUCT(持仓配置!$B$4:$N$4,'净值数据(iFinD公式)'!$B35:$N35/'净值数据(iFinD公式)'!$B$5:$N$5)*(1-持仓配置!$P$4)^((ROW()-6)/说明!$C$17)) | C36: =IF(OR(B36="",B35=""),"",B36/B35-1) | D36: =IF(B36="","",B36/MAX(B$6:B36)-1) | E36: =IF(OR('净值数据(iFinD公式)'!$A35="",'净值数据(iFinD公式)'!$B35=""),"",SUMPRODUCT(持仓配置!$B$5:$N$5,'净值数据(iFinD公式)'!$B35:$N35/'净值数据(iFinD公式)'!$B$5:$N$5)*(1-持仓配置!$P$5)^((ROW()-6)/说明!$C$17)) | F36: =IF(OR(E36="",E35=""),"",E36/E35-1) | G36: =IF(E36="","",E36/MAX(E$6:E36)-1) | H36: =IF(OR('净值数据(iFinD公式)'!$A35="",'净值数据(iFinD公式)'!$B35=""),"",SUMPRODUCT(持仓配置!$B$6:$N$6,'净值数据(iFinD公式)'!$B35:$N35/'净值数据(iFinD公式)'!$B$5:$N$5)*(1-持仓配置!$P$6)^((ROW()-6)/说明!$C$17)) | I36: =IF(OR(H36="",H35=""),"",H36/H35-1) | J36: =IF(H36="","",H36/MAX(H$6:H36)-1) | K36: =IF(OR('净值数据(iFinD公式)'!$A35="",'净值数据(iFinD公式)'!$B35=""),"",SUMPRODUCT(持仓配置!$B$7:$N$7,'净值数据(iFinD公式)'!$B35:$N35/'净值数据(iFinD公式)'!$B$5:$N$5)*(1-持仓配置!$P$7)^((ROW()-6)/说明!$C$17)) | L36: =IF(OR(K36="",K35=""),"",K36/K35-1) | M36: =IF(K36="","",K36/MAX(K$6:K36)-1)
A37: =IF('净值数据(iFinD公式)'!A36="","",'净值数据(iFinD公式)'!A36) | B37: =IF(OR('净值数据(iFinD公式)'!$A36="",'净值数据(iFinD公式)'!$B36=""),"",SUMPRODUCT(持仓配置!$B$4:$N$4,'净值数据(iFinD公式)'!$B36:$N36/'净值数据(iFinD公式)'!$B$5:$N$5)*(1-持仓配置!$P$4)^((ROW()-6)/说明!$C$17)) | C37: =IF(OR(B37="",B36=""),"",B37/B36-1) | D37: =IF(B37="","",B37/MAX(B$6:B37)-1) | E37: =IF(OR('净值数据(iFinD公式)'!$A36="",'净值数据(iFinD公式)'!$B36=""),"",SUMPRODUCT(持仓配置!$B$5:$N$5,'净值数据(iFinD公式)'!$B36:$N36/'净值数据(iFinD公式)'!$B$5:$N$5)*(1-持仓配置!$P$5)^((ROW()-6)/说明!$C$17)) | F37: =IF(OR(E37="",E36=""),"",E37/E36-1) | G37: =IF(E37="","",E37/MAX(E$6:E37)-1) | H37: =IF(OR('净值数据(iFinD公式)'!$A36="",'净值数据(iFinD公式)'!$B36=""),"",SUMPRODUCT(持仓配置!$B$6:$N$6,'净值数据(iFinD公式)'!$B36:$N36/'净值数据(iFinD公式)'!$B$5:$N$5)*(1-持仓配置!$P$6)^((ROW()-6)/说明!$C$17)) | I37: =IF(OR(H37="",H36=""),"",H37/H36-1) | J37: =IF(H37="","",H37/MAX(H$6:H37)-1) | K37: =IF(OR('净值数据(iFinD公式)'!$A36="",'净值数据(iFinD公式)'!$B36=""),"",SUMPRODUCT(持仓配置!$B$7:$N$7,'净值数据(iFinD公式)'!$B36:$N36/'净值数据(iFinD公式)'!$B$5:$N$5)*(1-持仓配置!$P$7)^((ROW()-6)/说明!$C$17)) | L37: =IF(OR(K37="",K36=""),"",K37/K36-1) | M37: =IF(K37="","",K37/MAX(K$6:K37)-1)
A38: =IF('净值数据(iFinD公式)'!A37="","",'净值数据(iFinD公式)'!A37) | B38: =IF(OR('净值数据(iFinD公式)'!$A37="",'净值数据(iFinD公式)'!$B37=""),"",SUMPRODUCT(持仓配置!$B$4:$N$4,'净值数据(iFinD公式)'!$B37:$N37/'净值数据(iFinD公式)'!$B$5:$N$5)*(1-持仓配置!$P$4)^((ROW()-6)/说明!$C$17)) | C38: =IF(OR(B38="",B37=""),"",B38/B37-1) | D38: =IF(B38="","",B38/MAX(B$6:B38)-1) | E38: =IF(OR('净值数据(iFinD公式)'!$A37="",'净值数据(iFinD公式)'!$B37=""),"",SUMPRODUCT(持仓配置!$B$5:$N$5,'净值数据(iFinD公式)'!$B37:$N37/'净值数据(iFinD公式)'!$B$5:$N$5)*(1-持仓配置!$P$5)^((ROW()-6)/说明!$C$17)) | F38: =IF(OR(E38="",E37=""),"",E38/E37-1) | G38: =IF(E38="","",E38/MAX(E$6:E38)-1) | H38: =IF(OR('净值数据(iFinD公式)'!$A37="",'净值数据(iFinD公式)'!$B37=""),"",SUMPRODUCT(持仓配置!$B$6:$N$6,'净值数据(iFinD公式)'!$B37:$N37/'净值数据(iFinD公式)'!$B$5:$N$5)*(1-持仓配置!$P$6)^((ROW()-6)/说明!$C$17)) | I38: =IF(OR(H38="",H37=""),"",H38/H37-1) | J38: =IF(H38="","",H38/MAX(H$6:H38)-1) | K38: =IF(OR('净值数据(iFinD公式)'!$A37="",'净值数据(iFinD公式)'!$B37=""),"",SUMPRODUCT(持仓配置!$B$7:$N$7,'净值数据(iFinD公式)'!$B37:$N37/'净值数据(iFinD公式)'!$B$5:$N$5)*(1-持仓配置!$P$7)^((ROW()-6)/说明!$C$17)) | L38: =IF(OR(K38="",K37=""),"",K38/K37-1) | M38: =IF(K38="","",K38/MAX(K$6:K38)-1)
A39: =IF('净值数据(iFinD公式)'!A38="","",'净值数据(iFinD公式)'!A38) | B39: =IF(OR('净值数据(iFinD公式)'!$A38="",'净值数据(iFinD公式)'!$B38=""),"",SUMPRODUCT(持仓配置!$B$4:$N$4,'净值数据(iFinD公式)'!$B38:$N38/'净值数据(iFinD公式)'!$B$5:$N$5)*(1-持仓配置!$P$4)^((ROW()-6)/说明!$C$17)) | C39: =IF(OR(B39="",B38=""),"",B39/B38-1) | D39: =IF(B39="","",B39/MAX(B$6:B39)-1) | E39: =IF(OR('净值数据(iFinD公式)'!$A38="",'净值数据(iFinD公式)'!$B38=""),"",SUMPRODUCT(持仓配置!$B$5:$N$5,'净值数据(iFinD公式)'!$B38:$N38/'净值数据(iFinD公式)'!$B$5:$N$5)*(1-持仓配置!$P$5)^((ROW()-6)/说明!$C$17)) | F39: =IF(OR(E39="",E38=""),"",E39/E38-1) | G39: =IF(E39="","",E39/MAX(E$6:E39)-1) | H39: =IF(OR('净值数据(iFinD公式)'!$A38="",'净值数据(iFinD公式)'!$B38=""),"",SUMPRODUCT(持仓配置!$B$6:$N$6,'净值数据(iFinD公式)'!$B38:$N38/'净值数据(iFinD公式)'!$B$5:$N$5)*(1-持仓配置!$P$6)^((ROW()-6)/说明!$C$17)) | I39: =IF(OR(H39="",H38=""),"",H39/H38-1) | J39: =IF(H39="","",H39/MAX(H$6:H39)-1) | K39: =IF(OR('净值数据(iFinD公式)'!$A38="",'净值数据(iFinD公式)'!$B38=""),"",SUMPRODUCT(持仓配置!$B$7:$N$7,'净值数据(iFinD公式)'!$B38:$N38/'净值数据(iFinD公式)'!$B$5:$N$5)*(1-持仓配置!$P$7)^((ROW()-6)/说明!$C$17)) | L39: =IF(OR(K39="",K38=""),"",K39/K38-1) | M39: =IF(K39="","",K39/MAX(K$6:K39)-1)
... A60: =IF('净值数据(iFinD公式)'!A59="","",'净值数据(iFinD公式)'!A59) | B60: =IF(OR('净值数据(iFinD公式)'!$A59="",'净值数据(iFinD公式)'!$B59=""),"",SUMPRODUCT(持仓配置!$B$4:$N$4,'净值数据(iFinD公式)'!$B59:$N59/'净值数据(iFinD公式)'!$B$5:$N$5)*(1-持仓配置!$P$4)^((ROW()-6)/说明!$C$17)) | C60: =IF(OR(B60="",B59=""),"",B60/B59-1) | D60: =IF(B60="","",B60/MAX(B$6:B60)-1) | E60: =IF(OR('净值数据(iFinD公式)'!$A59="",'净值数据(iFinD公式)'!$B59=""),"",SUMPRODUCT(持仓配置!$B$5:$N$5,'净值数据(iFinD公式)'!$B59:$N59/'净值数据(iFinD公式)'!$B$5:$N$5)*(1-持仓配置!$P$5)^((ROW()-6)/说明!$C$17)) | F60: =IF(OR(E60="",E59=""),"",E60/E59-1) | G60: =IF(E60="","",E60/MAX(E$6:E60)-1) | H60: =IF(OR('净值数据(iFinD公式)'!$A59="",'净值数据(iFinD公式)'!$B59=""),"",SUMPRODUCT(持仓配置!$B$6:$N$6,'净值数据(iFinD公式)'!$B59:$N59/'净值数据(iFinD公式)'!$B$5:$N$5)*(1-持仓配置!$P$6)^((ROW()-6)/说明!$C$17)) | I60: =IF(OR(H60="",H59=""),"",H60/H59-1) | J60: =IF(H60="","",H60/MAX(H$6:H60)-1) | K60: =IF(OR('净值数据(iFinD公式)'!$A59="",'净值数据(iFinD公式)'!$B59=""),"",SUMPRODUCT(持仓配置!$B$7:$N$7,'净值数据(iFinD公式)'!$B59:$N59/'净值数据(iFinD公式)'!$B$5:$N$5)*(1-持仓配置!$P$7)^((ROW()-6)/说明!$C$17)) | L60: =IF(OR(K60="",K59=""),"",K60/K59-1) | M60: =IF(K60="","",K60/MAX(K$6:K60)-1)
A62: 组合净值起始=1.0000；买入持有，权重随涨跌漂移；净值已按年化费率折每日扣费。新增日期下拉填充。

Sheet 看板-10-90
B2: 样板间组合走势看板（10-90 账户）
B3: ="买入持有 · 已扣年化费率 "&TEXT(持仓配置!$M$4,"0.0%")&"（折每日计入净值）" | E3: ="净值日期："&TEXT(LOOKUP(2,1/(组合净值!$B$6:$B$60<>""),组合净值!$A$6:$A$60),"yyyy-mm-dd")
B5: 产品业绩表现（历史表现不代表未来收益承诺）
B6: 最新净值 | C6: 累计收益 | D6: 年化收益 | E6: 年化波动率 | F6: 最大回撤 | G6: 夏普比率
B7: =LOOKUP(2,1/(组合净值!$B$6:$B$60<>""),组合净值!$B$6:$B$60) | C7: =(LOOKUP(2,1/(组合净值!$B$6:$B$60<>""),组合净值!$B$6:$B$60))/组合净值!$B$6-1 | D7: =(LOOKUP(2,1/(组合净值!$B$6:$B$60<>""),组合净值!$B$6:$B$60)/组合净值!$B$6)^(说明!$C$17/MAX(COUNT(组合净值!$C$6:$C$60),1))-1 | E7: =STDEV(组合净值!$C$6:$C$60)*SQRT(说明!$C$17) | F7: =MIN(组合净值!$D$6:$D$60) | G7: =(((LOOKUP(2,1/(组合净值!$B$6:$B$60<>""),组合净值!$B$6:$B$60)/组合净值!$B$6)^(说明!$C$17/MAX(COUNT(组合净值!$C$6:$C$60),1))-1)-说明!$C$16)/IF((STDEV(组合净值!$C$6:$C$60)*SQRT(说明!$C$17))=0,"",(STDEV(组合净值!$C$6:$C$60)*SQRT(说明!$C$17)))
B9: 收益表现 | E9: 风险特征
B10: 区间 | C10: 累计收益 | D10: 年化收益 | E10: 指标 | G10: 数值
B11: 起始以来 | C11: =IFERROR((LOOKUP(2,1/(组合净值!$B$6:$B$60<>""),组合净值!$B$6:$B$60))/(组合净值!$B$6)-1,"") | D11: =IFERROR((LOOKUP(2,1/(组合净值!$B$6:$B$60<>""),组合净值!$B$6:$B$60)/(组合净值!$B$6))^(说明!$C$17/COUNT(组合净值!$C$6:$C$60))-1,"") | E11: 最大回撤 | G11: =MIN(组合净值!$D$6:$D$60)
B12: 2026YTD | C12: =IFERROR((LOOKUP(2,1/(组合净值!$B$6:$B$60<>""),组合净值!$B$6:$B$60))/(IFERROR(LOOKUP(DATE(2026,1,1),组合净值!$A$6:$A$60,组合净值!$B$6:$B$60),组合净值!$B$6))-1,"") | D12: =IFERROR((LOOKUP(2,1/(组合净值!$B$6:$B$60<>""),组合净值!$B$6:$B$60)/(IFERROR(LOOKUP(DATE(2026,1,1),组合净值!$A$6:$A$60,组合净值!$B$6:$B$60),组合净值!$B$6)))^(说明!$C$17/MAX(COUNTIF(组合净值!$A$6:$A$60,">="&(DATE(2026,1,1))),1))-1,"") | E12: 回撤修复天数(未创新高) | G12: =IFERROR((LOOKUP(2,1/(组合净值!$B$6:$B$60<>""),ROW(组合净值!$B$6:$B$60)))-(LOOKUP(2,1/(组合净值!$D$6:$D$60=0),ROW(组合净值!$D$6:$D$60))),"")
B13: 近3个月 | C13: =IFERROR((LOOKUP(2,1/(组合净值!$B$6:$B$60<>""),组合净值!$B$6:$B$60))/(IFERROR(LOOKUP(EDATE(LOOKUP(2,1/(组合净值!$B$6:$B$60<>""),组合净值!$A$6:$A$60),-3),组合净值!$A$6:$A$60,组合净值!$B$6:$B$60),组合净值!$B$6))-1,"") | D13: =IFERROR((LOOKUP(2,1/(组合净值!$B$6:$B$60<>""),组合净值!$B$6:$B$60)/(IFERROR(LOOKUP(EDATE(LOOKUP(2,1/(组合净值!$B$6:$B$60<>""),组合净值!$A$6:$A$60),-3),组合净值!$A$6:$A$60,组合净值!$B$6:$B$60),组合净值!$B$6)))^(说明!$C$17/MAX(COUNTIF(组合净值!$A$6:$A$60,">="&(EDATE(LOOKUP(2,1/(组合净值!$B$6:$B$60<>""),组合净值!$A$6:$A$60),-3))),1))-1,"") | E13: 正收益占比 | G13: =COUNTIF(组合净值!$C$6:$C$60,">0")/MAX(COUNT(组合净值!$C$6:$C$60),1)
B14: 近6个月 | C14: =IFERROR((LOOKUP(2,1/(组合净值!$B$6:$B$60<>""),组合净值!$B$6:$B$60))/(IFERROR(LOOKUP(EDATE(LOOKUP(2,1/(组合净值!$B$6:$B$60<>""),组合净值!$A$6:$A$60),-6),组合净值!$A$6:$A$60,组合净值!$B$6:$B$60),组合净值!$B$6))-1,"") | D14: =IFERROR((LOOKUP(2,1/(组合净值!$B$6:$B$60<>""),组合净值!$B$6:$B$60)/(IFERROR(LOOKUP(EDATE(LOOKUP(2,1/(组合净值!$B$6:$B$60<>""),组合净值!$A$6:$A$60),-6),组合净值!$A$6:$A$60,组合净值!$B$6:$B$60),组合净值!$B$6)))^(说明!$C$17/MAX(COUNTIF(组合净值!$A$6:$A$60,">="&(EDATE(LOOKUP(2,1/(组合净值!$B$6:$B$60<>""),组合净值!$A$6:$A$60),-6))),1))-1,"") | E14: 年化波动率 | G14: =STDEV(组合净值!$C$6:$C$60)*SQRT(说明!$C$17)
B15: 近1年 | C15: =IFERROR((LOOKUP(2,1/(组合净值!$B$6:$B$60<>""),组合净值!$B$6:$B$60))/(IFERROR(LOOKUP(EDATE(LOOKUP(2,1/(组合净值!$B$6:$B$60<>""),组合净值!$A$6:$A$60),-12),组合净值!$A$6:$A$60,组合净值!$B$6:$B$60),组合净值!$B$6))-1,"") | D15: =IFERROR((LOOKUP(2,1/(组合净值!$B$6:$B$60<>""),组合净值!$B$6:$B$60)/(IFERROR(LOOKUP(EDATE(LOOKUP(2,1/(组合净值!$B$6:$B$60<>""),组合净值!$A$6:$A$60),-12),组合净值!$A$6:$A$60,组合净值!$B$6:$B$60),组合净值!$B$6)))^(说明!$C$17/MAX(COUNTIF(组合净值!$A$6:$A$60,">="&(EDATE(LOOKUP(2,1/(组合净值!$B$6:$B$60<>""),组合净值!$A$6:$A$60),-12))),1))-1,"") | E15: 夏普比率 | G15: =(((LOOKUP(2,1/(组合净值!$B$6:$B$60<>""),组合净值!$B$6:$B$60)/组合净值!$B$6)^(说明!$C$17/MAX(COUNT(组合净值!$C$6:$C$60),1))-1)-说明!$C$16)/IF((STDEV(组合净值!$C$6:$C$60)*SQRT(说明!$C$17))=0,"",(STDEV(组合净值!$C$6:$C$60)*SQRT(说明!$C$17)))
E16: 卡玛比率 | G16: =IFERROR(((LOOKUP(2,1/(组合净值!$B$6:$B$60<>""),组合净值!$B$6:$B$60)/组合净值!$B$6)^(说明!$C$17/MAX(COUNT(组合净值!$C$6:$C$60),1))-1)/ABS(MIN(组合净值!$D$6:$D$60)),"")
B18: 产品运作情况 · 组合净值曲线
B35: 统计区间自2026/6/1起；运作初期样本少，年化类指标仅供参考。新增交易日后请同步扩展本图数据区。

Sheet 看板-20-80
B2: 样板间组合走势看板（20-80 账户）
B3: ="买入持有 · 已扣年化费率 "&TEXT(持仓配置!$M$5,"0.0%")&"（折每日计入净值）" | E3: ="净值日期："&TEXT(LOOKUP(2,1/(组合净值!$E$6:$E$60<>""),组合净值!$A$6:$A$60),"yyyy-mm-dd")
B5: 产品业绩表现（历史表现不代表未来收益承诺）
B6: 最新净值 | C6: 累计收益 | D6: 年化收益 | E6: 年化波动率 | F6: 最大回撤 | G6: 夏普比率
B7: =LOOKUP(2,1/(组合净值!$E$6:$E$60<>""),组合净值!$E$6:$E$60) | C7: =(LOOKUP(2,1/(组合净值!$E$6:$E$60<>""),组合净值!$E$6:$E$60))/组合净值!$E$6-1 | D7: =(LOOKUP(2,1/(组合净值!$E$6:$E$60<>""),组合净值!$E$6:$E$60)/组合净值!$E$6)^(说明!$C$17/MAX(COUNT(组合净值!$F$6:$F$60),1))-1 | E7: =STDEV(组合净值!$F$6:$F$60)*SQRT(说明!$C$17) | F7: =MIN(组合净值!$G$6:$G$60) | G7: =(((LOOKUP(2,1/(组合净值!$E$6:$E$60<>""),组合净值!$E$6:$E$60)/组合净值!$E$6)^(说明!$C$17/MAX(COUNT(组合净值!$F$6:$F$60),1))-1)-说明!$C$16)/IF((STDEV(组合净值!$F$6:$F$60)*SQRT(说明!$C$17))=0,"",(STDEV(组合净值!$F$6:$F$60)*SQRT(说明!$C$17)))
B9: 收益表现 | E9: 风险特征
B10: 区间 | C10: 累计收益 | D10: 年化收益 | E10: 指标 | G10: 数值
B11: 起始以来 | C11: =IFERROR((LOOKUP(2,1/(组合净值!$E$6:$E$60<>""),组合净值!$E$6:$E$60))/(组合净值!$E$6)-1,"") | D11: =IFERROR((LOOKUP(2,1/(组合净值!$E$6:$E$60<>""),组合净值!$E$6:$E$60)/(组合净值!$E$6))^(说明!$C$17/COUNT(组合净值!$F$6:$F$60))-1,"") | E11: 最大回撤 | G11: =MIN(组合净值!$G$6:$G$60)
B12: 2026YTD | C12: =IFERROR((LOOKUP(2,1/(组合净值!$E$6:$E$60<>""),组合净值!$E$6:$E$60))/(IFERROR(LOOKUP(DATE(2026,1,1),组合净值!$A$6:$A$60,组合净值!$E$6:$E$60),组合净值!$E$6))-1,"") | D12: =IFERROR((LOOKUP(2,1/(组合净值!$E$6:$E$60<>""),组合净值!$E$6:$E$60)/(IFERROR(LOOKUP(DATE(2026,1,1),组合净值!$A$6:$A$60,组合净值!$E$6:$E$60),组合净值!$E$6)))^(说明!$C$17/MAX(COUNTIF(组合净值!$A$6:$A$60,">="&(DATE(2026,1,1))),1))-1,"") | E12: 回撤修复天数(未创新高) | G12: =IFERROR((LOOKUP(2,1/(组合净值!$E$6:$E$60<>""),ROW(组合净值!$E$6:$E$60)))-(LOOKUP(2,1/(组合净值!$G$6:$G$60=0),ROW(组合净值!$G$6:$G$60))),"")
B13: 近3个月 | C13: =IFERROR((LOOKUP(2,1/(组合净值!$E$6:$E$60<>""),组合净值!$E$6:$E$60))/(IFERROR(LOOKUP(EDATE(LOOKUP(2,1/(组合净值!$E$6:$E$60<>""),组合净值!$A$6:$A$60),-3),组合净值!$A$6:$A$60,组合净值!$E$6:$E$60),组合净值!$E$6))-1,"") | D13: =IFERROR((LOOKUP(2,1/(组合净值!$E$6:$E$60<>""),组合净值!$E$6:$E$60)/(IFERROR(LOOKUP(EDATE(LOOKUP(2,1/(组合净值!$E$6:$E$60<>""),组合净值!$A$6:$A$60),-3),组合净值!$A$6:$A$60,组合净值!$E$6:$E$60),组合净值!$E$6)))^(说明!$C$17/MAX(COUNTIF(组合净值!$A$6:$A$60,">="&(EDATE(LOOKUP(2,1/(组合净值!$E$6:$E$60<>""),组合净值!$A$6:$A$60),-3))),1))-1,"") | E13: 正收益占比 | G13: =COUNTIF(组合净值!$F$6:$F$60,">0")/MAX(COUNT(组合净值!$F$6:$F$60),1)
B14: 近6个月 | C14: =IFERROR((LOOKUP(2,1/(组合净值!$E$6:$E$60<>""),组合净值!$E$6:$E$60))/(IFERROR(LOOKUP(EDATE(LOOKUP(2,1/(组合净值!$E$6:$E$60<>""),组合净值!$A$6:$A$60),-6),组合净值!$A$6:$A$60,组合净值!$E$6:$E$60),组合净值!$E$6))-1,"") | D14: =IFERROR((LOOKUP(2,1/(组合净值!$E$6:$E$60<>""),组合净值!$E$6:$E$60)/(IFERROR(LOOKUP(EDATE(LOOKUP(2,1/(组合净值!$E$6:$E$60<>""),组合净值!$A$6:$A$60),-6),组合净值!$A$6:$A$60,组合净值!$E$6:$E$60),组合净值!$E$6)))^(说明!$C$17/MAX(COUNTIF(组合净值!$A$6:$A$60,">="&(EDATE(LOOKUP(2,1/(组合净值!$E$6:$E$60<>""),组合净值!$A$6:$A$60),-6))),1))-1,"") | E14: 年化波动率 | G14: =STDEV(组合净值!$F$6:$F$60)*SQRT(说明!$C$17)
B15: 近1年 | C15: =IFERROR((LOOKUP(2,1/(组合净值!$E$6:$E$60<>""),组合净值!$E$6:$E$60))/(IFERROR(LOOKUP(EDATE(LOOKUP(2,1/(组合净值!$E$6:$E$60<>""),组合净值!$A$6:$A$60),-12),组合净值!$A$6:$A$60,组合净值!$E$6:$E$60),组合净值!$E$6))-1,"") | D15: =IFERROR((LOOKUP(2,1/(组合净值!$E$6:$E$60<>""),组合净值!$E$6:$E$60)/(IFERROR(LOOKUP(EDATE(LOOKUP(2,1/(组合净值!$E$6:$E$60<>""),组合净值!$A$6:$A$60),-12),组合净值!$A$6:$A$60,组合净值!$E$6:$E$60),组合净值!$E$6)))^(说明!$C$17/MAX(COUNTIF(组合净值!$A$6:$A$60,">="&(EDATE(LOOKUP(2,1/(组合净值!$E$6:$E$60<>""),组合净值!$A$6:$A$60),-12))),1))-1,"") | E15: 夏普比率 | G15: =(((LOOKUP(2,1/(组合净值!$E$6:$E$60<>""),组合净值!$E$6:$E$60)/组合净值!$E$6)^(说明!$C$17/MAX(COUNT(组合净值!$F$6:$F$60),1))-1)-说明!$C$16)/IF((STDEV(组合净值!$F$6:$F$60)*SQRT(说明!$C$17))=0,"",(STDEV(组合净值!$F$6:$F$60)*SQRT(说明!$C$17)))
E16: 卡玛比率 | G16: =IFERROR(((LOOKUP(2,1/(组合净值!$E$6:$E$60<>""),组合净值!$E$6:$E$60)/组合净值!$E$6)^(说明!$C$17/MAX(COUNT(组合净值!$F$6:$F$60),1))-1)/ABS(MIN(组合净值!$G$6:$G$60)),"")
B18: 产品运作情况 · 组合净值曲线
B35: 统计区间自2026/6/1起；运作初期样本少，年化类指标仅供参考。新增交易日后请同步扩展本图数据区。

Sheet 看板-30-70
B2: 样板间组合走势看板（30-70 账户）
B3: ="买入持有 · 已扣年化费率 "&TEXT(持仓配置!$M$6,"0.0%")&"（折每日计入净值）" | E3: ="净值日期："&TEXT(LOOKUP(2,1/(组合净值!$H$6:$H$60<>""),组合净值!$A$6:$A$60),"yyyy-mm-dd")
B5: 产品业绩表现（历史表现不代表未来收益承诺）
B6: 最新净值 | C6: 累计收益 | D6: 年化收益 | E6: 年化波动率 | F6: 最大回撤 | G6: 夏普比率
B7: =LOOKUP(2,1/(组合净值!$H$6:$H$60<>""),组合净值!$H$6:$H$60) | C7: =(LOOKUP(2,1/(组合净值!$H$6:$H$60<>""),组合净值!$H$6:$H$60))/组合净值!$H$6-1 | D7: =(LOOKUP(2,1/(组合净值!$H$6:$H$60<>""),组合净值!$H$6:$H$60)/组合净值!$H$6)^(说明!$C$17/MAX(COUNT(组合净值!$I$6:$I$60),1))-1 | E7: =STDEV(组合净值!$I$6:$I$60)*SQRT(说明!$C$17) | F7: =MIN(组合净值!$J$6:$J$60) | G7: =(((LOOKUP(2,1/(组合净值!$H$6:$H$60<>""),组合净值!$H$6:$H$60)/组合净值!$H$6)^(说明!$C$17/MAX(COUNT(组合净值!$I$6:$I$60),1))-1)-说明!$C$16)/IF((STDEV(组合净值!$I$6:$I$60)*SQRT(说明!$C$17))=0,"",(STDEV(组合净值!$I$6:$I$60)*SQRT(说明!$C$17)))
B9: 收益表现 | E9: 风险特征
B10: 区间 | C10: 累计收益 | D10: 年化收益 | E10: 指标 | G10: 数值
B11: 起始以来 | C11: =IFERROR((LOOKUP(2,1/(组合净值!$H$6:$H$60<>""),组合净值!$H$6:$H$60))/(组合净值!$H$6)-1,"") | D11: =IFERROR((LOOKUP(2,1/(组合净值!$H$6:$H$60<>""),组合净值!$H$6:$H$60)/(组合净值!$H$6))^(说明!$C$17/COUNT(组合净值!$I$6:$I$60))-1,"") | E11: 最大回撤 | G11: =MIN(组合净值!$J$6:$J$60)
B12: 2026YTD | C12: =IFERROR((LOOKUP(2,1/(组合净值!$H$6:$H$60<>""),组合净值!$H$6:$H$60))/(IFERROR(LOOKUP(DATE(2026,1,1),组合净值!$A$6:$A$60,组合净值!$H$6:$H$60),组合净值!$H$6))-1,"") | D12: =IFERROR((LOOKUP(2,1/(组合净值!$H$6:$H$60<>""),组合净值!$H$6:$H$60)/(IFERROR(LOOKUP(DATE(2026,1,1),组合净值!$A$6:$A$60,组合净值!$H$6:$H$60),组合净值!$H$6)))^(说明!$C$17/MAX(COUNTIF(组合净值!$A$6:$A$60,">="&(DATE(2026,1,1))),1))-1,"") | E12: 回撤修复天数(未创新高) | G12: =IFERROR((LOOKUP(2,1/(组合净值!$H$6:$H$60<>""),ROW(组合净值!$H$6:$H$60)))-(LOOKUP(2,1/(组合净值!$J$6:$J$60=0),ROW(组合净值!$J$6:$J$60))),"")
B13: 近3个月 | C13: =IFERROR((LOOKUP(2,1/(组合净值!$H$6:$H$60<>""),组合净值!$H$6:$H$60))/(IFERROR(LOOKUP(EDATE(LOOKUP(2,1/(组合净值!$H$6:$H$60<>""),组合净值!$A$6:$A$60),-3),组合净值!$A$6:$A$60,组合净值!$H$6:$H$60),组合净值!$H$6))-1,"") | D13: =IFERROR((LOOKUP(2,1/(组合净值!$H$6:$H$60<>""),组合净值!$H$6:$H$60)/(IFERROR(LOOKUP(EDATE(LOOKUP(2,1/(组合净值!$H$6:$H$60<>""),组合净值!$A$6:$A$60),-3),组合净值!$A$6:$A$60,组合净值!$H$6:$H$60),组合净值!$H$6)))^(说明!$C$17/MAX(COUNTIF(组合净值!$A$6:$A$60,">="&(EDATE(LOOKUP(2,1/(组合净值!$H$6:$H$60<>""),组合净值!$A$6:$A$60),-3))),1))-1,"") | E13: 正收益占比 | G13: =COUNTIF(组合净值!$I$6:$I$60,">0")/MAX(COUNT(组合净值!$I$6:$I$60),1)
B14: 近6个月 | C14: =IFERROR((LOOKUP(2,1/(组合净值!$H$6:$H$60<>""),组合净值!$H$6:$H$60))/(IFERROR(LOOKUP(EDATE(LOOKUP(2,1/(组合净值!$H$6:$H$60<>""),组合净值!$A$6:$A$60),-6),组合净值!$A$6:$A$60,组合净值!$H$6:$H$60),组合净值!$H$6))-1,"") | D14: =IFERROR((LOOKUP(2,1/(组合净值!$H$6:$H$60<>""),组合净值!$H$6:$H$60)/(IFERROR(LOOKUP(EDATE(LOOKUP(2,1/(组合净值!$H$6:$H$60<>""),组合净值!$A$6:$A$60),-6),组合净值!$A$6:$A$60,组合净值!$H$6:$H$60),组合净值!$H$6)))^(说明!$C$17/MAX(COUNTIF(组合净值!$A$6:$A$60,">="&(EDATE(LOOKUP(2,1/(组合净值!$H$6:$H$60<>""),组合净值!$A$6:$A$60),-6))),1))-1,"") | E14: 年化波动率 | G14: =STDEV(组合净值!$I$6:$I$60)*SQRT(说明!$C$17)
B15: 近1年 | C15: =IFERROR((LOOKUP(2,1/(组合净值!$H$6:$H$60<>""),组合净值!$H$6:$H$60))/(IFERROR(LOOKUP(EDATE(LOOKUP(2,1/(组合净值!$H$6:$H$60<>""),组合净值!$A$6:$A$60),-12),组合净值!$A$6:$A$60,组合净值!$H$6:$H$60),组合净值!$H$6))-1,"") | D15: =IFERROR((LOOKUP(2,1/(组合净值!$H$6:$H$60<>""),组合净值!$H$6:$H$60)/(IFERROR(LOOKUP(EDATE(LOOKUP(2,1/(组合净值!$H$6:$H$60<>""),组合净值!$A$6:$A$60),-12),组合净值!$A$6:$A$60,组合净值!$H$6:$H$60),组合净值!$H$6)))^(说明!$C$17/MAX(COUNTIF(组合净值!$A$6:$A$60,">="&(EDATE(LOOKUP(2,1/(组合净值!$H$6:$H$60<>""),组合净值!$A$6:$A$60),-12))),1))-1,"") | E15: 夏普比率 | G15: =(((LOOKUP(2,1/(组合净值!$H$6:$H$60<>""),组合净值!$H$6:$H$60)/组合净值!$H$6)^(说明!$C$17/MAX(COUNT(组合净值!$I$6:$I$60),1))-1)-说明!$C$16)/IF((STDEV(组合净值!$I$6:$I$60)*SQRT(说明!$C$17))=0,"",(STDEV(组合净值!$I$6:$I$60)*SQRT(说明!$C$17)))
E16: 卡玛比率 | G16: =IFERROR(((LOOKUP(2,1/(组合净值!$H$6:$H$60<>""),组合净值!$H$6:$H$60)/组合净值!$H$6)^(说明!$C$17/MAX(COUNT(组合净值!$I$6:$I$60),1))-1)/ABS(MIN(组合净值!$J$6:$J$60)),"")
B18: 产品运作情况 · 组合净值曲线
B35: 统计区间自2026/6/1起；运作初期样本少，年化类指标仅供参考。新增交易日后请同步扩展本图数据区。

Sheet 看板-增值
B2: 样板间组合走势看板（增值组合）
B3: ="买入持有 · 已扣年化费率 "&TEXT(持仓配置!$M$7,"0.0%")&"（折每日计入净值）" | E3: ="净值日期："&TEXT(LOOKUP(2,1/(组合净值!$K$6:$K$60<>""),组合净值!$A$6:$A$60),"yyyy-mm-dd")
B5: 产品业绩表现（历史表现不代表未来收益承诺）
B6: 最新净值 | C6: 累计收益 | D6: 年化收益 | E6: 年化波动率 | F6: 最大回撤 | G6: 夏普比率
B7: =LOOKUP(2,1/(组合净值!$K$6:$K$60<>""),组合净值!$K$6:$K$60) | C7: =(LOOKUP(2,1/(组合净值!$K$6:$K$60<>""),组合净值!$K$6:$K$60))/组合净值!$K$6-1 | D7: =(LOOKUP(2,1/(组合净值!$K$6:$K$60<>""),组合净值!$K$6:$K$60)/组合净值!$K$6)^(说明!$C$17/MAX(COUNT(组合净值!$L$6:$L$60),1))-1 | E7: =STDEV(组合净值!$L$6:$L$60)*SQRT(说明!$C$17) | F7: =MIN(组合净值!$M$6:$M$60) | G7: =(((LOOKUP(2,1/(组合净值!$K$6:$K$60<>""),组合净值!$K$6:$K$60)/组合净值!$K$6)^(说明!$C$17/MAX(COUNT(组合净值!$L$6:$L$60),1))-1)-说明!$C$16)/IF((STDEV(组合净值!$L$6:$L$60)*SQRT(说明!$C$17))=0,"",(STDEV(组合净值!$L$6:$L$60)*SQRT(说明!$C$17)))
B9: 收益表现 | E9: 风险特征
B10: 区间 | C10: 累计收益 | D10: 年化收益 | E10: 指标 | G10: 数值
B11: 起始以来 | C11: =IFERROR((LOOKUP(2,1/(组合净值!$K$6:$K$60<>""),组合净值!$K$6:$K$60))/(组合净值!$K$6)-1,"") | D11: =IFERROR((LOOKUP(2,1/(组合净值!$K$6:$K$60<>""),组合净值!$K$6:$K$60)/(组合净值!$K$6))^(说明!$C$17/COUNT(组合净值!$L$6:$L$60))-1,"") | E11: 最大回撤 | G11: =MIN(组合净值!$M$6:$M$60)
B12: 2026YTD | C12: =IFERROR((LOOKUP(2,1/(组合净值!$K$6:$K$60<>""),组合净值!$K$6:$K$60))/(IFERROR(LOOKUP(DATE(2026,1,1),组合净值!$A$6:$A$60,组合净值!$K$6:$K$60),组合净值!$K$6))-1,"") | D12: =IFERROR((LOOKUP(2,1/(组合净值!$K$6:$K$60<>""),组合净值!$K$6:$K$60)/(IFERROR(LOOKUP(DATE(2026,1,1),组合净值!$A$6:$A$60,组合净值!$K$6:$K$60),组合净值!$K$6)))^(说明!$C$17/MAX(COUNTIF(组合净值!$A$6:$A$60,">="&(DATE(2026,1,1))),1))-1,"") | E12: 回撤修复天数(未创新高) | G12: =IFERROR((LOOKUP(2,1/(组合净值!$K$6:$K$60<>""),ROW(组合净值!$K$6:$K$60)))-(LOOKUP(2,1/(组合净值!$M$6:$M$60=0),ROW(组合净值!$M$6:$M$60))),"")
B13: 近3个月 | C13: =IFERROR((LOOKUP(2,1/(组合净值!$K$6:$K$60<>""),组合净值!$K$6:$K$60))/(IFERROR(LOOKUP(EDATE(LOOKUP(2,1/(组合净值!$K$6:$K$60<>""),组合净值!$A$6:$A$60),-3),组合净值!$A$6:$A$60,组合净值!$K$6:$K$60),组合净值!$K$6))-1,"") | D13: =IFERROR((LOOKUP(2,1/(组合净值!$K$6:$K$60<>""),组合净值!$K$6:$K$60)/(IFERROR(LOOKUP(EDATE(LOOKUP(2,1/(组合净值!$K$6:$K$60<>""),组合净值!$A$6:$A$60),-3),组合净值!$A$6:$A$60,组合净值!$K$6:$K$60),组合净值!$K$6)))^(说明!$C$17/MAX(COUNTIF(组合净值!$A$6:$A$60,">="&(EDATE(LOOKUP(2,1/(组合净值!$K$6:$K$60<>""),组合净值!$A$6:$A$60),-3))),1))-1,"") | E13: 正收益占比 | G13: =COUNTIF(组合净值!$L$6:$L$60,">0")/MAX(COUNT(组合净值!$L$6:$L$60),1)
B14: 近6个月 | C14: =IFERROR((LOOKUP(2,1/(组合净值!$K$6:$K$60<>""),组合净值!$K$6:$K$60))/(IFERROR(LOOKUP(EDATE(LOOKUP(2,1/(组合净值!$K$6:$K$60<>""),组合净值!$A$6:$A$60),-6),组合净值!$A$6:$A$60,组合净值!$K$6:$K$60),组合净值!$K$6))-1,"") | D14: =IFERROR((LOOKUP(2,1/(组合净值!$K$6:$K$60<>""),组合净值!$K$6:$K$60)/(IFERROR(LOOKUP(EDATE(LOOKUP(2,1/(组合净值!$K$6:$K$60<>""),组合净值!$A$6:$A$60),-6),组合净值!$A$6:$A$60,组合净值!$K$6:$K$60),组合净值!$K$6)))^(说明!$C$17/MAX(COUNTIF(组合净值!$A$6:$A$60,">="&(EDATE(LOOKUP(2,1/(组合净值!$K$6:$K$60<>""),组合净值!$A$6:$A$60),-6))),1))-1,"") | E14: 年化波动率 | G14: =STDEV(组合净值!$L$6:$L$60)*SQRT(说明!$C$17)
B15: 近1年 | C15: =IFERROR((LOOKUP(2,1/(组合净值!$K$6:$K$60<>""),组合净值!$K$6:$K$60))/(IFERROR(LOOKUP(EDATE(LOOKUP(2,1/(组合净值!$K$6:$K$60<>""),组合净值!$A$6:$A$60),-12),组合净值!$A$6:$A$60,组合净值!$K$6:$K$60),组合净值!$K$6))-1,"") | D15: =IFERROR((LOOKUP(2,1/(组合净值!$K$6:$K$60<>""),组合净值!$K$6:$K$60)/(IFERROR(LOOKUP(EDATE(LOOKUP(2,1/(组合净值!$K$6:$K$60<>""),组合净值!$A$6:$A$60),-12),组合净值!$A$6:$A$60,组合净值!$K$6:$K$60),组合净值!$K$6)))^(说明!$C$17/MAX(COUNTIF(组合净值!$A$6:$A$60,">="&(EDATE(LOOKUP(2,1/(组合净值!$K$6:$K$60<>""),组合净值!$A$6:$A$60),-12))),1))-1,"") | E15: 夏普比率 | G15: =(((LOOKUP(2,1/(组合净值!$K$6:$K$60<>""),组合净值!$K$6:$K$60)/组合净值!$K$6)^(说明!$C$17/MAX(COUNT(组合净值!$L$6:$L$60),1))-1)-说明!$C$16)/IF((STDEV(组合净值!$L$6:$L$60)*SQRT(说明!$C$17))=0,"",(STDEV(组合净值!$L$6:$L$60)*SQRT(说明!$C$17)))
E16: 卡玛比率 | G16: =IFERROR(((LOOKUP(2,1/(组合净值!$K$6:$K$60<>""),组合净值!$K$6:$K$60)/组合净值!$K$6)^(说明!$C$17/MAX(COUNT(组合净值!$L$6:$L$60),1))-1)/ABS(MIN(组合净值!$M$6:$M$60)),"")
B18: 产品运作情况 · 组合净值曲线
B35: 统计区间自2026/6/1起；运作初期样本少，年化类指标仅供参考。新增交易日后请同步扩展本图数据区。

Sheet 说明
B2: 样板间投顾组合 · 净值监控模板
B3: 运作起始日 2026/6/1 ｜ 净值口径：复权单位净值(iFinD) ｜ 模拟：买入持有(权重漂移)
B5: 一、模板结构
B6: 持仓配置 | C6: 四组合(10-90/20-80/30-70/增值)成份基金、代码与初始权重，可直接编辑。
B7: 净值数据(iFinD公式) | C7: 同花顺公式拉取复权单位净值
B8: 组合净值 | C8: 按买入持有逐日计算四组合净值、日收益与回撤；净值已按年化费率折每日扣费(扣费后口径)。
B9: 看板-10/20/30/增值 | C9: 业绩表现KPI＋收益表现＋风险特征＋净值曲线。增值组合为8只权益基金、无债无黄金。
B11: 二、使用说明
B12: 每日更新 | C12: 在『净值数据』『组合净值』底部按日期顺序新增一行(公式可下拉)，看板自动刷新。
B13: iFinD指标 | C13: 复权净值指标代码集中在『净值数据』B2，与本地版本不符时只改此处。
B14: 买入持有口径 | C14: 起始日按初始权重买入后持有，权重随涨跌漂移；组合起始净值=1.0000。
B15: 扣费方式 | C15: 各组合年化费率见『持仓配置』M列(10-90=0.8%/20-80=1.0%/30-70=1.2%/增值=1.0%)；按 净值×(1-费率)^(已运作交易日数/年化交易日数) 折每日计入，看板均为扣费后口径。
B16: 参数：无风险利率(年化) | C16: 0
B17: 参数：年化交易日数 | C17: 242
B18: 净值曲线 | C18: 四看板曲线已改用动态命名区域(chtDate/chtB/chtE/chtH/chtK，OFFSET+COUNT)，新增交易日后自动延伸到最新，无需手动改图表数据区。
B19: 数据来源：同花顺 iFinD(复权单位净值)

Sheet vs招行
F1: 46171 | G1: 46191 | N1: 10-90 | P1: 30-70
F2: 46174 | G2: 46195 | H2: 46174 | N2: =VLOOKUP(F1,组合净值!A:M,2,0) | O2: =VLOOKUP(G1,实盘组合净值!A:S,14,0) | P2: =VLOOKUP(F1,组合净值!A:M,8,0)
F3: 46203 | G3: =F3 | H3: 46199 | N3: =VLOOKUP(F3,组合净值!A:M,2,0) | O3: =VLOOKUP(G3,实盘组合净值!A:S,14,0) | P3: =VLOOKUP(F3,组合净值!A:M,8,0)
C4: 权益中枢 | D4: 列2 | E4: 组合/基金 | F4: 6月以来（截止630） | G4: 6.18上线以来 | H4: 最大回撤 | I4: 年化波动率 | J4: 夏普比率 | K4: 卡玛比率
B5: 嘉实财富样板间 | C5: 0.1 | E5: 10-90账户 | F5: =N3/N2-1 | G5: =O3/O2-1 | H5: ='看板-10-90'!F7 | I5: ='看板-10-90'!E7 | J5: ='看板-10-90'!G7 | K5: =IFERROR('看板-10-90'!D7/ABS('看板-10-90'!F7),"")
B6: 招行长盈计划-安稳盈 | C6: ≤15% | D6: 016768.OF | E6: =[1]!thsiFinD("ths_fund_official_short_name_fund",D6) | F6: =[1]!thsiFinD("ths_adjustment_nvg_ratio_fund",$D6,F$2,F$3,101)/100 | G6: =[1]!thsiFinD("ths_adjustment_nvg_ratio_fund",$D6,G$2,G$3,101)/100 | H6: =-[1]!thsiFinD("ths_max_retrace_rate_all_fund",$D6,$H$2,$H$3)/100 | I6: =IFERROR(HLOOKUP($D6,'对标基金净值(iFinD公式)'!$2:$5,3,0),"") | J6: =IFERROR((HLOOKUP($D6,'对标基金净值(iFinD公式)'!$2:$5,4,0)-说明!$C$16)/HLOOKUP($D6,'对标基金净值(iFinD公式)'!$2:$5,3,0),"") | K6: =IFERROR(HLOOKUP($D6,'对标基金净值(iFinD公式)'!$2:$5,4,0)/ABS(H6),"")
D7: 025218.OF | E7: =[1]!thsiFinD("ths_fund_official_short_name_fund",D7) | F7: =[1]!thsiFinD("ths_adjustment_nvg_ratio_fund",$D7,F$2,F$3,101)/100 | G7: =[1]!thsiFinD("ths_adjustment_nvg_ratio_fund",$D7,G$2,G$3,101)/100 | H7: =-[1]!thsiFinD("ths_max_retrace_rate_all_fund",$D7,$H$2,$H$3)/100 | I7: =IFERROR(HLOOKUP($D7,'对标基金净值(iFinD公式)'!$2:$5,3,0),"") | J7: =IFERROR((HLOOKUP($D7,'对标基金净值(iFinD公式)'!$2:$5,4,0)-说明!$C$16)/HLOOKUP($D7,'对标基金净值(iFinD公式)'!$2:$5,3,0),"") | K7: =IFERROR(HLOOKUP($D7,'对标基金净值(iFinD公式)'!$2:$5,4,0)/ABS(H7),"")
D8: 022978.OF | E8: =[1]!thsiFinD("ths_fund_official_short_name_fund",D8) | F8: =[1]!thsiFinD("ths_adjustment_nvg_ratio_fund",$D8,F$2,F$3,101)/100 | G8: =[1]!thsiFinD("ths_adjustment_nvg_ratio_fund",$D8,G$2,G$3,101)/100 | H8: =-[1]!thsiFinD("ths_max_retrace_rate_all_fund",$D8,$H$2,$H$3)/100 | I8: =IFERROR(HLOOKUP($D8,'对标基金净值(iFinD公式)'!$2:$5,3,0),"") | J8: =IFERROR((HLOOKUP($D8,'对标基金净值(iFinD公式)'!$2:$5,4,0)-说明!$C$16)/HLOOKUP($D8,'对标基金净值(iFinD公式)'!$2:$5,3,0),"") | K8: =IFERROR(HLOOKUP($D8,'对标基金净值(iFinD公式)'!$2:$5,4,0)/ABS(H8),"")
D9: 017587.OF | E9: =[1]!thsiFinD("ths_fund_official_short_name_fund",D9) | F9: =[1]!thsiFinD("ths_adjustment_nvg_ratio_fund",$D9,F$2,F$3,101)/100 | G9: =[1]!thsiFinD("ths_adjustment_nvg_ratio_fund",$D9,G$2,G$3,101)/100 | H9: =-[1]!thsiFinD("ths_max_retrace_rate_all_fund",$D9,$H$2,$H$3)/100 | I9: =IFERROR(HLOOKUP($D9,'对标基金净值(iFinD公式)'!$2:$5,3,0),"") | J9: =IFERROR((HLOOKUP($D9,'对标基金净值(iFinD公式)'!$2:$5,4,0)-说明!$C$16)/HLOOKUP($D9,'对标基金净值(iFinD公式)'!$2:$5,3,0),"") | K9: =IFERROR(HLOOKUP($D9,'对标基金净值(iFinD公式)'!$2:$5,4,0)/ABS(H9),"")
D10: 026682.OF | E10: =[1]!thsiFinD("ths_fund_official_short_name_fund",D10) | F10: =[1]!thsiFinD("ths_adjustment_nvg_ratio_fund",$D10,F$2,F$3,101)/100 | G10: =[1]!thsiFinD("ths_adjustment_nvg_ratio_fund",$D10,G$2,G$3,101)/100 | H10: =-[1]!thsiFinD("ths_max_retrace_rate_all_fund",$D10,$H$2,$H$3)/100 | I10: =IFERROR(HLOOKUP($D10,'对标基金净值(iFinD公式)'!$2:$5,3,0),"") | J10: =IFERROR((HLOOKUP($D10,'对标基金净值(iFinD公式)'!$2:$5,4,0)-说明!$C$16)/HLOOKUP($D10,'对标基金净值(iFinD公式)'!$2:$5,3,0),"") | K10: =IFERROR(HLOOKUP($D10,'对标基金净值(iFinD公式)'!$2:$5,4,0)/ABS(H10),"")
B11: 招行长盈计划-安定盈 | C11: ≤25% | D11: 025822.OF | E11: =[1]!thsiFinD("ths_fund_official_short_name_fund",D11) | F11: =[1]!thsiFinD("ths_adjustment_nvg_ratio_fund",$D11,F$2,F$3,101)/100 | G11: =[1]!thsiFinD("ths_adjustment_nvg_ratio_fund",$D11,G$2,G$3,101)/100 | H11: =-[1]!thsiFinD("ths_max_retrace_rate_all_fund",$D11,$H$2,$H$3)/100 | I11: =IFERROR(HLOOKUP($D11,'对标基金净值(iFinD公式)'!$2:$5,3,0),"") | J11: =IFERROR((HLOOKUP($D11,'对标基金净值(iFinD公式)'!$2:$5,4,0)-说明!$C$16)/HLOOKUP($D11,'对标基金净值(iFinD公式)'!$2:$5,3,0),"") | K11: =IFERROR(HLOOKUP($D11,'对标基金净值(iFinD公式)'!$2:$5,4,0)/ABS(H11),"")
D12: 018312.OF | E12: =[1]!thsiFinD("ths_fund_official_short_name_fund",D12) | F12: =[1]!thsiFinD("ths_adjustment_nvg_ratio_fund",$D12,F$2,F$3,101)/100 | G12: =[1]!thsiFinD("ths_adjustment_nvg_ratio_fund",$D12,G$2,G$3,101)/100 | H12: =-[1]!thsiFinD("ths_max_retrace_rate_all_fund",$D12,$H$2,$H$3)/100 | I12: =IFERROR(HLOOKUP($D12,'对标基金净值(iFinD公式)'!$2:$5,3,0),"") | J12: =IFERROR((HLOOKUP($D12,'对标基金净值(iFinD公式)'!$2:$5,4,0)-说明!$C$16)/HLOOKUP($D12,'对标基金净值(iFinD公式)'!$2:$5,3,0),"") | K12: =IFERROR(HLOOKUP($D12,'对标基金净值(iFinD公式)'!$2:$5,4,0)/ABS(H12),"")
D16: 列2 | E16: 组合/基金 | F16: 6月以来（截止626） | H16: 最大回撤 | I16: 年化波动率 | J16: 夏普比率 | K16: 卡玛比率
B17: 嘉实财富样板间 | E17: 30-70账户 | F17: =P3/P2-1 | H17: ='看板-30-70'!F7 | I17: ='看板-30-70'!E7 | J17: ='看板-30-70'!G7 | K17: =IFERROR('看板-30-70'!D7/ABS('看板-30-70'!F7),"")
B18: 招行长盈计划-安鑫盈 | D18: 024757.OF | E18: =[1]!thsiFinD("ths_fund_official_short_name_fund",D18) | F18: =[1]!thsiFinD("ths_adjustment_nvg_ratio_fund",$D18,$F$2,$F$3,101)/100 | H18: =-[1]!thsiFinD("ths_max_retrace_rate_all_fund",$D18,$H$2,$H$3)/100 | I18: =IFERROR(HLOOKUP($D18,'对标基金净值(iFinD公式)'!$2:$5,3,0),"") | J18: =IFERROR((HLOOKUP($D18,'对标基金净值(iFinD公式)'!$2:$5,4,0)-说明!$C$16)/HLOOKUP($D18,'对标基金净值(iFinD公式)'!$2:$5,3,0),"") | K18: =IFERROR(HLOOKUP($D18,'对标基金净值(iFinD公式)'!$2:$5,4,0)/ABS(H18),"")
D19: 022202.OF | E19: =[1]!thsiFinD("ths_fund_official_short_name_fund",D19) | F19: =[1]!thsiFinD("ths_adjustment_nvg_ratio_fund",$D19,$F$2,$F$3,101)/100 | H19: =-[1]!thsiFinD("ths_max_retrace_rate_all_fund",$D19,$H$2,$H$3)/100 | I19: =IFERROR(HLOOKUP($D19,'对标基金净值(iFinD公式)'!$2:$5,3,0),"") | J19: =IFERROR((HLOOKUP($D19,'对标基金净值(iFinD公式)'!$2:$5,4,0)-说明!$C$16)/HLOOKUP($D19,'对标基金净值(iFinD公式)'!$2:$5,3,0),"") | K19: =IFERROR(HLOOKUP($D19,'对标基金净值(iFinD公式)'!$2:$5,4,0)/ABS(H19),"")
B21: 注：年化波动率/夏普/卡玛——基金按D列代码自动匹配「对标基金净值(iFinD公式)」页（复权净值日收益，年化242个交易日、无风险利率见「说明」C16），账户取自对应看板；卡玛=区间年化收益÷|最大回撤(H列)|。替换基金改D列代码+对标页第2行代码；新增基金见对标页底部说明。

Sheet vs固收+
F1: ='vs招行'!F1 | G1: ='vs招行'!G1
B2: 区间参数联动「vs招行」页黄色单元格 | F2: ='vs招行'!F2 | G2: ='vs招行'!G2 | H2: ='vs招行'!H2 | K2: 最新季报报告期→ | L2: 2026-03-31
F3: ='vs招行'!F3 | G3: ='vs招行'!G3 | H3: ='vs招行'!H3
C4: 权益中枢 | D4: 基金代码 | E4: 组合/基金 | F4: ="6月以来（截止"&TEXT($F$3,"m.d")&"）" | G4: 6.18上线以来 | H4: 最大回撤 | I4: 年化波动率 | J4: 夏普比率 | K4: 卡玛比率 | L4: 股票仓位 | M4: 转债仓位(穿透)
B5: 嘉实财富样板间 | C5: 0.1 | E5: 10-90账户 | F5: ='vs招行'!F5 | G5: ='vs招行'!G5 | H5: ='vs招行'!H5 | I5: ='vs招行'!I5 | J5: ='vs招行'!J5 | K5: ='vs招行'!K5
C6: 0.3 | E6: 30-70账户 | F6: ='vs招行'!F17 | H6: ='vs招行'!H17 | I6: ='vs招行'!I17 | J6: ='vs招行'!J17 | K6: ='vs招行'!K17
B7: 固收+产品池 | D7: 001316.OF | E7: =[1]!thsiFinD("ths_fund_official_short_name_fund",D7) | F7: =[1]!thsiFinD("ths_adjustment_nvg_ratio_fund",$D7,F$2,F$3,101)/100 | G7: =[1]!thsiFinD("ths_adjustment_nvg_ratio_fund",$D7,G$2,G$3,101)/100 | H7: =-[1]!thsiFinD("ths_max_retrace_rate_all_fund",$D7,$H$2,$H$3)/100 | I7: =IFERROR(HLOOKUP($D7,'对标基金净值(iFinD公式)'!$2:$5,3,0),"") | J7: =IFERROR((HLOOKUP($D7,'对标基金净值(iFinD公式)'!$2:$5,4,0)-说明!$C$16)/HLOOKUP($D7,'对标基金净值(iFinD公式)'!$2:$5,3,0),"") | K7: =IFERROR(HLOOKUP($D7,'对标基金净值(iFinD公式)'!$2:$5,4,0)/ABS(H7),"") | L7: =[1]!thsiFinD("ths_stock_mv_to_fanv_fund",$D7,$L$2)/100 | M7: =[1]!thsiFinD("ths_cbb_to_bond_invest_mv_fund",$D7,$L$2)/100*[1]!thsiFinD("ths_bond_mv_to_fanv_fund",$D7,$L$2)/100
D8: 004010.OF | E8: =[1]!thsiFinD("ths_fund_official_short_name_fund",D8) | F8: =[1]!thsiFinD("ths_adjustment_nvg_ratio_fund",$D8,F$2,F$3,101)/100 | G8: =[1]!thsiFinD("ths_adjustment_nvg_ratio_fund",$D8,G$2,G$3,101)/100 | H8: =-[1]!thsiFinD("ths_max_retrace_rate_all_fund",$D8,$H$2,$H$3)/100 | I8: =IFERROR(HLOOKUP($D8,'对标基金净值(iFinD公式)'!$2:$5,3,0),"") | J8: =IFERROR((HLOOKUP($D8,'对标基金净值(iFinD公式)'!$2:$5,4,0)-说明!$C$16)/HLOOKUP($D8,'对标基金净值(iFinD公式)'!$2:$5,3,0),"") | K8: =IFERROR(HLOOKUP($D8,'对标基金净值(iFinD公式)'!$2:$5,4,0)/ABS(H8),"") | L8: =[1]!thsiFinD("ths_stock_mv_to_fanv_fund",$D8,$L$2)/100 | M8: =[1]!thsiFinD("ths_cbb_to_bond_invest_mv_fund",$D8,$L$2)/100*[1]!thsiFinD("ths_bond_mv_to_fanv_fund",$D8,$L$2)/100
D9: 016809.OF | E9: =[1]!thsiFinD("ths_fund_official_short_name_fund",D9) | F9: =[1]!thsiFinD("ths_adjustment_nvg_ratio_fund",$D9,F$2,F$3,101)/100 | G9: =[1]!thsiFinD("ths_adjustment_nvg_ratio_fund",$D9,G$2,G$3,101)/100 | H9: =-[1]!thsiFinD("ths_max_retrace_rate_all_fund",$D9,$H$2,$H$3)/100 | I9: =IFERROR(HLOOKUP($D9,'对标基金净值(iFinD公式)'!$2:$5,3,0),"") | J9: =IFERROR((HLOOKUP($D9,'对标基金净值(iFinD公式)'!$2:$5,4,0)-说明!$C$16)/HLOOKUP($D9,'对标基金净值(iFinD公式)'!$2:$5,3,0),"") | K9: =IFERROR(HLOOKUP($D9,'对标基金净值(iFinD公式)'!$2:$5,4,0)/ABS(H9),"") | L9: =[1]!thsiFinD("ths_stock_mv_to_fanv_fund",$D9,$L$2)/100 | M9: =[1]!thsiFinD("ths_cbb_to_bond_invest_mv_fund",$D9,$L$2)/100*[1]!thsiFinD("ths_bond_mv_to_fanv_fund",$D9,$L$2)/100
D10: 002009.OF | E10: =[1]!thsiFinD("ths_fund_official_short_name_fund",D10) | F10: =[1]!thsiFinD("ths_adjustment_nvg_ratio_fund",$D10,F$2,F$3,101)/100 | G10: =[1]!thsiFinD("ths_adjustment_nvg_ratio_fund",$D10,G$2,G$3,101)/100 | H10: =-[1]!thsiFinD("ths_max_retrace_rate_all_fund",$D10,$H$2,$H$3)/100 | I10: =IFERROR(HLOOKUP($D10,'对标基金净值(iFinD公式)'!$2:$5,3,0),"") | J10: =IFERROR((HLOOKUP($D10,'对标基金净值(iFinD公式)'!$2:$5,4,0)-说明!$C$16)/HLOOKUP($D10,'对标基金净值(iFinD公式)'!$2:$5,3,0),"") | K10: =IFERROR(HLOOKUP($D10,'对标基金净值(iFinD公式)'!$2:$5,4,0)/ABS(H10),"") | L10: =[1]!thsiFinD("ths_stock_mv_to_fanv_fund",$D10,$L$2)/100 | M10: =[1]!thsiFinD("ths_cbb_to_bond_invest_mv_fund",$D10,$L$2)/100*[1]!thsiFinD("ths_bond_mv_to_fanv_fund",$D10,$L$2)/100
D11: 009089.OF | E11: =[1]!thsiFinD("ths_fund_official_short_name_fund",D11) | F11: =[1]!thsiFinD("ths_adjustment_nvg_ratio_fund",$D11,F$2,F$3,101)/100 | G11: =[1]!thsiFinD("ths_adjustment_nvg_ratio_fund",$D11,G$2,G$3,101)/100 | H11: =-[1]!thsiFinD("ths_max_retrace_rate_all_fund",$D11,$H$2,$H$3)/100 | I11: =IFERROR(HLOOKUP($D11,'对标基金净值(iFinD公式)'!$2:$5,3,0),"") | J11: =IFERROR((HLOOKUP($D11,'对标基金净值(iFinD公式)'!$2:$5,4,0)-说明!$C$16)/HLOOKUP($D11,'对标基金净值(iFinD公式)'!$2:$5,3,0),"") | K11: =IFERROR(HLOOKUP($D11,'对标基金净值(iFinD公式)'!$2:$5,4,0)/ABS(H11),"") | L11: =[1]!thsiFinD("ths_stock_mv_to_fanv_fund",$D11,$L$2)/100 | M11: =[1]!thsiFinD("ths_cbb_to_bond_invest_mv_fund",$D11,$L$2)/100*[1]!thsiFinD("ths_bond_mv_to_fanv_fund",$D11,$L$2)/100
D12: 675121.OF | E12: =[1]!thsiFinD("ths_fund_official_short_name_fund",D12) | F12: =[1]!thsiFinD("ths_adjustment_nvg_ratio_fund",$D12,F$2,F$3,101)/100 | G12: =[1]!thsiFinD("ths_adjustment_nvg_ratio_fund",$D12,G$2,G$3,101)/100 | H12: =-[1]!thsiFinD("ths_max_retrace_rate_all_fund",$D12,$H$2,$H$3)/100 | I12: =IFERROR(HLOOKUP($D12,'对标基金净值(iFinD公式)'!$2:$5,3,0),"") | J12: =IFERROR((HLOOKUP($D12,'对标基金净值(iFinD公式)'!$2:$5,4,0)-说明!$C$16)/HLOOKUP($D12,'对标基金净值(iFinD公式)'!$2:$5,3,0),"") | K12: =IFERROR(HLOOKUP($D12,'对标基金净值(iFinD公式)'!$2:$5,4,0)/ABS(H12),"") | L12: =[1]!thsiFinD("ths_stock_mv_to_fanv_fund",$D12,$L$2)/100 | M12: =[1]!thsiFinD("ths_cbb_to_bond_invest_mv_fund",$D12,$L$2)/100*[1]!thsiFinD("ths_bond_mv_to_fanv_fund",$D12,$L$2)/100
D13: 005717.OF | E13: =[1]!thsiFinD("ths_fund_official_short_name_fund",D13) | F13: =[1]!thsiFinD("ths_adjustment_nvg_ratio_fund",$D13,F$2,F$3,101)/100 | G13: =[1]!thsiFinD("ths_adjustment_nvg_ratio_fund",$D13,G$2,G$3,101)/100 | H13: =-[1]!thsiFinD("ths_max_retrace_rate_all_fund",$D13,$H$2,$H$3)/100 | I13: =IFERROR(HLOOKUP($D13,'对标基金净值(iFinD公式)'!$2:$5,3,0),"") | J13: =IFERROR((HLOOKUP($D13,'对标基金净值(iFinD公式)'!$2:$5,4,0)-说明!$C$16)/HLOOKUP($D13,'对标基金净值(iFinD公式)'!$2:$5,3,0),"") | K13: =IFERROR(HLOOKUP($D13,'对标基金净值(iFinD公式)'!$2:$5,4,0)/ABS(H13),"") | L13: =[1]!thsiFinD("ths_stock_mv_to_fanv_fund",$D13,$L$2)/100 | M13: =[1]!thsiFinD("ths_cbb_to_bond_invest_mv_fund",$D13,$L$2)/100*[1]!thsiFinD("ths_bond_mv_to_fanv_fund",$D13,$L$2)/100
D14: 018595.OF | E14: =[1]!thsiFinD("ths_fund_official_short_name_fund",D14) | F14: =[1]!thsiFinD("ths_adjustment_nvg_ratio_fund",$D14,F$2,F$3,101)/100 | G14: =[1]!thsiFinD("ths_adjustment_nvg_ratio_fund",$D14,G$2,G$3,101)/100 | H14: =-[1]!thsiFinD("ths_max_retrace_rate_all_fund",$D14,$H$2,$H$3)/100 | I14: =IFERROR(HLOOKUP($D14,'对标基金净值(iFinD公式)'!$2:$5,3,0),"") | J14: =IFERROR((HLOOKUP($D14,'对标基金净值(iFinD公式)'!$2:$5,4,0)-说明!$C$16)/HLOOKUP($D14,'对标基金净值(iFinD公式)'!$2:$5,3,0),"") | K14: =IFERROR(HLOOKUP($D14,'对标基金净值(iFinD公式)'!$2:$5,4,0)/ABS(H14),"") | L14: =[1]!thsiFinD("ths_stock_mv_to_fanv_fund",$D14,$L$2)/100 | M14: =[1]!thsiFinD("ths_cbb_to_bond_invest_mv_fund",$D14,$L$2)/100*[1]!thsiFinD("ths_bond_mv_to_fanv_fund",$D14,$L$2)/100
D15: 003504.OF | E15: =[1]!thsiFinD("ths_fund_official_short_name_fund",D15) | F15: =[1]!thsiFinD("ths_adjustment_nvg_ratio_fund",$D15,F$2,F$3,101)/100 | G15: =[1]!thsiFinD("ths_adjustment_nvg_ratio_fund",$D15,G$2,G$3,101)/100 | H15: =-[1]!thsiFinD("ths_max_retrace_rate_all_fund",$D15,$H$2,$H$3)/100 | I15: =IFERROR(HLOOKUP($D15,'对标基金净值(iFinD公式)'!$2:$5,3,0),"") | J15: =IFERROR((HLOOKUP($D15,'对标基金净值(iFinD公式)'!$2:$5,4,0)-说明!$C$16)/HLOOKUP($D15,'对标基金净值(iFinD公式)'!$2:$5,3,0),"") | K15: =IFERROR(HLOOKUP($D15,'对标基金净值(iFinD公式)'!$2:$5,4,0)/ABS(H15),"") | L15: =[1]!thsiFinD("ths_stock_mv_to_fanv_fund",$D15,$L$2)/100 | M15: =[1]!thsiFinD("ths_cbb_to_bond_invest_mv_fund",$D15,$L$2)/100*[1]!thsiFinD("ths_bond_mv_to_fanv_fund",$D15,$L$2)/100
D16: 016718.OF | E16: =[1]!thsiFinD("ths_fund_official_short_name_fund",D16) | F16: =[1]!thsiFinD("ths_adjustment_nvg_ratio_fund",$D16,F$2,F$3,101)/100 | G16: =[1]!thsiFinD("ths_adjustment_nvg_ratio_fund",$D16,G$2,G$3,101)/100 | H16: =-[1]!thsiFinD("ths_max_retrace_rate_all_fund",$D16,$H$2,$H$3)/100 | I16: =IFERROR(HLOOKUP($D16,'对标基金净值(iFinD公式)'!$2:$5,3,0),"") | J16: =IFERROR((HLOOKUP($D16,'对标基金净值(iFinD公式)'!$2:$5,4,0)-说明!$C$16)/HLOOKUP($D16,'对标基金净值(iFinD公式)'!$2:$5,3,0),"") | K16: =IFERROR(HLOOKUP($D16,'对标基金净值(iFinD公式)'!$2:$5,4,0)/ABS(H16),"") | L16: =[1]!thsiFinD("ths_stock_mv_to_fanv_fund",$D16,$L$2)/100 | M16: =[1]!thsiFinD("ths_cbb_to_bond_invest_mv_fund",$D16,$L$2)/100*[1]!thsiFinD("ths_bond_mv_to_fanv_fund",$D16,$L$2)/100
D17: 020857.OF | E17: =[1]!thsiFinD("ths_fund_official_short_name_fund",D17) | F17: =[1]!thsiFinD("ths_adjustment_nvg_ratio_fund",$D17,F$2,F$3,101)/100 | G17: =[1]!thsiFinD("ths_adjustment_nvg_ratio_fund",$D17,G$2,G$3,101)/100 | H17: =-[1]!thsiFinD("ths_max_retrace_rate_all_fund",$D17,$H$2,$H$3)/100 | I17: =IFERROR(HLOOKUP($D17,'对标基金净值(iFinD公式)'!$2:$5,3,0),"") | J17: =IFERROR((HLOOKUP($D17,'对标基金净值(iFinD公式)'!$2:$5,4,0)-说明!$C$16)/HLOOKUP($D17,'对标基金净值(iFinD公式)'!$2:$5,3,0),"") | K17: =IFERROR(HLOOKUP($D17,'对标基金净值(iFinD公式)'!$2:$5,4,0)/ABS(H17),"") | L17: =[1]!thsiFinD("ths_stock_mv_to_fanv_fund",$D17,$L$2)/100 | M17: =[1]!thsiFinD("ths_cbb_to_bond_invest_mv_fund",$D17,$L$2)/100*[1]!thsiFinD("ths_bond_mv_to_fanv_fund",$D17,$L$2)/100
B19: 注1：股票仓位＝股票市值占基金资产净值比（iFinD：ths_stock_mv_to_fanv_fund，取最新季报）；转债仓位＝可转债市值占债券市值比（ths_cbb_to_bond_invest_mv_fund）×债券市值占基金资产净值比（ths_bond_mv_to_fanv_fund），即穿透后可转债占基金净值的比例；报告期统一取L2黄色单元格（当前2026-03-31，二季报披露后请改为2026-06-30）。
B20: 注2：年化波动率/夏普/卡玛按D列代码自动匹配「对标基金净值(iFinD公式)」页，口径与账户看板一致（年化242个交易日、无风险利率见「说明」C16）；卡玛＝区间年化收益÷|最大回撤(H列)|；区间起止日期联动「vs招行」页。替换/新增基金的操作见对标页底部说明。

Sheet 对标基金净值(iFinD公式)
A1: 对标基金净值 · iFinD复权单位净值（每基金两列一组：净值+日收益；供 vs招行 / vs固收+ 按代码HLOOKUP匹配）
A2: 基金代码→ | B2: 016768.OF | D2: 025218.OF | F2: 022978.OF | H2: 017587.OF | J2: 026682.OF | L2: 025822.OF | N2: 018312.OF | P2: 024757.OF | R2: 022202.OF | T2: 001316.OF | V2: 004010.OF | X2: 016809.OF | Z2: 002009.OF | AB2: 009089.OF | AD2: 675121.OF | AF2: 005717.OF | AH2: 018595.OF | AJ2: 003504.OF | AL2: 016718.OF | AN2: 020857.OF
A3: 基金简称 | B3: =[1]!thsiFinD("ths_fund_official_short_name_fund",B2) | D3: =[1]!thsiFinD("ths_fund_official_short_name_fund",D2) | F3: =[1]!thsiFinD("ths_fund_official_short_name_fund",F2) | H3: =[1]!thsiFinD("ths_fund_official_short_name_fund",H2) | J3: =[1]!thsiFinD("ths_fund_official_short_name_fund",J2) | L3: =[1]!thsiFinD("ths_fund_official_short_name_fund",L2) | N3: =[1]!thsiFinD("ths_fund_official_short_name_fund",N2) | P3: =[1]!thsiFinD("ths_fund_official_short_name_fund",P2) | R3: =[1]!thsiFinD("ths_fund_official_short_name_fund",R2) | T3: =[1]!thsiFinD("ths_fund_official_short_name_fund",T2) | V3: =[1]!thsiFinD("ths_fund_official_short_name_fund",V2) | X3: =[1]!thsiFinD("ths_fund_official_short_name_fund",X2) | Z3: =[1]!thsiFinD("ths_fund_official_short_name_fund",Z2) | AB3: =[1]!thsiFinD("ths_fund_official_short_name_fund",AB2) | AD3: =[1]!thsiFinD("ths_fund_official_short_name_fund",AD2) | AF3: =[1]!thsiFinD("ths_fund_official_short_name_fund",AF2) | AH3: =[1]!thsiFinD("ths_fund_official_short_name_fund",AH2) | AJ3: =[1]!thsiFinD("ths_fund_official_short_name_fund",AJ2) | AL3: =[1]!thsiFinD("ths_fund_official_short_name_fund",AL2) | AN3: =[1]!thsiFinD("ths_fund_official_short_name_fund",AN2)
A4: 年化波动率 | B4: =IF(COUNT(C8:C61)<2,"",STDEV(C8:C61)*SQRT(说明!$C$17)) | D4: =IF(COUNT(E8:E61)<2,"",STDEV(E8:E61)*SQRT(说明!$C$17)) | F4: =IF(COUNT(G8:G61)<2,"",STDEV(G8:G61)*SQRT(说明!$C$17)) | H4: =IF(COUNT(I8:I61)<2,"",STDEV(I8:I61)*SQRT(说明!$C$17)) | J4: =IF(COUNT(K8:K61)<2,"",STDEV(K8:K61)*SQRT(说明!$C$17)) | L4: =IF(COUNT(M8:M61)<2,"",STDEV(M8:M61)*SQRT(说明!$C$17)) | N4: =IF(COUNT(O8:O61)<2,"",STDEV(O8:O61)*SQRT(说明!$C$17)) | P4: =IF(COUNT(Q8:Q61)<2,"",STDEV(Q8:Q61)*SQRT(说明!$C$17)) | R4: =IF(COUNT(S8:S61)<2,"",STDEV(S8:S61)*SQRT(说明!$C$17)) | T4: =IF(COUNT(U8:U61)<2,"",STDEV(U8:U61)*SQRT(说明!$C$17)) | V4: =IF(COUNT(W8:W61)<2,"",STDEV(W8:W61)*SQRT(说明!$C$17)) | X4: =IF(COUNT(Y8:Y61)<2,"",STDEV(Y8:Y61)*SQRT(说明!$C$17)) | Z4: =IF(COUNT(AA8:AA61)<2,"",STDEV(AA8:AA61)*SQRT(说明!$C$17)) | AB4: =IF(COUNT(AC8:AC61)<2,"",STDEV(AC8:AC61)*SQRT(说明!$C$17)) | AD4: =IF(COUNT(AE8:AE61)<2,"",STDEV(AE8:AE61)*SQRT(说明!$C$17)) | AF4: =IF(COUNT(AG8:AG61)<2,"",STDEV(AG8:AG61)*SQRT(说明!$C$17)) | AH4: =IF(COUNT(AI8:AI61)<2,"",STDEV(AI8:AI61)*SQRT(说明!$C$17)) | AJ4: =IF(COUNT(AK8:AK61)<2,"",STDEV(AK8:AK61)*SQRT(说明!$C$17)) | AL4: =IF(COUNT(AM8:AM61)<2,"",STDEV(AM8:AM61)*SQRT(说明!$C$17)) | AN4: =IF(COUNT(AO8:AO61)<2,"",STDEV(AO8:AO61)*SQRT(说明!$C$17))
A5: 区间年化收益 | B5: =IFERROR((LOOKUP(2,1/(B7:B61<>""),B7:B61)/B7)^(说明!$C$17/MAX(COUNT(C8:C61),1))-1,"") | D5: =IFERROR((LOOKUP(2,1/(D7:D61<>""),D7:D61)/D7)^(说明!$C$17/MAX(COUNT(E8:E61),1))-1,"") | F5: =IFERROR((LOOKUP(2,1/(F7:F61<>""),F7:F61)/F7)^(说明!$C$17/MAX(COUNT(G8:G61),1))-1,"") | H5: =IFERROR((LOOKUP(2,1/(H7:H61<>""),H7:H61)/H7)^(说明!$C$17/MAX(COUNT(I8:I61),1))-1,"") | J5: =IFERROR((LOOKUP(2,1/(J7:J61<>""),J7:J61)/J7)^(说明!$C$17/MAX(COUNT(K8:K61),1))-1,"") | L5: =IFERROR((LOOKUP(2,1/(L7:L61<>""),L7:L61)/L7)^(说明!$C$17/MAX(COUNT(M8:M61),1))-1,"") | N5: =IFERROR((LOOKUP(2,1/(N7:N61<>""),N7:N61)/N7)^(说明!$C$17/MAX(COUNT(O8:O61),1))-1,"") | P5: =IFERROR((LOOKUP(2,1/(P7:P61<>""),P7:P61)/P7)^(说明!$C$17/MAX(COUNT(Q8:Q61),1))-1,"") | R5: =IFERROR((LOOKUP(2,1/(R7:R61<>""),R7:R61)/R7)^(说明!$C$17/MAX(COUNT(S8:S61),1))-1,"") | T5: =IFERROR((LOOKUP(2,1/(T7:T61<>""),T7:T61)/T7)^(说明!$C$17/MAX(COUNT(U8:U61),1))-1,"") | V5: =IFERROR((LOOKUP(2,1/(V7:V61<>""),V7:V61)/V7)^(说明!$C$17/MAX(COUNT(W8:W61),1))-1,"") | X5: =IFERROR((LOOKUP(2,1/(X7:X61<>""),X7:X61)/X7)^(说明!$C$17/MAX(COUNT(Y8:Y61),1))-1,"") | Z5: =IFERROR((LOOKUP(2,1/(Z7:Z61<>""),Z7:Z61)/Z7)^(说明!$C$17/MAX(COUNT(AA8:AA61),1))-1,"") | AB5: =IFERROR((LOOKUP(2,1/(AB7:AB61<>""),AB7:AB61)/AB7)^(说明!$C$17/MAX(COUNT(AC8:AC61),1))-1,"") | AD5: =IFERROR((LOOKUP(2,1/(AD7:AD61<>""),AD7:AD61)/AD7)^(说明!$C$17/MAX(COUNT(AE8:AE61),1))-1,"") | AF5: =IFERROR((LOOKUP(2,1/(AF7:AF61<>""),AF7:AF61)/AF7)^(说明!$C$17/MAX(COUNT(AG8:AG61),1))-1,"") | AH5: =IFERROR((LOOKUP(2,1/(AH7:AH61<>""),AH7:AH61)/AH7)^(说明!$C$17/MAX(COUNT(AI8:AI61),1))-1,"") | AJ5: =IFERROR((LOOKUP(2,1/(AJ7:AJ61<>""),AJ7:AJ61)/AJ7)^(说明!$C$17/MAX(COUNT(AK8:AK61),1))-1,"") | AL5: =IFERROR((LOOKUP(2,1/(AL7:AL61<>""),AL7:AL61)/AL7)^(说明!$C$17/MAX(COUNT(AM8:AM61),1))-1,"") | AN5: =IFERROR((LOOKUP(2,1/(AN7:AN61<>""),AN7:AN61)/AN7)^(说明!$C$17/MAX(COUNT(AO8:AO61),1))-1,"")
A6: 日期 | B6: 复权净值 | C6: 日收益 | D6: 复权净值 | E6: 日收益 | F6: 复权净值 | G6: 日收益 | H6: 复权净值 | I6: 日收益 | J6: 复权净值 | K6: 日收益 | L6: 复权净值 | M6: 日收益 | N6: 复权净值 | O6: 日收益 | P6: 复权净值 | Q6: 日收益 | R6: 复权净值 | S6: 日收益 | T6: 复权净值 | U6: 日收益 | V6: 复权净值 | W6: 日收益 | X6: 复权净值 | Y6: 日收益 | Z6: 复权净值 | AA6: 日收益 | AB6: 复权净值 | AC6: 日收益 | AD6: 复权净值 | AE6: 日收益 | AF6: 复权净值 | AG6: 日收益 | AH6: 复权净值 | AI6: 日收益 | AJ6: 复权净值 | AK6: 日收益 | AL6: 复权净值 | AM6: 日收益 | AN6: 复权净值 | AO6: 日收益
A7: =IF(组合净值!A6="","",组合净值!A6) | B7: =IF($A7="","",[1]!thsiFinD("ths_adjustment_nv_fund",B$2,$A7)) | D7: =IF($A7="","",[1]!thsiFinD("ths_adjustment_nv_fund",D$2,$A7)) | F7: =IF($A7="","",[1]!thsiFinD("ths_adjustment_nv_fund",F$2,$A7)) | H7: =IF($A7="","",[1]!thsiFinD("ths_adjustment_nv_fund",H$2,$A7)) | J7: =IF($A7="","",[1]!thsiFinD("ths_adjustment_nv_fund",J$2,$A7)) | L7: =IF($A7="","",[1]!thsiFinD("ths_adjustment_nv_fund",L$2,$A7)) | N7: =IF($A7="","",[1]!thsiFinD("ths_adjustment_nv_fund",N$2,$A7)) | P7: =IF($A7="","",[1]!thsiFinD("ths_adjustment_nv_fund",P$2,$A7)) | R7: =IF($A7="","",[1]!thsiFinD("ths_adjustment_nv_fund",R$2,$A7)) | T7: =IF($A7="","",[1]!thsiFinD("ths_adjustment_nv_fund",T$2,$A7)) | V7: =IF($A7="","",[1]!thsiFinD("ths_adjustment_nv_fund",V$2,$A7)) | X7: =IF($A7="","",[1]!thsiFinD("ths_adjustment_nv_fund",X$2,$A7)) | Z7: =IF($A7="","",[1]!thsiFinD("ths_adjustment_nv_fund",Z$2,$A7)) | AB7: =IF($A7="","",[1]!thsiFinD("ths_adjustment_nv_fund",AB$2,$A7)) | AD7: =IF($A7="","",[1]!thsiFinD("ths_adjustment_nv_fund",AD$2,$A7)) | AF7: =IF($A7="","",[1]!thsiFinD("ths_adjustment_nv_fund",AF$2,$A7)) | AH7: =IF($A7="","",[1]!thsiFinD("ths_adjustment_nv_fund",AH$2,$A7)) | AJ7: =IF($A7="","",[1]!thsiFinD("ths_adjustment_nv_fund",AJ$2,$A7)) | AL7: =IF($A7="","",[1]!thsiFinD("ths_adjustment_nv_fund",AL$2,$A7)) | AN7: =IF($A7="","",[1]!thsiFinD("ths_adjustment_nv_fund",AN$2,$A7))
A8: =IF(组合净值!A7="","",组合净值!A7) | B8: =IF($A8="","",[1]!thsiFinD("ths_adjustment_nv_fund",B$2,$A8)) | C8: =IF(OR($A8="",B8="",B7=""),"",B8/B7-1) | D8: =IF($A8="","",[1]!thsiFinD("ths_adjustment_nv_fund",D$2,$A8)) | E8: =IF(OR($A8="",D8="",D7=""),"",D8/D7-1) | F8: =IF($A8="","",[1]!thsiFinD("ths_adjustment_nv_fund",F$2,$A8)) | G8: =IF(OR($A8="",F8="",F7=""),"",F8/F7-1) | H8: =IF($A8="","",[1]!thsiFinD("ths_adjustment_nv_fund",H$2,$A8)) | I8: =IF(OR($A8="",H8="",H7=""),"",H8/H7-1) | J8: =IF($A8="","",[1]!thsiFinD("ths_adjustment_nv_fund",J$2,$A8)) | K8: =IF(OR($A8="",J8="",J7=""),"",J8/J7-1) | L8: =IF($A8="","",[1]!thsiFinD("ths_adjustment_nv_fund",L$2,$A8)) | M8: =IF(OR($A8="",L8="",L7=""),"",L8/L7-1) | N8: =IF($A8="","",[1]!thsiFinD("ths_adjustment_nv_fund",N$2,$A8)) | O8: =IF(OR($A8="",N8="",N7=""),"",N8/N7-1) | P8: =IF($A8="","",[1]!thsiFinD("ths_adjustment_nv_fund",P$2,$A8)) | Q8: =IF(OR($A8="",P8="",P7=""),"",P8/P7-1) | R8: =IF($A8="","",[1]!thsiFinD("ths_adjustment_nv_fund",R$2,$A8)) | S8: =IF(OR($A8="",R8="",R7=""),"",R8/R7-1) | T8: =IF($A8="","",[1]!thsiFinD("ths_adjustment_nv_fund",T$2,$A8)) | U8: =IF(OR($A8="",T8="",T7=""),"",T8/T7-1) | V8: =IF($A8="","",[1]!thsiFinD("ths_adjustment_nv_fund",V$2,$A8)) | W8: =IF(OR($A8="",V8="",V7=""),"",V8/V7-1) | X8: =IF($A8="","",[1]!thsiFinD("ths_adjustment_nv_fund",X$2,$A8)) | Y8: =IF(OR($A8="",X8="",X7=""),"",X8/X7-1) | Z8: =IF($A8="","",[1]!thsiFinD("ths_adjustment_nv_fund",Z$2,$A8)) | AA8: =IF(OR($A8="",Z8="",Z7=""),"",Z8/Z7-1) | AB8: =IF($A8="","",[1]!thsiFinD("ths_adjustment_nv_fund",AB$2,$A8)) | AC8: =IF(OR($A8="",AB8="",AB7=""),"",AB8/AB7-1) | AD8: =IF($A8="","",[1]!thsiFinD("ths_adjustment_nv_fund",AD$2,$A8)) | AE8: =IF(OR($A8="",AD8="",AD7=""),"",AD8/AD7-1) | AF8: =IF($A8="","",[1]!thsiFinD("ths_adjustment_nv_fund",AF$2,$A8)) | AG8: =IF(OR($A8="",AF8="",AF7=""),"",AF8/AF7-1) | AH8: =IF($A8="","",[1]!thsiFinD("ths_adjustment_nv_fund",AH$2,$A8)) | AI8: =IF(OR($A8="",AH8="",AH7=""),"",AH8/AH7-1) | AJ8: =IF($A8="","",[1]!thsiFinD("ths_adjustment_nv_fund",AJ$2,$A8)) | AK8: =IF(OR($A8="",AJ8="",AJ7=""),"",AJ8/AJ7-1) | AL8: =IF($A8="","",[1]!thsiFinD("ths_adjustment_nv_fund",AL$2,$A8)) | AM8: =IF(OR($A8="",AL8="",AL7=""),"",AL8/AL7-1) | AN8: =IF($A8="","",[1]!thsiFinD("ths_adjustment_nv_fund",AN$2,$A8)) | AO8: =IF(OR($A8="",AN8="",AN7=""),"",AN8/AN7-1)
A9: =IF(组合净值!A8="","",组合净值!A8) | B9: =IF($A9="","",[1]!thsiFinD("ths_adjustment_nv_fund",B$2,$A9)) | C9: =IF(OR($A9="",B9="",B8=""),"",B9/B8-1) | D9: =IF($A9="","",[1]!thsiFinD("ths_adjustment_nv_fund",D$2,$A9)) | E9: =IF(OR($A9="",D9="",D8=""),"",D9/D8-1) | F9: =IF($A9="","",[1]!thsiFinD("ths_adjustment_nv_fund",F$2,$A9)) | G9: =IF(OR($A9="",F9="",F8=""),"",F9/F8-1) | H9: =IF($A9="","",[1]!thsiFinD("ths_adjustment_nv_fund",H$2,$A9)) | I9: =IF(OR($A9="",H9="",H8=""),"",H9/H8-1) | J9: =IF($A9="","",[1]!thsiFinD("ths_adjustment_nv_fund",J$2,$A9)) | K9: =IF(OR($A9="",J9="",J8=""),"",J9/J8-1) | L9: =IF($A9="","",[1]!thsiFinD("ths_adjustment_nv_fund",L$2,$A9)) | M9: =IF(OR($A9="",L9="",L8=""),"",L9/L8-1) | N9: =IF($A9="","",[1]!thsiFinD("ths_adjustment_nv_fund",N$2,$A9)) | O9: =IF(OR($A9="",N9="",N8=""),"",N9/N8-1) | P9: =IF($A9="","",[1]!thsiFinD("ths_adjustment_nv_fund",P$2,$A9)) | Q9: =IF(OR($A9="",P9="",P8=""),"",P9/P8-1) | R9: =IF($A9="","",[1]!thsiFinD("ths_adjustment_nv_fund",R$2,$A9)) | S9: =IF(OR($A9="",R9="",R8=""),"",R9/R8-1) | T9: =IF($A9="","",[1]!thsiFinD("ths_adjustment_nv_fund",T$2,$A9)) | U9: =IF(OR($A9="",T9="",T8=""),"",T9/T8-1) | V9: =IF($A9="","",[1]!thsiFinD("ths_adjustment_nv_fund",V$2,$A9)) | W9: =IF(OR($A9="",V9="",V8=""),"",V9/V8-1) | X9: =IF($A9="","",[1]!thsiFinD("ths_adjustment_nv_fund",X$2,$A9)) | Y9: =IF(OR($A9="",X9="",X8=""),"",X9/X8-1) | Z9: =IF($A9="","",[1]!thsiFinD("ths_adjustment_nv_fund",Z$2,$A9)) | AA9: =IF(OR($A9="",Z9="",Z8=""),"",Z9/Z8-1) | AB9: =IF($A9="","",[1]!thsiFinD("ths_adjustment_nv_fund",AB$2,$A9)) | AC9: =IF(OR($A9="",AB9="",AB8=""),"",AB9/AB8-1) | AD9: =IF($A9="","",[1]!thsiFinD("ths_adjustment_nv_fund",AD$2,$A9)) | AE9: =IF(OR($A9="",AD9="",AD8=""),"",AD9/AD8-1) | AF9: =IF($A9="","",[1]!thsiFinD("ths_adjustment_nv_fund",AF$2,$A9)) | AG9: =IF(OR($A9="",AF9="",AF8=""),"",AF9/AF8-1) | AH9: =IF($A9="","",[1]!thsiFinD("ths_adjustment_nv_fund",AH$2,$A9)) | AI9: =IF(OR($A9="",AH9="",AH8=""),"",AH9/AH8-1) | AJ9: =IF($A9="","",[1]!thsiFinD("ths_adjustment_nv_fund",AJ$2,$A9)) | AK9: =IF(OR($A9="",AJ9="",AJ8=""),"",AJ9/AJ8-1) | AL9: =IF($A9="","",[1]!thsiFinD("ths_adjustment_nv_fund",AL$2,$A9)) | AM9: =IF(OR($A9="",AL9="",AL8=""),"",AL9/AL8-1) | AN9: =IF($A9="","",[1]!thsiFinD("ths_adjustment_nv_fund",AN$2,$A9)) | AO9: =IF(OR($A9="",AN9="",AN8=""),"",AN9/AN8-1)
A10: =IF(组合净值!A9="","",组合净值!A9) | B10: =IF($A10="","",[1]!thsiFinD("ths_adjustment_nv_fund",B$2,$A10)) | C10: =IF(OR($A10="",B10="",B9=""),"",B10/B9-1) | D10: =IF($A10="","",[1]!thsiFinD("ths_adjustment_nv_fund",D$2,$A10)) | E10: =IF(OR($A10="",D10="",D9=""),"",D10/D9-1) | F10: =IF($A10="","",[1]!thsiFinD("ths_adjustment_nv_fund",F$2,$A10)) | G10: =IF(OR($A10="",F10="",F9=""),"",F10/F9-1) | H10: =IF($A10="","",[1]!thsiFinD("ths_adjustment_nv_fund",H$2,$A10)) | I10: =IF(OR($A10="",H10="",H9=""),"",H10/H9-1) | J10: =IF($A10="","",[1]!thsiFinD("ths_adjustment_nv_fund",J$2,$A10)) | K10: =IF(OR($A10="",J10="",J9=""),"",J10/J9-1) | L10: =IF($A10="","",[1]!thsiFinD("ths_adjustment_nv_fund",L$2,$A10)) | M10: =IF(OR($A10="",L10="",L9=""),"",L10/L9-1) | N10: =IF($A10="","",[1]!thsiFinD("ths_adjustment_nv_fund",N$2,$A10)) | O10: =IF(OR($A10="",N10="",N9=""),"",N10/N9-1) | P10: =IF($A10="","",[1]!thsiFinD("ths_adjustment_nv_fund",P$2,$A10)) | Q10: =IF(OR($A10="",P10="",P9=""),"",P10/P9-1) | R10: =IF($A10="","",[1]!thsiFinD("ths_adjustment_nv_fund",R$2,$A10)) | S10: =IF(OR($A10="",R10="",R9=""),"",R10/R9-1) | T10: =IF($A10="","",[1]!thsiFinD("ths_adjustment_nv_fund",T$2,$A10)) | U10: =IF(OR($A10="",T10="",T9=""),"",T10/T9-1) | V10: =IF($A10="","",[1]!thsiFinD("ths_adjustment_nv_fund",V$2,$A10)) | W10: =IF(OR($A10="",V10="",V9=""),"",V10/V9-1) | X10: =IF($A10="","",[1]!thsiFinD("ths_adjustment_nv_fund",X$2,$A10)) | Y10: =IF(OR($A10="",X10="",X9=""),"",X10/X9-1) | Z10: =IF($A10="","",[1]!thsiFinD("ths_adjustment_nv_fund",Z$2,$A10)) | AA10: =IF(OR($A10="",Z10="",Z9=""),"",Z10/Z9-1) | AB10: =IF($A10="","",[1]!thsiFinD("ths_adjustment_nv_fund",AB$2,$A10)) | AC10: =IF(OR($A10="",AB10="",AB9=""),"",AB10/AB9-1) | AD10: =IF($A10="","",[1]!thsiFinD("ths_adjustment_nv_fund",AD$2,$A10)) | AE10: =IF(OR($A10="",AD10="",AD9=""),"",AD10/AD9-1) | AF10: =IF($A10="","",[1]!thsiFinD("ths_adjustment_nv_fund",AF$2,$A10)) | AG10: =IF(OR($A10="",AF10="",AF9=""),"",AF10/AF9-1) | AH10: =IF($A10="","",[1]!thsiFinD("ths_adjustment_nv_fund",AH$2,$A10)) | AI10: =IF(OR($A10="",AH10="",AH9=""),"",AH10/AH9-1) | AJ10: =IF($A10="","",[1]!thsiFinD("ths_adjustment_nv_fund",AJ$2,$A10)) | AK10: =IF(OR($A10="",AJ10="",AJ9=""),"",AJ10/AJ9-1) | AL10: =IF($A10="","",[1]!thsiFinD("ths_adjustment_nv_fund",AL$2,$A10)) | AM10: =IF(OR($A10="",AL10="",AL9=""),"",AL10/AL9-1) | AN10: =IF($A10="","",[1]!thsiFinD("ths_adjustment_nv_fund",AN$2,$A10)) | AO10: =IF(OR($A10="",AN10="",AN9=""),"",AN10/AN9-1)
A11: =IF(组合净值!A10="","",组合净值!A10) | B11: =IF($A11="","",[1]!thsiFinD("ths_adjustment_nv_fund",B$2,$A11)) | C11: =IF(OR($A11="",B11="",B10=""),"",B11/B10-1) | D11: =IF($A11="","",[1]!thsiFinD("ths_adjustment_nv_fund",D$2,$A11)) | E11: =IF(OR($A11="",D11="",D10=""),"",D11/D10-1) | F11: =IF($A11="","",[1]!thsiFinD("ths_adjustment_nv_fund",F$2,$A11)) | G11: =IF(OR($A11="",F11="",F10=""),"",F11/F10-1) | H11: =IF($A11="","",[1]!thsiFinD("ths_adjustment_nv_fund",H$2,$A11)) | I11: =IF(OR($A11="",H11="",H10=""),"",H11/H10-1) | J11: =IF($A11="","",[1]!thsiFinD("ths_adjustment_nv_fund",J$2,$A11)) | K11: =IF(OR($A11="",J11="",J10=""),"",J11/J10-1) | L11: =IF($A11="","",[1]!thsiFinD("ths_adjustment_nv_fund",L$2,$A11)) | M11: =IF(OR($A11="",L11="",L10=""),"",L11/L10-1) | N11: =IF($A11="","",[1]!thsiFinD("ths_adjustment_nv_fund",N$2,$A11)) | O11: =IF(OR($A11="",N11="",N10=""),"",N11/N10-1) | P11: =IF($A11="","",[1]!thsiFinD("ths_adjustment_nv_fund",P$2,$A11)) | Q11: =IF(OR($A11="",P11="",P10=""),"",P11/P10-1) | R11: =IF($A11="","",[1]!thsiFinD("ths_adjustment_nv_fund",R$2,$A11)) | S11: =IF(OR($A11="",R11="",R10=""),"",R11/R10-1) | T11: =IF($A11="","",[1]!thsiFinD("ths_adjustment_nv_fund",T$2,$A11)) | U11: =IF(OR($A11="",T11="",T10=""),"",T11/T10-1) | V11: =IF($A11="","",[1]!thsiFinD("ths_adjustment_nv_fund",V$2,$A11)) | W11: =IF(OR($A11="",V11="",V10=""),"",V11/V10-1) | X11: =IF($A11="","",[1]!thsiFinD("ths_adjustment_nv_fund",X$2,$A11)) | Y11: =IF(OR($A11="",X11="",X10=""),"",X11/X10-1) | Z11: =IF($A11="","",[1]!thsiFinD("ths_adjustment_nv_fund",Z$2,$A11)) | AA11: =IF(OR($A11="",Z11="",Z10=""),"",Z11/Z10-1) | AB11: =IF($A11="","",[1]!thsiFinD("ths_adjustment_nv_fund",AB$2,$A11)) | AC11: =IF(OR($A11="",AB11="",AB10=""),"",AB11/AB10-1) | AD11: =IF($A11="","",[1]!thsiFinD("ths_adjustment_nv_fund",AD$2,$A11)) | AE11: =IF(OR($A11="",AD11="",AD10=""),"",AD11/AD10-1) | AF11: =IF($A11="","",[1]!thsiFinD("ths_adjustment_nv_fund",AF$2,$A11)) | AG11: =IF(OR($A11="",AF11="",AF10=""),"",AF11/AF10-1) | AH11: =IF($A11="","",[1]!thsiFinD("ths_adjustment_nv_fund",AH$2,$A11)) | AI11: =IF(OR($A11="",AH11="",AH10=""),"",AH11/AH10-1) | AJ11: =IF($A11="","",[1]!thsiFinD("ths_adjustment_nv_fund",AJ$2,$A11)) | AK11: =IF(OR($A11="",AJ11="",AJ10=""),"",AJ11/AJ10-1) | AL11: =IF($A11="","",[1]!thsiFinD("ths_adjustment_nv_fund",AL$2,$A11)) | AM11: =IF(OR($A11="",AL11="",AL10=""),"",AL11/AL10-1) | AN11: =IF($A11="","",[1]!thsiFinD("ths_adjustment_nv_fund",AN$2,$A11)) | AO11: =IF(OR($A11="",AN11="",AN10=""),"",AN11/AN10-1)
A12: =IF(组合净值!A11="","",组合净值!A11) | B12: =IF($A12="","",[1]!thsiFinD("ths_adjustment_nv_fund",B$2,$A12)) | C12: =IF(OR($A12="",B12="",B11=""),"",B12/B11-1) | D12: =IF($A12="","",[1]!thsiFinD("ths_adjustment_nv_fund",D$2,$A12)) | E12: =IF(OR($A12="",D12="",D11=""),"",D12/D11-1) | F12: =IF($A12="","",[1]!thsiFinD("ths_adjustment_nv_fund",F$2,$A12)) | G12: =IF(OR($A12="",F12="",F11=""),"",F12/F11-1) | H12: =IF($A12="","",[1]!thsiFinD("ths_adjustment_nv_fund",H$2,$A12)) | I12: =IF(OR($A12="",H12="",H11=""),"",H12/H11-1) | J12: =IF($A12="","",[1]!thsiFinD("ths_adjustment_nv_fund",J$2,$A12)) | K12: =IF(OR($A12="",J12="",J11=""),"",J12/J11-1) | L12: =IF($A12="","",[1]!thsiFinD("ths_adjustment_nv_fund",L$2,$A12)) | M12: =IF(OR($A12="",L12="",L11=""),"",L12/L11-1) | N12: =IF($A12="","",[1]!thsiFinD("ths_adjustment_nv_fund",N$2,$A12)) | O12: =IF(OR($A12="",N12="",N11=""),"",N12/N11-1) | P12: =IF($A12="","",[1]!thsiFinD("ths_adjustment_nv_fund",P$2,$A12)) | Q12: =IF(OR($A12="",P12="",P11=""),"",P12/P11-1) | R12: =IF($A12="","",[1]!thsiFinD("ths_adjustment_nv_fund",R$2,$A12)) | S12: =IF(OR($A12="",R12="",R11=""),"",R12/R11-1) | T12: =IF($A12="","",[1]!thsiFinD("ths_adjustment_nv_fund",T$2,$A12)) | U12: =IF(OR($A12="",T12="",T11=""),"",T12/T11-1) | V12: =IF($A12="","",[1]!thsiFinD("ths_adjustment_nv_fund",V$2,$A12)) | W12: =IF(OR($A12="",V12="",V11=""),"",V12/V11-1) | X12: =IF($A12="","",[1]!thsiFinD("ths_adjustment_nv_fund",X$2,$A12)) | Y12: =IF(OR($A12="",X12="",X11=""),"",X12/X11-1) | Z12: =IF($A12="","",[1]!thsiFinD("ths_adjustment_nv_fund",Z$2,$A12)) | AA12: =IF(OR($A12="",Z12="",Z11=""),"",Z12/Z11-1) | AB12: =IF($A12="","",[1]!thsiFinD("ths_adjustment_nv_fund",AB$2,$A12)) | AC12: =IF(OR($A12="",AB12="",AB11=""),"",AB12/AB11-1) | AD12: =IF($A12="","",[1]!thsiFinD("ths_adjustment_nv_fund",AD$2,$A12)) | AE12: =IF(OR($A12="",AD12="",AD11=""),"",AD12/AD11-1) | AF12: =IF($A12="","",[1]!thsiFinD("ths_adjustment_nv_fund",AF$2,$A12)) | AG12: =IF(OR($A12="",AF12="",AF11=""),"",AF12/AF11-1) | AH12: =IF($A12="","",[1]!thsiFinD("ths_adjustment_nv_fund",AH$2,$A12)) | AI12: =IF(OR($A12="",AH12="",AH11=""),"",AH12/AH11-1) | AJ12: =IF($A12="","",[1]!thsiFinD("ths_adjustment_nv_fund",AJ$2,$A12)) | AK12: =IF(OR($A12="",AJ12="",AJ11=""),"",AJ12/AJ11-1) | AL12: =IF($A12="","",[1]!thsiFinD("ths_adjustment_nv_fund",AL$2,$A12)) | AM12: =IF(OR($A12="",AL12="",AL11=""),"",AL12/AL11-1) | AN12: =IF($A12="","",[1]!thsiFinD("ths_adjustment_nv_fund",AN$2,$A12)) | AO12: =IF(OR($A12="",AN12="",AN11=""),"",AN12/AN11-1)
A13: =IF(组合净值!A12="","",组合净值!A12) | B13: =IF($A13="","",[1]!thsiFinD("ths_adjustment_nv_fund",B$2,$A13)) | C13: =IF(OR($A13="",B13="",B12=""),"",B13/B12-1) | D13: =IF($A13="","",[1]!thsiFinD("ths_adjustment_nv_fund",D$2,$A13)) | E13: =IF(OR($A13="",D13="",D12=""),"",D13/D12-1) | F13: =IF($A13="","",[1]!thsiFinD("ths_adjustment_nv_fund",F$2,$A13)) | G13: =IF(OR($A13="",F13="",F12=""),"",F13/F12-1) | H13: =IF($A13="","",[1]!thsiFinD("ths_adjustment_nv_fund",H$2,$A13)) | I13: =IF(OR($A13="",H13="",H12=""),"",H13/H12-1) | J13: =IF($A13="","",[1]!thsiFinD("ths_adjustment_nv_fund",J$2,$A13)) | K13: =IF(OR($A13="",J13="",J12=""),"",J13/J12-1) | L13: =IF($A13="","",[1]!thsiFinD("ths_adjustment_nv_fund",L$2,$A13)) | M13: =IF(OR($A13="",L13="",L12=""),"",L13/L12-1) | N13: =IF($A13="","",[1]!thsiFinD("ths_adjustment_nv_fund",N$2,$A13)) | O13: =IF(OR($A13="",N13="",N12=""),"",N13/N12-1) | P13: =IF($A13="","",[1]!thsiFinD("ths_adjustment_nv_fund",P$2,$A13)) | Q13: =IF(OR($A13="",P13="",P12=""),"",P13/P12-1) | R13: =IF($A13="","",[1]!thsiFinD("ths_adjustment_nv_fund",R$2,$A13)) | S13: =IF(OR($A13="",R13="",R12=""),"",R13/R12-1) | T13: =IF($A13="","",[1]!thsiFinD("ths_adjustment_nv_fund",T$2,$A13)) | U13: =IF(OR($A13="",T13="",T12=""),"",T13/T12-1) | V13: =IF($A13="","",[1]!thsiFinD("ths_adjustment_nv_fund",V$2,$A13)) | W13: =IF(OR($A13="",V13="",V12=""),"",V13/V12-1) | X13: =IF($A13="","",[1]!thsiFinD("ths_adjustment_nv_fund",X$2,$A13)) | Y13: =IF(OR($A13="",X13="",X12=""),"",X13/X12-1) | Z13: =IF($A13="","",[1]!thsiFinD("ths_adjustment_nv_fund",Z$2,$A13)) | AA13: =IF(OR($A13="",Z13="",Z12=""),"",Z13/Z12-1) | AB13: =IF($A13="","",[1]!thsiFinD("ths_adjustment_nv_fund",AB$2,$A13)) | AC13: =IF(OR($A13="",AB13="",AB12=""),"",AB13/AB12-1) | AD13: =IF($A13="","",[1]!thsiFinD("ths_adjustment_nv_fund",AD$2,$A13)) | AE13: =IF(OR($A13="",AD13="",AD12=""),"",AD13/AD12-1) | AF13: =IF($A13="","",[1]!thsiFinD("ths_adjustment_nv_fund",AF$2,$A13)) | AG13: =IF(OR($A13="",AF13="",AF12=""),"",AF13/AF12-1) | AH13: =IF($A13="","",[1]!thsiFinD("ths_adjustment_nv_fund",AH$2,$A13)) | AI13: =IF(OR($A13="",AH13="",AH12=""),"",AH13/AH12-1) | AJ13: =IF($A13="","",[1]!thsiFinD("ths_adjustment_nv_fund",AJ$2,$A13)) | AK13: =IF(OR($A13="",AJ13="",AJ12=""),"",AJ13/AJ12-1) | AL13: =IF($A13="","",[1]!thsiFinD("ths_adjustment_nv_fund",AL$2,$A13)) | AM13: =IF(OR($A13="",AL13="",AL12=""),"",AL13/AL12-1) | AN13: =IF($A13="","",[1]!thsiFinD("ths_adjustment_nv_fund",AN$2,$A13)) | AO13: =IF(OR($A13="",AN13="",AN12=""),"",AN13/AN12-1)
A14: =IF(组合净值!A13="","",组合净值!A13) | B14: =IF($A14="","",[1]!thsiFinD("ths_adjustment_nv_fund",B$2,$A14)) | C14: =IF(OR($A14="",B14="",B13=""),"",B14/B13-1) | D14: =IF($A14="","",[1]!thsiFinD("ths_adjustment_nv_fund",D$2,$A14)) | E14: =IF(OR($A14="",D14="",D13=""),"",D14/D13-1) | F14: =IF($A14="","",[1]!thsiFinD("ths_adjustment_nv_fund",F$2,$A14)) | G14: =IF(OR($A14="",F14="",F13=""),"",F14/F13-1) | H14: =IF($A14="","",[1]!thsiFinD("ths_adjustment_nv_fund",H$2,$A14)) | I14: =IF(OR($A14="",H14="",H13=""),"",H14/H13-1) | J14: =IF($A14="","",[1]!thsiFinD("ths_adjustment_nv_fund",J$2,$A14)) | K14: =IF(OR($A14="",J14="",J13=""),"",J14/J13-1) | L14: =IF($A14="","",[1]!thsiFinD("ths_adjustment_nv_fund",L$2,$A14)) | M14: =IF(OR($A14="",L14="",L13=""),"",L14/L13-1) | N14: =IF($A14="","",[1]!thsiFinD("ths_adjustment_nv_fund",N$2,$A14)) | O14: =IF(OR($A14="",N14="",N13=""),"",N14/N13-1) | P14: =IF($A14="","",[1]!thsiFinD("ths_adjustment_nv_fund",P$2,$A14)) | Q14: =IF(OR($A14="",P14="",P13=""),"",P14/P13-1) | R14: =IF($A14="","",[1]!thsiFinD("ths_adjustment_nv_fund",R$2,$A14)) | S14: =IF(OR($A14="",R14="",R13=""),"",R14/R13-1) | T14: =IF($A14="","",[1]!thsiFinD("ths_adjustment_nv_fund",T$2,$A14)) | U14: =IF(OR($A14="",T14="",T13=""),"",T14/T13-1) | V14: =IF($A14="","",[1]!thsiFinD("ths_adjustment_nv_fund",V$2,$A14)) | W14: =IF(OR($A14="",V14="",V13=""),"",V14/V13-1) | X14: =IF($A14="","",[1]!thsiFinD("ths_adjustment_nv_fund",X$2,$A14)) | Y14: =IF(OR($A14="",X14="",X13=""),"",X14/X13-1) | Z14: =IF($A14="","",[1]!thsiFinD("ths_adjustment_nv_fund",Z$2,$A14)) | AA14: =IF(OR($A14="",Z14="",Z13=""),"",Z14/Z13-1) | AB14: =IF($A14="","",[1]!thsiFinD("ths_adjustment_nv_fund",AB$2,$A14)) | AC14: =IF(OR($A14="",AB14="",AB13=""),"",AB14/AB13-1) | AD14: =IF($A14="","",[1]!thsiFinD("ths_adjustment_nv_fund",AD$2,$A14)) | AE14: =IF(OR($A14="",AD14="",AD13=""),"",AD14/AD13-1) | AF14: =IF($A14="","",[1]!thsiFinD("ths_adjustment_nv_fund",AF$2,$A14)) | AG14: =IF(OR($A14="",AF14="",AF13=""),"",AF14/AF13-1) | AH14: =IF($A14="","",[1]!thsiFinD("ths_adjustment_nv_fund",AH$2,$A14)) | AI14: =IF(OR($A14="",AH14="",AH13=""),"",AH14/AH13-1) | AJ14: =IF($A14="","",[1]!thsiFinD("ths_adjustment_nv_fund",AJ$2,$A14)) | AK14: =IF(OR($A14="",AJ14="",AJ13=""),"",AJ14/AJ13-1) | AL14: =IF($A14="","",[1]!thsiFinD("ths_adjustment_nv_fund",AL$2,$A14)) | AM14: =IF(OR($A14="",AL14="",AL13=""),"",AL14/AL13-1) | AN14: =IF($A14="","",[1]!thsiFinD("ths_adjustment_nv_fund",AN$2,$A14)) | AO14: =IF(OR($A14="",AN14="",AN13=""),"",AN14/AN13-1)
A15: =IF(组合净值!A14="","",组合净值!A14) | B15: =IF($A15="","",[1]!thsiFinD("ths_adjustment_nv_fund",B$2,$A15)) | C15: =IF(OR($A15="",B15="",B14=""),"",B15/B14-1) | D15: =IF($A15="","",[1]!thsiFinD("ths_adjustment_nv_fund",D$2,$A15)) | E15: =IF(OR($A15="",D15="",D14=""),"",D15/D14-1) | F15: =IF($A15="","",[1]!thsiFinD("ths_adjustment_nv_fund",F$2,$A15)) | G15: =IF(OR($A15="",F15="",F14=""),"",F15/F14-1) | H15: =IF($A15="","",[1]!thsiFinD("ths_adjustment_nv_fund",H$2,$A15)) | I15: =IF(OR($A15="",H15="",H14=""),"",H15/H14-1) | J15: =IF($A15="","",[1]!thsiFinD("ths_adjustment_nv_fund",J$2,$A15)) | K15: =IF(OR($A15="",J15="",J14=""),"",J15/J14-1) | L15: =IF($A15="","",[1]!thsiFinD("ths_adjustment_nv_fund",L$2,$A15)) | M15: =IF(OR($A15="",L15="",L14=""),"",L15/L14-1) | N15: =IF($A15="","",[1]!thsiFinD("ths_adjustment_nv_fund",N$2,$A15)) | O15: =IF(OR($A15="",N15="",N14=""),"",N15/N14-1) | P15: =IF($A15="","",[1]!thsiFinD("ths_adjustment_nv_fund",P$2,$A15)) | Q15: =IF(OR($A15="",P15="",P14=""),"",P15/P14-1) | R15: =IF($A15="","",[1]!thsiFinD("ths_adjustment_nv_fund",R$2,$A15)) | S15: =IF(OR($A15="",R15="",R14=""),"",R15/R14-1) | T15: =IF($A15="","",[1]!thsiFinD("ths_adjustment_nv_fund",T$2,$A15)) | U15: =IF(OR($A15="",T15="",T14=""),"",T15/T14-1) | V15: =IF($A15="","",[1]!thsiFinD("ths_adjustment_nv_fund",V$2,$A15)) | W15: =IF(OR($A15="",V15="",V14=""),"",V15/V14-1) | X15: =IF($A15="","",[1]!thsiFinD("ths_adjustment_nv_fund",X$2,$A15)) | Y15: =IF(OR($A15="",X15="",X14=""),"",X15/X14-1) | Z15: =IF($A15="","",[1]!thsiFinD("ths_adjustment_nv_fund",Z$2,$A15)) | AA15: =IF(OR($A15="",Z15="",Z14=""),"",Z15/Z14-1) | AB15: =IF($A15="","",[1]!thsiFinD("ths_adjustment_nv_fund",AB$2,$A15)) | AC15: =IF(OR($A15="",AB15="",AB14=""),"",AB15/AB14-1) | AD15: =IF($A15="","",[1]!thsiFinD("ths_adjustment_nv_fund",AD$2,$A15)) | AE15: =IF(OR($A15="",AD15="",AD14=""),"",AD15/AD14-1) | AF15: =IF($A15="","",[1]!thsiFinD("ths_adjustment_nv_fund",AF$2,$A15)) | AG15: =IF(OR($A15="",AF15="",AF14=""),"",AF15/AF14-1) | AH15: =IF($A15="","",[1]!thsiFinD("ths_adjustment_nv_fund",AH$2,$A15)) | AI15: =IF(OR($A15="",AH15="",AH14=""),"",AH15/AH14-1) | AJ15: =IF($A15="","",[1]!thsiFinD("ths_adjustment_nv_fund",AJ$2,$A15)) | AK15: =IF(OR($A15="",AJ15="",AJ14=""),"",AJ15/AJ14-1) | AL15: =IF($A15="","",[1]!thsiFinD("ths_adjustment_nv_fund",AL$2,$A15)) | AM15: =IF(OR($A15="",AL15="",AL14=""),"",AL15/AL14-1) | AN15: =IF($A15="","",[1]!thsiFinD("ths_adjustment_nv_fund",AN$2,$A15)) | AO15: =IF(OR($A15="",AN15="",AN14=""),"",AN15/AN14-1)
A16: =IF(组合净值!A15="","",组合净值!A15) | B16: =IF($A16="","",[1]!thsiFinD("ths_adjustment_nv_fund",B$2,$A16)) | C16: =IF(OR($A16="",B16="",B15=""),"",B16/B15-1) | D16: =IF($A16="","",[1]!thsiFinD("ths_adjustment_nv_fund",D$2,$A16)) | E16: =IF(OR($A16="",D16="",D15=""),"",D16/D15-1) | F16: =IF($A16="","",[1]!thsiFinD("ths_adjustment_nv_fund",F$2,$A16)) | G16: =IF(OR($A16="",F16="",F15=""),"",F16/F15-1) | H16: =IF($A16="","",[1]!thsiFinD("ths_adjustment_nv_fund",H$2,$A16)) | I16: =IF(OR($A16="",H16="",H15=""),"",H16/H15-1) | J16: =IF($A16="","",[1]!thsiFinD("ths_adjustment_nv_fund",J$2,$A16)) | K16: =IF(OR($A16="",J16="",J15=""),"",J16/J15-1) | L16: =IF($A16="","",[1]!thsiFinD("ths_adjustment_nv_fund",L$2,$A16)) | M16: =IF(OR($A16="",L16="",L15=""),"",L16/L15-1) | N16: =IF($A16="","",[1]!thsiFinD("ths_adjustment_nv_fund",N$2,$A16)) | O16: =IF(OR($A16="",N16="",N15=""),"",N16/N15-1) | P16: =IF($A16="","",[1]!thsiFinD("ths_adjustment_nv_fund",P$2,$A16)) | Q16: =IF(OR($A16="",P16="",P15=""),"",P16/P15-1) | R16: =IF($A16="","",[1]!thsiFinD("ths_adjustment_nv_fund",R$2,$A16)) | S16: =IF(OR($A16="",R16="",R15=""),"",R16/R15-1) | T16: =IF($A16="","",[1]!thsiFinD("ths_adjustment_nv_fund",T$2,$A16)) | U16: =IF(OR($A16="",T16="",T15=""),"",T16/T15-1) | V16: =IF($A16="","",[1]!thsiFinD("ths_adjustment_nv_fund",V$2,$A16)) | W16: =IF(OR($A16="",V16="",V15=""),"",V16/V15-1) | X16: =IF($A16="","",[1]!thsiFinD("ths_adjustment_nv_fund",X$2,$A16)) | Y16: =IF(OR($A16="",X16="",X15=""),"",X16/X15-1) | Z16: =IF($A16="","",[1]!thsiFinD("ths_adjustment_nv_fund",Z$2,$A16)) | AA16: =IF(OR($A16="",Z16="",Z15=""),"",Z16/Z15-1) | AB16: =IF($A16="","",[1]!thsiFinD("ths_adjustment_nv_fund",AB$2,$A16)) | AC16: =IF(OR($A16="",AB16="",AB15=""),"",AB16/AB15-1) | AD16: =IF($A16="","",[1]!thsiFinD("ths_adjustment_nv_fund",AD$2,$A16)) | AE16: =IF(OR($A16="",AD16="",AD15=""),"",AD16/AD15-1) | AF16: =IF($A16="","",[1]!thsiFinD("ths_adjustment_nv_fund",AF$2,$A16)) | AG16: =IF(OR($A16="",AF16="",AF15=""),"",AF16/AF15-1) | AH16: =IF($A16="","",[1]!thsiFinD("ths_adjustment_nv_fund",AH$2,$A16)) | AI16: =IF(OR($A16="",AH16="",AH15=""),"",AH16/AH15-1) | AJ16: =IF($A16="","",[1]!thsiFinD("ths_adjustment_nv_fund",AJ$2,$A16)) | AK16: =IF(OR($A16="",AJ16="",AJ15=""),"",AJ16/AJ15-1) | AL16: =IF($A16="","",[1]!thsiFinD("ths_adjustment_nv_fund",AL$2,$A16)) | AM16: =IF(OR($A16="",AL16="",AL15=""),"",AL16/AL15-1) | AN16: =IF($A16="","",[1]!thsiFinD("ths_adjustment_nv_fund",AN$2,$A16)) | AO16: =IF(OR($A16="",AN16="",AN15=""),"",AN16/AN15-1)
A17: =IF(组合净值!A16="","",组合净值!A16) | B17: =IF($A17="","",[1]!thsiFinD("ths_adjustment_nv_fund",B$2,$A17)) | C17: =IF(OR($A17="",B17="",B16=""),"",B17/B16-1) | D17: =IF($A17="","",[1]!thsiFinD("ths_adjustment_nv_fund",D$2,$A17)) | E17: =IF(OR($A17="",D17="",D16=""),"",D17/D16-1) | F17: =IF($A17="","",[1]!thsiFinD("ths_adjustment_nv_fund",F$2,$A17)) | G17: =IF(OR($A17="",F17="",F16=""),"",F17/F16-1) | H17: =IF($A17="","",[1]!thsiFinD("ths_adjustment_nv_fund",H$2,$A17)) | I17: =IF(OR($A17="",H17="",H16=""),"",H17/H16-1) | J17: =IF($A17="","",[1]!thsiFinD("ths_adjustment_nv_fund",J$2,$A17)) | K17: =IF(OR($A17="",J17="",J16=""),"",J17/J16-1) | L17: =IF($A17="","",[1]!thsiFinD("ths_adjustment_nv_fund",L$2,$A17)) | M17: =IF(OR($A17="",L17="",L16=""),"",L17/L16-1) | N17: =IF($A17="","",[1]!thsiFinD("ths_adjustment_nv_fund",N$2,$A17)) | O17: =IF(OR($A17="",N17="",N16=""),"",N17/N16-1) | P17: =IF($A17="","",[1]!thsiFinD("ths_adjustment_nv_fund",P$2,$A17)) | Q17: =IF(OR($A17="",P17="",P16=""),"",P17/P16-1) | R17: =IF($A17="","",[1]!thsiFinD("ths_adjustment_nv_fund",R$2,$A17)) | S17: =IF(OR($A17="",R17="",R16=""),"",R17/R16-1) | T17: =IF($A17="","",[1]!thsiFinD("ths_adjustment_nv_fund",T$2,$A17)) | U17: =IF(OR($A17="",T17="",T16=""),"",T17/T16-1) | V17: =IF($A17="","",[1]!thsiFinD("ths_adjustment_nv_fund",V$2,$A17)) | W17: =IF(OR($A17="",V17="",V16=""),"",V17/V16-1) | X17: =IF($A17="","",[1]!thsiFinD("ths_adjustment_nv_fund",X$2,$A17)) | Y17: =IF(OR($A17="",X17="",X16=""),"",X17/X16-1) | Z17: =IF($A17="","",[1]!thsiFinD("ths_adjustment_nv_fund",Z$2,$A17)) | AA17: =IF(OR($A17="",Z17="",Z16=""),"",Z17/Z16-1) | AB17: =IF($A17="","",[1]!thsiFinD("ths_adjustment_nv_fund",AB$2,$A17)) | AC17: =IF(OR($A17="",AB17="",AB16=""),"",AB17/AB16-1) | AD17: =IF($A17="","",[1]!thsiFinD("ths_adjustment_nv_fund",AD$2,$A17)) | AE17: =IF(OR($A17="",AD17="",AD16=""),"",AD17/AD16-1) | AF17: =IF($A17="","",[1]!thsiFinD("ths_adjustment_nv_fund",AF$2,$A17)) | AG17: =IF(OR($A17="",AF17="",AF16=""),"",AF17/AF16-1) | AH17: =IF($A17="","",[1]!thsiFinD("ths_adjustment_nv_fund",AH$2,$A17)) | AI17: =IF(OR($A17="",AH17="",AH16=""),"",AH17/AH16-1) | AJ17: =IF($A17="","",[1]!thsiFinD("ths_adjustment_nv_fund",AJ$2,$A17)) | AK17: =IF(OR($A17="",AJ17="",AJ16=""),"",AJ17/AJ16-1) | AL17: =IF($A17="","",[1]!thsiFinD("ths_adjustment_nv_fund",AL$2,$A17)) | AM17: =IF(OR($A17="",AL17="",AL16=""),"",AL17/AL16-1) | AN17: =IF($A17="","",[1]!thsiFinD("ths_adjustment_nv_fund",AN$2,$A17)) | AO17: =IF(OR($A17="",AN17="",AN16=""),"",AN17/AN16-1)
A18: =IF(组合净值!A17="","",组合净值!A17) | B18: =IF($A18="","",[1]!thsiFinD("ths_adjustment_nv_fund",B$2,$A18)) | C18: =IF(OR($A18="",B18="",B17=""),"",B18/B17-1) | D18: =IF($A18="","",[1]!thsiFinD("ths_adjustment_nv_fund",D$2,$A18)) | E18: =IF(OR($A18="",D18="",D17=""),"",D18/D17-1) | F18: =IF($A18="","",[1]!thsiFinD("ths_adjustment_nv_fund",F$2,$A18)) | G18: =IF(OR($A18="",F18="",F17=""),"",F18/F17-1) | H18: =IF($A18="","",[1]!thsiFinD("ths_adjustment_nv_fund",H$2,$A18)) | I18: =IF(OR($A18="",H18="",H17=""),"",H18/H17-1) | J18: =IF($A18="","",[1]!thsiFinD("ths_adjustment_nv_fund",J$2,$A18)) | K18: =IF(OR($A18="",J18="",J17=""),"",J18/J17-1) | L18: =IF($A18="","",[1]!thsiFinD("ths_adjustment_nv_fund",L$2,$A18)) | M18: =IF(OR($A18="",L18="",L17=""),"",L18/L17-1) | N18: =IF($A18="","",[1]!thsiFinD("ths_adjustment_nv_fund",N$2,$A18)) | O18: =IF(OR($A18="",N18="",N17=""),"",N18/N17-1) | P18: =IF($A18="","",[1]!thsiFinD("ths_adjustment_nv_fund",P$2,$A18)) | Q18: =IF(OR($A18="",P18="",P17=""),"",P18/P17-1) | R18: =IF($A18="","",[1]!thsiFinD("ths_adjustment_nv_fund",R$2,$A18)) | S18: =IF(OR($A18="",R18="",R17=""),"",R18/R17-1) | T18: =IF($A18="","",[1]!thsiFinD("ths_adjustment_nv_fund",T$2,$A18)) | U18: =IF(OR($A18="",T18="",T17=""),"",T18/T17-1) | V18: =IF($A18="","",[1]!thsiFinD("ths_adjustment_nv_fund",V$2,$A18)) | W18: =IF(OR($A18="",V18="",V17=""),"",V18/V17-1) | X18: =IF($A18="","",[1]!thsiFinD("ths_adjustment_nv_fund",X$2,$A18)) | Y18: =IF(OR($A18="",X18="",X17=""),"",X18/X17-1) | Z18: =IF($A18="","",[1]!thsiFinD("ths_adjustment_nv_fund",Z$2,$A18)) | AA18: =IF(OR($A18="",Z18="",Z17=""),"",Z18/Z17-1) | AB18: =IF($A18="","",[1]!thsiFinD("ths_adjustment_nv_fund",AB$2,$A18)) | AC18: =IF(OR($A18="",AB18="",AB17=""),"",AB18/AB17-1) | AD18: =IF($A18="","",[1]!thsiFinD("ths_adjustment_nv_fund",AD$2,$A18)) | AE18: =IF(OR($A18="",AD18="",AD17=""),"",AD18/AD17-1) | AF18: =IF($A18="","",[1]!thsiFinD("ths_adjustment_nv_fund",AF$2,$A18)) | AG18: =IF(OR($A18="",AF18="",AF17=""),"",AF18/AF17-1) | AH18: =IF($A18="","",[1]!thsiFinD("ths_adjustment_nv_fund",AH$2,$A18)) | AI18: =IF(OR($A18="",AH18="",AH17=""),"",AH18/AH17-1) | AJ18: =IF($A18="","",[1]!thsiFinD("ths_adjustment_nv_fund",AJ$2,$A18)) | AK18: =IF(OR($A18="",AJ18="",AJ17=""),"",AJ18/AJ17-1) | AL18: =IF($A18="","",[1]!thsiFinD("ths_adjustment_nv_fund",AL$2,$A18)) | AM18: =IF(OR($A18="",AL18="",AL17=""),"",AL18/AL17-1) | AN18: =IF($A18="","",[1]!thsiFinD("ths_adjustment_nv_fund",AN$2,$A18)) | AO18: =IF(OR($A18="",AN18="",AN17=""),"",AN18/AN17-1)
A19: =IF(组合净值!A18="","",组合净值!A18) | B19: =IF($A19="","",[1]!thsiFinD("ths_adjustment_nv_fund",B$2,$A19)) | C19: =IF(OR($A19="",B19="",B18=""),"",B19/B18-1) | D19: =IF($A19="","",[1]!thsiFinD("ths_adjustment_nv_fund",D$2,$A19)) | E19: =IF(OR($A19="",D19="",D18=""),"",D19/D18-1) | F19: =IF($A19="","",[1]!thsiFinD("ths_adjustment_nv_fund",F$2,$A19)) | G19: =IF(OR($A19="",F19="",F18=""),"",F19/F18-1) | H19: =IF($A19="","",[1]!thsiFinD("ths_adjustment_nv_fund",H$2,$A19)) | I19: =IF(OR($A19="",H19="",H18=""),"",H19/H18-1) | J19: =IF($A19="","",[1]!thsiFinD("ths_adjustment_nv_fund",J$2,$A19)) | K19: =IF(OR($A19="",J19="",J18=""),"",J19/J18-1) | L19: =IF($A19="","",[1]!thsiFinD("ths_adjustment_nv_fund",L$2,$A19)) | M19: =IF(OR($A19="",L19="",L18=""),"",L19/L18-1) | N19: =IF($A19="","",[1]!thsiFinD("ths_adjustment_nv_fund",N$2,$A19)) | O19: =IF(OR($A19="",N19="",N18=""),"",N19/N18-1) | P19: =IF($A19="","",[1]!thsiFinD("ths_adjustment_nv_fund",P$2,$A19)) | Q19: =IF(OR($A19="",P19="",P18=""),"",P19/P18-1) | R19: =IF($A19="","",[1]!thsiFinD("ths_adjustment_nv_fund",R$2,$A19)) | S19: =IF(OR($A19="",R19="",R18=""),"",R19/R18-1) | T19: =IF($A19="","",[1]!thsiFinD("ths_adjustment_nv_fund",T$2,$A19)) | U19: =IF(OR($A19="",T19="",T18=""),"",T19/T18-1) | V19: =IF($A19="","",[1]!thsiFinD("ths_adjustment_nv_fund",V$2,$A19)) | W19: =IF(OR($A19="",V19="",V18=""),"",V19/V18-1) | X19: =IF($A19="","",[1]!thsiFinD("ths_adjustment_nv_fund",X$2,$A19)) | Y19: =IF(OR($A19="",X19="",X18=""),"",X19/X18-1) | Z19: =IF($A19="","",[1]!thsiFinD("ths_adjustment_nv_fund",Z$2,$A19)) | AA19: =IF(OR($A19="",Z19="",Z18=""),"",Z19/Z18-1) | AB19: =IF($A19="","",[1]!thsiFinD("ths_adjustment_nv_fund",AB$2,$A19)) | AC19: =IF(OR($A19="",AB19="",AB18=""),"",AB19/AB18-1) | AD19: =IF($A19="","",[1]!thsiFinD("ths_adjustment_nv_fund",AD$2,$A19)) | AE19: =IF(OR($A19="",AD19="",AD18=""),"",AD19/AD18-1) | AF19: =IF($A19="","",[1]!thsiFinD("ths_adjustment_nv_fund",AF$2,$A19)) | AG19: =IF(OR($A19="",AF19="",AF18=""),"",AF19/AF18-1) | AH19: =IF($A19="","",[1]!thsiFinD("ths_adjustment_nv_fund",AH$2,$A19)) | AI19: =IF(OR($A19="",AH19="",AH18=""),"",AH19/AH18-1) | AJ19: =IF($A19="","",[1]!thsiFinD("ths_adjustment_nv_fund",AJ$2,$A19)) | AK19: =IF(OR($A19="",AJ19="",AJ18=""),"",AJ19/AJ18-1) | AL19: =IF($A19="","",[1]!thsiFinD("ths_adjustment_nv_fund",AL$2,$A19)) | AM19: =IF(OR($A19="",AL19="",AL18=""),"",AL19/AL18-1) | AN19: =IF($A19="","",[1]!thsiFinD("ths_adjustment_nv_fund",AN$2,$A19)) | AO19: =IF(OR($A19="",AN19="",AN18=""),"",AN19/AN18-1)
... A61: =IF(组合净值!A60="","",组合净值!A60) | B61: =IF($A61="","",[1]!thsiFinD("ths_adjustment_nv_fund",B$2,$A61)) | C61: =IF(OR($A61="",B61="",B60=""),"",B61/B60-1) | D61: =IF($A61="","",[1]!thsiFinD("ths_adjustment_nv_fund",D$2,$A61)) | E61: =IF(OR($A61="",D61="",D60=""),"",D61/D60-1) | F61: =IF($A61="","",[1]!thsiFinD("ths_adjustment_nv_fund",F$2,$A61)) | G61: =IF(OR($A61="",F61="",F60=""),"",F61/F60-1) | H61: =IF($A61="","",[1]!thsiFinD("ths_adjustment_nv_fund",H$2,$A61)) | I61: =IF(OR($A61="",H61="",H60=""),"",H61/H60-1) | J61: =IF($A61="","",[1]!thsiFinD("ths_adjustment_nv_fund",J$2,$A61)) | K61: =IF(OR($A61="",J61="",J60=""),"",J61/J60-1) | L61: =IF($A61="","",[1]!thsiFinD("ths_adjustment_nv_fund",L$2,$A61)) | M61: =IF(OR($A61="",L61="",L60=""),"",L61/L60-1) | N61: =IF($A61="","",[1]!thsiFinD("ths_adjustment_nv_fund",N$2,$A61)) | O61: =IF(OR($A61="",N61="",N60=""),"",N61/N60-1) | P61: =IF($A61="","",[1]!thsiFinD("ths_adjustment_nv_fund",P$2,$A61)) | Q61: =IF(OR($A61="",P61="",P60=""),"",P61/P60-1) | R61: =IF($A61="","",[1]!thsiFinD("ths_adjustment_nv_fund",R$2,$A61)) | S61: =IF(OR($A61="",R61="",R60=""),"",R61/R60-1) | T61: =IF($A61="","",[1]!thsiFinD("ths_adjustment_nv_fund",T$2,$A61)) | U61: =IF(OR($A61="",T61="",T60=""),"",T61/T60-1) | V61: =IF($A61="","",[1]!thsiFinD("ths_adjustment_nv_fund",V$2,$A61)) | W61: =IF(OR($A61="",V61="",V60=""),"",V61/V60-1) | X61: =IF($A61="","",[1]!thsiFinD("ths_adjustment_nv_fund",X$2,$A61)) | Y61: =IF(OR($A61="",X61="",X60=""),"",X61/X60-1) | Z61: =IF($A61="","",[1]!thsiFinD("ths_adjustment_nv_fund",Z$2,$A61)) | AA61: =IF(OR($A61="",Z61="",Z60=""),"",Z61/Z60-1) | AB61: =IF($A61="","",[1]!thsiFinD("ths_adjustment_nv_fund",AB$2,$A61)) | AC61: =IF(OR($A61="",AB61="",AB60=""),"",AB61/AB60-1) | AD61: =IF($A61="","",[1]!thsiFinD("ths_adjustment_nv_fund",AD$2,$A61)) | AE61: =IF(OR($A61="",AD61="",AD60=""),"",AD61/AD60-1) | AF61: =IF($A61="","",[1]!thsiFinD("ths_adjustment_nv_fund",AF$2,$A61)) | AG61: =IF(OR($A61="",AF61="",AF60=""),"",AF61/AF60-1) | AH61: =IF($A61="","",[1]!thsiFinD("ths_adjustment_nv_fund",AH$2,$A61)) | AI61: =IF(OR($A61="",AH61="",AH60=""),"",AH61/AH60-1) | AJ61: =IF($A61="","",[1]!thsiFinD("ths_adjustment_nv_fund",AJ$2,$A61)) | AK61: =IF(OR($A61="",AJ61="",AJ60=""),"",AJ61/AJ60-1) | AL61: =IF($A61="","",[1]!thsiFinD("ths_adjustment_nv_fund",AL$2,$A61)) | AM61: =IF(OR($A61="",AL61="",AL60=""),"",AL61/AL60-1) | AN61: =IF($A61="","",[1]!thsiFinD("ths_adjustment_nv_fund",AN$2,$A61)) | AO61: =IF(OR($A61="",AN61="",AN60=""),"",AN61/AN60-1)
A63: 新增基金：整列复制最后一只基金的两列→粘贴到右侧空白两列→改第2行代码即可；替换基金：只改第2行代码。vs页按D列代码自动HLOOKUP匹配，无需改公式。

Sheet 实盘持仓配置
A1: 持仓配置（实盘·初始权重）
A2: 基金简称 | B2: 华安黄金ETF联接A | C2: 嘉实快线货币A | D2: 宏利复兴混合A | E2: 博道沪深300增强A | F2: 博道沪深300指增C | G2: 国泰通信设备ETF联接A | H2: 国泰通信设备C | I2: 嘉实前沿科技创新 | J2: 银华集成电路混合A | K2: 银华集成电路混合C | L2: 天弘中证1000指增A | M2: 天弘中证1000指增C | N2: 中欧中证500指增A | O2: 中欧中证500指增C | P2: 信澳业绩驱动A | Q2: 嘉实信息产业A | R2: 嘉实信息产业C | S2: 宏利复兴伟业C | T2: 国泰半导体材料设备ETF联接A | U2: 国泰半导体材料设备C | V2: 华泰柏瑞中证2000指增A | W2: 华泰柏瑞中证2000指增C | X2: 易方达中债新综指LOFA | Y2: 合计 | Z2: 年化费率 | AA2: 净值起始日
A3: 基金代码 | B3: 000216.OF | C3: 000917.OF | D3: 001170.OF | E3: 007044.OF | F3: 007045.OF | G3: 007817.OF | H3: 007818.OF | I3: 009993.OF | J3: 013840.OF | K3: 013841.OF | L3: 014201.OF | M3: 014202.OF | N3: 015453.OF | O3: 015454.OF | P3: 016370.OF | Q3: 017488.OF | R3: 017489.OF | S3: 017612.OF | T3: 019632.OF | U3: 019633.OF | V3: 019923.OF | W3: 019924.OF | X3: 161119.OF
A4: 产业趋势 权重 | B4: 0 | C4: 0.02 | D4: 0.19 | E4: 0 | F4: 0 | G4: 0.11 | H4: 0 | I4: 0 | J4: 0.19 | K4: 0 | L4: 0 | M4: 0 | N4: 0 | O4: 0 | P4: 0.19 | Q4: 0.19 | R4: 0 | S4: 0 | T4: 0.11 | U4: 0 | V4: 0 | W4: 0 | X4: 0 | Y4: =SUM(B4:X4) | Z4: 0.015 | AA4: 46195
A5: 产业趋势基石 权重 | B5: 0 | C5: 0.02 | D5: 0.19 | E5: 0 | F5: 0 | G5: 0.11 | H5: 0 | I5: 0 | J5: 0.19 | K5: 0 | L5: 0 | M5: 0 | N5: 0 | O5: 0 | P5: 0.19 | Q5: 0.19 | R5: 0 | S5: 0 | T5: 0.11 | U5: 0 | V5: 0 | W5: 0 | X5: 0 | Y5: =SUM(B5:X5) | Z5: 0.012 | AA5: 46191
A6: 产业趋势2号 权重 | B6: 0 | C6: 0.02 | D6: 0 | E6: 0 | F6: 0 | G6: 0 | H6: 0.11 | I6: 0.19 | J6: 0 | K6: 0.19 | L6: 0 | M6: 0 | N6: 0 | O6: 0 | P6: 0 | Q6: 0 | R6: 0.19 | S6: 0.19 | T6: 0 | U6: 0.11 | V6: 0 | W6: 0 | X6: 0 | Y6: =SUM(B6:X6) | Z6: 0.015 | AA6: 46196
A7: 10-90 权重 | B7: 0.05 | C7: 0.02 | D7: 0 | E7: 0 | F7: 0.0125 | G7: 0 | H7: 0.005 | I7: 0.01 | J7: 0 | K7: 0.01 | L7: 0 | M7: 0.0125 | N7: 0 | O7: 0.0125 | P7: 0 | Q7: 0 | R7: 0.01 | S7: 0.01 | T7: 0 | U7: 0.005 | V7: 0 | W7: 0.0125 | X7: 0.83 | Y7: =SUM(B7:X7) | Z7: 0.008 | AA7: 46197
A8: 10-90基石 权重 | B8: 0.05 | C8: 0.02 | D8: 0.01 | E8: 0.0125 | F8: 0 | G8: 0.005 | H8: 0 | I8: 0 | J8: 0.01 | K8: 0 | L8: 0.0125 | M8: 0 | N8: 0.0125 | O8: 0 | P8: 0.01 | Q8: 0.01 | R8: 0 | S8: 0 | T8: 0.005 | U8: 0 | V8: 0.0125 | W8: 0 | X8: 0.83 | Y8: =SUM(B8:X8) | Z8: 0.005 | AA8: 46191
A9: 30-70 权重 | B9: 0.1 | C9: 0.02 | D9: 0 | E9: 0 | F9: 0.0375 | G9: 0 | H9: 0.015 | I9: 0.03 | J9: 0 | K9: 0.03 | L9: 0 | M9: 0.0375 | N9: 0 | O9: 0.0375 | P9: 0 | Q9: 0 | R9: 0.03 | S9: 0.03 | T9: 0 | U9: 0.015 | V9: 0 | W9: 0.0375 | X9: 0.58 | Y9: =SUM(B9:X9) | Z9: 0.012 | AA9: 46197
A11: 权重蓝色输入；Z列为各组合年化费率、AA列为各组合净值起始日(当日净值=1)。新增交易日下拉填充，下游净值与看板自动重算。

Sheet 实盘净值数据(iFinD公式)
A1: 净值数据 * 实盘
A2: =TODAY()
A3: 基金代码→ | B3: =实盘持仓配置!B3 | C3: =实盘持仓配置!C3 | D3: =实盘持仓配置!D3 | E3: =实盘持仓配置!E3 | F3: =实盘持仓配置!F3 | G3: =实盘持仓配置!G3 | H3: =实盘持仓配置!H3 | I3: =实盘持仓配置!I3 | ... X3: =实盘持仓配置!X3
A4: =[1]!HX_AutoDate(1,"2026-06-18",A2,-1,-1,0,0,0,0,0,"SSE",12,0) | B4: 华安黄金ETF联接A | C4: 嘉实快线货币A | D4: 宏利复兴混合A | E4: 博道沪深300增强A | F4: 博道沪深300指增C | G4: 国泰通信设备ETF联接A | H4: 国泰通信设备C | I4: 嘉实前沿科技创新 | J4: 银华集成电路混合A | K4: 银华集成电路混合C | L4: 天弘中证1000指增A | M4: 天弘中证1000指增C | N4: 中欧中证500指增A | O4: 中欧中证500指增C | P4: 信澳业绩驱动A | Q4: 嘉实信息产业A | R4: 嘉实信息产业C | S4: 宏利复兴伟业C | T4: 国泰半导体材料设备ETF联接A | U4: 国泰半导体材料设备C | V4: 华泰柏瑞中证2000指增A | W4: 华泰柏瑞中证2000指增C | X4: 易方达中债新综指LOFA
A5: 46191 | B5: =IF($A5="","",[1]!thsiFinD("ths_adjustment_nv_fund",B$3,$A5)) | C5: =IF($A5="","",[1]!thsiFinD("ths_adjustment_nv_fund",C$3,$A5)) | D5: =IF($A5="","",[1]!thsiFinD("ths_adjustment_nv_fund",D$3,$A5)) | E5: =IF($A5="","",[1]!thsiFinD("ths_adjustment_nv_fund",E$3,$A5)) | F5: =IF($A5="","",[1]!thsiFinD("ths_adjustment_nv_fund",F$3,$A5)) | G5: =IF($A5="","",[1]!thsiFinD("ths_adjustment_nv_fund",G$3,$A5)) | H5: =IF($A5="","",[1]!thsiFinD("ths_adjustment_nv_fund",H$3,$A5)) | I5: =IF($A5="","",[1]!thsiFinD("ths_adjustment_nv_fund",I$3,$A5)) | ... X5: =IF($A5="","",[1]!thsiFinD("ths_adjustment_nv_fund",X$3,$A5))
A6: 46195 | B6: =IF($A6="","",[1]!thsiFinD("ths_adjustment_nv_fund",B$3,$A6)) | C6: =IF($A6="","",[1]!thsiFinD("ths_adjustment_nv_fund",C$3,$A6)) | D6: =IF($A6="","",[1]!thsiFinD("ths_adjustment_nv_fund",D$3,$A6)) | E6: =IF($A6="","",[1]!thsiFinD("ths_adjustment_nv_fund",E$3,$A6)) | F6: =IF($A6="","",[1]!thsiFinD("ths_adjustment_nv_fund",F$3,$A6)) | G6: =IF($A6="","",[1]!thsiFinD("ths_adjustment_nv_fund",G$3,$A6)) | H6: =IF($A6="","",[1]!thsiFinD("ths_adjustment_nv_fund",H$3,$A6)) | I6: =IF($A6="","",[1]!thsiFinD("ths_adjustment_nv_fund",I$3,$A6)) | ... X6: =IF($A6="","",[1]!thsiFinD("ths_adjustment_nv_fund",X$3,$A6))
A7: 46196 | B7: =IF($A7="","",[1]!thsiFinD("ths_adjustment_nv_fund",B$3,$A7)) | C7: =IF($A7="","",[1]!thsiFinD("ths_adjustment_nv_fund",C$3,$A7)) | D7: =IF($A7="","",[1]!thsiFinD("ths_adjustment_nv_fund",D$3,$A7)) | E7: =IF($A7="","",[1]!thsiFinD("ths_adjustment_nv_fund",E$3,$A7)) | F7: =IF($A7="","",[1]!thsiFinD("ths_adjustment_nv_fund",F$3,$A7)) | G7: =IF($A7="","",[1]!thsiFinD("ths_adjustment_nv_fund",G$3,$A7)) | H7: =IF($A7="","",[1]!thsiFinD("ths_adjustment_nv_fund",H$3,$A7)) | I7: =IF($A7="","",[1]!thsiFinD("ths_adjustment_nv_fund",I$3,$A7)) | ... X7: =IF($A7="","",[1]!thsiFinD("ths_adjustment_nv_fund",X$3,$A7))
A8: 46197 | B8: =IF($A8="","",[1]!thsiFinD("ths_adjustment_nv_fund",B$3,$A8)) | C8: =IF($A8="","",[1]!thsiFinD("ths_adjustment_nv_fund",C$3,$A8)) | D8: =IF($A8="","",[1]!thsiFinD("ths_adjustment_nv_fund",D$3,$A8)) | E8: =IF($A8="","",[1]!thsiFinD("ths_adjustment_nv_fund",E$3,$A8)) | F8: =IF($A8="","",[1]!thsiFinD("ths_adjustment_nv_fund",F$3,$A8)) | G8: =IF($A8="","",[1]!thsiFinD("ths_adjustment_nv_fund",G$3,$A8)) | H8: =IF($A8="","",[1]!thsiFinD("ths_adjustment_nv_fund",H$3,$A8)) | I8: =IF($A8="","",[1]!thsiFinD("ths_adjustment_nv_fund",I$3,$A8)) | ... X8: =IF($A8="","",[1]!thsiFinD("ths_adjustment_nv_fund",X$3,$A8))
A9: 46198 | B9: =IF($A9="","",[1]!thsiFinD("ths_adjustment_nv_fund",B$3,$A9)) | C9: =IF($A9="","",[1]!thsiFinD("ths_adjustment_nv_fund",C$3,$A9)) | D9: =IF($A9="","",[1]!thsiFinD("ths_adjustment_nv_fund",D$3,$A9)) | E9: =IF($A9="","",[1]!thsiFinD("ths_adjustment_nv_fund",E$3,$A9)) | F9: =IF($A9="","",[1]!thsiFinD("ths_adjustment_nv_fund",F$3,$A9)) | G9: =IF($A9="","",[1]!thsiFinD("ths_adjustment_nv_fund",G$3,$A9)) | H9: =IF($A9="","",[1]!thsiFinD("ths_adjustment_nv_fund",H$3,$A9)) | I9: =IF($A9="","",[1]!thsiFinD("ths_adjustment_nv_fund",I$3,$A9)) | ... X9: =IF($A9="","",[1]!thsiFinD("ths_adjustment_nv_fund",X$3,$A9))
A10: 46199 | B10: =IF($A10="","",[1]!thsiFinD("ths_adjustment_nv_fund",B$3,$A10)) | C10: =IF($A10="","",[1]!thsiFinD("ths_adjustment_nv_fund",C$3,$A10)) | D10: =IF($A10="","",[1]!thsiFinD("ths_adjustment_nv_fund",D$3,$A10)) | E10: =IF($A10="","",[1]!thsiFinD("ths_adjustment_nv_fund",E$3,$A10)) | F10: =IF($A10="","",[1]!thsiFinD("ths_adjustment_nv_fund",F$3,$A10)) | G10: =IF($A10="","",[1]!thsiFinD("ths_adjustment_nv_fund",G$3,$A10)) | H10: =IF($A10="","",[1]!thsiFinD("ths_adjustment_nv_fund",H$3,$A10)) | I10: =IF($A10="","",[1]!thsiFinD("ths_adjustment_nv_fund",I$3,$A10)) | ... X10: =IF($A10="","",[1]!thsiFinD("ths_adjustment_nv_fund",X$3,$A10))
A11: 46202 | B11: =IF($A11="","",[1]!thsiFinD("ths_adjustment_nv_fund",B$3,$A11)) | C11: =IF($A11="","",[1]!thsiFinD("ths_adjustment_nv_fund",C$3,$A11)) | D11: =IF($A11="","",[1]!thsiFinD("ths_adjustment_nv_fund",D$3,$A11)) | E11: =IF($A11="","",[1]!thsiFinD("ths_adjustment_nv_fund",E$3,$A11)) | F11: =IF($A11="","",[1]!thsiFinD("ths_adjustment_nv_fund",F$3,$A11)) | G11: =IF($A11="","",[1]!thsiFinD("ths_adjustment_nv_fund",G$3,$A11)) | H11: =IF($A11="","",[1]!thsiFinD("ths_adjustment_nv_fund",H$3,$A11)) | I11: =IF($A11="","",[1]!thsiFinD("ths_adjustment_nv_fund",I$3,$A11)) | ... X11: =IF($A11="","",[1]!thsiFinD("ths_adjustment_nv_fund",X$3,$A11))
A12: 46203 | B12: =IF($A12="","",[1]!thsiFinD("ths_adjustment_nv_fund",B$3,$A12)) | C12: =IF($A12="","",[1]!thsiFinD("ths_adjustment_nv_fund",C$3,$A12)) | D12: =IF($A12="","",[1]!thsiFinD("ths_adjustment_nv_fund",D$3,$A12)) | E12: =IF($A12="","",[1]!thsiFinD("ths_adjustment_nv_fund",E$3,$A12)) | F12: =IF($A12="","",[1]!thsiFinD("ths_adjustment_nv_fund",F$3,$A12)) | G12: =IF($A12="","",[1]!thsiFinD("ths_adjustment_nv_fund",G$3,$A12)) | H12: =IF($A12="","",[1]!thsiFinD("ths_adjustment_nv_fund",H$3,$A12)) | I12: =IF($A12="","",[1]!thsiFinD("ths_adjustment_nv_fund",I$3,$A12)) | ... X12: =IF($A12="","",[1]!thsiFinD("ths_adjustment_nv_fund",X$3,$A12))
A13: 46204 | B13: =IF($A13="","",[1]!thsiFinD("ths_adjustment_nv_fund",B$3,$A13)) | C13: =IF($A13="","",[1]!thsiFinD("ths_adjustment_nv_fund",C$3,$A13)) | D13: =IF($A13="","",[1]!thsiFinD("ths_adjustment_nv_fund",D$3,$A13)) | E13: =IF($A13="","",[1]!thsiFinD("ths_adjustment_nv_fund",E$3,$A13)) | F13: =IF($A13="","",[1]!thsiFinD("ths_adjustment_nv_fund",F$3,$A13)) | G13: =IF($A13="","",[1]!thsiFinD("ths_adjustment_nv_fund",G$3,$A13)) | H13: =IF($A13="","",[1]!thsiFinD("ths_adjustment_nv_fund",H$3,$A13)) | I13: =IF($A13="","",[1]!thsiFinD("ths_adjustment_nv_fund",I$3,$A13)) | ... X13: =IF($A13="","",[1]!thsiFinD("ths_adjustment_nv_fund",X$3,$A13))
A14: 46205 | B14: =IF($A14="","",[1]!thsiFinD("ths_adjustment_nv_fund",B$3,$A14)) | C14: =IF($A14="","",[1]!thsiFinD("ths_adjustment_nv_fund",C$3,$A14)) | D14: =IF($A14="","",[1]!thsiFinD("ths_adjustment_nv_fund",D$3,$A14)) | E14: =IF($A14="","",[1]!thsiFinD("ths_adjustment_nv_fund",E$3,$A14)) | F14: =IF($A14="","",[1]!thsiFinD("ths_adjustment_nv_fund",F$3,$A14)) | G14: =IF($A14="","",[1]!thsiFinD("ths_adjustment_nv_fund",G$3,$A14)) | H14: =IF($A14="","",[1]!thsiFinD("ths_adjustment_nv_fund",H$3,$A14)) | I14: =IF($A14="","",[1]!thsiFinD("ths_adjustment_nv_fund",I$3,$A14)) | ... X14: =IF($A14="","",[1]!thsiFinD("ths_adjustment_nv_fund",X$3,$A14))
A15: 46206 | B15: =IF($A15="","",[1]!thsiFinD("ths_adjustment_nv_fund",B$3,$A15)) | C15: =IF($A15="","",[1]!thsiFinD("ths_adjustment_nv_fund",C$3,$A15)) | D15: =IF($A15="","",[1]!thsiFinD("ths_adjustment_nv_fund",D$3,$A15)) | E15: =IF($A15="","",[1]!thsiFinD("ths_adjustment_nv_fund",E$3,$A15)) | F15: =IF($A15="","",[1]!thsiFinD("ths_adjustment_nv_fund",F$3,$A15)) | G15: =IF($A15="","",[1]!thsiFinD("ths_adjustment_nv_fund",G$3,$A15)) | H15: =IF($A15="","",[1]!thsiFinD("ths_adjustment_nv_fund",H$3,$A15)) | I15: =IF($A15="","",[1]!thsiFinD("ths_adjustment_nv_fund",I$3,$A15)) | ... X15: =IF($A15="","",[1]!thsiFinD("ths_adjustment_nv_fund",X$3,$A15))
A16: 46209 | B16: =IF($A16="","",[1]!thsiFinD("ths_adjustment_nv_fund",B$3,$A16)) | C16: =IF($A16="","",[1]!thsiFinD("ths_adjustment_nv_fund",C$3,$A16)) | D16: =IF($A16="","",[1]!thsiFinD("ths_adjustment_nv_fund",D$3,$A16)) | E16: =IF($A16="","",[1]!thsiFinD("ths_adjustment_nv_fund",E$3,$A16)) | F16: =IF($A16="","",[1]!thsiFinD("ths_adjustment_nv_fund",F$3,$A16)) | G16: =IF($A16="","",[1]!thsiFinD("ths_adjustment_nv_fund",G$3,$A16)) | H16: =IF($A16="","",[1]!thsiFinD("ths_adjustment_nv_fund",H$3,$A16)) | I16: =IF($A16="","",[1]!thsiFinD("ths_adjustment_nv_fund",I$3,$A16)) | ... X16: =IF($A16="","",[1]!thsiFinD("ths_adjustment_nv_fund",X$3,$A16))
B17: =IF($A17="","",[1]!thsiFinD("ths_adjustment_nv_fund",B$3,$A17)) | C17: =IF($A17="","",[1]!thsiFinD("ths_adjustment_nv_fund",C$3,$A17)) | D17: =IF($A17="","",[1]!thsiFinD("ths_adjustment_nv_fund",D$3,$A17)) | E17: =IF($A17="","",[1]!thsiFinD("ths_adjustment_nv_fund",E$3,$A17)) | F17: =IF($A17="","",[1]!thsiFinD("ths_adjustment_nv_fund",F$3,$A17)) | G17: =IF($A17="","",[1]!thsiFinD("ths_adjustment_nv_fund",G$3,$A17)) | H17: =IF($A17="","",[1]!thsiFinD("ths_adjustment_nv_fund",H$3,$A17)) | I17: =IF($A17="","",[1]!thsiFinD("ths_adjustment_nv_fund",I$3,$A17)) | ... X17: =IF($A17="","",[1]!thsiFinD("ths_adjustment_nv_fund",X$3,$A17))
B18: =IF($A18="","",[1]!thsiFinD("ths_adjustment_nv_fund",B$3,$A18)) | C18: =IF($A18="","",[1]!thsiFinD("ths_adjustment_nv_fund",C$3,$A18)) | D18: =IF($A18="","",[1]!thsiFinD("ths_adjustment_nv_fund",D$3,$A18)) | E18: =IF($A18="","",[1]!thsiFinD("ths_adjustment_nv_fund",E$3,$A18)) | F18: =IF($A18="","",[1]!thsiFinD("ths_adjustment_nv_fund",F$3,$A18)) | G18: =IF($A18="","",[1]!thsiFinD("ths_adjustment_nv_fund",G$3,$A18)) | H18: =IF($A18="","",[1]!thsiFinD("ths_adjustment_nv_fund",H$3,$A18)) | I18: =IF($A18="","",[1]!thsiFinD("ths_adjustment_nv_fund",I$3,$A18)) | ... X18: =IF($A18="","",[1]!thsiFinD("ths_adjustment_nv_fund",X$3,$A18))
B19: =IF($A19="","",[1]!thsiFinD("ths_adjustment_nv_fund",B$3,$A19)) | C19: =IF($A19="","",[1]!thsiFinD("ths_adjustment_nv_fund",C$3,$A19)) | D19: =IF($A19="","",[1]!thsiFinD("ths_adjustment_nv_fund",D$3,$A19)) | E19: =IF($A19="","",[1]!thsiFinD("ths_adjustment_nv_fund",E$3,$A19)) | F19: =IF($A19="","",[1]!thsiFinD("ths_adjustment_nv_fund",F$3,$A19)) | G19: =IF($A19="","",[1]!thsiFinD("ths_adjustment_nv_fund",G$3,$A19)) | H19: =IF($A19="","",[1]!thsiFinD("ths_adjustment_nv_fund",H$3,$A19)) | I19: =IF($A19="","",[1]!thsiFinD("ths_adjustment_nv_fund",I$3,$A19)) | ... X19: =IF($A19="","",[1]!thsiFinD("ths_adjustment_nv_fund",X$3,$A19))
B20: =IF($A20="","",[1]!thsiFinD("ths_adjustment_nv_fund",B$3,$A20)) | C20: =IF($A20="","",[1]!thsiFinD("ths_adjustment_nv_fund",C$3,$A20)) | D20: =IF($A20="","",[1]!thsiFinD("ths_adjustment_nv_fund",D$3,$A20)) | E20: =IF($A20="","",[1]!thsiFinD("ths_adjustment_nv_fund",E$3,$A20)) | F20: =IF($A20="","",[1]!thsiFinD("ths_adjustment_nv_fund",F$3,$A20)) | G20: =IF($A20="","",[1]!thsiFinD("ths_adjustment_nv_fund",G$3,$A20)) | H20: =IF($A20="","",[1]!thsiFinD("ths_adjustment_nv_fund",H$3,$A20)) | I20: =IF($A20="","",[1]!thsiFinD("ths_adjustment_nv_fund",I$3,$A20)) | ... X20: =IF($A20="","",[1]!thsiFinD("ths_adjustment_nv_fund",X$3,$A20))
B21: =IF($A21="","",[1]!thsiFinD("ths_adjustment_nv_fund",B$3,$A21)) | C21: =IF($A21="","",[1]!thsiFinD("ths_adjustment_nv_fund",C$3,$A21)) | D21: =IF($A21="","",[1]!thsiFinD("ths_adjustment_nv_fund",D$3,$A21)) | E21: =IF($A21="","",[1]!thsiFinD("ths_adjustment_nv_fund",E$3,$A21)) | F21: =IF($A21="","",[1]!thsiFinD("ths_adjustment_nv_fund",F$3,$A21)) | G21: =IF($A21="","",[1]!thsiFinD("ths_adjustment_nv_fund",G$3,$A21)) | H21: =IF($A21="","",[1]!thsiFinD("ths_adjustment_nv_fund",H$3,$A21)) | I21: =IF($A21="","",[1]!thsiFinD("ths_adjustment_nv_fund",I$3,$A21)) | ... X21: =IF($A21="","",[1]!thsiFinD("ths_adjustment_nv_fund",X$3,$A21))
B22: =IF($A22="","",[1]!thsiFinD("ths_adjustment_nv_fund",B$3,$A22)) | C22: =IF($A22="","",[1]!thsiFinD("ths_adjustment_nv_fund",C$3,$A22)) | D22: =IF($A22="","",[1]!thsiFinD("ths_adjustment_nv_fund",D$3,$A22)) | E22: =IF($A22="","",[1]!thsiFinD("ths_adjustment_nv_fund",E$3,$A22)) | F22: =IF($A22="","",[1]!thsiFinD("ths_adjustment_nv_fund",F$3,$A22)) | G22: =IF($A22="","",[1]!thsiFinD("ths_adjustment_nv_fund",G$3,$A22)) | H22: =IF($A22="","",[1]!thsiFinD("ths_adjustment_nv_fund",H$3,$A22)) | I22: =IF($A22="","",[1]!thsiFinD("ths_adjustment_nv_fund",I$3,$A22)) | ... X22: =IF($A22="","",[1]!thsiFinD("ths_adjustment_nv_fund",X$3,$A22))
B23: =IF($A23="","",[1]!thsiFinD("ths_adjustment_nv_fund",B$3,$A23)) | C23: =IF($A23="","",[1]!thsiFinD("ths_adjustment_nv_fund",C$3,$A23)) | D23: =IF($A23="","",[1]!thsiFinD("ths_adjustment_nv_fund",D$3,$A23)) | E23: =IF($A23="","",[1]!thsiFinD("ths_adjustment_nv_fund",E$3,$A23)) | F23: =IF($A23="","",[1]!thsiFinD("ths_adjustment_nv_fund",F$3,$A23)) | G23: =IF($A23="","",[1]!thsiFinD("ths_adjustment_nv_fund",G$3,$A23)) | H23: =IF($A23="","",[1]!thsiFinD("ths_adjustment_nv_fund",H$3,$A23)) | I23: =IF($A23="","",[1]!thsiFinD("ths_adjustment_nv_fund",I$3,$A23)) | ... X23: =IF($A23="","",[1]!thsiFinD("ths_adjustment_nv_fund",X$3,$A23))
B24: =IF($A24="","",[1]!thsiFinD("ths_adjustment_nv_fund",B$3,$A24)) | C24: =IF($A24="","",[1]!thsiFinD("ths_adjustment_nv_fund",C$3,$A24)) | D24: =IF($A24="","",[1]!thsiFinD("ths_adjustment_nv_fund",D$3,$A24)) | E24: =IF($A24="","",[1]!thsiFinD("ths_adjustment_nv_fund",E$3,$A24)) | F24: =IF($A24="","",[1]!thsiFinD("ths_adjustment_nv_fund",F$3,$A24)) | G24: =IF($A24="","",[1]!thsiFinD("ths_adjustment_nv_fund",G$3,$A24)) | H24: =IF($A24="","",[1]!thsiFinD("ths_adjustment_nv_fund",H$3,$A24)) | I24: =IF($A24="","",[1]!thsiFinD("ths_adjustment_nv_fund",I$3,$A24)) | ... X24: =IF($A24="","",[1]!thsiFinD("ths_adjustment_nv_fund",X$3,$A24))
B25: =IF($A25="","",[1]!thsiFinD("ths_adjustment_nv_fund",B$3,$A25)) | C25: =IF($A25="","",[1]!thsiFinD("ths_adjustment_nv_fund",C$3,$A25)) | D25: =IF($A25="","",[1]!thsiFinD("ths_adjustment_nv_fund",D$3,$A25)) | E25: =IF($A25="","",[1]!thsiFinD("ths_adjustment_nv_fund",E$3,$A25)) | F25: =IF($A25="","",[1]!thsiFinD("ths_adjustment_nv_fund",F$3,$A25)) | G25: =IF($A25="","",[1]!thsiFinD("ths_adjustment_nv_fund",G$3,$A25)) | H25: =IF($A25="","",[1]!thsiFinD("ths_adjustment_nv_fund",H$3,$A25)) | I25: =IF($A25="","",[1]!thsiFinD("ths_adjustment_nv_fund",I$3,$A25)) | ... X25: =IF($A25="","",[1]!thsiFinD("ths_adjustment_nv_fund",X$3,$A25))
B26: =IF($A26="","",[1]!thsiFinD("ths_adjustment_nv_fund",B$3,$A26)) | C26: =IF($A26="","",[1]!thsiFinD("ths_adjustment_nv_fund",C$3,$A26)) | D26: =IF($A26="","",[1]!thsiFinD("ths_adjustment_nv_fund",D$3,$A26)) | E26: =IF($A26="","",[1]!thsiFinD("ths_adjustment_nv_fund",E$3,$A26)) | F26: =IF($A26="","",[1]!thsiFinD("ths_adjustment_nv_fund",F$3,$A26)) | G26: =IF($A26="","",[1]!thsiFinD("ths_adjustment_nv_fund",G$3,$A26)) | H26: =IF($A26="","",[1]!thsiFinD("ths_adjustment_nv_fund",H$3,$A26)) | I26: =IF($A26="","",[1]!thsiFinD("ths_adjustment_nv_fund",I$3,$A26)) | ... X26: =IF($A26="","",[1]!thsiFinD("ths_adjustment_nv_fund",X$3,$A26))
B27: =IF($A27="","",[1]!thsiFinD("ths_adjustment_nv_fund",B$3,$A27)) | C27: =IF($A27="","",[1]!thsiFinD("ths_adjustment_nv_fund",C$3,$A27)) | D27: =IF($A27="","",[1]!thsiFinD("ths_adjustment_nv_fund",D$3,$A27)) | E27: =IF($A27="","",[1]!thsiFinD("ths_adjustment_nv_fund",E$3,$A27)) | F27: =IF($A27="","",[1]!thsiFinD("ths_adjustment_nv_fund",F$3,$A27)) | G27: =IF($A27="","",[1]!thsiFinD("ths_adjustment_nv_fund",G$3,$A27)) | H27: =IF($A27="","",[1]!thsiFinD("ths_adjustment_nv_fund",H$3,$A27)) | I27: =IF($A27="","",[1]!thsiFinD("ths_adjustment_nv_fund",I$3,$A27)) | ... X27: =IF($A27="","",[1]!thsiFinD("ths_adjustment_nv_fund",X$3,$A27))
B28: =IF($A28="","",[1]!thsiFinD("ths_adjustment_nv_fund",B$3,$A28)) | C28: =IF($A28="","",[1]!thsiFinD("ths_adjustment_nv_fund",C$3,$A28)) | D28: =IF($A28="","",[1]!thsiFinD("ths_adjustment_nv_fund",D$3,$A28)) | E28: =IF($A28="","",[1]!thsiFinD("ths_adjustment_nv_fund",E$3,$A28)) | F28: =IF($A28="","",[1]!thsiFinD("ths_adjustment_nv_fund",F$3,$A28)) | G28: =IF($A28="","",[1]!thsiFinD("ths_adjustment_nv_fund",G$3,$A28)) | H28: =IF($A28="","",[1]!thsiFinD("ths_adjustment_nv_fund",H$3,$A28)) | I28: =IF($A28="","",[1]!thsiFinD("ths_adjustment_nv_fund",I$3,$A28)) | ... X28: =IF($A28="","",[1]!thsiFinD("ths_adjustment_nv_fund",X$3,$A28))
... B60: =IF($A60="","",[1]!thsiFinD("ths_adjustment_nv_fund",B$3,$A60)) | C60: =IF($A60="","",[1]!thsiFinD("ths_adjustment_nv_fund",C$3,$A60)) | D60: =IF($A60="","",[1]!thsiFinD("ths_adjustment_nv_fund",D$3,$A60)) | E60: =IF($A60="","",[1]!thsiFinD("ths_adjustment_nv_fund",E$3,$A60)) | F60: =IF($A60="","",[1]!thsiFinD("ths_adjustment_nv_fund",F$3,$A60)) | G60: =IF($A60="","",[1]!thsiFinD("ths_adjustment_nv_fund",G$3,$A60)) | H60: =IF($A60="","",[1]!thsiFinD("ths_adjustment_nv_fund",H$3,$A60)) | I60: =IF($A60="","",[1]!thsiFinD("ths_adjustment_nv_fund",I$3,$A60)) | ... X60: =IF($A60="","",[1]!thsiFinD("ths_adjustment_nv_fund",X$3,$A60))

Sheet 实盘组合净值
A1: 组合净值（实盘）· 各组合自起始日买入持有逐日计算
B3: 组合 产业趋势 | E3: 组合 产业趋势基石 | H3: 组合 产业趋势2号 | K3: 组合 10-90 | N3: 组合 10-90基石 | Q3: 组合 30-70
A4: 日期 | B4: 净值 | C4: 日收益 | D4: 回撤 | E4: 净值 | F4: 日收益 | G4: 回撤 | H4: 净值 | I4: 日收益 | J4: 回撤 | K4: 净值 | L4: 日收益 | M4: 回撤 | N4: 净值 | O4: 日收益 | P4: 回撤 | Q4: 净值 | R4: 日收益 | S4: 回撤
A5: =IF('实盘净值数据(iFinD公式)'!A5="","",'实盘净值数据(iFinD公式)'!A5) | B5: =IF(OR((ROW()-1)<6,'实盘净值数据(iFinD公式)'!$A5="",'实盘净值数据(iFinD公式)'!$B5=""),"",SUMPRODUCT(实盘持仓配置!$B$4:$X$4,'实盘净值数据(iFinD公式)'!$B5:$X5/'实盘净值数据(iFinD公式)'!$B$6:$X$6)*(1-实盘持仓配置!$Z$4)^(('实盘净值数据(iFinD公式)'!$A5-'实盘净值数据(iFinD公式)'!$A$6)/365)) | D5: =IF(B5="","",B5/MAX(B$5:B5)-1) | E5: 1 | G5: =IF(E5="","",E5/MAX(E$5:E5)-1) | H5: =IF(OR((ROW()-1)<7,'实盘净值数据(iFinD公式)'!$A5="",'实盘净值数据(iFinD公式)'!$B5=""),"",SUMPRODUCT(实盘持仓配置!$B$6:$X$6,'实盘净值数据(iFinD公式)'!$B5:$X5/'实盘净值数据(iFinD公式)'!$B$7:$X$7)*(1-实盘持仓配置!$Z$6)^(('实盘净值数据(iFinD公式)'!$A5-'实盘净值数据(iFinD公式)'!$A$7)/365)) | J5: =IF(H5="","",H5/MAX(H$5:H5)-1) | K5: =IF(OR((ROW()-1)<8,'实盘净值数据(iFinD公式)'!$A5="",'实盘净值数据(iFinD公式)'!$B5=""),"",SUMPRODUCT(实盘持仓配置!$B$7:$X$7,'实盘净值数据(iFinD公式)'!$B5:$X5/'实盘净值数据(iFinD公式)'!$B$8:$X$8)*(1-实盘持仓配置!$Z$7)^(('实盘净值数据(iFinD公式)'!$A5-'实盘净值数据(iFinD公式)'!$A$8)/365)) | M5: =IF(K5="","",K5/MAX(K$5:K5)-1) | N5: 1 | P5: =IF(N5="","",N5/MAX(N$5:N5)-1) | Q5: =IF(OR((ROW()-1)<8,'实盘净值数据(iFinD公式)'!$A5="",'实盘净值数据(iFinD公式)'!$B5=""),"",SUMPRODUCT(实盘持仓配置!$B$9:$X$9,'实盘净值数据(iFinD公式)'!$B5:$X5/'实盘净值数据(iFinD公式)'!$B$8:$X$8)*(1-实盘持仓配置!$Z$9)^(('实盘净值数据(iFinD公式)'!$A5-'实盘净值数据(iFinD公式)'!$A$8)/365)) | S5: =IF(Q5="","",Q5/MAX(Q$5:Q5)-1)
A6: =IF('实盘净值数据(iFinD公式)'!A6="","",'实盘净值数据(iFinD公式)'!A6) | B6: 1 | C6: =IF(OR(B5="",'实盘净值数据(iFinD公式)'!$A6="",'实盘净值数据(iFinD公式)'!$B6=""),"",(SUMPRODUCT(实盘持仓配置!$B$4:$X$4,'实盘净值数据(iFinD公式)'!$B5:$X5/'实盘净值数据(iFinD公式)'!$B$6:$X$6,'实盘净值数据(iFinD公式)'!$B6:$X6/'实盘净值数据(iFinD公式)'!$B5:$X5)/SUMPRODUCT(实盘持仓配置!$B$4:$X$4,'实盘净值数据(iFinD公式)'!$B5:$X5/'实盘净值数据(iFinD公式)'!$B$6:$X$6))*(1-实盘持仓配置!$Z$4)^(('实盘净值数据(iFinD公式)'!$A6-'实盘净值数据(iFinD公式)'!$A5)/365)-1) | D6: =IF(B6="","",B6/MAX(B$5:B6)-1) | E6: =IF(OR((ROW()-1)<5,'实盘净值数据(iFinD公式)'!$A6="",'实盘净值数据(iFinD公式)'!$B6=""),"",SUMPRODUCT(实盘持仓配置!$B$5:$X$5,'实盘净值数据(iFinD公式)'!$B6:$X6/'实盘净值数据(iFinD公式)'!$B$5:$X$5)*(1-实盘持仓配置!$Z$5)^(('实盘净值数据(iFinD公式)'!$A6-'实盘净值数据(iFinD公式)'!$A$5)/365)) | F6: =IF(OR(E5="",'实盘净值数据(iFinD公式)'!$A6="",'实盘净值数据(iFinD公式)'!$B6=""),"",(SUMPRODUCT(实盘持仓配置!$B$5:$X$5,'实盘净值数据(iFinD公式)'!$B5:$X5/'实盘净值数据(iFinD公式)'!$B$5:$X$5,'实盘净值数据(iFinD公式)'!$B6:$X6/'实盘净值数据(iFinD公式)'!$B5:$X5)/SUMPRODUCT(实盘持仓配置!$B$5:$X$5,'实盘净值数据(iFinD公式)'!$B5:$X5/'实盘净值数据(iFinD公式)'!$B$5:$X$5))*(1-实盘持仓配置!$Z$5)^(('实盘净值数据(iFinD公式)'!$A6-'实盘净值数据(iFinD公式)'!$A5)/365)-1) | G6: =IF(E6="","",E6/MAX(E$5:E6)-1) | H6: =IF(OR((ROW()-1)<7,'实盘净值数据(iFinD公式)'!$A6="",'实盘净值数据(iFinD公式)'!$B6=""),"",SUMPRODUCT(实盘持仓配置!$B$6:$X$6,'实盘净值数据(iFinD公式)'!$B6:$X6/'实盘净值数据(iFinD公式)'!$B$7:$X$7)*(1-实盘持仓配置!$Z$6)^(('实盘净值数据(iFinD公式)'!$A6-'实盘净值数据(iFinD公式)'!$A$7)/365)) | I6: =IF(OR(H5="",'实盘净值数据(iFinD公式)'!$A6="",'实盘净值数据(iFinD公式)'!$B6=""),"",(SUMPRODUCT(实盘持仓配置!$B$6:$X$6,'实盘净值数据(iFinD公式)'!$B5:$X5/'实盘净值数据(iFinD公式)'!$B$7:$X$7,'实盘净值数据(iFinD公式)'!$B6:$X6/'实盘净值数据(iFinD公式)'!$B5:$X5)/SUMPRODUCT(实盘持仓配置!$B$6:$X$6,'实盘净值数据(iFinD公式)'!$B5:$X5/'实盘净值数据(iFinD公式)'!$B$7:$X$7))*(1-实盘持仓配置!$Z$6)^(('实盘净值数据(iFinD公式)'!$A6-'实盘净值数据(iFinD公式)'!$A5)/365)-1) | J6: =IF(H6="","",H6/MAX(H$5:H6)-1) | K6: =IF(OR((ROW()-1)<8,'实盘净值数据(iFinD公式)'!$A6="",'实盘净值数据(iFinD公式)'!$B6=""),"",SUMPRODUCT(实盘持仓配置!$B$7:$X$7,'实盘净值数据(iFinD公式)'!$B6:$X6/'实盘净值数据(iFinD公式)'!$B$8:$X$8)*(1-实盘持仓配置!$Z$7)^(('实盘净值数据(iFinD公式)'!$A6-'实盘净值数据(iFinD公式)'!$A$8)/365)) | L6: =IF(OR(K5="",'实盘净值数据(iFinD公式)'!$A6="",'实盘净值数据(iFinD公式)'!$B6=""),"",(SUMPRODUCT(实盘持仓配置!$B$7:$X$7,'实盘净值数据(iFinD公式)'!$B5:$X5/'实盘净值数据(iFinD公式)'!$B$8:$X$8,'实盘净值数据(iFinD公式)'!$B6:$X6/'实盘净值数据(iFinD公式)'!$B5:$X5)/SUMPRODUCT(实盘持仓配置!$B$7:$X$7,'实盘净值数据(iFinD公式)'!$B5:$X5/'实盘净值数据(iFinD公式)'!$B$8:$X$8))*(1-实盘持仓配置!$Z$7)^(('实盘净值数据(iFinD公式)'!$A6-'实盘净值数据(iFinD公式)'!$A5)/365)-1) | M6: =IF(K6="","",K6/MAX(K$5:K6)-1) | N6: =IF(OR((ROW()-1)<5,'实盘净值数据(iFinD公式)'!$A6="",'实盘净值数据(iFinD公式)'!$B6=""),"",SUMPRODUCT(实盘持仓配置!$B$8:$X$8,'实盘净值数据(iFinD公式)'!$B6:$X6/'实盘净值数据(iFinD公式)'!$B$5:$X$5)*(1-实盘持仓配置!$Z$8)^(('实盘净值数据(iFinD公式)'!$A6-'实盘净值数据(iFinD公式)'!$A$5)/365)) | O6: =IF(OR(N5="",'实盘净值数据(iFinD公式)'!$A6="",'实盘净值数据(iFinD公式)'!$B6=""),"",(SUMPRODUCT(实盘持仓配置!$B$8:$X$8,'实盘净值数据(iFinD公式)'!$B5:$X5/'实盘净值数据(iFinD公式)'!$B$5:$X$5,'实盘净值数据(iFinD公式)'!$B6:$X6/'实盘净值数据(iFinD公式)'!$B5:$X5)/SUMPRODUCT(实盘持仓配置!$B$8:$X$8,'实盘净值数据(iFinD公式)'!$B5:$X5/'实盘净值数据(iFinD公式)'!$B$5:$X$5))*(1-实盘持仓配置!$Z$8)^(('实盘净值数据(iFinD公式)'!$A6-'实盘净值数据(iFinD公式)'!$A5)/365)-1) | P6: =IF(N6="","",N6/MAX(N$5:N6)-1) | Q6: =IF(OR((ROW()-1)<8,'实盘净值数据(iFinD公式)'!$A6="",'实盘净值数据(iFinD公式)'!$B6=""),"",SUMPRODUCT(实盘持仓配置!$B$9:$X$9,'实盘净值数据(iFinD公式)'!$B6:$X6/'实盘净值数据(iFinD公式)'!$B$8:$X$8)*(1-实盘持仓配置!$Z$9)^(('实盘净值数据(iFinD公式)'!$A6-'实盘净值数据(iFinD公式)'!$A$8)/365)) | R6: =IF(OR(Q5="",'实盘净值数据(iFinD公式)'!$A6="",'实盘净值数据(iFinD公式)'!$B6=""),"",(SUMPRODUCT(实盘持仓配置!$B$9:$X$9,'实盘净值数据(iFinD公式)'!$B5:$X5/'实盘净值数据(iFinD公式)'!$B$8:$X$8,'实盘净值数据(iFinD公式)'!$B6:$X6/'实盘净值数据(iFinD公式)'!$B5:$X5)/SUMPRODUCT(实盘持仓配置!$B$9:$X$9,'实盘净值数据(iFinD公式)'!$B5:$X5/'实盘净值数据(iFinD公式)'!$B$8:$X$8))*(1-实盘持仓配置!$Z$9)^(('实盘净值数据(iFinD公式)'!$A6-'实盘净值数据(iFinD公式)'!$A5)/365)-1) | S6: =IF(Q6="","",Q6/MAX(Q$5:Q6)-1)
A7: =IF('实盘净值数据(iFinD公式)'!A7="","",'实盘净值数据(iFinD公式)'!A7) | B7: =IF(OR((ROW()-1)<6,'实盘净值数据(iFinD公式)'!$A7="",'实盘净值数据(iFinD公式)'!$B7=""),"",SUMPRODUCT(实盘持仓配置!$B$4:$X$4,'实盘净值数据(iFinD公式)'!$B7:$X7/'实盘净值数据(iFinD公式)'!$B$6:$X$6)*(1-实盘持仓配置!$Z$4)^(('实盘净值数据(iFinD公式)'!$A7-'实盘净值数据(iFinD公式)'!$A$6)/365)) | C7: =IF(OR(B6="",'实盘净值数据(iFinD公式)'!$A7="",'实盘净值数据(iFinD公式)'!$B7=""),"",(SUMPRODUCT(实盘持仓配置!$B$4:$X$4,'实盘净值数据(iFinD公式)'!$B6:$X6/'实盘净值数据(iFinD公式)'!$B$6:$X$6,'实盘净值数据(iFinD公式)'!$B7:$X7/'实盘净值数据(iFinD公式)'!$B6:$X6)/SUMPRODUCT(实盘持仓配置!$B$4:$X$4,'实盘净值数据(iFinD公式)'!$B6:$X6/'实盘净值数据(iFinD公式)'!$B$6:$X$6))*(1-实盘持仓配置!$Z$4)^(('实盘净值数据(iFinD公式)'!$A7-'实盘净值数据(iFinD公式)'!$A6)/365)-1) | D7: =IF(B7="","",B7/MAX(B$5:B7)-1) | E7: =IF(OR((ROW()-1)<5,'实盘净值数据(iFinD公式)'!$A7="",'实盘净值数据(iFinD公式)'!$B7=""),"",SUMPRODUCT(实盘持仓配置!$B$5:$X$5,'实盘净值数据(iFinD公式)'!$B7:$X7/'实盘净值数据(iFinD公式)'!$B$5:$X$5)*(1-实盘持仓配置!$Z$5)^(('实盘净值数据(iFinD公式)'!$A7-'实盘净值数据(iFinD公式)'!$A$5)/365)) | F7: =IF(OR(E6="",'实盘净值数据(iFinD公式)'!$A7="",'实盘净值数据(iFinD公式)'!$B7=""),"",(SUMPRODUCT(实盘持仓配置!$B$5:$X$5,'实盘净值数据(iFinD公式)'!$B6:$X6/'实盘净值数据(iFinD公式)'!$B$5:$X$5,'实盘净值数据(iFinD公式)'!$B7:$X7/'实盘净值数据(iFinD公式)'!$B6:$X6)/SUMPRODUCT(实盘持仓配置!$B$5:$X$5,'实盘净值数据(iFinD公式)'!$B6:$X6/'实盘净值数据(iFinD公式)'!$B$5:$X$5))*(1-实盘持仓配置!$Z$5)^(('实盘净值数据(iFinD公式)'!$A7-'实盘净值数据(iFinD公式)'!$A6)/365)-1) | G7: =IF(E7="","",E7/MAX(E$5:E7)-1) | H7: 1 | I7: =IF(OR(H6="",'实盘净值数据(iFinD公式)'!$A7="",'实盘净值数据(iFinD公式)'!$B7=""),"",(SUMPRODUCT(实盘持仓配置!$B$6:$X$6,'实盘净值数据(iFinD公式)'!$B6:$X6/'实盘净值数据(iFinD公式)'!$B$7:$X$7,'实盘净值数据(iFinD公式)'!$B7:$X7/'实盘净值数据(iFinD公式)'!$B6:$X6)/SUMPRODUCT(实盘持仓配置!$B$6:$X$6,'实盘净值数据(iFinD公式)'!$B6:$X6/'实盘净值数据(iFinD公式)'!$B$7:$X$7))*(1-实盘持仓配置!$Z$6)^(('实盘净值数据(iFinD公式)'!$A7-'实盘净值数据(iFinD公式)'!$A6)/365)-1) | J7: =IF(H7="","",H7/MAX(H$5:H7)-1) | K7: =IF(OR((ROW()-1)<8,'实盘净值数据(iFinD公式)'!$A7="",'实盘净值数据(iFinD公式)'!$B7=""),"",SUMPRODUCT(实盘持仓配置!$B$7:$X$7,'实盘净值数据(iFinD公式)'!$B7:$X7/'实盘净值数据(iFinD公式)'!$B$8:$X$8)*(1-实盘持仓配置!$Z$7)^(('实盘净值数据(iFinD公式)'!$A7-'实盘净值数据(iFinD公式)'!$A$8)/365)) | L7: =IF(OR(K6="",'实盘净值数据(iFinD公式)'!$A7="",'实盘净值数据(iFinD公式)'!$B7=""),"",(SUMPRODUCT(实盘持仓配置!$B$7:$X$7,'实盘净值数据(iFinD公式)'!$B6:$X6/'实盘净值数据(iFinD公式)'!$B$8:$X$8,'实盘净值数据(iFinD公式)'!$B7:$X7/'实盘净值数据(iFinD公式)'!$B6:$X6)/SUMPRODUCT(实盘持仓配置!$B$7:$X$7,'实盘净值数据(iFinD公式)'!$B6:$X6/'实盘净值数据(iFinD公式)'!$B$8:$X$8))*(1-实盘持仓配置!$Z$7)^(('实盘净值数据(iFinD公式)'!$A7-'实盘净值数据(iFinD公式)'!$A6)/365)-1) | M7: =IF(K7="","",K7/MAX(K$5:K7)-1) | N7: =IF(OR((ROW()-1)<5,'实盘净值数据(iFinD公式)'!$A7="",'实盘净值数据(iFinD公式)'!$B7=""),"",SUMPRODUCT(实盘持仓配置!$B$8:$X$8,'实盘净值数据(iFinD公式)'!$B7:$X7/'实盘净值数据(iFinD公式)'!$B$5:$X$5)*(1-实盘持仓配置!$Z$8)^(('实盘净值数据(iFinD公式)'!$A7-'实盘净值数据(iFinD公式)'!$A$5)/365)) | O7: =IF(OR(N6="",'实盘净值数据(iFinD公式)'!$A7="",'实盘净值数据(iFinD公式)'!$B7=""),"",(SUMPRODUCT(实盘持仓配置!$B$8:$X$8,'实盘净值数据(iFinD公式)'!$B6:$X6/'实盘净值数据(iFinD公式)'!$B$5:$X$5,'实盘净值数据(iFinD公式)'!$B7:$X7/'实盘净值数据(iFinD公式)'!$B6:$X6)/SUMPRODUCT(实盘持仓配置!$B$8:$X$8,'实盘净值数据(iFinD公式)'!$B6:$X6/'实盘净值数据(iFinD公式)'!$B$5:$X$5))*(1-实盘持仓配置!$Z$8)^(('实盘净值数据(iFinD公式)'!$A7-'实盘净值数据(iFinD公式)'!$A6)/365)-1) | P7: =IF(N7="","",N7/MAX(N$5:N7)-1) | Q7: =IF(OR((ROW()-1)<8,'实盘净值数据(iFinD公式)'!$A7="",'实盘净值数据(iFinD公式)'!$B7=""),"",SUMPRODUCT(实盘持仓配置!$B$9:$X$9,'实盘净值数据(iFinD公式)'!$B7:$X7/'实盘净值数据(iFinD公式)'!$B$8:$X$8)*(1-实盘持仓配置!$Z$9)^(('实盘净值数据(iFinD公式)'!$A7-'实盘净值数据(iFinD公式)'!$A$8)/365)) | R7: =IF(OR(Q6="",'实盘净值数据(iFinD公式)'!$A7="",'实盘净值数据(iFinD公式)'!$B7=""),"",(SUMPRODUCT(实盘持仓配置!$B$9:$X$9,'实盘净值数据(iFinD公式)'!$B6:$X6/'实盘净值数据(iFinD公式)'!$B$8:$X$8,'实盘净值数据(iFinD公式)'!$B7:$X7/'实盘净值数据(iFinD公式)'!$B6:$X6)/SUMPRODUCT(实盘持仓配置!$B$9:$X$9,'实盘净值数据(iFinD公式)'!$B6:$X6/'实盘净值数据(iFinD公式)'!$B$8:$X$8))*(1-实盘持仓配置!$Z$9)^(('实盘净值数据(iFinD公式)'!$A7-'实盘净值数据(iFinD公式)'!$A6)/365)-1) | S7: =IF(Q7="","",Q7/MAX(Q$5:Q7)-1)
A8: =IF('实盘净值数据(iFinD公式)'!A8="","",'实盘净值数据(iFinD公式)'!A8) | B8: =IF(OR((ROW()-1)<6,'实盘净值数据(iFinD公式)'!$A8="",'实盘净值数据(iFinD公式)'!$B8=""),"",SUMPRODUCT(实盘持仓配置!$B$4:$X$4,'实盘净值数据(iFinD公式)'!$B8:$X8/'实盘净值数据(iFinD公式)'!$B$6:$X$6)*(1-实盘持仓配置!$Z$4)^(('实盘净值数据(iFinD公式)'!$A8-'实盘净值数据(iFinD公式)'!$A$6)/365)) | C8: =IF(OR(B7="",'实盘净值数据(iFinD公式)'!$A8="",'实盘净值数据(iFinD公式)'!$B8=""),"",(SUMPRODUCT(实盘持仓配置!$B$4:$X$4,'实盘净值数据(iFinD公式)'!$B7:$X7/'实盘净值数据(iFinD公式)'!$B$6:$X$6,'实盘净值数据(iFinD公式)'!$B8:$X8/'实盘净值数据(iFinD公式)'!$B7:$X7)/SUMPRODUCT(实盘持仓配置!$B$4:$X$4,'实盘净值数据(iFinD公式)'!$B7:$X7/'实盘净值数据(iFinD公式)'!$B$6:$X$6))*(1-实盘持仓配置!$Z$4)^(('实盘净值数据(iFinD公式)'!$A8-'实盘净值数据(iFinD公式)'!$A7)/365)-1) | D8: =IF(B8="","",B8/MAX(B$5:B8)-1) | E8: =IF(OR((ROW()-1)<5,'实盘净值数据(iFinD公式)'!$A8="",'实盘净值数据(iFinD公式)'!$B8=""),"",SUMPRODUCT(实盘持仓配置!$B$5:$X$5,'实盘净值数据(iFinD公式)'!$B8:$X8/'实盘净值数据(iFinD公式)'!$B$5:$X$5)*(1-实盘持仓配置!$Z$5)^(('实盘净值数据(iFinD公式)'!$A8-'实盘净值数据(iFinD公式)'!$A$5)/365)) | F8: =IF(OR(E7="",'实盘净值数据(iFinD公式)'!$A8="",'实盘净值数据(iFinD公式)'!$B8=""),"",(SUMPRODUCT(实盘持仓配置!$B$5:$X$5,'实盘净值数据(iFinD公式)'!$B7:$X7/'实盘净值数据(iFinD公式)'!$B$5:$X$5,'实盘净值数据(iFinD公式)'!$B8:$X8/'实盘净值数据(iFinD公式)'!$B7:$X7)/SUMPRODUCT(实盘持仓配置!$B$5:$X$5,'实盘净值数据(iFinD公式)'!$B7:$X7/'实盘净值数据(iFinD公式)'!$B$5:$X$5))*(1-实盘持仓配置!$Z$5)^(('实盘净值数据(iFinD公式)'!$A8-'实盘净值数据(iFinD公式)'!$A7)/365)-1) | G8: =IF(E8="","",E8/MAX(E$5:E8)-1) | H8: =IF(OR((ROW()-1)<7,'实盘净值数据(iFinD公式)'!$A8="",'实盘净值数据(iFinD公式)'!$B8=""),"",SUMPRODUCT(实盘持仓配置!$B$6:$X$6,'实盘净值数据(iFinD公式)'!$B8:$X8/'实盘净值数据(iFinD公式)'!$B$7:$X$7)*(1-实盘持仓配置!$Z$6)^(('实盘净值数据(iFinD公式)'!$A8-'实盘净值数据(iFinD公式)'!$A$7)/365)) | I8: =IF(OR(H7="",'实盘净值数据(iFinD公式)'!$A8="",'实盘净值数据(iFinD公式)'!$B8=""),"",(SUMPRODUCT(实盘持仓配置!$B$6:$X$6,'实盘净值数据(iFinD公式)'!$B7:$X7/'实盘净值数据(iFinD公式)'!$B$7:$X$7,'实盘净值数据(iFinD公式)'!$B8:$X8/'实盘净值数据(iFinD公式)'!$B7:$X7)/SUMPRODUCT(实盘持仓配置!$B$6:$X$6,'实盘净值数据(iFinD公式)'!$B7:$X7/'实盘净值数据(iFinD公式)'!$B$7:$X$7))*(1-实盘持仓配置!$Z$6)^(('实盘净值数据(iFinD公式)'!$A8-'实盘净值数据(iFinD公式)'!$A7)/365)-1) | J8: =IF(H8="","",H8/MAX(H$5:H8)-1) | K8: 1 | L8: =IF(OR(K7="",'实盘净值数据(iFinD公式)'!$A8="",'实盘净值数据(iFinD公式)'!$B8=""),"",(SUMPRODUCT(实盘持仓配置!$B$7:$X$7,'实盘净值数据(iFinD公式)'!$B7:$X7/'实盘净值数据(iFinD公式)'!$B$8:$X$8,'实盘净值数据(iFinD公式)'!$B8:$X8/'实盘净值数据(iFinD公式)'!$B7:$X7)/SUMPRODUCT(实盘持仓配置!$B$7:$X$7,'实盘净值数据(iFinD公式)'!$B7:$X7/'实盘净值数据(iFinD公式)'!$B$8:$X$8))*(1-实盘持仓配置!$Z$7)^(('实盘净值数据(iFinD公式)'!$A8-'实盘净值数据(iFinD公式)'!$A7)/365)-1) | M8: =IF(K8="","",K8/MAX(K$5:K8)-1) | N8: =IF(OR((ROW()-1)<5,'实盘净值数据(iFinD公式)'!$A8="",'实盘净值数据(iFinD公式)'!$B8=""),"",SUMPRODUCT(实盘持仓配置!$B$8:$X$8,'实盘净值数据(iFinD公式)'!$B8:$X8/'实盘净值数据(iFinD公式)'!$B$5:$X$5)*(1-实盘持仓配置!$Z$8)^(('实盘净值数据(iFinD公式)'!$A8-'实盘净值数据(iFinD公式)'!$A$5)/365)) | O8: =IF(OR(N7="",'实盘净值数据(iFinD公式)'!$A8="",'实盘净值数据(iFinD公式)'!$B8=""),"",(SUMPRODUCT(实盘持仓配置!$B$8:$X$8,'实盘净值数据(iFinD公式)'!$B7:$X7/'实盘净值数据(iFinD公式)'!$B$5:$X$5,'实盘净值数据(iFinD公式)'!$B8:$X8/'实盘净值数据(iFinD公式)'!$B7:$X7)/SUMPRODUCT(实盘持仓配置!$B$8:$X$8,'实盘净值数据(iFinD公式)'!$B7:$X7/'实盘净值数据(iFinD公式)'!$B$5:$X$5))*(1-实盘持仓配置!$Z$8)^(('实盘净值数据(iFinD公式)'!$A8-'实盘净值数据(iFinD公式)'!$A7)/365)-1) | P8: =IF(N8="","",N8/MAX(N$5:N8)-1) | Q8: 1 | R8: =IF(OR(Q7="",'实盘净值数据(iFinD公式)'!$A8="",'实盘净值数据(iFinD公式)'!$B8=""),"",(SUMPRODUCT(实盘持仓配置!$B$9:$X$9,'实盘净值数据(iFinD公式)'!$B7:$X7/'实盘净值数据(iFinD公式)'!$B$8:$X$8,'实盘净值数据(iFinD公式)'!$B8:$X8/'实盘净值数据(iFinD公式)'!$B7:$X7)/SUMPRODUCT(实盘持仓配置!$B$9:$X$9,'实盘净值数据(iFinD公式)'!$B7:$X7/'实盘净值数据(iFinD公式)'!$B$8:$X$8))*(1-实盘持仓配置!$Z$9)^(('实盘净值数据(iFinD公式)'!$A8-'实盘净值数据(iFinD公式)'!$A7)/365)-1) | S8: =IF(Q8="","",Q8/MAX(Q$5:Q8)-1)
A9: =IF('实盘净值数据(iFinD公式)'!A9="","",'实盘净值数据(iFinD公式)'!A9) | B9: =IF(OR((ROW()-1)<6,'实盘净值数据(iFinD公式)'!$A9="",'实盘净值数据(iFinD公式)'!$B9=""),"",SUMPRODUCT(实盘持仓配置!$B$4:$X$4,'实盘净值数据(iFinD公式)'!$B9:$X9/'实盘净值数据(iFinD公式)'!$B$6:$X$6)*(1-实盘持仓配置!$Z$4)^(('实盘净值数据(iFinD公式)'!$A9-'实盘净值数据(iFinD公式)'!$A$6)/365)) | C9: =IF(OR(B8="",'实盘净值数据(iFinD公式)'!$A9="",'实盘净值数据(iFinD公式)'!$B9=""),"",(SUMPRODUCT(实盘持仓配置!$B$4:$X$4,'实盘净值数据(iFinD公式)'!$B8:$X8/'实盘净值数据(iFinD公式)'!$B$6:$X$6,'实盘净值数据(iFinD公式)'!$B9:$X9/'实盘净值数据(iFinD公式)'!$B8:$X8)/SUMPRODUCT(实盘持仓配置!$B$4:$X$4,'实盘净值数据(iFinD公式)'!$B8:$X8/'实盘净值数据(iFinD公式)'!$B$6:$X$6))*(1-实盘持仓配置!$Z$4)^(('实盘净值数据(iFinD公式)'!$A9-'实盘净值数据(iFinD公式)'!$A8)/365)-1) | D9: =IF(B9="","",B9/MAX(B$5:B9)-1) | E9: =IF(OR((ROW()-1)<5,'实盘净值数据(iFinD公式)'!$A9="",'实盘净值数据(iFinD公式)'!$B9=""),"",SUMPRODUCT(实盘持仓配置!$B$5:$X$5,'实盘净值数据(iFinD公式)'!$B9:$X9/'实盘净值数据(iFinD公式)'!$B$5:$X$5)*(1-实盘持仓配置!$Z$5)^(('实盘净值数据(iFinD公式)'!$A9-'实盘净值数据(iFinD公式)'!$A$5)/365)) | F9: =IF(OR(E8="",'实盘净值数据(iFinD公式)'!$A9="",'实盘净值数据(iFinD公式)'!$B9=""),"",(SUMPRODUCT(实盘持仓配置!$B$5:$X$5,'实盘净值数据(iFinD公式)'!$B8:$X8/'实盘净值数据(iFinD公式)'!$B$5:$X$5,'实盘净值数据(iFinD公式)'!$B9:$X9/'实盘净值数据(iFinD公式)'!$B8:$X8)/SUMPRODUCT(实盘持仓配置!$B$5:$X$5,'实盘净值数据(iFinD公式)'!$B8:$X8/'实盘净值数据(iFinD公式)'!$B$5:$X$5))*(1-实盘持仓配置!$Z$5)^(('实盘净值数据(iFinD公式)'!$A9-'实盘净值数据(iFinD公式)'!$A8)/365)-1) | G9: =IF(E9="","",E9/MAX(E$5:E9)-1) | H9: =IF(OR((ROW()-1)<7,'实盘净值数据(iFinD公式)'!$A9="",'实盘净值数据(iFinD公式)'!$B9=""),"",SUMPRODUCT(实盘持仓配置!$B$6:$X$6,'实盘净值数据(iFinD公式)'!$B9:$X9/'实盘净值数据(iFinD公式)'!$B$7:$X$7)*(1-实盘持仓配置!$Z$6)^(('实盘净值数据(iFinD公式)'!$A9-'实盘净值数据(iFinD公式)'!$A$7)/365)) | I9: =IF(OR(H8="",'实盘净值数据(iFinD公式)'!$A9="",'实盘净值数据(iFinD公式)'!$B9=""),"",(SUMPRODUCT(实盘持仓配置!$B$6:$X$6,'实盘净值数据(iFinD公式)'!$B8:$X8/'实盘净值数据(iFinD公式)'!$B$7:$X$7,'实盘净值数据(iFinD公式)'!$B9:$X9/'实盘净值数据(iFinD公式)'!$B8:$X8)/SUMPRODUCT(实盘持仓配置!$B$6:$X$6,'实盘净值数据(iFinD公式)'!$B8:$X8/'实盘净值数据(iFinD公式)'!$B$7:$X$7))*(1-实盘持仓配置!$Z$6)^(('实盘净值数据(iFinD公式)'!$A9-'实盘净值数据(iFinD公式)'!$A8)/365)-1) | J9: =IF(H9="","",H9/MAX(H$5:H9)-1) | K9: =IF(OR((ROW()-1)<8,'实盘净值数据(iFinD公式)'!$A9="",'实盘净值数据(iFinD公式)'!$B9=""),"",SUMPRODUCT(实盘持仓配置!$B$7:$X$7,'实盘净值数据(iFinD公式)'!$B9:$X9/'实盘净值数据(iFinD公式)'!$B$8:$X$8)*(1-实盘持仓配置!$Z$7)^(('实盘净值数据(iFinD公式)'!$A9-'实盘净值数据(iFinD公式)'!$A$8)/365)) | L9: =IF(OR(K8="",'实盘净值数据(iFinD公式)'!$A9="",'实盘净值数据(iFinD公式)'!$B9=""),"",(SUMPRODUCT(实盘持仓配置!$B$7:$X$7,'实盘净值数据(iFinD公式)'!$B8:$X8/'实盘净值数据(iFinD公式)'!$B$8:$X$8,'实盘净值数据(iFinD公式)'!$B9:$X9/'实盘净值数据(iFinD公式)'!$B8:$X8)/SUMPRODUCT(实盘持仓配置!$B$7:$X$7,'实盘净值数据(iFinD公式)'!$B8:$X8/'实盘净值数据(iFinD公式)'!$B$8:$X$8))*(1-实盘持仓配置!$Z$7)^(('实盘净值数据(iFinD公式)'!$A9-'实盘净值数据(iFinD公式)'!$A8)/365)-1) | M9: =IF(K9="","",K9/MAX(K$5:K9)-1) | N9: =IF(OR((ROW()-1)<5,'实盘净值数据(iFinD公式)'!$A9="",'实盘净值数据(iFinD公式)'!$B9=""),"",SUMPRODUCT(实盘持仓配置!$B$8:$X$8,'实盘净值数据(iFinD公式)'!$B9:$X9/'实盘净值数据(iFinD公式)'!$B$5:$X$5)*(1-实盘持仓配置!$Z$8)^(('实盘净值数据(iFinD公式)'!$A9-'实盘净值数据(iFinD公式)'!$A$5)/365)) | O9: =IF(OR(N8="",'实盘净值数据(iFinD公式)'!$A9="",'实盘净值数据(iFinD公式)'!$B9=""),"",(SUMPRODUCT(实盘持仓配置!$B$8:$X$8,'实盘净值数据(iFinD公式)'!$B8:$X8/'实盘净值数据(iFinD公式)'!$B$5:$X$5,'实盘净值数据(iFinD公式)'!$B9:$X9/'实盘净值数据(iFinD公式)'!$B8:$X8)/SUMPRODUCT(实盘持仓配置!$B$8:$X$8,'实盘净值数据(iFinD公式)'!$B8:$X8/'实盘净值数据(iFinD公式)'!$B$5:$X$5))*(1-实盘持仓配置!$Z$8)^(('实盘净值数据(iFinD公式)'!$A9-'实盘净值数据(iFinD公式)'!$A8)/365)-1) | P9: =IF(N9="","",N9/MAX(N$5:N9)-1) | Q9: =IF(OR((ROW()-1)<8,'实盘净值数据(iFinD公式)'!$A9="",'实盘净值数据(iFinD公式)'!$B9=""),"",SUMPRODUCT(实盘持仓配置!$B$9:$X$9,'实盘净值数据(iFinD公式)'!$B9:$X9/'实盘净值数据(iFinD公式)'!$B$8:$X$8)*(1-实盘持仓配置!$Z$9)^(('实盘净值数据(iFinD公式)'!$A9-'实盘净值数据(iFinD公式)'!$A$8)/365)) | R9: =IF(OR(Q8="",'实盘净值数据(iFinD公式)'!$A9="",'实盘净值数据(iFinD公式)'!$B9=""),"",(SUMPRODUCT(实盘持仓配置!$B$9:$X$9,'实盘净值数据(iFinD公式)'!$B8:$X8/'实盘净值数据(iFinD公式)'!$B$8:$X$8,'实盘净值数据(iFinD公式)'!$B9:$X9/'实盘净值数据(iFinD公式)'!$B8:$X8)/SUMPRODUCT(实盘持仓配置!$B$9:$X$9,'实盘净值数据(iFinD公式)'!$B8:$X8/'实盘净值数据(iFinD公式)'!$B$8:$X$8))*(1-实盘持仓配置!$Z$9)^(('实盘净值数据(iFinD公式)'!$A9-'实盘净值数据(iFinD公式)'!$A8)/365)-1) | S9: =IF(Q9="","",Q9/MAX(Q$5:Q9)-1)
A10: =IF('实盘净值数据(iFinD公式)'!A10="","",'实盘净值数据(iFinD公式)'!A10) | B10: =IF(OR((ROW()-1)<6,'实盘净值数据(iFinD公式)'!$A10="",'实盘净值数据(iFinD公式)'!$B10=""),"",SUMPRODUCT(实盘持仓配置!$B$4:$X$4,'实盘净值数据(iFinD公式)'!$B10:$X10/'实盘净值数据(iFinD公式)'!$B$6:$X$6)*(1-实盘持仓配置!$Z$4)^(('实盘净值数据(iFinD公式)'!$A10-'实盘净值数据(iFinD公式)'!$A$6)/365)) | C10: =IF(OR(B9="",'实盘净值数据(iFinD公式)'!$A10="",'实盘净值数据(iFinD公式)'!$B10=""),"",(SUMPRODUCT(实盘持仓配置!$B$4:$X$4,'实盘净值数据(iFinD公式)'!$B9:$X9/'实盘净值数据(iFinD公式)'!$B$6:$X$6,'实盘净值数据(iFinD公式)'!$B10:$X10/'实盘净值数据(iFinD公式)'!$B9:$X9)/SUMPRODUCT(实盘持仓配置!$B$4:$X$4,'实盘净值数据(iFinD公式)'!$B9:$X9/'实盘净值数据(iFinD公式)'!$B$6:$X$6))*(1-实盘持仓配置!$Z$4)^(('实盘净值数据(iFinD公式)'!$A10-'实盘净值数据(iFinD公式)'!$A9)/365)-1) | D10: =IF(B10="","",B10/MAX(B$5:B10)-1) | E10: =IF(OR((ROW()-1)<5,'实盘净值数据(iFinD公式)'!$A10="",'实盘净值数据(iFinD公式)'!$B10=""),"",SUMPRODUCT(实盘持仓配置!$B$5:$X$5,'实盘净值数据(iFinD公式)'!$B10:$X10/'实盘净值数据(iFinD公式)'!$B$5:$X$5)*(1-实盘持仓配置!$Z$5)^(('实盘净值数据(iFinD公式)'!$A10-'实盘净值数据(iFinD公式)'!$A$5)/365)) | F10: =IF(OR(E9="",'实盘净值数据(iFinD公式)'!$A10="",'实盘净值数据(iFinD公式)'!$B10=""),"",(SUMPRODUCT(实盘持仓配置!$B$5:$X$5,'实盘净值数据(iFinD公式)'!$B9:$X9/'实盘净值数据(iFinD公式)'!$B$5:$X$5,'实盘净值数据(iFinD公式)'!$B10:$X10/'实盘净值数据(iFinD公式)'!$B9:$X9)/SUMPRODUCT(实盘持仓配置!$B$5:$X$5,'实盘净值数据(iFinD公式)'!$B9:$X9/'实盘净值数据(iFinD公式)'!$B$5:$X$5))*(1-实盘持仓配置!$Z$5)^(('实盘净值数据(iFinD公式)'!$A10-'实盘净值数据(iFinD公式)'!$A9)/365)-1) | G10: =IF(E10="","",E10/MAX(E$5:E10)-1) | H10: =IF(OR((ROW()-1)<7,'实盘净值数据(iFinD公式)'!$A10="",'实盘净值数据(iFinD公式)'!$B10=""),"",SUMPRODUCT(实盘持仓配置!$B$6:$X$6,'实盘净值数据(iFinD公式)'!$B10:$X10/'实盘净值数据(iFinD公式)'!$B$7:$X$7)*(1-实盘持仓配置!$Z$6)^(('实盘净值数据(iFinD公式)'!$A10-'实盘净值数据(iFinD公式)'!$A$7)/365)) | I10: =IF(OR(H9="",'实盘净值数据(iFinD公式)'!$A10="",'实盘净值数据(iFinD公式)'!$B10=""),"",(SUMPRODUCT(实盘持仓配置!$B$6:$X$6,'实盘净值数据(iFinD公式)'!$B9:$X9/'实盘净值数据(iFinD公式)'!$B$7:$X$7,'实盘净值数据(iFinD公式)'!$B10:$X10/'实盘净值数据(iFinD公式)'!$B9:$X9)/SUMPRODUCT(实盘持仓配置!$B$6:$X$6,'实盘净值数据(iFinD公式)'!$B9:$X9/'实盘净值数据(iFinD公式)'!$B$7:$X$7))*(1-实盘持仓配置!$Z$6)^(('实盘净值数据(iFinD公式)'!$A10-'实盘净值数据(iFinD公式)'!$A9)/365)-1) | J10: =IF(H10="","",H10/MAX(H$5:H10)-1) | K10: =IF(OR((ROW()-1)<8,'实盘净值数据(iFinD公式)'!$A10="",'实盘净值数据(iFinD公式)'!$B10=""),"",SUMPRODUCT(实盘持仓配置!$B$7:$X$7,'实盘净值数据(iFinD公式)'!$B10:$X10/'实盘净值数据(iFinD公式)'!$B$8:$X$8)*(1-实盘持仓配置!$Z$7)^(('实盘净值数据(iFinD公式)'!$A10-'实盘净值数据(iFinD公式)'!$A$8)/365)) | L10: =IF(OR(K9="",'实盘净值数据(iFinD公式)'!$A10="",'实盘净值数据(iFinD公式)'!$B10=""),"",(SUMPRODUCT(实盘持仓配置!$B$7:$X$7,'实盘净值数据(iFinD公式)'!$B9:$X9/'实盘净值数据(iFinD公式)'!$B$8:$X$8,'实盘净值数据(iFinD公式)'!$B10:$X10/'实盘净值数据(iFinD公式)'!$B9:$X9)/SUMPRODUCT(实盘持仓配置!$B$7:$X$7,'实盘净值数据(iFinD公式)'!$B9:$X9/'实盘净值数据(iFinD公式)'!$B$8:$X$8))*(1-实盘持仓配置!$Z$7)^(('实盘净值数据(iFinD公式)'!$A10-'实盘净值数据(iFinD公式)'!$A9)/365)-1) | M10: =IF(K10="","",K10/MAX(K$5:K10)-1) | N10: =IF(OR((ROW()-1)<5,'实盘净值数据(iFinD公式)'!$A10="",'实盘净值数据(iFinD公式)'!$B10=""),"",SUMPRODUCT(实盘持仓配置!$B$8:$X$8,'实盘净值数据(iFinD公式)'!$B10:$X10/'实盘净值数据(iFinD公式)'!$B$5:$X$5)*(1-实盘持仓配置!$Z$8)^(('实盘净值数据(iFinD公式)'!$A10-'实盘净值数据(iFinD公式)'!$A$5)/365)) | O10: =IF(OR(N9="",'实盘净值数据(iFinD公式)'!$A10="",'实盘净值数据(iFinD公式)'!$B10=""),"",(SUMPRODUCT(实盘持仓配置!$B$8:$X$8,'实盘净值数据(iFinD公式)'!$B9:$X9/'实盘净值数据(iFinD公式)'!$B$5:$X$5,'实盘净值数据(iFinD公式)'!$B10:$X10/'实盘净值数据(iFinD公式)'!$B9:$X9)/SUMPRODUCT(实盘持仓配置!$B$8:$X$8,'实盘净值数据(iFinD公式)'!$B9:$X9/'实盘净值数据(iFinD公式)'!$B$5:$X$5))*(1-实盘持仓配置!$Z$8)^(('实盘净值数据(iFinD公式)'!$A10-'实盘净值数据(iFinD公式)'!$A9)/365)-1) | P10: =IF(N10="","",N10/MAX(N$5:N10)-1) | Q10: =IF(OR((ROW()-1)<8,'实盘净值数据(iFinD公式)'!$A10="",'实盘净值数据(iFinD公式)'!$B10=""),"",SUMPRODUCT(实盘持仓配置!$B$9:$X$9,'实盘净值数据(iFinD公式)'!$B10:$X10/'实盘净值数据(iFinD公式)'!$B$8:$X$8)*(1-实盘持仓配置!$Z$9)^(('实盘净值数据(iFinD公式)'!$A10-'实盘净值数据(iFinD公式)'!$A$8)/365)) | R10: =IF(OR(Q9="",'实盘净值数据(iFinD公式)'!$A10="",'实盘净值数据(iFinD公式)'!$B10=""),"",(SUMPRODUCT(实盘持仓配置!$B$9:$X$9,'实盘净值数据(iFinD公式)'!$B9:$X9/'实盘净值数据(iFinD公式)'!$B$8:$X$8,'实盘净值数据(iFinD公式)'!$B10:$X10/'实盘净值数据(iFinD公式)'!$B9:$X9)/SUMPRODUCT(实盘持仓配置!$B$9:$X$9,'实盘净值数据(iFinD公式)'!$B9:$X9/'实盘净值数据(iFinD公式)'!$B$8:$X$8))*(1-实盘持仓配置!$Z$9)^(('实盘净值数据(iFinD公式)'!$A10-'实盘净值数据(iFinD公式)'!$A9)/365)-1) | S10: =IF(Q10="","",Q10/MAX(Q$5:Q10)-1)
A11: =IF('实盘净值数据(iFinD公式)'!A11="","",'实盘净值数据(iFinD公式)'!A11) | B11: =IF(OR((ROW()-1)<6,'实盘净值数据(iFinD公式)'!$A11="",'实盘净值数据(iFinD公式)'!$B11=""),"",SUMPRODUCT(实盘持仓配置!$B$4:$X$4,'实盘净值数据(iFinD公式)'!$B11:$X11/'实盘净值数据(iFinD公式)'!$B$6:$X$6)*(1-实盘持仓配置!$Z$4)^(('实盘净值数据(iFinD公式)'!$A11-'实盘净值数据(iFinD公式)'!$A$6)/365)) | C11: =IF(OR(B10="",'实盘净值数据(iFinD公式)'!$A11="",'实盘净值数据(iFinD公式)'!$B11=""),"",(SUMPRODUCT(实盘持仓配置!$B$4:$X$4,'实盘净值数据(iFinD公式)'!$B10:$X10/'实盘净值数据(iFinD公式)'!$B$6:$X$6,'实盘净值数据(iFinD公式)'!$B11:$X11/'实盘净值数据(iFinD公式)'!$B10:$X10)/SUMPRODUCT(实盘持仓配置!$B$4:$X$4,'实盘净值数据(iFinD公式)'!$B10:$X10/'实盘净值数据(iFinD公式)'!$B$6:$X$6))*(1-实盘持仓配置!$Z$4)^(('实盘净值数据(iFinD公式)'!$A11-'实盘净值数据(iFinD公式)'!$A10)/365)-1) | D11: =IF(B11="","",B11/MAX(B$5:B11)-1) | E11: =IF(OR((ROW()-1)<5,'实盘净值数据(iFinD公式)'!$A11="",'实盘净值数据(iFinD公式)'!$B11=""),"",SUMPRODUCT(实盘持仓配置!$B$5:$X$5,'实盘净值数据(iFinD公式)'!$B11:$X11/'实盘净值数据(iFinD公式)'!$B$5:$X$5)*(1-实盘持仓配置!$Z$5)^(('实盘净值数据(iFinD公式)'!$A11-'实盘净值数据(iFinD公式)'!$A$5)/365)) | F11: =IF(OR(E10="",'实盘净值数据(iFinD公式)'!$A11="",'实盘净值数据(iFinD公式)'!$B11=""),"",(SUMPRODUCT(实盘持仓配置!$B$5:$X$5,'实盘净值数据(iFinD公式)'!$B10:$X10/'实盘净值数据(iFinD公式)'!$B$5:$X$5,'实盘净值数据(iFinD公式)'!$B11:$X11/'实盘净值数据(iFinD公式)'!$B10:$X10)/SUMPRODUCT(实盘持仓配置!$B$5:$X$5,'实盘净值数据(iFinD公式)'!$B10:$X10/'实盘净值数据(iFinD公式)'!$B$5:$X$5))*(1-实盘持仓配置!$Z$5)^(('实盘净值数据(iFinD公式)'!$A11-'实盘净值数据(iFinD公式)'!$A10)/365)-1) | G11: =IF(E11="","",E11/MAX(E$5:E11)-1) | H11: =IF(OR((ROW()-1)<7,'实盘净值数据(iFinD公式)'!$A11="",'实盘净值数据(iFinD公式)'!$B11=""),"",SUMPRODUCT(实盘持仓配置!$B$6:$X$6,'实盘净值数据(iFinD公式)'!$B11:$X11/'实盘净值数据(iFinD公式)'!$B$7:$X$7)*(1-实盘持仓配置!$Z$6)^(('实盘净值数据(iFinD公式)'!$A11-'实盘净值数据(iFinD公式)'!$A$7)/365)) | I11: =IF(OR(H10="",'实盘净值数据(iFinD公式)'!$A11="",'实盘净值数据(iFinD公式)'!$B11=""),"",(SUMPRODUCT(实盘持仓配置!$B$6:$X$6,'实盘净值数据(iFinD公式)'!$B10:$X10/'实盘净值数据(iFinD公式)'!$B$7:$X$7,'实盘净值数据(iFinD公式)'!$B11:$X11/'实盘净值数据(iFinD公式)'!$B10:$X10)/SUMPRODUCT(实盘持仓配置!$B$6:$X$6,'实盘净值数据(iFinD公式)'!$B10:$X10/'实盘净值数据(iFinD公式)'!$B$7:$X$7))*(1-实盘持仓配置!$Z$6)^(('实盘净值数据(iFinD公式)'!$A11-'实盘净值数据(iFinD公式)'!$A10)/365)-1) | J11: =IF(H11="","",H11/MAX(H$5:H11)-1) | K11: =IF(OR((ROW()-1)<8,'实盘净值数据(iFinD公式)'!$A11="",'实盘净值数据(iFinD公式)'!$B11=""),"",SUMPRODUCT(实盘持仓配置!$B$7:$X$7,'实盘净值数据(iFinD公式)'!$B11:$X11/'实盘净值数据(iFinD公式)'!$B$8:$X$8)*(1-实盘持仓配置!$Z$7)^(('实盘净值数据(iFinD公式)'!$A11-'实盘净值数据(iFinD公式)'!$A$8)/365)) | L11: =IF(OR(K10="",'实盘净值数据(iFinD公式)'!$A11="",'实盘净值数据(iFinD公式)'!$B11=""),"",(SUMPRODUCT(实盘持仓配置!$B$7:$X$7,'实盘净值数据(iFinD公式)'!$B10:$X10/'实盘净值数据(iFinD公式)'!$B$8:$X$8,'实盘净值数据(iFinD公式)'!$B11:$X11/'实盘净值数据(iFinD公式)'!$B10:$X10)/SUMPRODUCT(实盘持仓配置!$B$7:$X$7,'实盘净值数据(iFinD公式)'!$B10:$X10/'实盘净值数据(iFinD公式)'!$B$8:$X$8))*(1-实盘持仓配置!$Z$7)^(('实盘净值数据(iFinD公式)'!$A11-'实盘净值数据(iFinD公式)'!$A10)/365)-1) | M11: =IF(K11="","",K11/MAX(K$5:K11)-1) | N11: =IF(OR((ROW()-1)<5,'实盘净值数据(iFinD公式)'!$A11="",'实盘净值数据(iFinD公式)'!$B11=""),"",SUMPRODUCT(实盘持仓配置!$B$8:$X$8,'实盘净值数据(iFinD公式)'!$B11:$X11/'实盘净值数据(iFinD公式)'!$B$5:$X$5)*(1-实盘持仓配置!$Z$8)^(('实盘净值数据(iFinD公式)'!$A11-'实盘净值数据(iFinD公式)'!$A$5)/365)) | O11: =IF(OR(N10="",'实盘净值数据(iFinD公式)'!$A11="",'实盘净值数据(iFinD公式)'!$B11=""),"",(SUMPRODUCT(实盘持仓配置!$B$8:$X$8,'实盘净值数据(iFinD公式)'!$B10:$X10/'实盘净值数据(iFinD公式)'!$B$5:$X$5,'实盘净值数据(iFinD公式)'!$B11:$X11/'实盘净值数据(iFinD公式)'!$B10:$X10)/SUMPRODUCT(实盘持仓配置!$B$8:$X$8,'实盘净值数据(iFinD公式)'!$B10:$X10/'实盘净值数据(iFinD公式)'!$B$5:$X$5))*(1-实盘持仓配置!$Z$8)^(('实盘净值数据(iFinD公式)'!$A11-'实盘净值数据(iFinD公式)'!$A10)/365)-1) | P11: =IF(N11="","",N11/MAX(N$5:N11)-1) | Q11: =IF(OR((ROW()-1)<8,'实盘净值数据(iFinD公式)'!$A11="",'实盘净值数据(iFinD公式)'!$B11=""),"",SUMPRODUCT(实盘持仓配置!$B$9:$X$9,'实盘净值数据(iFinD公式)'!$B11:$X11/'实盘净值数据(iFinD公式)'!$B$8:$X$8)*(1-实盘持仓配置!$Z$9)^(('实盘净值数据(iFinD公式)'!$A11-'实盘净值数据(iFinD公式)'!$A$8)/365)) | R11: =IF(OR(Q10="",'实盘净值数据(iFinD公式)'!$A11="",'实盘净值数据(iFinD公式)'!$B11=""),"",(SUMPRODUCT(实盘持仓配置!$B$9:$X$9,'实盘净值数据(iFinD公式)'!$B10:$X10/'实盘净值数据(iFinD公式)'!$B$8:$X$8,'实盘净值数据(iFinD公式)'!$B11:$X11/'实盘净值数据(iFinD公式)'!$B10:$X10)/SUMPRODUCT(实盘持仓配置!$B$9:$X$9,'实盘净值数据(iFinD公式)'!$B10:$X10/'实盘净值数据(iFinD公式)'!$B$8:$X$8))*(1-实盘持仓配置!$Z$9)^(('实盘净值数据(iFinD公式)'!$A11-'实盘净值数据(iFinD公式)'!$A10)/365)-1) | S11: =IF(Q11="","",Q11/MAX(Q$5:Q11)-1)
A12: =IF('实盘净值数据(iFinD公式)'!A12="","",'实盘净值数据(iFinD公式)'!A12) | B12: =IF(OR((ROW()-1)<6,'实盘净值数据(iFinD公式)'!$A12="",'实盘净值数据(iFinD公式)'!$B12=""),"",SUMPRODUCT(实盘持仓配置!$B$4:$X$4,'实盘净值数据(iFinD公式)'!$B12:$X12/'实盘净值数据(iFinD公式)'!$B$6:$X$6)*(1-实盘持仓配置!$Z$4)^(('实盘净值数据(iFinD公式)'!$A12-'实盘净值数据(iFinD公式)'!$A$6)/365)) | C12: =IF(OR(B11="",'实盘净值数据(iFinD公式)'!$A12="",'实盘净值数据(iFinD公式)'!$B12=""),"",(SUMPRODUCT(实盘持仓配置!$B$4:$X$4,'实盘净值数据(iFinD公式)'!$B11:$X11/'实盘净值数据(iFinD公式)'!$B$6:$X$6,'实盘净值数据(iFinD公式)'!$B12:$X12/'实盘净值数据(iFinD公式)'!$B11:$X11)/SUMPRODUCT(实盘持仓配置!$B$4:$X$4,'实盘净值数据(iFinD公式)'!$B11:$X11/'实盘净值数据(iFinD公式)'!$B$6:$X$6))*(1-实盘持仓配置!$Z$4)^(('实盘净值数据(iFinD公式)'!$A12-'实盘净值数据(iFinD公式)'!$A11)/365)-1) | D12: =IF(B12="","",B12/MAX(B$5:B12)-1) | E12: =IF(OR((ROW()-1)<5,'实盘净值数据(iFinD公式)'!$A12="",'实盘净值数据(iFinD公式)'!$B12=""),"",SUMPRODUCT(实盘持仓配置!$B$5:$X$5,'实盘净值数据(iFinD公式)'!$B12:$X12/'实盘净值数据(iFinD公式)'!$B$5:$X$5)*(1-实盘持仓配置!$Z$5)^(('实盘净值数据(iFinD公式)'!$A12-'实盘净值数据(iFinD公式)'!$A$5)/365)) | F12: =IF(OR(E11="",'实盘净值数据(iFinD公式)'!$A12="",'实盘净值数据(iFinD公式)'!$B12=""),"",(SUMPRODUCT(实盘持仓配置!$B$5:$X$5,'实盘净值数据(iFinD公式)'!$B11:$X11/'实盘净值数据(iFinD公式)'!$B$5:$X$5,'实盘净值数据(iFinD公式)'!$B12:$X12/'实盘净值数据(iFinD公式)'!$B11:$X11)/SUMPRODUCT(实盘持仓配置!$B$5:$X$5,'实盘净值数据(iFinD公式)'!$B11:$X11/'实盘净值数据(iFinD公式)'!$B$5:$X$5))*(1-实盘持仓配置!$Z$5)^(('实盘净值数据(iFinD公式)'!$A12-'实盘净值数据(iFinD公式)'!$A11)/365)-1) | G12: =IF(E12="","",E12/MAX(E$5:E12)-1) | H12: =IF(OR((ROW()-1)<7,'实盘净值数据(iFinD公式)'!$A12="",'实盘净值数据(iFinD公式)'!$B12=""),"",SUMPRODUCT(实盘持仓配置!$B$6:$X$6,'实盘净值数据(iFinD公式)'!$B12:$X12/'实盘净值数据(iFinD公式)'!$B$7:$X$7)*(1-实盘持仓配置!$Z$6)^(('实盘净值数据(iFinD公式)'!$A12-'实盘净值数据(iFinD公式)'!$A$7)/365)) | I12: =IF(OR(H11="",'实盘净值数据(iFinD公式)'!$A12="",'实盘净值数据(iFinD公式)'!$B12=""),"",(SUMPRODUCT(实盘持仓配置!$B$6:$X$6,'实盘净值数据(iFinD公式)'!$B11:$X11/'实盘净值数据(iFinD公式)'!$B$7:$X$7,'实盘净值数据(iFinD公式)'!$B12:$X12/'实盘净值数据(iFinD公式)'!$B11:$X11)/SUMPRODUCT(实盘持仓配置!$B$6:$X$6,'实盘净值数据(iFinD公式)'!$B11:$X11/'实盘净值数据(iFinD公式)'!$B$7:$X$7))*(1-实盘持仓配置!$Z$6)^(('实盘净值数据(iFinD公式)'!$A12-'实盘净值数据(iFinD公式)'!$A11)/365)-1) | J12: =IF(H12="","",H12/MAX(H$5:H12)-1) | K12: =IF(OR((ROW()-1)<8,'实盘净值数据(iFinD公式)'!$A12="",'实盘净值数据(iFinD公式)'!$B12=""),"",SUMPRODUCT(实盘持仓配置!$B$7:$X$7,'实盘净值数据(iFinD公式)'!$B12:$X12/'实盘净值数据(iFinD公式)'!$B$8:$X$8)*(1-实盘持仓配置!$Z$7)^(('实盘净值数据(iFinD公式)'!$A12-'实盘净值数据(iFinD公式)'!$A$8)/365)) | L12: =IF(OR(K11="",'实盘净值数据(iFinD公式)'!$A12="",'实盘净值数据(iFinD公式)'!$B12=""),"",(SUMPRODUCT(实盘持仓配置!$B$7:$X$7,'实盘净值数据(iFinD公式)'!$B11:$X11/'实盘净值数据(iFinD公式)'!$B$8:$X$8,'实盘净值数据(iFinD公式)'!$B12:$X12/'实盘净值数据(iFinD公式)'!$B11:$X11)/SUMPRODUCT(实盘持仓配置!$B$7:$X$7,'实盘净值数据(iFinD公式)'!$B11:$X11/'实盘净值数据(iFinD公式)'!$B$8:$X$8))*(1-实盘持仓配置!$Z$7)^(('实盘净值数据(iFinD公式)'!$A12-'实盘净值数据(iFinD公式)'!$A11)/365)-1) | M12: =IF(K12="","",K12/MAX(K$5:K12)-1) | N12: =IF(OR((ROW()-1)<5,'实盘净值数据(iFinD公式)'!$A12="",'实盘净值数据(iFinD公式)'!$B12=""),"",SUMPRODUCT(实盘持仓配置!$B$8:$X$8,'实盘净值数据(iFinD公式)'!$B12:$X12/'实盘净值数据(iFinD公式)'!$B$5:$X$5)*(1-实盘持仓配置!$Z$8)^(('实盘净值数据(iFinD公式)'!$A12-'实盘净值数据(iFinD公式)'!$A$5)/365)) | O12: =IF(OR(N11="",'实盘净值数据(iFinD公式)'!$A12="",'实盘净值数据(iFinD公式)'!$B12=""),"",(SUMPRODUCT(实盘持仓配置!$B$8:$X$8,'实盘净值数据(iFinD公式)'!$B11:$X11/'实盘净值数据(iFinD公式)'!$B$5:$X$5,'实盘净值数据(iFinD公式)'!$B12:$X12/'实盘净值数据(iFinD公式)'!$B11:$X11)/SUMPRODUCT(实盘持仓配置!$B$8:$X$8,'实盘净值数据(iFinD公式)'!$B11:$X11/'实盘净值数据(iFinD公式)'!$B$5:$X$5))*(1-实盘持仓配置!$Z$8)^(('实盘净值数据(iFinD公式)'!$A12-'实盘净值数据(iFinD公式)'!$A11)/365)-1) | P12: =IF(N12="","",N12/MAX(N$5:N12)-1) | Q12: =IF(OR((ROW()-1)<8,'实盘净值数据(iFinD公式)'!$A12="",'实盘净值数据(iFinD公式)'!$B12=""),"",SUMPRODUCT(实盘持仓配置!$B$9:$X$9,'实盘净值数据(iFinD公式)'!$B12:$X12/'实盘净值数据(iFinD公式)'!$B$8:$X$8)*(1-实盘持仓配置!$Z$9)^(('实盘净值数据(iFinD公式)'!$A12-'实盘净值数据(iFinD公式)'!$A$8)/365)) | R12: =IF(OR(Q11="",'实盘净值数据(iFinD公式)'!$A12="",'实盘净值数据(iFinD公式)'!$B12=""),"",(SUMPRODUCT(实盘持仓配置!$B$9:$X$9,'实盘净值数据(iFinD公式)'!$B11:$X11/'实盘净值数据(iFinD公式)'!$B$8:$X$8,'实盘净值数据(iFinD公式)'!$B12:$X12/'实盘净值数据(iFinD公式)'!$B11:$X11)/SUMPRODUCT(实盘持仓配置!$B$9:$X$9,'实盘净值数据(iFinD公式)'!$B11:$X11/'实盘净值数据(iFinD公式)'!$B$8:$X$8))*(1-实盘持仓配置!$Z$9)^(('实盘净值数据(iFinD公式)'!$A12-'实盘净值数据(iFinD公式)'!$A11)/365)-1) | S12: =IF(Q12="","",Q12/MAX(Q$5:Q12)-1)
A13: =IF('实盘净值数据(iFinD公式)'!A13="","",'实盘净值数据(iFinD公式)'!A13) | B13: =IF(OR((ROW()-1)<6,'实盘净值数据(iFinD公式)'!$A13="",'实盘净值数据(iFinD公式)'!$B13=""),"",SUMPRODUCT(实盘持仓配置!$B$4:$X$4,'实盘净值数据(iFinD公式)'!$B13:$X13/'实盘净值数据(iFinD公式)'!$B$6:$X$6)*(1-实盘持仓配置!$Z$4)^(('实盘净值数据(iFinD公式)'!$A13-'实盘净值数据(iFinD公式)'!$A$6)/365)) | C13: =IF(OR(B12="",'实盘净值数据(iFinD公式)'!$A13="",'实盘净值数据(iFinD公式)'!$B13=""),"",(SUMPRODUCT(实盘持仓配置!$B$4:$X$4,'实盘净值数据(iFinD公式)'!$B12:$X12/'实盘净值数据(iFinD公式)'!$B$6:$X$6,'实盘净值数据(iFinD公式)'!$B13:$X13/'实盘净值数据(iFinD公式)'!$B12:$X12)/SUMPRODUCT(实盘持仓配置!$B$4:$X$4,'实盘净值数据(iFinD公式)'!$B12:$X12/'实盘净值数据(iFinD公式)'!$B$6:$X$6))*(1-实盘持仓配置!$Z$4)^(('实盘净值数据(iFinD公式)'!$A13-'实盘净值数据(iFinD公式)'!$A12)/365)-1) | D13: =IF(B13="","",B13/MAX(B$5:B13)-1) | E13: =IF(OR((ROW()-1)<5,'实盘净值数据(iFinD公式)'!$A13="",'实盘净值数据(iFinD公式)'!$B13=""),"",SUMPRODUCT(实盘持仓配置!$B$5:$X$5,'实盘净值数据(iFinD公式)'!$B13:$X13/'实盘净值数据(iFinD公式)'!$B$5:$X$5)*(1-实盘持仓配置!$Z$5)^(('实盘净值数据(iFinD公式)'!$A13-'实盘净值数据(iFinD公式)'!$A$5)/365)) | F13: =IF(OR(E12="",'实盘净值数据(iFinD公式)'!$A13="",'实盘净值数据(iFinD公式)'!$B13=""),"",(SUMPRODUCT(实盘持仓配置!$B$5:$X$5,'实盘净值数据(iFinD公式)'!$B12:$X12/'实盘净值数据(iFinD公式)'!$B$5:$X$5,'实盘净值数据(iFinD公式)'!$B13:$X13/'实盘净值数据(iFinD公式)'!$B12:$X12)/SUMPRODUCT(实盘持仓配置!$B$5:$X$5,'实盘净值数据(iFinD公式)'!$B12:$X12/'实盘净值数据(iFinD公式)'!$B$5:$X$5))*(1-实盘持仓配置!$Z$5)^(('实盘净值数据(iFinD公式)'!$A13-'实盘净值数据(iFinD公式)'!$A12)/365)-1) | G13: =IF(E13="","",E13/MAX(E$5:E13)-1) | H13: =IF(OR((ROW()-1)<7,'实盘净值数据(iFinD公式)'!$A13="",'实盘净值数据(iFinD公式)'!$B13=""),"",SUMPRODUCT(实盘持仓配置!$B$6:$X$6,'实盘净值数据(iFinD公式)'!$B13:$X13/'实盘净值数据(iFinD公式)'!$B$7:$X$7)*(1-实盘持仓配置!$Z$6)^(('实盘净值数据(iFinD公式)'!$A13-'实盘净值数据(iFinD公式)'!$A$7)/365)) | I13: =IF(OR(H12="",'实盘净值数据(iFinD公式)'!$A13="",'实盘净值数据(iFinD公式)'!$B13=""),"",(SUMPRODUCT(实盘持仓配置!$B$6:$X$6,'实盘净值数据(iFinD公式)'!$B12:$X12/'实盘净值数据(iFinD公式)'!$B$7:$X$7,'实盘净值数据(iFinD公式)'!$B13:$X13/'实盘净值数据(iFinD公式)'!$B12:$X12)/SUMPRODUCT(实盘持仓配置!$B$6:$X$6,'实盘净值数据(iFinD公式)'!$B12:$X12/'实盘净值数据(iFinD公式)'!$B$7:$X$7))*(1-实盘持仓配置!$Z$6)^(('实盘净值数据(iFinD公式)'!$A13-'实盘净值数据(iFinD公式)'!$A12)/365)-1) | J13: =IF(H13="","",H13/MAX(H$5:H13)-1) | K13: =IF(OR((ROW()-1)<8,'实盘净值数据(iFinD公式)'!$A13="",'实盘净值数据(iFinD公式)'!$B13=""),"",SUMPRODUCT(实盘持仓配置!$B$7:$X$7,'实盘净值数据(iFinD公式)'!$B13:$X13/'实盘净值数据(iFinD公式)'!$B$8:$X$8)*(1-实盘持仓配置!$Z$7)^(('实盘净值数据(iFinD公式)'!$A13-'实盘净值数据(iFinD公式)'!$A$8)/365)) | L13: =IF(OR(K12="",'实盘净值数据(iFinD公式)'!$A13="",'实盘净值数据(iFinD公式)'!$B13=""),"",(SUMPRODUCT(实盘持仓配置!$B$7:$X$7,'实盘净值数据(iFinD公式)'!$B12:$X12/'实盘净值数据(iFinD公式)'!$B$8:$X$8,'实盘净值数据(iFinD公式)'!$B13:$X13/'实盘净值数据(iFinD公式)'!$B12:$X12)/SUMPRODUCT(实盘持仓配置!$B$7:$X$7,'实盘净值数据(iFinD公式)'!$B12:$X12/'实盘净值数据(iFinD公式)'!$B$8:$X$8))*(1-实盘持仓配置!$Z$7)^(('实盘净值数据(iFinD公式)'!$A13-'实盘净值数据(iFinD公式)'!$A12)/365)-1) | M13: =IF(K13="","",K13/MAX(K$5:K13)-1) | N13: =IF(OR((ROW()-1)<5,'实盘净值数据(iFinD公式)'!$A13="",'实盘净值数据(iFinD公式)'!$B13=""),"",SUMPRODUCT(实盘持仓配置!$B$8:$X$8,'实盘净值数据(iFinD公式)'!$B13:$X13/'实盘净值数据(iFinD公式)'!$B$5:$X$5)*(1-实盘持仓配置!$Z$8)^(('实盘净值数据(iFinD公式)'!$A13-'实盘净值数据(iFinD公式)'!$A$5)/365)) | O13: =IF(OR(N12="",'实盘净值数据(iFinD公式)'!$A13="",'实盘净值数据(iFinD公式)'!$B13=""),"",(SUMPRODUCT(实盘持仓配置!$B$8:$X$8,'实盘净值数据(iFinD公式)'!$B12:$X12/'实盘净值数据(iFinD公式)'!$B$5:$X$5,'实盘净值数据(iFinD公式)'!$B13:$X13/'实盘净值数据(iFinD公式)'!$B12:$X12)/SUMPRODUCT(实盘持仓配置!$B$8:$X$8,'实盘净值数据(iFinD公式)'!$B12:$X12/'实盘净值数据(iFinD公式)'!$B$5:$X$5))*(1-实盘持仓配置!$Z$8)^(('实盘净值数据(iFinD公式)'!$A13-'实盘净值数据(iFinD公式)'!$A12)/365)-1) | P13: =IF(N13="","",N13/MAX(N$5:N13)-1) | Q13: =IF(OR((ROW()-1)<8,'实盘净值数据(iFinD公式)'!$A13="",'实盘净值数据(iFinD公式)'!$B13=""),"",SUMPRODUCT(实盘持仓配置!$B$9:$X$9,'实盘净值数据(iFinD公式)'!$B13:$X13/'实盘净值数据(iFinD公式)'!$B$8:$X$8)*(1-实盘持仓配置!$Z$9)^(('实盘净值数据(iFinD公式)'!$A13-'实盘净值数据(iFinD公式)'!$A$8)/365)) | R13: =IF(OR(Q12="",'实盘净值数据(iFinD公式)'!$A13="",'实盘净值数据(iFinD公式)'!$B13=""),"",(SUMPRODUCT(实盘持仓配置!$B$9:$X$9,'实盘净值数据(iFinD公式)'!$B12:$X12/'实盘净值数据(iFinD公式)'!$B$8:$X$8,'实盘净值数据(iFinD公式)'!$B13:$X13/'实盘净值数据(iFinD公式)'!$B12:$X12)/SUMPRODUCT(实盘持仓配置!$B$9:$X$9,'实盘净值数据(iFinD公式)'!$B12:$X12/'实盘净值数据(iFinD公式)'!$B$8:$X$8))*(1-实盘持仓配置!$Z$9)^(('实盘净值数据(iFinD公式)'!$A13-'实盘净值数据(iFinD公式)'!$A12)/365)-1) | S13: =IF(Q13="","",Q13/MAX(Q$5:Q13)-1)
A14: =IF('实盘净值数据(iFinD公式)'!A14="","",'实盘净值数据(iFinD公式)'!A14) | B14: =IF(OR((ROW()-1)<6,'实盘净值数据(iFinD公式)'!$A14="",'实盘净值数据(iFinD公式)'!$B14=""),"",SUMPRODUCT(实盘持仓配置!$B$4:$X$4,'实盘净值数据(iFinD公式)'!$B14:$X14/'实盘净值数据(iFinD公式)'!$B$6:$X$6)*(1-实盘持仓配置!$Z$4)^(('实盘净值数据(iFinD公式)'!$A14-'实盘净值数据(iFinD公式)'!$A$6)/365)) | C14: =IF(OR(B13="",'实盘净值数据(iFinD公式)'!$A14="",'实盘净值数据(iFinD公式)'!$B14=""),"",(SUMPRODUCT(实盘持仓配置!$B$4:$X$4,'实盘净值数据(iFinD公式)'!$B13:$X13/'实盘净值数据(iFinD公式)'!$B$6:$X$6,'实盘净值数据(iFinD公式)'!$B14:$X14/'实盘净值数据(iFinD公式)'!$B13:$X13)/SUMPRODUCT(实盘持仓配置!$B$4:$X$4,'实盘净值数据(iFinD公式)'!$B13:$X13/'实盘净值数据(iFinD公式)'!$B$6:$X$6))*(1-实盘持仓配置!$Z$4)^(('实盘净值数据(iFinD公式)'!$A14-'实盘净值数据(iFinD公式)'!$A13)/365)-1) | D14: =IF(B14="","",B14/MAX(B$5:B14)-1) | E14: =IF(OR((ROW()-1)<5,'实盘净值数据(iFinD公式)'!$A14="",'实盘净值数据(iFinD公式)'!$B14=""),"",SUMPRODUCT(实盘持仓配置!$B$5:$X$5,'实盘净值数据(iFinD公式)'!$B14:$X14/'实盘净值数据(iFinD公式)'!$B$5:$X$5)*(1-实盘持仓配置!$Z$5)^(('实盘净值数据(iFinD公式)'!$A14-'实盘净值数据(iFinD公式)'!$A$5)/365)) | F14: =IF(OR(E13="",'实盘净值数据(iFinD公式)'!$A14="",'实盘净值数据(iFinD公式)'!$B14=""),"",(SUMPRODUCT(实盘持仓配置!$B$5:$X$5,'实盘净值数据(iFinD公式)'!$B13:$X13/'实盘净值数据(iFinD公式)'!$B$5:$X$5,'实盘净值数据(iFinD公式)'!$B14:$X14/'实盘净值数据(iFinD公式)'!$B13:$X13)/SUMPRODUCT(实盘持仓配置!$B$5:$X$5,'实盘净值数据(iFinD公式)'!$B13:$X13/'实盘净值数据(iFinD公式)'!$B$5:$X$5))*(1-实盘持仓配置!$Z$5)^(('实盘净值数据(iFinD公式)'!$A14-'实盘净值数据(iFinD公式)'!$A13)/365)-1) | G14: =IF(E14="","",E14/MAX(E$5:E14)-1) | H14: =IF(OR((ROW()-1)<7,'实盘净值数据(iFinD公式)'!$A14="",'实盘净值数据(iFinD公式)'!$B14=""),"",SUMPRODUCT(实盘持仓配置!$B$6:$X$6,'实盘净值数据(iFinD公式)'!$B14:$X14/'实盘净值数据(iFinD公式)'!$B$7:$X$7)*(1-实盘持仓配置!$Z$6)^(('实盘净值数据(iFinD公式)'!$A14-'实盘净值数据(iFinD公式)'!$A$7)/365)) | I14: =IF(OR(H13="",'实盘净值数据(iFinD公式)'!$A14="",'实盘净值数据(iFinD公式)'!$B14=""),"",(SUMPRODUCT(实盘持仓配置!$B$6:$X$6,'实盘净值数据(iFinD公式)'!$B13:$X13/'实盘净值数据(iFinD公式)'!$B$7:$X$7,'实盘净值数据(iFinD公式)'!$B14:$X14/'实盘净值数据(iFinD公式)'!$B13:$X13)/SUMPRODUCT(实盘持仓配置!$B$6:$X$6,'实盘净值数据(iFinD公式)'!$B13:$X13/'实盘净值数据(iFinD公式)'!$B$7:$X$7))*(1-实盘持仓配置!$Z$6)^(('实盘净值数据(iFinD公式)'!$A14-'实盘净值数据(iFinD公式)'!$A13)/365)-1) | J14: =IF(H14="","",H14/MAX(H$5:H14)-1) | K14: =IF(OR((ROW()-1)<8,'实盘净值数据(iFinD公式)'!$A14="",'实盘净值数据(iFinD公式)'!$B14=""),"",SUMPRODUCT(实盘持仓配置!$B$7:$X$7,'实盘净值数据(iFinD公式)'!$B14:$X14/'实盘净值数据(iFinD公式)'!$B$8:$X$8)*(1-实盘持仓配置!$Z$7)^(('实盘净值数据(iFinD公式)'!$A14-'实盘净值数据(iFinD公式)'!$A$8)/365)) | L14: =IF(OR(K13="",'实盘净值数据(iFinD公式)'!$A14="",'实盘净值数据(iFinD公式)'!$B14=""),"",(SUMPRODUCT(实盘持仓配置!$B$7:$X$7,'实盘净值数据(iFinD公式)'!$B13:$X13/'实盘净值数据(iFinD公式)'!$B$8:$X$8,'实盘净值数据(iFinD公式)'!$B14:$X14/'实盘净值数据(iFinD公式)'!$B13:$X13)/SUMPRODUCT(实盘持仓配置!$B$7:$X$7,'实盘净值数据(iFinD公式)'!$B13:$X13/'实盘净值数据(iFinD公式)'!$B$8:$X$8))*(1-实盘持仓配置!$Z$7)^(('实盘净值数据(iFinD公式)'!$A14-'实盘净值数据(iFinD公式)'!$A13)/365)-1) | M14: =IF(K14="","",K14/MAX(K$5:K14)-1) | N14: =IF(OR((ROW()-1)<5,'实盘净值数据(iFinD公式)'!$A14="",'实盘净值数据(iFinD公式)'!$B14=""),"",SUMPRODUCT(实盘持仓配置!$B$8:$X$8,'实盘净值数据(iFinD公式)'!$B14:$X14/'实盘净值数据(iFinD公式)'!$B$5:$X$5)*(1-实盘持仓配置!$Z$8)^(('实盘净值数据(iFinD公式)'!$A14-'实盘净值数据(iFinD公式)'!$A$5)/365)) | O14: =IF(OR(N13="",'实盘净值数据(iFinD公式)'!$A14="",'实盘净值数据(iFinD公式)'!$B14=""),"",(SUMPRODUCT(实盘持仓配置!$B$8:$X$8,'实盘净值数据(iFinD公式)'!$B13:$X13/'实盘净值数据(iFinD公式)'!$B$5:$X$5,'实盘净值数据(iFinD公式)'!$B14:$X14/'实盘净值数据(iFinD公式)'!$B13:$X13)/SUMPRODUCT(实盘持仓配置!$B$8:$X$8,'实盘净值数据(iFinD公式)'!$B13:$X13/'实盘净值数据(iFinD公式)'!$B$5:$X$5))*(1-实盘持仓配置!$Z$8)^(('实盘净值数据(iFinD公式)'!$A14-'实盘净值数据(iFinD公式)'!$A13)/365)-1) | P14: =IF(N14="","",N14/MAX(N$5:N14)-1) | Q14: =IF(OR((ROW()-1)<8,'实盘净值数据(iFinD公式)'!$A14="",'实盘净值数据(iFinD公式)'!$B14=""),"",SUMPRODUCT(实盘持仓配置!$B$9:$X$9,'实盘净值数据(iFinD公式)'!$B14:$X14/'实盘净值数据(iFinD公式)'!$B$8:$X$8)*(1-实盘持仓配置!$Z$9)^(('实盘净值数据(iFinD公式)'!$A14-'实盘净值数据(iFinD公式)'!$A$8)/365)) | R14: =IF(OR(Q13="",'实盘净值数据(iFinD公式)'!$A14="",'实盘净值数据(iFinD公式)'!$B14=""),"",(SUMPRODUCT(实盘持仓配置!$B$9:$X$9,'实盘净值数据(iFinD公式)'!$B13:$X13/'实盘净值数据(iFinD公式)'!$B$8:$X$8,'实盘净值数据(iFinD公式)'!$B14:$X14/'实盘净值数据(iFinD公式)'!$B13:$X13)/SUMPRODUCT(实盘持仓配置!$B$9:$X$9,'实盘净值数据(iFinD公式)'!$B13:$X13/'实盘净值数据(iFinD公式)'!$B$8:$X$8))*(1-实盘持仓配置!$Z$9)^(('实盘净值数据(iFinD公式)'!$A14-'实盘净值数据(iFinD公式)'!$A13)/365)-1) | S14: =IF(Q14="","",Q14/MAX(Q$5:Q14)-1)
A15: =IF('实盘净值数据(iFinD公式)'!A15="","",'实盘净值数据(iFinD公式)'!A15) | B15: =IF(OR((ROW()-1)<6,'实盘净值数据(iFinD公式)'!$A15="",'实盘净值数据(iFinD公式)'!$B15=""),"",SUMPRODUCT(实盘持仓配置!$B$4:$X$4,'实盘净值数据(iFinD公式)'!$B15:$X15/'实盘净值数据(iFinD公式)'!$B$6:$X$6)*(1-实盘持仓配置!$Z$4)^(('实盘净值数据(iFinD公式)'!$A15-'实盘净值数据(iFinD公式)'!$A$6)/365)) | C15: =IF(OR(B14="",'实盘净值数据(iFinD公式)'!$A15="",'实盘净值数据(iFinD公式)'!$B15=""),"",(SUMPRODUCT(实盘持仓配置!$B$4:$X$4,'实盘净值数据(iFinD公式)'!$B14:$X14/'实盘净值数据(iFinD公式)'!$B$6:$X$6,'实盘净值数据(iFinD公式)'!$B15:$X15/'实盘净值数据(iFinD公式)'!$B14:$X14)/SUMPRODUCT(实盘持仓配置!$B$4:$X$4,'实盘净值数据(iFinD公式)'!$B14:$X14/'实盘净值数据(iFinD公式)'!$B$6:$X$6))*(1-实盘持仓配置!$Z$4)^(('实盘净值数据(iFinD公式)'!$A15-'实盘净值数据(iFinD公式)'!$A14)/365)-1) | D15: =IF(B15="","",B15/MAX(B$5:B15)-1) | E15: =IF(OR((ROW()-1)<5,'实盘净值数据(iFinD公式)'!$A15="",'实盘净值数据(iFinD公式)'!$B15=""),"",SUMPRODUCT(实盘持仓配置!$B$5:$X$5,'实盘净值数据(iFinD公式)'!$B15:$X15/'实盘净值数据(iFinD公式)'!$B$5:$X$5)*(1-实盘持仓配置!$Z$5)^(('实盘净值数据(iFinD公式)'!$A15-'实盘净值数据(iFinD公式)'!$A$5)/365)) | F15: =IF(OR(E14="",'实盘净值数据(iFinD公式)'!$A15="",'实盘净值数据(iFinD公式)'!$B15=""),"",(SUMPRODUCT(实盘持仓配置!$B$5:$X$5,'实盘净值数据(iFinD公式)'!$B14:$X14/'实盘净值数据(iFinD公式)'!$B$5:$X$5,'实盘净值数据(iFinD公式)'!$B15:$X15/'实盘净值数据(iFinD公式)'!$B14:$X14)/SUMPRODUCT(实盘持仓配置!$B$5:$X$5,'实盘净值数据(iFinD公式)'!$B14:$X14/'实盘净值数据(iFinD公式)'!$B$5:$X$5))*(1-实盘持仓配置!$Z$5)^(('实盘净值数据(iFinD公式)'!$A15-'实盘净值数据(iFinD公式)'!$A14)/365)-1) | G15: =IF(E15="","",E15/MAX(E$5:E15)-1) | H15: =IF(OR((ROW()-1)<7,'实盘净值数据(iFinD公式)'!$A15="",'实盘净值数据(iFinD公式)'!$B15=""),"",SUMPRODUCT(实盘持仓配置!$B$6:$X$6,'实盘净值数据(iFinD公式)'!$B15:$X15/'实盘净值数据(iFinD公式)'!$B$7:$X$7)*(1-实盘持仓配置!$Z$6)^(('实盘净值数据(iFinD公式)'!$A15-'实盘净值数据(iFinD公式)'!$A$7)/365)) | I15: =IF(OR(H14="",'实盘净值数据(iFinD公式)'!$A15="",'实盘净值数据(iFinD公式)'!$B15=""),"",(SUMPRODUCT(实盘持仓配置!$B$6:$X$6,'实盘净值数据(iFinD公式)'!$B14:$X14/'实盘净值数据(iFinD公式)'!$B$7:$X$7,'实盘净值数据(iFinD公式)'!$B15:$X15/'实盘净值数据(iFinD公式)'!$B14:$X14)/SUMPRODUCT(实盘持仓配置!$B$6:$X$6,'实盘净值数据(iFinD公式)'!$B14:$X14/'实盘净值数据(iFinD公式)'!$B$7:$X$7))*(1-实盘持仓配置!$Z$6)^(('实盘净值数据(iFinD公式)'!$A15-'实盘净值数据(iFinD公式)'!$A14)/365)-1) | J15: =IF(H15="","",H15/MAX(H$5:H15)-1) | K15: =IF(OR((ROW()-1)<8,'实盘净值数据(iFinD公式)'!$A15="",'实盘净值数据(iFinD公式)'!$B15=""),"",SUMPRODUCT(实盘持仓配置!$B$7:$X$7,'实盘净值数据(iFinD公式)'!$B15:$X15/'实盘净值数据(iFinD公式)'!$B$8:$X$8)*(1-实盘持仓配置!$Z$7)^(('实盘净值数据(iFinD公式)'!$A15-'实盘净值数据(iFinD公式)'!$A$8)/365)) | L15: =IF(OR(K14="",'实盘净值数据(iFinD公式)'!$A15="",'实盘净值数据(iFinD公式)'!$B15=""),"",(SUMPRODUCT(实盘持仓配置!$B$7:$X$7,'实盘净值数据(iFinD公式)'!$B14:$X14/'实盘净值数据(iFinD公式)'!$B$8:$X$8,'实盘净值数据(iFinD公式)'!$B15:$X15/'实盘净值数据(iFinD公式)'!$B14:$X14)/SUMPRODUCT(实盘持仓配置!$B$7:$X$7,'实盘净值数据(iFinD公式)'!$B14:$X14/'实盘净值数据(iFinD公式)'!$B$8:$X$8))*(1-实盘持仓配置!$Z$7)^(('实盘净值数据(iFinD公式)'!$A15-'实盘净值数据(iFinD公式)'!$A14)/365)-1) | M15: =IF(K15="","",K15/MAX(K$5:K15)-1) | N15: =IF(OR((ROW()-1)<5,'实盘净值数据(iFinD公式)'!$A15="",'实盘净值数据(iFinD公式)'!$B15=""),"",SUMPRODUCT(实盘持仓配置!$B$8:$X$8,'实盘净值数据(iFinD公式)'!$B15:$X15/'实盘净值数据(iFinD公式)'!$B$5:$X$5)*(1-实盘持仓配置!$Z$8)^(('实盘净值数据(iFinD公式)'!$A15-'实盘净值数据(iFinD公式)'!$A$5)/365)) | O15: =IF(OR(N14="",'实盘净值数据(iFinD公式)'!$A15="",'实盘净值数据(iFinD公式)'!$B15=""),"",(SUMPRODUCT(实盘持仓配置!$B$8:$X$8,'实盘净值数据(iFinD公式)'!$B14:$X14/'实盘净值数据(iFinD公式)'!$B$5:$X$5,'实盘净值数据(iFinD公式)'!$B15:$X15/'实盘净值数据(iFinD公式)'!$B14:$X14)/SUMPRODUCT(实盘持仓配置!$B$8:$X$8,'实盘净值数据(iFinD公式)'!$B14:$X14/'实盘净值数据(iFinD公式)'!$B$5:$X$5))*(1-实盘持仓配置!$Z$8)^(('实盘净值数据(iFinD公式)'!$A15-'实盘净值数据(iFinD公式)'!$A14)/365)-1) | P15: =IF(N15="","",N15/MAX(N$5:N15)-1) | Q15: =IF(OR((ROW()-1)<8,'实盘净值数据(iFinD公式)'!$A15="",'实盘净值数据(iFinD公式)'!$B15=""),"",SUMPRODUCT(实盘持仓配置!$B$9:$X$9,'实盘净值数据(iFinD公式)'!$B15:$X15/'实盘净值数据(iFinD公式)'!$B$8:$X$8)*(1-实盘持仓配置!$Z$9)^(('实盘净值数据(iFinD公式)'!$A15-'实盘净值数据(iFinD公式)'!$A$8)/365)) | R15: =IF(OR(Q14="",'实盘净值数据(iFinD公式)'!$A15="",'实盘净值数据(iFinD公式)'!$B15=""),"",(SUMPRODUCT(实盘持仓配置!$B$9:$X$9,'实盘净值数据(iFinD公式)'!$B14:$X14/'实盘净值数据(iFinD公式)'!$B$8:$X$8,'实盘净值数据(iFinD公式)'!$B15:$X15/'实盘净值数据(iFinD公式)'!$B14:$X14)/SUMPRODUCT(实盘持仓配置!$B$9:$X$9,'实盘净值数据(iFinD公式)'!$B14:$X14/'实盘净值数据(iFinD公式)'!$B$8:$X$8))*(1-实盘持仓配置!$Z$9)^(('实盘净值数据(iFinD公式)'!$A15-'实盘净值数据(iFinD公式)'!$A14)/365)-1) | S15: =IF(Q15="","",Q15/MAX(Q$5:Q15)-1)
A16: =IF('实盘净值数据(iFinD公式)'!A16="","",'实盘净值数据(iFinD公式)'!A16) | B16: =IF(OR((ROW()-1)<6,'实盘净值数据(iFinD公式)'!$A16="",'实盘净值数据(iFinD公式)'!$B16=""),"",SUMPRODUCT(实盘持仓配置!$B$4:$X$4,'实盘净值数据(iFinD公式)'!$B16:$X16/'实盘净值数据(iFinD公式)'!$B$6:$X$6)*(1-实盘持仓配置!$Z$4)^(('实盘净值数据(iFinD公式)'!$A16-'实盘净值数据(iFinD公式)'!$A$6)/365)) | C16: =IF(OR(B15="",'实盘净值数据(iFinD公式)'!$A16="",'实盘净值数据(iFinD公式)'!$B16=""),"",(SUMPRODUCT(实盘持仓配置!$B$4:$X$4,'实盘净值数据(iFinD公式)'!$B15:$X15/'实盘净值数据(iFinD公式)'!$B$6:$X$6,'实盘净值数据(iFinD公式)'!$B16:$X16/'实盘净值数据(iFinD公式)'!$B15:$X15)/SUMPRODUCT(实盘持仓配置!$B$4:$X$4,'实盘净值数据(iFinD公式)'!$B15:$X15/'实盘净值数据(iFinD公式)'!$B$6:$X$6))*(1-实盘持仓配置!$Z$4)^(('实盘净值数据(iFinD公式)'!$A16-'实盘净值数据(iFinD公式)'!$A15)/365)-1) | D16: =IF(B16="","",B16/MAX(B$5:B16)-1) | E16: =IF(OR((ROW()-1)<5,'实盘净值数据(iFinD公式)'!$A16="",'实盘净值数据(iFinD公式)'!$B16=""),"",SUMPRODUCT(实盘持仓配置!$B$5:$X$5,'实盘净值数据(iFinD公式)'!$B16:$X16/'实盘净值数据(iFinD公式)'!$B$5:$X$5)*(1-实盘持仓配置!$Z$5)^(('实盘净值数据(iFinD公式)'!$A16-'实盘净值数据(iFinD公式)'!$A$5)/365)) | F16: =IF(OR(E15="",'实盘净值数据(iFinD公式)'!$A16="",'实盘净值数据(iFinD公式)'!$B16=""),"",(SUMPRODUCT(实盘持仓配置!$B$5:$X$5,'实盘净值数据(iFinD公式)'!$B15:$X15/'实盘净值数据(iFinD公式)'!$B$5:$X$5,'实盘净值数据(iFinD公式)'!$B16:$X16/'实盘净值数据(iFinD公式)'!$B15:$X15)/SUMPRODUCT(实盘持仓配置!$B$5:$X$5,'实盘净值数据(iFinD公式)'!$B15:$X15/'实盘净值数据(iFinD公式)'!$B$5:$X$5))*(1-实盘持仓配置!$Z$5)^(('实盘净值数据(iFinD公式)'!$A16-'实盘净值数据(iFinD公式)'!$A15)/365)-1) | G16: =IF(E16="","",E16/MAX(E$5:E16)-1) | H16: =IF(OR((ROW()-1)<7,'实盘净值数据(iFinD公式)'!$A16="",'实盘净值数据(iFinD公式)'!$B16=""),"",SUMPRODUCT(实盘持仓配置!$B$6:$X$6,'实盘净值数据(iFinD公式)'!$B16:$X16/'实盘净值数据(iFinD公式)'!$B$7:$X$7)*(1-实盘持仓配置!$Z$6)^(('实盘净值数据(iFinD公式)'!$A16-'实盘净值数据(iFinD公式)'!$A$7)/365)) | I16: =IF(OR(H15="",'实盘净值数据(iFinD公式)'!$A16="",'实盘净值数据(iFinD公式)'!$B16=""),"",(SUMPRODUCT(实盘持仓配置!$B$6:$X$6,'实盘净值数据(iFinD公式)'!$B15:$X15/'实盘净值数据(iFinD公式)'!$B$7:$X$7,'实盘净值数据(iFinD公式)'!$B16:$X16/'实盘净值数据(iFinD公式)'!$B15:$X15)/SUMPRODUCT(实盘持仓配置!$B$6:$X$6,'实盘净值数据(iFinD公式)'!$B15:$X15/'实盘净值数据(iFinD公式)'!$B$7:$X$7))*(1-实盘持仓配置!$Z$6)^(('实盘净值数据(iFinD公式)'!$A16-'实盘净值数据(iFinD公式)'!$A15)/365)-1) | J16: =IF(H16="","",H16/MAX(H$5:H16)-1) | K16: =IF(OR((ROW()-1)<8,'实盘净值数据(iFinD公式)'!$A16="",'实盘净值数据(iFinD公式)'!$B16=""),"",SUMPRODUCT(实盘持仓配置!$B$7:$X$7,'实盘净值数据(iFinD公式)'!$B16:$X16/'实盘净值数据(iFinD公式)'!$B$8:$X$8)*(1-实盘持仓配置!$Z$7)^(('实盘净值数据(iFinD公式)'!$A16-'实盘净值数据(iFinD公式)'!$A$8)/365)) | L16: =IF(OR(K15="",'实盘净值数据(iFinD公式)'!$A16="",'实盘净值数据(iFinD公式)'!$B16=""),"",(SUMPRODUCT(实盘持仓配置!$B$7:$X$7,'实盘净值数据(iFinD公式)'!$B15:$X15/'实盘净值数据(iFinD公式)'!$B$8:$X$8,'实盘净值数据(iFinD公式)'!$B16:$X16/'实盘净值数据(iFinD公式)'!$B15:$X15)/SUMPRODUCT(实盘持仓配置!$B$7:$X$7,'实盘净值数据(iFinD公式)'!$B15:$X15/'实盘净值数据(iFinD公式)'!$B$8:$X$8))*(1-实盘持仓配置!$Z$7)^(('实盘净值数据(iFinD公式)'!$A16-'实盘净值数据(iFinD公式)'!$A15)/365)-1) | M16: =IF(K16="","",K16/MAX(K$5:K16)-1) | N16: =IF(OR((ROW()-1)<5,'实盘净值数据(iFinD公式)'!$A16="",'实盘净值数据(iFinD公式)'!$B16=""),"",SUMPRODUCT(实盘持仓配置!$B$8:$X$8,'实盘净值数据(iFinD公式)'!$B16:$X16/'实盘净值数据(iFinD公式)'!$B$5:$X$5)*(1-实盘持仓配置!$Z$8)^(('实盘净值数据(iFinD公式)'!$A16-'实盘净值数据(iFinD公式)'!$A$5)/365)) | O16: =IF(OR(N15="",'实盘净值数据(iFinD公式)'!$A16="",'实盘净值数据(iFinD公式)'!$B16=""),"",(SUMPRODUCT(实盘持仓配置!$B$8:$X$8,'实盘净值数据(iFinD公式)'!$B15:$X15/'实盘净值数据(iFinD公式)'!$B$5:$X$5,'实盘净值数据(iFinD公式)'!$B16:$X16/'实盘净值数据(iFinD公式)'!$B15:$X15)/SUMPRODUCT(实盘持仓配置!$B$8:$X$8,'实盘净值数据(iFinD公式)'!$B15:$X15/'实盘净值数据(iFinD公式)'!$B$5:$X$5))*(1-实盘持仓配置!$Z$8)^(('实盘净值数据(iFinD公式)'!$A16-'实盘净值数据(iFinD公式)'!$A15)/365)-1) | P16: =IF(N16="","",N16/MAX(N$5:N16)-1) | Q16: =IF(OR((ROW()-1)<8,'实盘净值数据(iFinD公式)'!$A16="",'实盘净值数据(iFinD公式)'!$B16=""),"",SUMPRODUCT(实盘持仓配置!$B$9:$X$9,'实盘净值数据(iFinD公式)'!$B16:$X16/'实盘净值数据(iFinD公式)'!$B$8:$X$8)*(1-实盘持仓配置!$Z$9)^(('实盘净值数据(iFinD公式)'!$A16-'实盘净值数据(iFinD公式)'!$A$8)/365)) | R16: =IF(OR(Q15="",'实盘净值数据(iFinD公式)'!$A16="",'实盘净值数据(iFinD公式)'!$B16=""),"",(SUMPRODUCT(实盘持仓配置!$B$9:$X$9,'实盘净值数据(iFinD公式)'!$B15:$X15/'实盘净值数据(iFinD公式)'!$B$8:$X$8,'实盘净值数据(iFinD公式)'!$B16:$X16/'实盘净值数据(iFinD公式)'!$B15:$X15)/SUMPRODUCT(实盘持仓配置!$B$9:$X$9,'实盘净值数据(iFinD公式)'!$B15:$X15/'实盘净值数据(iFinD公式)'!$B$8:$X$8))*(1-实盘持仓配置!$Z$9)^(('实盘净值数据(iFinD公式)'!$A16-'实盘净值数据(iFinD公式)'!$A15)/365)-1) | S16: =IF(Q16="","",Q16/MAX(Q$5:Q16)-1)
A17: =IF('实盘净值数据(iFinD公式)'!A17="","",'实盘净值数据(iFinD公式)'!A17) | B17: =IF(OR((ROW()-1)<6,'实盘净值数据(iFinD公式)'!$A17="",'实盘净值数据(iFinD公式)'!$B17=""),"",SUMPRODUCT(实盘持仓配置!$B$4:$X$4,'实盘净值数据(iFinD公式)'!$B17:$X17/'实盘净值数据(iFinD公式)'!$B$6:$X$6)*(1-实盘持仓配置!$Z$4)^(('实盘净值数据(iFinD公式)'!$A17-'实盘净值数据(iFinD公式)'!$A$6)/365)) | C17: =IF(OR(B16="",'实盘净值数据(iFinD公式)'!$A17="",'实盘净值数据(iFinD公式)'!$B17=""),"",(SUMPRODUCT(实盘持仓配置!$B$4:$X$4,'实盘净值数据(iFinD公式)'!$B16:$X16/'实盘净值数据(iFinD公式)'!$B$6:$X$6,'实盘净值数据(iFinD公式)'!$B17:$X17/'实盘净值数据(iFinD公式)'!$B16:$X16)/SUMPRODUCT(实盘持仓配置!$B$4:$X$4,'实盘净值数据(iFinD公式)'!$B16:$X16/'实盘净值数据(iFinD公式)'!$B$6:$X$6))*(1-实盘持仓配置!$Z$4)^(('实盘净值数据(iFinD公式)'!$A17-'实盘净值数据(iFinD公式)'!$A16)/365)-1) | D17: =IF(B17="","",B17/MAX(B$5:B17)-1) | E17: =IF(OR((ROW()-1)<5,'实盘净值数据(iFinD公式)'!$A17="",'实盘净值数据(iFinD公式)'!$B17=""),"",SUMPRODUCT(实盘持仓配置!$B$5:$X$5,'实盘净值数据(iFinD公式)'!$B17:$X17/'实盘净值数据(iFinD公式)'!$B$5:$X$5)*(1-实盘持仓配置!$Z$5)^(('实盘净值数据(iFinD公式)'!$A17-'实盘净值数据(iFinD公式)'!$A$5)/365)) | F17: =IF(OR(E16="",'实盘净值数据(iFinD公式)'!$A17="",'实盘净值数据(iFinD公式)'!$B17=""),"",(SUMPRODUCT(实盘持仓配置!$B$5:$X$5,'实盘净值数据(iFinD公式)'!$B16:$X16/'实盘净值数据(iFinD公式)'!$B$5:$X$5,'实盘净值数据(iFinD公式)'!$B17:$X17/'实盘净值数据(iFinD公式)'!$B16:$X16)/SUMPRODUCT(实盘持仓配置!$B$5:$X$5,'实盘净值数据(iFinD公式)'!$B16:$X16/'实盘净值数据(iFinD公式)'!$B$5:$X$5))*(1-实盘持仓配置!$Z$5)^(('实盘净值数据(iFinD公式)'!$A17-'实盘净值数据(iFinD公式)'!$A16)/365)-1) | G17: =IF(E17="","",E17/MAX(E$5:E17)-1) | H17: =IF(OR((ROW()-1)<7,'实盘净值数据(iFinD公式)'!$A17="",'实盘净值数据(iFinD公式)'!$B17=""),"",SUMPRODUCT(实盘持仓配置!$B$6:$X$6,'实盘净值数据(iFinD公式)'!$B17:$X17/'实盘净值数据(iFinD公式)'!$B$7:$X$7)*(1-实盘持仓配置!$Z$6)^(('实盘净值数据(iFinD公式)'!$A17-'实盘净值数据(iFinD公式)'!$A$7)/365)) | I17: =IF(OR(H16="",'实盘净值数据(iFinD公式)'!$A17="",'实盘净值数据(iFinD公式)'!$B17=""),"",(SUMPRODUCT(实盘持仓配置!$B$6:$X$6,'实盘净值数据(iFinD公式)'!$B16:$X16/'实盘净值数据(iFinD公式)'!$B$7:$X$7,'实盘净值数据(iFinD公式)'!$B17:$X17/'实盘净值数据(iFinD公式)'!$B16:$X16)/SUMPRODUCT(实盘持仓配置!$B$6:$X$6,'实盘净值数据(iFinD公式)'!$B16:$X16/'实盘净值数据(iFinD公式)'!$B$7:$X$7))*(1-实盘持仓配置!$Z$6)^(('实盘净值数据(iFinD公式)'!$A17-'实盘净值数据(iFinD公式)'!$A16)/365)-1) | J17: =IF(H17="","",H17/MAX(H$5:H17)-1) | K17: =IF(OR((ROW()-1)<8,'实盘净值数据(iFinD公式)'!$A17="",'实盘净值数据(iFinD公式)'!$B17=""),"",SUMPRODUCT(实盘持仓配置!$B$7:$X$7,'实盘净值数据(iFinD公式)'!$B17:$X17/'实盘净值数据(iFinD公式)'!$B$8:$X$8)*(1-实盘持仓配置!$Z$7)^(('实盘净值数据(iFinD公式)'!$A17-'实盘净值数据(iFinD公式)'!$A$8)/365)) | L17: =IF(OR(K16="",'实盘净值数据(iFinD公式)'!$A17="",'实盘净值数据(iFinD公式)'!$B17=""),"",(SUMPRODUCT(实盘持仓配置!$B$7:$X$7,'实盘净值数据(iFinD公式)'!$B16:$X16/'实盘净值数据(iFinD公式)'!$B$8:$X$8,'实盘净值数据(iFinD公式)'!$B17:$X17/'实盘净值数据(iFinD公式)'!$B16:$X16)/SUMPRODUCT(实盘持仓配置!$B$7:$X$7,'实盘净值数据(iFinD公式)'!$B16:$X16/'实盘净值数据(iFinD公式)'!$B$8:$X$8))*(1-实盘持仓配置!$Z$7)^(('实盘净值数据(iFinD公式)'!$A17-'实盘净值数据(iFinD公式)'!$A16)/365)-1) | M17: =IF(K17="","",K17/MAX(K$5:K17)-1) | N17: =IF(OR((ROW()-1)<5,'实盘净值数据(iFinD公式)'!$A17="",'实盘净值数据(iFinD公式)'!$B17=""),"",SUMPRODUCT(实盘持仓配置!$B$8:$X$8,'实盘净值数据(iFinD公式)'!$B17:$X17/'实盘净值数据(iFinD公式)'!$B$5:$X$5)*(1-实盘持仓配置!$Z$8)^(('实盘净值数据(iFinD公式)'!$A17-'实盘净值数据(iFinD公式)'!$A$5)/365)) | O17: =IF(OR(N16="",'实盘净值数据(iFinD公式)'!$A17="",'实盘净值数据(iFinD公式)'!$B17=""),"",(SUMPRODUCT(实盘持仓配置!$B$8:$X$8,'实盘净值数据(iFinD公式)'!$B16:$X16/'实盘净值数据(iFinD公式)'!$B$5:$X$5,'实盘净值数据(iFinD公式)'!$B17:$X17/'实盘净值数据(iFinD公式)'!$B16:$X16)/SUMPRODUCT(实盘持仓配置!$B$8:$X$8,'实盘净值数据(iFinD公式)'!$B16:$X16/'实盘净值数据(iFinD公式)'!$B$5:$X$5))*(1-实盘持仓配置!$Z$8)^(('实盘净值数据(iFinD公式)'!$A17-'实盘净值数据(iFinD公式)'!$A16)/365)-1) | P17: =IF(N17="","",N17/MAX(N$5:N17)-1) | Q17: =IF(OR((ROW()-1)<8,'实盘净值数据(iFinD公式)'!$A17="",'实盘净值数据(iFinD公式)'!$B17=""),"",SUMPRODUCT(实盘持仓配置!$B$9:$X$9,'实盘净值数据(iFinD公式)'!$B17:$X17/'实盘净值数据(iFinD公式)'!$B$8:$X$8)*(1-实盘持仓配置!$Z$9)^(('实盘净值数据(iFinD公式)'!$A17-'实盘净值数据(iFinD公式)'!$A$8)/365)) | R17: =IF(OR(Q16="",'实盘净值数据(iFinD公式)'!$A17="",'实盘净值数据(iFinD公式)'!$B17=""),"",(SUMPRODUCT(实盘持仓配置!$B$9:$X$9,'实盘净值数据(iFinD公式)'!$B16:$X16/'实盘净值数据(iFinD公式)'!$B$8:$X$8,'实盘净值数据(iFinD公式)'!$B17:$X17/'实盘净值数据(iFinD公式)'!$B16:$X16)/SUMPRODUCT(实盘持仓配置!$B$9:$X$9,'实盘净值数据(iFinD公式)'!$B16:$X16/'实盘净值数据(iFinD公式)'!$B$8:$X$8))*(1-实盘持仓配置!$Z$9)^(('实盘净值数据(iFinD公式)'!$A17-'实盘净值数据(iFinD公式)'!$A16)/365)-1) | S17: =IF(Q17="","",Q17/MAX(Q$5:Q17)-1)
A18: =IF('实盘净值数据(iFinD公式)'!A18="","",'实盘净值数据(iFinD公式)'!A18) | B18: =IF(OR((ROW()-1)<6,'实盘净值数据(iFinD公式)'!$A18="",'实盘净值数据(iFinD公式)'!$B18=""),"",SUMPRODUCT(实盘持仓配置!$B$4:$X$4,'实盘净值数据(iFinD公式)'!$B18:$X18/'实盘净值数据(iFinD公式)'!$B$6:$X$6)*(1-实盘持仓配置!$Z$4)^(('实盘净值数据(iFinD公式)'!$A18-'实盘净值数据(iFinD公式)'!$A$6)/365)) | C18: =IF(OR(B17="",'实盘净值数据(iFinD公式)'!$A18="",'实盘净值数据(iFinD公式)'!$B18=""),"",(SUMPRODUCT(实盘持仓配置!$B$4:$X$4,'实盘净值数据(iFinD公式)'!$B17:$X17/'实盘净值数据(iFinD公式)'!$B$6:$X$6,'实盘净值数据(iFinD公式)'!$B18:$X18/'实盘净值数据(iFinD公式)'!$B17:$X17)/SUMPRODUCT(实盘持仓配置!$B$4:$X$4,'实盘净值数据(iFinD公式)'!$B17:$X17/'实盘净值数据(iFinD公式)'!$B$6:$X$6))*(1-实盘持仓配置!$Z$4)^(('实盘净值数据(iFinD公式)'!$A18-'实盘净值数据(iFinD公式)'!$A17)/365)-1) | D18: =IF(B18="","",B18/MAX(B$5:B18)-1) | E18: =IF(OR((ROW()-1)<5,'实盘净值数据(iFinD公式)'!$A18="",'实盘净值数据(iFinD公式)'!$B18=""),"",SUMPRODUCT(实盘持仓配置!$B$5:$X$5,'实盘净值数据(iFinD公式)'!$B18:$X18/'实盘净值数据(iFinD公式)'!$B$5:$X$5)*(1-实盘持仓配置!$Z$5)^(('实盘净值数据(iFinD公式)'!$A18-'实盘净值数据(iFinD公式)'!$A$5)/365)) | F18: =IF(OR(E17="",'实盘净值数据(iFinD公式)'!$A18="",'实盘净值数据(iFinD公式)'!$B18=""),"",(SUMPRODUCT(实盘持仓配置!$B$5:$X$5,'实盘净值数据(iFinD公式)'!$B17:$X17/'实盘净值数据(iFinD公式)'!$B$5:$X$5,'实盘净值数据(iFinD公式)'!$B18:$X18/'实盘净值数据(iFinD公式)'!$B17:$X17)/SUMPRODUCT(实盘持仓配置!$B$5:$X$5,'实盘净值数据(iFinD公式)'!$B17:$X17/'实盘净值数据(iFinD公式)'!$B$5:$X$5))*(1-实盘持仓配置!$Z$5)^(('实盘净值数据(iFinD公式)'!$A18-'实盘净值数据(iFinD公式)'!$A17)/365)-1) | G18: =IF(E18="","",E18/MAX(E$5:E18)-1) | H18: =IF(OR((ROW()-1)<7,'实盘净值数据(iFinD公式)'!$A18="",'实盘净值数据(iFinD公式)'!$B18=""),"",SUMPRODUCT(实盘持仓配置!$B$6:$X$6,'实盘净值数据(iFinD公式)'!$B18:$X18/'实盘净值数据(iFinD公式)'!$B$7:$X$7)*(1-实盘持仓配置!$Z$6)^(('实盘净值数据(iFinD公式)'!$A18-'实盘净值数据(iFinD公式)'!$A$7)/365)) | I18: =IF(OR(H17="",'实盘净值数据(iFinD公式)'!$A18="",'实盘净值数据(iFinD公式)'!$B18=""),"",(SUMPRODUCT(实盘持仓配置!$B$6:$X$6,'实盘净值数据(iFinD公式)'!$B17:$X17/'实盘净值数据(iFinD公式)'!$B$7:$X$7,'实盘净值数据(iFinD公式)'!$B18:$X18/'实盘净值数据(iFinD公式)'!$B17:$X17)/SUMPRODUCT(实盘持仓配置!$B$6:$X$6,'实盘净值数据(iFinD公式)'!$B17:$X17/'实盘净值数据(iFinD公式)'!$B$7:$X$7))*(1-实盘持仓配置!$Z$6)^(('实盘净值数据(iFinD公式)'!$A18-'实盘净值数据(iFinD公式)'!$A17)/365)-1) | J18: =IF(H18="","",H18/MAX(H$5:H18)-1) | K18: =IF(OR((ROW()-1)<8,'实盘净值数据(iFinD公式)'!$A18="",'实盘净值数据(iFinD公式)'!$B18=""),"",SUMPRODUCT(实盘持仓配置!$B$7:$X$7,'实盘净值数据(iFinD公式)'!$B18:$X18/'实盘净值数据(iFinD公式)'!$B$8:$X$8)*(1-实盘持仓配置!$Z$7)^(('实盘净值数据(iFinD公式)'!$A18-'实盘净值数据(iFinD公式)'!$A$8)/365)) | L18: =IF(OR(K17="",'实盘净值数据(iFinD公式)'!$A18="",'实盘净值数据(iFinD公式)'!$B18=""),"",(SUMPRODUCT(实盘持仓配置!$B$7:$X$7,'实盘净值数据(iFinD公式)'!$B17:$X17/'实盘净值数据(iFinD公式)'!$B$8:$X$8,'实盘净值数据(iFinD公式)'!$B18:$X18/'实盘净值数据(iFinD公式)'!$B17:$X17)/SUMPRODUCT(实盘持仓配置!$B$7:$X$7,'实盘净值数据(iFinD公式)'!$B17:$X17/'实盘净值数据(iFinD公式)'!$B$8:$X$8))*(1-实盘持仓配置!$Z$7)^(('实盘净值数据(iFinD公式)'!$A18-'实盘净值数据(iFinD公式)'!$A17)/365)-1) | M18: =IF(K18="","",K18/MAX(K$5:K18)-1) | N18: =IF(OR((ROW()-1)<5,'实盘净值数据(iFinD公式)'!$A18="",'实盘净值数据(iFinD公式)'!$B18=""),"",SUMPRODUCT(实盘持仓配置!$B$8:$X$8,'实盘净值数据(iFinD公式)'!$B18:$X18/'实盘净值数据(iFinD公式)'!$B$5:$X$5)*(1-实盘持仓配置!$Z$8)^(('实盘净值数据(iFinD公式)'!$A18-'实盘净值数据(iFinD公式)'!$A$5)/365)) | O18: =IF(OR(N17="",'实盘净值数据(iFinD公式)'!$A18="",'实盘净值数据(iFinD公式)'!$B18=""),"",(SUMPRODUCT(实盘持仓配置!$B$8:$X$8,'实盘净值数据(iFinD公式)'!$B17:$X17/'实盘净值数据(iFinD公式)'!$B$5:$X$5,'实盘净值数据(iFinD公式)'!$B18:$X18/'实盘净值数据(iFinD公式)'!$B17:$X17)/SUMPRODUCT(实盘持仓配置!$B$8:$X$8,'实盘净值数据(iFinD公式)'!$B17:$X17/'实盘净值数据(iFinD公式)'!$B$5:$X$5))*(1-实盘持仓配置!$Z$8)^(('实盘净值数据(iFinD公式)'!$A18-'实盘净值数据(iFinD公式)'!$A17)/365)-1) | P18: =IF(N18="","",N18/MAX(N$5:N18)-1) | Q18: =IF(OR((ROW()-1)<8,'实盘净值数据(iFinD公式)'!$A18="",'实盘净值数据(iFinD公式)'!$B18=""),"",SUMPRODUCT(实盘持仓配置!$B$9:$X$9,'实盘净值数据(iFinD公式)'!$B18:$X18/'实盘净值数据(iFinD公式)'!$B$8:$X$8)*(1-实盘持仓配置!$Z$9)^(('实盘净值数据(iFinD公式)'!$A18-'实盘净值数据(iFinD公式)'!$A$8)/365)) | R18: =IF(OR(Q17="",'实盘净值数据(iFinD公式)'!$A18="",'实盘净值数据(iFinD公式)'!$B18=""),"",(SUMPRODUCT(实盘持仓配置!$B$9:$X$9,'实盘净值数据(iFinD公式)'!$B17:$X17/'实盘净值数据(iFinD公式)'!$B$8:$X$8,'实盘净值数据(iFinD公式)'!$B18:$X18/'实盘净值数据(iFinD公式)'!$B17:$X17)/SUMPRODUCT(实盘持仓配置!$B$9:$X$9,'实盘净值数据(iFinD公式)'!$B17:$X17/'实盘净值数据(iFinD公式)'!$B$8:$X$8))*(1-实盘持仓配置!$Z$9)^(('实盘净值数据(iFinD公式)'!$A18-'实盘净值数据(iFinD公式)'!$A17)/365)-1) | S18: =IF(Q18="","",Q18/MAX(Q$5:Q18)-1)
A19: =IF('实盘净值数据(iFinD公式)'!A19="","",'实盘净值数据(iFinD公式)'!A19) | B19: =IF(OR((ROW()-1)<6,'实盘净值数据(iFinD公式)'!$A19="",'实盘净值数据(iFinD公式)'!$B19=""),"",SUMPRODUCT(实盘持仓配置!$B$4:$X$4,'实盘净值数据(iFinD公式)'!$B19:$X19/'实盘净值数据(iFinD公式)'!$B$6:$X$6)*(1-实盘持仓配置!$Z$4)^(('实盘净值数据(iFinD公式)'!$A19-'实盘净值数据(iFinD公式)'!$A$6)/365)) | C19: =IF(OR(B18="",'实盘净值数据(iFinD公式)'!$A19="",'实盘净值数据(iFinD公式)'!$B19=""),"",(SUMPRODUCT(实盘持仓配置!$B$4:$X$4,'实盘净值数据(iFinD公式)'!$B18:$X18/'实盘净值数据(iFinD公式)'!$B$6:$X$6,'实盘净值数据(iFinD公式)'!$B19:$X19/'实盘净值数据(iFinD公式)'!$B18:$X18)/SUMPRODUCT(实盘持仓配置!$B$4:$X$4,'实盘净值数据(iFinD公式)'!$B18:$X18/'实盘净值数据(iFinD公式)'!$B$6:$X$6))*(1-实盘持仓配置!$Z$4)^(('实盘净值数据(iFinD公式)'!$A19-'实盘净值数据(iFinD公式)'!$A18)/365)-1) | D19: =IF(B19="","",B19/MAX(B$5:B19)-1) | E19: =IF(OR((ROW()-1)<5,'实盘净值数据(iFinD公式)'!$A19="",'实盘净值数据(iFinD公式)'!$B19=""),"",SUMPRODUCT(实盘持仓配置!$B$5:$X$5,'实盘净值数据(iFinD公式)'!$B19:$X19/'实盘净值数据(iFinD公式)'!$B$5:$X$5)*(1-实盘持仓配置!$Z$5)^(('实盘净值数据(iFinD公式)'!$A19-'实盘净值数据(iFinD公式)'!$A$5)/365)) | F19: =IF(OR(E18="",'实盘净值数据(iFinD公式)'!$A19="",'实盘净值数据(iFinD公式)'!$B19=""),"",(SUMPRODUCT(实盘持仓配置!$B$5:$X$5,'实盘净值数据(iFinD公式)'!$B18:$X18/'实盘净值数据(iFinD公式)'!$B$5:$X$5,'实盘净值数据(iFinD公式)'!$B19:$X19/'实盘净值数据(iFinD公式)'!$B18:$X18)/SUMPRODUCT(实盘持仓配置!$B$5:$X$5,'实盘净值数据(iFinD公式)'!$B18:$X18/'实盘净值数据(iFinD公式)'!$B$5:$X$5))*(1-实盘持仓配置!$Z$5)^(('实盘净值数据(iFinD公式)'!$A19-'实盘净值数据(iFinD公式)'!$A18)/365)-1) | G19: =IF(E19="","",E19/MAX(E$5:E19)-1) | H19: =IF(OR((ROW()-1)<7,'实盘净值数据(iFinD公式)'!$A19="",'实盘净值数据(iFinD公式)'!$B19=""),"",SUMPRODUCT(实盘持仓配置!$B$6:$X$6,'实盘净值数据(iFinD公式)'!$B19:$X19/'实盘净值数据(iFinD公式)'!$B$7:$X$7)*(1-实盘持仓配置!$Z$6)^(('实盘净值数据(iFinD公式)'!$A19-'实盘净值数据(iFinD公式)'!$A$7)/365)) | I19: =IF(OR(H18="",'实盘净值数据(iFinD公式)'!$A19="",'实盘净值数据(iFinD公式)'!$B19=""),"",(SUMPRODUCT(实盘持仓配置!$B$6:$X$6,'实盘净值数据(iFinD公式)'!$B18:$X18/'实盘净值数据(iFinD公式)'!$B$7:$X$7,'实盘净值数据(iFinD公式)'!$B19:$X19/'实盘净值数据(iFinD公式)'!$B18:$X18)/SUMPRODUCT(实盘持仓配置!$B$6:$X$6,'实盘净值数据(iFinD公式)'!$B18:$X18/'实盘净值数据(iFinD公式)'!$B$7:$X$7))*(1-实盘持仓配置!$Z$6)^(('实盘净值数据(iFinD公式)'!$A19-'实盘净值数据(iFinD公式)'!$A18)/365)-1) | J19: =IF(H19="","",H19/MAX(H$5:H19)-1) | K19: =IF(OR((ROW()-1)<8,'实盘净值数据(iFinD公式)'!$A19="",'实盘净值数据(iFinD公式)'!$B19=""),"",SUMPRODUCT(实盘持仓配置!$B$7:$X$7,'实盘净值数据(iFinD公式)'!$B19:$X19/'实盘净值数据(iFinD公式)'!$B$8:$X$8)*(1-实盘持仓配置!$Z$7)^(('实盘净值数据(iFinD公式)'!$A19-'实盘净值数据(iFinD公式)'!$A$8)/365)) | L19: =IF(OR(K18="",'实盘净值数据(iFinD公式)'!$A19="",'实盘净值数据(iFinD公式)'!$B19=""),"",(SUMPRODUCT(实盘持仓配置!$B$7:$X$7,'实盘净值数据(iFinD公式)'!$B18:$X18/'实盘净值数据(iFinD公式)'!$B$8:$X$8,'实盘净值数据(iFinD公式)'!$B19:$X19/'实盘净值数据(iFinD公式)'!$B18:$X18)/SUMPRODUCT(实盘持仓配置!$B$7:$X$7,'实盘净值数据(iFinD公式)'!$B18:$X18/'实盘净值数据(iFinD公式)'!$B$8:$X$8))*(1-实盘持仓配置!$Z$7)^(('实盘净值数据(iFinD公式)'!$A19-'实盘净值数据(iFinD公式)'!$A18)/365)-1) | M19: =IF(K19="","",K19/MAX(K$5:K19)-1) | N19: =IF(OR((ROW()-1)<5,'实盘净值数据(iFinD公式)'!$A19="",'实盘净值数据(iFinD公式)'!$B19=""),"",SUMPRODUCT(实盘持仓配置!$B$8:$X$8,'实盘净值数据(iFinD公式)'!$B19:$X19/'实盘净值数据(iFinD公式)'!$B$5:$X$5)*(1-实盘持仓配置!$Z$8)^(('实盘净值数据(iFinD公式)'!$A19-'实盘净值数据(iFinD公式)'!$A$5)/365)) | O19: =IF(OR(N18="",'实盘净值数据(iFinD公式)'!$A19="",'实盘净值数据(iFinD公式)'!$B19=""),"",(SUMPRODUCT(实盘持仓配置!$B$8:$X$8,'实盘净值数据(iFinD公式)'!$B18:$X18/'实盘净值数据(iFinD公式)'!$B$5:$X$5,'实盘净值数据(iFinD公式)'!$B19:$X19/'实盘净值数据(iFinD公式)'!$B18:$X18)/SUMPRODUCT(实盘持仓配置!$B$8:$X$8,'实盘净值数据(iFinD公式)'!$B18:$X18/'实盘净值数据(iFinD公式)'!$B$5:$X$5))*(1-实盘持仓配置!$Z$8)^(('实盘净值数据(iFinD公式)'!$A19-'实盘净值数据(iFinD公式)'!$A18)/365)-1) | P19: =IF(N19="","",N19/MAX(N$5:N19)-1) | Q19: =IF(OR((ROW()-1)<8,'实盘净值数据(iFinD公式)'!$A19="",'实盘净值数据(iFinD公式)'!$B19=""),"",SUMPRODUCT(实盘持仓配置!$B$9:$X$9,'实盘净值数据(iFinD公式)'!$B19:$X19/'实盘净值数据(iFinD公式)'!$B$8:$X$8)*(1-实盘持仓配置!$Z$9)^(('实盘净值数据(iFinD公式)'!$A19-'实盘净值数据(iFinD公式)'!$A$8)/365)) | R19: =IF(OR(Q18="",'实盘净值数据(iFinD公式)'!$A19="",'实盘净值数据(iFinD公式)'!$B19=""),"",(SUMPRODUCT(实盘持仓配置!$B$9:$X$9,'实盘净值数据(iFinD公式)'!$B18:$X18/'实盘净值数据(iFinD公式)'!$B$8:$X$8,'实盘净值数据(iFinD公式)'!$B19:$X19/'实盘净值数据(iFinD公式)'!$B18:$X18)/SUMPRODUCT(实盘持仓配置!$B$9:$X$9,'实盘净值数据(iFinD公式)'!$B18:$X18/'实盘净值数据(iFinD公式)'!$B$8:$X$8))*(1-实盘持仓配置!$Z$9)^(('实盘净值数据(iFinD公式)'!$A19-'实盘净值数据(iFinD公式)'!$A18)/365)-1) | S19: =IF(Q19="","",Q19/MAX(Q$5:Q19)-1)
A20: =IF('实盘净值数据(iFinD公式)'!A20="","",'实盘净值数据(iFinD公式)'!A20) | B20: =IF(OR((ROW()-1)<6,'实盘净值数据(iFinD公式)'!$A20="",'实盘净值数据(iFinD公式)'!$B20=""),"",SUMPRODUCT(实盘持仓配置!$B$4:$X$4,'实盘净值数据(iFinD公式)'!$B20:$X20/'实盘净值数据(iFinD公式)'!$B$6:$X$6)*(1-实盘持仓配置!$Z$4)^(('实盘净值数据(iFinD公式)'!$A20-'实盘净值数据(iFinD公式)'!$A$6)/365)) | C20: =IF(OR(B19="",'实盘净值数据(iFinD公式)'!$A20="",'实盘净值数据(iFinD公式)'!$B20=""),"",(SUMPRODUCT(实盘持仓配置!$B$4:$X$4,'实盘净值数据(iFinD公式)'!$B19:$X19/'实盘净值数据(iFinD公式)'!$B$6:$X$6,'实盘净值数据(iFinD公式)'!$B20:$X20/'实盘净值数据(iFinD公式)'!$B19:$X19)/SUMPRODUCT(实盘持仓配置!$B$4:$X$4,'实盘净值数据(iFinD公式)'!$B19:$X19/'实盘净值数据(iFinD公式)'!$B$6:$X$6))*(1-实盘持仓配置!$Z$4)^(('实盘净值数据(iFinD公式)'!$A20-'实盘净值数据(iFinD公式)'!$A19)/365)-1) | D20: =IF(B20="","",B20/MAX(B$5:B20)-1) | E20: =IF(OR((ROW()-1)<5,'实盘净值数据(iFinD公式)'!$A20="",'实盘净值数据(iFinD公式)'!$B20=""),"",SUMPRODUCT(实盘持仓配置!$B$5:$X$5,'实盘净值数据(iFinD公式)'!$B20:$X20/'实盘净值数据(iFinD公式)'!$B$5:$X$5)*(1-实盘持仓配置!$Z$5)^(('实盘净值数据(iFinD公式)'!$A20-'实盘净值数据(iFinD公式)'!$A$5)/365)) | F20: =IF(OR(E19="",'实盘净值数据(iFinD公式)'!$A20="",'实盘净值数据(iFinD公式)'!$B20=""),"",(SUMPRODUCT(实盘持仓配置!$B$5:$X$5,'实盘净值数据(iFinD公式)'!$B19:$X19/'实盘净值数据(iFinD公式)'!$B$5:$X$5,'实盘净值数据(iFinD公式)'!$B20:$X20/'实盘净值数据(iFinD公式)'!$B19:$X19)/SUMPRODUCT(实盘持仓配置!$B$5:$X$5,'实盘净值数据(iFinD公式)'!$B19:$X19/'实盘净值数据(iFinD公式)'!$B$5:$X$5))*(1-实盘持仓配置!$Z$5)^(('实盘净值数据(iFinD公式)'!$A20-'实盘净值数据(iFinD公式)'!$A19)/365)-1) | G20: =IF(E20="","",E20/MAX(E$5:E20)-1) | H20: =IF(OR((ROW()-1)<7,'实盘净值数据(iFinD公式)'!$A20="",'实盘净值数据(iFinD公式)'!$B20=""),"",SUMPRODUCT(实盘持仓配置!$B$6:$X$6,'实盘净值数据(iFinD公式)'!$B20:$X20/'实盘净值数据(iFinD公式)'!$B$7:$X$7)*(1-实盘持仓配置!$Z$6)^(('实盘净值数据(iFinD公式)'!$A20-'实盘净值数据(iFinD公式)'!$A$7)/365)) | I20: =IF(OR(H19="",'实盘净值数据(iFinD公式)'!$A20="",'实盘净值数据(iFinD公式)'!$B20=""),"",(SUMPRODUCT(实盘持仓配置!$B$6:$X$6,'实盘净值数据(iFinD公式)'!$B19:$X19/'实盘净值数据(iFinD公式)'!$B$7:$X$7,'实盘净值数据(iFinD公式)'!$B20:$X20/'实盘净值数据(iFinD公式)'!$B19:$X19)/SUMPRODUCT(实盘持仓配置!$B$6:$X$6,'实盘净值数据(iFinD公式)'!$B19:$X19/'实盘净值数据(iFinD公式)'!$B$7:$X$7))*(1-实盘持仓配置!$Z$6)^(('实盘净值数据(iFinD公式)'!$A20-'实盘净值数据(iFinD公式)'!$A19)/365)-1) | J20: =IF(H20="","",H20/MAX(H$5:H20)-1) | K20: =IF(OR((ROW()-1)<8,'实盘净值数据(iFinD公式)'!$A20="",'实盘净值数据(iFinD公式)'!$B20=""),"",SUMPRODUCT(实盘持仓配置!$B$7:$X$7,'实盘净值数据(iFinD公式)'!$B20:$X20/'实盘净值数据(iFinD公式)'!$B$8:$X$8)*(1-实盘持仓配置!$Z$7)^(('实盘净值数据(iFinD公式)'!$A20-'实盘净值数据(iFinD公式)'!$A$8)/365)) | L20: =IF(OR(K19="",'实盘净值数据(iFinD公式)'!$A20="",'实盘净值数据(iFinD公式)'!$B20=""),"",(SUMPRODUCT(实盘持仓配置!$B$7:$X$7,'实盘净值数据(iFinD公式)'!$B19:$X19/'实盘净值数据(iFinD公式)'!$B$8:$X$8,'实盘净值数据(iFinD公式)'!$B20:$X20/'实盘净值数据(iFinD公式)'!$B19:$X19)/SUMPRODUCT(实盘持仓配置!$B$7:$X$7,'实盘净值数据(iFinD公式)'!$B19:$X19/'实盘净值数据(iFinD公式)'!$B$8:$X$8))*(1-实盘持仓配置!$Z$7)^(('实盘净值数据(iFinD公式)'!$A20-'实盘净值数据(iFinD公式)'!$A19)/365)-1) | M20: =IF(K20="","",K20/MAX(K$5:K20)-1) | N20: =IF(OR((ROW()-1)<5,'实盘净值数据(iFinD公式)'!$A20="",'实盘净值数据(iFinD公式)'!$B20=""),"",SUMPRODUCT(实盘持仓配置!$B$8:$X$8,'实盘净值数据(iFinD公式)'!$B20:$X20/'实盘净值数据(iFinD公式)'!$B$5:$X$5)*(1-实盘持仓配置!$Z$8)^(('实盘净值数据(iFinD公式)'!$A20-'实盘净值数据(iFinD公式)'!$A$5)/365)) | O20: =IF(OR(N19="",'实盘净值数据(iFinD公式)'!$A20="",'实盘净值数据(iFinD公式)'!$B20=""),"",(SUMPRODUCT(实盘持仓配置!$B$8:$X$8,'实盘净值数据(iFinD公式)'!$B19:$X19/'实盘净值数据(iFinD公式)'!$B$5:$X$5,'实盘净值数据(iFinD公式)'!$B20:$X20/'实盘净值数据(iFinD公式)'!$B19:$X19)/SUMPRODUCT(实盘持仓配置!$B$8:$X$8,'实盘净值数据(iFinD公式)'!$B19:$X19/'实盘净值数据(iFinD公式)'!$B$5:$X$5))*(1-实盘持仓配置!$Z$8)^(('实盘净值数据(iFinD公式)'!$A20-'实盘净值数据(iFinD公式)'!$A19)/365)-1) | P20: =IF(N20="","",N20/MAX(N$5:N20)-1) | Q20: =IF(OR((ROW()-1)<8,'实盘净值数据(iFinD公式)'!$A20="",'实盘净值数据(iFinD公式)'!$B20=""),"",SUMPRODUCT(实盘持仓配置!$B$9:$X$9,'实盘净值数据(iFinD公式)'!$B20:$X20/'实盘净值数据(iFinD公式)'!$B$8:$X$8)*(1-实盘持仓配置!$Z$9)^(('实盘净值数据(iFinD公式)'!$A20-'实盘净值数据(iFinD公式)'!$A$8)/365)) | R20: =IF(OR(Q19="",'实盘净值数据(iFinD公式)'!$A20="",'实盘净值数据(iFinD公式)'!$B20=""),"",(SUMPRODUCT(实盘持仓配置!$B$9:$X$9,'实盘净值数据(iFinD公式)'!$B19:$X19/'实盘净值数据(iFinD公式)'!$B$8:$X$8,'实盘净值数据(iFinD公式)'!$B20:$X20/'实盘净值数据(iFinD公式)'!$B19:$X19)/SUMPRODUCT(实盘持仓配置!$B$9:$X$9,'实盘净值数据(iFinD公式)'!$B19:$X19/'实盘净值数据(iFinD公式)'!$B$8:$X$8))*(1-实盘持仓配置!$Z$9)^(('实盘净值数据(iFinD公式)'!$A20-'实盘净值数据(iFinD公式)'!$A19)/365)-1) | S20: =IF(Q20="","",Q20/MAX(Q$5:Q20)-1)
