Workbook
Name AccountMethod: [1]投资!$C$66
Name DebtFinancing: [1]筹资!$E$22
Name DepositRate: [1]筹资!$B$6
Name EndYear: [1]首页!$C$9
Name EstiDate: 首页!$C$7
Name FinancingMethod: [1]筹资!$B$18
Name ics: 非财务信息!$E$17
Name iRepType: 1
Name IsInitialization: 0
Name IssuePrice: [1]筹资!$E$24
Name LastEndYear: 2007
Name LastEstiDate: 40128
Name LastEstNum: 2
Name LastHasNew: "否"
Name LastReportList: "2004;2005;2006;2007"
Name LastStYear: 2004
Name LastTransitionYear: 0
Name LastWindCode: "600028.SH"
Name LDebtFinancing: [1]筹资!$E$23
Name LongBorrowRate: [1]筹资!$B$8
Name MinCashBalance: [1]筹资!$B$9
Name nrAfter: 假设表!$C$8:$C$162
Name nrBefore: 假设表!$C$4:$C$7
Name NRPredictWay: 假设表!$C:$C
Name PeriodGrowth: [1]绝对估值!$C$5
Name RepType: [1]首页!$C$11
Name ShortBorrowRate: [1]筹资!$B$7
Name StockCode: 首页!$C$6
Name ThisEndYear: 2008
Name ThisEstiDate: 40128
Name ThisEstNum: 3
Name ThisHasNew: "否"
Name ThisReportList: "2005;2006;2007;2008"
Name ThisStYear: 2005
Name ThisTransitionYear: 0
Name ThisWindCode: "600028.SH"
Name unit: 10000
Name 高6: #REF!
Name 高6: #REF!

Sheet 首页
B9: 估值模型插件首页
B11: 需要填写的数据 | E11: 自动生成的数据
B13: 需要检查的数据 | C13: 如有数值，说明可能存在未导出的会计科目
B15: 研究部财务估值系统 | C15: A股标准估值模型 | E15: 版本号： | F15: v3.0.0.2
B17: 证券代码 | C17: 300223 | E17: 证券简称 | F17: 北京君正
B18: 预测日期 | C18: 46140 | E18: 最新收盘价（元） | F18: 124.02
B19: 历史数据始于（年） | C19: 2021 | E19: 最新股本（千股） | F19: 482540.72
B20: 历史数据止于（年） | C20: 2025 | E20: 分析师姓名 | F20: 程子盈
B21: 预测年份数 | C21: 10 | E21: 所属行业 | F21: Unknown
B22: 货币单位 | C22: 百万元 | E22: 关联模型ID | F22: 0
B23: 是否A+H股 | C23: 否 | E23: 港股证券简称
B24: 港股代码 | E24: H股价格
B25: A股评级 | C25: 买入 | E25: A股目标价
B26: A股评级变动 | C26: 维持 | E26: H股评级
B27: H股目标价 | E27: H股评级变动
B28: 市值（百万元） | C28: 59844.7 | E28: EV | F28: =C28+历史数据及预测表!H51+历史数据及预测表!H62+历史数据及预测表!H72+历史数据及预测表!H71 -> 59853.115
B30: 首页 | C30: 设置公司模型的全局参数
B31: 历史数据（原始） | C31: WIND自动导入
B32: 经营模型 | C32: 分析师手动录入收入成本的分拆预测，汇总数据汇总到前几行
B33: 假设表 | C33: 历史数据自动生成，预测数据根据所选方法生成
B34: 关键项目预测 | C34: 折旧信息需分析师手动输入相关数据，其他数据自动生成
B35: 历史数据及预测表 | C35: 历史数据自动生成，预测数据根据假设表生成
B36: 估值表 | C36: 自动生成，不可修改
B37: 非财务信息 | C37: 自动生成，不可修改
B38: 关键比率 | C38: 自动生成，不可修改
B39: 输出表-首页用表 | C39: 自动生成，不可修改
B40: 输出表-利润表 | C40: 自动生成，不可修改
B41: 输出表-资产负债表 | C41: 自动生成，不可修改
... B52: 数据单位： | C52: 目前系统所有的数据单位都为百万元，如自行录入数据，要注意单位处理。

Sheet Financials at a glance
C1: =历史数据及预测表!G4 -> 2024 | D1: =历史数据及预测表!H4 -> 2025 | E1: =历史数据及预测表!I4 -> 2026 | F1: =历史数据及预测表!J4 -> 2027 | G1: =历史数据及预测表!K4 -> 2028
B2: Overview
B3: Operating income (Rmb mn) | C3: ='输出表-首页用表'!C3 -> 4212.6259 | D3: ='输出表-首页用表'!D3 -> 4741.0076 | E3: ='输出表-首页用表'!E3 -> 8307.8438 | F3: ='输出表-首页用表'!F3 -> 10593.134 | G3: ='输出表-首页用表'!G3 -> 12526.556
B4: Growth rate (YoY,%) | C4: ='输出表-首页用表'!C4 -> -0.070250496 | D4: ='输出表-首页用表'!D4 -> 0.12542811 | E4: ='输出表-首页用表'!E4 -> 0.75233716 | F4: ='输出表-首页用表'!F4 -> 0.27507621 | G4: ='输出表-首页用表'!G4 -> 0.18251654
B5: Net profits(Rmb mn) | C5: ='输出表-首页用表'!C5 -> 366.2021 | D5: ='输出表-首页用表'!D5 -> 376.22602 | E5: ='输出表-首页用表'!E5 -> 2509.6073 | F5: ='输出表-首页用表'!F5 -> 2865.056 | G5: ='输出表-首页用表'!G5 -> 2754.3684
B6: Growth rate (YoY,%) | C6: ='输出表-首页用表'!C6 -> -0.31838231 | D6: ='输出表-首页用表'!D6 -> 0.027372662 | E6: ='输出表-首页用表'!E6 -> 5.6704777 | F6: ='输出表-首页用表'!F6 -> 0.14163519 | G6: ='输出表-首页用表'!G6 -> -0.038633644
B7: EPS (Rmb, Basic) | C7: ='输出表-首页用表'!C7 -> 0.7604 | D7: ='输出表-首页用表'!D7 -> 0.7803 | E7: ='输出表-首页用表'!E7 -> 5.2008197 | F7: ='输出表-首页用表'!F7 -> 5.9374387 | G7: ='输出表-首页用表'!G7 -> 5.7080538
B8: Gross margin (%) | C8: ='输出表-首页用表'!C8 -> 0.36729198 | D8: ='输出表-首页用表'!D8 -> 0.34086456 | E8: ='输出表-首页用表'!E8 -> 0.49659152 | F8: ='输出表-首页用表'!F8 -> 0.46612794 | G8: ='输出表-首页用表'!G8 -> 0.40944851
B9: ROE (%) | C9: ='输出表-首页用表'!C9 -> 0.030380316 | D9: ='输出表-首页用表'!D9 -> 0.030221729 | E9: ='输出表-首页用表'!E9 -> 0.16872113 | F9: ='输出表-首页用表'!F9 -> 0.16186463 | G9: ='输出表-首页用表'!G9 -> 0.13486911
B10: BVPS (Rmb) | C10: ='输出表-首页用表'!C10 -> 24.980122 | D10: ='输出表-首页用表'!D10 -> 25.798565 | E10: ='输出表-首页用表'!E10 -> 30.824945 | F10: ='输出表-首页用表'!F10 -> 36.681508 | G10: ='输出表-首页用表'!G10 -> 42.322914
B11: PE (x) | C11: ='输出表-首页用表'!C11 -> 163.09837 | D11: ='输出表-首页用表'!D11 -> 158.93887 | E11: ='输出表-首页用表'!E11 -> 23.846241 | F11: ='输出表-首页用表'!F11 -> 20.887794 | G11: ='输出表-首页用表'!G11 -> 21.727195
B12: PB (x) | C12: ='输出表-首页用表'!C12 -> 4.9647475 | D12: ='输出表-首页用表'!D12 -> 4.8072441 | E12: ='输出表-首页用表'!E12 -> 4.0233649 | F12: ='输出表-首页用表'!F12 -> 3.3809951 | G12: ='输出表-首页用表'!G12 -> 2.9303275
B13: PS (x) | C13: ='输出表-首页用表'!C13 -> 14.206033 | D13: ='输出表-首页用表'!D13 -> 12.622781 | E13: ='输出表-首页用表'!E13 -> 7.2033974 | F13: ='输出表-首页用表'!F13 -> 5.6493858 | G13: ='输出表-首页用表'!G13 -> 4.7774265
B14: EV/EBITDA | C14: ='输出表-首页用表'!C14 -> 113.29726 | D14: ='输出表-首页用表'!D14 -> 120.83313 | E14: ='输出表-首页用表'!E14 -> 22.014455 | F14: ='输出表-首页用表'!F14 -> 18.951601 | G14: ='输出表-首页用表'!G14 -> 19.850602
B15: Income statement (mn)
B16: Operating income | C16: ='输出表-利润表'!C3 -> 4212.6259 | D16: ='输出表-利润表'!D3 -> 4741.0076 | E16: ='输出表-利润表'!E3 -> 8307.8438 | F16: ='输出表-利润表'!F3 -> 10593.134 | G16: ='输出表-利润表'!G3 -> 12526.556
B17: COGS | C17: ='输出表-利润表'!C4 -> 2665.3622 | D17: ='输出表-利润表'!D4 -> 3124.9661 | E17: ='输出表-利润表'!E4 -> 4182.239 | F17: ='输出表-利润表'!F4 -> 5655.3783 | G17: ='输出表-利润表'!G4 -> 7397.5763
B18: Gross profit margin | C18: ='输出表-利润表'!C5 -> 0.36729198 | D18: ='输出表-利润表'!D5 -> 0.34086456 | E18: ='输出表-利润表'!E5 -> 0.49659152 | F18: ='输出表-利润表'!F5 -> 0.46612794 | G18: ='输出表-利润表'!G5 -> 0.40944851
B19: Taxes and surcharges | C19: ='输出表-利润表'!C6 -> 8.6082334 | D19: ='输出表-利润表'!D6 -> 13.127126 | E19: ='输出表-利润表'!E6 -> 19.482823 | F19: ='输出表-利润表'!F6 -> 25.273084 | G19: ='输出表-利润表'!G6 -> 31.315379
B20: Selling expenses | C20: ='输出表-利润表'!C7 -> 294.59831 | D20: ='输出表-利润表'!D7 -> 319.8337 | E20: ='输出表-利润表'!E7 -> 383.80044 | F20: ='输出表-利润表'!F7 -> 452.88452 | G20: ='输出表-利润表'!G7 -> 525.34604
B21: Selling expenses ratio | C21: ='输出表-利润表'!C8 -> 0.069932226 | D21: ='输出表-利润表'!D8 -> 0.067461123 | E21: ='输出表-利润表'!E8 -> 0.046197359 | F21: ='输出表-利润表'!F8 -> 0.042752647 | G21: ='输出表-利润表'!G8 -> 0.041938585
B22: Administrative expenses | C22: ='输出表-利润表'!C9 -> 215.16816 | D22: ='输出表-利润表'!D9 -> 268.14405 | E22: ='输出表-利润表'!E9 -> 321.77286 | F22: ='输出表-利润表'!F9 -> 379.69197 | G22: ='输出表-利润表'!G9 -> 440.44269
B23: Administrative expenses ratio | C23: ='输出表-利润表'!C10 -> 0.051076969 | D23: ='输出表-利润表'!D10 -> 0.056558451 | E23: ='输出表-利润表'!E10 -> 0.038731212 | F23: ='输出表-利润表'!F10 -> 0.035843214 | G23: ='输出表-利润表'!G10 -> 0.035160716
B24: Finance expenses | C24: ='输出表-利润表'!C11 -> -74.751475 | D24: ='输出表-利润表'!D11 -> -103.8903 | E24: ='输出表-利润表'!E11 -> -86.408107 | F24: ='输出表-利润表'!F11 -> -93.430081 | G24: ='输出表-利润表'!G11 -> -116.31471
B25: Finance expenses ratio | C25: ='输出表-利润表'!C12 -> -0.017744627 | D25: ='输出表-利润表'!D12 -> -0.021913126 | E25: ='输出表-利润表'!E12 -> -0.010400786 | F25: ='输出表-利润表'!F12 -> -0.0088198716 | G25: ='输出表-利润表'!G12 -> -0.0092854502
B26: R&D expense | C26: ='输出表-利润表'!C13 -> 681.33896 | D26: ='输出表-利润表'!D13 -> 712.02656 | E26: ='输出表-利润表'!E13 -> 854.43187 | F26: ='输出表-利润表'!F13 -> 1025.3182 | G26: ='输出表-利润表'!G13 -> 1230.3819
B27: R&D ratio | C27: ='输出表-利润表'!C14 -> 0.16173735 | D27: ='输出表-利润表'!D14 -> 0.15018465 | E27: ='输出表-利润表'!E14 -> 0.10284641 | F27: ='输出表-利润表'!F14 -> 0.096790832 | G27: ='输出表-利润表'!G14 -> 0.098221881
... B39: Net profit margin | C39: ='输出表-利润表'!C26 -> 0.086929651 | D39: ='输出表-利润表'!D26 -> 0.07935571 | E39: ='输出表-利润表'!E26 -> 0.30207685 | F39: ='输出表-利润表'!F26 -> 0.27046349 | G39: ='输出表-利润表'!G26 -> 0.21988234
B40: Balance sheet (mn)
B41: Cash and cash equivalent | C41: ='输出表-资产负债表'!C3 -> 3716.6476 | D41: ='输出表-资产负债表'!D3 -> 4091.6442 | E41: ='输出表-资产负债表'!E3 -> 7233.5472 | F41: ='输出表-资产负债表'!F3 -> 9237.1612 | G41: ='输出表-资产负债表'!G3 -> 10880.219
B42: Inventories | C42: ='输出表-资产负债表'!C4 -> 2672.0205 | D42: ='输出表-资产负债表'!D4 -> 2974.6471 | E42: ='输出表-资产负债表'!E4 -> 3145.0437 | F42: ='输出表-资产负债表'!F4 -> 4252.8445 | G42: ='输出表-资产负债表'!G4 -> 5562.9774
B43: Account receivable | C43: ='输出表-资产负债表'!C5 -> 388.72856 | D43: ='输出表-资产负债表'!D5 -> 466.53246 | E43: ='输出表-资产负债表'!E5 -> 774.57337 | F43: ='输出表-资产负债表'!F5 -> 1002.5153 | G43: ='输出表-资产负债表'!G5 -> 1195.3502
B44: Other current assets | C44: ='输出表-资产负债表'!C6 -> 1271.0588 | D44: ='输出表-资产负债表'!D6 -> 1160.5334 | E44: ='输出表-资产负债表'!E6 -> 1516.2664 | F44: ='输出表-资产负债表'!F6 -> 1625.17 | G44: ='输出表-资产负债表'!G6 -> 1657.7298
B45: Current assets | C45: ='输出表-资产负债表'!C7 -> 8048.4555 | D45: ='输出表-资产负债表'!D7 -> 8693.3572 | E45: ='输出表-资产负债表'!E7 -> 12669.431 | F45: ='输出表-资产负债表'!F7 -> 16117.691 | G45: ='输出表-资产负债表'!G7 -> 19296.276
B46: Fixed assets | C46: ='输出表-资产负债表'!C8 -> 467.43575 | D46: ='输出表-资产负债表'!D8 -> 462.27066 | E46: ='输出表-资产负债表'!E8 -> 599.35495 | F46: ='输出表-资产负债表'!F8 -> 717.43923 | G46: ='输出表-资产负债表'!G8 -> 816.52352
B47: Long-term equity investment | C47: ='输出表-资产负债表'!C9 -> 0.58587464 | D47: ='输出表-资产负债表'!D9 -> 0.84342957 | E47: ='输出表-资产负债表'!E9 -> 0.84342957 | F47: ='输出表-资产负债表'!F9 -> 0.84342957 | G47: ='输出表-资产负债表'!G9 -> 0.84342957
B48: Intangible assets | C48: ='输出表-资产负债表'!C10 -> 554.23946 | D48: ='输出表-资产负债表'!D10 -> 467.16111 | E48: ='输出表-资产负债表'!E10 -> 467.16111 | F48: ='输出表-资产负债表'!F10 -> 467.16111 | G48: ='输出表-资产负债表'!G10 -> 467.16111
B49: Other non-current assets | C49: ='输出表-资产负债表'!C11 -> 3856.2285 | D49: ='输出表-资产负债表'!D11 -> 3949.5729 | E49: ='输出表-资产负债表'!E11 -> 4057.0898 | F49: ='输出表-资产负债表'!F11 -> 4166.3802 | G49: ='输出表-资产负债表'!G11 -> 4272.1975
B50: Non-current assets | C50: ='输出表-资产负债表'!C12 -> 4878.4896 | D50: ='输出表-资产负债表'!D12 -> 4879.8481 | E50: ='输出表-资产负债表'!E12 -> 5124.4493 | F50: ='输出表-资产负债表'!F12 -> 5351.824 | G50: ='输出表-资产负债表'!G12 -> 5556.7255
B51: Total asset | C51: ='输出表-资产负债表'!C13 -> 12926.945 | D51: ='输出表-资产负债表'!D13 -> 13573.205 | E51: ='输出表-资产负债表'!E13 -> 17793.88 | F51: ='输出表-资产负债表'!F13 -> 21469.515 | G51: ='输出表-资产负债表'!G13 -> 24853.001
B52: Short-term loans | C52: ='输出表-资产负债表'!C14 -> 0 | D52: ='输出表-资产负债表'!D14 -> 0 | E52: ='输出表-资产负债表'!E14 -> 1659.5217 | F52: ='输出表-资产负债表'!F14 -> 2155.5962 | G52: ='输出表-资产负债表'!G14 -> 2408.5979
... B65: Total owners’ equity and liabilities | C65: ='输出表-资产负债表'!C27 -> 12926.945 | D65: ='输出表-资产负债表'!D27 -> 13573.205 | E65: ='输出表-资产负债表'!E27 -> 17793.88 | F65: ='输出表-资产负债表'!F27 -> 21469.515 | G65: ='输出表-资产负债表'!G27 -> 24853.001
B66: Cah flow statement (mn)
B67: Net profit | C67: ='输出表-现金流量表'!C3 -> 364.19778 | D67: ='输出表-现金流量表'!D3 -> 375.33076 | E67: ='输出表-现金流量表'!E3 -> 2468.7611 | F67: ='输出表-现金流量表'!F3 -> 2841.9097 | G67: ='输出表-现金流量表'!G3 -> 2729.7325
B68: D&A | C68: ='输出表-现金流量表'!C4 -> 191.06622 | D68: ='输出表-现金流量表'!D4 -> 184.65244 | E68: ='输出表-现金流量表'!E4 -> 62.915713 | F68: ='输出表-现金流量表'!F4 -> 81.915713 | G68: ='输出表-现金流量表'!G4 -> 100.91571
B69: Change in working capital | C69: ='输出表-现金流量表'!C5 -> -301.69009 | D69: ='输出表-现金流量表'!D5 -> 21.20451 | E69: ='输出表-现金流量表'!E5 -> -654.32809 | F69: ='输出表-现金流量表'!F5 -> -1138.6805 | G69: ='输出表-现金流量表'!G5 -> -1186.2405
B70: Other oprating cash flow | C70: ='输出表-现金流量表'!C6 -> 109.88102 | D70: ='输出表-现金流量表'!D6 -> 41.415069 | E70: ='输出表-现金流量表'!E6 -> -118.81831 | F70: ='输出表-现金流量表'!F6 -> -53.659737 | G70: ='输出表-现金流量表'!G6 -> -64.62309
B71: Net cash flow from operating activities | C71: ='输出表-现金流量表'!C7 -> 363.45493 | D71: ='输出表-现金流量表'!D7 -> 622.60278 | E71: ='输出表-现金流量表'!E7 -> 1758.5304 | F71: ='输出表-现金流量表'!F7 -> 1731.4852 | G71: ='输出表-现金流量表'!G7 -> 1579.7846
B72: CAPEX | C72: ='输出表-现金流量表'!C8 -> -113.10741 | D72: ='输出表-现金流量表'!D8 -> -96.866345 | E72: ='输出表-现金流量表'!E8 -> -200 | F72: ='输出表-现金流量表'!F8 -> -200 | G72: ='输出表-现金流量表'!G8 -> -200
B73: Investment income | C73: ='输出表-现金流量表'!C9 -> 25.237235 | D73: ='输出表-现金流量表'!D9 -> 33.204846 | E73: ='输出表-现金流量表'!E9 -> 26.542434 | F73: ='输出表-现金流量表'!F9 -> 28.328172 | G73: ='输出表-现金流量表'!G9 -> 29.358484
B74: Other investing cash flow | C74: ='输出表-现金流量表'!C10 -> -325.3344 | D74: ='输出表-现金流量表'!D10 -> -169.99563 | E74: ='输出表-现金流量表'!E10 -> -104.92524 | F74: ='输出表-现金流量表'!F10 -> -106.67829 | G74: ='输出表-现金流量表'!G10 -> -103.24183
B75: Net cash flow from investing activities | C75: ='输出表-现金流量表'!C11 -> -413.20458 | D75: ='输出表-现金流量表'!D11 -> -233.65713 | E75: ='输出表-现金流量表'!E11 -> -278.38281 | F75: ='输出表-现金流量表'!F11 -> -278.35012 | G75: ='输出表-现金流量表'!G11 -> -273.88334
B76: Change in equity | C76: ='输出表-现金流量表'!C12 -> 0 | D76: ='输出表-现金流量表'!D12 -> 69.936392 | E76: ='输出表-现金流量表'!E12 -> 0 | F76: ='输出表-现金流量表'!F12 -> 0 | G76: ='输出表-现金流量表'!G12 -> 0
B77: Change in liability | C77: ='输出表-现金流量表'!C13 -> 0 | D77: ='输出表-现金流量表'!D13 -> 0 | E77: ='输出表-现金流量表'!E13 -> 1659.5217 | F77: ='输出表-现金流量表'!F13 -> 496.07452 | G77: ='输出表-现金流量表'!G13 -> 253.00169
B78: Dividends payments | C78: ='输出表-现金流量表'!C14 -> -96.313981 | D78: ='输出表-现金流量表'!D14 -> -48.156239 | E78: ='输出表-现金流量表'!E14 -> -72.381108 | F78: ='输出表-现金流量表'!F14 -> 0 | G78: ='输出表-现金流量表'!G14 -> 0
... B81: Net increase in cash and cash equivalents | C81: ='输出表-现金流量表'!C17 -> -156.5559 | D81: ='输出表-现金流量表'!D17 -> 381.69771 | E81: ='输出表-现金流量表'!E17 -> 3141.903 | F81: ='输出表-现金流量表'!F17 -> 2003.614 | G81: ='输出表-现金流量表'!G17 -> 1643.0574
B82: Ratio
B83: Indicator per share
B84: EPS (Basic) | C84: =关键比率!H5 -> 0.7604 | D84: =关键比率!I5 -> 0.7803 | E84: =关键比率!J5 -> 5.2008197 | F84: =关键比率!K5 -> 5.9374387 | G84: =关键比率!L5 -> 5.7080538
B85: BVPS | C85: =关键比率!H6 -> 24.980122 | D85: =关键比率!I6 -> 25.798565 | E85: =关键比率!J6 -> 30.824945 | F85: =关键比率!K6 -> 36.681508 | G85: =关键比率!L6 -> 42.322914
B86: CFO per share | C86: =关键比率!H7 -> 0.75321089 | D86: =关键比率!I7 -> 1.2902596 | E86: =关键比率!J7 -> 3.644315 | F86: =关键比率!K7 -> 3.5882674 | G86: =关键比率!L7 -> 3.2738886
B87: EBIT per share | C87: =关键比率!H8 -> 0.69883772 | D87: =关键比率!I8 -> 0.64385135 | E87: =关键比率!J8 -> 5.5039789 | F87: =关键比率!K8 -> 6.3751991 | G87: =关键比率!L8 -> 6.0394139
B88: Free cash flow per share | C88: =关键比率!H9 -> -0.5396 | D88: =关键比率!I9 -> -0.0514 | E88: =关键比率!J9 -> 2.8208045 | F88: =关键比率!K9 -> 3.3069414 | G88: =关键比率!L9 -> 5.8531044
B89: Free cash flow per shareholder | C89: =关键比率!H10 -> -0.5592 | D89: =关键比率!I10 -> -0.0514 | E89: =关键比率!J10 -> 6.3942392 | F89: =关键比率!K10 -> 4.4802042 | G89: =关键比率!L10 -> 6.5582008
B90: Dividends | C90: =关键比率!H11 -> -0.001313 | D90: =关键比率!I11 -> 0.000991 | E90: =关键比率!J11 -> 0 | F90: =关键比率!K11 -> 0 | G90: =关键比率!L11 -> 0
B91: Profitability
B92: ROE(%) | C92: =关键比率!H13 -> 3.0715 | D92: =关键比率!I13 -> 3.0709 | E92: =关键比率!J13 -> 16.872113 | F92: =关键比率!K13 -> 16.186463 | G92: =关键比率!L13 -> 13.486911
B93: ROA(%) | C93: =关键比率!H14 -> 3.2027 | D93: =关键比率!I14 -> 2.338 | E93: =关键比率!J14 -> 14.103766 | F93: =关键比率!K14 -> 13.344763 | G93: =关键比率!L14 -> 11.082639
B94: ROIC(%) | C94: =关键比率!H15 -> 3.0715 | D94: =关键比率!I15 -> 3.0698 | E94: =关键比率!J15 -> 17.307935 | F94: =关键比率!K15 -> 15.73923 | G94: =关键比率!L15 -> 12.899853
B95: Net profit margin(%) | C95: =关键比率!H16 -> 8.6454 | D95: =关键比率!I16 -> 7.9387 | E95: =关键比率!J16 -> 30.207685 | F95: =关键比率!K16 -> 27.046349 | G95: =关键比率!L16 -> 21.988234
B96: Gross sales margin(%) | C96: =关键比率!H17 -> 34.9693 | D96: =关键比率!I17 -> 33.9034 | E96: =关键比率!J17 -> 49.659152 | F96: =关键比率!K17 -> 46.612794 | G96: =关键比率!L17 -> 40.944851
B97: Cost to sales ratio (%) | C97: =关键比率!H18 -> 65.0307 | D97: =关键比率!I18 -> 66.0966 | E97: =关键比率!J18 -> 50.340848 | F97: =关键比率!K18 -> 53.387206 | G97: =关键比率!L18 -> 59.055149
B98: Period expense ratio(%) | C98: =关键比率!H19 -> 7.1976 | D98: =关键比率!I19 -> 6.7648 | E98: =关键比率!J19 -> 7.4527784 | F98: =关键比率!K19 -> 6.977599 | G98: =关键比率!L19 -> 6.7813851
B99: EBIT margin(%) | C99: =关键比率!H20 -> 9.7575 | D99: =关键比率!I20 -> 6.5524 | E99: =关键比率!J20 -> 31.968511 | F99: =关键比率!K20 -> 29.040444 | G99: =关键比率!L20 -> 23.26468
B100: EBITDA margin(%) | C100: =关键比率!H21 -> 12.540489 | D100: =关键比率!I21 -> 10.447925 | E100: =关键比率!J21 -> 32.725816 | F100: =关键比率!K21 -> 29.813735 | G100: =关键比率!L21 -> 24.070294
B101: EBIT | C101: =关键比率!H22 -> 337.21766 | D101: =关键比率!I22 -> 310.6845 | E101: =关键比率!J22 -> 2655.894 | F101: =关键比率!K22 -> 3076.2932 | G101: =关键比率!L22 -> 2914.2631
B102: EBITDA | C102: =关键比率!H23 -> 528.28388 | D102: =关键比率!I23 -> 495.33694 | E102: =关键比率!J23 -> 2718.8097 | F102: =关键比率!K23 -> 3158.2089 | G102: =关键比率!L23 -> 3015.1789
B103: Capital Structure
B104: Asset-liability ratio(%) | C104: =关键比率!H25 -> 6.5292 | D104: =关键比率!I25 -> 7.9885 | E104: =关键比率!J25 -> 16.412256 | F104: =关键比率!K25 -> 17.667507 | G104: =关键比率!L25 -> 18.022139
B105: Long term capital liability ratio (%) | C105: =关键比率!H26 -> 0 | D105: =关键比率!I26 -> 0 | E105: =关键比率!J26 -> 0.56363341 | F105: =关键比率!K26 -> 0.47407041 | G105: =关键比率!L26 -> 0.4111393
B106: Equity Multiplier(%) | C106: =关键比率!H27 -> 1.0699 | D106: =关键比率!I27 -> 1.0868 | E106: =关键比率!J27 -> 1.1963476 | F106: =关键比率!K27 -> 1.2145873 | G106: =关键比率!L27 -> 1.2198415
B107: Tangible assets / total assets (%) | C107: =关键比率!H28 -> 65.3404 | D107: =关键比率!I28 -> 65.1385 | E107: =关键比率!J28 -> 79.516945 | F107: =关键比率!K28 -> 83.023696 | G107: =关键比率!L28 -> 85.334849
B108: Equity attributable to shareholders of the parent company / total invested capital (%) | C108: =关键比率!H29 -> 100 | D108: =关键比率!I29 -> 99.9325 | E108: =关键比率!J29 -> 89.917102 | F108: =关键比率!K29 -> 89.10605 | G108: =关键比率!L29 -> 89.417423
B109: Interest-bearing debt / total capital invested (%) | C109: =关键比率!H30 -> 0 | D109: =关键比率!I30 -> 0.0675 | E109: =关键比率!J30 -> 10.082898 | F109: =关键比率!K30 -> 10.89395 | G109: =关键比率!L30 -> 10.582577
B110: Solvency
B111: Current ratio | C111: =关键比率!H32 -> 10.9042 | D111: =关键比率!I32 -> 8.6936 | E111: =关键比率!J32 -> 4.467256 | F111: =关键比率!K32 -> 4.3457774 | G111: =关键比率!L32 -> 4.3907754
B112: Quick ratio | C112: =关键比率!H33 -> 7.2841 | D112: =关键比率!I33 -> 5.7188 | E112: =关键比率!J33 -> 3.3583099 | F112: =关键比率!K33 -> 3.1990924 | G112: =关键比率!L33 -> 3.1249465
B113: Super Quick Ratio | C113: =关键比率!H34 -> 7.2776 | D113: =关键比率!I34 -> 5.617 | E113: =关键比率!J34 -> 3.2707307 | F113: =关键比率!K34 -> 3.111738 | G113: =关键比率!L34 -> 3.0317617
B114: Cash to Current Ratio | C114: =关键比率!H35 -> 0.4924 | D114: =关键比率!I35 -> 0.6226 | E114: =关键比率!J35 -> 2.867794 | F114: =关键比率!K35 -> 2.7331807 | G114: =关键比率!L35 -> 2.6804652
B115: Oper-cash into Due-debt | C115: =关键比率!H36 -> 0 | D115: =关键比率!I36 -> 0 | E115: =关键比率!J36 -> 1.0543153 | F115: =关键比率!K36 -> 0.80012793 | G115: =关键比率!L36 -> 0.65361054
B116: Cash flow interest coverage ratio | C116: =关键比率!H37 -> 0 | D116: =关键比率!I37 -> 0 | E116: =关键比率!J37 -> 46.072217 | F116: =关键比率!K37 -> 19.732539 | G116: =关键比率!L37 -> 15.048941
B117: Total tangible assets / liabilities | C117: =关键比率!H38 -> 10.0073 | D117: =关键比率!I38 -> 8.1541 | E117: =关键比率!J38 -> 4.8449734 | F117: =关键比率!K38 -> 4.6992308 | G117: =关键比率!L38 -> 4.7350012
B118: Tangible assets / debt | C118: =关键比率!H39 -> 0 | D118: =关键比率!I39 -> 1050.7671 | E118: =关键比率!J39 -> 8.4830297 | F118: =关键比率!K39 -> 8.2369219 | G118: =关键比率!L39 -> 8.7745822
B119: Tangible assets / net debt | C119: =关键比率!H40 -> -2.2755 | D119: =关键比率!I40 -> -2.1677 | E119: =关键比率!J40 -> -2.5422454 | F119: =关键比率!K40 -> -2.5200629 | G119: =关键比率!L40 -> -2.5059381
B120: EBITDA / liabilities | C120: =关键比率!H41 -> 0 | D120: =关键比率!I41 -> 0.4462 | E120: =关键比率!J41 -> 0.93097895 | F120: =关键比率!K41 -> 0.83261328 | G120: =关键比率!L41 -> 0.67317488
B121: Interest earned multiple (EBIT / interest expense) | C121: =关键比率!H42 -> 0 | D121: =关键比率!I42 -> 0 | E121: =关键比率!J42 -> 69.58249 | F121: =关键比率!K42 -> 35.058386 | G121: =关键比率!L42 -> 27.76111
B122: Long term debt to working capital ratio | C122: =关键比率!H43 -> 0.0145 | D122: =关键比率!I43 -> 0.011 | E122: =关键比率!J43 -> 0.023742238 | F122: =关键比率!K43 -> 0.017977646 | G122: =关键比率!L43 -> 0.014348367
... B125: EBITDA / interest expense | C125: =关键比率!H46 -> 0 | D125: =关键比率!I46 -> 0 | E125: =关键比率!J46 -> 71.230836 | F125: =关键比率!K46 -> 35.991923 | G125: =关键比率!L46 -> 28.722427
B126: Operating capacity
B127: Operating Business cycle | C127: =关键比率!H48 -> 367.69 | D127: =关键比率!I48 -> 358.0698 | E127: =关键比率!J48 -> 290.27641 | F127: =关键比率!K48 -> 265.65733 | G127: =关键比率!L48 -> 270.42363
...

Sheet 历史数据
B1: 财务年报年份 | C1: =首页!C19 -> 2021 | D1: =C1+1 -> 2022 | E1: =D1+1 -> 2023 | F1: =E1+1 -> 2024 | G1: =F1+1 -> 2025 | I1: 季报数据
B2: 利润表
A3: TTL_OPER_INC | B3: 一、营业总收入 | C3: =5274059129.97/1000000 -> 5274.0591 | D3: =5411867514.79/1000000 -> 5411.8675 | E3: =4530925656.37/1000000 -> 4530.9257 | F3: =4212625881.35/1000000 -> 4212.6259 | G3: =4741007597.96/1000000 -> 4741.0076
A4: OPER_INC | B4: 营业收入 | C4: =5274059129.97/1000000 -> 5274.0591 | D4: =5411867514.79/1000000 -> 5411.8675 | E4: =4530925656.37/1000000 -> 4530.9257 | F4: =4212625881.35/1000000 -> 4212.6259 | G4: =4741007597.96/1000000 -> 4741.0076
A5: INT_INC | B5: 利息收入 | C5: =0/1000000 -> 0 | D5: =0/1000000 -> 0 | E5: =0/1000000 -> 0 | F5: =0/1000000 -> 0 | G5: =0/1000000 -> 0
A6: IN_PREM_EARN | B6: 已赚保费 | C6: =0/1000000 -> 0 | D6: =0/1000000 -> 0 | E6: =0/1000000 -> 0 | F6: =0/1000000 -> 0 | G6: =0/1000000 -> 0
A7: INC_FEE_COMM | B7: 手续费及佣金收入 | C7: =0/1000000 -> 0 | D7: =0/1000000 -> 0 | E7: =0/1000000 -> 0 | F7: =0/1000000 -> 0 | G7: =0/1000000 -> 0
A8: TTL_OPER_COST | B8: 二、营业总成本 | C8: =4374370170.65/1000000 -> 4374.3702 | D8: =4641432866.3/1000000 -> 4641.4329 | E8: =4040530925.21/1000000 -> 4040.5309 | F8: =3864463078.61/1000000 -> 3864.4631 | G8: =4407680380.74/1000000 -> 4407.6804
A9: OPER_COST | B9: 营业成本 | C9: =3324947550.35/1000000 -> 3324.9476 | D9: =3325137649.79/1000000 -> 3325.1376 | E9: =2850000488.26/1000000 -> 2850.0005 | F9: =2665362168.81/1000000 -> 2665.3622 | G9: =3124966134.74/1000000 -> 3124.9661
A10: INT_EXP | B10: 利息支出 | C10: =0/1000000 -> 0 | D10: =0/1000000 -> 0 | E10: =0/1000000 -> 0 | F10: =0/1000000 -> 0 | G10: =0/1000000 -> 0
A11: EXP_FEE_COMM | B11: 手续费及佣金支出 | C11: =0/1000000 -> 0 | D11: =0/1000000 -> 0 | E11: =0/1000000 -> 0 | F11: =0/1000000 -> 0 | G11: =0/1000000 -> 0
A12: RFD_PREM | B12: 退保金 | C12: =0/1000000 -> 0 | D12: =0/1000000 -> 0 | E12: =0/1000000 -> 0 | F12: =0/1000000 -> 0 | G12: =0/1000000 -> 0
A13: COMP_PAY | B13: 赔付支出净额 | C13: =0/1000000 -> 0 | D13: =0/1000000 -> 0 | E13: =0/1000000 -> 0 | F13: =0/1000000 -> 0 | G13: =0/1000000 -> 0
A14: CHG_RSV | B14: 提取保险合同准备金净额 | C14: =0/1000000 -> 0 | D14: =0/1000000 -> 0 | E14: =0/1000000 -> 0 | F14: =0/1000000 -> 0 | G14: =0/1000000 -> 0
A15: PH_DVD_EXP | B15: 保单红利支出 | C15: =0/1000000 -> 0 | D15: =0/1000000 -> 0 | E15: =0/1000000 -> 0 | F15: =0/1000000 -> 0 | G15: =0/1000000 -> 0
A16: RIN_PREM_EXP | B16: 分保费用 | C16: =0/1000000 -> 0 | D16: =0/1000000 -> 0 | E16: =0/1000000 -> 0 | F16: =0/1000000 -> 0 | G16: =0/1000000 -> 0
A17: BIZ_TAX_SUR | B17: 税金及附加 | C17: =11305142.21/1000000 -> 11.305142 | D17: =6657646.68/1000000 -> 6.6576467 | E17: =10072483.48/1000000 -> 10.072483 | F17: =8608233.39/1000000 -> 8.6082334 | G17: =13127125.82/1000000 -> 13.127126
A18: SELL_EXP | B18: 销售费用 | C18: =258623991.98/1000000 -> 258.62399 | D18: =291342196.16/1000000 -> 291.3422 | E18: =313072501.21/1000000 -> 313.0725 | F18: =294598306.69/1000000 -> 294.59831 | G18: =319833698.94/1000000 -> 319.8337
A19: ADM_EXP | B19: 管理费用 | C19: =159620351.63/1000000 -> 159.62035 | D19: =166115463.65/1000000 -> 166.11546 | E19: =178849144.37/1000000 -> 178.84914 | F19: =215168160.04/1000000 -> 215.16816 | G19: =268144047.85/1000000 -> 268.14405
A20: R_D_EXP | B20: 研发费用 | C20: =521200919.41/1000000 -> 521.20092 | D20: =641629834.65/1000000 -> 641.62983 | E20: =708345090/1000000 -> 708.34509 | F20: =681338961.4/1000000 -> 681.33896 | G20: =712026562.17/1000000 -> 712.02656
A21: FIN_EXP | B21: 财务费用 | C21: =-19706705.54/1000000 -> -19.706706 | D21: =-67663031.77/1000000 -> -67.663032 | E21: =-92701810.9/1000000 -> -92.701811 | F21: =-74751474.5/1000000 -> -74.751475 | G21: =-103890297.65/1000000 -> -103.8903
A22: FIN_EXP_INT_INC | B22: 其中：利息收入 | C22: =19310772.45/1000000 -> 19.310772 | D22: =40733965.84/1000000 -> 40.733966 | E22: =67904103.32/1000000 -> 67.904103 | F22: =98688849.07/1000000 -> 98.688849 | G22: =90984362.54/1000000 -> 90.984363
A23: FIN_EXP_INT_FEE | B23: 利息费用 | C23: =800531.45/1000000 -> 0.80053145 | D23: =117139.83/1000000 -> 0.11713983 | E23: =141686.73/1000000 -> 0.14168673 | F23: =1083250.58/1000000 -> 1.0832506 | G23: =865703.21/1000000 -> 0.86570321
B24: 三、其他经营收益 | C24: 0 | D24: 0 | E24: 0 | F24: 0 | G24: 0
A25: OTH_INC | B25: 其他收益 | C25: =21504855.59/1000000 -> 21.504856 | D25: =27308135.8/1000000 -> 27.308136 | E25: =30369928.17/1000000 -> 30.369928 | F25: =32395579.86/1000000 -> 32.39558 | G25: =21326596.17/1000000 -> 21.326596
A26: AST_IMPR_LOSS | B26: 资产减值损失 | C26: =-118383667.51/1000000 -> -118.38367 | D26: =-278084891.46/1000000 -> -278.08489 | E26: =-72893028.79/1000000 -> -72.893029 | F26: =-74138722.78/1000000 -> -74.138723 | G26: =-73473108.87/1000000 -> -73.473109
A27: CRED_IMPR_LOSS | B27: 信用减值损失 | C27: =4746.9/1000000 -> 0.0047469 | D27: =-128215.68/1000000 -> -0.12821568 | E27: =0/1000000 -> 0 | F27: =0/1000000 -> 0 | G27: =0/1000000 -> 0
A28: FV_CHG_INC | B28: 公允价值变动净收益 | C28: =6362.95/1000000 -> 0.00636295 | D28: =755968.21/1000000 -> 0.75596821 | E28: =2530060.34/1000000 -> 2.5300603 | F28: =2722478/1000000 -> 2.722478 | G28: =2522389.88/1000000 -> 2.5223899
A29: INV_INC | B29: 投资净收益 | C29: =11269117.96/1000000 -> 11.269118 | D29: =14865805.07/1000000 -> 14.865805 | E29: =21185220.61/1000000 -> 21.185221 | F29: =25237234.61/1000000 -> 25.237235 | G29: =33204846.25/1000000 -> 33.204846
A30: INV_INC_JV_P | B30: 其中：对联营企业和合营企业的投资收益 | C30: =-25.12/1000000 -> -2.512e-05 | D30: =-53480.47/1000000 -> -0.05348047 | E30: =-908757.11/1000000 -> -0.90875711 | F30: =-355196.02/1000000 -> -0.35519602 | G30: =257554.93/1000000 -> 0.25755493
A31: NET_EXP_HED_BEN | B31: 净敞口套期收益 | C31: =0/1000000 -> 0 | D31: =0/1000000 -> 0 | E31: =0/1000000 -> 0 | F31: =0/1000000 -> 0 | G31: =0/1000000 -> 0
A32: AST_DSPL_INC | B32: 资产处置收益 | C32: =2058.6/1000000 -> 0.0020586 | D32: =364632.44/1000000 -> 0.36463244 | E32: =29120.05/1000000 -> 0.02912005 | F32: =8522.57/1000000 -> 0.00852257 | G32: =24130114.41/1000000 -> 24.130114
A33: FX_INC | B33: 汇兑净收益 | C33: =0/1000000 -> 0 | D33: =0/1000000 -> 0 | E33: =0/1000000 -> 0 | F33: =0/1000000 -> 0 | G33: =0/1000000 -> 0
B34: 加：营业利润差额(特殊报表科目) | C34: =C35-(C4+C5+C6+C7-C9-C10-C11-C12-C13-C14-C15-C16-C17-C18-C19-C20-C21+C26+C27+C25+C28+C29+C31+C32+C33) -> 0 | D34: =D35-(D4+D5+D6+D7-D9-D10-D11-D12-D13-D14-D15-D16-D17-D18-D19-D20-D21+D26+D27+D25+D28+D29+D31+D32+D33) -> 0 | E34: =E35-(E4+E5+E6+E7-E9-E10-E11-E12-E13-E14-E15-E16-E17-E18-E19-E20-E21+E26+E27+E25+E28+E29+E31+E32+E33) -> 0 | F34: =F35-(F4+F5+F6+F7-F9-F10-F11-F12-F13-F14-F15-F16-F17-F18-F19-F20-F21+F26+F27+F25+F28+F29+F31+F32+F33) -> 0 | G34: =G35-(G4+G5+G6+G7-G9-G10-G11-G12-G13-G14-G15-G16-G17-G18-G19-G20-G21+G26+G27+G25+G28+G29+G31+G32+G33) -> 0
A35: OPER_PROF | B35: 四、营业利润 | C35: =932471354.42/1000000 -> 932.47135 | D35: =813729190.01/1000000 -> 813.72919 | E35: =544509060.33/1000000 -> 544.50906 | F35: =408526617.78/1000000 -> 408.52662 | G35: =414511163.93/1000000 -> 414.51116
A36: NOPER_INC | B36: 加：营业外收入 | C36: =1609327.87/1000000 -> 1.6093279 | D36: =1458929.36/1000000 -> 1.4589294 | E36: =1140517.89/1000000 -> 1.1405179 | F36: =3050670.71/1000000 -> 3.0506707 | G36: =1119670.31/1000000 -> 1.1196703
A37: NOPER_EXP | B37: 减：营业外支出 | C37: =65686.68/1000000 -> 0.06568668 | D37: =192701.11/1000000 -> 0.19270111 | E37: =444660.41/1000000 -> 0.44466041 | F37: =1612472.3/1000000 -> 1.6124723 | G37: =1951303.39/1000000 -> 1.9513034
A38: LOSS_DSPL_NCUR_AST | B38: 其中：非流动资产处置净损失 | C38: =0/1000000 -> 0 | D38: =0/1000000 -> 0 | E38: =0/1000000 -> 0 | F38: =0/1000000 -> 0 | G38: =0/1000000 -> 0
B39: 加：利润总额差额(特殊报表科目) | C39: =C40-(C35+C36-C37) -> 0 | D39: =D40-(D35+D36-D37) -> 0 | E39: =E40-(E35+E36-E37) -> 0 | F39: =F40-(F35+F36-F37) -> 0 | G39: =G40-(G35+G36-G37) -> 0
A40: TTL_PROF | B40: 五、利润总额 | C40: =934014995.61/1000000 -> 934.015 | D40: =814995418.26/1000000 -> 814.99542 | E40: =545204917.81/1000000 -> 545.20492 | F40: =409964816.19/1000000 -> 409.96482 | G40: =413679530.85/1000000 -> 413.67953
A41: INC_TAX_EXP | B41: 减：所得税 | C41: =12644002.49/1000000 -> 12.644002 | D41: =36058611.32/1000000 -> 36.058611 | E41: =29480483.3/1000000 -> 29.480483 | F41: =45767036.44/1000000 -> 45.767036 | G41: =38348772.15/1000000 -> 38.348772
A42: NREC_INV_LOSS | B42: 加：未确认的投资损失 | C42: =0/1000000 -> 0 | D42: =0/1000000 -> 0 | E42: =0/1000000 -> 0 | F42: =0/1000000 -> 0 | G42: =0/1000000 -> 0
B43: 加：净利润差额(特殊报表科目) | C43: =C44-(C40-C41+C42) -> 0 | D43: =D44-(D40-D41+D42) -> 0 | E43: =E44-(E40-E41+E42) -> 0 | F43: =F44-(F40-F41+F42) -> 0 | G43: =G44-(G40-G41+G42) -> 0
A44: NET_PRO | B44: 六、净利润 | C44: =921370993.12/1000000 -> 921.37099 | D44: =778936806.94/1000000 -> 778.93681 | E44: =515724434.51/1000000 -> 515.72443 | F44: =364197779.75/1000000 -> 364.19778 | G44: =375330758.7/1000000 -> 375.33076
A45: MIN_SH_INC | B45: 减：少数股东损益 | C45: =-4810177.59/1000000 -> -4.8101776 | D45: =-10306753.1/1000000 -> -10.306753 | E45: =-21529953.56/1000000 -> -21.529954 | F45: =-2004316.99/1000000 -> -2.004317 | G45: =-895264.36/1000000 -> -0.89526436
A46: NET_PROF_PCO_SPCL | B46: 归属于母公司所有者的净利润 | C46: =926181170.71/1000000 -> 926.18117 | D46: =789243560.04/1000000 -> 789.24356 | E46: =537254388.07/1000000 -> 537.25439 | F46: =366202096.74/1000000 -> 366.2021 | G46: =376226023.06/1000000 -> 376.22602
A47: OTH_TTL_INC | B47: 加：其他综合收益 | C47: =-39835858.7/1000000 -> -39.835859 | D47: =224784081.29/1000000 -> 224.78408 | E47: =69903818.39/1000000 -> 69.903818 | F47: =-59621816.37/1000000 -> -59.621816 | G47: =-45661901.09/1000000 -> -45.661901
A48: TTL_COMP_INC | B48: 七、综合收益总额 | C48: =881535134.42/1000000 -> 881.53513 | D48: =1003720888.23/1000000 -> 1003.7209 | E48: =585628252.9/1000000 -> 585.62825 | F48: =304575963.38/1000000 -> 304.57596 | G48: =329668857.61/1000000 -> 329.66886
A49: PCO_TTL_COMP_INC | B49: 减：归属于少数股东的综合收益总额 | C49: =-4722158.38/1000000 -> -4.7221584 | D49: =-10069512.76/1000000 -> -10.069513 | E49: =-21109596.32/1000000 -> -21.109596 | F49: =-2784013.5/1000000 -> -2.7840135 | G49: =-755620.19/1000000 -> -0.75562019
A50: MS_TTL_COMP_INC | B50: 归属于母公司普通股东综合收益总额 | C50: =886257292.8/1000000 -> 886.25729 | D50: =1013790400.99/1000000 -> 1013.7904 | E50: =606737849.22/1000000 -> 606.73785 | F50: =307359976.88/1000000 -> 307.35998 | G50: =330424477.8/1000000 -> 330.42448
B51: 八、每股收益： | C51: 0 | D51: 0 | E51: 0 | F51: 0 | G51: 0
A52: EPS_BAS | B52: (一) 基本每股收益(元) | C52: 1.9705 | D52: 1.6389 | E52: 1.1156 | F52: 0.7604 | G52: 0.7803
A53: EPS_DIL | B53: (二) 稀释每股收益(元) | C53: 1.9705 | D53: 1.6389 | E53: 1.1156 | F53: 0.7592 | G53: 0.7781
B55: 资产负债表
B56: 流动资产：
A57: MNY_CPTL | B57: 货币资金 | C57: =2918515815.85/1000000 -> 2918.5158 | D57: =3400750573.3/1000000 -> 3400.7506 | E57: =3927271066.93/1000000 -> 3927.2711 | F57: =3716647634.05/1000000 -> 3716.6476 | G57: =4091644233.3/1000000 -> 4091.6442
A58: BAL_CLR | B58: 结算备付金 | C58: =0/1000000 -> 0 | D58: =0/1000000 -> 0 | E58: =0/1000000 -> 0 | F58: =0/1000000 -> 0 | G58: =0/1000000 -> 0
A59: LN_TO_OB | B59: 拆出资金 | C59: =0/1000000 -> 0 | D59: =0/1000000 -> 0 | E59: =0/1000000 -> 0 | F59: =0/1000000 -> 0 | G59: =0/1000000 -> 0
A60: TRD_FIN_AST | B60: 交易性金融资产 | C60: =962223278.55/1000000 -> 962.22328 | D60: =350606803.1/1000000 -> 350.6068 | E60: =393865132/1000000 -> 393.86513 | F60: =757737081.95/1000000 -> 757.73708 | G60: =899704566.73/1000000 -> 899.70457
A61: DERIV_FIN_AST | B61: 衍生金融资产 | C61: =0/1000000 -> 0 | D61: =0/1000000 -> 0 | E61: =0/1000000 -> 0 | F61: =0/1000000 -> 0 | G61: =0/1000000 -> 0
A62: ACCT_RCV | B62: 应收账款 | C62: =658228909.43/1000000 -> 658.22891 | D62: =515980742.71/1000000 -> 515.98074 | E62: =403348797.21/1000000 -> 403.3488 | F62: =388728561.44/1000000 -> 388.72856 | G62: =466532460.33/1000000 -> 466.53246
A63: NOTE_RCV | B63: 应收票据 | C63: =2702368.75/1000000 -> 2.7023688 | D63: =4441972.61/1000000 -> 4.4419726 | E63: =3983684.21/1000000 -> 3.9836842 | F63: =2222831.71/1000000 -> 2.2228317 | G63: =4248796.06/1000000 -> 4.2487961
A64: ACCT_RCV_FIN | B64: 应收款项融资 | C64: =0/1000000 -> 0 | D64: =0/1000000 -> 0 | E64: =0/1000000 -> 0 | F64: =0/1000000 -> 0 | G64: =0/1000000 -> 0
A65: PPAY | B65: 预付款项 | C65: =29270318.65/1000000 -> 29.270319 | D65: =54214687.7/1000000 -> 54.214688 | E65: =69007065.53/1000000 -> 69.007066 | F65: =89784502.68/1000000 -> 89.784503 | G65: =157536178.01/1000000 -> 157.53618
A66: PREM_RCV | B66: 应收保费 | C66: =0/1000000 -> 0 | D66: =0/1000000 -> 0 | E66: =0/1000000 -> 0 | F66: =0/1000000 -> 0 | G66: =0/1000000 -> 0
A67: PREM_RCV_RIN | B67: 应收分保账款 | C67: =0/1000000 -> 0 | D67: =0/1000000 -> 0 | E67: =0/1000000 -> 0 | F67: =0/1000000 -> 0 | G67: =0/1000000 -> 0
A68: RCV_RIN_RSV | B68: 应收分保合同准备金 | C68: =0/1000000 -> 0 | D68: =0/1000000 -> 0 | E68: =0/1000000 -> 0 | F68: =0/1000000 -> 0 | G68: =0/1000000 -> 0
A69: OTH_RCV_H | B69: 其他应收款 | C69: =94215122.4/1000000 -> 94.215122 | D69: =101897452.84/1000000 -> 101.89745 | E69: =284038530.38/1000000 -> 284.03853 | F69: =284817717.83/1000000 -> 284.81772 | G69: =1657225.2/1000000 -> 1.6572252
A70: PUR_RESELL_FIN_AST | B70: 买入返售金融资产 | C70: =0/1000000 -> 0 | D70: =0/1000000 -> 0 | E70: =0/1000000 -> 0 | F70: =0/1000000 -> 0 | G70: =0/1000000 -> 0
A71: INVT | B71: 存货 | C71: =1419402116.56/1000000 -> 1419.4021 | D71: =2303836726.95/1000000 -> 2303.8367 | E71: =2404780777.28/1000000 -> 2404.7808 | F71: =2672020502.5/1000000 -> 2672.0205 | G71: =2974647122.48/1000000 -> 2974.6471
A72: CONS_BIO_AST | B72: 其中：消耗性生物资产 | C72: =0/1000000 -> 0 | D72: =0/1000000 -> 0 | E72: =0/1000000 -> 0 | F72: =0/1000000 -> 0 | G72: =0/1000000 -> 0
A73: CONTR_AST | B73: 合同资产 | C73: =0/1000000 -> 0 | D73: =0/1000000 -> 0 | E73: =0/1000000 -> 0 | F73: =0/1000000 -> 0 | G73: =0/1000000 -> 0
A74: HTS_AST | B74: 持有待售资产 | C74: =0/1000000 -> 0 | D74: =0/1000000 -> 0 | E74: =0/1000000 -> 0 | F74: =0/1000000 -> 0 | G74: =0/1000000 -> 0
A75: NCUR_AST_ONE_Y | B75: 一年内到期的非流动资产 | C75: =0/1000000 -> 0 | D75: =0/1000000 -> 0 | E75: =0/1000000 -> 0 | F75: =43804254.99/1000000 -> 43.804255 | G75: =0/1000000 -> 0
A76: PPAY_EXP | B76: 待摊费用 | C76: =0/1000000 -> 0 | D76: =0/1000000 -> 0 | E76: =0/1000000 -> 0 | F76: =0/1000000 -> 0 | G76: =0/1000000 -> 0
A77: OTH_CUR_AST | B77: 其他流动资产 | C77: =45749647.72/1000000 -> 45.749648 | D77: =63361565.1/1000000 -> 63.361565 | E77: =96716587.31/1000000 -> 96.716587 | F77: =92692403.8/1000000 -> 92.692404 | G77: =97386625.59/1000000 -> 97.386626
B78: 流动资产差额(特殊报表科目) | C78: =C79-SUM(C57:C77) -> 0 | D78: =D79-SUM(D57:D77) -> 0 | E78: =E79-SUM(E57:E77) -> 0 | F78: =F79-SUM(F57:F77) -> 0 | G78: =G79-SUM(G57:G77) -> 0
A79: TTL_CUR_AST | B79: 流动资产合计 | C79: =6130307577.91/1000000 -> 6130.3076 | D79: =6795090524.31/1000000 -> 6795.0905 | E79: =7583011640.85/1000000 -> 7583.0116 | F79: =8048455490.95/1000000 -> 8048.4555 | G79: =8693357207.7/1000000 -> 8693.3572
B80: 非流动资产： | C80: 0 | D80: 0 | E80: 0 | F80: 0 | G80: 0
A81: LN_ADV_CUST | B81: 发放贷款及垫款 | C81: =0/1000000 -> 0 | D81: =0/1000000 -> 0 | E81: =0/1000000 -> 0 | F81: =0/1000000 -> 0 | G81: =0/1000000 -> 0
A82: DEBT_INV | B82: 债权投资 | C82: =0/1000000 -> 0 | D82: =0/1000000 -> 0 | E82: =0/1000000 -> 0 | F82: =0/1000000 -> 0 | G82: =0/1000000 -> 0
A83: OTS_DEBT_INV | B83: 其他债权投资 | C83: =0/1000000 -> 0 | D83: =0/1000000 -> 0 | E83: =0/1000000 -> 0 | F83: =0/1000000 -> 0 | G83: =0/1000000 -> 0
A84: AVAL_SALE_FIN_AST | B84: 可供出售金融资产 | C84: =0/1000000 -> 0 | D84: =0/1000000 -> 0 | E84: =0/1000000 -> 0 | F84: =0/1000000 -> 0 | G84: =0/1000000 -> 0
A85: HTM_INV | B85: 持有至到期投资 | C85: =0/1000000 -> 0 | D85: =0/1000000 -> 0 | E85: =0/1000000 -> 0 | F85: =0/1000000 -> 0 | G85: =0/1000000 -> 0
A86: LT_RCV | B86: 长期应收款 | C86: =522284758.37/1000000 -> 522.28476 | D86: =393131221.93/1000000 -> 393.13122 | E86: =222039309.05/1000000 -> 222.03931 | F86: =0/1000000 -> 0 | G86: =0/1000000 -> 0
A87: LT_EQY_INV | B87: 长期股权投资 | C87: =1903308.24/1000000 -> 1.9033082 | D87: =1849827.77/1000000 -> 1.8498278 | E87: =941070.66/1000000 -> 0.94107066 | F87: =585874.64/1000000 -> 0.58587464 | G87: =843429.57/1000000 -> 0.84342957
A88: OTH_EQY_INV | B88: 其他权益工具投资 | C88: =153490097.14/1000000 -> 153.4901 | D88: =325616710.73/1000000 -> 325.61671 | E88: =427812867.67/1000000 -> 427.81287 | F88: =547523024.09/1000000 -> 547.52302 | G88: =648167360.97/1000000 -> 648.16736
A89: OTH_NCUR_FIN_AST | B89: 其他非流动金融资产 | C89: =0/1000000 -> 0 | D89: =0/1000000 -> 0 | E89: =0/1000000 -> 0 | F89: =0/1000000 -> 0 | G89: =0/1000000 -> 0
A90: INV_PROP | B90: 投资性房地产 | C90: =29402909.36/1000000 -> 29.402909 | D90: =28665983.96/1000000 -> 28.665984 | E90: =79583366.31/1000000 -> 79.583366 | F90: =83488206.28/1000000 -> 83.488206 | G90: =83174293.84/1000000 -> 83.174294
A91: FIX_AST_H | B91: 固定资产 | C91: =378439328.06/1000000 -> 378.43933 | D91: =367426474.25/1000000 -> 367.42647 | E91: =451352120.3/1000000 -> 451.35212 | F91: =467435747.82/1000000 -> 467.43575 | G91: =462270658.41/1000000 -> 462.27066
A92: CONST_PROG_H | B92: 在建工程 | C92: =111591235.93/1000000 -> 111.59124 | D92: =133476198.16/1000000 -> 133.4762 | E92: =4067220.6/1000000 -> 4.0672206 | F92: =1326662.35/1000000 -> 1.3266624 | G92: =9680007.14/1000000 -> 9.6800071
A93: CPTL_BIO_AST | B93: 生产性生物资产 | C93: =0/1000000 -> 0 | D93: =0/1000000 -> 0 | E93: =0/1000000 -> 0 | F93: =0/1000000 -> 0 | G93: =0/1000000 -> 0
A94: OIL_GAS_AST | B94: 油气资产 | C94: =0/1000000 -> 0 | D94: =0/1000000 -> 0 | E94: =0/1000000 -> 0 | F94: =0/1000000 -> 0 | G94: =0/1000000 -> 0
A95: RIG_AST | B95: 使用权资产 | C95: =14418877.21/1000000 -> 14.418877 | D95: =14735645.63/1000000 -> 14.735646 | E95: =31789417.65/1000000 -> 31.789418 | F95: =22866891.48/1000000 -> 22.866891 | G95: =16938198.79/1000000 -> 16.938199
A96: INTG_AST | B96: 无形资产 | C96: =778579462.07/1000000 -> 778.57946 | D96: =720851735.36/1000000 -> 720.85174 | E96: =644585228.69/1000000 -> 644.58523 | F96: =554239455.09/1000000 -> 554.23946 | G96: =467161105.25/1000000 -> 467.16111
A97: R_D_EXP | B97: 开发支出 | C97: =98804344.04/1000000 -> 98.804344 | D97: =82689957.55/1000000 -> 82.689958 | E97: =46655253.52/1000000 -> 46.655254 | F97: =55854248.99/1000000 -> 55.854249 | G97: =37254586.98/1000000 -> 37.254587
A98: GW | B98: 商誉 | C98: =3007784304.89/1000000 -> 3007.7843 | D98: =3007784304.89/1000000 -> 3007.7843 | E98: =3007784304.89/1000000 -> 3007.7843 | F98: =3007784304.89/1000000 -> 3007.7843 | G98: =3007784304.89/1000000 -> 3007.7843
A99: LT_PPAY_EXP | B99: 长期待摊费用 | C99: =5231924.91/1000000 -> 5.2319249 | D99: =3123706.24/1000000 -> 3.1237062 | E99: =0/1000000 -> 0 | F99: =0/1000000 -> 0 | G99: =0/1000000 -> 0
A100: DFR_TAX_AST | B100: 递延所得税资产 | C100: =90376920.35/1000000 -> 90.37692 | D100: =119256755.39/1000000 -> 119.25676 | E100: =134871756.1/1000000 -> 134.87176 | F100: =129085624.04/1000000 -> 129.08562 | G100: =132530178.87/1000000 -> 132.53018
A101: OTH_NCUR_AST | B101: 其他非流动资产 | C101: =12411177.68/1000000 -> 12.411178 | D101: =428137584.4/1000000 -> 428.13758 | E101: =107533383.12/1000000 -> 107.53338 | F101: =8299569.65/1000000 -> 8.2995697 | G101: =14043961.06/1000000 -> 14.043961
...

Sheet 经营模型
K1: 单位：百万元
C2: 历史数据 | H2: 预测数据
C3: =历史数据!C1 -> 2021 | D3: =历史数据!D1 -> 2022 | E3: =历史数据!E1 -> 2023 | F3: =历史数据!F1 -> 2024 | G3: =历史数据!G1 -> 2025 | H3: =历史数据及预测表!I4 -> 2026 | I3: =历史数据及预测表!J4 -> 2027 | J3: =历史数据及预测表!K4 -> 2028 | K3: =历史数据及预测表!L4 -> 2029
B4: 营业收入合计 | C4: =历史数据及预测表!D107 -> 5274.0591 | D4: =历史数据及预测表!E107 -> 5411.8675 | E4: =历史数据及预测表!F107 -> 4530.9257 | F4: =历史数据及预测表!G107 -> 4212.6259 | G4: =历史数据及预测表!H107 -> 4741.0076 | H4: =经营模型拆分!H4 -> 8307.8438 | I4: =经营模型拆分!I4 -> 10593.134 | J4: =经营模型拆分!J4 -> 12526.556 | K4: =经营模型拆分!K4 -> 14734.016
B5: 营业成本合计 | C5: =历史数据及预测表!D110 -> 3324.9476 | D5: =历史数据及预测表!E110 -> 3325.1376 | E5: =历史数据及预测表!F110 -> 2850.0005 | F5: =历史数据及预测表!G110 -> 2665.3622 | G5: =历史数据及预测表!H110 -> 3124.9661 | H5: =经营模型拆分!H5 -> 4182.239 | I5: =经营模型拆分!I5 -> 5655.3783 | J5: =经营模型拆分!J5 -> 7397.5763 | K5: =经营模型拆分!K5 -> 8874.2543
B7: 其他业务收入（金融类） | C7: =历史数据及预测表!D108 -> 0 | D7: =历史数据及预测表!E108 -> 0 | E7: =历史数据及预测表!F108 -> 0 | F7: =历史数据及预测表!G108 -> 0 | G7: =历史数据及预测表!H108 -> 0 | H7: 1 | I7: 1 | J7: 1 | K7: 1
B8: 其他业务成本（金融类） | C8: =历史数据及预测表!D116 -> 0 | D8: =历史数据及预测表!E116 -> 0 | E8: =历史数据及预测表!F116 -> 0 | F8: =历史数据及预测表!G116 -> 0 | G8: =历史数据及预测表!H116 -> 0 | H8: 0 | I8: 0 | J8: 0 | K8: 0

Sheet 经营模型拆分
J1: 单位：百万元
B2: 历史数据 | G2: 预测数据
B3: 2020 | C3: 2021 | D3: 2022 | E3: 2023 | F3: 2024 | G3: 2025 | H3: =[2]历史数据及预测表!J4 -> 2026 | I3: =[2]历史数据及预测表!K4 -> 2027 | J3: =[2]历史数据及预测表!L4 -> 2028 | K3: =[2]历史数据及预测表!M4 -> 2029
A4: 营业收入合计 | B4: 2169.8011 | C4: 5274.0591 | D4: 5411.8675 | E4: 4530.9257 | F4: =经营模型!F4 -> 4212.6259 | G4: =经营模型!G4 -> 4741.0076 | H4: =H12 -> 8307.8438 | I4: =I12 -> 10593.134 | J4: =J12 -> 12526.556 | K4: =K12 -> 14734.016
A5: 营业成本合计 | B5: 1581.2153 | C5: 3324.9476 | D5: 3325.1376 | E5: 2850.0005 | F5: =经营模型!F5 -> 2665.3622 | G5: =经营模型!G5 -> 3124.9661 | H5: =H19 -> 4182.239 | I5: =I19 -> 5655.3783 | J5: =J19 -> 7397.5763 | K5: =K19 -> 8874.2543
A7: 其他业务收入（金融类） | H7: 1 | I7: 1 | J7: 1
A8: 其他业务成本（金融类） | H8: 0 | I8: 0 | J8: 0
A10: 红色为假设数据，蓝色为计算数据 | B10: 假设汇率按照6.5计算 | G10: =G18 -> 0.34086456 | H10: =H18 -> 0.49659152 | I10: =I18 -> 0.46612794 | J10: =J18 -> 0.40944851
B11: 2020 | C11: 2021 | D11: 2022 | E11: 2023 | F11: 2024 | G11: 2025 | H11: 2026 | I11: 2027 | J11: 2028 | K11: 2029 | M11: 说明 | N11: CAGR
A12: 营业收入 | B12: 2169.8011 | C12: 5274.0591 | D12: 5411.8675 | E12: 4530.9257 | F12: 4212.6259 | G12: =G4 -> 4741.0076 | H12: =H20+H103+H117+H119+H121 -> 8307.8438 | I12: =I20+I103+I117+I119+I121 -> 10593.134 | J12: =J20+J103+J117+J119+J121 -> 12526.556 | K12: =K20+K103+K117+K119+K121 -> 14734.016 | N12: =(I12/E12)^(1/4)-1 -> 0.23654345
A13: YoY | B13: =B12/#REF!-1 -> #REF! | C13: =C12/B12-1 -> 1.4306648 | D13: =D12/C12-1 -> 0.026129473 | E13: =E12/D12-1 -> -0.16277964 | F13: =F12/E12-1 -> -0.070250496 | G13: =G12/F12-1 -> 0.12542811 | H13: =H12/G12-1 -> 0.75233716 | I13: =I12/H12-1 -> 0.27507621 | J13: =J12/I12-1 -> 0.18251654 | K13: =K12/J12-1 -> 0.17622244
A14: 销量（百万颗） | B14: 21.236903 | C14: 414.08087 | D14: 994.31534
A15: YoY | B15: =B14/#REF!-1 -> #REF! | C15: =C14/B14-1 -> 18.498176 | D15: =D14/C14-1 -> 1.4012588
A16: 均价（元） | B16: =#REF!/B14 -> #REF! | C16: =#REF!/C14 -> #REF! | D16: =#REF!/D14 -> #REF!
A17: YoY | B17: =B16/#REF!-1 -> #REF! | C17: =C16/B16-1 -> #REF! | D17: =D16/C16-1 -> #REF!
A18: 毛利率 | B18: 0.27126256 | C18: 0.36956574 | D18: 0.38558406 | E18: 0.37098935 | F18: 0.36729198 | G18: =1-G5/G4 -> 0.34086456 | H18: =1-H5/H4 -> 0.49659152 | I18: =1-I5/I4 -> 0.46612794 | J18: =1-J5/J4 -> 0.40944851 | K18: =1-K5/K4 -> 0.39770297
A19: 营业成本 | B19: =B12*(1-B18) -> 1581.2153 | C19: =C12*(1-C18) -> 3324.9476 | D19: =D12*(1-D18) -> 3325.1376 | E19: =E12*(1-E18) -> 2850.0005 | F19: =F12*(1-F18) -> 2665.3622 | G19: =G12*(1-G18) -> 3124.9661 | H19: =H124 -> 4182.239 | I19: =I124 -> 5655.3783 | J19: =J124 -> 7397.5763 | K19: =K124 -> 8874.2543 | N19: =(I19/E19)^(1/4)-1 -> 0.18687281
A20: 1.北京矽成（仅芯片） | B20: =B30+B92 -> 1712.9356 | C20: =C30+C92 -> 4007.0977 | D20: =D30+D92 -> 4533.225 | E20: =E30+E92 -> 3320.48 | F20: =F30+F92 -> 3061.01 | G20: =G30+G92 -> 3416.89 | H20: =H30+H92 -> 6093.8969 | I20: =I30+I92 -> 7941.3757 | ... K20: =K30+K92 -> 10934.116
A21: YoY | C21: =C20/B20-1 -> 1.3393161 | D21: =D20/C20-1 -> 0.13129884 | E21: =E20/D20-1 -> -0.26752367 | F21: =F20/E20-1 -> -0.078142317 | G21: =G20/F20-1 -> 0.11626228 | H21: =H20/G20-1 -> 0.78346302 | I21: =I20/H20-1 -> 0.3031687 | J21: =J20/I20-1 -> 0.17760758 | K21: =K20/J20-1 -> 0.16919607
A22: 在公司总收入占比 | C22: =C20/D12 -> 0.7404279 | D22: =D20/D12 -> 0.83764523 | E22: =E20/E12 -> 0.73284804 | F22: =F20/F12 -> 0.72662754 | G22: =G20/G12 -> 0.72070967 | H22: =H20/H12 -> 0.73351126 | I22: =I20/I12 -> 0.74967198 | J22: =J20/J12 -> 0.74655988 | K22: =K20/K12 -> 0.74210018
A23: 收购备考口径 | B23: =B32+B94 -> 2805.2748
A24: YoY | B24: =B23/#REF!-1 -> #REF!
A25: 销量（百万颗）
A26: YoY
A27: 均价（元）
A28: YoY
A29: 毛利率 | C29: =(C30*C45+C92*C101)/C20 -> 0.32895246 | D29: =(D30*D45+D92*D101)/D20 -> 0.38554391 | E29: =(E30*E45+E92*E101)/E20 -> 0.38307715 | F29: =(F30*F45+F92*F101)/F20 -> 0.3687051 | G29: =1-G125/G20 -> 0.34783678 | H29: =1-H125/H20 -> 0.47979316 | I29: =1-I125/I20 -> 0.47294298 | J29: =1-J125/J20 -> 0.41101903 | K29: =1-K125/K20 -> 0.39571637
A30: 1.1存储芯片 | B30: 1525.4586 | C30: 3594.44 | D30: 4054.5031 | E30: 2911.56 | F30: 2589.49 | G30: 2911.25 | H30: =H46+H60+H74 -> 5487.1289 | I30: =I46+I60+I74 -> 7213.2541 | J30: =J46+J60+J74 -> 8478.0783 | K30: =K46+K60+K74 -> 9885.6211 | M30: =(H30/D30)^(1/4)-1 -> 0.078578806
A31: YoY | C31: =C30/B30-1 -> 1.3563013 | D31: =D30/C30-1 -> 0.12799298 | E31: =E30/D30-1 -> -0.28189474 | F31: =F30/E30-1 -> -0.11061768 | G31: =G30/F30-1 -> 0.12425613 | H31: =H30/G30-1 -> 0.8848017 | I31: =I30/H30-1 -> 0.31457711 | J31: =J30/I30-1 -> 0.17534724 | K31: =K30/J30-1 -> 0.16602144
A32: 收购备考口径 | B32: 2526.2536
A33: YoY | B33: =B32/#REF!-1 -> #REF!
A34: 在矽成占比 | B34: =B32/B23 -> 0.90053695 | C34: =C30/C20 -> 0.89701831 | D34: =D30/D20 -> 0.89439706 | E34: =E30/E20 -> 0.87684913 | F34: =F30/F20 -> 0.84595934 | G34: =G30/G20 -> 0.85201748 | H34: =H30/H20 -> 0.90043022 | I34: =I30/I20 -> 0.90831291 | J34: =J30/J20 -> 0.90656947 | K34: =K30/K20 -> 0.90410792
A35: 全球存储芯片市场规模（亿美元） | B35: 1174.82 | C35: 1538.38 | D35: 1826.61 | E35: =D35*(1+E36) -> 1278.627 | F35: =E35*(1+F36) -> 1342.5584 | G35: =F35*(1+G36) -> 1409.6863 | H35: =G35*(1+H36) -> 1480.1706 | I35: =H35*(1+I36) -> 1554.1791 | J35: =I35*(1+J36) -> 1631.8881 | K35: =J35*(1+K36) -> 1713.4825 | L35: 资料来源：WSTS
A36: YoY | B36: =B35/#REF!-1 -> #REF! | C36: =C35/B35-1 -> 0.30946017 | D36: =D35/C35-1 -> 0.18735943 | E36: -0.3 | F36: 0.05 | G36: 0.05 | H36: 0.05 | I36: 0.05 | J36: 0.05 | K36: 0.05
A37: 公司份额 | B37: =B32/100/6.5/B35 -> 0.0033082038 | C37: =C30/100/6.5/C35 -> 0.0035946305 | D37: =D30/100/6.5/D35 -> 0.0034149036 | E37: =E30/100/6.5/E35 -> 0.0035032289 | F37: =F30/100/6.5/F35 -> 0.0029673427 | G37: =G30/100/6.5/G35 -> 0.0031771936 | H37: =H30/100/6.5/H35 -> 0.0057032189 | I37: =I30/100/6.5/I35 -> 0.0071403058 | J37: =J30/100/6.5/J35 -> 0.0079927035 | K37: =K30/100/6.5/K35 -> 0.0088758701 | L37: 根据Trendforce，2020Q1-Q3，三星、SK海力士、美光份额分别为38%/21%/17%
A38: 全球车载存储市场规模（亿美元） | B38: =#REF!*(1+B39) -> #REF! | C38: =B38*(1+C39) -> #REF! | D38: =C38*(1+D39) -> #REF! | E38: =D38*(1+E39) -> #REF! | F38: =E38*(1+F39) -> #REF! | G38: 83 | H38: =G38*(1+H39) -> #REF! | I38: =H38*(1+I39) -> #REF! | J38: =I38*(1+J39) -> #REF! | K38: =J38*(1+K39) -> #REF! | L38: 资料来源：IHS
A39: YoY | B39: =POWER($G38/#REF!,1/6)-1 -> #REF! | C39: =POWER($G38/#REF!,1/6)-1 -> #REF! | D39: =POWER($G38/#REF!,1/6)-1 -> #REF! | E39: =POWER($G38/#REF!,1/6)-1 -> #REF! | F39: =POWER($G38/#REF!,1/6)-1 -> #REF! | G39: =POWER($G38/#REF!,1/6)-1 -> #REF! | H39: =POWER($G38/#REF!,1/6)-1 -> #REF! | I39: =POWER($G38/#REF!,1/6)-1 -> #REF! | ... K39: =POWER($G38/#REF!,1/6)-1 -> #REF!
A40: 公司份额 | B40: =B32*35%/100/6.5/B38 -> #REF! | C40: =C30*40%/100/6.5/C38 -> #REF! | D40: =D30*40%/100/6.5/D38 -> #REF! | E40: =E30*40%/100/6.5/E38 -> #REF! | F40: =F30*40%/100/6.5/F38 -> #REF! | G40: =G30*40%/100/6.5/G38 -> 0.021584801 | H40: =H30*40%/100/6.5/H38 -> #REF! | I40: =I30*40%/100/6.5/I38 -> #REF! | J40: =J30*40%/100/6.5/J38 -> #REF! | K40: =K30*40%/100/6.5/K38 -> #REF! | L40: 无
A41: 芯片销量（百万颗）
A42: YoY
A43: 芯片均价（元）
A44: YoY
A45: 存储毛利率 | B45: 0.2073 | C45: 0.304 | D45: =1-D126/D30 -> 0.36850146 | E45: =1-E126/E30 -> 0.36477352 | F45: =1-F126/F30 -> 0.34550433 | G45: =1-G126/G30 -> 0.31951224 | H45: =(H46*H59+H60*H73+H74*H91)/H30 -> 0.47424128 | I45: =(I46*I59+I60*I73+I74*I91)/I30 -> 0.46819295 | J45: =(J46*J59+J60*J73+J74*J91)/J30 -> 0.39978751 | K45: =(K46*K59+K60*K73+K74*K91)/K30 -> 0.38253452
A46: DRAM | B46: =C46/(1+C47) -> 1431.1063 | C46: =C20*C48 -> 2003.5489 | D46: =C46*(1+D47) -> 2264.0102 | E46: =D46*(1+E47) -> 1584.8071 | F46: =E46*(1+F47) -> 1426.3264 | G46: =F46*(1+G47) -> 1640.2754 | H46: =G46*(1+H47) -> 3608.6059 | I46: =H46*(1+I47) -> 5052.0482 | J46: =I46*(1+J47) -> 6062.4579 | K46: =J46*(1+K47) -> 7274.9494 | L46: 君正能做的部分： DRAM 燃油车目前单车4GB，自动驾驶、智能座舱，在L2大概16GB，L3大概50GB，L4/5大概100GB，其中一大半是用在主控里面，另外还有摄像头、雷达、仪表盘、hud、环视等，每处需要1~4Gb不等的内存，对应大概需要4~16GB的容量，所以对于君正来说，可触及的空间从现在4GB到未来20GB（对于三星海力士，可触及的空间可以高达100GB），单车价值量从16美金到80美金，市场空间从14亿美金到68亿美金。如果做到其中20%，就是88亿人民币的收入。 | M46: =(H46/D46)^(1/4)-1 -> 0.12360915
A47: YoY | B47: =B46/#REF!-1 -> #REF! | C47: 0.4 | D47: 0.13 | E47: -0.3 | F47: -0.1 | G47: 0.15 | H47: 1.2 | I47: 0.4 | J47: 0.2 | K47: 0.2
A48: 在矽成占比 | B48: =B46/B23 -> 0.51014836 | C48: 0.5 | D48: =D46/D20 -> 0.49942595 | E48: =E46/E20 -> 0.47728255 | F48: =F46/F20 -> 0.46596595 | G48: =G46/G20 -> 0.48004923 | H48: =H46/H20 -> 0.5921672 | I48: =I46/I20 -> 0.63616789 | J48: =J46/J20 -> 0.64826474 | K48: =K46/K20 -> 0.66534408
A49: 全球DRAM芯片市场规模（亿美元） | B49: 677 | C49: 961 | D49: 900 | E49: =D49*(1+E50) -> 477 | F49: =E49*(1+F50) -> 715.5 | G49: =F49*(1+G50) -> 858.6 | H49: =G49*(1+H50) -> 901.53 | I49: =H49*(1+I50) -> 902.13914 | J49: =I49*(1+J50) -> 1849.3852 | K49: =J49*(1+K50) -> 1850.6348 | L49: 资料来源：Trendforce | M49: =(H49/D49)^(1/4)-1 -> 0.00042472933
A50: YoY | B50: =B49/#REF!-1 -> #REF! | C50: =C49/B49-1 -> 0.41949778 | D50: =D49/C49-1 -> -0.063475546 | E50: -0.47 | F50: 0.5 | G50: 0.2 | H50: 0.05 | I50: =I49/H49-1 -> 0.00067567568 | J50: 1.05 | K50: =K49/J49-1 -> 0.00067567568
A51: 公司份额 | B51: =B46/100/6.5/B49 -> 0.0032521448 | C51: =C46/100/6.5/C49 -> 0.0032074744 | D51: =D46/100/6.5/D49 -> 0.0038701029 | E51: =E46/100/6.5/E49 -> 0.0051114567 | F51: =F46/100/6.5/F49 -> 0.003066874 | G51: =G46/100/6.5/G49 -> 0.0029390876 | H51: =H46/100/6.5/H49 -> 0.0061580883 | I51: =I46/100/6.5/I49 -> 0.0086155023 | ... K51: =K46/100/6.5/K49 -> 0.0060477787 | L51: 根据IHS数据，2019H1全球DRAM市场中三大巨头三星、SK海力士、美光市场份额绝对领先，分别为41.5%/29.0%/24.8%，CR3达95.3%，北京矽成收入位居第7名，占比约为0.4%，2020、2021年均维持相同排名地位
A52: 全球车载DRAM市场规模（亿美元） | B52: 15 | C52: =B52*(1+C53) -> 18.25093 | D52: =C52*(1+D53) -> 22.20643 | E52: =D52*(1+E53) -> 27.019201 | F52: =E52*(1+F53) -> 32.875037 | G52: 40 | H52: =G52*(1+H53) -> 48.669147 | I52: =H52*(1+I53) -> 59.217148 | J52: =I52*(1+J53) -> 72.051202 | K52: =J52*(1+K53) -> 87.666764 | L52: 资料来源：IHS | M52: =(H52/D52)^(1/4)-1 -> 0.21672868
A53: YoY | C53: =POWER($G52/$B52,1/5)-1 -> 0.21672868 | D53: =POWER($G52/$B52,1/5)-1 -> 0.21672868 | E53: =POWER($G52/$B52,1/5)-1 -> 0.21672868 | F53: =POWER($G52/$B52,1/5)-1 -> 0.21672868 | G53: =POWER($G52/$B52,1/5)-1 -> 0.21672868 | H53: =POWER($G52/$B52,1/5)-1 -> 0.21672868 | I53: =POWER($G52/$B52,1/5)-1 -> 0.21672868 | J53: =POWER($G52/$B52,1/5)-1 -> 0.21672868 | K53: =POWER($G52/$B52,1/5)-1 -> 0.21672868
A54: 公司份额 | C54: =C46/100/6.5/C52 -> 0.16888908 | D54: =D46/100/6.5/D52 -> 0.15685063 | E54: =E46/100/6.5/E52 -> 0.09023823 | F54: =F46/100/6.5/F52 -> 0.066748165 | G54: =G46/100/6.5/G52 -> 0.063087515 | H54: =H46/100/6.5/H52 -> 0.11407024 | I54: =I46/100/6.5/I52 -> 0.13125222 | J54: =J46/100/6.5/J52 -> 0.12944764 | K54: =K46/100/6.5/K52 -> 0.12766788 | L54: 根据IC Insights数据，美光45.0%，矽成15.0%，三星10.8%，南亚科9.5%，华邦电8.5%
A55: 芯片销量（百万颗）
A56: YoY
A57: 芯片均价（元） | L57: DRAM 4Gb一般2美金，8Gb一般3美金，公司均价大概2美金，基本对应产品容量在4Gb或以下
A58: YoY | L58: 公司产品涵盖16M、32M、64M、128M到1G、2G、4G、8G、16G等不同容量、不同界面、不同功耗规格产品，具备在极端环境下稳定工作以及节能降耗等特点。公司加强对于高速DRAM及不同容量的低功耗DDR4、LPDDR4、LPDDR2等产品的研发，目前最高支持25nm DDR4 8/16Gb、LPDDR4 4Gb型产品，2022年有望推出LPDDR4 8Gb型产品。
A59: 毛利率 | B59: 0.3 | C59: 0.3 | D59: 0.36 | E59: 0.35 | F59: 0.325 | G59: 0.3 | H59: 0.5 | I59: 0.49 | J59: 0.4 | K59: 0.38
A60: SRAM | B60: =B23*B62 -> 476.89672 | C60: =C20*C62 -> 480.85173 | D60: =D62*D20 -> 453.3225 | E60: =D60*(1+E61) -> 407.99025 | F60: =E60*(1+F61) -> 387.59074 | G60: =F60*(1+G61) -> 387.59074 | H60: =G60*(1+H61) -> 465.10889 | I60: =H60*(1+I61) -> 465.10889 | J60: =I60*(1+J61) -> 465.10889 | K60: =J60*(1+K61) -> 465.10889 | M60: =(H60/D60)^(1/4)-1 -> 0.0064375693
A61: YoY | B61: =B60/#REF!-1 -> #REF! | C61: =C60/B60-1 -> 0.0082932221 | D61: =D60/C60-1 -> -0.057250967 | E61: -0.1 | F61: -0.05 | G61: 0 | H61: 0.2 | I61: 0 | J61: 0 | K61: 0
A62: 在存储占比 | B62: 0.17 | C62: 0.12 | D62: 0.1 | E62: =E60/E$30 -> 0.14012772 | F62: =F60/F$30 -> 0.14967841 | G62: =G60/G$30 -> 0.1331355 | H62: =H60/H$30 -> 0.084763615 | I62: =I60/I$30 -> 0.064479759 | J62: =J60/J$30 -> 0.054860178 | K62: =K60/K$30 -> 0.04704903
A63: 全球SRAM芯片市场规模（亿美元） | C63: 3.92 | D63: =C63*(1+D64) -> 3.83768 | E63: =D63*(1+E64) -> 3.7570887 | F63: =E63*(1+F64) -> 3.6781899 | G63: =F63*(1+G64) -> 3.6009479 | H63: =G63*(1+H64) -> 3.525328 | I63: =H63*(1+I64) -> 6.976624 | J63: =I63*(1+J64) -> 20.783363 | K63: =J63*(1+K64) -> 82.697001 | L63: 资料来源：GIR
A64: YoY | D64: -0.021 | E64: -0.021 | F64: -0.021 | G64: -0.021 | H64: -0.021 | I64: 0.979 | J64: 1.979 | K64: 2.979
A65: 公司份额 | C65: =C60/100/6.5/C63 -> 0.18871732 | D65: =D60/100/6.5/D63 -> 0.18172939 | E65: =E60/100/6.5/E63 -> 0.16706481 | F65: =F60/100/6.5/F63 -> 0.162116 | G65: =G60/100/6.5/G63 -> 0.16559347 | H65: =H60/100/6.5/H63 -> 0.20297463 | I65: =I60/100/6.5/I63 -> 0.10256424 | J65: =J60/100/6.5/J63 -> 0.034429083 | K65: =K60/100/6.5/K63 -> 0.0086526974 | L65: 根据IHS统计，2019H1全球SRAM市场中赛普拉斯/北京矽成分别占比33.9%/21.8%，2020、2021年仍维持全球第2名的领先地位
A66: 全球车载SRAM市场规模（亿美元） | B66: =#REF!*(1+B67) -> #REF! | C66: =B66*(1+C67) -> #REF! | D66: =C66*(1+D67) -> #REF! | E66: =D66*(1+E67) -> #REF! | F66: =E66*(1+F67) -> #REF! | G66: 1.2 | H66: =G66*(1+H67) -> #REF! | I66: =H66*(1+I67) -> #REF! | J66: =I66*(1+J67) -> #REF! | L66: 资料来源：IHS
A67: YoY | B67: =POWER($G66/#REF!,1/6)-1 -> #REF! | C67: =POWER($G66/#REF!,1/6)-1 -> #REF! | D67: =POWER($G66/#REF!,1/6)-1 -> #REF! | E67: =POWER($G66/#REF!,1/6)-1 -> #REF! | F67: =POWER($G66/#REF!,1/6)-1 -> #REF! | G67: =POWER($G66/#REF!,1/6)-1 -> #REF! | H67: =POWER($G66/#REF!,1/6)-1 -> #REF! | I67: =POWER($G66/#REF!,1/6)-1 -> #REF! | J67: =POWER($G66/#REF!,1/6)-1 -> #REF!
A68: 公司份额 | B68: =B60*50%/100/6.5/B66 -> #REF! | C68: =C60*50%/100/6.5/C66 -> #REF! | D68: =D60*50%/100/6.5/D66 -> #REF! | E68: =E60*50%/100/6.5/E66 -> #REF! | F68: =F60*50%/100/6.5/F66 -> #REF! | G68: =G60*50%/100/6.5/G66 -> 0.2484556 | H68: =H60*50%/100/6.5/H66 -> #REF! | I68: =I60*50%/100/6.5/I66 -> #REF! | J68: =J60*50%/100/6.5/J66 -> #REF! | L68: 根据IHS数据，公司在全球SRAM市场中长年位居前2名，2019H1份额约21.80%
A69: 芯片销量（百万颗）
A70: YoY
A71: 芯片均价（元）
A72: YoY
A73: 毛利率 | B73: 0.4 | C73: 0.4 | D73: 0.45 | E73: 0.45 | F73: =E73 -> 0.45 | G73: =F73 -> 0.45 | H73: 0.5 | I73: 0.48 | J73: =I73 -> 0.48 | K73: =J73 -> 0.48
A74: FLASH（剔除P-fusion） | B74: =B32-B46-B60 -> 618.25056 | C74: =C30-C46-C60 -> 1110.0394 | D74: =D30-D46-D60 -> 1337.1704 | E74: =E30-E46-E60 -> 918.7626 | F74: =F30-F46-F60 -> 775.57283 | G74: =G30-G46-G60 -> 883.38386 | H74: =G74*(1+H75) -> 1413.4142 | I74: =H74*(1+I75) -> 1696.097 | J74: =I74*(1+J75) -> 1950.5116 | K74: =J74*(1+K75) -> 2145.5627 | L74: 君正能做的部分： NOR目前单车10美金，未来自动驾驶、传感器、仪表盘等都需要NOR来做快速启动，单车价值量可以提升到30美金，都是君正可以做的，对应市场空间25亿美金。如果做到其中20%，就是33亿人民币的收入。 | M74: =(H74/D74)^(1/4)-1 -> 0.013959652
A75: YoY | B75: =B74/#REF!-1 -> #REF! | C75: =C74/B74-1 -> 0.79545237 | D75: =D74/C74-1 -> 0.20461522 | E75: =E74/D74-1 -> -0.31290536 | F75: =F74/E74-1 -> -0.15585068 | G75: =G74/F74-1 -> 0.13900827 | H75: 0.6 | I75: 0.2 | J75: 0.15 | K75: 0.1
A76: 在存储占比 | B76: =B74/B30 -> 0.40528833 | C76: =C74/C30 -> 0.30882124 | D76: =D74/D30 -> 0.32979883 | E76: =E74/E30 -> 0.31555682 | F76: =F74/F30 -> 0.29950795 | G76: =G74/G30 -> 0.303438 | H76: =H74/H30 -> 0.2575872 | I76: =I74/I30 -> 0.23513618 | ... K76: =K74/K30 -> 0.21703874
A77: 全球NOR芯片市场规模（亿美元） | B77: 26.24 | C77: 28.84 | D77: 34.0997 | E77: 36.2895 | F77: 38.9795 | G77: 41.6767 | H77: 44.3739 | I77: 45.3739 | J77: 46.3739 | K77: 47.3739 | L77: 资料来源：CINNO Research，IC Insights，Maia Research | M77: =(H77/D77)^(1/4)-1 -> 0.068056581
A78: YoY | B78: =B77/#REF!-1 -> #REF! | C78: =C77/B77-1 -> 0.099085366 | D78: =D77/C77-1 -> 0.18237517 | E78: =E77/D77-1 -> 0.064217574 | F78: =F77/E77-1 -> 0.074126125 | G78: =G77/F77-1 -> 0.069195346 | H78: =H77/G77-1 -> 0.064717216 | I78: =I77/H77-1 -> 0.02253577 | J78: =J77/I77-1 -> 0.022039102 | K78: =K77/J77-1 -> 0.021563854
A79: 全球NAND芯片市场规模（亿美元） | B79: 565.83333 | C79: 679 | D79: 720 | E79: 740 | F79: 830 | G79: 950 | H79: 1070 | I79: 1071 | J79: 1072 | K79: 1073 | L79: 资料来源：CFM闪存市场，Yole（2021Q2预测） | M79: =(H79/D79)^(1/4)-1 -> 0.10411121
A80: YoY | B80: =B79/#REF!-1 -> #REF! | C80: =C79/B79-1 -> 0.2 | D80: =D79/C79-1 -> 0.060382916 | E80: =E79/D79-1 -> 0.027777778 | F80: =F79/E79-1 -> 0.12162162 | G80: =G79/F79-1 -> 0.14457831 | H80: =H79/G79-1 -> 0.12631579 | I80: =I79/H79-1 -> 0.00093457944 | J80: =J79/I79-1 -> 0.00093370682 | K80: =K79/J79-1 -> 0.00093283582
A81: 公司份额 | B81: =B74/100/6.5/B77 -> 0.036248274 | C81: =C74/100/6.5/C77 -> 0.059214735 | D81: =D74/100/6.5/D77 -> 0.060328543 | E81: =E74/100/6.5/E77 -> 0.038950135 | F81: =F74/100/6.5/F77 -> 0.030610679 | G81: =G74/100/6.5/G77 -> 0.032609398 | H81: =H74/100/6.5/H77 -> 0.049003657 | I81: =I74/100/6.5/I77 -> 0.057508392 | ... K81: =K74/100/6.5/K77 -> 0.069676884 | L81: 根据CFM闪存市场统计，2021Q4全球NAND Flash市场中三星、铠侠份额分别为34%/19%，CR2达53%，SK海力士、西部数据、美光、英特尔次之，CR6达97%。 | M81: 根据CINNO Research数据，近年来美国厂商赛普拉斯、美光等逐步退出NOR Flash市场，中国大陆/中国台湾厂商华邦、旺宏、兆易创新等逐步承接产能，2020年全球NOR Flash市场中旺宏、华邦、赛普莱斯、兆易创新、美光占比分别为25.4%/22.5%/15.6%/10.9%/4.0%，CR5合计为88.4%。根据Omdia统计，2020、2021年公司NOR Flash产品收入在全球均位居第6位
A82: 全球车载NOR市场规模（亿美元） | B82: 4.2 | C82: =B82*(1+C83) -> 5.0155604 | D82: =C82*(1+D83) -> 5.9894872 | E82: =D82*(1+E83) -> 7.1525322 | F82: =E82*(1+F83) -> 8.5414184 | G82: 10.2 | H82: =G82*(1+H83) -> 12.180647 | I82: =H82*(1+I83) -> 14.545898 | J82: =I82*(1+J83) -> 17.370435 | K82: =J82*(1+K83) -> 20.743445 | L82: 资料来源：IHS | M82: =(H82/D82)^(1/4)-1 -> 0.19418105
A83: YoY | C83: =POWER($G82/$B82,1/5)-1 -> 0.19418105 | D83: =POWER($G82/$B82,1/5)-1 -> 0.19418105 | E83: =POWER($G82/$B82,1/5)-1 -> 0.19418105 | F83: =POWER($G82/$B82,1/5)-1 -> 0.19418105 | G83: =POWER($G82/$B82,1/5)-1 -> 0.19418105 | H83: =POWER($G82/$B82,1/5)-1 -> 0.19418105 | I83: =POWER($G82/$B82,1/5)-1 -> 0.19418105 | J83: =POWER($G82/$B82,1/5)-1 -> 0.19418105 | K83: =POWER($G82/$B82,1/5)-1 -> 0.19418105
A84: 全球车载NAND市场规模（亿美元） | B84: =#REF!*(1+B85) -> #REF! | C84: =B84*(1+C85) -> #REF! | D84: =C84*(1+D85) -> #REF! | E84: =D84*(1+E85) -> #REF! | F84: =E84*(1+F85) -> #REF! | G84: 29 | H84: =G84*(1+H85) -> #REF! | I84: =H84*(1+I85) -> #REF! | J84: =I84*(1+J85) -> #REF! | K84: =J84*(1+K85) -> #REF! | L84: 资料来源：IHS | M84: =(H84/D84)^(1/4)-1 -> #REF!
A85: YoY | B85: =POWER($G84/#REF!,1/6)-1 -> #REF! | C85: =POWER($G84/#REF!,1/6)-1 -> #REF! | D85: =POWER($G84/#REF!,1/6)-1 -> #REF! | E85: =POWER($G84/#REF!,1/6)-1 -> #REF! | F85: =POWER($G84/#REF!,1/6)-1 -> #REF! | G85: =POWER($G84/#REF!,1/6)-1 -> #REF! | H85: =POWER($G84/#REF!,1/6)-1 -> #REF! | I85: =POWER($G84/#REF!,1/6)-1 -> #REF! | ... K85: =POWER($G84/#REF!,1/6)-1 -> #REF!
A86: 公司份额 | B86: =B74*10%/100/6.5/B82 -> 0.02264654 | C86: =C74*10%/100/6.5/C82 -> 0.034049096 | D86: =D74*40%/100/6.5/D82 -> 0.1373864 | E86: =E74*40%/100/6.5/E82 -> 0.079047861 | F86: =F74*40%/100/6.5/F82 -> 0.055877791 | G86: =G74*40%/100/6.5/G82 -> 0.053296161 | H86: =H74*40%/100/6.5/H82 -> 0.071407813 | I86: =I74*40%/100/6.5/I82 -> 0.071755765 | J86: =J74*40%/100/6.5/J82 -> 0.069101021 | K86: =K74*40%/100/6.5/K82 -> 0.063651255 | L86: 无
A87: 芯片销量（百万颗）
A88: YoY
A89: 芯片均价（元） | L89: NOR一般512Kb在0.4美金，公司均价在0.3美金左右
A90: YoY | L90: NOR Flash包含串口型和并口型结构，具备256Kb~1Gb等规格，最新制程为50nm
A91: 毛利率 | B91: 0.3 | C91: =(C30*C45-C46*C59-C60*C73)/C74 -> 0.26963404 | D91: =(D30*D45-D46*D59-D60*D73)/D74 -> 0.35526624 | E91: =(E30*E45-E46*E59-E60*E73)/E74 -> 0.35241082 | F91: =(F30*F45-F46*F59-F60*F73)/F74 -> 0.33099158 | G91: =(G30*G45-G46*G59-G60*G73)/G74 -> 0.29849034 | H91: 0.4 | I91: 0.4 | J91: 0.38 | K91: 0.37
A92: 1.2 模拟与互联芯片 | B92: 187.47701 | C92: 412.65771 | D92: 478.7219 | E92: 408.92 | F92: 471.52 | G92: 505.64 | H92: =G92*(1+H93) -> 606.768 | I92: =H92*(1+I93) -> 728.1216 | J92: =I92*(1+J93) -> 873.74592 | K92: =J92*(1+K93) -> 1048.4951 | M92: =(H92/D92)^(1/4)-1 -> 0.061047541
A93: YoY | C93: =C92/B92-1 -> 1.201111 | D93: =D92/C92-1 -> 0.1600944 | E93: =E92/D92-1 -> -0.14580887 | F93: =F92/E92-1 -> 0.15308618 | G93: =G92/F92-1 -> 0.072361724 | H93: 0.2 | I93: 0.2 | J93: 0.2 | K93: 0.2
A94: 收购备考口径 | B94: 279.0212
A95: YoY
A96: 在矽成占比 | B96: =B94/B23 -> 0.099463054 | C96: =C92/C20 -> 0.10298169 | D96: =D92/D20 -> 0.10560294 | E96: =E92/E20 -> 0.12315087 | F96: =F92/F20 -> 0.15404066 | G96: =G92/G20 -> 0.14798252 | H96: =H92/H20 -> 0.099569784 | I96: =I92/I20 -> 0.091687086 | J96: =J92/J20 -> 0.093430533 | K96: =K92/K20 -> 0.095892077
A97: 芯片销量（百万颗）
A98: YoY
A99: 芯片均价（元）
A100: YoY
A101: 毛利率 | B101: 0.4883 | C101: 0.5463 | D101: =1-D130/D92 -> 0.52988384 | E101: =1-E130/E92 -> 0.51340115 | F101: =1-F130/F92 -> 0.49611893 | G101: =1-G130/G92 -> 0.51091686 | H101: 0.53 | I101: 0.52 | J101: =I101 -> 0.52 | K101: =J101 -> 0.52
A103: 2 北京君正（仅芯片） | B103: =B109+B113 -> 415.04386 | C103: =C109+C113 -> 1177.6315 | D103: =D109+D113 -> 770.2036 | E103: 1108.37 | F103: 1090.1 | G103: 1293.41 | H103: =H109+H113 -> 2129.0568 | I103: =I109+I113 -> 2554.8682 | J103: =J109+J113 -> 3065.8418 | K103: =K109+K113 -> 3679.0102
...

Sheet 假设表
D1: 历史数据 | I1: 预测数据
C2: 预测值生成方式 | D2: =历史数据!C1 -> 2021 | E2: =历史数据!D1 -> 2022 | F2: =历史数据!E1 -> 2023 | G2: =历史数据!F1 -> 2024 | H2: =历史数据!G1 -> 2025 | I2: =H2+1 -> 2026 | J2: =I2+1 -> 2027 | K2: =J2+1 -> 2028 | L2: =K2+1 -> 2029 | M2: =L2+1 -> 2030 | N2: =M2+1 -> 2031 | O2: =N2+1 -> 2032 | P2: =O2+1 -> 2033 | ... T2: =S2+1 -> 2037
A3: 利润表假设
B4: 营业收入增长率 | C4: 前三年平均数据 | E4: =历史数据及预测表!E107/历史数据及预测表!D107-1 -> 0.026129473 | F4: =历史数据及预测表!F107/历史数据及预测表!E107-1 -> -0.16277964 | G4: =历史数据及预测表!G107/历史数据及预测表!F107-1 -> -0.070250496 | H4: =历史数据及预测表!H107/历史数据及预测表!G107-1 -> 0.12542811 | I4: =经营模型!H4/经营模型!G4-1 -> 0.75233716 | J4: =经营模型!I4/经营模型!H4-1 -> 0.27507621 | K4: =经营模型!J4/经营模型!I4-1 -> 0.18251654 | L4: =经营模型!K4/经营模型!J4-1 -> 0.17622244 | M4: =IF(ISERR(AVERAGE($J$4:$L$4)),0,AVERAGE($J$4:$L$4)) -> 0.21127173 | N4: =IF(ISERR(AVERAGE($K$4:$M$4)),0,AVERAGE($K$4:$M$4)) -> 0.19000357 | O4: =IF(ISERR(AVERAGE($L$4:$N$4)),0,AVERAGE($L$4:$N$4)) -> 0.19249925 | P4: =IF(ISERR(AVERAGE($M$4:$O$4)),0,AVERAGE($M$4:$O$4)) -> 0.19792485 | Q4: =IF(ISERR(AVERAGE($N$4:$P$4)),0,AVERAGE($N$4:$P$4)) -> 0.19347589 | R4: =IF(ISERR(AVERAGE($O$4:$Q$4)),0,AVERAGE($O$4:$Q$4)) -> 0.19463333 | S4: =IF(ISERR(AVERAGE($O$4:$Q$4)),0,AVERAGE($O$4:$Q$4)) -> 0.19463333 | T4: =IF(ISERR(AVERAGE($O$4:$Q$4)),0,AVERAGE($O$4:$Q$4)) -> 0.19463333
B5: 其他业务收入（金融类）增长率 | C5: 前三年平均数据 | E5: =IF(历史数据及预测表!E108=历史数据及预测表!D108,0%,历史数据及预测表!E108/历史数据及预测表!D108-1) -> 0 | F5: =IF(历史数据及预测表!F108=历史数据及预测表!E108,0%,历史数据及预测表!F108/历史数据及预测表!E108-1) -> 0 | G5: =IF(历史数据及预测表!G108=历史数据及预测表!F108,0%,历史数据及预测表!G108/历史数据及预测表!F108-1) -> 0 | H5: =IF(历史数据及预测表!H108=历史数据及预测表!G108,0%,历史数据及预测表!H108/历史数据及预测表!G108-1) -> 0 | I5: =IF(经营模型!G7=0,0%,经营模型!H7/经营模型!G7-1) -> 0 | J5: =IF(经营模型!H7=0,0%,经营模型!I7/经营模型!H7-1) -> 0 | K5: =IF(经营模型!I7=0,0%,经营模型!J7/经营模型!I7-1) -> 0 | L5: =IF(经营模型!J7=0,0%,经营模型!K7/经营模型!J7-1) -> 0 | M5: =IF(ISERR(AVERAGE($J$5:$L$5)),0,AVERAGE($J$5:$L$5)) -> 0 | N5: =IF(ISERR(AVERAGE($K$5:$M$5)),0,AVERAGE($K$5:$M$5)) -> 0 | O5: =IF(ISERR(AVERAGE($L$5:$N$5)),0,AVERAGE($L$5:$N$5)) -> 0 | P5: =IF(ISERR(AVERAGE($M$5:$O$5)),0,AVERAGE($M$5:$O$5)) -> 0 | Q5: =IF(ISERR(AVERAGE($N$5:$P$5)),0,AVERAGE($N$5:$P$5)) -> 0 | R5: =IF(ISERR(AVERAGE($O$5:$Q$5)),0,AVERAGE($O$5:$Q$5)) -> 0 | S5: =IF(ISERR(AVERAGE($O$5:$Q$5)),0,AVERAGE($O$5:$Q$5)) -> 0 | T5: =IF(ISERR(AVERAGE($O$5:$Q$5)),0,AVERAGE($O$5:$Q$5)) -> 0
B6: 营业成本/营业收入 | C6: 前三年平均数据 | D6: =历史数据及预测表!D110/历史数据及预测表!D107 -> 0.63043426 | E6: =历史数据及预测表!E110/历史数据及预测表!E107 -> 0.61441594 | F6: =历史数据及预测表!F110/历史数据及预测表!F107 -> 0.62901065 | G6: =历史数据及预测表!G110/历史数据及预测表!G107 -> 0.63270802 | H6: =历史数据及预测表!H110/历史数据及预测表!H107 -> 0.65913544 | I6: =经营模型!H5/经营模型!H4 -> 0.50340848 | J6: =经营模型!I5/经营模型!I4 -> 0.53387206 | K6: =经营模型!J5/经营模型!J4 -> 0.59055149 | L6: =经营模型!K5/经营模型!K4 -> 0.60229703 | M6: =IF(ISERR(AVERAGE($J$6:$L$6)),0,AVERAGE($J$6:$L$6)) -> 0.57557353 | N6: =IF(ISERR(AVERAGE($K$6:$M$6)),0,AVERAGE($K$6:$M$6)) -> 0.58947401 | O6: =IF(ISERR(AVERAGE($L$6:$N$6)),0,AVERAGE($L$6:$N$6)) -> 0.58911486 | P6: =IF(ISERR(AVERAGE($M$6:$O$6)),0,AVERAGE($M$6:$O$6)) -> 0.5847208 | Q6: =IF(ISERR(AVERAGE($N$6:$P$6)),0,AVERAGE($N$6:$P$6)) -> 0.58776989 | R6: =IF(ISERR(AVERAGE($O$6:$Q$6)),0,AVERAGE($O$6:$Q$6)) -> 0.58720185 | S6: =IF(ISERR(AVERAGE($O$6:$Q$6)),0,AVERAGE($O$6:$Q$6)) -> 0.58720185 | T6: =IF(ISERR(AVERAGE($O$6:$Q$6)),0,AVERAGE($O$6:$Q$6)) -> 0.58720185
B7: 其他业务成本/其他业务收入（金融类） | C7: 前三年平均数据 | D7: =IF(历史数据及预测表!D108=历史数据及预测表!D116,0%,历史数据及预测表!D116/历史数据及预测表!D108) -> 0 | E7: =IF(历史数据及预测表!E108=历史数据及预测表!E116,0%,历史数据及预测表!E116/历史数据及预测表!E108) -> 0 | F7: =IF(历史数据及预测表!F108=历史数据及预测表!F116,0%,历史数据及预测表!F116/历史数据及预测表!F108) -> 0 | G7: =IF(历史数据及预测表!G108=历史数据及预测表!G116,0%,历史数据及预测表!G116/历史数据及预测表!G108) -> 0 | H7: =IF(历史数据及预测表!H108=历史数据及预测表!H116,0%,历史数据及预测表!H116/历史数据及预测表!H108) -> 0 | I7: =IF(经营模型!G8=0,0%,经营模型!H8/经营模型!H7) -> 0 | J7: =IF(经营模型!H8=0,0%,经营模型!I8/经营模型!I7) -> 0 | K7: =IF(经营模型!I8=0,0%,经营模型!J8/经营模型!J7) -> 0 | L7: =IF(经营模型!J8=0,0%,经营模型!K8/经营模型!K7) -> 0 | M7: =IF(ISERR(AVERAGE($J$7:$L$7)),0,AVERAGE($J$7:$L$7)) -> 0 | N7: =IF(ISERR(AVERAGE($K$7:$M$7)),0,AVERAGE($K$7:$M$7)) -> 0 | O7: =IF(ISERR(AVERAGE($L$7:$N$7)),0,AVERAGE($L$7:$N$7)) -> 0 | P7: =IF(ISERR(AVERAGE($M$7:$O$7)),0,AVERAGE($M$7:$O$7)) -> 0 | Q7: =IF(ISERR(AVERAGE($N$7:$P$7)),0,AVERAGE($N$7:$P$7)) -> 0 | R7: =IF(ISERR(AVERAGE($O$7:$Q$7)),0,AVERAGE($O$7:$Q$7)) -> 0 | S7: =IF(ISERR(AVERAGE($O$7:$Q$7)),0,AVERAGE($O$7:$Q$7)) -> 0 | T7: =IF(ISERR(AVERAGE($O$7:$Q$7)),0,AVERAGE($O$7:$Q$7)) -> 0
B8: 营业税金及附加/营业收入 | C8: 前三年平均数据 | D8: =历史数据及预测表!D111/历史数据及预测表!D107 -> 0.0021435373 | E8: =历史数据及预测表!E111/历史数据及预测表!E107 -> 0.001230194 | F8: =历史数据及预测表!F111/历史数据及预测表!F107 -> 0.002223052 | G8: =历史数据及预测表!G111/历史数据及预测表!G107 -> 0.0020434365 | H8: =历史数据及预测表!H111/历史数据及预测表!H107 -> 0.0027688472 | I8: =IF(ISERR(AVERAGE($F$8:$H$8)),0,AVERAGE($F$8:$H$8)) -> 0.0023451119 | J8: =IF(ISERR(AVERAGE($G$8:$I$8)),0,AVERAGE($G$8:$I$8)) -> 0.0023857985 | K8: =IF(ISERR(AVERAGE($H$8:$J$8)),0,AVERAGE($H$8:$J$8)) -> 0.0024999192 | L8: =IF(ISERR(AVERAGE($I$8:$K$8)),0,AVERAGE($I$8:$K$8)) -> 0.0024102766 | M8: =IF(ISERR(AVERAGE($J$8:$L$8)),0,AVERAGE($J$8:$L$8)) -> 0.0024319981 | N8: =IF(ISERR(AVERAGE($K$8:$M$8)),0,AVERAGE($K$8:$M$8)) -> 0.002447398 | O8: =IF(ISERR(AVERAGE($L$8:$N$8)),0,AVERAGE($L$8:$N$8)) -> 0.0024298909 | P8: =IF(ISERR(AVERAGE($M$8:$O$8)),0,AVERAGE($M$8:$O$8)) -> 0.002436429 | Q8: =IF(ISERR(AVERAGE($N$8:$P$8)),0,AVERAGE($N$8:$P$8)) -> 0.0024379059 | R8: =IF(ISERR(AVERAGE($O$8:$Q$8)),0,AVERAGE($O$8:$Q$8)) -> 0.0024347419 | S8: =IF(ISERR(AVERAGE($O$8:$Q$8)),0,AVERAGE($O$8:$Q$8)) -> 0.0024347419 | T8: =IF(ISERR(AVERAGE($O$8:$Q$8)),0,AVERAGE($O$8:$Q$8)) -> 0.0024347419
B9: 销售费用/营业收入 | C9: 保持上一年数据 | D9: =历史数据及预测表!D112/历史数据及预测表!D107 -> 0.049036991 | E9: =历史数据及预测表!E112/历史数据及预测表!E107 -> 0.053833948 | F9: =历史数据及预测表!F112/历史数据及预测表!F107 -> 0.069096808 | G9: =历史数据及预测表!G112/历史数据及预测表!G107 -> 0.069932226 | H9: =历史数据及预测表!H112/历史数据及预测表!H107 -> 0.067461123 | I9: =历史数据及预测表!H112*(1+20%)/历史数据及预测表!I$106 -> 0.046197359 | J9: =历史数据及预测表!I112*(1+18%)/历史数据及预测表!J$106 -> 0.042752647 | K9: =历史数据及预测表!J112*(1+16%)/历史数据及预测表!K$106 -> 0.041938585 | L9: =$K$9 -> 0.041938585 | M9: =$L$9 -> 0.041938585 | N9: =$M$9 -> 0.041938585 | O9: =$N$9 -> 0.041938585 | P9: =$O$9 -> 0.041938585 | Q9: =$P$9 -> 0.041938585 | R9: =$Q$9 -> 0.041938585 | S9: =$R$9 -> 0.041938585 | T9: =$S$9 -> 0.041938585
B10: 管理费用/营业收入 | C10: 保持上一年数据 | D10: =历史数据及预测表!D113/历史数据及预测表!D107 -> 0.030265181 | E10: =历史数据及预测表!E113/历史数据及预测表!E107 -> 0.030694666 | F10: =历史数据及预测表!F113/历史数据及预测表!F107 -> 0.039472981 | G10: =历史数据及预测表!G113/历史数据及预测表!G107 -> 0.051076969 | H10: =历史数据及预测表!H113/历史数据及预测表!H107 -> 0.056558451 | I10: =历史数据及预测表!H113*(1+20%)/历史数据及预测表!I$106 -> 0.038731212 | J10: =历史数据及预测表!I113*(1+18%)/历史数据及预测表!J$106 -> 0.035843214 | K10: =历史数据及预测表!J113*(1+16%)/历史数据及预测表!K$106 -> 0.035160716 | L10: =$K$10 -> 0.035160716 | M10: =$L$10 -> 0.035160716 | N10: =$M$10 -> 0.035160716 | O10: =$N$10 -> 0.035160716 | P10: =$O$10 -> 0.035160716 | Q10: =$P$10 -> 0.035160716 | R10: =$Q$10 -> 0.035160716 | S10: =$R$10 -> 0.035160716 | T10: =$S$10 -> 0.035160716
B11: 研发费用/营业收入 | C11: 保持上一年数据 | D11: =历史数据及预测表!D114/历史数据及预测表!D107 -> 0.098823488 | E11: =历史数据及预测表!E114/历史数据及预测表!E107 -> 0.11855978 | F11: =历史数据及预测表!F114/历史数据及预测表!F107 -> 0.15633562 | G11: =历史数据及预测表!G114/历史数据及预测表!G107 -> 0.16173735 | H11: =历史数据及预测表!H114/历史数据及预测表!H107 -> 0.15018465 | I11: =历史数据及预测表!H114*(1+20%)/历史数据及预测表!I$106 -> 0.10284641 | J11: =历史数据及预测表!I114*(1+20%)/历史数据及预测表!J$106 -> 0.096790832 | K11: =历史数据及预测表!J114*(1+20%)/历史数据及预测表!K$106 -> 0.098221881 | L11: =$K$11 -> 0.098221881 | M11: =$L$11 -> 0.098221881 | N11: =$M$11 -> 0.098221881 | O11: =$N$11 -> 0.098221881 | P11: =$O$11 -> 0.098221881 | Q11: =$P$11 -> 0.098221881 | R11: =$Q$11 -> 0.098221881 | S11: =$R$11 -> 0.098221881 | T11: =$S$11 -> 0.098221881
B12: 公允价值变动净收益 | C12: 前三年平均数据 | D12: =历史数据及预测表!D117 -> 0.00636295 | E12: =历史数据及预测表!E117 -> 0.75596821 | F12: =历史数据及预测表!F117 -> 2.5300603 | G12: =历史数据及预测表!G117 -> 2.722478 | H12: =历史数据及预测表!H117 -> 2.5223899 | I12: =IF(ISERR(AVERAGE($F$12:$H$12)),0,AVERAGE($F$12:$H$12)) -> 2.5916427 | J12: =IF(ISERR(AVERAGE($G$12:$I$12)),0,AVERAGE($G$12:$I$12)) -> 2.6121702 | K12: =IF(ISERR(AVERAGE($H$12:$J$12)),0,AVERAGE($H$12:$J$12)) -> 2.5754009 | L12: =IF(ISERR(AVERAGE($I$12:$K$12)),0,AVERAGE($I$12:$K$12)) -> 2.5930713 | M12: =IF(ISERR(AVERAGE($J$12:$L$12)),0,AVERAGE($J$12:$L$12)) -> 2.5935475 | N12: =IF(ISERR(AVERAGE($K$12:$M$12)),0,AVERAGE($K$12:$M$12)) -> 2.5873399 | O12: =IF(ISERR(AVERAGE($L$12:$N$12)),0,AVERAGE($L$12:$N$12)) -> 2.5913196 | P12: =IF(ISERR(AVERAGE($M$12:$O$12)),0,AVERAGE($M$12:$O$12)) -> 2.5907357 | Q12: =IF(ISERR(AVERAGE($N$12:$P$12)),0,AVERAGE($N$12:$P$12)) -> 2.5897984 | R12: =IF(ISERR(AVERAGE($O$12:$Q$12)),0,AVERAGE($O$12:$Q$12)) -> 2.5906179 | S12: =IF(ISERR(AVERAGE($O$12:$Q$12)),0,AVERAGE($O$12:$Q$12)) -> 2.5906179 | T12: =IF(ISERR(AVERAGE($O$12:$Q$12)),0,AVERAGE($O$12:$Q$12)) -> 2.5906179
B13: 其他收益 | C13: 前三年平均数据 | D13: =历史数据及预测表!D120 -> 21.504856 | E13: =历史数据及预测表!E120 -> 27.308136 | F13: =历史数据及预测表!F120 -> 30.369928 | G13: =历史数据及预测表!G120 -> 32.39558 | H13: =历史数据及预测表!H120 -> 21.326596 | I13: =IF(ISERR(AVERAGE($F$13:$H$13)),0,AVERAGE($F$13:$H$13)) -> 28.030701 | J13: =IF(ISERR(AVERAGE($G$13:$I$13)),0,AVERAGE($G$13:$I$13)) -> 27.250959 | K13: =IF(ISERR(AVERAGE($H$13:$J$13)),0,AVERAGE($H$13:$J$13)) -> 25.536086 | L13: =IF(ISERR(AVERAGE($I$13:$K$13)),0,AVERAGE($I$13:$K$13)) -> 26.939249 | M13: =IF(ISERR(AVERAGE($J$13:$L$13)),0,AVERAGE($J$13:$L$13)) -> 26.575431 | N13: =IF(ISERR(AVERAGE($K$13:$M$13)),0,AVERAGE($K$13:$M$13)) -> 26.350255 | O13: =IF(ISERR(AVERAGE($L$13:$N$13)),0,AVERAGE($L$13:$N$13)) -> 26.621645 | P13: =IF(ISERR(AVERAGE($M$13:$O$13)),0,AVERAGE($M$13:$O$13)) -> 26.515777 | Q13: =IF(ISERR(AVERAGE($N$13:$P$13)),0,AVERAGE($N$13:$P$13)) -> 26.495892 | R13: =IF(ISERR(AVERAGE($O$13:$Q$13)),0,AVERAGE($O$13:$Q$13)) -> 26.544438 | S13: =IF(ISERR(AVERAGE($O$13:$Q$13)),0,AVERAGE($O$13:$Q$13)) -> 26.544438 | T13: =IF(ISERR(AVERAGE($O$13:$Q$13)),0,AVERAGE($O$13:$Q$13)) -> 26.544438
B14: 净敞口套期收益 | C14: 前三年平均数据 | D14: =历史数据及预测表!D121 -> 0 | E14: =历史数据及预测表!E121 -> 0 | F14: =历史数据及预测表!F121 -> 0 | G14: =历史数据及预测表!G121 -> 0 | H14: =历史数据及预测表!H121 -> 0 | I14: =IF(ISERR(AVERAGE($F$14:$H$14)),0,AVERAGE($F$14:$H$14)) -> 0 | J14: =IF(ISERR(AVERAGE($G$14:$I$14)),0,AVERAGE($G$14:$I$14)) -> 0 | K14: =IF(ISERR(AVERAGE($H$14:$J$14)),0,AVERAGE($H$14:$J$14)) -> 0 | L14: =IF(ISERR(AVERAGE($I$14:$K$14)),0,AVERAGE($I$14:$K$14)) -> 0 | M14: =IF(ISERR(AVERAGE($J$14:$L$14)),0,AVERAGE($J$14:$L$14)) -> 0 | N14: =IF(ISERR(AVERAGE($K$14:$M$14)),0,AVERAGE($K$14:$M$14)) -> 0 | O14: =IF(ISERR(AVERAGE($L$14:$N$14)),0,AVERAGE($L$14:$N$14)) -> 0 | P14: =IF(ISERR(AVERAGE($M$14:$O$14)),0,AVERAGE($M$14:$O$14)) -> 0 | Q14: =IF(ISERR(AVERAGE($N$14:$P$14)),0,AVERAGE($N$14:$P$14)) -> 0 | R14: =IF(ISERR(AVERAGE($O$14:$Q$14)),0,AVERAGE($O$14:$Q$14)) -> 0 | S14: =IF(ISERR(AVERAGE($O$14:$Q$14)),0,AVERAGE($O$14:$Q$14)) -> 0 | T14: =IF(ISERR(AVERAGE($O$14:$Q$14)),0,AVERAGE($O$14:$Q$14)) -> 0
B15: 资产处置收益 | C15: 前三年平均数据 | D15: =历史数据及预测表!D122 -> 0.0020586 | E15: =历史数据及预测表!E122 -> 0.36463244 | F15: =历史数据及预测表!F122 -> 0.02912005 | G15: =历史数据及预测表!G122 -> 0.00852257 | H15: =历史数据及预测表!H122 -> 24.130114 | I15: =IF(ISERR(AVERAGE($F$15:$H$15)),0,AVERAGE($F$15:$H$15)) -> 8.055919 | J15: =IF(ISERR(AVERAGE($G$15:$I$15)),0,AVERAGE($G$15:$I$15)) -> 10.731519 | K15: =IF(ISERR(AVERAGE($H$15:$J$15)),0,AVERAGE($H$15:$J$15)) -> 14.305851 | L15: =IF(ISERR(AVERAGE($I$15:$K$15)),0,AVERAGE($I$15:$K$15)) -> 11.031096 | M15: =IF(ISERR(AVERAGE($J$15:$L$15)),0,AVERAGE($J$15:$L$15)) -> 12.022822 | N15: =IF(ISERR(AVERAGE($K$15:$M$15)),0,AVERAGE($K$15:$M$15)) -> 12.453256 | O15: =IF(ISERR(AVERAGE($L$15:$N$15)),0,AVERAGE($L$15:$N$15)) -> 11.835725 | P15: =IF(ISERR(AVERAGE($M$15:$O$15)),0,AVERAGE($M$15:$O$15)) -> 12.103934 | Q15: =IF(ISERR(AVERAGE($N$15:$P$15)),0,AVERAGE($N$15:$P$15)) -> 12.130972 | R15: =IF(ISERR(AVERAGE($O$15:$Q$15)),0,AVERAGE($O$15:$Q$15)) -> 12.023544 | S15: =IF(ISERR(AVERAGE($O$15:$Q$15)),0,AVERAGE($O$15:$Q$15)) -> 12.023544 | T15: =IF(ISERR(AVERAGE($O$15:$Q$15)),0,AVERAGE($O$15:$Q$15)) -> 12.023544
B16: 投资净收益 | C16: 前三年平均数据 | D16: =历史数据及预测表!D123 -> 11.269118 | E16: =历史数据及预测表!E123 -> 14.865805 | F16: =历史数据及预测表!F123 -> 21.185221 | G16: =历史数据及预测表!G123 -> 25.237235 | H16: =历史数据及预测表!H123 -> 33.204846 | I16: =IF(ISERR(AVERAGE($F$16:$H$16)),0,AVERAGE($F$16:$H$16)) -> 26.542434 | J16: =IF(ISERR(AVERAGE($G$16:$I$16)),0,AVERAGE($G$16:$I$16)) -> 28.328172 | K16: =IF(ISERR(AVERAGE($H$16:$J$16)),0,AVERAGE($H$16:$J$16)) -> 29.358484 | L16: =IF(ISERR(AVERAGE($I$16:$K$16)),0,AVERAGE($I$16:$K$16)) -> 28.076363 | M16: =IF(ISERR(AVERAGE($J$16:$L$16)),0,AVERAGE($J$16:$L$16)) -> 28.587673 | N16: =IF(ISERR(AVERAGE($K$16:$M$16)),0,AVERAGE($K$16:$M$16)) -> 28.674173 | O16: =IF(ISERR(AVERAGE($L$16:$N$16)),0,AVERAGE($L$16:$N$16)) -> 28.44607 | P16: =IF(ISERR(AVERAGE($M$16:$O$16)),0,AVERAGE($M$16:$O$16)) -> 28.569305 | Q16: =IF(ISERR(AVERAGE($N$16:$P$16)),0,AVERAGE($N$16:$P$16)) -> 28.563183 | R16: =IF(ISERR(AVERAGE($O$16:$Q$16)),0,AVERAGE($O$16:$Q$16)) -> 28.526186 | S16: =IF(ISERR(AVERAGE($O$16:$Q$16)),0,AVERAGE($O$16:$Q$16)) -> 28.526186 | T16: =IF(ISERR(AVERAGE($O$16:$Q$16)),0,AVERAGE($O$16:$Q$16)) -> 28.526186
B17: 汇兑净收益 | C17: 前三年平均数据 | D17: =历史数据及预测表!D124 -> 0 | E17: =历史数据及预测表!E124 -> 0 | F17: =历史数据及预测表!F124 -> 0 | G17: =历史数据及预测表!G124 -> 0 | H17: =历史数据及预测表!H124 -> 0 | I17: =IF(ISERR(AVERAGE($F$17:$H$17)),0,AVERAGE($F$17:$H$17)) -> 0 | J17: =IF(ISERR(AVERAGE($G$17:$I$17)),0,AVERAGE($G$17:$I$17)) -> 0 | K17: =IF(ISERR(AVERAGE($H$17:$J$17)),0,AVERAGE($H$17:$J$17)) -> 0 | L17: =IF(ISERR(AVERAGE($I$17:$K$17)),0,AVERAGE($I$17:$K$17)) -> 0 | M17: =IF(ISERR(AVERAGE($J$17:$L$17)),0,AVERAGE($J$17:$L$17)) -> 0 | N17: =IF(ISERR(AVERAGE($K$17:$M$17)),0,AVERAGE($K$17:$M$17)) -> 0 | O17: =IF(ISERR(AVERAGE($L$17:$N$17)),0,AVERAGE($L$17:$N$17)) -> 0 | P17: =IF(ISERR(AVERAGE($M$17:$O$17)),0,AVERAGE($M$17:$O$17)) -> 0 | Q17: =IF(ISERR(AVERAGE($N$17:$P$17)),0,AVERAGE($N$17:$P$17)) -> 0 | R17: =IF(ISERR(AVERAGE($O$17:$Q$17)),0,AVERAGE($O$17:$Q$17)) -> 0 | S17: =IF(ISERR(AVERAGE($O$17:$Q$17)),0,AVERAGE($O$17:$Q$17)) -> 0 | T17: =IF(ISERR(AVERAGE($O$17:$Q$17)),0,AVERAGE($O$17:$Q$17)) -> 0
B18: 营业外收入 | C18: 前三年平均数据 | D18: =历史数据及预测表!D127 -> 1.6093279 | E18: =历史数据及预测表!E127 -> 1.4589294 | F18: =历史数据及预测表!F127 -> 1.1405179 | G18: =历史数据及预测表!G127 -> 3.0506707 | H18: =历史数据及预测表!H127 -> 1.1196703 | I18: =IF(ISERR(AVERAGE($F$18:$H$18)),0,AVERAGE($F$18:$H$18)) -> 1.7702863 | J18: =IF(ISERR(AVERAGE($G$18:$I$18)),0,AVERAGE($G$18:$I$18)) -> 1.9802091 | K18: =IF(ISERR(AVERAGE($H$18:$J$18)),0,AVERAGE($H$18:$J$18)) -> 1.6233886 | L18: =IF(ISERR(AVERAGE($I$18:$K$18)),0,AVERAGE($I$18:$K$18)) -> 1.7912947 | M18: =IF(ISERR(AVERAGE($J$18:$L$18)),0,AVERAGE($J$18:$L$18)) -> 1.7982974 | N18: =IF(ISERR(AVERAGE($K$18:$M$18)),0,AVERAGE($K$18:$M$18)) -> 1.7376602 | O18: =IF(ISERR(AVERAGE($L$18:$N$18)),0,AVERAGE($L$18:$N$18)) -> 1.7757508 | P18: =IF(ISERR(AVERAGE($M$18:$O$18)),0,AVERAGE($M$18:$O$18)) -> 1.7705695 | Q18: =IF(ISERR(AVERAGE($N$18:$P$18)),0,AVERAGE($N$18:$P$18)) -> 1.7613268 | R18: =IF(ISERR(AVERAGE($O$18:$Q$18)),0,AVERAGE($O$18:$Q$18)) -> 1.7692157 | S18: =IF(ISERR(AVERAGE($O$18:$Q$18)),0,AVERAGE($O$18:$Q$18)) -> 1.7692157 | T18: =IF(ISERR(AVERAGE($O$18:$Q$18)),0,AVERAGE($O$18:$Q$18)) -> 1.7692157
B19: 营业外支出 | C19: 前三年平均数据 | D19: =历史数据及预测表!D128 -> 0.06568668 | E19: =历史数据及预测表!E128 -> 0.19270111 | F19: =历史数据及预测表!F128 -> 0.44466041 | G19: =历史数据及预测表!G128 -> 1.6124723 | H19: =历史数据及预测表!H128 -> 1.9513034 | I19: =IF(ISERR(AVERAGE($F$19:$H$19)),0,AVERAGE($F$19:$H$19)) -> 1.3361454 | J19: =IF(ISERR(AVERAGE($G$19:$I$19)),0,AVERAGE($G$19:$I$19)) -> 1.633307 | K19: =IF(ISERR(AVERAGE($H$19:$J$19)),0,AVERAGE($H$19:$J$19)) -> 1.6402519 | L19: =IF(ISERR(AVERAGE($I$19:$K$19)),0,AVERAGE($I$19:$K$19)) -> 1.5365681 | M19: =IF(ISERR(AVERAGE($J$19:$L$19)),0,AVERAGE($J$19:$L$19)) -> 1.6033757 | N19: =IF(ISERR(AVERAGE($K$19:$M$19)),0,AVERAGE($K$19:$M$19)) -> 1.5933986 | O19: =IF(ISERR(AVERAGE($L$19:$N$19)),0,AVERAGE($L$19:$N$19)) -> 1.5777808 | P19: =IF(ISERR(AVERAGE($M$19:$O$19)),0,AVERAGE($M$19:$O$19)) -> 1.5915183 | Q19: =IF(ISERR(AVERAGE($N$19:$P$19)),0,AVERAGE($N$19:$P$19)) -> 1.5875659 | R19: =IF(ISERR(AVERAGE($O$19:$Q$19)),0,AVERAGE($O$19:$Q$19)) -> 1.5856217 | S19: =IF(ISERR(AVERAGE($O$19:$Q$19)),0,AVERAGE($O$19:$Q$19)) -> 1.5856217 | T19: =IF(ISERR(AVERAGE($O$19:$Q$19)),0,AVERAGE($O$19:$Q$19)) -> 1.5856217
B20: 实际所得税率 | C20: 前三年平均数据 | D20: =历史数据及预测表!D131/历史数据及预测表!D130 -> 0.013537259 | E20: =历史数据及预测表!E131/历史数据及预测表!E130 -> 0.044243944 | F20: =历史数据及预测表!F131/历史数据及预测表!F130 -> 0.054072299 | G20: =历史数据及预测表!G131/历史数据及预测表!G130 -> 0.1116365 | H20: =历史数据及预测表!H131/历史数据及预测表!H130 -> 0.092701643 | I20: =IF(ISERR(AVERAGE($F$20:$H$20)),0,AVERAGE($F$20:$H$20)) -> 0.086136813 | J20: =IF(ISERR(AVERAGE($G$20:$I$20)),0,AVERAGE($G$20:$I$20)) -> 0.096824985 | K20: =IF(ISERR(AVERAGE($H$20:$J$20)),0,AVERAGE($H$20:$J$20)) -> 0.091887814 | L20: =IF(ISERR(AVERAGE($I$20:$K$20)),0,AVERAGE($I$20:$K$20)) -> 0.091616537 | M20: =IF(ISERR(AVERAGE($J$20:$L$20)),0,AVERAGE($J$20:$L$20)) -> 0.093443112 | N20: =IF(ISERR(AVERAGE($K$20:$M$20)),0,AVERAGE($K$20:$M$20)) -> 0.092315821 | O20: =IF(ISERR(AVERAGE($L$20:$N$20)),0,AVERAGE($L$20:$N$20)) -> 0.09245849 | P20: =IF(ISERR(AVERAGE($M$20:$O$20)),0,AVERAGE($M$20:$O$20)) -> 0.092739141 | Q20: =IF(ISERR(AVERAGE($N$20:$P$20)),0,AVERAGE($N$20:$P$20)) -> 0.092504484 | R20: =IF(ISERR(AVERAGE($O$20:$Q$20)),0,AVERAGE($O$20:$Q$20)) -> 0.092567372 | S20: =IF(ISERR(AVERAGE($O$20:$Q$20)),0,AVERAGE($O$20:$Q$20)) -> 0.092567372 | T20: =IF(ISERR(AVERAGE($O$20:$Q$20)),0,AVERAGE($O$20:$Q$20)) -> 0.092567372
B21: 未确认的投资损失 | C21: 前三年平均数据 | D21: =历史数据及预测表!D132 -> 0 | E21: =历史数据及预测表!E132 -> 0 | F21: =历史数据及预测表!F132 -> 0 | G21: =历史数据及预测表!G132 -> 0 | H21: =历史数据及预测表!H132 -> 0 | I21: =IF(ISERR(AVERAGE($F$21:$H$21)),0,AVERAGE($F$21:$H$21)) -> 0 | J21: =IF(ISERR(AVERAGE($G$21:$I$21)),0,AVERAGE($G$21:$I$21)) -> 0 | K21: =IF(ISERR(AVERAGE($H$21:$J$21)),0,AVERAGE($H$21:$J$21)) -> 0 | L21: =IF(ISERR(AVERAGE($I$21:$K$21)),0,AVERAGE($I$21:$K$21)) -> 0 | M21: =IF(ISERR(AVERAGE($J$21:$L$21)),0,AVERAGE($J$21:$L$21)) -> 0 | N21: =IF(ISERR(AVERAGE($K$21:$M$21)),0,AVERAGE($K$21:$M$21)) -> 0 | O21: =IF(ISERR(AVERAGE($L$21:$N$21)),0,AVERAGE($L$21:$N$21)) -> 0 | P21: =IF(ISERR(AVERAGE($M$21:$O$21)),0,AVERAGE($M$21:$O$21)) -> 0 | Q21: =IF(ISERR(AVERAGE($N$21:$P$21)),0,AVERAGE($N$21:$P$21)) -> 0 | R21: =IF(ISERR(AVERAGE($O$21:$Q$21)),0,AVERAGE($O$21:$Q$21)) -> 0 | S21: =IF(ISERR(AVERAGE($O$21:$Q$21)),0,AVERAGE($O$21:$Q$21)) -> 0 | T21: =IF(ISERR(AVERAGE($O$21:$Q$21)),0,AVERAGE($O$21:$Q$21)) -> 0
B22: 少数股东损益/净利润 | C22: 前三年平均数据 | D22: =历史数据及预测表!D135/历史数据及预测表!D134 -> -0.005220674 | E22: =历史数据及预测表!E135/历史数据及预测表!E134 -> -0.013231822 | F22: =历史数据及预测表!F135/历史数据及预测表!F134 -> -0.041747011 | G22: =历史数据及预测表!G135/历史数据及预测表!G134 -> -0.0055033751 | H22: =历史数据及预测表!H135/历史数据及预测表!H134 -> -0.0023852678 | I22: =IF(ISERR(AVERAGE($F$22:$H$22)),0,AVERAGE($F$22:$H$22)) -> -0.016545218 | J22: =IF(ISERR(AVERAGE($G$22:$I$22)),0,AVERAGE($G$22:$I$22)) -> -0.0081446203 | K22: =IF(ISERR(AVERAGE($H$22:$J$22)),0,AVERAGE($H$22:$J$22)) -> -0.0090250353 | L22: =IF(ISERR(AVERAGE($I$22:$K$22)),0,AVERAGE($I$22:$K$22)) -> -0.011238291 | M22: =IF(ISERR(AVERAGE($J$22:$L$22)),0,AVERAGE($J$22:$L$22)) -> -0.0094693156 | N22: =IF(ISERR(AVERAGE($K$22:$M$22)),0,AVERAGE($K$22:$M$22)) -> -0.0099108807 | O22: =IF(ISERR(AVERAGE($L$22:$N$22)),0,AVERAGE($L$22:$N$22)) -> -0.010206162 | P22: =IF(ISERR(AVERAGE($M$22:$O$22)),0,AVERAGE($M$22:$O$22)) -> -0.0098621196 | Q22: =IF(ISERR(AVERAGE($N$22:$P$22)),0,AVERAGE($N$22:$P$22)) -> -0.0099930542 | R22: =IF(ISERR(AVERAGE($O$22:$Q$22)),0,AVERAGE($O$22:$Q$22)) -> -0.010020445 | S22: =IF(ISERR(AVERAGE($O$22:$Q$22)),0,AVERAGE($O$22:$Q$22)) -> -0.010020445 | T22: =IF(ISERR(AVERAGE($O$22:$Q$22)),0,AVERAGE($O$22:$Q$22)) -> -0.010020445
B23: 其他综合收益 | C23: 前三年平均数据 | D23: =历史数据及预测表!D137 -> -39.835859 | E23: =历史数据及预测表!E137 -> 224.78408 | F23: =历史数据及预测表!F137 -> 69.903818 | G23: =历史数据及预测表!G137 -> -59.621816 | H23: =历史数据及预测表!H137 -> -45.661901 | I23: =IF(ISERR(AVERAGE($F$23:$H$23)),0,AVERAGE($F$23:$H$23)) -> -11.7933 | J23: =IF(ISERR(AVERAGE($G$23:$I$23)),0,AVERAGE($G$23:$I$23)) -> -39.025672 | K23: =IF(ISERR(AVERAGE($H$23:$J$23)),0,AVERAGE($H$23:$J$23)) -> -32.160291 | L23: =IF(ISERR(AVERAGE($I$23:$K$23)),0,AVERAGE($I$23:$K$23)) -> -27.659754 | M23: =IF(ISERR(AVERAGE($J$23:$L$23)),0,AVERAGE($J$23:$L$23)) -> -32.948573 | N23: =IF(ISERR(AVERAGE($K$23:$M$23)),0,AVERAGE($K$23:$M$23)) -> -30.922873 | O23: =IF(ISERR(AVERAGE($L$23:$N$23)),0,AVERAGE($L$23:$N$23)) -> -30.5104 | P23: =IF(ISERR(AVERAGE($M$23:$O$23)),0,AVERAGE($M$23:$O$23)) -> -31.460615 | Q23: =IF(ISERR(AVERAGE($N$23:$P$23)),0,AVERAGE($N$23:$P$23)) -> -30.964629 | R23: =IF(ISERR(AVERAGE($O$23:$Q$23)),0,AVERAGE($O$23:$Q$23)) -> -30.978548 | S23: =IF(ISERR(AVERAGE($O$23:$Q$23)),0,AVERAGE($O$23:$Q$23)) -> -30.978548 | T23: =IF(ISERR(AVERAGE($O$23:$Q$23)),0,AVERAGE($O$23:$Q$23)) -> -30.978548
B24: 少数股东综合收益/综合收益总额 | C24: 前三年平均数据 | D24: =历史数据及预测表!D139/历史数据及预测表!D138 -> -0.0053567444 | E24: =历史数据及预测表!E139/历史数据及预测表!E138 -> -0.010032184 | F24: =历史数据及预测表!F139/历史数据及预测表!F138 -> -0.036046069 | G24: =历史数据及预测表!G139/历史数据及预测表!G138 -> -0.0091406212 | H24: =历史数据及预测表!H139/历史数据及预测表!H138 -> -0.0022920581 | I24: =IF(ISERR(AVERAGE($F$24:$H$24)),0,AVERAGE($F$24:$H$24)) -> -0.015826249 | J24: =IF(ISERR(AVERAGE($G$24:$I$24)),0,AVERAGE($G$24:$I$24)) -> -0.0090863096 | K24: =IF(ISERR(AVERAGE($H$24:$J$24)),0,AVERAGE($H$24:$J$24)) -> -0.0090682057 | L24: =IF(ISERR(AVERAGE($I$24:$K$24)),0,AVERAGE($I$24:$K$24)) -> -0.011326922 | M24: =IF(ISERR(AVERAGE($J$24:$L$24)),0,AVERAGE($J$24:$L$24)) -> -0.0098271456 | N24: =IF(ISERR(AVERAGE($K$24:$M$24)),0,AVERAGE($K$24:$M$24)) -> -0.010074091 | O24: =IF(ISERR(AVERAGE($L$24:$N$24)),0,AVERAGE($L$24:$N$24)) -> -0.010409386 | P24: =IF(ISERR(AVERAGE($M$24:$O$24)),0,AVERAGE($M$24:$O$24)) -> -0.010103541 | Q24: =IF(ISERR(AVERAGE($N$24:$P$24)),0,AVERAGE($N$24:$P$24)) -> -0.010195673 | R24: =IF(ISERR(AVERAGE($O$24:$Q$24)),0,AVERAGE($O$24:$Q$24)) -> -0.0102362 | S24: =IF(ISERR(AVERAGE($O$24:$Q$24)),0,AVERAGE($O$24:$Q$24)) -> -0.0102362 | T24: =IF(ISERR(AVERAGE($O$24:$Q$24)),0,AVERAGE($O$24:$Q$24)) -> -0.0102362
B25: DPS-Q1 | D25: =历史数据及预测表!D214 -> 0 | E25: =历史数据及预测表!E214 -> 0 | F25: =历史数据及预测表!F214 -> 0 | G25: =历史数据及预测表!G214 -> 0 | H25: =历史数据及预测表!H214 -> 0
B26: DPS-Q2/年中 | D26: =历史数据及预测表!D215 -> 0 | E26: =历史数据及预测表!E215 -> 0 | F26: =历史数据及预测表!F215 -> 0 | G26: =历史数据及预测表!G215 -> 0 | H26: =历史数据及预测表!H215 -> 0
B27: DPS-Q3 | D27: =历史数据及预测表!D216 -> 0 | E27: =历史数据及预测表!E216 -> 0 | F27: =历史数据及预测表!F216 -> 0 | G27: =历史数据及预测表!G216 -> 0 | H27: =历史数据及预测表!H216 -> 0
B28: DPS-Q4/年末 | D28: =历史数据及预测表!D217 -> 0.19 | E28: =历史数据及预测表!E217 -> 0.08 | F28: =历史数据及预测表!F217 -> 0.2 | G28: =历史数据及预测表!G217 -> 0.0998 | H28: =历史数据及预测表!H217 -> 0.15
B29: DPS-特殊 | D29: =历史数据及预测表!D218 -> 0 | E29: =历史数据及预测表!E218 -> 0 | F29: =历史数据及预测表!F218 -> 0 | G29: =历史数据及预测表!G218 -> 0 | H29: =历史数据及预测表!H218 -> 0
B30: 股利支付率 | D30: =历史数据及预测表!D226 -> 0.098790913 | E30: =历史数据及预测表!E226 -> 0.048813313 | F30: =历史数据及预测表!F226 -> 0.17927072 | G30: =历史数据及预测表!G226 -> 0.13124086 | H30: =历史数据及预测表!H226 -> 0.1923873 | I30: 0.2 | J30: 0.2 | K30: 0.2 | L30: 0.2 | M30: 0.2 | N30: 0.2 | O30: 0.2 | P30: 0.2 | Q30: 0.2 | R30: 0.2 | S30: 0.2 | T30: 0.2
A32: 营运资金假设
B33: 交易性金融资产本期增减 | C33: 默认值0 | E33: =历史数据及预测表!E8-历史数据及预测表!D8 -> -611.61648 | F33: =历史数据及预测表!F8-历史数据及预测表!E8 -> 43.258329 | G33: =历史数据及预测表!G8-历史数据及预测表!F8 -> 363.87195 | H33: =历史数据及预测表!H8-历史数据及预测表!G8 -> 141.96748 | I33: 0 | J33: 0 | K33: 0 | L33: 0 | M33: 0 | N33: 0 | O33: 0 | P33: 0 | Q33: 0 | R33: 0 | S33: 0 | T33: 0
B34: 衍生金融资产本期增减 | C34: 默认值0 | E34: =历史数据及预测表!E9-历史数据及预测表!D9 -> 0 | F34: =历史数据及预测表!F9-历史数据及预测表!E9 -> 0 | G34: =历史数据及预测表!G9-历史数据及预测表!F9 -> 0 | H34: =历史数据及预测表!H9-历史数据及预测表!G9 -> 0 | I34: 0 | J34: 0 | K34: 0 | L34: 0 | M34: 0 | N34: 0 | O34: 0 | P34: 0 | Q34: 0 | R34: 0 | S34: 0 | T34: 0
B35: 应收账款原值/营业收入 | C35: 前三年平均数据 | D35: =历史数据及预测表!D189/历史数据及预测表!D107 -> 0.12480499 | E35: =历史数据及预测表!E189/历史数据及预测表!E107 -> 0.095342456 | F35: =历史数据及预测表!F189/历史数据及预测表!F107 -> 0.089021279 | G35: =历史数据及预测表!G189/历史数据及预测表!G107 -> 0.09227702 | H35: =历史数据及预测表!H189/历史数据及预测表!H107 -> 0.098403652 | I35: =IF(ISERR(AVERAGE($F$35:$H$35)),0,AVERAGE($F$35:$H$35)) -> 0.093233983 | J35: =IF(ISERR(AVERAGE($G$35:$I$35)),0,AVERAGE($G$35:$I$35)) -> 0.094638218 | K35: =IF(ISERR(AVERAGE($H$35:$J$35)),0,AVERAGE($H$35:$J$35)) -> 0.095425284 | L35: =IF(ISERR(AVERAGE($I$35:$K$35)),0,AVERAGE($I$35:$K$35)) -> 0.094432495 | M35: =IF(ISERR(AVERAGE($J$35:$L$35)),0,AVERAGE($J$35:$L$35)) -> 0.094831999 | N35: =IF(ISERR(AVERAGE($K$35:$M$35)),0,AVERAGE($K$35:$M$35)) -> 0.094896593 | O35: =IF(ISERR(AVERAGE($L$35:$N$35)),0,AVERAGE($L$35:$N$35)) -> 0.094720363 | P35: =IF(ISERR(AVERAGE($M$35:$O$35)),0,AVERAGE($M$35:$O$35)) -> 0.094816318 | Q35: =IF(ISERR(AVERAGE($N$35:$P$35)),0,AVERAGE($N$35:$P$35)) -> 0.094811091 | R35: =IF(ISERR(AVERAGE($O$35:$Q$35)),0,AVERAGE($O$35:$Q$35)) -> 0.094782591 | S35: =IF(ISERR(AVERAGE($O$35:$Q$35)),0,AVERAGE($O$35:$Q$35)) -> 0.094782591 | T35: =IF(ISERR(AVERAGE($O$35:$Q$35)),0,AVERAGE($O$35:$Q$35)) -> 0.094782591
B36: 坏账准备/应收账款 | C36: 前三年平均数据 | D36: =历史数据及预测表!D190/历史数据及预测表!D189 -> 0 | E36: =历史数据及预测表!E190/历史数据及预测表!E189 -> 0 | F36: =历史数据及预测表!F190/历史数据及预测表!F189 -> 0 | G36: =历史数据及预测表!G190/历史数据及预测表!G189 -> 0 | H36: =历史数据及预测表!H190/历史数据及预测表!H189 -> 0 | I36: =IF(ISERR(AVERAGE($F$36:$H$36)),0,AVERAGE($F$36:$H$36)) -> 0 | J36: =IF(ISERR(AVERAGE($G$36:$I$36)),0,AVERAGE($G$36:$I$36)) -> 0 | K36: =IF(ISERR(AVERAGE($H$36:$J$36)),0,AVERAGE($H$36:$J$36)) -> 0 | L36: =IF(ISERR(AVERAGE($I$36:$K$36)),0,AVERAGE($I$36:$K$36)) -> 0 | M36: =IF(ISERR(AVERAGE($J$36:$L$36)),0,AVERAGE($J$36:$L$36)) -> 0 | N36: =IF(ISERR(AVERAGE($K$36:$M$36)),0,AVERAGE($K$36:$M$36)) -> 0 | O36: =IF(ISERR(AVERAGE($L$36:$N$36)),0,AVERAGE($L$36:$N$36)) -> 0 | P36: =IF(ISERR(AVERAGE($M$36:$O$36)),0,AVERAGE($M$36:$O$36)) -> 0 | Q36: =IF(ISERR(AVERAGE($N$36:$P$36)),0,AVERAGE($N$36:$P$36)) -> 0 | R36: =IF(ISERR(AVERAGE($O$36:$Q$36)),0,AVERAGE($O$36:$Q$36)) -> 0 | S36: =IF(ISERR(AVERAGE($O$36:$Q$36)),0,AVERAGE($O$36:$Q$36)) -> 0 | T36: =IF(ISERR(AVERAGE($O$36:$Q$36)),0,AVERAGE($O$36:$Q$36)) -> 0
B37: 应收票据/营业收入 | C37: 前三年平均数据 | D37: =历史数据及预测表!D11/历史数据及预测表!D107 -> 0.00051238879 | E37: =历史数据及预测表!E11/历史数据及预测表!E107 -> 0.00082078369 | F37: =历史数据及预测表!F11/历史数据及预测表!F107 -> 0.00087922083 | G37: =历史数据及预测表!G11/历史数据及预测表!G107 -> 0.00052765942 | H37: =历史数据及预测表!H11/历史数据及预测表!H107 -> 0.00089617997 | I37: =IF(ISERR(AVERAGE($F$37:$H$37)),0,AVERAGE($F$37:$H$37)) -> 0.00076768674 | J37: =IF(ISERR(AVERAGE($G$37:$I$37)),0,AVERAGE($G$37:$I$37)) -> 0.00073050871 | K37: =IF(ISERR(AVERAGE($H$37:$J$37)),0,AVERAGE($H$37:$J$37)) -> 0.00079812514 | L37: =IF(ISERR(AVERAGE($I$37:$K$37)),0,AVERAGE($I$37:$K$37)) -> 0.0007654402 | M37: =IF(ISERR(AVERAGE($J$37:$L$37)),0,AVERAGE($J$37:$L$37)) -> 0.00076469135 | N37: =IF(ISERR(AVERAGE($K$37:$M$37)),0,AVERAGE($K$37:$M$37)) -> 0.00077608556 | O37: =IF(ISERR(AVERAGE($L$37:$N$37)),0,AVERAGE($L$37:$N$37)) -> 0.00076873904 | P37: =IF(ISERR(AVERAGE($M$37:$O$37)),0,AVERAGE($M$37:$O$37)) -> 0.00076983865 | Q37: =IF(ISERR(AVERAGE($N$37:$P$37)),0,AVERAGE($N$37:$P$37)) -> 0.00077155442 | R37: =IF(ISERR(AVERAGE($O$37:$Q$37)),0,AVERAGE($O$37:$Q$37)) -> 0.00077004403 | S37: =IF(ISERR(AVERAGE($O$37:$Q$37)),0,AVERAGE($O$37:$Q$37)) -> 0.00077004403 | T37: =IF(ISERR(AVERAGE($O$37:$Q$37)),0,AVERAGE($O$37:$Q$37)) -> 0.00077004403
B38: 应收款项融资/营业收入 | C38: 前三年平均数据 | D38: =历史数据及预测表!D12/历史数据及预测表!D107 -> 0 | E38: =历史数据及预测表!E12/历史数据及预测表!E107 -> 0 | F38: =历史数据及预测表!F12/历史数据及预测表!F107 -> 0 | G38: =历史数据及预测表!G12/历史数据及预测表!G107 -> 0 | H38: =历史数据及预测表!H12/历史数据及预测表!H107 -> 0 | I38: =IF(ISERR(AVERAGE($F$38:$H$38)),0,AVERAGE($F$38:$H$38)) -> 0 | J38: =IF(ISERR(AVERAGE($G$38:$I$38)),0,AVERAGE($G$38:$I$38)) -> 0 | K38: =IF(ISERR(AVERAGE($H$38:$J$38)),0,AVERAGE($H$38:$J$38)) -> 0 | L38: =IF(ISERR(AVERAGE($I$38:$K$38)),0,AVERAGE($I$38:$K$38)) -> 0 | M38: =IF(ISERR(AVERAGE($J$38:$L$38)),0,AVERAGE($J$38:$L$38)) -> 0 | N38: =IF(ISERR(AVERAGE($K$38:$M$38)),0,AVERAGE($K$38:$M$38)) -> 0 | O38: =IF(ISERR(AVERAGE($L$38:$N$38)),0,AVERAGE($L$38:$N$38)) -> 0 | P38: =IF(ISERR(AVERAGE($M$38:$O$38)),0,AVERAGE($M$38:$O$38)) -> 0 | Q38: =IF(ISERR(AVERAGE($N$38:$P$38)),0,AVERAGE($N$38:$P$38)) -> 0 | R38: =IF(ISERR(AVERAGE($O$38:$Q$38)),0,AVERAGE($O$38:$Q$38)) -> 0 | S38: =IF(ISERR(AVERAGE($O$38:$Q$38)),0,AVERAGE($O$38:$Q$38)) -> 0 | T38: =IF(ISERR(AVERAGE($O$38:$Q$38)),0,AVERAGE($O$38:$Q$38)) -> 0
B39: 预付账款/营业成本 | C39: 前三年平均数据 | D39: =历史数据及预测表!D13/历史数据及预测表!D110 -> 0.0088032422 | E39: =历史数据及预测表!E13/历史数据及预测表!E110 -> 0.016304494 | F39: =历史数据及预测表!F13/历史数据及预测表!F110 -> 0.024213001 | G39: =历史数据及预测表!G13/历史数据及预测表!G110 -> 0.033685667 | H39: =历史数据及预测表!H13/历史数据及预测表!H110 -> 0.050412123 | I39: =IF(ISERR(AVERAGE($F$39:$H$39)),0,AVERAGE($F$39:$H$39)) -> 0.036103597 | J39: =IF(ISERR(AVERAGE($G$39:$I$39)),0,AVERAGE($G$39:$I$39)) -> 0.040067129 | K39: =IF(ISERR(AVERAGE($H$39:$J$39)),0,AVERAGE($H$39:$J$39)) -> 0.042194283 | L39: =IF(ISERR(AVERAGE($I$39:$K$39)),0,AVERAGE($I$39:$K$39)) -> 0.039455003 | M39: =IF(ISERR(AVERAGE($J$39:$L$39)),0,AVERAGE($J$39:$L$39)) -> 0.040572139 | N39: =IF(ISERR(AVERAGE($K$39:$M$39)),0,AVERAGE($K$39:$M$39)) -> 0.040740475 | O39: =IF(ISERR(AVERAGE($L$39:$N$39)),0,AVERAGE($L$39:$N$39)) -> 0.040255872 | P39: =IF(ISERR(AVERAGE($M$39:$O$39)),0,AVERAGE($M$39:$O$39)) -> 0.040522829 | Q39: =IF(ISERR(AVERAGE($N$39:$P$39)),0,AVERAGE($N$39:$P$39)) -> 0.040506392 | R39: =IF(ISERR(AVERAGE($O$39:$Q$39)),0,AVERAGE($O$39:$Q$39)) -> 0.040428364 | S39: =IF(ISERR(AVERAGE($O$39:$Q$39)),0,AVERAGE($O$39:$Q$39)) -> 0.040428364 | T39: =IF(ISERR(AVERAGE($O$39:$Q$39)),0,AVERAGE($O$39:$Q$39)) -> 0.040428364
B40: 其他应收款/营业收入 | C40: 前三年平均数据 | D40: =历史数据及预测表!D192/历史数据及预测表!D107 -> 0.017863873 | E40: =历史数据及预测表!E192/历史数据及预测表!E107 -> 0.018828519 | F40: =历史数据及预测表!F192/历史数据及预测表!F107 -> 0.062688853 | G40: =历史数据及预测表!G192/历史数据及预测表!G107 -> 0.067610494 | H40: =历史数据及预测表!H192/历史数据及预测表!H107 -> 0.00034955126 | I40: =IF(ISERR(AVERAGE($F$40:$H$40)),0,AVERAGE($F$40:$H$40)) -> 0.043549633 | J40: =IF(ISERR(AVERAGE($G$40:$I$40)),0,AVERAGE($G$40:$I$40)) -> 0.037169893 | K40: =IF(ISERR(AVERAGE($H$40:$J$40)),0,AVERAGE($H$40:$J$40)) -> 0.027023026 | L40: =IF(ISERR(AVERAGE($I$40:$K$40)),0,AVERAGE($I$40:$K$40)) -> 0.035914184 | M40: =IF(ISERR(AVERAGE($J$40:$L$40)),0,AVERAGE($J$40:$L$40)) -> 0.033369034 | N40: =IF(ISERR(AVERAGE($K$40:$M$40)),0,AVERAGE($K$40:$M$40)) -> 0.032102081 | O40: =IF(ISERR(AVERAGE($L$40:$N$40)),0,AVERAGE($L$40:$N$40)) -> 0.0337951 | P40: =IF(ISERR(AVERAGE($M$40:$O$40)),0,AVERAGE($M$40:$O$40)) -> 0.033088738 | Q40: =IF(ISERR(AVERAGE($N$40:$P$40)),0,AVERAGE($N$40:$P$40)) -> 0.032995306 | R40: =IF(ISERR(AVERAGE($O$40:$Q$40)),0,AVERAGE($O$40:$Q$40)) -> 0.033293048 | S40: =IF(ISERR(AVERAGE($O$40:$Q$40)),0,AVERAGE($O$40:$Q$40)) -> 0.033293048 | T40: =IF(ISERR(AVERAGE($O$40:$Q$40)),0,AVERAGE($O$40:$Q$40)) -> 0.033293048
B41: 其他应收款坏账准备/其他应收款 | C41: 前三年平均数据 | D41: =历史数据及预测表!D193/历史数据及预测表!D192 -> 0 | E41: =历史数据及预测表!E193/历史数据及预测表!E192 -> 0 | F41: =历史数据及预测表!F193/历史数据及预测表!F192 -> 0 | G41: =历史数据及预测表!G193/历史数据及预测表!G192 -> 0 | H41: =历史数据及预测表!H193/历史数据及预测表!H192 -> 0 | I41: =IF(ISERR(AVERAGE($F$41:$H$41)),0,AVERAGE($F$41:$H$41)) -> 0 | J41: =IF(ISERR(AVERAGE($G$41:$I$41)),0,AVERAGE($G$41:$I$41)) -> 0 | K41: =IF(ISERR(AVERAGE($H$41:$J$41)),0,AVERAGE($H$41:$J$41)) -> 0 | L41: =IF(ISERR(AVERAGE($I$41:$K$41)),0,AVERAGE($I$41:$K$41)) -> 0 | M41: =IF(ISERR(AVERAGE($J$41:$L$41)),0,AVERAGE($J$41:$L$41)) -> 0 | N41: =IF(ISERR(AVERAGE($K$41:$M$41)),0,AVERAGE($K$41:$M$41)) -> 0 | O41: =IF(ISERR(AVERAGE($L$41:$N$41)),0,AVERAGE($L$41:$N$41)) -> 0 | P41: =IF(ISERR(AVERAGE($M$41:$O$41)),0,AVERAGE($M$41:$O$41)) -> 0 | Q41: =IF(ISERR(AVERAGE($N$41:$P$41)),0,AVERAGE($N$41:$P$41)) -> 0 | R41: =IF(ISERR(AVERAGE($O$41:$Q$41)),0,AVERAGE($O$41:$Q$41)) -> 0 | S41: =IF(ISERR(AVERAGE($O$41:$Q$41)),0,AVERAGE($O$41:$Q$41)) -> 0 | T41: =IF(ISERR(AVERAGE($O$41:$Q$41)),0,AVERAGE($O$41:$Q$41)) -> 0
B42: 存货/营业成本 | C42: 保持上一年数据 | D42: =历史数据及预测表!D195/历史数据及预测表!D110 -> 0.47209921 | E42: =历史数据及预测表!E195/历史数据及预测表!E110 -> 0.80743961 | F42: =历史数据及预测表!F195/历史数据及预测表!F110 -> 0.94461347 | G42: =历史数据及预测表!G195/历史数据及预测表!G110 -> 1.0958703 | H42: =历史数据及预测表!H195/历史数据及预测表!H110 -> 1.0171857 | I42: 0.8 | J42: =$I$42 -> 0.8 | K42: =$J$42 -> 0.8 | L42: =$K$42 -> 0.8 | M42: =$L$42 -> 0.8 | N42: =$M$42 -> 0.8 | O42: =$N$42 -> 0.8 | P42: =$O$42 -> 0.8 | Q42: =$P$42 -> 0.8 | R42: =$Q$42 -> 0.8 | S42: =$R$42 -> 0.8 | T42: =$S$42 -> 0.8
B43: 存货跌价准备/存货 | C43: 保持上一年数据 | D43: =历史数据及预测表!D196/历史数据及预测表!D195 -> 0.095752381 | E43: =历史数据及预测表!E196/历史数据及预测表!E195 -> 0.14191162 | F43: =历史数据及预测表!F196/历史数据及预测表!F195 -> 0.10674301 | G43: =历史数据及预测表!G196/历史数据及预测表!G195 -> 0.085203718 | H43: =历史数据及预测表!H196/历史数据及预测表!H195 -> 0.064185195 | I43: 0.06 | J43: =$I$43 -> 0.06 | K43: =$J$43 -> 0.06 | L43: =$K$43 -> 0.06 | M43: =$L$43 -> 0.06 | N43: =$M$43 -> 0.06 | O43: =$N$43 -> 0.06 | P43: =$O$43 -> 0.06 | Q43: =$P$43 -> 0.06 | R43: =$Q$43 -> 0.06 | S43: =$R$43 -> 0.06 | T43: =$S$43 -> 0.06
B44: 合同资产原值/营业成本 | C44: 前三年平均数据 | D44: =历史数据及预测表!D198/历史数据及预测表!D110 -> 0 | E44: =历史数据及预测表!E198/历史数据及预测表!E110 -> 0 | F44: =历史数据及预测表!F198/历史数据及预测表!F110 -> 0 | G44: =历史数据及预测表!G198/历史数据及预测表!G110 -> 0 | H44: =历史数据及预测表!H198/历史数据及预测表!H110 -> 0 | I44: =IF(ISERR(AVERAGE($F$44:$H$44)),0,AVERAGE($F$44:$H$44)) -> 0 | J44: =IF(ISERR(AVERAGE($G$44:$I$44)),0,AVERAGE($G$44:$I$44)) -> 0 | K44: =IF(ISERR(AVERAGE($H$44:$J$44)),0,AVERAGE($H$44:$J$44)) -> 0 | L44: =IF(ISERR(AVERAGE($I$44:$K$44)),0,AVERAGE($I$44:$K$44)) -> 0 | M44: =IF(ISERR(AVERAGE($J$44:$L$44)),0,AVERAGE($J$44:$L$44)) -> 0 | N44: =IF(ISERR(AVERAGE($K$44:$M$44)),0,AVERAGE($K$44:$M$44)) -> 0 | O44: =IF(ISERR(AVERAGE($L$44:$N$44)),0,AVERAGE($L$44:$N$44)) -> 0 | P44: =IF(ISERR(AVERAGE($M$44:$O$44)),0,AVERAGE($M$44:$O$44)) -> 0 | Q44: =IF(ISERR(AVERAGE($N$44:$P$44)),0,AVERAGE($N$44:$P$44)) -> 0 | R44: =IF(ISERR(AVERAGE($O$44:$Q$44)),0,AVERAGE($O$44:$Q$44)) -> 0 | S44: =IF(ISERR(AVERAGE($O$44:$Q$44)),0,AVERAGE($O$44:$Q$44)) -> 0 | T44: =IF(ISERR(AVERAGE($O$44:$Q$44)),0,AVERAGE($O$44:$Q$44)) -> 0
B45: 合同资产减值准备/合同资产 | C45: 前三年平均数据 | D45: =历史数据及预测表!D199/历史数据及预测表!D198 -> #DIV/0! | E45: =历史数据及预测表!E199/历史数据及预测表!E198 -> #DIV/0! | F45: =历史数据及预测表!F199/历史数据及预测表!F198 -> #DIV/0! | G45: =历史数据及预测表!G199/历史数据及预测表!G198 -> #DIV/0! | H45: =历史数据及预测表!H199/历史数据及预测表!H198 -> #DIV/0! | I45: =IF(ISERR(AVERAGE($F$45:$H$45)),0,AVERAGE($F$45:$H$45)) -> 0 | J45: =IF(ISERR(AVERAGE($G$45:$I$45)),0,AVERAGE($G$45:$I$45)) -> 0 | K45: =IF(ISERR(AVERAGE($H$45:$J$45)),0,AVERAGE($H$45:$J$45)) -> 0 | L45: =IF(ISERR(AVERAGE($I$45:$K$45)),0,AVERAGE($I$45:$K$45)) -> 0 | M45: =IF(ISERR(AVERAGE($J$45:$L$45)),0,AVERAGE($J$45:$L$45)) -> 0 | N45: =IF(ISERR(AVERAGE($K$45:$M$45)),0,AVERAGE($K$45:$M$45)) -> 0 | O45: =IF(ISERR(AVERAGE($L$45:$N$45)),0,AVERAGE($L$45:$N$45)) -> 0 | P45: =IF(ISERR(AVERAGE($M$45:$O$45)),0,AVERAGE($M$45:$O$45)) -> 0 | Q45: =IF(ISERR(AVERAGE($N$45:$P$45)),0,AVERAGE($N$45:$P$45)) -> 0 | R45: =IF(ISERR(AVERAGE($O$45:$Q$45)),0,AVERAGE($O$45:$Q$45)) -> 0 | S45: =IF(ISERR(AVERAGE($O$45:$Q$45)),0,AVERAGE($O$45:$Q$45)) -> 0 | T45: =IF(ISERR(AVERAGE($O$45:$Q$45)),0,AVERAGE($O$45:$Q$45)) -> 0
B46: 划分为持有待售的资产本期增减 | C46: 默认值0 | E46: =历史数据及预测表!E17-历史数据及预测表!D17 -> 0 | F46: =历史数据及预测表!F17-历史数据及预测表!E17 -> 0 | G46: =历史数据及预测表!G17-历史数据及预测表!F17 -> 0 | H46: =历史数据及预测表!H17-历史数据及预测表!G17 -> 0 | I46: 0 | J46: 0 | K46: 0 | L46: 0 | M46: 0 | N46: 0 | O46: 0 | P46: 0 | Q46: 0 | R46: 0 | S46: 0 | T46: 0
B47: 一年内到期的非流动资产本期增减 | C47: 默认值0 | E47: =历史数据及预测表!E18-历史数据及预测表!D18 -> 0 | F47: =历史数据及预测表!F18-历史数据及预测表!E18 -> 0 | G47: =历史数据及预测表!G18-历史数据及预测表!F18 -> 43.804255 | H47: =历史数据及预测表!H18-历史数据及预测表!G18 -> -43.804255 | I47: 0 | J47: 0 | K47: 0 | L47: 0 | M47: 0 | N47: 0 | O47: 0 | P47: 0 | Q47: 0 | R47: 0 | S47: 0 | T47: 0
B48: 待摊费用/营业收入 | C48: 前三年平均数据 | D48: =历史数据及预测表!D19/历史数据及预测表!D107 -> 0 | E48: =历史数据及预测表!E19/历史数据及预测表!E107 -> 0 | F48: =历史数据及预测表!F19/历史数据及预测表!F107 -> 0 | G48: =历史数据及预测表!G19/历史数据及预测表!G107 -> 0 | H48: =历史数据及预测表!H19/历史数据及预测表!H107 -> 0 | I48: =IF(ISERR(AVERAGE($F$48:$H$48)),0,AVERAGE($F$48:$H$48)) -> 0 | J48: =IF(ISERR(AVERAGE($G$48:$I$48)),0,AVERAGE($G$48:$I$48)) -> 0 | K48: =IF(ISERR(AVERAGE($H$48:$J$48)),0,AVERAGE($H$48:$J$48)) -> 0 | L48: =IF(ISERR(AVERAGE($I$48:$K$48)),0,AVERAGE($I$48:$K$48)) -> 0 | M48: =IF(ISERR(AVERAGE($J$48:$L$48)),0,AVERAGE($J$48:$L$48)) -> 0 | N48: =IF(ISERR(AVERAGE($K$48:$M$48)),0,AVERAGE($K$48:$M$48)) -> 0 | O48: =IF(ISERR(AVERAGE($L$48:$N$48)),0,AVERAGE($L$48:$N$48)) -> 0 | P48: =IF(ISERR(AVERAGE($M$48:$O$48)),0,AVERAGE($M$48:$O$48)) -> 0 | Q48: =IF(ISERR(AVERAGE($N$48:$P$48)),0,AVERAGE($N$48:$P$48)) -> 0 | R48: =IF(ISERR(AVERAGE($O$48:$Q$48)),0,AVERAGE($O$48:$Q$48)) -> 0 | S48: =IF(ISERR(AVERAGE($O$48:$Q$48)),0,AVERAGE($O$48:$Q$48)) -> 0 | T48: =IF(ISERR(AVERAGE($O$48:$Q$48)),0,AVERAGE($O$48:$Q$48)) -> 0
B49: 其他流动资产本期增减 | C49: 默认值0 | E49: =历史数据及预测表!E20-历史数据及预测表!D20 -> 17.611917 | F49: =历史数据及预测表!F20-历史数据及预测表!E20 -> 33.355022 | G49: =历史数据及预测表!G20-历史数据及预测表!F20 -> -4.0241835 | H49: =历史数据及预测表!H20-历史数据及预测表!G20 -> 4.6942218 | I49: 0 | J49: 0 | K49: 0 | L49: 0 | M49: 0 | N49: 0 | O49: 0 | P49: 0 | Q49: 0 | R49: 0 | S49: 0 | T49: 0
B50: 其他金融类流动资产本期增减 | C50: 默认值0 | E50: =历史数据及预测表!E21-历史数据及预测表!D21 -> 0 | F50: =历史数据及预测表!F21-历史数据及预测表!E21 -> 0 | G50: =历史数据及预测表!G21-历史数据及预测表!F21 -> 0 | H50: =历史数据及预测表!H21-历史数据及预测表!G21 -> 0 | I50: 0 | J50: 0 | K50: 0 | L50: 0 | M50: 0 | N50: 0 | O50: 0 | P50: 0 | Q50: 0 | R50: 0 | S50: 0 | T50: 0
B51: 递延所得税资产本期增减 | C51: 默认值0 | E51: =历史数据及预测表!E43-历史数据及预测表!D43 -> 28.879835 | F51: =历史数据及预测表!F43-历史数据及预测表!E43 -> 15.615001 | G51: =历史数据及预测表!G43-历史数据及预测表!F43 -> -5.7861321 | H51: =历史数据及预测表!H43-历史数据及预测表!G43 -> 3.4445548 | I51: 0 | J51: 0 | K51: 0 | L51: 0 | M51: 0 | N51: 0 | O51: 0 | P51: 0 | Q51: 0 | R51: 0 | S51: 0 | T51: 0
B52: 其他非流动资产本期增减 | C52: 默认值0 | E52: =历史数据及预测表!E44-历史数据及预测表!D44 -> 415.72641 | F52: =历史数据及预测表!F44-历史数据及预测表!E44 -> -320.6042 | G52: =历史数据及预测表!G44-历史数据及预测表!F44 -> -99.233813 | H52: =历史数据及预测表!H44-历史数据及预测表!G44 -> 5.7443914 | I52: 0 | J52: 0 | K52: 0 | L52: 0 | M52: 0 | N52: 0 | O52: 0 | P52: 0 | Q52: 0 | R52: 0 | S52: 0 | T52: 0
B53: 其他金融类非流动资产本期增减 | C53: 默认值0 | E53: =历史数据及预测表!E45-历史数据及预测表!D45 -> 0 | F53: =历史数据及预测表!F45-历史数据及预测表!E45 -> 0 | G53: =历史数据及预测表!G45-历史数据及预测表!F45 -> 0 | H53: =历史数据及预测表!H45-历史数据及预测表!G45 -> 0 | I53: 0 | J53: 0 | K53: 0 | L53: 0 | M53: 0 | N53: 0 | O53: 0 | P53: 0 | Q53: 0 | R53: 0 | S53: 0 | T53: 0
B55: 交易性金融负债本期增减 | C55: 默认值0 | E55: =历史数据及预测表!E52-历史数据及预测表!D52 -> 0 | F55: =历史数据及预测表!F52-历史数据及预测表!E52 -> 0 | G55: =历史数据及预测表!G52-历史数据及预测表!F52 -> 0 | H55: =历史数据及预测表!H52-历史数据及预测表!G52 -> 0 | I55: 0 | J55: 0 | K55: 0 | L55: 0 | M55: 0 | N55: 0 | O55: 0 | P55: 0 | Q55: 0 | R55: 0 | S55: 0 | T55: 0
B56: 衍生金融负债 | C56: 前三年平均数据 | D56: =历史数据及预测表!D53 -> 0 | E56: =历史数据及预测表!E53 -> 0 | F56: =历史数据及预测表!F53 -> 0 | G56: =历史数据及预测表!G53 -> 0 | H56: =历史数据及预测表!H53 -> 0 | I56: =IF(ISERR(AVERAGE($F$56:$H$56)),0,AVERAGE($F$56:$H$56)) -> 0 | J56: =IF(ISERR(AVERAGE($G$56:$I$56)),0,AVERAGE($G$56:$I$56)) -> 0 | K56: =IF(ISERR(AVERAGE($H$56:$J$56)),0,AVERAGE($H$56:$J$56)) -> 0 | L56: =IF(ISERR(AVERAGE($I$56:$K$56)),0,AVERAGE($I$56:$K$56)) -> 0 | M56: =IF(ISERR(AVERAGE($J$56:$L$56)),0,AVERAGE($J$56:$L$56)) -> 0 | N56: =IF(ISERR(AVERAGE($K$56:$M$56)),0,AVERAGE($K$56:$M$56)) -> 0 | O56: =IF(ISERR(AVERAGE($L$56:$N$56)),0,AVERAGE($L$56:$N$56)) -> 0 | P56: =IF(ISERR(AVERAGE($M$56:$O$56)),0,AVERAGE($M$56:$O$56)) -> 0 | Q56: =IF(ISERR(AVERAGE($N$56:$P$56)),0,AVERAGE($N$56:$P$56)) -> 0 | R56: =IF(ISERR(AVERAGE($O$56:$Q$56)),0,AVERAGE($O$56:$Q$56)) -> 0 | S56: =IF(ISERR(AVERAGE($O$56:$Q$56)),0,AVERAGE($O$56:$Q$56)) -> 0 | T56: =IF(ISERR(AVERAGE($O$56:$Q$56)),0,AVERAGE($O$56:$Q$56)) -> 0
B57: 应付账款/营业成本 | C57: 前三年平均数据 | D57: =历史数据及预测表!D54/历史数据及预测表!D110 -> 0.19810497 | E57: =历史数据及预测表!E54/历史数据及预测表!E110 -> 0.19842864 | F57: =历史数据及预测表!F54/历史数据及预测表!F110 -> 0.14826926 | G57: =历史数据及预测表!G54/历史数据及预测表!G110 -> 0.16273369 | H57: =历史数据及预测表!H54/历史数据及预测表!H110 -> 0.19169279 | I57: =IF(ISERR(AVERAGE($F$57:$H$57)),0,AVERAGE($F$57:$H$57)) -> 0.16756525 | J57: =IF(ISERR(AVERAGE($G$57:$I$57)),0,AVERAGE($G$57:$I$57)) -> 0.17399724 | K57: =IF(ISERR(AVERAGE($H$57:$J$57)),0,AVERAGE($H$57:$J$57)) -> 0.17775176 | L57: =IF(ISERR(AVERAGE($I$57:$K$57)),0,AVERAGE($I$57:$K$57)) -> 0.17310475 | M57: =IF(ISERR(AVERAGE($J$57:$L$57)),0,AVERAGE($J$57:$L$57)) -> 0.17495125 | N57: =IF(ISERR(AVERAGE($K$57:$M$57)),0,AVERAGE($K$57:$M$57)) -> 0.17526925 | O57: =IF(ISERR(AVERAGE($L$57:$N$57)),0,AVERAGE($L$57:$N$57)) -> 0.17444175 | P57: =IF(ISERR(AVERAGE($M$57:$O$57)),0,AVERAGE($M$57:$O$57)) -> 0.17488742 | Q57: =IF(ISERR(AVERAGE($N$57:$P$57)),0,AVERAGE($N$57:$P$57)) -> 0.17486614 | R57: =IF(ISERR(AVERAGE($O$57:$Q$57)),0,AVERAGE($O$57:$Q$57)) -> 0.17473177 | S57: =IF(ISERR(AVERAGE($O$57:$Q$57)),0,AVERAGE($O$57:$Q$57)) -> 0.17473177 | T57: =IF(ISERR(AVERAGE($O$57:$Q$57)),0,AVERAGE($O$57:$Q$57)) -> 0.17473177
B58: 应付票据/营业成本 | C58: 默认值0 | D58: =历史数据及预测表!D55/历史数据及预测表!D110 -> 0 | E58: =历史数据及预测表!E55/历史数据及预测表!E110 -> 0 | F58: =历史数据及预测表!F55/历史数据及预测表!F110 -> 0 | G58: =历史数据及预测表!G55/历史数据及预测表!G110 -> 0 | H58: =历史数据及预测表!H55/历史数据及预测表!H110 -> 0 | I58: 0 | J58: 0 | K58: 0 | L58: 0 | M58: 0 | N58: 0 | O58: 0 | P58: 0 | Q58: 0 | R58: 0 | S58: 0 | T58: 0
B59: 预收款项/营业收入 | C59: 前三年平均数据 | D59: =历史数据及预测表!D56/历史数据及预测表!D107 -> 0 | E59: =历史数据及预测表!E56/历史数据及预测表!E107 -> 0 | F59: =历史数据及预测表!F56/历史数据及预测表!F107 -> 0 | G59: =历史数据及预测表!G56/历史数据及预测表!G107 -> 0 | H59: =历史数据及预测表!H56/历史数据及预测表!H107 -> 0 | I59: =IF(ISERR(AVERAGE($F$59:$H$59)),0,AVERAGE($F$59:$H$59)) -> 0 | J59: =IF(ISERR(AVERAGE($G$59:$I$59)),0,AVERAGE($G$59:$I$59)) -> 0 | K59: =IF(ISERR(AVERAGE($H$59:$J$59)),0,AVERAGE($H$59:$J$59)) -> 0 | L59: =IF(ISERR(AVERAGE($I$59:$K$59)),0,AVERAGE($I$59:$K$59)) -> 0 | M59: =IF(ISERR(AVERAGE($J$59:$L$59)),0,AVERAGE($J$59:$L$59)) -> 0 | N59: =IF(ISERR(AVERAGE($K$59:$M$59)),0,AVERAGE($K$59:$M$59)) -> 0 | O59: =IF(ISERR(AVERAGE($L$59:$N$59)),0,AVERAGE($L$59:$N$59)) -> 0 | P59: =IF(ISERR(AVERAGE($M$59:$O$59)),0,AVERAGE($M$59:$O$59)) -> 0 | Q59: =IF(ISERR(AVERAGE($N$59:$P$59)),0,AVERAGE($N$59:$P$59)) -> 0 | R59: =IF(ISERR(AVERAGE($O$59:$Q$59)),0,AVERAGE($O$59:$Q$59)) -> 0 | S59: =IF(ISERR(AVERAGE($O$59:$Q$59)),0,AVERAGE($O$59:$Q$59)) -> 0 | T59: =IF(ISERR(AVERAGE($O$59:$Q$59)),0,AVERAGE($O$59:$Q$59)) -> 0
B60: 合同负债/营业收入 | C60: 前三年平均数据 | D60: =历史数据及预测表!D57/历史数据及预测表!D107 -> 0.0068454314 | E60: =历史数据及预测表!E57/历史数据及预测表!E107 -> 0.023532761 | F60: =历史数据及预测表!F57/历史数据及预测表!F107 -> 0.016526275 | G60: =历史数据及预测表!G57/历史数据及预测表!G107 -> 0.015600493 | H60: =历史数据及预测表!H57/历史数据及预测表!H107 -> 0.023120334 | I60: =IF(ISERR(AVERAGE($F$60:$H$60)),0,AVERAGE($F$60:$H$60)) -> 0.018415701 | J60: =IF(ISERR(AVERAGE($G$60:$I$60)),0,AVERAGE($G$60:$I$60)) -> 0.019045509 | K60: =IF(ISERR(AVERAGE($H$60:$J$60)),0,AVERAGE($H$60:$J$60)) -> 0.020193848 | L60: =IF(ISERR(AVERAGE($I$60:$K$60)),0,AVERAGE($I$60:$K$60)) -> 0.019218353 | M60: =IF(ISERR(AVERAGE($J$60:$L$60)),0,AVERAGE($J$60:$L$60)) -> 0.019485904 | N60: =IF(ISERR(AVERAGE($K$60:$M$60)),0,AVERAGE($K$60:$M$60)) -> 0.019632702 | O60: =IF(ISERR(AVERAGE($L$60:$N$60)),0,AVERAGE($L$60:$N$60)) -> 0.019445653 | P60: =IF(ISERR(AVERAGE($M$60:$O$60)),0,AVERAGE($M$60:$O$60)) -> 0.019521419 | Q60: =IF(ISERR(AVERAGE($N$60:$P$60)),0,AVERAGE($N$60:$P$60)) -> 0.019533258 | R60: =IF(ISERR(AVERAGE($O$60:$Q$60)),0,AVERAGE($O$60:$Q$60)) -> 0.01950011 | S60: =IF(ISERR(AVERAGE($O$60:$Q$60)),0,AVERAGE($O$60:$Q$60)) -> 0.01950011 | T60: =IF(ISERR(AVERAGE($O$60:$Q$60)),0,AVERAGE($O$60:$Q$60)) -> 0.01950011
B61: 应付职工薪酬/管理费用 | C61: 保持上一年数据 | D61: =历史数据及预测表!D58/历史数据及预测表!D113 -> 0.70759421 | E61: =历史数据及预测表!E58/历史数据及预测表!E113 -> 1.1452835 | F61: =历史数据及预测表!F58/历史数据及预测表!F113 -> 1.2340647 | G61: =历史数据及预测表!G58/历史数据及预测表!G113 -> 0.89055389 | H61: =历史数据及预测表!H58/历史数据及预测表!H113 -> 0.77673884 | I61: =$H$61 -> 0.77673884 | J61: =$I$61 -> 0.77673884 | K61: =$J$61 -> 0.77673884 | L61: =$K$61 -> 0.77673884 | M61: =$L$61 -> 0.77673884 | N61: =$M$61 -> 0.77673884 | O61: =$N$61 -> 0.77673884 | P61: =$O$61 -> 0.77673884 | Q61: =$P$61 -> 0.77673884 | R61: =$Q$61 -> 0.77673884 | S61: =$R$61 -> 0.77673884 | T61: =$S$61 -> 0.77673884
B62: 应交税费 | C62: 前三年平均数据 | D62: =历史数据及预测表!D59 -> 28.257338 | E62: =历史数据及预测表!E59 -> 11.014879 | F62: =历史数据及预测表!F59 -> 24.874944 | G62: =历史数据及预测表!G59 -> 12.895499 | H62: =历史数据及预测表!H59 -> 34.237409 | I62: =IF(ISERR(AVERAGE($F$62:$H$62)),0,AVERAGE($F$62:$H$62)) -> 24.002617 | J62: =IF(ISERR(AVERAGE($G$62:$I$62)),0,AVERAGE($G$62:$I$62)) -> 23.711842 | K62: =IF(ISERR(AVERAGE($H$62:$J$62)),0,AVERAGE($H$62:$J$62)) -> 27.317289 | L62: =IF(ISERR(AVERAGE($I$62:$K$62)),0,AVERAGE($I$62:$K$62)) -> 25.010583 | M62: =IF(ISERR(AVERAGE($J$62:$L$62)),0,AVERAGE($J$62:$L$62)) -> 25.346571 | N62: =IF(ISERR(AVERAGE($K$62:$M$62)),0,AVERAGE($K$62:$M$62)) -> 25.891481 | O62: =IF(ISERR(AVERAGE($L$62:$N$62)),0,AVERAGE($L$62:$N$62)) -> 25.416212 | P62: =IF(ISERR(AVERAGE($M$62:$O$62)),0,AVERAGE($M$62:$O$62)) -> 25.551421 | Q62: =IF(ISERR(AVERAGE($N$62:$P$62)),0,AVERAGE($N$62:$P$62)) -> 25.619705 | R62: =IF(ISERR(AVERAGE($O$62:$Q$62)),0,AVERAGE($O$62:$Q$62)) -> 25.529112 | S62: =IF(ISERR(AVERAGE($O$62:$Q$62)),0,AVERAGE($O$62:$Q$62)) -> 25.529112 | T62: =IF(ISERR(AVERAGE($O$62:$Q$62)),0,AVERAGE($O$62:$Q$62)) -> 25.529112
B63: 其他应付款本期增减 | C63: 默认值0 | E63: =历史数据及预测表!E60-历史数据及预测表!D60 -> 15.566055 | F63: =历史数据及预测表!F60-历史数据及预测表!E60 -> -24.853413 | G63: =历史数据及预测表!G60-历史数据及预测表!F60 -> -5.7334307 | H63: =历史数据及预测表!H60-历史数据及预测表!G60 -> 11.194981 | I63: 0 | J63: 0 | K63: 0 | L63: 0 | M63: 0 | N63: 0 | O63: 0 | P63: 0 | Q63: 0 | R63: 0 | S63: 0 | T63: 0
B64: 划分为持有待售的负债本期增减 | C64: 默认值0 | E64: =历史数据及预测表!E61-历史数据及预测表!D61 -> 0 | F64: =历史数据及预测表!F61-历史数据及预测表!E61 -> 0 | G64: =历史数据及预测表!G61-历史数据及预测表!F61 -> 0 | H64: =历史数据及预测表!H61-历史数据及预测表!G61 -> 0 | I64: 0 | J64: 0 | K64: 0 | L64: 0 | M64: 0 | N64: 0 | O64: 0 | P64: 0 | Q64: 0 | R64: 0 | S64: 0 | T64: 0
B65: 一年内到期的非流动负债本期增减 | C65: 默认值0 | E65: =历史数据及预测表!E62-历史数据及预测表!D62 -> -0.92307652 | F65: =历史数据及预测表!F62-历史数据及预测表!E62 -> 4.1715512 | G65: =历史数据及预测表!G62-历史数据及预测表!F62 -> -2.5000551 | H65: =历史数据及预测表!H62-历史数据及预测表!G62 -> -1.6475467 | I65: 0 | J65: 0 | K65: 0 | L65: 0 | M65: 0 | N65: 0 | O65: 0 | P65: 0 | Q65: 0 | R65: 0 | S65: 0 | T65: 0
B66: 预提费用/销售费用和管理费用 | C66: 前三年平均数据 | D66: =历史数据及预测表!D63/(历史数据及预测表!D112+历史数据及预测表!D113) -> 0 | E66: =历史数据及预测表!E63/(历史数据及预测表!E112+历史数据及预测表!E113) -> 0 | F66: =历史数据及预测表!F63/(历史数据及预测表!F112+历史数据及预测表!F113) -> 0 | G66: =历史数据及预测表!G63/(历史数据及预测表!G112+历史数据及预测表!G113) -> 0 | H66: =历史数据及预测表!H63/(历史数据及预测表!H112+历史数据及预测表!H113) -> 0 | I66: =IF(ISERR(AVERAGE($F$66:$H$66)),0,AVERAGE($F$66:$H$66)) -> 0 | J66: =IF(ISERR(AVERAGE($G$66:$I$66)),0,AVERAGE($G$66:$I$66)) -> 0 | K66: =IF(ISERR(AVERAGE($H$66:$J$66)),0,AVERAGE($H$66:$J$66)) -> 0 | L66: =IF(ISERR(AVERAGE($I$66:$K$66)),0,AVERAGE($I$66:$K$66)) -> 0 | M66: =IF(ISERR(AVERAGE($J$66:$L$66)),0,AVERAGE($J$66:$L$66)) -> 0 | N66: =IF(ISERR(AVERAGE($K$66:$M$66)),0,AVERAGE($K$66:$M$66)) -> 0 | O66: =IF(ISERR(AVERAGE($L$66:$N$66)),0,AVERAGE($L$66:$N$66)) -> 0 | P66: =IF(ISERR(AVERAGE($M$66:$O$66)),0,AVERAGE($M$66:$O$66)) -> 0 | Q66: =IF(ISERR(AVERAGE($N$66:$P$66)),0,AVERAGE($N$66:$P$66)) -> 0 | R66: =IF(ISERR(AVERAGE($O$66:$Q$66)),0,AVERAGE($O$66:$Q$66)) -> 0 | S66: =IF(ISERR(AVERAGE($O$66:$Q$66)),0,AVERAGE($O$66:$Q$66)) -> 0 | T66: =IF(ISERR(AVERAGE($O$66:$Q$66)),0,AVERAGE($O$66:$Q$66)) -> 0
B67: 递延收益-流动负债本期增减 | C67: 默认值0 | E67: =历史数据及预测表!E64-历史数据及预测表!D64 -> 0 | F67: =历史数据及预测表!F64-历史数据及预测表!E64 -> 0 | G67: =历史数据及预测表!G64-历史数据及预测表!F64 -> 0 | H67: =历史数据及预测表!H64-历史数据及预测表!G64 -> 0 | I67: 0 | J67: 0 | K67: 0 | L67: 0 | M67: 0 | N67: 0 | O67: 0 | P67: 0 | Q67: 0 | R67: 0 | S67: 0 | T67: 0
B68: 应付短期债券本期增减 | C68: 默认值0 | E68: =历史数据及预测表!E65-历史数据及预测表!D65 -> 0 | F68: =历史数据及预测表!F65-历史数据及预测表!E65 -> 0 | G68: =历史数据及预测表!G65-历史数据及预测表!F65 -> 0 | H68: =历史数据及预测表!H65-历史数据及预测表!G65 -> 0 | I68: 0 | J68: 0 | K68: 0 | L68: 0 | M68: 0 | N68: 0 | O68: 0 | P68: 0 | Q68: 0 | R68: 0 | S68: 0 | T68: 0
B69: 其他流动负债本期增减 | C69: 默认值0 | E69: =历史数据及预测表!E66-历史数据及预测表!D66 -> -1.1246728 | F69: =历史数据及预测表!F66-历史数据及预测表!E66 -> -0.05297945 | G69: =历史数据及预测表!G66-历史数据及预测表!F66 -> 0.80248378 | H69: =历史数据及预测表!H66-历史数据及预测表!G66 -> 5.1353414 | I69: 0 | J69: 0 | K69: 0 | L69: 0 | M69: 0 | N69: 0 | O69: 0 | P69: 0 | Q69: 0 | R69: 0 | S69: 0 | T69: 0
B70: 其他金融类流动负债本期增减 | C70: 默认值0 | E70: =历史数据及预测表!E67-历史数据及预测表!D67 -> 0 | F70: =历史数据及预测表!F67-历史数据及预测表!E67 -> 0 | G70: =历史数据及预测表!G67-历史数据及预测表!F67 -> 0 | H70: =历史数据及预测表!H67-历史数据及预测表!G67 -> 0 | I70: 0 | J70: 0 | K70: 0 | L70: 0 | M70: 0 | N70: 0 | O70: 0 | P70: 0 | Q70: 0 | R70: 0 | S70: 0 | T70: 0
B71: 预计负债本期增减 | C71: 默认值0 | E71: =历史数据及预测表!E76-历史数据及预测表!D76 -> 1.8260117 | F71: =历史数据及预测表!F76-历史数据及预测表!E76 -> -10.727276 | G71: =历史数据及预测表!G76-历史数据及预测表!F76 -> 0.65919618 | H71: =历史数据及预测表!H76-历史数据及预测表!G76 -> -2.2708211 | I71: 0 | J71: 0 | K71: 0 | L71: 0 | M71: 0 | N71: 0 | O71: 0 | P71: 0 | Q71: 0 | R71: 0 | S71: 0 | T71: 0
B72: 递延所得税负债本期增减 | C72: 默认值0 | E72: =历史数据及预测表!E77-历史数据及预测表!D77 -> -21.954133 | F72: =历史数据及预测表!F77-历史数据及预测表!E77 -> 10.033107 | G72: =历史数据及预测表!G77-历史数据及预测表!F77 -> -10.326129 | H72: =历史数据及预测表!H77-历史数据及预测表!G77 -> -6.2557027 | I72: 0 | J72: 0 | K72: 0 | L72: 0 | M72: 0 | N72: 0 | O72: 0 | P72: 0 | Q72: 0 | R72: 0 | S72: 0 | T72: 0
B73: 递延收益-非流动负债本期增减 | C73: 默认值0 | E73: =历史数据及预测表!E78-历史数据及预测表!D78 -> 4.6818901 | F73: =历史数据及预测表!F78-历史数据及预测表!E78 -> 3.3202136 | G73: =历史数据及预测表!G78-历史数据及预测表!F78 -> -6.2412037 | H73: =历史数据及预测表!H78-历史数据及预测表!G78 -> -8.8040953 | I73: 0 | J73: 0 | K73: 0 | L73: 0 | M73: 0 | N73: 0 | O73: 0 | P73: 0 | Q73: 0 | R73: 0 | S73: 0 | T73: 0
B74: 其他非流动负债本期增减 | C74: 默认值0 | E74: =历史数据及预测表!E79-历史数据及预测表!D79 -> 0 | F74: =历史数据及预测表!F79-历史数据及预测表!E79 -> 0 | G74: =历史数据及预测表!G79-历史数据及预测表!F79 -> 0 | H74: =历史数据及预测表!H79-历史数据及预测表!G79 -> 0 | I74: 0 | J74: 0 | K74: 0 | L74: 0 | M74: 0 | N74: 0 | O74: 0 | P74: 0 | Q74: 0 | R74: 0 | S74: 0 | T74: 0
A76: 资本性投资假设
B77: 可供出售金融资产本期增减 | C77: 默认值0 | E77: =历史数据及预测表!E25-历史数据及预测表!D25 -> 0 | F77: =历史数据及预测表!F25-历史数据及预测表!E25 -> 0 | G77: =历史数据及预测表!G25-历史数据及预测表!F25 -> 0 | H77: =历史数据及预测表!H25-历史数据及预测表!G25 -> 0 | I77: 0 | J77: 0 | K77: 0 | L77: 0 | M77: 0 | N77: 0 | O77: 0 | P77: 0 | Q77: 0 | R77: 0 | S77: 0 | T77: 0
B78: 持有至到期投资本期增减 | C78: 默认值0 | E78: =历史数据及预测表!E28-历史数据及预测表!D28 -> 0 | F78: =历史数据及预测表!F28-历史数据及预测表!E28 -> 0 | G78: =历史数据及预测表!G28-历史数据及预测表!F28 -> 0 | H78: =历史数据及预测表!H28-历史数据及预测表!G28 -> 0 | I78: 0 | J78: 0 | K78: 0 | L78: 0 | M78: 0 | N78: 0 | O78: 0 | P78: 0 | Q78: 0 | R78: 0 | S78: 0 | T78: 0
B79: 债权投资本期增减 | C79: 前三年平均数据 | E79: =历史数据及预测表!E26-历史数据及预测表!D26 -> 0 | F79: =历史数据及预测表!F26-历史数据及预测表!E26 -> 0 | G79: =历史数据及预测表!G26-历史数据及预测表!F26 -> 0 | H79: =历史数据及预测表!H26-历史数据及预测表!G26 -> 0 | I79: =IF(ISERR(AVERAGE($F$79:$H$79)),0,AVERAGE($F$79:$H$79)) -> 0 | J79: =IF(ISERR(AVERAGE($G$79:$I$79)),0,AVERAGE($G$79:$I$79)) -> 0 | K79: =IF(ISERR(AVERAGE($H$79:$J$79)),0,AVERAGE($H$79:$J$79)) -> 0 | L79: =IF(ISERR(AVERAGE($I$79:$K$79)),0,AVERAGE($I$79:$K$79)) -> 0 | M79: =IF(ISERR(AVERAGE($J$79:$L$79)),0,AVERAGE($J$79:$L$79)) -> 0 | N79: =IF(ISERR(AVERAGE($K$79:$M$79)),0,AVERAGE($K$79:$M$79)) -> 0 | O79: =IF(ISERR(AVERAGE($L$79:$N$79)),0,AVERAGE($L$79:$N$79)) -> 0 | P79: =IF(ISERR(AVERAGE($M$79:$O$79)),0,AVERAGE($M$79:$O$79)) -> 0 | Q79: =IF(ISERR(AVERAGE($N$79:$P$79)),0,AVERAGE($N$79:$P$79)) -> 0 | R79: =IF(ISERR(AVERAGE($O$79:$Q$79)),0,AVERAGE($O$79:$Q$79)) -> 0 | S79: =IF(ISERR(AVERAGE($O$79:$Q$79)),0,AVERAGE($O$79:$Q$79)) -> 0 | T79: =IF(ISERR(AVERAGE($O$79:$Q$79)),0,AVERAGE($O$79:$Q$79)) -> 0
B80: 其他债权投资本期增减 | C80: 前三年平均数据 | E80: =历史数据及预测表!E27-历史数据及预测表!D27 -> 0 | F80: =历史数据及预测表!F27-历史数据及预测表!E27 -> 0 | G80: =历史数据及预测表!G27-历史数据及预测表!F27 -> 0 | H80: =历史数据及预测表!H27-历史数据及预测表!G27 -> 0 | I80: =IF(ISERR(AVERAGE($F$80:$H$80)),0,AVERAGE($F$80:$H$80)) -> 0 | J80: =IF(ISERR(AVERAGE($G$80:$I$80)),0,AVERAGE($G$80:$I$80)) -> 0 | K80: =IF(ISERR(AVERAGE($H$80:$J$80)),0,AVERAGE($H$80:$J$80)) -> 0 | L80: =IF(ISERR(AVERAGE($I$80:$K$80)),0,AVERAGE($I$80:$K$80)) -> 0 | M80: =IF(ISERR(AVERAGE($J$80:$L$80)),0,AVERAGE($J$80:$L$80)) -> 0 | N80: =IF(ISERR(AVERAGE($K$80:$M$80)),0,AVERAGE($K$80:$M$80)) -> 0 | O80: =IF(ISERR(AVERAGE($L$80:$N$80)),0,AVERAGE($L$80:$N$80)) -> 0 | P80: =IF(ISERR(AVERAGE($M$80:$O$80)),0,AVERAGE($M$80:$O$80)) -> 0 | Q80: =IF(ISERR(AVERAGE($N$80:$P$80)),0,AVERAGE($N$80:$P$80)) -> 0 | R80: =IF(ISERR(AVERAGE($O$80:$Q$80)),0,AVERAGE($O$80:$Q$80)) -> 0 | S80: =IF(ISERR(AVERAGE($O$80:$Q$80)),0,AVERAGE($O$80:$Q$80)) -> 0 | T80: =IF(ISERR(AVERAGE($O$80:$Q$80)),0,AVERAGE($O$80:$Q$80)) -> 0
B81: 长期应收款本期增减 | C81: 默认值0 | E81: =历史数据及预测表!E29-历史数据及预测表!D29 -> -129.15354 | F81: =历史数据及预测表!F29-历史数据及预测表!E29 -> -171.09191 | G81: =历史数据及预测表!G29-历史数据及预测表!F29 -> -222.03931 | H81: =历史数据及预测表!H29-历史数据及预测表!G29 -> 0 | I81: 0 | J81: 0 | K81: 0 | L81: 0 | M81: 0 | N81: 0 | O81: 0 | P81: 0 | Q81: 0 | R81: 0 | S81: 0 | T81: 0
B82: 长期股权投资原值本期增减 | C82: 默认值0 | E82: =历史数据及预测表!E244-历史数据及预测表!D244 -> -0.05348047 | F82: =历史数据及预测表!F244-历史数据及预测表!E244 -> -0.90875711 | G82: =历史数据及预测表!G244-历史数据及预测表!F244 -> -0.35519602 | H82: =历史数据及预测表!H244-历史数据及预测表!G244 -> 0.25755493 | I82: 0 | J82: 0 | K82: 0 | L82: 0 | M82: 0 | N82: 0 | O82: 0 | P82: 0 | Q82: 0 | R82: 0 | S82: 0 | T82: 0
B83: 其他权益工具投资本期增减 | C83: 前三年平均数据 | E83: =历史数据及预测表!E31-历史数据及预测表!D31 -> 172.12661 | F83: =历史数据及预测表!F31-历史数据及预测表!E31 -> 102.19616 | G83: =历史数据及预测表!G31-历史数据及预测表!F31 -> 119.71016 | H83: =历史数据及预测表!H31-历史数据及预测表!G31 -> 100.64434 | I83: =IF(ISERR(AVERAGE($F$83:$H$83)),0,AVERAGE($F$83:$H$83)) -> 107.51688 | J83: =IF(ISERR(AVERAGE($G$83:$I$83)),0,AVERAGE($G$83:$I$83)) -> 109.29046 | K83: =IF(ISERR(AVERAGE($H$83:$J$83)),0,AVERAGE($H$83:$J$83)) -> 105.81723 | L83: =IF(ISERR(AVERAGE($I$83:$K$83)),0,AVERAGE($I$83:$K$83)) -> 107.54152 | M83: =IF(ISERR(AVERAGE($J$83:$L$83)),0,AVERAGE($J$83:$L$83)) -> 107.54974 | N83: =IF(ISERR(AVERAGE($K$83:$M$83)),0,AVERAGE($K$83:$M$83)) -> 106.9695 | O83: =IF(ISERR(AVERAGE($L$83:$N$83)),0,AVERAGE($L$83:$N$83)) -> 107.35358 | P83: =IF(ISERR(AVERAGE($M$83:$O$83)),0,AVERAGE($M$83:$O$83)) -> 107.29094 | Q83: =IF(ISERR(AVERAGE($N$83:$P$83)),0,AVERAGE($N$83:$P$83)) -> 107.20467 | R83: =IF(ISERR(AVERAGE($O$83:$Q$83)),0,AVERAGE($O$83:$Q$83)) -> 107.28307 | S83: =IF(ISERR(AVERAGE($O$83:$Q$83)),0,AVERAGE($O$83:$Q$83)) -> 107.28307 | T83: =IF(ISERR(AVERAGE($O$83:$Q$83)),0,AVERAGE($O$83:$Q$83)) -> 107.28307
B84: 其他非流动金融资产本期增减 | C84: 前三年平均数据 | E84: =历史数据及预测表!E32-历史数据及预测表!D32 -> 0 | F84: =历史数据及预测表!F32-历史数据及预测表!E32 -> 0 | G84: =历史数据及预测表!G32-历史数据及预测表!F32 -> 0 | H84: =历史数据及预测表!H32-历史数据及预测表!G32 -> 0 | I84: =IF(ISERR(AVERAGE($F$84:$H$84)),0,AVERAGE($F$84:$H$84)) -> 0 | J84: =IF(ISERR(AVERAGE($G$84:$I$84)),0,AVERAGE($G$84:$I$84)) -> 0 | K84: =IF(ISERR(AVERAGE($H$84:$J$84)),0,AVERAGE($H$84:$J$84)) -> 0 | L84: =IF(ISERR(AVERAGE($I$84:$K$84)),0,AVERAGE($I$84:$K$84)) -> 0 | M84: =IF(ISERR(AVERAGE($J$84:$L$84)),0,AVERAGE($J$84:$L$84)) -> 0 | N84: =IF(ISERR(AVERAGE($K$84:$M$84)),0,AVERAGE($K$84:$M$84)) -> 0 | O84: =IF(ISERR(AVERAGE($L$84:$N$84)),0,AVERAGE($L$84:$N$84)) -> 0 | P84: =IF(ISERR(AVERAGE($M$84:$O$84)),0,AVERAGE($M$84:$O$84)) -> 0 | Q84: =IF(ISERR(AVERAGE($N$84:$P$84)),0,AVERAGE($N$84:$P$84)) -> 0 | R84: =IF(ISERR(AVERAGE($O$84:$Q$84)),0,AVERAGE($O$84:$Q$84)) -> 0 | S84: =IF(ISERR(AVERAGE($O$84:$Q$84)),0,AVERAGE($O$84:$Q$84)) -> 0 | T84: =IF(ISERR(AVERAGE($O$84:$Q$84)),0,AVERAGE($O$84:$Q$84)) -> 0
B85: 投资性房地产本期增减 | C85: 默认值0 | E85: =历史数据及预测表!E33-历史数据及预测表!D33 -> -0.7369254 | F85: =历史数据及预测表!F33-历史数据及预测表!E33 -> 50.917382 | G85: =历史数据及预测表!G33-历史数据及预测表!F33 -> 3.90484 | H85: =历史数据及预测表!H33-历史数据及预测表!G33 -> -0.31391244 | I85: 0 | J85: 0 | K85: 0 | L85: 0 | M85: 0 | N85: 0 | O85: 0 | P85: 0 | Q85: 0 | R85: 0 | S85: 0 | T85: 0
B86: 固定资产本期整体增减 | C86: 保持上一年数据 | H86: =历史数据及预测表!H34 -> 462.27066 | I86: 200 | J86: =$I$86 -> 200 | K86: =$J$86 -> 200 | L86: =$K$86 -> 200 | M86: =$L$86 -> 200 | N86: =$M$86 -> 200 | O86: =$N$86 -> 200 | P86: =$O$86 -> 200 | Q86: =$P$86 -> 200 | R86: =$Q$86 -> 200 | S86: =$R$86 -> 200 | T86: =$S$86 -> 200
B87: 固定资产中房屋及建筑物本期增减 | C87: 默认值0 | H87: =历史数据及预测表!H235 -> 0 | I87: 0 | J87: 0 | K87: 0 | L87: 0 | M87: 0 | N87: 0 | O87: 0 | P87: 0 | Q87: 0 | R87: 0 | S87: 0 | T87: 0
B88: 固定资产中机械设备本期增减 | C88: 默认值0 | H88: =历史数据及预测表!H236 -> 0 | I88: 0 | J88: 0 | K88: 0 | L88: 0 | M88: 0 | N88: 0 | O88: 0 | P88: 0 | Q88: 0 | R88: 0 | S88: 0 | T88: 0
B89: 固定资产中运输设备本期增减 | C89: 默认值0 | H89: =历史数据及预测表!H237 -> 0 | I89: 0 | J89: 0 | K89: 0 | L89: 0 | M89: 0 | N89: 0 | O89: 0 | P89: 0 | Q89: 0 | R89: 0 | S89: 0 | T89: 0
B90: 固定资产中其他本期增减 | C90: 默认值0 | H90: =历史数据及预测表!H238 -> 462.27066 | I90: 0 | J90: 0 | K90: 0 | L90: 0 | M90: 0 | N90: 0 | O90: 0 | P90: 0 | Q90: 0 | R90: 0 | S90: 0 | T90: 0
B91: 本期在建工程转入固定资产 | C91: 前三年平均数据 | H91: =历史数据及预测表!H239 -> 0 | I91: =IF(ISERR(AVERAGE($F$91:$H$91)),0,AVERAGE($F$91:$H$91)) -> 0 | J91: =IF(ISERR(AVERAGE($G$91:$I$91)),0,AVERAGE($G$91:$I$91)) -> 0 | K91: =IF(ISERR(AVERAGE($H$91:$J$91)),0,AVERAGE($H$91:$J$91)) -> 0 | L91: =IF(ISERR(AVERAGE($I$91:$K$91)),0,AVERAGE($I$91:$K$91)) -> 0 | M91: =IF(ISERR(AVERAGE($J$91:$L$91)),0,AVERAGE($J$91:$L$91)) -> 0 | N91: =IF(ISERR(AVERAGE($K$91:$M$91)),0,AVERAGE($K$91:$M$91)) -> 0 | O91: =IF(ISERR(AVERAGE($L$91:$N$91)),0,AVERAGE($L$91:$N$91)) -> 0 | P91: =IF(ISERR(AVERAGE($M$91:$O$91)),0,AVERAGE($M$91:$O$91)) -> 0 | Q91: =IF(ISERR(AVERAGE($N$91:$P$91)),0,AVERAGE($N$91:$P$91)) -> 0 | R91: =IF(ISERR(AVERAGE($O$91:$Q$91)),0,AVERAGE($O$91:$Q$91)) -> 0 | S91: =IF(ISERR(AVERAGE($O$91:$Q$91)),0,AVERAGE($O$91:$Q$91)) -> 0 | T91: =IF(ISERR(AVERAGE($O$91:$Q$91)),0,AVERAGE($O$91:$Q$91)) -> 0
B92: 在建工程本期增减 | C92: 默认值0 | E92: =历史数据及预测表!E35-历史数据及预测表!D35 -> 21.884962 | F92: =历史数据及预测表!F35-历史数据及预测表!E35 -> -129.40898 | G92: =历史数据及预测表!G35-历史数据及预测表!F35 -> -2.7405582 | H92: =历史数据及预测表!H35-历史数据及预测表!G35 -> 8.3533448 | I92: 0 | J92: 0 | K92: 0 | L92: 0 | M92: 0 | N92: 0 | O92: 0 | P92: 0 | Q92: 0 | R92: 0 | S92: 0 | T92: 0
B93: 生产性生物资产本期增减 | C93: 默认值0 | H93: =历史数据及预测表!H240 -> 0 | I93: 0 | J93: 0 | K93: 0 | L93: 0 | M93: 0 | N93: 0 | O93: 0 | P93: 0 | Q93: 0 | R93: 0 | S93: 0 | T93: 0
B94: 油气资产本期增减 | C94: 默认值0 | H94: =历史数据及预测表!H241 -> 0 | I94: 0 | J94: 0 | K94: 0 | L94: 0 | M94: 0 | N94: 0 | O94: 0 | P94: 0 | Q94: 0 | R94: 0 | S94: 0 | T94: 0
B95: 使用权资产原值本期增减 | H95: =历史数据及预测表!H39 -> 16.938199
B96: 租赁负债本期增减 | E96: =历史数据及预测表!E73-历史数据及预测表!D73 -> 1.0440532 | F96: =历史数据及预测表!F73-历史数据及预测表!E73 -> 13.186209 | G96: =历史数据及预测表!G73-历史数据及预测表!F73 -> -6.0778811 | H96: =历史数据及预测表!H73-历史数据及预测表!G73 -> -4.2791917
B97: 无形资产原值本期增减 | C97: 默认值0 | E97: =历史数据及预测表!E246-历史数据及预测表!D246 -> -57.727727 | F97: =历史数据及预测表!F246-历史数据及预测表!E246 -> -76.266507 | G97: =历史数据及预测表!G246-历史数据及预测表!F246 -> -90.345774 | H97: =历史数据及预测表!H246-历史数据及预测表!G246 -> -87.07835 | I97: 0 | J97: 0 | K97: 0 | L97: 0 | M97: 0 | N97: 0 | O97: 0 | P97: 0 | Q97: 0 | R97: 0 | S97: 0 | T97: 0
B98: 无形资产本期摊销 | C98: 前三年平均数据 | D98: =历史数据及预测表!D247 -> 0 | E98: =历史数据及预测表!E247 -> 0 | F98: =历史数据及预测表!F247 -> 0 | G98: =历史数据及预测表!G247 -> 0 | H98: =历史数据及预测表!H247 -> 0 | I98: =IF(ISERR(AVERAGE($F$98:$H$98)),0,AVERAGE($F$98:$H$98)) -> 0 | J98: =IF(ISERR(AVERAGE($G$98:$I$98)),0,AVERAGE($G$98:$I$98)) -> 0 | K98: =IF(ISERR(AVERAGE($H$98:$J$98)),0,AVERAGE($H$98:$J$98)) -> 0 | L98: =IF(ISERR(AVERAGE($I$98:$K$98)),0,AVERAGE($I$98:$K$98)) -> 0 | M98: =IF(ISERR(AVERAGE($J$98:$L$98)),0,AVERAGE($J$98:$L$98)) -> 0 | N98: =IF(ISERR(AVERAGE($K$98:$M$98)),0,AVERAGE($K$98:$M$98)) -> 0 | O98: =IF(ISERR(AVERAGE($L$98:$N$98)),0,AVERAGE($L$98:$N$98)) -> 0 | P98: =IF(ISERR(AVERAGE($M$98:$O$98)),0,AVERAGE($M$98:$O$98)) -> 0 | Q98: =IF(ISERR(AVERAGE($N$98:$P$98)),0,AVERAGE($N$98:$P$98)) -> 0 | R98: =IF(ISERR(AVERAGE($O$98:$Q$98)),0,AVERAGE($O$98:$Q$98)) -> 0 | S98: =IF(ISERR(AVERAGE($O$98:$Q$98)),0,AVERAGE($O$98:$Q$98)) -> 0 | T98: =IF(ISERR(AVERAGE($O$98:$Q$98)),0,AVERAGE($O$98:$Q$98)) -> 0
B99: 开发支出本期增减 | C99: 默认值0 | E99: =历史数据及预测表!E40-历史数据及预测表!D40 -> -16.114386 | F99: =历史数据及预测表!F40-历史数据及预测表!E40 -> -36.034704 | G99: =历史数据及预测表!G40-历史数据及预测表!F40 -> 9.1989955 | H99: =历史数据及预测表!H40-历史数据及预测表!G40 -> -18.599662 | I99: 0 | J99: 0 | K99: 0 | L99: 0 | M99: 0 | N99: 0 | O99: 0 | P99: 0 | Q99: 0 | R99: 0 | S99: 0 | T99: 0
B100: 商誉原值本期增减 | C100: 默认值0 | E100: =历史数据及预测表!E248-历史数据及预测表!D248 -> 0 | F100: =历史数据及预测表!F248-历史数据及预测表!E248 -> 0 | G100: =历史数据及预测表!G248-历史数据及预测表!F248 -> 0 | H100: =历史数据及预测表!H248-历史数据及预测表!G248 -> 0 | I100: 0 | J100: 0 | K100: 0 | L100: 0 | M100: 0 | N100: 0 | O100: 0 | P100: 0 | Q100: 0 | R100: 0 | S100: 0 | T100: 0
B101: 长期待摊费用原值本期增减 | C101: 默认值0 | E101: =历史数据及预测表!E249-历史数据及预测表!D249 -> -2.1082187 | F101: =历史数据及预测表!F249-历史数据及预测表!E249 -> -3.1237062 | G101: =历史数据及预测表!G249-历史数据及预测表!F249 -> 0 | H101: =历史数据及预测表!H249-历史数据及预测表!G249 -> 0 | I101: 0 | J101: 0 | K101: 0 | L101: 0 | M101: 0 | N101: 0 | O101: 0 | P101: 0 | Q101: 0 | R101: 0 | S101: 0 | T101: 0
B102: 长期待摊费用本期摊销 | C102: 前三年平均数据 | D102: =历史数据及预测表!D250 -> 0 | E102: =历史数据及预测表!E250 -> 0 | F102: =历史数据及预测表!F250 -> 0 | G102: =历史数据及预测表!G250 -> 0 | H102: =历史数据及预测表!H250 -> 0 | I102: =IF(ISERR(AVERAGE($F$102:$H$102)),0,AVERAGE($F$102:$H$102)) -> 0 | J102: =IF(ISERR(AVERAGE($G$102:$I$102)),0,AVERAGE($G$102:$I$102)) -> 0 | K102: =IF(ISERR(AVERAGE($H$102:$J$102)),0,AVERAGE($H$102:$J$102)) -> 0 | L102: =IF(ISERR(AVERAGE($I$102:$K$102)),0,AVERAGE($I$102:$K$102)) -> 0 | M102: =IF(ISERR(AVERAGE($J$102:$L$102)),0,AVERAGE($J$102:$L$102)) -> 0 | N102: =IF(ISERR(AVERAGE($K$102:$M$102)),0,AVERAGE($K$102:$M$102)) -> 0 | O102: =IF(ISERR(AVERAGE($L$102:$N$102)),0,AVERAGE($L$102:$N$102)) -> 0 | P102: =IF(ISERR(AVERAGE($M$102:$O$102)),0,AVERAGE($M$102:$O$102)) -> 0 | Q102: =IF(ISERR(AVERAGE($N$102:$P$102)),0,AVERAGE($N$102:$P$102)) -> 0 | R102: =IF(ISERR(AVERAGE($O$102:$Q$102)),0,AVERAGE($O$102:$Q$102)) -> 0 | S102: =IF(ISERR(AVERAGE($O$102:$Q$102)),0,AVERAGE($O$102:$Q$102)) -> 0 | T102: =IF(ISERR(AVERAGE($O$102:$Q$102)),0,AVERAGE($O$102:$Q$102)) -> 0
B104: 当年新增长期股权投资减值准备 | C104: 前三年平均数据 | D104: =历史数据及预测表!D252 -> 0 | E104: =历史数据及预测表!E252 -> 0 | F104: =历史数据及预测表!F252 -> 0 | G104: =历史数据及预测表!G252 -> 0 | H104: =历史数据及预测表!H252 -> 0 | I104: =IF(ISERR(AVERAGE($F$104:$H$104)),0,AVERAGE($F$104:$H$104)) -> 0 | J104: =IF(ISERR(AVERAGE($G$104:$I$104)),0,AVERAGE($G$104:$I$104)) -> 0 | K104: =IF(ISERR(AVERAGE($H$104:$J$104)),0,AVERAGE($H$104:$J$104)) -> 0 | L104: =IF(ISERR(AVERAGE($I$104:$K$104)),0,AVERAGE($I$104:$K$104)) -> 0 | M104: =IF(ISERR(AVERAGE($J$104:$L$104)),0,AVERAGE($J$104:$L$104)) -> 0 | N104: =IF(ISERR(AVERAGE($K$104:$M$104)),0,AVERAGE($K$104:$M$104)) -> 0 | O104: =IF(ISERR(AVERAGE($L$104:$N$104)),0,AVERAGE($L$104:$N$104)) -> 0 | P104: =IF(ISERR(AVERAGE($M$104:$O$104)),0,AVERAGE($M$104:$O$104)) -> 0 | Q104: =IF(ISERR(AVERAGE($N$104:$P$104)),0,AVERAGE($N$104:$P$104)) -> 0 | R104: =IF(ISERR(AVERAGE($O$104:$Q$104)),0,AVERAGE($O$104:$Q$104)) -> 0 | S104: =IF(ISERR(AVERAGE($O$104:$Q$104)),0,AVERAGE($O$104:$Q$104)) -> 0 | T104: =IF(ISERR(AVERAGE($O$104:$Q$104)),0,AVERAGE($O$104:$Q$104)) -> 0
...

Sheet 关键项目预测
B1: 资本性支出预测
B3: 预测方法 | C3: 1 | E3: =IF(C3=1,NOT(ISBLANK(C10)),OR(NOT(ISBLANK(C31)),NOT(ISBLANK(C50)),NOT(ISBLANK(C69)),NOT(ISBLANK(C88)))) -> TRUE
B4: 方法1 | C4: 固定资产整体预测（整体预测+在建工程转入）
B5: 方法2 | C5: 固定资产分类别预测
A7: 方法1 | C7: 整体预测
B8: 固定资产
B9: 固定资产-整体预测
B10: 折旧年限 | C10: 10 | E10: 残值率 | F10: 0.05 | H10: 折旧率 | I10: =(1-F10)/C10 -> 0.095
E11: =假设表!I2 -> 2026 | F11: =假设表!J2 -> 2027 | G11: =假设表!K2 -> 2028 | H11: =假设表!L2 -> 2029 | I11: =假设表!M2 -> 2030 | J11: =假设表!N2 -> 2031 | K11: =假设表!O2 -> 2032 | L11: =假设表!P2 -> 2033 | ... P11: =假设表!T2 -> 2037
B12: 年份 | C12: 金额
B13: {=TRANSPOSE(历史数据及预测表!H4:T4)} -> 2025 | C13: 期末固定资产（账面原值） | D13: {=TRANSPOSE(假设表!H86:T86)} -> 462.27066 | E13: =IF(E$11-$B13<=$C$10,$I$10*$D13,0) -> 43.915713 | F13: =IF(F$11-$B13<=$C$10,$I$10*$D13,0) -> 43.915713 | G13: =IF(G$11-$B13<=$C$10,$I$10*$D13,0) -> 43.915713 | H13: =IF(H$11-$B13<=$C$10,$I$10*$D13,0) -> 43.915713 | I13: =IF(I$11-$B13<=$C$10,$I$10*$D13,0) -> 43.915713 | J13: =IF(J$11-$B13<=$C$10,$I$10*$D13,0) -> 43.915713 | K13: =IF(K$11-$B13<=$C$10,$I$10*$D13,0) -> 43.915713 | L13: =IF(L$11-$B13<=$C$10,$I$10*$D13,0) -> 43.915713 | ... P13: =IF(P$11-$B13<=$C$10,$I$10*$D13,0) -> 0
B14: 2026 | C14: 新增数 | D14: 200 | E14: =IF(E$11-$B14<=$C$10-1,$I$10*$D14,0) -> 19 | F14: =IF(F$11-$B14<=$C$10-1,$I$10*$D14,0) -> 19 | G14: =IF(G$11-$B14<=$C$10-1,$I$10*$D14,0) -> 19 | H14: =IF(H$11-$B14<=$C$10-1,$I$10*$D14,0) -> 19 | I14: =IF(I$11-$B14<=$C$10-1,$I$10*$D14,0) -> 19 | J14: =IF(J$11-$B14<=$C$10-1,$I$10*$D14,0) -> 19 | K14: =IF(K$11-$B14<=$C$10-1,$I$10*$D14,0) -> 19 | L14: =IF(L$11-$B14<=$C$10-1,$I$10*$D14,0) -> 19 | ... P14: =IF(P$11-$B14<=$C$10-1,$I$10*$D14,0) -> 0
B15: 2027 | C15: 新增数 | D15: 200 | F15: =IF(F$11-$B15<=$C$10-1,$I$10*$D15,0) -> 19 | G15: =IF(G$11-$B15<=$C$10-1,$I$10*$D15,0) -> 19 | H15: =IF(H$11-$B15<=$C$10-1,$I$10*$D15,0) -> 19 | I15: =IF(I$11-$B15<=$C$10-1,$I$10*$D15,0) -> 19 | J15: =IF(J$11-$B15<=$C$10-1,$I$10*$D15,0) -> 19 | K15: =IF(K$11-$B15<=$C$10-1,$I$10*$D15,0) -> 19 | L15: =IF(L$11-$B15<=$C$10-1,$I$10*$D15,0) -> 19 | M15: =IF(M$11-$B15<=$C$10-1,$I$10*$D15,0) -> 19 | ... P15: =IF(P$11-$B15<=$C$10-1,$I$10*$D15,0) -> 0
B16: 2028 | C16: 新增数 | D16: 200 | G16: =IF(G$11-$B16<=$C$10-1,$I$10*$D16,0) -> 19 | H16: =IF(H$11-$B16<=$C$10-1,$I$10*$D16,0) -> 19 | I16: =IF(I$11-$B16<=$C$10-1,$I$10*$D16,0) -> 19 | J16: =IF(J$11-$B16<=$C$10-1,$I$10*$D16,0) -> 19 | K16: =IF(K$11-$B16<=$C$10-1,$I$10*$D16,0) -> 19 | L16: =IF(L$11-$B16<=$C$10-1,$I$10*$D16,0) -> 19 | M16: =IF(M$11-$B16<=$C$10-1,$I$10*$D16,0) -> 19 | N16: =IF(N$11-$B16<=$C$10-1,$I$10*$D16,0) -> 19 | ... P16: =IF(P$11-$B16<=$C$10-1,$I$10*$D16,0) -> 19
B17: 2029 | C17: 新增数 | D17: 200 | H17: =IF(H$11-$B17<=$C$10-1,$I$10*$D17,0) -> 19 | I17: =IF(I$11-$B17<=$C$10-1,$I$10*$D17,0) -> 19 | J17: =IF(J$11-$B17<=$C$10-1,$I$10*$D17,0) -> 19 | K17: =IF(K$11-$B17<=$C$10-1,$I$10*$D17,0) -> 19 | L17: =IF(L$11-$B17<=$C$10-1,$I$10*$D17,0) -> 19 | M17: =IF(M$11-$B17<=$C$10-1,$I$10*$D17,0) -> 19 | N17: =IF(N$11-$B17<=$C$10-1,$I$10*$D17,0) -> 19 | O17: =IF(O$11-$B17<=$C$10-1,$I$10*$D17,0) -> 19 | P17: =IF(P$11-$B17<=$C$10-1,$I$10*$D17,0) -> 19
B18: 2030 | C18: 新增数 | D18: 200 | I18: =IF(I$11-$B18<=$C$10-1,$I$10*$D18,0) -> 19 | J18: =IF(J$11-$B18<=$C$10-1,$I$10*$D18,0) -> 19 | K18: =IF(K$11-$B18<=$C$10-1,$I$10*$D18,0) -> 19 | L18: =IF(L$11-$B18<=$C$10-1,$I$10*$D18,0) -> 19 | M18: =IF(M$11-$B18<=$C$10-1,$I$10*$D18,0) -> 19 | N18: =IF(N$11-$B18<=$C$10-1,$I$10*$D18,0) -> 19 | O18: =IF(O$11-$B18<=$C$10-1,$I$10*$D18,0) -> 19 | P18: =IF(P$11-$B18<=$C$10-1,$I$10*$D18,0) -> 19
B19: 2031 | C19: 新增数 | D19: 200 | J19: =IF(J$11-$B19<=$C$10-1,$I$10*$D19,0) -> 19 | K19: =IF(K$11-$B19<=$C$10-1,$I$10*$D19,0) -> 19 | L19: =IF(L$11-$B19<=$C$10-1,$I$10*$D19,0) -> 19 | M19: =IF(M$11-$B19<=$C$10-1,$I$10*$D19,0) -> 19 | N19: =IF(N$11-$B19<=$C$10-1,$I$10*$D19,0) -> 19 | O19: =IF(O$11-$B19<=$C$10-1,$I$10*$D19,0) -> 19 | P19: =IF(P$11-$B19<=$C$10-1,$I$10*$D19,0) -> 19
B20: 2032 | C20: 新增数 | D20: 200 | K20: =IF(K$11-$B20<=$C$10-1,$I$10*$D20,0) -> 19 | L20: =IF(L$11-$B20<=$C$10-1,$I$10*$D20,0) -> 19 | M20: =IF(M$11-$B20<=$C$10-1,$I$10*$D20,0) -> 19 | N20: =IF(N$11-$B20<=$C$10-1,$I$10*$D20,0) -> 19 | O20: =IF(O$11-$B20<=$C$10-1,$I$10*$D20,0) -> 19 | P20: =IF(P$11-$B20<=$C$10-1,$I$10*$D20,0) -> 19
B21: 2033 | C21: 新增数 | D21: 200 | L21: =IF(L$11-$B21<=$C$10-1,$I$10*$D21,0) -> 19 | M21: =IF(M$11-$B21<=$C$10-1,$I$10*$D21,0) -> 19 | N21: =IF(N$11-$B21<=$C$10-1,$I$10*$D21,0) -> 19 | O21: =IF(O$11-$B21<=$C$10-1,$I$10*$D21,0) -> 19 | P21: =IF(P$11-$B21<=$C$10-1,$I$10*$D21,0) -> 19
B22: 2034 | C22: 新增数 | D22: 200 | M22: =IF(M$11-$B22<=$C$10-1,$I$10*$D22,0) -> 19 | N22: =IF(N$11-$B22<=$C$10-1,$I$10*$D22,0) -> 19 | O22: =IF(O$11-$B22<=$C$10-1,$I$10*$D22,0) -> 19 | P22: =IF(P$11-$B22<=$C$10-1,$I$10*$D22,0) -> 19
B23: 2035 | C23: 新增数 | D23: 200 | N23: =IF(N$11-$B23<=$C$10-1,$I$10*$D23,0) -> 19 | O23: =IF(O$11-$B23<=$C$10-1,$I$10*$D23,0) -> 19 | P23: =IF(P$11-$B23<=$C$10-1,$I$10*$D23,0) -> 19
B24: 2036 | C24: 新增数 | D24: 200 | O24: =IF(O$11-$B24<=$C$10-1,$I$10*$D24,0) -> 19 | P24: =IF(P$11-$B24<=$C$10-1,$I$10*$D24,0) -> 19
B25: 2037 | C25: 新增数 | D25: 200 | P25: =IF(P$11-$B25<=$C$10-1,$I$10*$D25,0) -> 19
B26: 固定资产折旧合计 | E26: =SUM(E13:E25) -> 62.915713 | F26: =SUM(F13:F25) -> 81.915713 | G26: =SUM(G13:G25) -> 100.91571 | H26: =SUM(H13:H25) -> 119.91571 | I26: =SUM(I13:I25) -> 138.91571 | J26: =SUM(J13:J25) -> 157.91571 | K26: =SUM(K13:K25) -> 176.91571 | L26: =SUM(L13:L25) -> 195.91571 | ... P26: =SUM(P13:P25) -> 190
A28: 方法2 | C28: 分类别预测
B29: 固定资产
B30: 固定资产-房屋及建筑物
B31: 折旧年限 | E31: 残值率 | H31: 折旧率 | I31: =(1-F31)/C31 -> #DIV/0!
E32: =假设表!I2 -> 2026 | F32: =假设表!J2 -> 2027 | G32: =假设表!K2 -> 2028 | H32: =假设表!L2 -> 2029 | I32: =假设表!M2 -> 2030 | J32: =假设表!N2 -> 2031 | K32: =假设表!O2 -> 2032 | L32: =假设表!P2 -> 2033 | ... P32: =假设表!T2 -> 2037
B33: 年份 | C33: 金额
B34: {=TRANSPOSE(假设表!H2:T2)} -> 2025 | C34: 期末固定资产（账面原值） | D34: {=TRANSPOSE(假设表!H87:T87)} -> 0 | E34: =IF(E$32-$B34<=$C$31,$I$31*$D34,0) -> 0 | F34: =IF(F$32-$B34<=$C$31,$I$31*$D34,0) -> 0 | G34: =IF(G$32-$B34<=$C$31,$I$31*$D34,0) -> 0 | H34: =IF(H$32-$B34<=$C$31,$I$31*$D34,0) -> 0 | I34: =IF(I$32-$B34<=$C$31,$I$31*$D34,0) -> 0 | J34: =IF(J$32-$B34<=$C$31,$I$31*$D34,0) -> 0 | K34: =IF(K$32-$B34<=$C$31,$I$31*$D34,0) -> 0 | L34: =IF(L$32-$B34<=$C$31,$I$31*$D34,0) -> 0 | ... P34: =IF(P$32-$B34<=$C$31,$I$31*$D34,0) -> 0
B35: 2026 | C35: 新增数 | D35: 0 | E35: =IF(E$32-$B35<=$C$31-1,$I$31*$D35,0) -> 0 | F35: =IF(F$32-$B35<=$C$31-1,$I$31*$D35,0) -> 0 | G35: =IF(G$32-$B35<=$C$31-1,$I$31*$D35,0) -> 0 | H35: =IF(H$32-$B35<=$C$31-1,$I$31*$D35,0) -> 0 | I35: =IF(I$32-$B35<=$C$31-1,$I$31*$D35,0) -> 0 | J35: =IF(J$32-$B35<=$C$31-1,$I$31*$D35,0) -> 0 | K35: =IF(K$32-$B35<=$C$31-1,$I$31*$D35,0) -> 0 | L35: =IF(L$32-$B35<=$C$31-1,$I$31*$D35,0) -> 0 | ... P35: =IF(P$32-$B35<=$C$31-1,$I$31*$D35,0) -> 0
B36: 2027 | C36: 新增数 | D36: 0 | F36: =IF(F$32-$B36<=$C$31-1,$I$31*$D36,0) -> 0 | G36: =IF(G$32-$B36<=$C$31-1,$I$31*$D36,0) -> 0 | H36: =IF(H$32-$B36<=$C$31-1,$I$31*$D36,0) -> 0 | I36: =IF(I$32-$B36<=$C$31-1,$I$31*$D36,0) -> 0 | J36: =IF(J$32-$B36<=$C$31-1,$I$31*$D36,0) -> 0 | K36: =IF(K$32-$B36<=$C$31-1,$I$31*$D36,0) -> 0 | L36: =IF(L$32-$B36<=$C$31-1,$I$31*$D36,0) -> 0 | M36: =IF(M$32-$B36<=$C$31-1,$I$31*$D36,0) -> 0 | ... P36: =IF(P$32-$B36<=$C$31-1,$I$31*$D36,0) -> 0
B37: 2028 | C37: 新增数 | D37: 0 | G37: =IF(G$32-$B37<=$C$31-1,$I$31*$D37,0) -> 0 | H37: =IF(H$32-$B37<=$C$31-1,$I$31*$D37,0) -> 0 | I37: =IF(I$32-$B37<=$C$31-1,$I$31*$D37,0) -> 0 | J37: =IF(J$32-$B37<=$C$31-1,$I$31*$D37,0) -> 0 | K37: =IF(K$32-$B37<=$C$31-1,$I$31*$D37,0) -> 0 | L37: =IF(L$32-$B37<=$C$31-1,$I$31*$D37,0) -> 0 | M37: =IF(M$32-$B37<=$C$31-1,$I$31*$D37,0) -> 0 | N37: =IF(N$32-$B37<=$C$31-1,$I$31*$D37,0) -> 0 | ... P37: =IF(P$32-$B37<=$C$31-1,$I$31*$D37,0) -> 0
B38: 2029 | C38: 新增数 | D38: 0 | H38: =IF(H$32-$B38<=$C$31-1,$I$31*$D38,0) -> 0 | I38: =IF(I$32-$B38<=$C$31-1,$I$31*$D38,0) -> 0 | J38: =IF(J$32-$B38<=$C$31-1,$I$31*$D38,0) -> 0 | K38: =IF(K$32-$B38<=$C$31-1,$I$31*$D38,0) -> 0 | L38: =IF(L$32-$B38<=$C$31-1,$I$31*$D38,0) -> 0 | M38: =IF(M$32-$B38<=$C$31-1,$I$31*$D38,0) -> 0 | N38: =IF(N$32-$B38<=$C$31-1,$I$31*$D38,0) -> 0 | O38: =IF(O$32-$B38<=$C$31-1,$I$31*$D38,0) -> 0 | P38: =IF(P$32-$B38<=$C$31-1,$I$31*$D38,0) -> 0
B39: 2030 | C39: 新增数 | D39: 0 | I39: =IF(I$32-$B39<=$C$31-1,$I$31*$D39,0) -> 0 | J39: =IF(J$32-$B39<=$C$31-1,$I$31*$D39,0) -> 0 | K39: =IF(K$32-$B39<=$C$31-1,$I$31*$D39,0) -> 0 | L39: =IF(L$32-$B39<=$C$31-1,$I$31*$D39,0) -> 0 | M39: =IF(M$32-$B39<=$C$31-1,$I$31*$D39,0) -> 0 | N39: =IF(N$32-$B39<=$C$31-1,$I$31*$D39,0) -> 0 | O39: =IF(O$32-$B39<=$C$31-1,$I$31*$D39,0) -> 0 | P39: =IF(P$32-$B39<=$C$31-1,$I$31*$D39,0) -> 0
B40: 2031 | C40: 新增数 | D40: 0 | J40: =IF(J$32-$B40<=$C$31-1,$I$31*$D40,0) -> 0 | K40: =IF(K$32-$B40<=$C$31-1,$I$31*$D40,0) -> 0 | L40: =IF(L$32-$B40<=$C$31-1,$I$31*$D40,0) -> 0 | M40: =IF(M$32-$B40<=$C$31-1,$I$31*$D40,0) -> 0 | N40: =IF(N$32-$B40<=$C$31-1,$I$31*$D40,0) -> 0 | O40: =IF(O$32-$B40<=$C$31-1,$I$31*$D40,0) -> 0 | P40: =IF(P$32-$B40<=$C$31-1,$I$31*$D40,0) -> 0
B41: 2032 | C41: 新增数 | D41: 0 | K41: =IF(K$32-$B41<=$C$31-1,$I$31*$D41,0) -> 0 | L41: =IF(L$32-$B41<=$C$31-1,$I$31*$D41,0) -> 0 | M41: =IF(M$32-$B41<=$C$31-1,$I$31*$D41,0) -> 0 | N41: =IF(N$32-$B41<=$C$31-1,$I$31*$D41,0) -> 0 | O41: =IF(O$32-$B41<=$C$31-1,$I$31*$D41,0) -> 0 | P41: =IF(P$32-$B41<=$C$31-1,$I$31*$D41,0) -> 0
B42: 2033 | C42: 新增数 | D42: 0 | L42: =IF(L$32-$B42<=$C$31-1,$I$31*$D42,0) -> 0 | M42: =IF(M$32-$B42<=$C$31-1,$I$31*$D42,0) -> 0 | N42: =IF(N$32-$B42<=$C$31-1,$I$31*$D42,0) -> 0 | O42: =IF(O$32-$B42<=$C$31-1,$I$31*$D42,0) -> 0 | P42: =IF(P$32-$B42<=$C$31-1,$I$31*$D42,0) -> 0
B43: 2034 | C43: 新增数 | D43: 0 | M43: =IF(M$32-$B43<=$C$31-1,$I$31*$D43,0) -> 0 | N43: =IF(N$32-$B43<=$C$31-1,$I$31*$D43,0) -> 0 | O43: =IF(O$32-$B43<=$C$31-1,$I$31*$D43,0) -> 0 | P43: =IF(P$32-$B43<=$C$31-1,$I$31*$D43,0) -> 0
B44: 2035 | C44: 新增数 | D44: 0 | N44: =IF(N$32-$B44<=$C$31-1,$I$31*$D44,0) -> 0 | O44: =IF(O$32-$B44<=$C$31-1,$I$31*$D44,0) -> 0 | P44: =IF(P$32-$B44<=$C$31-1,$I$31*$D44,0) -> 0
B45: 2036 | C45: 新增数 | D45: 0 | O45: =IF(O$32-$B45<=$C$31-1,$I$31*$D45,0) -> 0 | P45: =IF(P$32-$B45<=$C$31-1,$I$31*$D45,0) -> 0
B46: 2037 | C46: 新增数 | D46: 0 | P46: =IF(P$32-$B46<=$C$31-1,$I$31*$D46,0) -> 0
B47: 房屋建筑物折旧合计 | E47: =SUM(E34:E46) -> 0 | F47: =SUM(F34:F46) -> 0 | G47: =SUM(G34:G46) -> 0 | H47: =SUM(H34:H46) -> 0 | I47: =SUM(I34:I46) -> 0 | J47: =SUM(J34:J46) -> 0 | K47: =SUM(K34:K46) -> 0 | L47: =SUM(L34:L46) -> 0 | ... P47: =SUM(P34:P46) -> 0
B49: 固定资产-机械设备
B50: 折旧年限 | E50: 残值率 | H50: 折旧率 | I50: =(1-F50)/C50 -> #DIV/0!
E51: =假设表!I2 -> 2026 | F51: =假设表!J2 -> 2027 | G51: =假设表!K2 -> 2028 | H51: =假设表!L2 -> 2029 | I51: =假设表!M2 -> 2030 | J51: =假设表!N2 -> 2031 | K51: =假设表!O2 -> 2032 | L51: =假设表!P2 -> 2033 | ... P51: =假设表!T2 -> 2037
B52: 年份 | C52: 金额
B53: {=TRANSPOSE(假设表!H2:T2)} -> 2025 | C53: 期末固定资产（账面原值） | D53: {=TRANSPOSE(假设表!H88:T88)} -> 0 | E53: =IF(E$51-$B53<=$C$50,$I$50*$D53,0) -> 0 | F53: =IF(F$51-$B53<=$C$50,$I$50*$D53,0) -> 0 | G53: =IF(G$51-$B53<=$C$50,$I$50*$D53,0) -> 0 | H53: =IF(H$51-$B53<=$C$50,$I$50*$D53,0) -> 0 | I53: =IF(I$51-$B53<=$C$50,$I$50*$D53,0) -> 0 | J53: =IF(J$51-$B53<=$C$50,$I$50*$D53,0) -> 0 | K53: =IF(K$51-$B53<=$C$50,$I$50*$D53,0) -> 0 | L53: =IF(L$51-$B53<=$C$50,$I$50*$D53,0) -> 0 | ... P53: =IF(P$51-$B53<=$C$50,$I$50*$D53,0) -> 0
B54: 2026 | C54: 新增数 | D54: 0 | E54: =IF(E$51-$B54<=$C$50-1,$I$50*$D54,0) -> 0 | F54: =IF(F$51-$B54<=$C$50-1,$I$50*$D54,0) -> 0 | G54: =IF(G$51-$B54<=$C$50-1,$I$50*$D54,0) -> 0 | H54: =IF(H$51-$B54<=$C$50-1,$I$50*$D54,0) -> 0 | I54: =IF(I$51-$B54<=$C$50-1,$I$50*$D54,0) -> 0 | J54: =IF(J$51-$B54<=$C$50-1,$I$50*$D54,0) -> 0 | K54: =IF(K$51-$B54<=$C$50-1,$I$50*$D54,0) -> 0 | L54: =IF(L$51-$B54<=$C$50-1,$I$50*$D54,0) -> 0 | ... P54: =IF(P$51-$B54<=$C$50-1,$I$50*$D54,0) -> 0
B55: 2027 | C55: 新增数 | D55: 0 | F55: =IF(F$51-$B55<=$C$50-1,$I$50*$D55,0) -> 0 | G55: =IF(G$51-$B55<=$C$50-1,$I$50*$D55,0) -> 0 | H55: =IF(H$51-$B55<=$C$50-1,$I$50*$D55,0) -> 0 | I55: =IF(I$51-$B55<=$C$50-1,$I$50*$D55,0) -> 0 | J55: =IF(J$51-$B55<=$C$50-1,$I$50*$D55,0) -> 0 | K55: =IF(K$51-$B55<=$C$50-1,$I$50*$D55,0) -> 0 | L55: =IF(L$51-$B55<=$C$50-1,$I$50*$D55,0) -> 0 | M55: =IF(M$51-$B55<=$C$50-1,$I$50*$D55,0) -> 0 | ... P55: =IF(P$51-$B55<=$C$50-1,$I$50*$D55,0) -> 0
B56: 2028 | C56: 新增数 | D56: 0 | G56: =IF(G$51-$B56<=$C$50-1,$I$50*$D56,0) -> 0 | H56: =IF(H$51-$B56<=$C$50-1,$I$50*$D56,0) -> 0 | I56: =IF(I$51-$B56<=$C$50-1,$I$50*$D56,0) -> 0 | J56: =IF(J$51-$B56<=$C$50-1,$I$50*$D56,0) -> 0 | K56: =IF(K$51-$B56<=$C$50-1,$I$50*$D56,0) -> 0 | L56: =IF(L$51-$B56<=$C$50-1,$I$50*$D56,0) -> 0 | M56: =IF(M$51-$B56<=$C$50-1,$I$50*$D56,0) -> 0 | N56: =IF(N$51-$B56<=$C$50-1,$I$50*$D56,0) -> 0 | ... P56: =IF(P$51-$B56<=$C$50-1,$I$50*$D56,0) -> 0
B57: 2029 | C57: 新增数 | D57: 0 | H57: =IF(H$51-$B57<=$C$50-1,$I$50*$D57,0) -> 0 | I57: =IF(I$51-$B57<=$C$50-1,$I$50*$D57,0) -> 0 | J57: =IF(J$51-$B57<=$C$50-1,$I$50*$D57,0) -> 0 | K57: =IF(K$51-$B57<=$C$50-1,$I$50*$D57,0) -> 0 | L57: =IF(L$51-$B57<=$C$50-1,$I$50*$D57,0) -> 0 | M57: =IF(M$51-$B57<=$C$50-1,$I$50*$D57,0) -> 0 | N57: =IF(N$51-$B57<=$C$50-1,$I$50*$D57,0) -> 0 | O57: =IF(O$51-$B57<=$C$50-1,$I$50*$D57,0) -> 0 | P57: =IF(P$51-$B57<=$C$50-1,$I$50*$D57,0) -> 0
B58: 2030 | C58: 新增数 | D58: 0 | I58: =IF(I$51-$B58<=$C$50-1,$I$50*$D58,0) -> 0 | J58: =IF(J$51-$B58<=$C$50-1,$I$50*$D58,0) -> 0 | K58: =IF(K$51-$B58<=$C$50-1,$I$50*$D58,0) -> 0 | L58: =IF(L$51-$B58<=$C$50-1,$I$50*$D58,0) -> 0 | M58: =IF(M$51-$B58<=$C$50-1,$I$50*$D58,0) -> 0 | N58: =IF(N$51-$B58<=$C$50-1,$I$50*$D58,0) -> 0 | O58: =IF(O$51-$B58<=$C$50-1,$I$50*$D58,0) -> 0 | P58: =IF(P$51-$B58<=$C$50-1,$I$50*$D58,0) -> 0
B59: 2031 | C59: 新增数 | D59: 0 | J59: =IF(J$51-$B59<=$C$50-1,$I$50*$D59,0) -> 0 | K59: =IF(K$51-$B59<=$C$50-1,$I$50*$D59,0) -> 0 | L59: =IF(L$51-$B59<=$C$50-1,$I$50*$D59,0) -> 0 | M59: =IF(M$51-$B59<=$C$50-1,$I$50*$D59,0) -> 0 | N59: =IF(N$51-$B59<=$C$50-1,$I$50*$D59,0) -> 0 | O59: =IF(O$51-$B59<=$C$50-1,$I$50*$D59,0) -> 0 | P59: =IF(P$51-$B59<=$C$50-1,$I$50*$D59,0) -> 0
B60: 2032 | C60: 新增数 | D60: 0 | K60: =IF(K$51-$B60<=$C$50-1,$I$50*$D60,0) -> 0 | L60: =IF(L$51-$B60<=$C$50-1,$I$50*$D60,0) -> 0 | M60: =IF(M$51-$B60<=$C$50-1,$I$50*$D60,0) -> 0 | N60: =IF(N$51-$B60<=$C$50-1,$I$50*$D60,0) -> 0 | O60: =IF(O$51-$B60<=$C$50-1,$I$50*$D60,0) -> 0 | P60: =IF(P$51-$B60<=$C$50-1,$I$50*$D60,0) -> 0
B61: 2033 | C61: 新增数 | D61: 0 | L61: =IF(L$51-$B61<=$C$50-1,$I$50*$D61,0) -> 0 | M61: =IF(M$51-$B61<=$C$50-1,$I$50*$D61,0) -> 0 | N61: =IF(N$51-$B61<=$C$50-1,$I$50*$D61,0) -> 0 | O61: =IF(O$51-$B61<=$C$50-1,$I$50*$D61,0) -> 0 | P61: =IF(P$51-$B61<=$C$50-1,$I$50*$D61,0) -> 0
B62: 2034 | C62: 新增数 | D62: 0 | M62: =IF(M$51-$B62<=$C$50-1,$I$50*$D62,0) -> 0 | N62: =IF(N$51-$B62<=$C$50-1,$I$50*$D62,0) -> 0 | O62: =IF(O$51-$B62<=$C$50-1,$I$50*$D62,0) -> 0 | P62: =IF(P$51-$B62<=$C$50-1,$I$50*$D62,0) -> 0
B63: 2035 | C63: 新增数 | D63: 0 | N63: =IF(N$51-$B63<=$C$50-1,$I$50*$D63,0) -> 0 | O63: =IF(O$51-$B63<=$C$50-1,$I$50*$D63,0) -> 0 | P63: =IF(P$51-$B63<=$C$50-1,$I$50*$D63,0) -> 0
B64: 2036 | C64: 新增数 | D64: 0 | O64: =IF(O$51-$B64<=$C$50-1,$I$50*$D64,0) -> 0 | P64: =IF(P$51-$B64<=$C$50-1,$I$50*$D64,0) -> 0
B65: 2037 | C65: 新增数 | D65: 0 | P65: =IF(P$51-$B65<=$C$50-1,$I$50*$D65,0) -> 0
B66: 机械设备折旧合计 | E66: =SUM(E53:E65) -> 0 | F66: =SUM(F53:F65) -> 0 | G66: =SUM(G53:G65) -> 0 | H66: =SUM(H53:H65) -> 0 | I66: =SUM(I53:I65) -> 0 | J66: =SUM(J53:J65) -> 0 | K66: =SUM(K53:K65) -> 0 | L66: =SUM(L53:L65) -> 0 | ... P66: =SUM(P53:P65) -> 0
B68: 固定资产-运输设备
B69: 折旧年限 | E69: 残值率 | H69: 折旧率 | I69: =(1-F69)/C69 -> #DIV/0!
E70: =假设表!I2 -> 2026 | F70: =假设表!J2 -> 2027 | G70: =假设表!K2 -> 2028 | H70: =假设表!L2 -> 2029 | I70: =假设表!M2 -> 2030 | J70: =假设表!N2 -> 2031 | K70: =假设表!O2 -> 2032 | L70: =假设表!P2 -> 2033 | ... P70: =假设表!T2 -> 2037
B71: 年份 | C71: 金额
B72: {=TRANSPOSE(假设表!H2:T2)} -> 2025 | C72: 期末固定资产（账面原值） | D72: {=TRANSPOSE(假设表!H89:T89)} -> 0 | E72: =IF(E$70-$B72<=$C$69,$I$69*$D72,0) -> 0 | F72: =IF(F$70-$B72<=$C$69,$I$69*$D72,0) -> 0 | G72: =IF(G$70-$B72<=$C$69,$I$69*$D72,0) -> 0 | H72: =IF(H$70-$B72<=$C$69,$I$69*$D72,0) -> 0 | I72: =IF(I$70-$B72<=$C$69,$I$69*$D72,0) -> 0 | J72: =IF(J$70-$B72<=$C$69,$I$69*$D72,0) -> 0 | K72: =IF(K$70-$B72<=$C$69,$I$69*$D72,0) -> 0 | L72: =IF(L$70-$B72<=$C$69,$I$69*$D72,0) -> 0 | ... P72: =IF(P$70-$B72<=$C$69,$I$69*$D72,0) -> 0
B73: 2026 | C73: 新增数 | D73: 0 | E73: =IF(E$70-$B73<=$C$69-1,$I$69*$D73,0) -> 0 | F73: =IF(F$70-$B73<=$C$69-1,$I$69*$D73,0) -> 0 | G73: =IF(G$70-$B73<=$C$69-1,$I$69*$D73,0) -> 0 | H73: =IF(H$70-$B73<=$C$69-1,$I$69*$D73,0) -> 0 | I73: =IF(I$70-$B73<=$C$69-1,$I$69*$D73,0) -> 0 | J73: =IF(J$70-$B73<=$C$69-1,$I$69*$D73,0) -> 0 | K73: =IF(K$70-$B73<=$C$69-1,$I$69*$D73,0) -> 0 | L73: =IF(L$70-$B73<=$C$69-1,$I$69*$D73,0) -> 0 | ... P73: =IF(P$70-$B73<=$C$69-1,$I$69*$D73,0) -> 0
B74: 2027 | C74: 新增数 | D74: 0 | F74: =IF(F$70-$B74<=$C$69-1,$I$69*$D74,0) -> 0 | G74: =IF(G$70-$B74<=$C$69-1,$I$69*$D74,0) -> 0 | H74: =IF(H$70-$B74<=$C$69-1,$I$69*$D74,0) -> 0 | I74: =IF(I$70-$B74<=$C$69-1,$I$69*$D74,0) -> 0 | J74: =IF(J$70-$B74<=$C$69-1,$I$69*$D74,0) -> 0 | K74: =IF(K$70-$B74<=$C$69-1,$I$69*$D74,0) -> 0 | L74: =IF(L$70-$B74<=$C$69-1,$I$69*$D74,0) -> 0 | M74: =IF(M$70-$B74<=$C$69-1,$I$69*$D74,0) -> 0 | ... P74: =IF(P$70-$B74<=$C$69-1,$I$69*$D74,0) -> 0
B75: 2028 | C75: 新增数 | D75: 0 | G75: =IF(G$70-$B75<=$C$69-1,$I$69*$D75,0) -> 0 | H75: =IF(H$70-$B75<=$C$69-1,$I$69*$D75,0) -> 0 | I75: =IF(I$70-$B75<=$C$69-1,$I$69*$D75,0) -> 0 | J75: =IF(J$70-$B75<=$C$69-1,$I$69*$D75,0) -> 0 | K75: =IF(K$70-$B75<=$C$69-1,$I$69*$D75,0) -> 0 | L75: =IF(L$70-$B75<=$C$69-1,$I$69*$D75,0) -> 0 | M75: =IF(M$70-$B75<=$C$69-1,$I$69*$D75,0) -> 0 | N75: =IF(N$70-$B75<=$C$69-1,$I$69*$D75,0) -> 0 | ... P75: =IF(P$70-$B75<=$C$69-1,$I$69*$D75,0) -> 0
B76: 2029 | C76: 新增数 | D76: 0 | H76: =IF(H$70-$B76<=$C$69-1,$I$69*$D76,0) -> 0 | I76: =IF(I$70-$B76<=$C$69-1,$I$69*$D76,0) -> 0 | J76: =IF(J$70-$B76<=$C$69-1,$I$69*$D76,0) -> 0 | K76: =IF(K$70-$B76<=$C$69-1,$I$69*$D76,0) -> 0 | L76: =IF(L$70-$B76<=$C$69-1,$I$69*$D76,0) -> 0 | M76: =IF(M$70-$B76<=$C$69-1,$I$69*$D76,0) -> 0 | N76: =IF(N$70-$B76<=$C$69-1,$I$69*$D76,0) -> 0 | O76: =IF(O$70-$B76<=$C$69-1,$I$69*$D76,0) -> 0 | P76: =IF(P$70-$B76<=$C$69-1,$I$69*$D76,0) -> 0
B77: 2030 | C77: 新增数 | D77: 0 | I77: =IF(I$70-$B77<=$C$69-1,$I$69*$D77,0) -> 0 | J77: =IF(J$70-$B77<=$C$69-1,$I$69*$D77,0) -> 0 | K77: =IF(K$70-$B77<=$C$69-1,$I$69*$D77,0) -> 0 | L77: =IF(L$70-$B77<=$C$69-1,$I$69*$D77,0) -> 0 | M77: =IF(M$70-$B77<=$C$69-1,$I$69*$D77,0) -> 0 | N77: =IF(N$70-$B77<=$C$69-1,$I$69*$D77,0) -> 0 | O77: =IF(O$70-$B77<=$C$69-1,$I$69*$D77,0) -> 0 | P77: =IF(P$70-$B77<=$C$69-1,$I$69*$D77,0) -> 0
B78: 2031 | C78: 新增数 | D78: 0 | J78: =IF(J$70-$B78<=$C$69-1,$I$69*$D78,0) -> 0 | K78: =IF(K$70-$B78<=$C$69-1,$I$69*$D78,0) -> 0 | L78: =IF(L$70-$B78<=$C$69-1,$I$69*$D78,0) -> 0 | M78: =IF(M$70-$B78<=$C$69-1,$I$69*$D78,0) -> 0 | N78: =IF(N$70-$B78<=$C$69-1,$I$69*$D78,0) -> 0 | O78: =IF(O$70-$B78<=$C$69-1,$I$69*$D78,0) -> 0 | P78: =IF(P$70-$B78<=$C$69-1,$I$69*$D78,0) -> 0
B79: 2032 | C79: 新增数 | D79: 0 | K79: =IF(K$70-$B79<=$C$69-1,$I$69*$D79,0) -> 0 | L79: =IF(L$70-$B79<=$C$69-1,$I$69*$D79,0) -> 0 | M79: =IF(M$70-$B79<=$C$69-1,$I$69*$D79,0) -> 0 | N79: =IF(N$70-$B79<=$C$69-1,$I$69*$D79,0) -> 0 | O79: =IF(O$70-$B79<=$C$69-1,$I$69*$D79,0) -> 0 | P79: =IF(P$70-$B79<=$C$69-1,$I$69*$D79,0) -> 0
B80: 2033 | C80: 新增数 | D80: 0 | L80: =IF(L$70-$B80<=$C$69-1,$I$69*$D80,0) -> 0 | M80: =IF(M$70-$B80<=$C$69-1,$I$69*$D80,0) -> 0 | N80: =IF(N$70-$B80<=$C$69-1,$I$69*$D80,0) -> 0 | O80: =IF(O$70-$B80<=$C$69-1,$I$69*$D80,0) -> 0 | P80: =IF(P$70-$B80<=$C$69-1,$I$69*$D80,0) -> 0
B81: 2034 | C81: 新增数 | D81: 0 | M81: =IF(M$70-$B81<=$C$69-1,$I$69*$D81,0) -> 0 | N81: =IF(N$70-$B81<=$C$69-1,$I$69*$D81,0) -> 0 | O81: =IF(O$70-$B81<=$C$69-1,$I$69*$D81,0) -> 0 | P81: =IF(P$70-$B81<=$C$69-1,$I$69*$D81,0) -> 0
B82: 2035 | C82: 新增数 | D82: 0 | N82: =IF(N$70-$B82<=$C$69-1,$I$69*$D82,0) -> 0 | O82: =IF(O$70-$B82<=$C$69-1,$I$69*$D82,0) -> 0 | P82: =IF(P$70-$B82<=$C$69-1,$I$69*$D82,0) -> 0
B83: 2036 | C83: 新增数 | D83: 0 | O83: =IF(O$70-$B83<=$C$69-1,$I$69*$D83,0) -> 0 | P83: =IF(P$70-$B83<=$C$69-1,$I$69*$D83,0) -> 0
B84: 2037 | C84: 新增数 | D84: 0 | P84: =IF(P$70-$B84<=$C$69-1,$I$69*$D84,0) -> 0
B85: 运输设备折旧合计 | E85: =SUM(E72:E84) -> 0 | F85: =SUM(F72:F84) -> 0 | G85: =SUM(G72:G84) -> 0 | H85: =SUM(H72:H84) -> 0 | I85: =SUM(I72:I84) -> 0 | J85: =SUM(J72:J84) -> 0 | K85: =SUM(K72:K84) -> 0 | L85: =SUM(L72:L84) -> 0 | ... P85: =SUM(P72:P84) -> 0
B87: 固定资产-其他资产
B88: 折旧年限 | E88: 残值率 | H88: 折旧率 | I88: =(1-F88)/C88 -> #DIV/0!
E89: =假设表!I2 -> 2026 | F89: =假设表!J2 -> 2027 | G89: =假设表!K2 -> 2028 | H89: =假设表!L2 -> 2029 | I89: =假设表!M2 -> 2030 | J89: =假设表!N2 -> 2031 | K89: =假设表!O2 -> 2032 | L89: =假设表!P2 -> 2033 | ... P89: =假设表!T2 -> 2037
B90: 年份 | C90: 金额
B91: {=TRANSPOSE(假设表!H2:T2)} -> 2025 | C91: 期末固定资产（账面原值） | D91: {=TRANSPOSE(假设表!H90:T90)} -> 462.27066 | E91: =IF(E$89-$B91<=$C$88,$I$88*$D91,0) -> 0 | F91: =IF(F$89-$B91<=$C$88,$I$88*$D91,0) -> 0 | G91: =IF(G$89-$B91<=$C$88,$I$88*$D91,0) -> 0 | H91: =IF(H$89-$B91<=$C$88,$I$88*$D91,0) -> 0 | I91: =IF(I$89-$B91<=$C$88,$I$88*$D91,0) -> 0 | J91: =IF(J$89-$B91<=$C$88,$I$88*$D91,0) -> 0 | K91: =IF(K$89-$B91<=$C$88,$I$88*$D91,0) -> 0 | L91: =IF(L$89-$B91<=$C$88,$I$88*$D91,0) -> 0 | ... P91: =IF(P$89-$B91<=$C$88,$I$88*$D91,0) -> 0
B92: 2026 | C92: 新增数 | D92: 0 | E92: =IF(E$89-$B92<=$C$88-1,$I$88*$D92,0) -> 0 | F92: =IF(F$89-$B92<=$C$88-1,$I$88*$D92,0) -> 0 | G92: =IF(G$89-$B92<=$C$88-1,$I$88*$D92,0) -> 0 | H92: =IF(H$89-$B92<=$C$88-1,$I$88*$D92,0) -> 0 | I92: =IF(I$89-$B92<=$C$88-1,$I$88*$D92,0) -> 0 | J92: =IF(J$89-$B92<=$C$88-1,$I$88*$D92,0) -> 0 | K92: =IF(K$89-$B92<=$C$88-1,$I$88*$D92,0) -> 0 | L92: =IF(L$89-$B92<=$C$88-1,$I$88*$D92,0) -> 0 | ... P92: =IF(P$89-$B92<=$C$88-1,$I$88*$D92,0) -> 0
B93: 2027 | C93: 新增数 | D93: 0 | F93: =IF(F$89-$B93<=$C$88-1,$I$88*$D93,0) -> 0 | G93: =IF(G$89-$B93<=$C$88-1,$I$88*$D93,0) -> 0 | H93: =IF(H$89-$B93<=$C$88-1,$I$88*$D93,0) -> 0 | I93: =IF(I$89-$B93<=$C$88-1,$I$88*$D93,0) -> 0 | J93: =IF(J$89-$B93<=$C$88-1,$I$88*$D93,0) -> 0 | K93: =IF(K$89-$B93<=$C$88-1,$I$88*$D93,0) -> 0 | L93: =IF(L$89-$B93<=$C$88-1,$I$88*$D93,0) -> 0 | M93: =IF(M$89-$B93<=$C$88-1,$I$88*$D93,0) -> 0 | ... P93: =IF(P$89-$B93<=$C$88-1,$I$88*$D93,0) -> 0
B94: 2028 | C94: 新增数 | D94: 0 | G94: =IF(G$89-$B94<=$C$88-1,$I$88*$D94,0) -> 0 | H94: =IF(H$89-$B94<=$C$88-1,$I$88*$D94,0) -> 0 | I94: =IF(I$89-$B94<=$C$88-1,$I$88*$D94,0) -> 0 | J94: =IF(J$89-$B94<=$C$88-1,$I$88*$D94,0) -> 0 | K94: =IF(K$89-$B94<=$C$88-1,$I$88*$D94,0) -> 0 | L94: =IF(L$89-$B94<=$C$88-1,$I$88*$D94,0) -> 0 | M94: =IF(M$89-$B94<=$C$88-1,$I$88*$D94,0) -> 0 | N94: =IF(N$89-$B94<=$C$88-1,$I$88*$D94,0) -> 0 | ... P94: =IF(P$89-$B94<=$C$88-1,$I$88*$D94,0) -> 0
B95: 2029 | C95: 新增数 | D95: 0 | H95: =IF(H$89-$B95<=$C$88-1,$I$88*$D95,0) -> 0 | I95: =IF(I$89-$B95<=$C$88-1,$I$88*$D95,0) -> 0 | J95: =IF(J$89-$B95<=$C$88-1,$I$88*$D95,0) -> 0 | K95: =IF(K$89-$B95<=$C$88-1,$I$88*$D95,0) -> 0 | L95: =IF(L$89-$B95<=$C$88-1,$I$88*$D95,0) -> 0 | M95: =IF(M$89-$B95<=$C$88-1,$I$88*$D95,0) -> 0 | N95: =IF(N$89-$B95<=$C$88-1,$I$88*$D95,0) -> 0 | O95: =IF(O$89-$B95<=$C$88-1,$I$88*$D95,0) -> 0 | P95: =IF(P$89-$B95<=$C$88-1,$I$88*$D95,0) -> 0
B96: 2030 | C96: 新增数 | D96: 0 | I96: =IF(I$89-$B96<=$C$88-1,$I$88*$D96,0) -> 0 | J96: =IF(J$89-$B96<=$C$88-1,$I$88*$D96,0) -> 0 | K96: =IF(K$89-$B96<=$C$88-1,$I$88*$D96,0) -> 0 | L96: =IF(L$89-$B96<=$C$88-1,$I$88*$D96,0) -> 0 | M96: =IF(M$89-$B96<=$C$88-1,$I$88*$D96,0) -> 0 | N96: =IF(N$89-$B96<=$C$88-1,$I$88*$D96,0) -> 0 | O96: =IF(O$89-$B96<=$C$88-1,$I$88*$D96,0) -> 0 | P96: =IF(P$89-$B96<=$C$88-1,$I$88*$D96,0) -> 0
B97: 2031 | C97: 新增数 | D97: 0 | J97: =IF(J$89-$B97<=$C$88-1,$I$88*$D97,0) -> 0 | K97: =IF(K$89-$B97<=$C$88-1,$I$88*$D97,0) -> 0 | L97: =IF(L$89-$B97<=$C$88-1,$I$88*$D97,0) -> 0 | M97: =IF(M$89-$B97<=$C$88-1,$I$88*$D97,0) -> 0 | N97: =IF(N$89-$B97<=$C$88-1,$I$88*$D97,0) -> 0 | O97: =IF(O$89-$B97<=$C$88-1,$I$88*$D97,0) -> 0 | P97: =IF(P$89-$B97<=$C$88-1,$I$88*$D97,0) -> 0
B98: 2032 | C98: 新增数 | D98: 0 | K98: =IF(K$89-$B98<=$C$88-1,$I$88*$D98,0) -> 0 | L98: =IF(L$89-$B98<=$C$88-1,$I$88*$D98,0) -> 0 | M98: =IF(M$89-$B98<=$C$88-1,$I$88*$D98,0) -> 0 | N98: =IF(N$89-$B98<=$C$88-1,$I$88*$D98,0) -> 0 | O98: =IF(O$89-$B98<=$C$88-1,$I$88*$D98,0) -> 0 | P98: =IF(P$89-$B98<=$C$88-1,$I$88*$D98,0) -> 0
B99: 2033 | C99: 新增数 | D99: 0 | L99: =IF(L$89-$B99<=$C$88-1,$I$88*$D99,0) -> 0 | M99: =IF(M$89-$B99<=$C$88-1,$I$88*$D99,0) -> 0 | N99: =IF(N$89-$B99<=$C$88-1,$I$88*$D99,0) -> 0 | O99: =IF(O$89-$B99<=$C$88-1,$I$88*$D99,0) -> 0 | P99: =IF(P$89-$B99<=$C$88-1,$I$88*$D99,0) -> 0
B100: 2034 | C100: 新增数 | D100: 0 | M100: =IF(M$89-$B100<=$C$88-1,$I$88*$D100,0) -> 0 | N100: =IF(N$89-$B100<=$C$88-1,$I$88*$D100,0) -> 0 | O100: =IF(O$89-$B100<=$C$88-1,$I$88*$D100,0) -> 0 | P100: =IF(P$89-$B100<=$C$88-1,$I$88*$D100,0) -> 0
B101: 2035 | C101: 新增数 | D101: 0 | N101: =IF(N$89-$B101<=$C$88-1,$I$88*$D101,0) -> 0 | O101: =IF(O$89-$B101<=$C$88-1,$I$88*$D101,0) -> 0 | P101: =IF(P$89-$B101<=$C$88-1,$I$88*$D101,0) -> 0
B102: 2036 | C102: 新增数 | D102: 0 | O102: =IF(O$89-$B102<=$C$88-1,$I$88*$D102,0) -> 0 | P102: =IF(P$89-$B102<=$C$88-1,$I$88*$D102,0) -> 0
B103: 2037 | C103: 新增数 | D103: 0 | P103: =IF(P$89-$B103<=$C$88-1,$I$88*$D103,0) -> 0
B104: 其他资产折旧合计 | E104: =SUM(E91:E103) -> 0 | F104: =SUM(F91:F103) -> 0 | G104: =SUM(G91:G103) -> 0 | H104: =SUM(H91:H103) -> 0 | I104: =SUM(I91:I103) -> 0 | J104: =SUM(J91:J103) -> 0 | K104: =SUM(K91:K103) -> 0 | L104: =SUM(L91:L103) -> 0 | ... P104: =SUM(P91:P103) -> 0
B106: 固定资产-在建工程转入
B107: 折旧年限 | E107: 残值率 | H107: 折旧率 | I107: =(1-F107)/C107 -> #DIV/0!
...

Sheet 历史数据及预测表
B2: 资产负债表
D3: 历史数据 | I3: 预测数据
D4: =历史数据!C1 -> 2021 | E4: =历史数据!D1 -> 2022 | F4: =历史数据!E1 -> 2023 | G4: =历史数据!F1 -> 2024 | H4: =历史数据!G1 -> 2025 | I4: =H4+1 -> 2026 | J4: =I4+1 -> 2027 | K4: =J4+1 -> 2028 | L4: =K4+1 -> 2029 | M4: =L4+1 -> 2030 | N4: =M4+1 -> 2031 | O4: =N4+1 -> 2032 | P4: =O4+1 -> 2033 | ... T4: =S4+1 -> 2037
B5: 资产
C6: 流动资产
C7: 货币资金 | D7: =历史数据!C57 -> 2918.5158 | E7: =历史数据!D57 -> 3400.7506 | F7: =历史数据!E57 -> 3927.2711 | G7: =历史数据!F57 -> 3716.6476 | H7: =历史数据!G57 -> 4091.6442 | I7: =历史数据及预测表!$I$184 -> 7233.5472 | J7: =历史数据及预测表!$J$184 -> 9237.1612 | K7: =历史数据及预测表!$K$184 -> 10880.219 | L7: =历史数据及预测表!$L$184 -> 12824.764 | M7: =历史数据及预测表!$M$184 -> 15532.667 | N7: =历史数据及预测表!$N$184 -> 18472.132 | O7: =历史数据及预测表!$O$184 -> 22038.142 | P7: =历史数据及预测表!$P$184 -> 26397.559 | Q7: =历史数据及预测表!$Q$184 -> 31501.991 | R7: =历史数据及预测表!$R$184 -> 37636.784 | S7: =历史数据及预测表!$S$184 -> 44962.156 | T7: =历史数据及预测表!$T$184 -> 53713.29
C8: 交易性金融资产 | D8: =历史数据!C60 -> 962.22328 | E8: =历史数据!D60 -> 350.6068 | F8: =历史数据!E60 -> 393.86513 | G8: =历史数据!F60 -> 757.73708 | H8: =历史数据!G60 -> 899.70457 | I8: =假设表!I33+历史数据及预测表!H8 -> 899.70457 | J8: =假设表!J33+历史数据及预测表!I8 -> 899.70457 | K8: =假设表!K33+历史数据及预测表!J8 -> 899.70457 | L8: =假设表!L33+历史数据及预测表!K8 -> 899.70457 | M8: =假设表!M33+历史数据及预测表!L8 -> 899.70457 | N8: =假设表!N33+历史数据及预测表!M8 -> 899.70457 | O8: =假设表!O33+历史数据及预测表!N8 -> 899.70457 | P8: =假设表!P33+历史数据及预测表!O8 -> 899.70457 | ... T8: =假设表!T33+历史数据及预测表!S8 -> 899.70457
C9: 衍生金融资产 | D9: =历史数据!C61 -> 0 | E9: =历史数据!D61 -> 0 | F9: =历史数据!E61 -> 0 | G9: =历史数据!F61 -> 0 | H9: =历史数据!G61 -> 0 | I9: =假设表!I34+历史数据及预测表!H9 -> 0 | J9: =假设表!J34+历史数据及预测表!I9 -> 0 | K9: =假设表!K34+历史数据及预测表!J9 -> 0 | L9: =假设表!L34+历史数据及预测表!K9 -> 0 | M9: =假设表!M34+历史数据及预测表!L9 -> 0 | N9: =假设表!N34+历史数据及预测表!M9 -> 0 | O9: =假设表!O34+历史数据及预测表!N9 -> 0 | P9: =假设表!P34+历史数据及预测表!O9 -> 0 | ... T9: =假设表!T34+历史数据及预测表!S9 -> 0
C10: 应收账款净值 | D10: =历史数据!C62 -> 658.22891 | E10: =历史数据!D62 -> 515.98074 | F10: =历史数据!E62 -> 403.3488 | G10: =历史数据!F62 -> 388.72856 | H10: =历史数据!G62 -> 466.53246 | I10: =I189-I190 -> 774.57337 | J10: =J189-J190 -> 1002.5153 | K10: =K189-K190 -> 1195.3502 | L10: =L189-L190 -> 1391.3699 | M10: =M189-M190 -> 1692.457 | N10: =N189-N190 -> 2015.4017 | O10: =O189-O190 -> 2398.9017 | P10: =P189-P190 -> 2876.6152 | ... T10: =T189-T190 -> 5851.1979
C11: 应收票据 | D11: =历史数据!C63 -> 2.7023688 | E11: =历史数据!D63 -> 4.4419726 | F11: =历史数据!E63 -> 3.9836842 | G11: =历史数据!F63 -> 2.2228317 | H11: =历史数据!G63 -> 4.2487961 | I11: =假设表!I37*历史数据及预测表!I107 -> 6.3778215 | J11: =假设表!J37*历史数据及预测表!J107 -> 7.7383766 | K11: =假设表!K37*历史数据及预测表!K107 -> 9.9977593 | L11: =假设表!L37*历史数据及预测表!L107 -> 11.278008 | M11: =假设表!M37*历史数据及预测表!M107 -> 13.647368 | N11: =假设表!N37*历史数据及预测表!N107 -> 16.482406 | O11: =假设表!O37*历史数据及预测表!O107 -> 19.469197 | P11: =假设表!P37*历史数据及预测表!P107 -> 23.355996 | ... T11: =假设表!T37*历史数据及预测表!T107 -> 47.537
C12: 应收款项融资 | D12: =历史数据!C64 -> 0 | E12: =历史数据!D64 -> 0 | F12: =历史数据!E64 -> 0 | G12: =历史数据!F64 -> 0 | H12: =历史数据!G64 -> 0 | I12: =假设表!I38*历史数据及预测表!I107 -> 0 | J12: =假设表!J38*历史数据及预测表!J107 -> 0 | K12: =假设表!K38*历史数据及预测表!K107 -> 0 | L12: =假设表!L38*历史数据及预测表!L107 -> 0 | M12: =假设表!M38*历史数据及预测表!M107 -> 0 | N12: =假设表!N38*历史数据及预测表!N107 -> 0 | O12: =假设表!O38*历史数据及预测表!O107 -> 0 | P12: =假设表!P38*历史数据及预测表!P107 -> 0 | ... T12: =假设表!T38*历史数据及预测表!T107 -> 0
C13: 预付款项 | D13: =历史数据!C65 -> 29.270319 | E13: =历史数据!D65 -> 54.214688 | F13: =历史数据!E65 -> 69.007066 | G13: =历史数据!F65 -> 89.784503 | H13: =历史数据!G65 -> 157.53618 | I13: =假设表!I39*历史数据及预测表!I110 -> 150.99387 | J13: =假设表!J39*历史数据及预测表!J110 -> 226.59477 | K13: =假设表!K39*历史数据及预测表!K110 -> 312.13543 | L13: =假设表!L39*历史数据及预测表!L110 -> 350.13373 | M13: =假设表!M39*历史数据及预测表!M110 -> 416.76519 | N13: =假设表!N39*历史数据及预测表!N110 -> 510.03707 | O13: =假设表!O39*历史数据及预测表!O110 -> 600.61797 | P13: =假设表!P39*历史数据及预测表!P110 -> 718.8644 | ... T13: =假设表!T39*历史数据及预测表!T110 -> 1465.5134
C14: 其他应收款净值 | D14: =历史数据!C69 -> 94.215122 | E14: =历史数据!D69 -> 101.89745 | F14: =历史数据!E69 -> 284.03853 | G14: =历史数据!F69 -> 284.81772 | H14: =历史数据!G69 -> 1.6572252 | I14: =历史数据及预测表!I192-历史数据及预测表!I193 -> 361.80355 | J14: =历史数据及预测表!J192-历史数据及预测表!J193 -> 393.74565 | K14: =历史数据及预测表!K192-历史数据及预测表!K193 -> 338.50545 | L14: =历史数据及预测表!L192-历史数据及预测表!L193 -> 529.16017 | M14: =历史数据及预测表!M192-历史数据及预测表!M193 -> 595.53373 | N14: =历史数据及预测表!N192-历史数据及预测表!N193 -> 681.77988 | O14: =历史数据及预测表!O192-历史数据及预测表!O193 -> 855.89963 | P14: =历史数据及预测表!P192-历史数据及预测表!P193 -> 1003.8733 | ... T14: =历史数据及预测表!T192-历史数据及预测表!T193 -> 2055.2742
C15: 存货净值 | D15: =历史数据!C71 -> 1419.4021 | E15: =历史数据!D71 -> 2303.8367 | F15: =历史数据!E71 -> 2404.7808 | G15: =历史数据!F71 -> 2672.0205 | H15: =历史数据!G71 -> 2974.6471 | I15: =I195-I196 -> 3145.0437 | J15: =J195-J196 -> 4252.8445 | K15: =K195-K196 -> 5562.9774 | L15: =L195-L196 -> 6673.4392 | M15: =M195-M196 -> 7724.6957 | N15: =N195-N196 -> 9414.4185 | O15: =O195-O196 -> 11219.847 | P15: =P195-P196 -> 13340.284 | ... T15: =T195-T196 -> 27259.725
C16: 合同资产 | D16: =历史数据!C73 -> 0 | E16: =历史数据!D73 -> 0 | F16: =历史数据!E73 -> 0 | G16: =历史数据!F73 -> 0 | H16: =历史数据!G73 -> 0 | I16: =I198-I199 -> 0 | J16: =J198-J199 -> 0 | K16: =K198-K199 -> 0 | L16: =L198-L199 -> 0 | M16: =M198-M199 -> 0 | N16: =N198-N199 -> 0 | O16: =O198-O199 -> 0 | P16: =P198-P199 -> 0 | ... T16: =T198-T199 -> 0
C17: 持有待售资产 | D17: =历史数据!C74 -> 0 | E17: =历史数据!D74 -> 0 | F17: =历史数据!E74 -> 0 | G17: =历史数据!F74 -> 0 | H17: =历史数据!G74 -> 0 | I17: =假设表!I46+历史数据及预测表!H17 -> 0 | J17: =假设表!J46+历史数据及预测表!I17 -> 0 | K17: =假设表!K46+历史数据及预测表!J17 -> 0 | L17: =假设表!L46+历史数据及预测表!K17 -> 0 | M17: =假设表!M46+历史数据及预测表!L17 -> 0 | N17: =假设表!N46+历史数据及预测表!M17 -> 0 | O17: =假设表!O46+历史数据及预测表!N17 -> 0 | P17: =假设表!P46+历史数据及预测表!O17 -> 0 | ... T17: =假设表!T46+历史数据及预测表!S17 -> 0
C18: 一年内到期的非流动资产 | D18: =历史数据!C75 -> 0 | E18: =历史数据!D75 -> 0 | F18: =历史数据!E75 -> 0 | G18: =历史数据!F75 -> 43.804255 | H18: =历史数据!G75 -> 0 | I18: =假设表!I47+历史数据及预测表!H18 -> 0 | J18: =假设表!J47+历史数据及预测表!I18 -> 0 | K18: =假设表!K47+历史数据及预测表!J18 -> 0 | L18: =假设表!L47+历史数据及预测表!K18 -> 0 | M18: =假设表!M47+历史数据及预测表!L18 -> 0 | N18: =假设表!N47+历史数据及预测表!M18 -> 0 | O18: =假设表!O47+历史数据及预测表!N18 -> 0 | P18: =假设表!P47+历史数据及预测表!O18 -> 0 | ... T18: =假设表!T47+历史数据及预测表!S18 -> 0
C19: 待摊费用 | D19: =历史数据!C76 -> 0 | E19: =历史数据!D76 -> 0 | F19: =历史数据!E76 -> 0 | G19: =历史数据!F76 -> 0 | H19: =历史数据!G76 -> 0 | I19: =假设表!I48*历史数据及预测表!I107 -> 0 | J19: =假设表!J48*历史数据及预测表!J107 -> 0 | K19: =假设表!K48*历史数据及预测表!K107 -> 0 | L19: =假设表!L48*历史数据及预测表!L107 -> 0 | M19: =假设表!M48*历史数据及预测表!M107 -> 0 | N19: =假设表!N48*历史数据及预测表!N107 -> 0 | O19: =假设表!O48*历史数据及预测表!O107 -> 0 | P19: =假设表!P48*历史数据及预测表!P107 -> 0 | ... T19: =假设表!T48*历史数据及预测表!T107 -> 0
C20: 其他流动资产 | D20: =历史数据!C77 -> 45.749648 | E20: =历史数据!D77 -> 63.361565 | F20: =历史数据!E77 -> 96.716587 | G20: =历史数据!F77 -> 92.692404 | H20: =历史数据!G77 -> 97.386626 | I20: =假设表!I49+历史数据及预测表!H20 -> 97.386626 | J20: =假设表!J49+历史数据及预测表!I20 -> 97.386626 | K20: =假设表!K49+历史数据及预测表!J20 -> 97.386626 | L20: =假设表!L49+历史数据及预测表!K20 -> 97.386626 | M20: =假设表!M49+历史数据及预测表!L20 -> 97.386626 | N20: =假设表!N49+历史数据及预测表!M20 -> 97.386626 | O20: =假设表!O49+历史数据及预测表!N20 -> 97.386626 | P20: =假设表!P49+历史数据及预测表!O20 -> 97.386626 | ... T20: =假设表!T49+历史数据及预测表!S20 -> 97.386626
C21: 其他金融类流动资产 | D21: =历史数据!C58+历史数据!C59+历史数据!C66+历史数据!C67+历史数据!C68+历史数据!C70 -> 0 | E21: =历史数据!D58+历史数据!D59+历史数据!D66+历史数据!D67+历史数据!D68+历史数据!D70 -> 0 | F21: =历史数据!E58+历史数据!E59+历史数据!E66+历史数据!E67+历史数据!E68+历史数据!E70 -> 0 | G21: =历史数据!F58+历史数据!F59+历史数据!F66+历史数据!F67+历史数据!F68+历史数据!F70 -> 0 | H21: =历史数据!G58+历史数据!G59+历史数据!G66+历史数据!G67+历史数据!G68+历史数据!G70 -> 0 | I21: =假设表!I50+历史数据及预测表!H21 -> 0 | J21: =假设表!J50+历史数据及预测表!I21 -> 0 | K21: =假设表!K50+历史数据及预测表!J21 -> 0 | L21: =假设表!L50+历史数据及预测表!K21 -> 0 | M21: =假设表!M50+历史数据及预测表!L21 -> 0 | N21: =假设表!N50+历史数据及预测表!M21 -> 0 | O21: =假设表!O50+历史数据及预测表!N21 -> 0 | P21: =假设表!P50+历史数据及预测表!O21 -> 0 | ... T21: =假设表!T50+历史数据及预测表!S21 -> 0
C22: 流动资产差额 | D22: =历史数据!C78 -> 0 | E22: =历史数据!D78 -> 0 | F22: =历史数据!E78 -> 0 | G22: =历史数据!F78 -> 0 | H22: =历史数据!G78 -> 0 | I22: =H22 -> 0 | J22: =I22 -> 0 | K22: =J22 -> 0 | L22: =K22 -> 0 | M22: =L22 -> 0 | N22: =M22 -> 0 | O22: =N22 -> 0 | P22: =O22 -> 0 | ... T22: =S22 -> 0
C23: 流动资产合计 | D23: =SUM(D7:D22) -> 6130.3076 | E23: =SUM(E7:E22) -> 6795.0905 | F23: =SUM(F7:F22) -> 7583.0116 | G23: =SUM(G7:G22) -> 8048.4555 | H23: =SUM(H7:H22) -> 8693.3572 | I23: =SUM(I7:I22) -> 12669.431 | J23: =SUM(J7:J22) -> 16117.691 | K23: =SUM(K7:K22) -> 19296.276 | ... T23: =SUM(T7:T22) -> 91389.629
C24: 非流动资产
C25: 可供出售金融资产 | D25: =历史数据!C84 -> 0 | E25: =历史数据!D84 -> 0 | F25: =历史数据!E84 -> 0 | G25: =历史数据!F84 -> 0 | H25: =历史数据!G84 -> 0 | I25: =假设表!I77+历史数据及预测表!H25 -> 0 | J25: =假设表!J77+历史数据及预测表!I25 -> 0 | K25: =假设表!K77+历史数据及预测表!J25 -> 0 | L25: =假设表!L77+历史数据及预测表!K25 -> 0 | M25: =假设表!M77+历史数据及预测表!L25 -> 0 | N25: =假设表!N77+历史数据及预测表!M25 -> 0 | O25: =假设表!O77+历史数据及预测表!N25 -> 0 | P25: =假设表!P77+历史数据及预测表!O25 -> 0 | ... T25: =假设表!T77+历史数据及预测表!S25 -> 0
C26: 债权投资 | D26: =历史数据!C82 -> 0 | E26: =历史数据!D82 -> 0 | F26: =历史数据!E82 -> 0 | G26: =历史数据!F82 -> 0 | H26: =历史数据!G82 -> 0 | I26: =假设表!I79+历史数据及预测表!H26-假设表!I113 -> 0 | J26: =假设表!J79+历史数据及预测表!I26-假设表!J113 -> 0 | K26: =假设表!K79+历史数据及预测表!J26-假设表!K113 -> 0 | L26: =假设表!L79+历史数据及预测表!K26-假设表!L113 -> 0 | M26: =假设表!M79+历史数据及预测表!L26-假设表!M113 -> 0 | N26: =假设表!N79+历史数据及预测表!M26-假设表!N113 -> 0 | O26: =假设表!O79+历史数据及预测表!N26-假设表!O113 -> 0 | P26: =假设表!P79+历史数据及预测表!O26-假设表!P113 -> 0 | ... T26: =假设表!T79+历史数据及预测表!S26-假设表!T113 -> 0
C27: 其他债权投资 | D27: =历史数据!C83 -> 0 | E27: =历史数据!D83 -> 0 | F27: =历史数据!E83 -> 0 | G27: =历史数据!F83 -> 0 | H27: =历史数据!G83 -> 0 | I27: =假设表!I80+历史数据及预测表!H27-假设表!I114 -> 0 | J27: =假设表!J80+历史数据及预测表!I27-假设表!J114 -> 0 | K27: =假设表!K80+历史数据及预测表!J27-假设表!K114 -> 0 | L27: =假设表!L80+历史数据及预测表!K27-假设表!L114 -> 0 | M27: =假设表!M80+历史数据及预测表!L27-假设表!M114 -> 0 | N27: =假设表!N80+历史数据及预测表!M27-假设表!N114 -> 0 | O27: =假设表!O80+历史数据及预测表!N27-假设表!O114 -> 0 | P27: =假设表!P80+历史数据及预测表!O27-假设表!P114 -> 0 | ... T27: =假设表!T80+历史数据及预测表!S27-假设表!T114 -> 0
C28: 持有至到期投资 | D28: =历史数据!C85 -> 0 | E28: =历史数据!D85 -> 0 | F28: =历史数据!E85 -> 0 | G28: =历史数据!F85 -> 0 | H28: =历史数据!G85 -> 0 | I28: =假设表!I78+历史数据及预测表!H28 -> 0 | J28: =假设表!J78+历史数据及预测表!I28 -> 0 | K28: =假设表!K78+历史数据及预测表!J28 -> 0 | L28: =假设表!L78+历史数据及预测表!K28 -> 0 | M28: =假设表!M78+历史数据及预测表!L28 -> 0 | N28: =假设表!N78+历史数据及预测表!M28 -> 0 | O28: =假设表!O78+历史数据及预测表!N28 -> 0 | P28: =假设表!P78+历史数据及预测表!O28 -> 0 | ... T28: =假设表!T78+历史数据及预测表!S28 -> 0
C29: 长期应收款 | D29: =历史数据!C86 -> 522.28476 | E29: =历史数据!D86 -> 393.13122 | F29: =历史数据!E86 -> 222.03931 | G29: =历史数据!F86 -> 0 | H29: =历史数据!G86 -> 0 | I29: =假设表!I81+历史数据及预测表!H29 -> 0 | J29: =假设表!J81+历史数据及预测表!I29 -> 0 | K29: =假设表!K81+历史数据及预测表!J29 -> 0 | L29: =假设表!L81+历史数据及预测表!K29 -> 0 | M29: =假设表!M81+历史数据及预测表!L29 -> 0 | N29: =假设表!N81+历史数据及预测表!M29 -> 0 | O29: =假设表!O81+历史数据及预测表!N29 -> 0 | P29: =假设表!P81+历史数据及预测表!O29 -> 0 | ... T29: =假设表!T81+历史数据及预测表!S29 -> 0
C30: 长期股权投资净值 | D30: =历史数据!C87 -> 1.9033082 | E30: =历史数据!D87 -> 1.8498278 | F30: =历史数据!E87 -> 0.94107066 | G30: =历史数据!F87 -> 0.58587464 | H30: =历史数据!G87 -> 0.84342957 | I30: =假设表!I82+历史数据及预测表!H30-假设表!I104 -> 0.84342957 | J30: =假设表!J82+历史数据及预测表!I30-假设表!J104 -> 0.84342957 | K30: =假设表!K82+历史数据及预测表!J30-假设表!K104 -> 0.84342957 | L30: =假设表!L82+历史数据及预测表!K30-假设表!L104 -> 0.84342957 | M30: =假设表!M82+历史数据及预测表!L30-假设表!M104 -> 0.84342957 | N30: =假设表!N82+历史数据及预测表!M30-假设表!N104 -> 0.84342957 | O30: =假设表!O82+历史数据及预测表!N30-假设表!O104 -> 0.84342957 | P30: =假设表!P82+历史数据及预测表!O30-假设表!P104 -> 0.84342957 | ... T30: =假设表!T82+历史数据及预测表!S30-假设表!T104 -> 0.84342957
C31: 其他权益工具投资 | D31: =历史数据!C88 -> 153.4901 | E31: =历史数据!D88 -> 325.61671 | F31: =历史数据!E88 -> 427.81287 | G31: =历史数据!F88 -> 547.52302 | H31: =历史数据!G88 -> 648.16736 | I31: =假设表!I83+历史数据及预测表!H31 -> 755.68424 | J31: =假设表!J83+历史数据及预测表!I31 -> 864.9747 | K31: =假设表!K83+历史数据及预测表!J31 -> 970.79193 | L31: =假设表!L83+历史数据及预测表!K31 -> 1078.3335 | M31: =假设表!M83+历史数据及预测表!L31 -> 1185.8832 | N31: =假设表!N83+历史数据及预测表!M31 -> 1292.8527 | O31: =假设表!O83+历史数据及预测表!N31 -> 1400.2063 | P31: =假设表!P83+历史数据及预测表!O31 -> 1507.4972 | ... T31: =假设表!T83+历史数据及预测表!S31 -> 1936.5511
C32: 其他非流动金融资产 | D32: =历史数据!C89 -> 0 | E32: =历史数据!D89 -> 0 | F32: =历史数据!E89 -> 0 | G32: =历史数据!F89 -> 0 | H32: =历史数据!G89 -> 0 | I32: =假设表!I84+历史数据及预测表!H32 -> 0 | J32: =假设表!J84+历史数据及预测表!I32 -> 0 | K32: =假设表!K84+历史数据及预测表!J32 -> 0 | L32: =假设表!L84+历史数据及预测表!K32 -> 0 | M32: =假设表!M84+历史数据及预测表!L32 -> 0 | N32: =假设表!N84+历史数据及预测表!M32 -> 0 | O32: =假设表!O84+历史数据及预测表!N32 -> 0 | P32: =假设表!P84+历史数据及预测表!O32 -> 0 | ... T32: =假设表!T84+历史数据及预测表!S32 -> 0
C33: 投资性房地产 | D33: =历史数据!C90 -> 29.402909 | E33: =历史数据!D90 -> 28.665984 | F33: =历史数据!E90 -> 79.583366 | G33: =历史数据!F90 -> 83.488206 | H33: =历史数据!G90 -> 83.174294 | I33: =假设表!I85+历史数据及预测表!H33 -> 83.174294 | J33: =假设表!J85+历史数据及预测表!I33 -> 83.174294 | K33: =假设表!K85+历史数据及预测表!J33 -> 83.174294 | L33: =假设表!L85+历史数据及预测表!K33 -> 83.174294 | M33: =假设表!M85+历史数据及预测表!L33 -> 83.174294 | N33: =假设表!N85+历史数据及预测表!M33 -> 83.174294 | O33: =假设表!O85+历史数据及预测表!N33 -> 83.174294 | P33: =假设表!P85+历史数据及预测表!O33 -> 83.174294 | ... T33: =假设表!T85+历史数据及预测表!S33 -> 83.174294
C34: 固定资产净值 | D34: =历史数据!C91 -> 378.43933 | E34: =历史数据!D91 -> 367.42647 | F34: =历史数据!E91 -> 451.35212 | G34: =历史数据!F91 -> 467.43575 | H34: =历史数据!G91 -> 462.27066 | I34: =关键项目预测!E140 -> 599.35495 | J34: =关键项目预测!F140 -> 717.43923 | K34: =关键项目预测!G140 -> 816.52352 | L34: =关键项目预测!H140 -> 896.60781 | M34: =关键项目预测!I140 -> 957.6921 | N34: =关键项目预测!J140 -> 999.77638 | O34: =关键项目预测!K140 -> 1022.8607 | P34: =关键项目预测!L140 -> 1026.945 | ... T34: =关键项目预测!P140 -> 998.11353
C35: 在建工程 | D35: =历史数据!C92 -> 111.59124 | E35: =历史数据!D92 -> 133.4762 | F35: =历史数据!E92 -> 4.0672206 | G35: =历史数据!F92 -> 1.3266624 | H35: =历史数据!G92 -> 9.6800071 | I35: =关键项目预测!E147 -> 9.6800071 | J35: =关键项目预测!F147 -> 9.6800071 | K35: =关键项目预测!G147 -> 9.6800071 | L35: =关键项目预测!H147 -> 9.6800071 | M35: =关键项目预测!I147 -> 9.6800071 | N35: =关键项目预测!J147 -> 9.6800071 | O35: =关键项目预测!K147 -> 9.6800071 | P35: =关键项目预测!L147 -> 9.6800071 | ... T35: =关键项目预测!P147 -> 9.6800071
C36: 生产性生物资产 | D36: =历史数据!C93 -> 0 | E36: =历史数据!D93 -> 0 | F36: =历史数据!E93 -> 0 | G36: =历史数据!F93 -> 0 | H36: =历史数据!G93 -> 0 | I36: =关键项目预测!E199 -> 0 | J36: =关键项目预测!F199 -> 0 | K36: =关键项目预测!G199 -> 0 | L36: =关键项目预测!H199 -> 0 | M36: =关键项目预测!I199 -> 0 | N36: =关键项目预测!J199 -> 0 | O36: =关键项目预测!K199 -> 0 | P36: =关键项目预测!L199 -> 0 | ... T36: =关键项目预测!P199 -> 0
C37: 油气资产 | D37: =历史数据!C94 -> 0 | E37: =历史数据!D94 -> 0 | F37: =历史数据!E94 -> 0 | G37: =历史数据!F94 -> 0 | H37: =历史数据!G94 -> 0 | I37: =关键项目预测!E225 -> 0 | J37: =关键项目预测!F225 -> 0 | K37: =关键项目预测!G225 -> 0 | L37: =关键项目预测!H225 -> 0 | M37: =关键项目预测!I225 -> 0 | N37: =关键项目预测!J225 -> 0 | O37: =关键项目预测!K225 -> 0 | P37: =关键项目预测!L225 -> 0 | ... T37: =关键项目预测!P225 -> 0
C38: 无形资产净值 | D38: =历史数据!C96 -> 778.57946 | E38: =历史数据!D96 -> 720.85174 | F38: =历史数据!E96 -> 644.58523 | G38: =历史数据!F96 -> 554.23946 | H38: =历史数据!G96 -> 467.16111 | I38: =关键项目预测!E239 -> 467.16111 | J38: =关键项目预测!F239 -> 467.16111 | K38: =关键项目预测!G239 -> 467.16111 | L38: =关键项目预测!H239 -> 467.16111 | M38: =关键项目预测!I239 -> 467.16111 | N38: =关键项目预测!J239 -> 467.16111 | O38: =关键项目预测!K239 -> 467.16111 | P38: =关键项目预测!L239 -> 467.16111 | ... T38: =关键项目预测!P239 -> 467.16111
C39: 使用权资产 | D39: =历史数据!C95 -> 14.418877 | E39: =历史数据!D95 -> 14.735646 | F39: =历史数据!E95 -> 31.789418 | G39: =历史数据!F95 -> 22.866891 | H39: =历史数据!G95 -> 16.938199 | I39: =关键项目预测!E173 -> 16.938199 | J39: =关键项目预测!F173 -> 16.938199 | K39: =关键项目预测!G173 -> 16.938199 | L39: =关键项目预测!H173 -> 16.938199 | M39: =关键项目预测!I173 -> 16.938199 | N39: =关键项目预测!J173 -> 16.938199 | O39: =关键项目预测!K173 -> 16.938199 | P39: =关键项目预测!L173 -> 16.938199 | ... T39: =关键项目预测!P173 -> 16.938199
C40: 开发支出 | D40: =历史数据!C97 -> 98.804344 | E40: =历史数据!D97 -> 82.689958 | F40: =历史数据!E97 -> 46.655254 | G40: =历史数据!F97 -> 55.854249 | H40: =历史数据!G97 -> 37.254587 | I40: =假设表!I99+历史数据及预测表!H40 -> 37.254587 | J40: =假设表!J99+历史数据及预测表!I40 -> 37.254587 | K40: =假设表!K99+历史数据及预测表!J40 -> 37.254587 | L40: =假设表!L99+历史数据及预测表!K40 -> 37.254587 | M40: =假设表!M99+历史数据及预测表!L40 -> 37.254587 | N40: =假设表!N99+历史数据及预测表!M40 -> 37.254587 | O40: =假设表!O99+历史数据及预测表!N40 -> 37.254587 | P40: =假设表!P99+历史数据及预测表!O40 -> 37.254587 | ... T40: =假设表!T99+历史数据及预测表!S40 -> 37.254587
C41: 商誉 | D41: =历史数据!C98 -> 3007.7843 | E41: =历史数据!D98 -> 3007.7843 | F41: =历史数据!E98 -> 3007.7843 | G41: =历史数据!F98 -> 3007.7843 | H41: =历史数据!G98 -> 3007.7843 | I41: =假设表!I100+历史数据及预测表!H41-假设表!I112 -> 3007.7843 | J41: =假设表!J100+历史数据及预测表!I41-假设表!J112 -> 3007.7843 | K41: =假设表!K100+历史数据及预测表!J41-假设表!K112 -> 3007.7843 | L41: =假设表!L100+历史数据及预测表!K41-假设表!L112 -> 3007.7843 | M41: =假设表!M100+历史数据及预测表!L41-假设表!M112 -> 3007.7843 | N41: =假设表!N100+历史数据及预测表!M41-假设表!N112 -> 3007.7843 | O41: =假设表!O100+历史数据及预测表!N41-假设表!O112 -> 3007.7843 | P41: =假设表!P100+历史数据及预测表!O41-假设表!P112 -> 3007.7843 | ... T41: =假设表!T100+历史数据及预测表!S41-假设表!T112 -> 3007.7843
C42: 长期待摊费用 | D42: =历史数据!C99 -> 5.2319249 | E42: =历史数据!D99 -> 3.1237062 | F42: =历史数据!E99 -> 0 | G42: =历史数据!F99 -> 0 | H42: =历史数据!G99 -> 0 | I42: =关键项目预测!E232 -> 0 | J42: =关键项目预测!F232 -> 0 | K42: =关键项目预测!G232 -> 0 | L42: =关键项目预测!H232 -> 0 | M42: =关键项目预测!I232 -> 0 | N42: =关键项目预测!J232 -> 0 | O42: =关键项目预测!K232 -> 0 | P42: =关键项目预测!L232 -> 0 | ... T42: =关键项目预测!P232 -> 0
C43: 递延所得税资产 | D43: =历史数据!C100 -> 90.37692 | E43: =历史数据!D100 -> 119.25676 | F43: =历史数据!E100 -> 134.87176 | G43: =历史数据!F100 -> 129.08562 | H43: =历史数据!G100 -> 132.53018 | I43: =假设表!I51+历史数据及预测表!H43 -> 132.53018 | J43: =假设表!J51+历史数据及预测表!I43 -> 132.53018 | K43: =假设表!K51+历史数据及预测表!J43 -> 132.53018 | L43: =假设表!L51+历史数据及预测表!K43 -> 132.53018 | M43: =假设表!M51+历史数据及预测表!L43 -> 132.53018 | N43: =假设表!N51+历史数据及预测表!M43 -> 132.53018 | O43: =假设表!O51+历史数据及预测表!N43 -> 132.53018 | P43: =假设表!P51+历史数据及预测表!O43 -> 132.53018 | ... T43: =假设表!T51+历史数据及预测表!S43 -> 132.53018
C44: 其他非流动资产 | D44: =历史数据!C101 -> 12.411178 | E44: =历史数据!D101 -> 428.13758 | F44: =历史数据!E101 -> 107.53338 | G44: =历史数据!F101 -> 8.2995697 | H44: =历史数据!G101 -> 14.043961 | I44: =假设表!I52+历史数据及预测表!H44 -> 14.043961 | J44: =假设表!J52+历史数据及预测表!I44 -> 14.043961 | K44: =假设表!K52+历史数据及预测表!J44 -> 14.043961 | L44: =假设表!L52+历史数据及预测表!K44 -> 14.043961 | M44: =假设表!M52+历史数据及预测表!L44 -> 14.043961 | N44: =假设表!N52+历史数据及预测表!M44 -> 14.043961 | O44: =假设表!O52+历史数据及预测表!N44 -> 14.043961 | P44: =假设表!P52+历史数据及预测表!O44 -> 14.043961 | ... T44: =假设表!T52+历史数据及预测表!S44 -> 14.043961
C45: 发放贷款及垫款 | D45: =历史数据!C81 -> 0 | E45: =历史数据!D81 -> 0 | F45: =历史数据!E81 -> 0 | G45: =历史数据!F81 -> 0 | H45: =历史数据!G81 -> 0 | I45: =假设表!I53+历史数据及预测表!H45 -> 0 | J45: =假设表!J53+历史数据及预测表!I45 -> 0 | K45: =假设表!K53+历史数据及预测表!J45 -> 0 | L45: =假设表!L53+历史数据及预测表!K45 -> 0 | M45: =假设表!M53+历史数据及预测表!L45 -> 0 | N45: =假设表!N53+历史数据及预测表!M45 -> 0 | O45: =假设表!O53+历史数据及预测表!N45 -> 0 | P45: =假设表!P53+历史数据及预测表!O45 -> 0 | ... T45: =假设表!T53+历史数据及预测表!S45 -> 0
C46: 非流动资产差额 | D46: =历史数据!C102 -> 0 | E46: =历史数据!D102 -> 0 | F46: =历史数据!E102 -> 0 | G46: =历史数据!F102 -> 0 | H46: =历史数据!G102 -> 0 | I46: =H46 -> 0 | J46: =I46 -> 0 | K46: =J46 -> 0 | L46: =K46 -> 0 | M46: =L46 -> 0 | N46: =M46 -> 0 | O46: =N46 -> 0 | P46: =O46 -> 0 | ... T46: =S46 -> 0
C47: 非流动资产合计 | D47: =SUM(D25:D46) -> 5204.7186 | E47: =SUM(E25:E46) -> 5626.7461 | F47: =SUM(F25:F46) -> 5159.0153 | G47: =SUM(G25:G46) -> 4878.4896 | H47: =SUM(H25:H46) -> 4879.8481 | I47: =SUM(I25:I46) -> 5124.4493 | J47: =SUM(J25:J46) -> 5351.824 | K47: =SUM(K25:K46) -> 5556.7255 | ... T47: =SUM(T25:T46) -> 6704.0747
C48: 资产总计 | D48: =D23+D47 -> 11335.026 | E48: =E23+E47 -> 12421.837 | F48: =F23+F47 -> 12742.027 | G48: =G23+G47 -> 12926.945 | H48: =H23+H47 -> 13573.205 | I48: =I23+I47 -> 17793.88 | J48: =J23+J47 -> 21469.515 | K48: =K23+K47 -> 24853.001 | ... T48: =T23+T47 -> 98093.703
C50: 流动负债
C51: 短期借款 | D51: =历史数据!C108 -> 0 | E51: =历史数据!D108 -> 0 | F51: =历史数据!E108 -> 0 | G51: =历史数据!F108 -> 0 | H51: =历史数据!G108 -> 0 | I51: =关键项目预测!E337 -> 1659.5217 | J51: =关键项目预测!F337 -> 2155.5962 | K51: =关键项目预测!G337 -> 2408.5979 | L51: =关键项目预测!H337 -> 2723.4485 | M51: =关键项目预测!I337 -> 2543.1845 | N51: =关键项目预测!J337 -> 2613.5814 | O51: =关键项目预测!K337 -> 2589.0484 | P51: =关键项目预测!L337 -> 2364.4367 | ... T51: =关键项目预测!P337 -> 868.6328
C52: 交易性金融负债 | D52: =历史数据!C112 -> 0 | E52: =历史数据!D112 -> 0 | F52: =历史数据!E112 -> 0 | G52: =历史数据!F112 -> 0 | H52: =历史数据!G112 -> 0 | I52: =假设表!I55+H52 -> 0 | J52: =假设表!J55+I52 -> 0 | K52: =假设表!K55+J52 -> 0 | L52: =假设表!L55+K52 -> 0 | M52: =假设表!M55+L52 -> 0 | N52: =假设表!N55+M52 -> 0 | O52: =假设表!O55+N52 -> 0 | P52: =假设表!P55+O52 -> 0 | ... T52: =假设表!T55+S52 -> 0
C53: 衍生金融负债 | D53: =历史数据!C113 -> 0 | E53: =历史数据!D113 -> 0 | F53: =历史数据!E113 -> 0 | G53: =历史数据!F113 -> 0 | H53: =历史数据!G113 -> 0 | I53: =假设表!I56 -> 0 | J53: =假设表!J56 -> 0 | K53: =假设表!K56 -> 0 | L53: =假设表!L56 -> 0 | M53: =假设表!M56 -> 0 | N53: =假设表!N56 -> 0 | O53: =假设表!O56 -> 0 | P53: =假设表!P56 -> 0 | ... T53: =假设表!T56 -> 0
C54: 应付账款 | D54: =历史数据!C114 -> 658.68864 | E54: =历史数据!D114 -> 659.80255 | F54: =历史数据!E114 -> 422.56747 | G54: =历史数据!F114 -> 433.74423 | H54: =历史数据!G114 -> 599.03347 | I54: =假设表!I57*历史数据及预测表!I110 -> 700.79791 | J54: =假设表!J57*历史数据及预测表!J110 -> 984.02022 | K54: =假设表!K57*历史数据及预测表!K110 -> 1314.9322 | L54: =假设表!L57*历史数据及预测表!L110 -> 1536.1756 | M54: =假设表!M57*历史数据及预测表!M110 -> 1797.1345 | N54: =假设表!N57*历史数据及预测表!N110 -> 2194.2262 | O54: =假设表!O57*历史数据及预测表!O110 -> 2602.6725 | P54: =假设表!P57*历史数据及预测表!P110 -> 3102.4571 | ... T54: =假设表!T57*历史数据及预测表!T110 -> 6333.9627
C55: 应付票据 | D55: =历史数据!C115 -> 0 | E55: =历史数据!D115 -> 0 | F55: =历史数据!E115 -> 0 | G55: =历史数据!F115 -> 0 | H55: =历史数据!G115 -> 0 | I55: =假设表!I58*历史数据及预测表!I110 -> 0 | J55: =假设表!J58*历史数据及预测表!J110 -> 0 | K55: =假设表!K58*历史数据及预测表!K110 -> 0 | L55: =假设表!L58*历史数据及预测表!L110 -> 0 | M55: =假设表!M58*历史数据及预测表!M110 -> 0 | N55: =假设表!N58*历史数据及预测表!N110 -> 0 | O55: =假设表!O58*历史数据及预测表!O110 -> 0 | P55: =假设表!P58*历史数据及预测表!P110 -> 0 | ... T55: =假设表!T58*历史数据及预测表!T110 -> 0
C56: 预收款项 | D56: =历史数据!C116 -> 0 | E56: =历史数据!D116 -> 0 | F56: =历史数据!E116 -> 0 | G56: =历史数据!F116 -> 0 | H56: =历史数据!G116 -> 0 | I56: =假设表!I59*历史数据及预测表!I107 -> 0 | J56: =假设表!J59*历史数据及预测表!J107 -> 0 | K56: =假设表!K59*历史数据及预测表!K107 -> 0 | L56: =假设表!L59*历史数据及预测表!L107 -> 0 | M56: =假设表!M59*历史数据及预测表!M107 -> 0 | N56: =假设表!N59*历史数据及预测表!N107 -> 0 | O56: =假设表!O59*历史数据及预测表!O107 -> 0 | P56: =假设表!P59*历史数据及预测表!P107 -> 0 | ... T56: =假设表!T59*历史数据及预测表!T107 -> 0
C57: 合同负债 | D57: =历史数据!C117 -> 36.10321 | E57: =历史数据!D117 -> 127.35618 | F57: =历史数据!E117 -> 74.879325 | G57: =历史数据!F117 -> 65.719041 | H57: =历史数据!G117 -> 109.61368 | I57: =假设表!I60*历史数据及预测表!I107 -> 152.99477 | J57: =假设表!J60*历史数据及预测表!J107 -> 201.75163 | K57: =假设表!K60*历史数据及预测表!K107 -> 252.95937 | L57: =假设表!L60*历史数据及预测表!L107 -> 283.16353 | M57: =假设表!M60*历史数据及预测表!M107 -> 347.76292 | N57: =假设表!N60*历史数据及预测表!N107 -> 416.9568 | O57: =假设表!O60*历史数据及预测表!O107 -> 492.48344 | P57: =假设表!P60*历史数据及预测表!P107 -> 592.25682 | ... T57: =假设表!T60*历史数据及预测表!T107 -> 1203.797
C58: 应付职工薪酬 | D58: =历史数据!C120 -> 112.94644 | E58: =历史数据!D120 -> 190.2493 | F58: =历史数据!E120 -> 220.71141 | G58: =历史数据!F120 -> 191.61884 | H58: =历史数据!G120 -> 208.2779 | I58: =假设表!I61*历史数据及预测表!I113 -> 249.93348 | J58: =假设表!J61*历史数据及预测表!J113 -> 294.9215 | K58: =假设表!K61*历史数据及预测表!K113 -> 342.10894 | L58: =假设表!L61*历史数据及预测表!L113 -> 402.39621 | M58: =假设表!M61*历史数据及预测表!M113 -> 487.41116 | N58: =假设表!N61*历史数据及预测表!N113 -> 580.02102 | O58: =假设表!O61*历史数据及预测表!O113 -> 691.67463 | P58: =假设表!P61*历史数据及预测表!P113 -> 828.57422 | ... T58: =假设表!T61*历史数据及预测表!T113 -> 1685.9665
C59: 应交税费 | D59: =历史数据!C121 -> 28.257338 | E59: =历史数据!D121 -> 11.014879 | F59: =历史数据!E121 -> 24.874944 | G59: =历史数据!F121 -> 12.895499 | H59: =历史数据!G121 -> 34.237409 | I59: =假设表!I62 -> 24.002617 | J59: =假设表!J62 -> 23.711842 | K59: =假设表!K62 -> 27.317289 | L59: =假设表!L62 -> 25.010583 | M59: =假设表!M62 -> 25.346571 | N59: =假设表!N62 -> 25.891481 | O59: =假设表!O62 -> 25.416212 | P59: =假设表!P62 -> 25.551421 | ... T59: =假设表!T62 -> 25.529112
C60: 其他应付款 | D60: =历史数据!C122 -> 36.014623 | E60: =历史数据!D122 -> 51.580678 | F60: =历史数据!E122 -> 26.727265 | G60: =历史数据!F122 -> 20.993834 | H60: =历史数据!G122 -> 32.188814 | I60: =假设表!I63+历史数据及预测表!H60 -> 32.188814 | J60: =假设表!J63+历史数据及预测表!I60 -> 32.188814 | K60: =假设表!K63+历史数据及预测表!J60 -> 32.188814 | L60: =假设表!L63+历史数据及预测表!K60 -> 32.188814 | M60: =假设表!M63+历史数据及预测表!L60 -> 32.188814 | N60: =假设表!N63+历史数据及预测表!M60 -> 32.188814 | O60: =假设表!O63+历史数据及预测表!N60 -> 32.188814 | P60: =假设表!P63+历史数据及预测表!O60 -> 32.188814 | ... T60: =假设表!T63+历史数据及预测表!S60 -> 32.188814
C61: 持有待售负债 | D61: =历史数据!C127 -> 0 | E61: =历史数据!D127 -> 0 | F61: =历史数据!E127 -> 0 | G61: =历史数据!F127 -> 0 | H61: =历史数据!G127 -> 0 | I61: =假设表!I64+历史数据及预测表!H61 -> 0 | J61: =假设表!J64+历史数据及预测表!I61 -> 0 | K61: =假设表!K64+历史数据及预测表!J61 -> 0 | L61: =假设表!L64+历史数据及预测表!K61 -> 0 | M61: =假设表!M64+历史数据及预测表!L61 -> 0 | N61: =假设表!N64+历史数据及预测表!M61 -> 0 | O61: =假设表!O64+历史数据及预测表!N61 -> 0 | P61: =假设表!P64+历史数据及预测表!O61 -> 0 | ... T61: =假设表!T64+历史数据及预测表!S61 -> 0
C62: 一年内到期的非流动负债 | D62: =历史数据!C128 -> 9.3133441 | E62: =历史数据!D128 -> 8.3902676 | F62: =历史数据!E128 -> 12.561819 | G62: =历史数据!F128 -> 10.061764 | H62: =历史数据!G128 -> 8.4142169 | I62: =假设表!I65+历史数据及预测表!H62 -> 8.4142169 | J62: =假设表!J65+历史数据及预测表!I62 -> 8.4142169 | K62: =假设表!K65+历史数据及预测表!J62 -> 8.4142169 | L62: =假设表!L65+历史数据及预测表!K62 -> 8.4142169 | M62: =假设表!M65+历史数据及预测表!L62 -> 8.4142169 | N62: =假设表!N65+历史数据及预测表!M62 -> 8.4142169 | O62: =假设表!O65+历史数据及预测表!N62 -> 8.4142169 | P62: =假设表!P65+历史数据及预测表!O62 -> 8.4142169 | ... T62: =假设表!T65+历史数据及预测表!S62 -> 8.4142169
C63: 预提费用 | D63: =历史数据!C129 -> 0 | E63: =历史数据!D129 -> 0 | F63: =历史数据!E129 -> 0 | G63: =历史数据!F129 -> 0 | H63: =历史数据!G129 -> 0 | I63: =假设表!I66*(历史数据及预测表!I112+历史数据及预测表!I113) -> 0 | J63: =假设表!J66*(历史数据及预测表!J112+历史数据及预测表!J113) -> 0 | K63: =假设表!K66*(历史数据及预测表!K112+历史数据及预测表!K113) -> 0 | L63: =假设表!L66*(历史数据及预测表!L112+历史数据及预测表!L113) -> 0 | M63: =假设表!M66*(历史数据及预测表!M112+历史数据及预测表!M113) -> 0 | N63: =假设表!N66*(历史数据及预测表!N112+历史数据及预测表!N113) -> 0 | O63: =假设表!O66*(历史数据及预测表!O112+历史数据及预测表!O113) -> 0 | P63: =假设表!P66*(历史数据及预测表!P112+历史数据及预测表!P113) -> 0 | ... T63: =假设表!T66*(历史数据及预测表!T112+历史数据及预测表!T113) -> 0
C64: 递延收益-流动负债 | D64: =历史数据!C130 -> 0 | E64: =历史数据!D130 -> 0 | F64: =历史数据!E130 -> 0 | G64: =历史数据!F130 -> 0 | H64: =历史数据!G130 -> 0 | I64: =假设表!I67+历史数据及预测表!H64 -> 0 | J64: =假设表!J67+历史数据及预测表!I64 -> 0 | K64: =假设表!K67+历史数据及预测表!J64 -> 0 | L64: =假设表!L67+历史数据及预测表!K64 -> 0 | M64: =假设表!M67+历史数据及预测表!L64 -> 0 | N64: =假设表!N67+历史数据及预测表!M64 -> 0 | O64: =假设表!O67+历史数据及预测表!N64 -> 0 | P64: =假设表!P67+历史数据及预测表!O64 -> 0 | ... T64: =假设表!T67+历史数据及预测表!S64 -> 0
C65: 应付短期债券 | D65: =历史数据!C131 -> 0 | E65: =历史数据!D131 -> 0 | F65: =历史数据!E131 -> 0 | G65: =历史数据!F131 -> 0 | H65: =历史数据!G131 -> 0 | I65: =假设表!I68+历史数据及预测表!H65 -> 0 | J65: =假设表!J68+历史数据及预测表!I65 -> 0 | K65: =假设表!K68+历史数据及预测表!J65 -> 0 | L65: =假设表!L68+历史数据及预测表!K65 -> 0 | M65: =假设表!M68+历史数据及预测表!L65 -> 0 | N65: =假设表!N68+历史数据及预测表!M65 -> 0 | O65: =假设表!O68+历史数据及预测表!N65 -> 0 | P65: =假设表!P68+历史数据及预测表!O65 -> 0 | ... T65: =假设表!T68+历史数据及预测表!S65 -> 0
C66: 其他流动负债 | D66: =历史数据!C132 -> 3.4518686 | E66: =历史数据!D132 -> 2.3271958 | F66: =历史数据!E132 -> 2.2742164 | G66: =历史数据!F132 -> 3.0767001 | H66: =历史数据!G132 -> 8.2120415 | I66: =假设表!I69+历史数据及预测表!H66 -> 8.2120415 | J66: =假设表!J69+历史数据及预测表!I66 -> 8.2120415 | K66: =假设表!K69+历史数据及预测表!J66 -> 8.2120415 | L66: =假设表!L69+历史数据及预测表!K66 -> 8.2120415 | M66: =假设表!M69+历史数据及预测表!L66 -> 8.2120415 | N66: =假设表!N69+历史数据及预测表!M66 -> 8.2120415 | O66: =假设表!O69+历史数据及预测表!N66 -> 8.2120415 | P66: =假设表!P69+历史数据及预测表!O66 -> 8.2120415 | ... T66: =假设表!T69+历史数据及预测表!S66 -> 8.2120415
C67: 其他金融类流动负债 | D67: =历史数据!C109+历史数据!C110+历史数据!C111+历史数据!C118+历史数据!C119+历史数据!C123+历史数据!C124+历史数据!C125+历史数据!C126 -> 0 | E67: =历史数据!D109+历史数据!D110+历史数据!D111+历史数据!D118+历史数据!D119+历史数据!D123+历史数据!D124+历史数据!D125+历史数据!D126 -> 0 | F67: =历史数据!E109+历史数据!E110+历史数据!E111+历史数据!E118+历史数据!E119+历史数据!E123+历史数据!E124+历史数据!E125+历史数据!E126 -> 0 | G67: =历史数据!F109+历史数据!F110+历史数据!F111+历史数据!F118+历史数据!F119+历史数据!F123+历史数据!F124+历史数据!F125+历史数据!F126 -> 0 | H67: =历史数据!G109+历史数据!G110+历史数据!G111+历史数据!G118+历史数据!G119+历史数据!G123+历史数据!G124+历史数据!G125+历史数据!G126 -> 0 | I67: =假设表!I70+历史数据及预测表!H67 -> 0 | J67: =假设表!J70+历史数据及预测表!I67 -> 0 | K67: =假设表!K70+历史数据及预测表!J67 -> 0 | L67: =假设表!L70+历史数据及预测表!K67 -> 0 | M67: =假设表!M70+历史数据及预测表!L67 -> 0 | N67: =假设表!N70+历史数据及预测表!M67 -> 0 | O67: =假设表!O70+历史数据及预测表!N67 -> 0 | P67: =假设表!P70+历史数据及预测表!O67 -> 0 | ... T67: =假设表!T70+历史数据及预测表!S67 -> 0
C68: 流动负债差额 | D68: =历史数据!C133 -> 0 | E68: =历史数据!D133 -> 0 | F68: =历史数据!E133 -> 0 | G68: =历史数据!F133 -> 0 | H68: =历史数据!G133 -> 0 | I68: =H68 -> 0 | J68: =I68 -> 0 | K68: =J68 -> 0 | L68: =K68 -> 0 | M68: =L68 -> 0 | N68: =M68 -> 0 | O68: =N68 -> 0 | P68: =O68 -> 0 | ... T68: =S68 -> 0
C69: 流动负债合计 | D69: =SUM(D51:D68) -> 884.77546 | E69: =SUM(E51:E68) -> 1050.7211 | F69: =SUM(F51:F68) -> 784.59645 | G69: =SUM(G51:G68) -> 738.10991 | H69: =SUM(H51:H68) -> 999.97753 | I69: =SUM(I51:I68) -> 2836.0655 | J69: =SUM(J51:J68) -> 3708.8165 | K69: =SUM(K51:K68) -> 4394.7308 | ... T69: =SUM(T51:T68) -> 10166.703
C70: 非流动负债
C71: 长期借款 | D71: =历史数据!C136 -> 0 | E71: =历史数据!D136 -> 0 | F71: =历史数据!E136 -> 0 | G71: =历史数据!F136 -> 0 | H71: =历史数据!G136 -> 0 | I71: =假设表!I121+历史数据及预测表!H71 -> 0 | J71: =假设表!J121+历史数据及预测表!I71 -> 0 | K71: =假设表!K121+历史数据及预测表!J71 -> 0 | L71: =假设表!L121+历史数据及预测表!K71 -> 0 | M71: =假设表!M121+历史数据及预测表!L71 -> 0 | N71: =假设表!N121+历史数据及预测表!M71 -> 0 | O71: =假设表!O121+历史数据及预测表!N71 -> 0 | P71: =假设表!P121+历史数据及预测表!O71 -> 0 | ... T71: =假设表!T121+历史数据及预测表!S71 -> 0
C72: 应付债券 | D72: =历史数据!C137 -> 0 | E72: =历史数据!D137 -> 0 | F72: =历史数据!E137 -> 0 | G72: =历史数据!F137 -> 0 | H72: =历史数据!G137 -> 0 | I72: =假设表!I122+H72 -> 0 | J72: =假设表!J122+I72 -> 0 | K72: =假设表!K122+J72 -> 0 | L72: =假设表!L122+K72 -> 0 | M72: =假设表!M122+L72 -> 0 | N72: =假设表!N122+M72 -> 0 | O72: =假设表!O122+N72 -> 0 | P72: =假设表!P122+O72 -> 0 | ... T72: =假设表!T122+S72 -> 0
C73: 租赁负债 | D73: =历史数据!C138 -> 5.4702084 | E73: =历史数据!D138 -> 6.5142615 | F73: =历史数据!E138 -> 19.700471 | G73: =历史数据!F138 -> 13.62259 | H73: =历史数据!G138 -> 9.3433979 | I73: =假设表!I96+历史数据及预测表!H73 -> 9.3433979 | J73: =假设表!J96+历史数据及预测表!I73 -> 9.3433979 | K73: =假设表!K96+历史数据及预测表!J73 -> 9.3433979 | L73: =假设表!L96+历史数据及预测表!K73 -> 9.3433979 | M73: =假设表!M96+历史数据及预测表!L73 -> 9.3433979 | N73: =假设表!N96+历史数据及预测表!M73 -> 9.3433979 | O73: =假设表!O96+历史数据及预测表!N73 -> 9.3433979 | P73: =假设表!P96+历史数据及预测表!O73 -> 9.3433979 | ... T73: =假设表!T96+历史数据及预测表!S73 -> 9.3433979
C74: 长期应付款 | D74: =历史数据!C139 -> 0 | E74: =历史数据!D139 -> 0 | F74: =历史数据!E139 -> 0 | G74: =历史数据!F139 -> 0 | H74: =历史数据!G139 -> 0 | I74: =假设表!I123+历史数据及预测表!H74 -> 0 | J74: =假设表!J123+历史数据及预测表!I74 -> 0 | K74: =假设表!K123+历史数据及预测表!J74 -> 0 | L74: =假设表!L123+历史数据及预测表!K74 -> 0 | M74: =假设表!M123+历史数据及预测表!L74 -> 0 | N74: =假设表!N123+历史数据及预测表!M74 -> 0 | O74: =假设表!O123+历史数据及预测表!N74 -> 0 | P74: =假设表!P123+历史数据及预测表!O74 -> 0 | ... T74: =假设表!T123+历史数据及预测表!S74 -> 0
C75: 长期应付职工薪酬 | D75: =历史数据!C140 -> 0.95561542 | E75: =历史数据!D140 -> 0 | F75: =历史数据!E140 -> 0 | G75: =历史数据!F140 -> 0 | H75: =历史数据!G140 -> 0 | I75: =假设表!I124+历史数据及预测表!H75 -> 0 | J75: =假设表!J124+历史数据及预测表!I75 -> 0 | K75: =假设表!K124+历史数据及预测表!J75 -> 0 | L75: =假设表!L124+历史数据及预测表!K75 -> 0 | M75: =假设表!M124+历史数据及预测表!L75 -> 0 | N75: =假设表!N124+历史数据及预测表!M75 -> 0 | O75: =假设表!O124+历史数据及预测表!N75 -> 0 | P75: =假设表!P124+历史数据及预测表!O75 -> 0 | ... T75: =假设表!T124+历史数据及预测表!S75 -> 0
C76: 预计负债 | D76: =历史数据!C141 -> 19.769235 | E76: =历史数据!D141 -> 21.595247 | F76: =历史数据!E141 -> 10.867971 | G76: =历史数据!F141 -> 11.527167 | H76: =历史数据!G141 -> 9.2563462 | I76: =假设表!I71+H76 -> 9.2563462 | J76: =假设表!J71+I76 -> 9.2563462 | K76: =假设表!K71+J76 -> 9.2563462 | L76: =假设表!L71+K76 -> 9.2563462 | M76: =假设表!M71+L76 -> 9.2563462 | N76: =假设表!N71+M76 -> 9.2563462 | O76: =假设表!O71+N76 -> 9.2563462 | P76: =假设表!P71+O76 -> 9.2563462 | ... T76: =假设表!T71+S76 -> 9.2563462
C77: 递延所得税负债 | D77: =历史数据!C142 -> 90.892208 | E77: =历史数据!D142 -> 68.938076 | F77: =历史数据!E142 -> 78.971182 | G77: =历史数据!F142 -> 68.645053 | H77: =历史数据!G142 -> 62.389351 | I77: =假设表!I72+历史数据及预测表!H77 -> 62.389351 | J77: =假设表!J72+历史数据及预测表!I77 -> 62.389351 | K77: =假设表!K72+历史数据及预测表!J77 -> 62.389351 | L77: =假设表!L72+历史数据及预测表!K77 -> 62.389351 | M77: =假设表!M72+历史数据及预测表!L77 -> 62.389351 | N77: =假设表!N72+历史数据及预测表!M77 -> 62.389351 | O77: =假设表!O72+历史数据及预测表!N77 -> 62.389351 | P77: =假设表!P72+历史数据及预测表!O77 -> 62.389351 | ... T77: =假设表!T72+历史数据及预测表!S77 -> 62.389351
C78: 递延收益-非流动负债 | D78: =历史数据!C143 -> 10.365784 | E78: =历史数据!D143 -> 15.047674 | F78: =历史数据!E143 -> 18.367888 | G78: =历史数据!F143 -> 12.126684 | H78: =历史数据!G143 -> 3.3225889 | I78: =假设表!I73+历史数据及预测表!H78 -> 3.3225889 | J78: =假设表!J73+历史数据及预测表!I78 -> 3.3225889 | K78: =假设表!K73+历史数据及预测表!J78 -> 3.3225889 | L78: =假设表!L73+历史数据及预测表!K78 -> 3.3225889 | M78: =假设表!M73+历史数据及预测表!L78 -> 3.3225889 | N78: =假设表!N73+历史数据及预测表!M78 -> 3.3225889 | O78: =假设表!O73+历史数据及预测表!N78 -> 3.3225889 | P78: =假设表!P73+历史数据及预测表!O78 -> 3.3225889 | ... T78: =假设表!T73+历史数据及预测表!S78 -> 3.3225889
C79: 其他非流动负债 | D79: =历史数据!C144 -> 0 | E79: =历史数据!D144 -> 0 | F79: =历史数据!E144 -> 0 | G79: =历史数据!F144 -> 0 | H79: =历史数据!G144 -> 0 | I79: =历史数据及预测表!H79 -> 0 | J79: =历史数据及预测表!I79 -> 0 | K79: =历史数据及预测表!J79 -> 0 | L79: =历史数据及预测表!K79 -> 0 | M79: =历史数据及预测表!L79 -> 0 | N79: =历史数据及预测表!M79 -> 0 | O79: =历史数据及预测表!N79 -> 0 | P79: =历史数据及预测表!O79 -> 0 | ... T79: =历史数据及预测表!S79 -> 0
C80: 非流动负债差额 | D80: =历史数据!C145 -> 0 | E80: =历史数据!D145 -> 0 | F80: =历史数据!E145 -> 0 | G80: =历史数据!F145 -> 0 | H80: =历史数据!G145 -> 0 | I80: =H80 -> 0 | J80: =I80 -> 0 | K80: =J80 -> 0 | L80: =K80 -> 0 | M80: =L80 -> 0 | N80: =M80 -> 0 | O80: =N80 -> 0 | P80: =O80 -> 0 | ... T80: =S80 -> 0
C81: 非流动负债合计 | D81: =SUM(D71:D80) -> 127.45305 | E81: =SUM(E71:E80) -> 112.09526 | F81: =SUM(F71:F80) -> 127.90751 | G81: =SUM(G71:G80) -> 105.92149 | H81: =SUM(H71:H80) -> 84.311684 | I81: =SUM(I71:I80) -> 84.311684 | J81: =SUM(J71:J80) -> 84.311684 | K81: =SUM(K71:K80) -> 84.311684 | ... T81: =SUM(T71:T80) -> 84.311684
C82: 负债总计 | D82: =D69+D81 -> 1012.2285 | E82: =E69+E81 -> 1162.8163 | F82: =F69+F81 -> 912.50396 | G82: =G69+G81 -> 844.0314 | H82: =H69+H81 -> 1084.2892 | I82: =I69+I81 -> 2920.3772 | J82: =J69+J81 -> 3793.1281 | K82: =K69+K81 -> 4479.0425 | ... T82: =T69+T81 -> 10251.015
C83: 所有者权益（股东权益）
C84: 实收资本（股本） | D84: =历史数据!C150 -> 481.56991 | E84: =历史数据!D150 -> 481.56991 | F84: =历史数据!E150 -> 481.56991 | G84: =历史数据!F150 -> 481.56991 | H84: =历史数据!G150 -> 482.54072 | I84: =假设表!I131+历史数据及预测表!H84+关键项目预测!E259+关键项目预测!E254+关键项目预测!E262 -> 482.54072 | J84: =假设表!J131+历史数据及预测表!I84+关键项目预测!F259+关键项目预测!F254+关键项目预测!F262 -> 482.54072 | K84: =假设表!K131+历史数据及预测表!J84+关键项目预测!G259+关键项目预测!G254+关键项目预测!G262 -> 482.54072 | L84: =假设表!L131+历史数据及预测表!K84+关键项目预测!H259+关键项目预测!H254+关键项目预测!H262 -> 482.54072 | M84: =假设表!M131+历史数据及预测表!L84+关键项目预测!I259+关键项目预测!I254+关键项目预测!I262 -> 482.54072 | N84: =假设表!N131+历史数据及预测表!M84+关键项目预测!J259+关键项目预测!J254+关键项目预测!J262 -> 482.54072 | O84: =假设表!O131+历史数据及预测表!N84+关键项目预测!K259+关键项目预测!K254+关键项目预测!K262 -> 482.54072 | P84: =假设表!P131+历史数据及预测表!O84+关键项目预测!L259+关键项目预测!L254+关键项目预测!L262 -> 482.54072 | ... T84: =假设表!T131+历史数据及预测表!S84+关键项目预测!P259+关键项目预测!P254+关键项目预测!P262 -> 482.54072
C85: 其他权益工具 | D85: =历史数据!C151 -> 0 | E85: =历史数据!D151 -> 0 | F85: =历史数据!E151 -> 0 | G85: =历史数据!F151 -> 0 | H85: =历史数据!G151 -> 0 | I85: =假设表!I134+历史数据及预测表!H85 -> 0 | J85: =假设表!J134+历史数据及预测表!I85 -> 0 | K85: =假设表!K134+历史数据及预测表!J85 -> 0 | L85: =假设表!L134+历史数据及预测表!K85 -> 0 | M85: =假设表!M134+历史数据及预测表!L85 -> 0 | N85: =假设表!N134+历史数据及预测表!M85 -> 0 | O85: =假设表!O134+历史数据及预测表!N85 -> 0 | P85: =假设表!P134+历史数据及预测表!O85 -> 0 | ... T85: =假设表!T134+历史数据及预测表!S85 -> 0
C86: 资本公积 | D86: =历史数据!C152 -> 8844.9222 | E86: =历史数据!D152 -> 8844.9222 | F86: =历史数据!E152 -> 8844.9222 | G86: =历史数据!F152 -> 8896.5786 | H86: =历史数据!G152 -> 9008.2715 | I86: =历史数据及预测表!H86+关键项目预测!E249-关键项目预测!E245+假设表!I136-关键项目预测!E254+关键项目预测!E266-关键项目预测!E262 -> 9008.2715 | J86: =历史数据及预测表!I86+关键项目预测!F249-关键项目预测!F245+假设表!J136-关键项目预测!F254+关键项目预测!F266-关键项目预测!F262 -> 9008.2715 | K86: =历史数据及预测表!J86+关键项目预测!G249-关键项目预测!G245+假设表!K136-关键项目预测!G254+关键项目预测!G266-关键项目预测!G262 -> 9008.2715 | L86: =历史数据及预测表!K86+关键项目预测!H249-关键项目预测!H245+假设表!L136-关键项目预测!H254+关键项目预测!H266-关键项目预测!H262 -> 9008.2715 | M86: =历史数据及预测表!L86+关键项目预测!I249-关键项目预测!I245+假设表!M136-关键项目预测!I254+关键项目预测!I266-关键项目预测!I262 -> 9008.2715 | N86: =历史数据及预测表!M86+关键项目预测!J249-关键项目预测!J245+假设表!N136-关键项目预测!J254+关键项目预测!J266-关键项目预测!J262 -> 9008.2715 | O86: =历史数据及预测表!N86+关键项目预测!K249-关键项目预测!K245+假设表!O136-关键项目预测!K254+关键项目预测!K266-关键项目预测!K262 -> 9008.2715 | P86: =历史数据及预测表!O86+关键项目预测!L249-关键项目预测!L245+假设表!P136-关键项目预测!L254+关键项目预测!L266-关键项目预测!L262 -> 9008.2715 | ... T86: =历史数据及预测表!S86+关键项目预测!P249-关键项目预测!P245+假设表!T136-关键项目预测!P254+关键项目预测!P266-关键项目预测!P262 -> 9008.2715
C87: 减：库存股 | D87: =历史数据!C153 -> 0 | E87: =历史数据!D153 -> 0 | F87: =历史数据!E153 -> 0 | G87: =历史数据!F153 -> 0 | H87: =历史数据!G153 -> 0 | I87: =假设表!I138+历史数据及预测表!H87 -> 0 | J87: =假设表!J138+历史数据及预测表!I87 -> 0 | K87: =假设表!K138+历史数据及预测表!J87 -> 0 | L87: =假设表!L138+历史数据及预测表!K87 -> 0 | M87: =假设表!M138+历史数据及预测表!L87 -> 0 | N87: =假设表!N138+历史数据及预测表!M87 -> 0 | O87: =假设表!O138+历史数据及预测表!N87 -> 0 | P87: =假设表!P138+历史数据及预测表!O87 -> 0 | ... T87: =假设表!T138+历史数据及预测表!S87 -> 0
C88: 其他综合收益 | D88: =历史数据!C154 -> -282.78501 | E88: =历史数据!D154 -> -61.342017 | F88: =历史数据!E154 -> 8.132012 | G88: =历史数据!F154 -> -52.561855 | H88: =历史数据!G154 -> -98.708592 | I88: =I137+H88 -> -110.50189 | J88: =J137+I88 -> -149.52756 | K88: =K137+J88 -> -181.68785 | L88: =L137+K88 -> -209.34761 | M88: =M137+L88 -> -242.29618 | N88: =N137+M88 -> -273.21905 | O88: =O137+N88 -> -303.72945 | P88: =P137+O88 -> -335.19007 | ... T88: =T137+S88 -> -459.09034
C89: 专项储备 | D89: =历史数据!C155 -> 0 | E89: =历史数据!D155 -> 0 | F89: =历史数据!E155 -> 0 | G89: =历史数据!F155 -> 0 | H89: =历史数据!G155 -> 0 | I89: =假设表!I139+历史数据及预测表!H89 -> 0 | J89: =假设表!J139+历史数据及预测表!I89 -> 0 | K89: =假设表!K139+历史数据及预测表!J89 -> 0 | L89: =假设表!L139+历史数据及预测表!K89 -> 0 | M89: =假设表!M139+历史数据及预测表!L89 -> 0 | N89: =假设表!N139+历史数据及预测表!M89 -> 0 | O89: =假设表!O139+历史数据及预测表!N89 -> 0 | P89: =假设表!P139+历史数据及预测表!O89 -> 0 | ... T89: =假设表!T139+历史数据及预测表!S89 -> 0
C90: 盈余公积 | D90: =历史数据!C156 -> 50.709773 | E90: =历史数据!D156 -> 51.837646 | F90: =历史数据!E156 -> 53.54105 | G90: =历史数据!F156 -> 77.41481 | H90: =历史数据!G156 -> 100.66706
C91: 一般风险准备 | D91: =历史数据!C157 -> 0 | E91: =历史数据!D157 -> 0 | F91: =历史数据!E157 -> 0 | G91: =历史数据!F157 -> 0 | H91: =历史数据!G157 -> 0
C92: 未分配利润 | D92: =历史数据!C158 -> 1206.3027 | E92: =历史数据!D158 -> 1906.0239 | F92: =历史数据!E158 -> 2403.0588 | G92: =历史数据!F158 -> 2650.9249 | H92: =历史数据!G158 -> 2956.0876
C93: 留存收益 | D93: =D90+D91+D92 -> 1257.0125 | E93: =E90+E91+E92 -> 1957.8616 | F93: =F90+F91+F92 -> 2456.5998 | G93: =G90+G91+G92 -> 2728.3397 | H93: =H90+H91+H92 -> 3056.7546 | I93: =I136+H93-关键项目预测!E259-H223-I220-I221-I222-I224 -> 5493.9808 | J93: =J136+I93-关键项目预测!F259-I223-J220-J221-J222-J224 -> 8359.0368 | K93: =K136+J93-关键项目预测!G259-J223-K220-K221-K222-K224 -> 11113.405 | L93: =L136+K93-关键项目预测!H259-K223-L220-L221-L222-L224 -> 14219.896 | M93: =M136+L93-关键项目预测!I259-L223-M220-M221-M222-M224 -> 18425.909 | N93: =N136+M93-关键项目预测!J259-M223-N220-N221-N222-N224 -> 23156.962 | O93: =O136+N93-关键项目预测!K259-N223-O220-O221-O222-O224 -> 28827.205 | P93: =P136+O93-关键项目预测!L259-O223-P220-P221-P222-P224 -> 35753.373 | ... T93: =T136+S93-关键项目预测!P259-S223-T220-T221-T222-T224 -> 79539.05
C94: 外币报表折算差额 | D94: =历史数据!C159 -> 0 | E94: =历史数据!D159 -> 0 | F94: =历史数据!E159 -> 0 | G94: =历史数据!F159 -> 0 | H94: =历史数据!G159 -> 0 | I94: =假设表!I140 -> 0 | J94: =假设表!J140 -> 0 | K94: =假设表!K140 -> 0 | L94: =假设表!L140 -> 0 | M94: =假设表!M140 -> 0 | N94: =假设表!N140 -> 0 | O94: =假设表!O140 -> 0 | P94: =假设表!P140 -> 0 | ... T94: =假设表!T140 -> 0
C95: 未确认的投资损失 | D95: =历史数据!C160 -> 0 | E95: =历史数据!D160 -> 0 | F95: =历史数据!E160 -> 0 | G95: =历史数据!F160 -> 0 | H95: =历史数据!G160 -> 0 | I95: =假设表!I141 -> 0 | J95: =假设表!J141 -> 0 | K95: =假设表!K141 -> 0 | L95: =假设表!L141 -> 0 | M95: =假设表!M141 -> 0 | N95: =假设表!N141 -> 0 | O95: =假设表!O141 -> 0 | P95: =假设表!P141 -> 0 | ... T95: =假设表!T141 -> 0
C96: 股东权益差额 | D96: =历史数据!C162 -> 0 | E96: =历史数据!D162 -> 3.6379788e-12 | F96: =历史数据!E162 -> -1.8189894e-12 | G96: =历史数据!F162 -> 0 | H96: =历史数据!G162 -> -1.8189894e-12 | I96: =H96 -> -1.8189894e-12 | J96: =I96 -> -1.8189894e-12 | K96: =J96 -> -1.8189894e-12 | L96: =K96 -> -1.8189894e-12 | M96: =L96 -> -1.8189894e-12 | N96: =M96 -> -1.8189894e-12 | O96: =N96 -> -1.8189894e-12 | P96: =O96 -> -1.8189894e-12 | ... T96: =S96 -> -1.8189894e-12
C97: 归属于母公司所有者权益合计 | D97: =SUM(D84:D96)-D93-2*D87 -> 10300.72 | E97: =SUM(E84:E96)-E93-2*E87 -> 11223.012 | F97: =SUM(F84:F96)-F93-2*F87 -> 11791.224 | G97: =SUM(G84:G96)-G93-2*G87 -> 12053.926 | H97: =SUM(H84:H96)-H93-2*H87 -> 12448.858 | I97: =SUM(I84:I96)-2*I87 -> 14874.291 | J97: =SUM(J84:J96)-2*J87 -> 17700.321 | K97: =SUM(K84:K96)-2*K87 -> 20422.53 | L97: =SUM(L84:L96)-2*L87 -> 23501.361 | M97: =SUM(M84:M96)-2*M87 -> 27674.425 | N97: =SUM(N84:N96)-2*N87 -> 32374.556 | O97: =SUM(O84:O96)-2*O87 -> 38014.288 | P97: =SUM(P84:P96)-2*P87 -> 44908.995 | ... T97: =SUM(T84:T96)-2*T87 -> 88570.772
C98: 少数股东权益 | D98: =历史数据!C161 -> 22.078171 | E98: =历史数据!D161 -> 36.008659 | F98: =历史数据!E161 -> 38.299062 | G98: =历史数据!F161 -> 28.987333 | H98: =历史数据!G161 -> 40.057835 | I98: =假设表!I145+I135+H98 -> -0.78835521 | J98: =假设表!J145+J135+I98 -> -23.934631 | K98: =假设表!K145+K135+J98 -> -48.570563 | L98: =假设表!L145+L135+K98 -> -83.094224 | M98: =假设表!M145+M135+L98 -> -122.54868 | N98: =假设表!N145+N135+M98 -> -168.97744 | O98: =假设表!O145+O135+N98 -> -226.26418 | P98: =假设表!P145+P135+O98 -> -293.90381 | ... T98: =假设表!T145+T135+S98 -> -728.08332
C99: 所有者权益总计 | D99: =D97+D98 -> 10322.798 | E99: =E97+E98 -> 11259.02 | F99: =F97+F98 -> 11829.523 | G99: =G97+G98 -> 12082.914 | H99: =H97+H98 -> 12488.916 | I99: =I97+I98 -> 14873.503 | J99: =J97+J98 -> 17676.387 | K99: =K97+K98 -> 20373.959 | ... T99: =T97+T98 -> 87842.688
C100: 负债及所有者权益总计 | D100: =D82+D99 -> 11335.026 | E100: =E82+E99 -> 12421.837 | F100: =F82+F99 -> 12742.027 | G100: =G82+G99 -> 12926.945 | H100: =H82+H99 -> 13573.205 | I100: =I82+I99 -> 17793.88 | J100: =J82+J99 -> 21469.515 | K100: =K82+K99 -> 24853.001 | ... T100: =T82+T99 -> 98093.703
C102: Check | D102: =IF(ABS(D48-D100)<0.1,"OK",(D48-D100)) -> OK | E102: =IF(ABS(E48-E100)<0.1,"OK",(E48-E100)) -> OK | F102: =IF(ABS(F48-F100)<0.1,"OK",(F48-F100)) -> OK | G102: =IF(ABS(G48-G100)<0.1,"OK",(G48-G100)) -> OK | H102: =IF(ABS(H48-H100)<0.1,"OK",(H48-H100)) -> OK | I102: =IF(ABS(I48-I100)<0.1,"OK",(I48-I100)) -> OK | J102: =IF(ABS(J48-J100)<0.1,"OK",(J48-J100)) -> OK | K102: =IF(ABS(K48-K100)<0.1,"OK",(K48-K100)) -> OK | ... T102: =IF(ABS(T48-T100)<0.1,"OK",(T48-T100)) -> OK
I103: =ABS(I100-I48) -> 3.6379788e-12 | J103: =ABS(J100-J48) -> 0 | K103: =ABS(K100-K48) -> 3.6379788e-12 | L103: =ABS(L100-L48) -> 3.6379788e-12 | M103: =ABS(M100-M48) -> 0 | N103: =ABS(N100-N48) -> 7.2759576e-12 | O103: =ABS(O100-O48) -> 7.2759576e-12 | P103: =ABS(P100-P48) -> 1.3897079e-09 | ... T103: =ABS(T100-T48) -> 0.00012431089
...

Sheet 估值表
B2: 折现基准年份 | C2: =假设表!I148 -> 0 | E2: 折现率计算
G3: 目标D/(D+E) | H3: =假设表!I152 -> 0
B4: 估值结果 | G4: Kd | H4: =假设表!I153 -> 0
B5: 方法 | C5: 估值结果 | E5: WACC | G5: T | H5: =假设表!I155 -> 0
B6: DCF | C6: =D32 -> #DIV/0! | E6: =H3*H4*(1-H5)+H7*H8 -> 0
B7: DDM | C7: =D40 -> #DIV/0! | G7: 目标E/(D+E) | H7: =1-H3 -> 1
B8: PE | C8: =D46 -> 0 | G8: Ke | H8: =K8+K9*K10 -> 0 | J8: 无风险利率 | K8: =假设表!I150 -> 0
B9: PB | C9: =D52 -> 0 | J9: 风险溢价 | K9: =假设表!I151 -> 0
B10: PS | C10: =D58 -> 0 | J10: 股票贝塔 | K10: =假设表!I149 -> 0
B11: PEG | C11: =D65 -> 0
B12: EV/EBITDA | C12: =D71 -> 11.533972 | E12: TV | F12: =假设表!I154 -> 0
B14: DCF
D15: =C2+1 -> 1 | E15: =D15+1 -> 2 | F15: =E15+1 -> 3 | G15: =F15+1 -> 4 | H15: =G15+1 -> 5 | I15: =H15+1 -> 6 | J15: =I15+1 -> 7 | K15: =J15+1 -> 8 | L15: =K15+1 -> 9 | M15: =L15+1 -> 10
B16: EBIT | D16: =IF($C$2=历史数据及预测表!$I$4,历史数据及预测表!J136+历史数据及预测表!J131+历史数据及预测表!J115,IF($C$2=历史数据及预测表!$H$4,历史数据及预测表!I136+历史数据及预测表!I131+历史数据及预测表!I115,历史数据及预测表!K136+历史数据及预测表!K131+历史数据及预测表!K115)) -> 2914.2631 | E16: =IF($C$2=历史数据及预测表!$I$4,历史数据及预测表!K136+历史数据及预测表!K131+历史数据及预测表!K115,IF($C$2=历史数据及预测表!$H$4,历史数据及预测表!J136+历史数据及预测表!J131+历史数据及预测表!J115,历史数据及预测表!L136+历史数据及预测表!L131+历史数据及预测表!L115)) -> 3273.6015 | F16: =IF($C$2=历史数据及预测表!$I$4,历史数据及预测表!L136+历史数据及预测表!L131+历史数据及预测表!L115,IF($C$2=历史数据及预测表!$H$4,历史数据及预测表!K136+历史数据及预测表!K131+历史数据及预测表!K115,历史数据及预测表!M136+历史数据及预测表!M131+历史数据及预测表!M115)) -> 4444.6804 | G16: =IF($C$2=历史数据及预测表!$I$4,历史数据及预测表!M136+历史数据及预测表!M131+历史数据及预测表!M115,IF($C$2=历史数据及预测表!$H$4,历史数据及预测表!L136+历史数据及预测表!L131+历史数据及预测表!L115,历史数据及预测表!N136+历史数据及预测表!N131+历史数据及预测表!N115)) -> 4952.0553 | H16: =IF($C$2=历史数据及预测表!$I$4,历史数据及预测表!N136+历史数据及预测表!N131+历史数据及预测表!N115,IF($C$2=历史数据及预测表!$H$4,历史数据及预测表!M136+历史数据及预测表!M131+历史数据及预测表!M115,历史数据及预测表!O136+历史数据及预测表!O131+历史数据及预测表!O115)) -> 5916.1269 | I16: =IF($C$2=历史数据及预测表!$I$4,历史数据及预测表!O136+历史数据及预测表!O131+历史数据及预测表!O115,IF($C$2=历史数据及预测表!$H$4,历史数据及预测表!N136+历史数据及预测表!N131+历史数据及预测表!N115,历史数据及预测表!P136+历史数据及预测表!P131+历史数据及预测表!P115)) -> 7208.3761 | J16: =IF($C$2=历史数据及预测表!$I$4,历史数据及预测表!P136+历史数据及预测表!P131+历史数据及预测表!P115,IF($C$2=历史数据及预测表!$H$4,历史数据及预测表!O136+历史数据及预测表!O131+历史数据及预测表!O115,历史数据及预测表!Q136+历史数据及预测表!Q131+历史数据及预测表!Q115)) -> 8470.7035 | K16: =IF($C$2=历史数据及预测表!$I$4,历史数据及预测表!Q136+历史数据及预测表!Q131+历史数据及预测表!Q115,IF($C$2=历史数据及预测表!$H$4,历史数据及预测表!P136+历史数据及预测表!P131+历史数据及预测表!P115,历史数据及预测表!R136+历史数据及预测表!R131+历史数据及预测表!R115)) -> 10136.59 | ... M16: =IF($C$2=历史数据及预测表!$I$4,历史数据及预测表!S136+历史数据及预测表!S131+历史数据及预测表!S115,IF($C$2=历史数据及预测表!$H$4,历史数据及预测表!R136+历史数据及预测表!R131+历史数据及预测表!R115,历史数据及预测表!T136+历史数据及预测表!T131+历史数据及预测表!T115)) -> 14435.595
B17: 所得税率 | D17: =IF($C$2=历史数据及预测表!$I$4,假设表!J20,IF($C$2=历史数据及预测表!$H$4,假设表!I20,假设表!K20)) -> 0.091887814 | E17: =IF($C$2=历史数据及预测表!$I$4,假设表!K20,IF($C$2=历史数据及预测表!$H$4,假设表!J20,假设表!L20)) -> 0.091616537 | F17: =IF($C$2=历史数据及预测表!$I$4,假设表!L20,IF($C$2=历史数据及预测表!$H$4,假设表!K20,假设表!M20)) -> 0.093443112 | G17: =IF($C$2=历史数据及预测表!$I$4,假设表!M20,IF($C$2=历史数据及预测表!$H$4,假设表!L20,假设表!N20)) -> 0.092315821 | H17: =IF($C$2=历史数据及预测表!$I$4,假设表!N20,IF($C$2=历史数据及预测表!$H$4,假设表!M20,假设表!O20)) -> 0.09245849 | I17: =IF($C$2=历史数据及预测表!$I$4,假设表!O20,IF($C$2=历史数据及预测表!$H$4,假设表!N20,假设表!P20)) -> 0.092739141 | J17: =IF($C$2=历史数据及预测表!$I$4,假设表!P20,IF($C$2=历史数据及预测表!$H$4,假设表!O20,假设表!Q20)) -> 0.092504484 | K17: =IF($C$2=历史数据及预测表!$I$4,假设表!Q20,IF($C$2=历史数据及预测表!$H$4,假设表!P20,假设表!R20)) -> 0.092567372 | ... M17: =IF($C$2=历史数据及预测表!$I$4,假设表!S20,IF($C$2=历史数据及预测表!$H$4,假设表!R20,假设表!T20)) -> 0.092567372
B18: EBIT*(1-所得税率) | D18: =D16*(1-D17) -> 2646.4779 | E18: =E16*(1-E17) -> 2973.6855 | F18: =F16*(1-F17) -> 4029.3556 | G18: =G16*(1-G17) -> 4494.9023 | H18: =H16*(1-H17) -> 5369.1307 | I18: =I16*(1-I17) -> 6539.8775 | J18: =J16*(1-J17) -> 7687.1254 | K18: =K16*(1-K17) -> 9198.2723 | ... M18: =M16*(1-M17) -> 13099.33
B19: 加：折旧和摊销 | D19: =IF($C$2=历史数据及预测表!$I$4,历史数据及预测表!J151,IF($C$2=历史数据及预测表!$H$4,历史数据及预测表!I151,历史数据及预测表!K151)) -> 100.91571 | E19: =IF($C$2=历史数据及预测表!$I$4,历史数据及预测表!K151,IF($C$2=历史数据及预测表!$H$4,历史数据及预测表!J151,历史数据及预测表!L151)) -> 119.91571 | F19: =IF($C$2=历史数据及预测表!$I$4,历史数据及预测表!L151,IF($C$2=历史数据及预测表!$H$4,历史数据及预测表!K151,历史数据及预测表!M151)) -> 138.91571 | G19: =IF($C$2=历史数据及预测表!$I$4,历史数据及预测表!M151,IF($C$2=历史数据及预测表!$H$4,历史数据及预测表!L151,历史数据及预测表!N151)) -> 157.91571 | H19: =IF($C$2=历史数据及预测表!$I$4,历史数据及预测表!N151,IF($C$2=历史数据及预测表!$H$4,历史数据及预测表!M151,历史数据及预测表!O151)) -> 176.91571 | I19: =IF($C$2=历史数据及预测表!$I$4,历史数据及预测表!O151,IF($C$2=历史数据及预测表!$H$4,历史数据及预测表!N151,历史数据及预测表!P151)) -> 195.91571 | J19: =IF($C$2=历史数据及预测表!$I$4,历史数据及预测表!P151,IF($C$2=历史数据及预测表!$H$4,历史数据及预测表!O151,历史数据及预测表!Q151)) -> 214.91571 | K19: =IF($C$2=历史数据及预测表!$I$4,历史数据及预测表!Q151,IF($C$2=历史数据及预测表!$H$4,历史数据及预测表!P151,历史数据及预测表!R151)) -> 233.91571 | ... M19: =IF($C$2=历史数据及预测表!$I$4,历史数据及预测表!S151,IF($C$2=历史数据及预测表!$H$4,历史数据及预测表!R151,历史数据及预测表!T151)) -> 190
B20: 减：运营资金的追加 | D20: =-IF($C$2=历史数据及预测表!$I$4,历史数据及预测表!J157,IF($C$2=历史数据及预测表!$H$4,历史数据及预测表!I157,历史数据及预测表!K157)) -> 1186.2405 | E20: =-IF($C$2=历史数据及预测表!$I$4,历史数据及预测表!K157,IF($C$2=历史数据及预测表!$H$4,历史数据及预测表!J157,历史数据及预测表!L157)) -> 1297.8673 | F20: =-IF($C$2=历史数据及预测表!$I$4,历史数据及预测表!L157,IF($C$2=历史数据及预测表!$H$4,历史数据及预测表!K157,历史数据及预测表!M157)) -> 1143.9101 | G20: =-IF($C$2=历史数据及预测表!$I$4,历史数据及预测表!M157,IF($C$2=历史数据及预测表!$H$4,历史数据及预测表!L157,历史数据及预测表!N157)) -> 1743.4349 | H20: =-IF($C$2=历史数据及预测表!$I$4,历史数据及预测表!N157,IF($C$2=历史数据及预测表!$H$4,历史数据及预测表!M157,历史数据及预测表!O157)) -> 1976.7045 | I20: =-IF($C$2=历史数据及预测表!$I$4,历史数据及预测表!O157,IF($C$2=历史数据及预测表!$H$4,历史数据及预测表!N157,历史数据及预测表!P157)) -> 2267.0115 | J20: =-IF($C$2=历史数据及预测表!$I$4,历史数据及预测表!P157,IF($C$2=历史数据及预测表!$H$4,历史数据及预测表!O157,历史数据及预测表!Q157)) -> 2834.5892 | K20: =-IF($C$2=历史数据及预测表!$I$4,历史数据及预测表!Q157,IF($C$2=历史数据及预测表!$H$4,历史数据及预测表!P157,历史数据及预测表!R157)) -> 3331.4459 | ... M20: =-IF($C$2=历史数据及预测表!$I$4,历史数据及预测表!S157,IF($C$2=历史数据及预测表!$H$4,历史数据及预测表!R157,历史数据及预测表!T157)) -> 4756.621
B21: 资本性支出 | D21: =-IF($C$2=历史数据及预测表!$I$4,历史数据及预测表!J162,IF($C$2=历史数据及预测表!$H$4,历史数据及预测表!I162,历史数据及预测表!K162)) -> 200 | E21: =-IF($C$2=历史数据及预测表!$I$4,历史数据及预测表!K162,IF($C$2=历史数据及预测表!$H$4,历史数据及预测表!J162,历史数据及预测表!L162)) -> 200 | F21: =-IF($C$2=历史数据及预测表!$I$4,历史数据及预测表!L162,IF($C$2=历史数据及预测表!$H$4,历史数据及预测表!K162,历史数据及预测表!M162)) -> 200 | G21: =-IF($C$2=历史数据及预测表!$I$4,历史数据及预测表!M162,IF($C$2=历史数据及预测表!$H$4,历史数据及预测表!L162,历史数据及预测表!N162)) -> 200 | H21: =-IF($C$2=历史数据及预测表!$I$4,历史数据及预测表!N162,IF($C$2=历史数据及预测表!$H$4,历史数据及预测表!M162,历史数据及预测表!O162)) -> 200 | I21: =-IF($C$2=历史数据及预测表!$I$4,历史数据及预测表!O162,IF($C$2=历史数据及预测表!$H$4,历史数据及预测表!N162,历史数据及预测表!P162)) -> 200 | J21: =-IF($C$2=历史数据及预测表!$I$4,历史数据及预测表!P162,IF($C$2=历史数据及预测表!$H$4,历史数据及预测表!O162,历史数据及预测表!Q162)) -> 200 | K21: =-IF($C$2=历史数据及预测表!$I$4,历史数据及预测表!Q162,IF($C$2=历史数据及预测表!$H$4,历史数据及预测表!P162,历史数据及预测表!R162)) -> 200 | ... M21: =-IF($C$2=历史数据及预测表!$I$4,历史数据及预测表!S162,IF($C$2=历史数据及预测表!$H$4,历史数据及预测表!R162,历史数据及预测表!T162)) -> 200
B22: FCF | D22: =D18+D19-D20-D21 -> 1361.1531 | E22: =E18+E19-E20-E21 -> 1595.7339 | F22: =F18+F19-F20-F21 -> 2824.3612 | G22: =G18+G19-G20-G21 -> 2709.3831 | H22: =H18+H19-H20-H21 -> 3369.3419 | I22: =I18+I19-I20-I21 -> 4268.7817 | J22: =J18+J19-J20-J21 -> 4867.4519 | K22: =K18+K19-K20-K21 -> 5900.7421 | ... M22: =M18+M19-M20-M21 -> 8332.7093
B23: FCF现值 | D23: =D22/(1+$E$6)^(D15-$C$2) -> 1361.1531 | E23: =E22/(1+$E$6)^(E15-$C$2) -> 1595.7339 | F23: =F22/(1+$E$6)^(F15-$C$2) -> 2824.3612 | G23: =G22/(1+$E$6)^(G15-$C$2) -> 2709.3831 | H23: =H22/(1+$E$6)^(H15-$C$2) -> 3369.3419 | I23: =I22/(1+$E$6)^(I15-$C$2) -> 4268.7817 | J23: =J22/(1+$E$6)^(J15-$C$2) -> 4867.4519 | K23: =K22/(1+$E$6)^(K15-$C$2) -> 5900.7421 | ... M23: =M22/(1+$E$6)^(M15-$C$2) -> 8332.7093
B24: TV | D24: =IF(E6<F12,0,M22*(1+F12)/(E6-F12)) -> #DIV/0!
B25: TV现值 | D25: =D24/(1+E6)^(M15-C2) -> #DIV/0!
B26: 企业价值 | D26: =D25+SUM(D23:M23) -> #DIV/0!
B27: 债务总额 | D27: =IF(C2=历史数据及预测表!I4,历史数据及预测表!I51+历史数据及预测表!I71+历史数据及预测表!I72+历史数据及预测表!I62+历史数据及预测表!I65,IF(C2=历史数据及预测表!H4,历史数据及预测表!H51+历史数据及预测表!H62+历史数据及预测表!H71+历史数据及预测表!H72+历史数据及预测表!H65,历史数据及预测表!J51+历史数据及预测表!J71+历史数据及预测表!J72+历史数据及预测表!J62+历史数据及预测表!J65)) -> 2164.0104
B28: 现金 | D28: =IF(C2=历史数据及预测表!I4,历史数据及预测表!I7,IF(C2=历史数据及预测表!H4,历史数据及预测表!H7,历史数据及预测表!J7)) -> 9237.1612
B29: 股权价值（含少数股东） | D29: =D26-D27+D28 -> #DIV/0!
B30: 股权价值（不含少数股东） | D30: =D29*(1-假设表!I156) -> #DIV/0!
B31: 总股数 | D31: =历史数据及预测表!I203 -> 482.54072
B32: 每股价值 | D32: =D30/D31 -> #DIV/0!
B34: DDM
D35: =历史数据及预测表!I4 -> 2026 | E35: =历史数据及预测表!J4 -> 2027 | F35: =历史数据及预测表!K4 -> 2028 | G35: =历史数据及预测表!L4 -> 2029 | H35: =历史数据及预测表!M4 -> 2030 | I35: =历史数据及预测表!N4 -> 2031 | J35: =历史数据及预测表!O4 -> 2032 | K35: =历史数据及预测表!P4 -> 2033 | ... M35: =历史数据及预测表!R4 -> 2035
B36: 每股股利 | D36: =历史数据及预测表!I219 -> 0 | E36: =历史数据及预测表!J219 -> 0 | F36: =历史数据及预测表!K219 -> 0 | G36: =历史数据及预测表!L219 -> 0 | H36: =历史数据及预测表!M219 -> 0 | I36: =历史数据及预测表!N219 -> 0 | J36: =历史数据及预测表!O219 -> 0 | K36: =历史数据及预测表!P219 -> 0 | ... M36: =历史数据及预测表!R219 -> 0
B37: 股利现值 | D37: =D36/(1+$E$6)^(D35-$C$2) -> 0 | E37: =E36/(1+$E$6)^(E35-$C$2) -> 0 | F37: =F36/(1+$E$6)^(F35-$C$2) -> 0 | G37: =G36/(1+$E$6)^(G35-$C$2) -> 0 | H37: =H36/(1+$E$6)^(H35-$C$2) -> 0 | I37: =I36/(1+$E$6)^(I35-$C$2) -> 0 | J37: =J36/(1+$E$6)^(J35-$C$2) -> 0 | K37: =K36/(1+$E$6)^(K35-$C$2) -> 0 | ... M37: =M36/(1+$E$6)^(M35-$C$2) -> 0
B38: TV | D38: =IF(E6<F12,0,M36*(1+E6)/(E6-F12)) -> #DIV/0!
