Workbook

Sheet 中信三级行业指数热度
A1: 指数代码 | B1: 指数名称 | C1: 指数成分股数 | D1: YTD涨幅(%) | E1: 近一周涨跌幅(%) | F1: 近一月涨跌幅(%) | G1: 动量加速度 | H1: CR5合计权重(%) | I1: CR1代码 | J1: CR1名称 | K1: CR1自由流通市值(亿) | L1: CR1权重(%) | M1: CR2代码 | N1: CR2名称 | O1: CR2自由流通市值(亿) | P1: CR2权重(%) | Q1: CR3代码 | R1: CR3名称 | S1: CR3自由流通市值(亿) | T1: CR3权重(%) | U1: CR4代码 | V1: CR4名称 | W1: CR4自由流通市值(亿) | X1: CR4权重(%) | Y1: CR5代码 | Z1: CR5名称 | AA1: CR5自由流通市值(亿) | AB1: CR5权重(%) | AD1: 基准日:今天 | AE1: =TODAY() -> 46199
A2: CI005541.CI | B2: 半导体设备指数 | C2: 29 | D2: =IFERROR(([1]!thsiFinD("ths_close_price_index",$A2,$AE$2,"","")/[1]!thsiFinD("ths_close_price_index",$A2,$AE$5,"","")-1)*100,"") -> 118.03563 | E2: =IFERROR(([1]!thsiFinD("ths_close_price_index",$A2,$AE$2,"","")/[1]!thsiFinD("ths_close_price_index",$A2,$AE$3,"","")-1)*100,"") -> 12.773946 | F2: =IFERROR(([1]!thsiFinD("ths_close_price_index",$A2,$AE$2,"","")/[1]!thsiFinD("ths_close_price_index",$A2,$AE$4,"","")-1)*100,"") -> 30.866909 | G2: =IFERROR(E2/5-F2/20,"") -> 1.0114438 | H2: 71.44 | I2: 002371.SZ | J2: 北方华创 | K2: 3209.173 | L2: 24.23 | M2: 688012.SH | N2: 中微公司 | O2: 2697.3147 | P2: 20.37 | Q2: 688072.SH | R2: 拓荆科技 | S2: 1518.2949 | T2: 11.47 | U2: 300604.SZ | V2: 长川科技 | W2: 1199.3993 | X2: 9.06 | Y2: 688120.SH | Z2: 华海清科 | AA2: 835.7473 | AB2: 6.31 | AD2: 前一交易日T0(工作日近似) | AE2: =TEXT(WORKDAY($AE$1,-1),"yyyy-mm-dd") -> 2026-06-25
A3: CI005539.CI | B3: 分立器件指数 | C3: 16 | D3: =IFERROR(([1]!thsiFinD("ths_close_price_index",$A3,$AE$2,"","")/[1]!thsiFinD("ths_close_price_index",$A3,$AE$5,"","")-1)*100,"") -> 63.771828 | E3: =IFERROR(([1]!thsiFinD("ths_close_price_index",$A3,$AE$2,"","")/[1]!thsiFinD("ths_close_price_index",$A3,$AE$3,"","")-1)*100,"") -> 10.727 | F3: =IFERROR(([1]!thsiFinD("ths_close_price_index",$A3,$AE$2,"","")/[1]!thsiFinD("ths_close_price_index",$A3,$AE$4,"","")-1)*100,"") -> 14.042782 | G3: =IFERROR(E3/5-F3/20,"") -> 1.4432608 | H3: 67.2 | I3: 600460.SH | J3: 士兰微 | K3: 493.4561 | L3: 20.19 | M3: 688172.SH | N3: 燕东微 | O3: 371.7856 | P3: 15.21 | Q3: 300373.SZ | R3: 扬杰科技 | S3: 356.7835 | T3: 14.6 | U3: 605111.SH | V3: 新洁能 | W3: 236.6472 | X3: 9.68 | Y3: 300623.SZ | Z3: 捷捷微电 | AA3: 183.7881 | AB3: 7.52 | AD3: 一周前(T0前5交易日) | AE3: =TEXT(WORKDAY($AE$1,-6),"yyyy-mm-dd") -> 2026-06-18
A4: CI005414.CI | B4: 碳纤维指数 | C4: 2 | D4: =IFERROR(([1]!thsiFinD("ths_close_price_index",$A4,$AE$2,"","")/[1]!thsiFinD("ths_close_price_index",$A4,$AE$5,"","")-1)*100,"") -> 76.22654 | E4: =IFERROR(([1]!thsiFinD("ths_close_price_index",$A4,$AE$2,"","")/[1]!thsiFinD("ths_close_price_index",$A4,$AE$3,"","")-1)*100,"") -> -0.93914612 | F4: =IFERROR(([1]!thsiFinD("ths_close_price_index",$A4,$AE$2,"","")/[1]!thsiFinD("ths_close_price_index",$A4,$AE$4,"","")-1)*100,"") -> 30.992531 | G4: =IFERROR(E4/5-F4/20,"") -> -1.7374558 | H4: 100 | I4: 688598.SH | J4: 金博股份 | K4: 111.1097 | L4: 56.73 | M4: 688295.SH | N4: 中复神鹰 | O4: 84.7332 | P4: 43.27 | AD4: 一月前(T0前20交易日) | AE4: =TEXT(WORKDAY($AE$1,-21),"yyyy-mm-dd") -> 2026-05-28
A5: CI005538.CI | B5: 集成电路指数 | C5: 110 | D5: =IFERROR(([1]!thsiFinD("ths_close_price_index",$A5,$AE$2,"","")/[1]!thsiFinD("ths_close_price_index",$A5,$AE$5,"","")-1)*100,"") -> 84.306331 | E5: =IFERROR(([1]!thsiFinD("ths_close_price_index",$A5,$AE$2,"","")/[1]!thsiFinD("ths_close_price_index",$A5,$AE$3,"","")-1)*100,"") -> 10.902559 | F5: =IFERROR(([1]!thsiFinD("ths_close_price_index",$A5,$AE$2,"","")/[1]!thsiFinD("ths_close_price_index",$A5,$AE$4,"","")-1)*100,"") -> 17.487046 | G5: =IFERROR(E5/5-F5/20,"") -> 1.3061596 | H5: 49.59 | I5: 688256.SH | J5: 寒武纪 | K5: 4468.3271 | L5: 12.66 | M5: 603986.SH | N5: 兆易创新 | O5: 4272.3406 | P5: 12.11 | Q5: 688008.SH | R5: 澜起科技 | S5: 3012.5987 | T5: 8.54 | U5: 688041.SH | V5: 海光信息 | W5: 2939.7339 | X5: 8.33 | Y5: 688981.SH | Z5: 中芯国际 | AA5: 2805.6528 | AB5: 7.95 | AD5: 年初基准(上年末交易日) | AE5: =TEXT(WORKDAY(DATE(YEAR($AE$1),1,1),-1),"yyyy-mm-dd") -> 2025-12-31
A6: CI005422.CI | B6: 橡胶助剂指数 | C6: 5 | D6: =IFERROR(([1]!thsiFinD("ths_close_price_index",$A6,$AE$2,"","")/[1]!thsiFinD("ths_close_price_index",$A6,$AE$5,"","")-1)*100,"") -> 47.346122 | E6: =IFERROR(([1]!thsiFinD("ths_close_price_index",$A6,$AE$2,"","")/[1]!thsiFinD("ths_close_price_index",$A6,$AE$3,"","")-1)*100,"") -> 16.97181 | F6: =IFERROR(([1]!thsiFinD("ths_close_price_index",$A6,$AE$2,"","")/[1]!thsiFinD("ths_close_price_index",$A6,$AE$4,"","")-1)*100,"") -> 27.839876 | G6: =IFERROR(E6/5-F6/20,"") -> 2.0023683 | H6: 100 | I6: 603650.SH | J6: 彤程新材 | K6: 165.2254 | L6: 57.1 | M6: 002068.SZ | N6: 黑猫股份 | O6: 53.5358 | P6: 18.5 | Q6: 300121.SZ | R6: 阳谷华泰 | S6: 37.2273 | T6: 12.87 | U6: 002442.SZ | V6: 龙星科技 | W6: 21.0056 | X6: 7.26 | Y6: 002753.SZ | Z6: 永东股份 | AA6: 12.3687 | AB6: 4.27
A7: CI005292.CI | B7: 卡车指数 | C7: 8 | D7: =IFERROR(([1]!thsiFinD("ths_close_price_index",$A7,$AE$2,"","")/[1]!thsiFinD("ths_close_price_index",$A7,$AE$5,"","")-1)*100,"") -> 39.333336 | E7: =IFERROR(([1]!thsiFinD("ths_close_price_index",$A7,$AE$2,"","")/[1]!thsiFinD("ths_close_price_index",$A7,$AE$3,"","")-1)*100,"") -> -4.0003812 | F7: =IFERROR(([1]!thsiFinD("ths_close_price_index",$A7,$AE$2,"","")/[1]!thsiFinD("ths_close_price_index",$A7,$AE$4,"","")-1)*100,"") -> -14.814469 | G7: =IFERROR(E7/5-F7/20,"") -> -0.059352782 | H7: 93.99 | I7: 000338.SZ | J7: 潍柴动力 | K7: 1525.8845 | L7: 75.12 | M7: 600166.SH | N7: 福田汽车 | O7: 140.3812 | P7: 6.91 | Q7: 000951.SZ | R7: 中国重汽 | S7: 124.8397 | T7: 6.15 | U7: 000800.SZ | V7: 一汽解放 | W7: 66.0473 | X7: 3.25 | Y7: 301039.SZ | Z7: 中集车辆 | AA7: 52.0545 | AB7: 2.56
A8: CI005323.CI | B8: 医疗服务指数 | C8: 47 | D8: =IFERROR(([1]!thsiFinD("ths_close_price_index",$A8,$AE$2,"","")/[1]!thsiFinD("ths_close_price_index",$A8,$AE$5,"","")-1)*100,"") -> 4.0206399 | E8: =IFERROR(([1]!thsiFinD("ths_close_price_index",$A8,$AE$2,"","")/[1]!thsiFinD("ths_close_price_index",$A8,$AE$3,"","")-1)*100,"") -> 8.0227067 | F8: =IFERROR(([1]!thsiFinD("ths_close_price_index",$A8,$AE$2,"","")/[1]!thsiFinD("ths_close_price_index",$A8,$AE$4,"","")-1)*100,"") -> 5.0132767 | G8: =IFERROR(E8/5-F8/20,"") -> 1.3538775 | H8: 67.5 | I8: 603259.SH | J8: 药明康德 | K8: 2293.7092 | L8: 45.98 | M8: 300015.SZ | N8: 爱尔眼科 | O8: 363.2255 | P8: 7.28 | Q8: 300759.SZ | R8: 康龙化成 | S8: 254.6971 | T8: 5.11 | U8: 002821.SZ | V8: 凯莱英 | W8: 245.5889 | X8: 4.92 | Y8: 300347.SZ | Z8: 泰格医药 | AA8: 209.9511 | AB8: 4.21
A9: CI005547.CI | B9: 显示零组指数 | C9: 28 | D9: =IFERROR(([1]!thsiFinD("ths_close_price_index",$A9,$AE$2,"","")/[1]!thsiFinD("ths_close_price_index",$A9,$AE$5,"","")-1)*100,"") -> 78.945039 | E9: =IFERROR(([1]!thsiFinD("ths_close_price_index",$A9,$AE$2,"","")/[1]!thsiFinD("ths_close_price_index",$A9,$AE$3,"","")-1)*100,"") -> 4.5272635 | F9: =IFERROR(([1]!thsiFinD("ths_close_price_index",$A9,$AE$2,"","")/[1]!thsiFinD("ths_close_price_index",$A9,$AE$4,"","")-1)*100,"") -> 8.1582128 | G9: =IFERROR(E9/5-F9/20,"") -> 0.49754206 | H9: 58.15 | I9: 603629.SH | J9: 利通电子 | K9: 274.0956 | L9: 15.21 | M9: 603773.SH | N9: 沃格光电 | O9: 259.3009 | P9: 14.39 | Q9: 300088.SZ | R9: 长信科技 | S9: 230.0351 | T9: 12.77 | U9: 688127.SH | V9: 蓝特光学 | W9: 175.6906 | X9: 9.75 | Y9: 688150.SH | Z9: 莱特光电 | AA9: 108.5704 | AB9: 6.03
A10: CI005480.CI | B10: 燃料电池指数 | C10: 9 | D10: =IFERROR(([1]!thsiFinD("ths_close_price_index",$A10,$AE$2,"","")/[1]!thsiFinD("ths_close_price_index",$A10,$AE$5,"","")-1)*100,"") -> 37.50765 | E10: =IFERROR(([1]!thsiFinD("ths_close_price_index",$A10,$AE$2,"","")/[1]!thsiFinD("ths_close_price_index",$A10,$AE$3,"","")-1)*100,"") -> 10.99687 | F10: =IFERROR(([1]!thsiFinD("ths_close_price_index",$A10,$AE$2,"","")/[1]!thsiFinD("ths_close_price_index",$A10,$AE$4,"","")-1)*100,"") -> 13.220679 | G10: =IFERROR(E10/5-F10/20,"") -> 1.53834 | H10: 100 | I10: 000811.SZ | J10: 冰轮环境 | K10: 273.7642 | L10: 43.69 | M10: 000969.SZ | N10: 安泰科技 | O10: 178.9266 | P10: 28.55 | Q10: 002639.SZ | R10: 雪人集团 | S10: 88.1494 | T10: 14.07 | U10: 600273.SH | V10: 嘉化能源 | W10: 53.3992 | X10: 8.52 | Y10: 688339.SH | Z10: 亿华通 | AA10: 32.4103 | AB10: 5.17
A11: CI005357.CI | B11: 航运指数 | C11: 17 | D11: =IFERROR(([1]!thsiFinD("ths_close_price_index",$A11,$AE$2,"","")/[1]!thsiFinD("ths_close_price_index",$A11,$AE$5,"","")-1)*100,"") -> 20.034214 | E11: =IFERROR(([1]!thsiFinD("ths_close_price_index",$A11,$AE$2,"","")/[1]!thsiFinD("ths_close_price_index",$A11,$AE$3,"","")-1)*100,"") -> 6.9384061 | F11: =IFERROR(([1]!thsiFinD("ths_close_price_index",$A11,$AE$2,"","")/[1]!thsiFinD("ths_close_price_index",$A11,$AE$4,"","")-1)*100,"") -> 5.376593 | G11: =IFERROR(E11/5-F11/20,"") -> 1.1188516 | H11: 82.06 | I11: 601919.SH | J11: 中远海控 | K11: 724.7891 | L11: 33.24 | M11: 601872.SH | N11: 招商轮船 | O11: 494.2193 | P11: 22.67 | Q11: 600026.SH | R11: 中远海能 | S11: 329.4191 | T11: 15.11 | U11: 601975.SH | V11: 招商南油 | W11: 147.7589 | X11: 6.78 | Y11: 600428.SH | Z11: 中远海特 | AA11: 92.8258 | AB11: 4.26
A12: CI005546.CI | B12: 面板指数 | C12: 12 | D12: =IFERROR(([1]!thsiFinD("ths_close_price_index",$A12,$AE$2,"","")/[1]!thsiFinD("ths_close_price_index",$A12,$AE$5,"","")-1)*100,"") -> 50.277387 | E12: =IFERROR(([1]!thsiFinD("ths_close_price_index",$A12,$AE$2,"","")/[1]!thsiFinD("ths_close_price_index",$A12,$AE$3,"","")-1)*100,"") -> 11.871478 | F12: =IFERROR(([1]!thsiFinD("ths_close_price_index",$A12,$AE$2,"","")/[1]!thsiFinD("ths_close_price_index",$A12,$AE$4,"","")-1)*100,"") -> 25.642215 | G12: =IFERROR(E12/5-F12/20,"") -> 1.0921849 | H12: 95.92 | I12: 000725.SZ | J12: 京东方A | K12: 2150.3835 | L12: 59.43 | M12: 000100.SZ | N12: TCL科技 | O12: 925.1556 | P12: 25.57 | Q12: 600707.SH | R12: 彩虹股份 | S12: 164.1556 | T12: 4.54 | U12: 000050.SZ | V12: 深天马A | W12: 126.8056 | X12: 3.5 | Y12: 688538.SH | Z12: 和辉光电 | AA12: 104.1695 | AB12: 2.88
A13: CI005255.CI | B13: 印染化学品指数 | C13: 14 | D13: =IFERROR(([1]!thsiFinD("ths_close_price_index",$A13,$AE$2,"","")/[1]!thsiFinD("ths_close_price_index",$A13,$AE$5,"","")-1)*100,"") -> 25.606664 | E13: =IFERROR(([1]!thsiFinD("ths_close_price_index",$A13,$AE$2,"","")/[1]!thsiFinD("ths_close_price_index",$A13,$AE$3,"","")-1)*100,"") -> 9.5575775 | F13: =IFERROR(([1]!thsiFinD("ths_close_price_index",$A13,$AE$2,"","")/[1]!thsiFinD("ths_close_price_index",$A13,$AE$4,"","")-1)*100,"") -> 9.3877472 | G13: =IFERROR(E13/5-F13/20,"") -> 1.4421281 | H13: 75.26 | I13: 600352.SH | J13: 浙江龙盛 | K13: 294.0162 | L13: 44.85 | M13: 002440.SZ | N13: 闰土股份 | O13: 69.4079 | P13: 10.59 | Q13: 300905.SZ | R13: 宝丽迪 | S13: 50.4684 | T13: 7.7 | U13: 300067.SZ | V13: 安诺其 | W13: 42.6645 | X13: 6.51 | Y13: 300522.SZ | Z13: 世名科技 | AA13: 36.7817 | AB13: 5.61
A14: CI005316.CI | B14: 化学原料药指数 | C14: 59 | D14: =IFERROR(([1]!thsiFinD("ths_close_price_index",$A14,$AE$2,"","")/[1]!thsiFinD("ths_close_price_index",$A14,$AE$5,"","")-1)*100,"") -> 2.0109929 | E14: =IFERROR(([1]!thsiFinD("ths_close_price_index",$A14,$AE$2,"","")/[1]!thsiFinD("ths_close_price_index",$A14,$AE$3,"","")-1)*100,"") -> 4.6023343 | F14: =IFERROR(([1]!thsiFinD("ths_close_price_index",$A14,$AE$2,"","")/[1]!thsiFinD("ths_close_price_index",$A14,$AE$4,"","")-1)*100,"") -> 0.34022749 | G14: =IFERROR(E14/5-F14/20,"") -> 0.90345549 | H14: 92.03 | I14: 688131.SH | J14: 皓元医药 | K14: 123.93 | L14: 32.89 | M14: 000739.SZ | N14: 普洛药业 | O14: 89.0288 | P14: 23.63 | Q14: 300436.SZ | R14: 广生堂 | S14: 82.627 | T14: 21.93 | U14: 301201.SZ | V14: 诚达药业 | W14: 31.1282 | X14: 8.26 | Y14: 300381.SZ | Z14: 溢多利 | AA14: 20.0589 | AB14: 5.32
A15: CI005230.CI | B15: 特钢指数 | C15: 14 | D15: =IFERROR(([1]!thsiFinD("ths_close_price_index",$A15,$AE$2,"","")/[1]!thsiFinD("ths_close_price_index",$A15,$AE$5,"","")-1)*100,"") -> -6.1889528 | E15: =IFERROR(([1]!thsiFinD("ths_close_price_index",$A15,$AE$2,"","")/[1]!thsiFinD("ths_close_price_index",$A15,$AE$3,"","")-1)*100,"") -> -1.8536246 | F15: =IFERROR(([1]!thsiFinD("ths_close_price_index",$A15,$AE$2,"","")/[1]!thsiFinD("ths_close_price_index",$A15,$AE$4,"","")-1)*100,"") -> -3.2375157 | G15: =IFERROR(E15/5-F15/20,"") -> -0.20884913 | H15: 71.76 | I15: 002318.SZ | J15: 久立特材 | K15: 146.483 | L15: 24.1 | M15: 000708.SZ | N15: 中信特钢 | O15: 111.3349 | P15: 18.32 | Q15: 600399.SH | R15: 抚顺特钢 | S15: 61.5034 | T15: 10.12 | U15: 002075.SZ | V15: 沙钢股份 | W15: 59.9019 | X15: 9.86 | Y15: 600507.SH | Z15: 方大特钢 | AA15: 56.8891 | AB15: 9.36
A16: CI005442.CI | B16: 其他专用材料指数 | C16: 13 | D16: =IFERROR(([1]!thsiFinD("ths_close_price_index",$A16,$AE$2,"","")/[1]!thsiFinD("ths_close_price_index",$A16,$AE$5,"","")-1)*100,"") -> 41.763779 | E16: =IFERROR(([1]!thsiFinD("ths_close_price_index",$A16,$AE$2,"","")/[1]!thsiFinD("ths_close_price_index",$A16,$AE$3,"","")-1)*100,"") -> 6.7269618 | F16: =IFERROR(([1]!thsiFinD("ths_close_price_index",$A16,$AE$2,"","")/[1]!thsiFinD("ths_close_price_index",$A16,$AE$4,"","")-1)*100,"") -> 10.41438 | G16: =IFERROR(E16/5-F16/20,"") -> 0.82467337 | H16: 69.09 | I16: 300179.SZ | J16: 四方达 | K16: 173.6464 | L16: 34.87 | M16: 002392.SZ | N16: 北京利尔 | O16: 72.5882 | P16: 14.58 | Q16: 002225.SZ | R16: 濮耐股份 | S16: 36.2324 | T16: 7.28 | U16: 300234.SZ | V16: 开尔新材 | W16: 31.796 | X16: 6.38 | Y16: 002066.SZ | Z16: 瑞泰科技 | AA16: 29.8042 | AB16: 5.98
A17: CI005386.CI | B17: 棉纺制品指数 | C17: 9 | D17: =IFERROR(([1]!thsiFinD("ths_close_price_index",$A17,$AE$2,"","")/[1]!thsiFinD("ths_close_price_index",$A17,$AE$5,"","")-1)*100,"") -> -13.107595 | E17: =IFERROR(([1]!thsiFinD("ths_close_price_index",$A17,$AE$2,"","")/[1]!thsiFinD("ths_close_price_index",$A17,$AE$3,"","")-1)*100,"") -> 2.2547549 | F17: =IFERROR(([1]!thsiFinD("ths_close_price_index",$A17,$AE$2,"","")/[1]!thsiFinD("ths_close_price_index",$A17,$AE$4,"","")-1)*100,"") -> -2.2380651 | G17: =IFERROR(E17/5-F17/20,"") -> 0.56285423 | H17: 78.13 | I17: 002083.SZ | J17: 孚日股份 | K17: 64.506 | L17: 24.46 | M17: 300888.SZ | N17: 稳健医疗 | O17: 47.6732 | P17: 18.08 | Q17: 002042.SZ | R17: 华孚时尚 | S17: 42.1185 | T17: 15.97 | U17: 601339.SH | V17: 百隆东方 | W17: 25.9815 | X17: 9.85 | Y17: 000726.SZ | Z17: 鲁泰A | AA17: 25.7716 | AB17: 9.77
... A23: CI005320.CI | B23: 生物医药Ⅲ指数 | C23: 84 | D23: =IFERROR(([1]!thsiFinD("ths_close_price_index",$A23,$AE$2,"","")/[1]!thsiFinD("ths_close_price_index",$A23,$AE$5,"","")-1)*100,"") -> -21.025632 | E23: =IFERROR(([1]!thsiFinD("ths_close_price_index",$A23,$AE$2,"","")/[1]!thsiFinD("ths_close_price_index",$A23,$AE$3,"","")-1)*100,"") -> 1.6050567 | F23: =IFERROR(([1]!thsiFinD("ths_close_price_index",$A23,$AE$2,"","")/[1]!thsiFinD("ths_close_price_index",$A23,$AE$4,"","")-1)*100,"") -> -7.124169 | G23: =IFERROR(E23/5-F23/20,"") -> 0.67721979 | H23: 25.36 | I23: 688235.SH | J23: 百济神州 | K23: 263.2349 | L23: 6.25 | M23: 002252.SZ | N23: 上海莱士 | O23: 210.8348 | P23: 5.01 | Q23: 688506.SH | R23: 百利天恒 | S23: 203.3973 | T23: 4.83 | U23: 603087.SH | V23: 甘李药业 | W23: 197.1162 | X23: 4.68 | Y23: 300142.SZ | Z23: 沃森生物 | AA23: 193.1902 | AB23: 4.59
A24: CI005533.CI | B24: 数字金融服务指数 | C24: 2 | D24: =IFERROR(([1]!thsiFinD("ths_close_price_index",$A24,$AE$2,"","")/[1]!thsiFinD("ths_close_price_index",$A24,$AE$5,"","")-1)*100,"") -> -25.834412 | E24: =IFERROR(([1]!thsiFinD("ths_close_price_index",$A24,$AE$2,"","")/[1]!thsiFinD("ths_close_price_index",$A24,$AE$3,"","")-1)*100,"") -> -3.4811007 | F24: =IFERROR(([1]!thsiFinD("ths_close_price_index",$A24,$AE$2,"","")/[1]!thsiFinD("ths_close_price_index",$A24,$AE$4,"","")-1)*100,"") -> -9.452406 | G24: =IFERROR(E24/5-F24/20,"") -> -0.22359984 | H24: 100 | I24: 300773.SZ | J24: 拉卡拉 | K24: 134.1753 | L24: 81.66 | M24: 603123.SH | N24: 翠微股份 | O24: 30.14 | P24: 18.34
A25: CI005452.CI | B25: 电梯指数 | C25: 12 | D25: =IFERROR(([1]!thsiFinD("ths_close_price_index",$A25,$AE$2,"","")/[1]!thsiFinD("ths_close_price_index",$A25,$AE$5,"","")-1)*100,"") -> -10.65691 | E25: =IFERROR(([1]!thsiFinD("ths_close_price_index",$A25,$AE$2,"","")/[1]!thsiFinD("ths_close_price_index",$A25,$AE$3,"","")-1)*100,"") -> -3.0996064 | F25: =IFERROR(([1]!thsiFinD("ths_close_price_index",$A25,$AE$2,"","")/[1]!thsiFinD("ths_close_price_index",$A25,$AE$4,"","")-1)*100,"") -> -6.1801029 | G25: =IFERROR(E25/5-F25/20,"") -> -0.31091614 | H25: 64.65 | I25: 600835.SH | J25: 上海机电 | K25: 70.8457 | L25: 25.14 | M25: 300669.SZ | N25: 沪宁股份 | O25: 33.263 | P25: 11.81 | Q25: 600894.SH | R25: 广日股份 | S25: 30.2195 | T25: 10.73 | U25: 002367.SZ | V25: 康力电梯 | W25: 25.0385 | X25: 8.89 | Y25: 300931.SZ | Z25: 通用电梯 | AA25: 22.7622 | AB25: 8.08
A26: CI005355.CI | B26: 公交指数 | C26: 6 | D26: =IFERROR(([1]!thsiFinD("ths_close_price_index",$A26,$AE$2,"","")/[1]!thsiFinD("ths_close_price_index",$A26,$AE$5,"","")-1)*100,"") -> -28.600451 | E26: =IFERROR(([1]!thsiFinD("ths_close_price_index",$A26,$AE$2,"","")/[1]!thsiFinD("ths_close_price_index",$A26,$AE$3,"","")-1)*100,"") -> -5.922553 | F26: =IFERROR(([1]!thsiFinD("ths_close_price_index",$A26,$AE$2,"","")/[1]!thsiFinD("ths_close_price_index",$A26,$AE$4,"","")-1)*100,"") -> -16.696199 | G26: =IFERROR(E26/5-F26/20,"") -> -0.34970065 | H26: 92.67 | I26: 600611.SH | J26: 大众交通 | K26: 46.5486 | L26: 36.71 | M26: 002357.SZ | N26: 富临运业 | O26: 21.6229 | P26: 17.05 | Q26: 603069.SH | R26: 海汽集团 | S26: 18.003 | T26: 14.2 | U26: 600650.SH | V26: 锦江在线 | W26: 17.5374 | X26: 13.83 | Y26: 600834.SH | Z26: 申通地铁 | AA26: 13.7914 | AB26: 10.88
A27: CI005565.CI | B27: 云基础设施服务指数 | C27: 13 | D27: =IFERROR(([1]!thsiFinD("ths_close_price_index",$A27,$AE$2,"","")/[1]!thsiFinD("ths_close_price_index",$A27,$AE$5,"","")-1)*100,"") -> 15.027812 | E27: =IFERROR(([1]!thsiFinD("ths_close_price_index",$A27,$AE$2,"","")/[1]!thsiFinD("ths_close_price_index",$A27,$AE$3,"","")-1)*100,"") -> -3.2396427 | F27: =IFERROR(([1]!thsiFinD("ths_close_price_index",$A27,$AE$2,"","")/[1]!thsiFinD("ths_close_price_index",$A27,$AE$4,"","")-1)*100,"") -> -9.2431938 | G27: =IFERROR(E27/5-F27/20,"") -> -0.18576884 | H27: 68.14 | I27: 300442.SZ | J27: 润泽科技 | K27: 577.3328 | L27: 26.4 | M27: 300017.SZ | N27: 网宿科技 | O27: 321.2089 | P27: 14.69 | Q27: 300454.SZ | R27: 深信服 | S27: 245.7691 | T27: 11.24 | U27: 300383.SZ | V27: 光环新网 | W27: 188.8693 | X27: 8.64 | Y27: 300738.SZ | Z27: 奥飞数据 | AA27: 156.8503 | AB27: 7.17
A28: CI005408.CI | B28: 贸易流通指数 | C28: 4 | D28: =IFERROR(([1]!thsiFinD("ths_close_price_index",$A28,$AE$2,"","")/[1]!thsiFinD("ths_close_price_index",$A28,$AE$5,"","")-1)*100,"") -> -15.250729 | E28: =IFERROR(([1]!thsiFinD("ths_close_price_index",$A28,$AE$2,"","")/[1]!thsiFinD("ths_close_price_index",$A28,$AE$3,"","")-1)*100,"") -> 5.7422695 | F28: =IFERROR(([1]!thsiFinD("ths_close_price_index",$A28,$AE$2,"","")/[1]!thsiFinD("ths_close_price_index",$A28,$AE$4,"","")-1)*100,"") -> -5.0957807 | G28: =IFERROR(E28/5-F28/20,"") -> 1.4032429 | H28: 100 | I28: 600058.SH | J28: 五矿发展 | K28: 45.3877 | L28: 54.09 | M28: 000906.SZ | N28: 浙商中拓 | O28: 20.4316 | P28: 24.35 | Q28: 605050.SH | R28: 福然德 | S28: 18.0928 | T28: 21.56
A29: CI005418.CI | B29: 其他化学原料指数 | C29: 23 | D29: =IFERROR(([1]!thsiFinD("ths_close_price_index",$A29,$AE$2,"","")/[1]!thsiFinD("ths_close_price_index",$A29,$AE$5,"","")-1)*100,"") -> 34.578953 | E29: =IFERROR(([1]!thsiFinD("ths_close_price_index",$A29,$AE$2,"","")/[1]!thsiFinD("ths_close_price_index",$A29,$AE$3,"","")-1)*100,"") -> 6.963528 | F29: =IFERROR(([1]!thsiFinD("ths_close_price_index",$A29,$AE$2,"","")/[1]!thsiFinD("ths_close_price_index",$A29,$AE$4,"","")-1)*100,"") -> 12.697609 | G29: =IFERROR(E29/5-F29/20,"") -> 0.75782513 | H29: 75.44 | I29: 002648.SZ | J29: 卫星化学 | K29: 382.0021 | L29: 31.54 | M29: 688300.SH | N29: 联瑞新材 | O29: 257.3746 | P29: 21.25 | Q29: 002430.SZ | R29: 杭氧股份 | S29: 108.9079 | T29: 8.99 | U29: 003022.SZ | V29: 联泓新科 | W29: 99.1859 | X29: 8.19 | Y29: 002549.SZ | Z29: 凯美特气 | AA29: 66.2993 | AB29: 5.47
A30: CI005558.CI | B30: 网络覆盖优化与运维指数 | C30: 6 | D30: =IFERROR(([1]!thsiFinD("ths_close_price_index",$A30,$AE$2,"","")/[1]!thsiFinD("ths_close_price_index",$A30,$AE$5,"","")-1)*100,"") -> -12.490011 | E30: =IFERROR(([1]!thsiFinD("ths_close_price_index",$A30,$AE$2,"","")/[1]!thsiFinD("ths_close_price_index",$A30,$AE$3,"","")-1)*100,"") -> -2.8461825 | F30: =IFERROR(([1]!thsiFinD("ths_close_price_index",$A30,$AE$2,"","")/[1]!thsiFinD("ths_close_price_index",$A30,$AE$4,"","")-1)*100,"") -> -11.056619 | G30: =IFERROR(E30/5-F30/20,"") -> -0.016405577 | H30: 97.39 | I30: 300560.SZ | J30: 中富通 | K30: 30.6516 | L30: 23.51 | M30: 300050.SZ | N30: 世纪鼎利 | O30: 29.5291 | P30: 22.65 | Q30: 300310.SZ | R30: 宜通世纪 | S30: 29.4694 | T30: 22.6 | U30: 300025.SZ | V30: 华星创业 | W30: 19.5607 | X30: 15 | Y30: 603206.SH | Z30: 嘉环科技 | AA30: 17.7729 | AB30: 13.63
A31: CI005490.CI | B31: 电商及服务Ⅲ指数 | C31: 17 | D31: =IFERROR(([1]!thsiFinD("ths_close_price_index",$A31,$AE$2,"","")/[1]!thsiFinD("ths_close_price_index",$A31,$AE$5,"","")-1)*100,"") -> 18.084723 | E31: =IFERROR(([1]!thsiFinD("ths_close_price_index",$A31,$AE$2,"","")/[1]!thsiFinD("ths_close_price_index",$A31,$AE$3,"","")-1)*100,"") -> 0.04780603 | F31: =IFERROR(([1]!thsiFinD("ths_close_price_index",$A31,$AE$2,"","")/[1]!thsiFinD("ths_close_price_index",$A31,$AE$4,"","")-1)*100,"") -> -4.3333033 | G31: =IFERROR(E31/5-F31/20,"") -> 0.22622637 | H31: 80.76 | I31: 300209.SZ | J31: 行云科技 | K31: 212.5412 | L31: 41.94 | M31: 002803.SZ | N31: 吉宏股份 | O31: 62.3061 | P31: 12.29 | Q31: 002640.SZ | R31: 跨境通 | S31: 47.57 | T31: 9.39 | U31: 002127.SZ | V31: 南极电商 | W31: 46.0242 | X31: 9.08 | Y31: 003010.SZ | Z31: 若羽臣 | AA31: 40.8279 | AB31: 8.06
A32: CI005563.CI | B32: 行业应用软件指数 | C32: 184 | D32: =IFERROR(([1]!thsiFinD("ths_close_price_index",$A32,$AE$2,"","")/[1]!thsiFinD("ths_close_price_index",$A32,$AE$5,"","")-1)*100,"") -> -13.927759 | E32: =IFERROR(([1]!thsiFinD("ths_close_price_index",$A32,$AE$2,"","")/[1]!thsiFinD("ths_close_price_index",$A32,$AE$3,"","")-1)*100,"") -> -1.6087978 | F32: =IFERROR(([1]!thsiFinD("ths_close_price_index",$A32,$AE$2,"","")/[1]!thsiFinD("ths_close_price_index",$A32,$AE$4,"","")-1)*100,"") -> -5.9870736 | G32: =IFERROR(E32/5-F32/20,"") -> -0.022405876 | H32: 46.01 | I32: 600570.SH | J32: 恒生电子 | K32: 333.7288 | L32: 12.71 | M32: 002261.SZ | N32: 拓维信息 | O32: 310.4848 | P32: 11.82 | Q32: 301269.SZ | R32: 华大九天 | S32: 239.3293 | T32: 9.11 | U32: 002065.SZ | V32: 东华软件 | W32: 162.9713 | X32: 6.21 | Y32: 600536.SH | Z32: 中国软件 | AA32: 161.8781 | AB32: 6.16
A33: CI005317.CI | B33: 化学制剂指数 | C33: 74 | D33: =IFERROR(([1]!thsiFinD("ths_close_price_index",$A33,$AE$2,"","")/[1]!thsiFinD("ths_close_price_index",$A33,$AE$5,"","")-1)*100,"") -> -11.420164 | E33: =IFERROR(([1]!thsiFinD("ths_close_price_index",$A33,$AE$2,"","")/[1]!thsiFinD("ths_close_price_index",$A33,$AE$3,"","")-1)*100,"") -> 3.2798066 | F33: =IFERROR(([1]!thsiFinD("ths_close_price_index",$A33,$AE$2,"","")/[1]!thsiFinD("ths_close_price_index",$A33,$AE$4,"","")-1)*100,"") -> 0.037137418 | G33: =IFERROR(E33/5-F33/20,"") -> 0.65410444 | H33: 73.51 | I33: 600276.SH | J33: 恒瑞医药 | K33: 1919.1493 | L33: 49.55 | M33: 002422.SZ | N33: 科伦药业 | O33: 406.8296 | P33: 10.5 | Q33: 688578.SH | R33: 艾力斯 | S33: 192.1826 | T33: 4.96 | U33: 600079.SH | V33: ST人福 | W33: 174.0025 | X33: 4.49 | Y33: 688266.SH | Z33: 泽璟制药 | AA33: 155.3624 | AB33: 4.01
A34: CI005293.CI | B34: 客车指数 | C34: 6 | D34: =IFERROR(([1]!thsiFinD("ths_close_price_index",$A34,$AE$2,"","")/[1]!thsiFinD("ths_close_price_index",$A34,$AE$5,"","")-1)*100,"") -> -18.11034 | E34: =IFERROR(([1]!thsiFinD("ths_close_price_index",$A34,$AE$2,"","")/[1]!thsiFinD("ths_close_price_index",$A34,$AE$3,"","")-1)*100,"") -> 0.34433546 | F34: =IFERROR(([1]!thsiFinD("ths_close_price_index",$A34,$AE$2,"","")/[1]!thsiFinD("ths_close_price_index",$A34,$AE$4,"","")-1)*100,"") -> -15.846114 | G34: =IFERROR(E34/5-F34/20,"") -> 0.86117278 | H34: 96.98 | I34: 600066.SH | J34: 宇通客车 | K34: 354.1994 | L34: 69.9 | M34: 600686.SH | N34: 金龙汽车 | O34: 49.5622 | P34: 9.78 | Q34: 000957.SZ | R34: 中通客车 | S34: 39.4996 | T34: 7.8 | U34: 600609.SH | V34: 金杯汽车 | W34: 30.6466 | X34: 6.05 | Y34: 000868.SZ | Z34: 安凯客车 | AA34: 17.4736 | AB34: 3.45
A35: CI005425.CI | B35: 电子化学品指数 | C35: 24 | D35: =IFERROR(([1]!thsiFinD("ths_close_price_index",$A35,$AE$2,"","")/[1]!thsiFinD("ths_close_price_index",$A35,$AE$5,"","")-1)*100,"") -> 99.00353 | E35: =IFERROR(([1]!thsiFinD("ths_close_price_index",$A35,$AE$2,"","")/[1]!thsiFinD("ths_close_price_index",$A35,$AE$3,"","")-1)*100,"") -> 6.1844263 | F35: =IFERROR(([1]!thsiFinD("ths_close_price_index",$A35,$AE$2,"","")/[1]!thsiFinD("ths_close_price_index",$A35,$AE$4,"","")-1)*100,"") -> 29.830647 | G35: =IFERROR(E35/5-F35/20,"") -> -0.2546471 | H35: 61.38 | I35: 300285.SZ | J35: 国瓷材料 | K35: 806.4518 | L35: 21.74 | M35: 300054.SZ | N35: 鼎龙股份 | O35: 615.6881 | P35: 16.6 | Q35: 688019.SH | R35: 安集科技 | S35: 412.0659 | T35: 11.11 | U35: 300236.SZ | V35: 上海新阳 | W35: 227.5715 | X35: 6.14 | Y35: 300398.SZ | Z35: 飞凯材料 | AA35: 214.6571 | AB35: 5.79
A36: CI005560.CI | B36: 通用计算机设备指数 | C36: 24 | D36: =IFERROR(([1]!thsiFinD("ths_close_price_index",$A36,$AE$2,"","")/[1]!thsiFinD("ths_close_price_index",$A36,$AE$5,"","")-1)*100,"") -> 27.965479 | E36: =IFERROR(([1]!thsiFinD("ths_close_price_index",$A36,$AE$2,"","")/[1]!thsiFinD("ths_close_price_index",$A36,$AE$3,"","")-1)*100,"") -> 5.0357421 | F36: =IFERROR(([1]!thsiFinD("ths_close_price_index",$A36,$AE$2,"","")/[1]!thsiFinD("ths_close_price_index",$A36,$AE$4,"","")-1)*100,"") -> 6.0053757 | G36: =IFERROR(E36/5-F36/20,"") -> 0.70687963 | H36: 78.8 | I36: 601138.SH | J36: 工业富联 | K36: 2537.4976 | L36: 31.99 | M36: 301308.SZ | N36: 江波龙 | O36: 1396.4275 | P36: 17.6 | Q36: 603019.SH | R36: 中科曙光 | S36: 1087.7655 | T36: 13.71 | U36: 000977.SZ | V36: 浪潮信息 | W36: 654.9753 | X36: 8.26 | Y36: 000938.SZ | Z36: 紫光股份 | AA36: 574.3114 | AB36: 7.24
A37: CI005564.CI | B37: 新兴计算机软件指数 | C37: 6 | D37: =IFERROR(([1]!thsiFinD("ths_close_price_index",$A37,$AE$2,"","")/[1]!thsiFinD("ths_close_price_index",$A37,$AE$5,"","")-1)*100,"") -> -14.685397 | E37: =IFERROR(([1]!thsiFinD("ths_close_price_index",$A37,$AE$2,"","")/[1]!thsiFinD("ths_close_price_index",$A37,$AE$3,"","")-1)*100,"") -> -4.3115381 | F37: =IFERROR(([1]!thsiFinD("ths_close_price_index",$A37,$AE$2,"","")/[1]!thsiFinD("ths_close_price_index",$A37,$AE$4,"","")-1)*100,"") -> -12.554904 | G37: =IFERROR(E37/5-F37/20,"") -> -0.23456244 | H37: 97.47 | I37: 002230.SZ | J37: 科大讯飞 | K37: 819.7338 | L37: 71.65 | M37: 688031.SH | N37: 星环科技 | O37: 100.2613 | P37: 8.76 | Q37: 688088.SH | R37: 虹软科技 | S37: 89.9376 | T37: 7.86 | U37: 688787.SH | V37: 海天瑞声 | W37: 64.1795 | X37: 5.61 | Y37: 688207.SH | Z37: 格灵深瞳 | AA37: 41.0937 | AB37: 3.59
A38: CI005557.CI | B38: 增值服务Ⅲ指数 | C38: 13 | D38: =IFERROR(([1]!thsiFinD("ths_close_price_index",$A38,$AE$2,"","")/[1]!thsiFinD("ths_close_price_index",$A38,$AE$5,"","")-1)*100,"") -> -2.6534483 | E38: =IFERROR(([1]!thsiFinD("ths_close_price_index",$A38,$AE$2,"","")/[1]!thsiFinD("ths_close_price_index",$A38,$AE$3,"","")-1)*100,"") -> -4.4966796 | F38: =IFERROR(([1]!thsiFinD("ths_close_price_index",$A38,$AE$2,"","")/[1]!thsiFinD("ths_close_price_index",$A38,$AE$4,"","")-1)*100,"") -> -10.765722 | G38: =IFERROR(E38/5-F38/20,"") -> -0.36104983 | H38: 58.43 | I38: 000839.SZ | J38: 国安股份 | K38: 73.2453 | L38: 13.5 | M38: 300292.SZ | N38: 吴通控股 | O38: 67.4036 | P38: 12.42 | Q38: 002467.SZ | R38: 二六三 | S38: 63.0134 | T38: 11.61 | U38: 300959.SZ | V38: 线上线下 | W38: 59.2937 | X38: 10.93 | Y38: 002123.SZ | Z38: 梦网科技 | AA38: 54.0636 | AB38: 9.97
A39: CI005554.CI | B39: 通信终端及配件指数 | C39: 30 | D39: =IFERROR(([1]!thsiFinD("ths_close_price_index",$A39,$AE$2,"","")/[1]!thsiFinD("ths_close_price_index",$A39,$AE$5,"","")-1)*100,"") -> 26.898451 | E39: =IFERROR(([1]!thsiFinD("ths_close_price_index",$A39,$AE$2,"","")/[1]!thsiFinD("ths_close_price_index",$A39,$AE$3,"","")-1)*100,"") -> 4.2681039 | F39: =IFERROR(([1]!thsiFinD("ths_close_price_index",$A39,$AE$2,"","")/[1]!thsiFinD("ths_close_price_index",$A39,$AE$4,"","")-1)*100,"") -> 1.4561327 | G39: =IFERROR(E39/5-F39/20,"") -> 0.78081414 | H39: 78.38 | I39: 603083.SH | J39: 剑桥科技 | K39: 564.3233 | L39: 34.78 | M39: 688027.SH | N39: 国盾量子 | O39: 317.3645 | P39: 19.56 | Q39: 300628.SZ | R39: 亿联网络 | S39: 154.1245 | T39: 9.5 | U39: 603236.SH | V39: 移远通信 | W39: 142.812 | X39: 8.8 | Y39: 300638.SZ | Z39: 广和通 | AA39: 93.1183 | AB39: 5.74
A40: CI005578.CI | B40: 其他文化娱乐指数 | C40: 7 | D40: =IFERROR(([1]!thsiFinD("ths_close_price_index",$A40,$AE$2,"","")/[1]!thsiFinD("ths_close_price_index",$A40,$AE$5,"","")-1)*100,"") -> -12.631676 | E40: =IFERROR(([1]!thsiFinD("ths_close_price_index",$A40,$AE$2,"","")/[1]!thsiFinD("ths_close_price_index",$A40,$AE$3,"","")-1)*100,"") -> -2.3298733 | F40: =IFERROR(([1]!thsiFinD("ths_close_price_index",$A40,$AE$2,"","")/[1]!thsiFinD("ths_close_price_index",$A40,$AE$4,"","")-1)*100,"") -> -20.14827 | G40: =IFERROR(E40/5-F40/20,"") -> 0.54143885 | H40: 86.6 | I40: 603533.SH | J40: 掌阅科技 | K40: 58.3757 | L40: 27.88 | M40: 600158.SH | N40: 中体产业 | O40: 52.0681 | P40: 24.87 | Q40: 603466.SH | R40: 风语筑 | S40: 35.7283 | T40: 17.06 | U40: 600136.SH | V40: ST明诚 | W40: 17.8507 | X40: 8.53 | Y40: 300860.SZ | Z40: 锋尚文化 | AA40: 17.2872 | AB40: 8.26
... A48: CI005545.CI | B48: LED指数 | C48: 26 | D48: =IFERROR(([1]!thsiFinD("ths_close_price_index",$A48,$AE$2,"","")/[1]!thsiFinD("ths_close_price_index",$A48,$AE$5,"","")-1)*100,"") -> 19.702331 | E48: =IFERROR(([1]!thsiFinD("ths_close_price_index",$A48,$AE$2,"","")/[1]!thsiFinD("ths_close_price_index",$A48,$AE$3,"","")-1)*100,"") -> 5.5178131 | F48: =IFERROR(([1]!thsiFinD("ths_close_price_index",$A48,$AE$2,"","")/[1]!thsiFinD("ths_close_price_index",$A48,$AE$4,"","")-1)*100,"") -> 5.6637977 | G48: =IFERROR(E48/5-F48/20,"") -> 0.82037274 | H48: 81.7 | I48: 600703.SH | J48: 三安光电 | K48: 654.6462 | L48: 56.05 | M48: 300303.SZ | N48: 聚飞光电 | O48: 111.7501 | P48: 9.57 | Q48: 002654.SZ | R48: 万润科技 | S48: 91.4079 | T48: 7.83 | U48: 300102.SZ | V48: 乾照光电 | W48: 54.2 | X48: 4.64 | Y48: 300219.SZ | Z48: 鸿利智汇 | AA48: 42.1244 | AB48: 3.61
A49: CI005294.CI | B49: 专用汽车指数 | C49: 3 | D49: =IFERROR(([1]!thsiFinD("ths_close_price_index",$A49,$AE$2,"","")/[1]!thsiFinD("ths_close_price_index",$A49,$AE$5,"","")-1)*100,"") -> 39.921973 | E49: =IFERROR(([1]!thsiFinD("ths_close_price_index",$A49,$AE$2,"","")/[1]!thsiFinD("ths_close_price_index",$A49,$AE$3,"","")-1)*100,"") -> -3.004264 | F49: =IFERROR(([1]!thsiFinD("ths_close_price_index",$A49,$AE$2,"","")/[1]!thsiFinD("ths_close_price_index",$A49,$AE$4,"","")-1)*100,"") -> -12.418249 | G49: =IFERROR(E49/5-F49/20,"") -> 0.020059677 | H49: 100 | I49: 601965.SH | J49: 中国汽研 | K49: 46.6219 | L49: 61.68 | M49: 603611.SH | N49: 诺力股份 | O49: 28.9697 | P49: 38.32
A50: CI005297.CI | B50: 摩托车及其他Ⅲ指数 | C50: 13 | D50: =IFERROR(([1]!thsiFinD("ths_close_price_index",$A50,$AE$2,"","")/[1]!thsiFinD("ths_close_price_index",$A50,$AE$5,"","")-1)*100,"") -> -15.701845 | E50: =IFERROR(([1]!thsiFinD("ths_close_price_index",$A50,$AE$2,"","")/[1]!thsiFinD("ths_close_price_index",$A50,$AE$3,"","")-1)*100,"") -> 1.4120549 | F50: =IFERROR(([1]!thsiFinD("ths_close_price_index",$A50,$AE$2,"","")/[1]!thsiFinD("ths_close_price_index",$A50,$AE$4,"","")-1)*100,"") -> -7.4219567 | G50: =IFERROR(E50/5-F50/20,"") -> 0.65350881 | H50: 79.22 | I50: 603129.SH | J50: 春风动力 | K50: 214.0442 | L50: 26.61 | M50: 601777.SH | N50: 千里科技 | O50: 171.181 | P50: 21.28 | Q50: 603766.SH | R50: 隆鑫通用 | S50: 139.926 | T50: 17.4 | U50: 301345.SZ | V50: 涛涛车业 | W50: 62.2649 | X50: 7.74 | Y50: 301322.SZ | Z50: 绿通科技 | AA50: 49.7629 | AB50: 6.19
A51: CI005436.CI | B51: 建筑装修Ⅲ指数 | C51: 27 | D51: =IFERROR(([1]!thsiFinD("ths_close_price_index",$A51,$AE$2,"","")/[1]!thsiFinD("ths_close_price_index",$A51,$AE$5,"","")-1)*100,"") -> 12.722416 | E51: =IFERROR(([1]!thsiFinD("ths_close_price_index",$A51,$AE$2,"","")/[1]!thsiFinD("ths_close_price_index",$A51,$AE$3,"","")-1)*100,"") -> 0.62448854 | F51: =IFERROR(([1]!thsiFinD("ths_close_price_index",$A51,$AE$2,"","")/[1]!thsiFinD("ths_close_price_index",$A51,$AE$4,"","")-1)*100,"") -> -5.2452475 | G51: =IFERROR(E51/5-F51/20,"") -> 0.38716008 | H51: 44.89 | I51: 002081.SZ | J51: 金螳螂 | K51: 63.1568 | L51: 12.47 | M51: 002047.SZ | N51: 宝鹰股份 | O51: 44.8026 | P51: 8.84 | Q51: 600234.SH | R51: 科新发展 | S51: 42.1723 | T51: 8.33 | U51: 300668.SZ | V51: 杰恩股份 | W51: 39.3722 | X51: 7.77 | Y51: 002989.SZ | Z51: 中天精装 | AA51: 37.908 | AB51: 7.48
A52: CI005387.CI | B52: 非棉纺织品指数 | C52: 13 | D52: =IFERROR(([1]!thsiFinD("ths_close_price_index",$A52,$AE$2,"","")/[1]!thsiFinD("ths_close_price_index",$A52,$AE$5,"","")-1)*100,"") -> -13.404022 | E52: =IFERROR(([1]!thsiFinD("ths_close_price_index",$A52,$AE$2,"","")/[1]!thsiFinD("ths_close_price_index",$A52,$AE$3,"","")-1)*100,"") -> -2.3782433 | F52: =IFERROR(([1]!thsiFinD("ths_close_price_index",$A52,$AE$2,"","")/[1]!thsiFinD("ths_close_price_index",$A52,$AE$4,"","")-1)*100,"") -> -10.676649 | G52: =IFERROR(E52/5-F52/20,"") -> 0.058183793 | H52: 51.24 | I52: 603889.SH | J52: 新澳股份 | K52: 29.4978 | L52: 11.82 | M52: 600527.SH | N52: 江南高纤 | O52: 28.2929 | P52: 11.33 | Q52: 601599.SH | R52: 浙文影业 | S52: 27.0496 | T52: 10.84 | U52: 600156.SH | V52: 华升股份 | W52: 21.6966 | X52: 8.69 | Y52: 603055.SH | Z52: 台华新材 | AA52: 21.3591 | AB52: 8.56
A53: CI005347.CI | B53: 信托指数 | C53: 2 | D53: =IFERROR(([1]!thsiFinD("ths_close_price_index",$A53,$AE$2,"","")/[1]!thsiFinD("ths_close_price_index",$A53,$AE$5,"","")-1)*100,"") -> -10.818778 | E53: =IFERROR(([1]!thsiFinD("ths_close_price_index",$A53,$AE$2,"","")/[1]!thsiFinD("ths_close_price_index",$A53,$AE$3,"","")-1)*100,"") -> 1.0053474 | F53: =IFERROR(([1]!thsiFinD("ths_close_price_index",$A53,$AE$2,"","")/[1]!thsiFinD("ths_close_price_index",$A53,$AE$4,"","")-1)*100,"") -> -8.9376049 | G53: =IFERROR(E53/5-F53/20,"") -> 0.64794974 | H53: 100 | I53: 600816.SH | J53: 建元信托 | K53: 92.4713 | L53: 51.89 | M53: 000563.SZ | N53: 陕国投A | O53: 85.7216 | P53: 48.11
A54: CI005318.CI | B54: 中药饮片指数 | C54: 4 | D54: =IFERROR(([1]!thsiFinD("ths_close_price_index",$A54,$AE$2,"","")/[1]!thsiFinD("ths_close_price_index",$A54,$AE$5,"","")-1)*100,"") -> -31.724172 | E54: =IFERROR(([1]!thsiFinD("ths_close_price_index",$A54,$AE$2,"","")/[1]!thsiFinD("ths_close_price_index",$A54,$AE$3,"","")-1)*100,"") -> -8.8269993 | F54: =IFERROR(([1]!thsiFinD("ths_close_price_index",$A54,$AE$2,"","")/[1]!thsiFinD("ths_close_price_index",$A54,$AE$4,"","")-1)*100,"") -> -14.464307 | G54: =IFERROR(E54/5-F54/20,"") -> -1.0421845 | H54: 100 | I54: 600518.SH | J54: 康美药业 | K54: 139.2247 | L54: 75.31 | M54: 603896.SH | N54: 寿仙谷 | O54: 16.1924 | P54: 8.76 | Q54: 002907.SZ | R54: 华森制药 | S54: 16.1261 | T54: 8.72 | U54: 002873.SZ | V54: 新天药业 | W54: 13.3236 | X54: 7.21
A55: CI005525.CI | B55: 其他非银金融指数 | C55: 7 | D55: =IFERROR(([1]!thsiFinD("ths_close_price_index",$A55,$AE$2,"","")/[1]!thsiFinD("ths_close_price_index",$A55,$AE$5,"","")-1)*100,"") -> -9.5134416 | E55: =IFERROR(([1]!thsiFinD("ths_close_price_index",$A55,$AE$2,"","")/[1]!thsiFinD("ths_close_price_index",$A55,$AE$3,"","")-1)*100,"") -> 2.4142643 | F55: =IFERROR(([1]!thsiFinD("ths_close_price_index",$A55,$AE$2,"","")/[1]!thsiFinD("ths_close_price_index",$A55,$AE$4,"","")-1)*100,"") -> -4.4574904 | G55: =IFERROR(E55/5-F55/20,"") -> 0.70572738 | H55: 90.44 | I55: 000617.SZ | J55: 中油资本 | K55: 218.1536 | L55: 40.82 | M55: 000987.SZ | N55: 越秀资本 | O55: 109.0819 | P55: 20.41 | Q55: 002647.SZ | R55: 仁东控股 | S55: 94.7077 | T55: 17.72 | U55: 603093.SH | V55: 南华期货 | W55: 30.7337 | X55: 5.75 | Y55: 002961.SZ | Z55: 瑞达期货 | AA55: 30.6532 | AB55: 5.74
A56: CI005284.CI | B56: 风电指数 | C56: 20 | D56: =IFERROR(([1]!thsiFinD("ths_close_price_index",$A56,$AE$2,"","")/[1]!thsiFinD("ths_close_price_index",$A56,$AE$5,"","")-1)*100,"") -> -10.983597 | E56: =IFERROR(([1]!thsiFinD("ths_close_price_index",$A56,$AE$2,"","")/[1]!thsiFinD("ths_close_price_index",$A56,$AE$3,"","")-1)*100,"") -> -3.942318 | F56: =IFERROR(([1]!thsiFinD("ths_close_price_index",$A56,$AE$2,"","")/[1]!thsiFinD("ths_close_price_index",$A56,$AE$4,"","")-1)*100,"") -> -18.765396 | G56: =IFERROR(E56/5-F56/20,"") -> 0.14980622 | H56: 89.48 | I56: 301526.SZ | J56: 国际复材 | K56: 584.2275 | L56: 48.02 | M56: 300748.SZ | N56: 金力永磁 | O56: 225.3239 | P56: 18.52 | Q56: 600416.SH | R56: 湘电股份 | S56: 102.352 | T56: 8.41 | U56: 300185.SZ | V56: 通裕重工 | W56: 95.7672 | X56: 7.87 | Y56: 002531.SZ | Z56: 天顺风能 | AA56: 81.0341 | AB56: 6.66
A57: CI005261.CI | B57: 陶瓷指数 | C57: 6 | D57: =IFERROR(([1]!thsiFinD("ths_close_price_index",$A57,$AE$2,"","")/[1]!thsiFinD("ths_close_price_index",$A57,$AE$5,"","")-1)*100,"") -> -21.870021 | E57: =IFERROR(([1]!thsiFinD("ths_close_price_index",$A57,$AE$2,"","")/[1]!thsiFinD("ths_close_price_index",$A57,$AE$3,"","")-1)*100,"") -> -6.070654 | F57: =IFERROR(([1]!thsiFinD("ths_close_price_index",$A57,$AE$2,"","")/[1]!thsiFinD("ths_close_price_index",$A57,$AE$4,"","")-1)*100,"") -> -14.574925 | G57: =IFERROR(E57/5-F57/20,"") -> -0.48538455 | H57: 89.45 | I57: 002798.SZ | J57: 帝欧水华 | K57: 22.7822 | L57: 21.93 | M57: 003012.SZ | N57: 东鹏控股 | O57: 22.077 | P57: 21.25 | Q57: 001386.SZ | R57: 马可波罗 | S57: 16.8089 | T57: 16.18 | U57: 002162.SZ | V57: 悦心健康 | W57: 15.6624 | X57: 15.07 | Y57: 002918.SZ | Z57: 蒙娜丽莎 | AA57: 15.6043 | AB57: 15.02
A58: CI005567.CI | B58: 云软件服务指数 | C58: 4 | D58: =IFERROR(([1]!thsiFinD("ths_close_price_index",$A58,$AE$2,"","")/[1]!thsiFinD("ths_close_price_index",$A58,$AE$5,"","")-1)*100,"") -> -30.784645 | E58: =IFERROR(([1]!thsiFinD("ths_close_price_index",$A58,$AE$2,"","")/[1]!thsiFinD("ths_close_price_index",$A58,$AE$3,"","")-1)*100,"") -> -3.2543881 | F58: =IFERROR(([1]!thsiFinD("ths_close_price_index",$A58,$AE$2,"","")/[1]!thsiFinD("ths_close_price_index",$A58,$AE$4,"","")-1)*100,"") -> -10.945201 | G58: =IFERROR(E58/5-F58/20,"") -> -0.10361754 | H58: 100 | I58: 688111.SH | J58: 金山办公 | K58: 450.13 | L58: 55.87 | M58: 600588.SH | N58: 用友网络 | O58: 178.5689 | P58: 22.16 | Q58: 002410.SZ | R58: 广联达 | S58: 116.7282 | T58: 14.49 | U58: 002153.SZ | V58: 石基信息 | W58: 60.2737 | X58: 7.48
A59: CI005451.CI | B59: 叉车指数 | C59: 4 | D59: =IFERROR(([1]!thsiFinD("ths_close_price_index",$A59,$AE$2,"","")/[1]!thsiFinD("ths_close_price_index",$A59,$AE$5,"","")-1)*100,"") -> -13.568778 | E59: =IFERROR(([1]!thsiFinD("ths_close_price_index",$A59,$AE$2,"","")/[1]!thsiFinD("ths_close_price_index",$A59,$AE$3,"","")-1)*100,"") -> -4.9300912 | F59: =IFERROR(([1]!thsiFinD("ths_close_price_index",$A59,$AE$2,"","")/[1]!thsiFinD("ths_close_price_index",$A59,$AE$4,"","")-1)*100,"") -> -4.8201327 | G59: =IFERROR(E59/5-F59/20,"") -> -0.7450116 | H59: 100 | I59: 603298.SH | J59: 杭叉集团 | K59: 130.622 | L59: 43.07 | M59: 600761.SH | N59: 安徽合力 | O59: 102.6424 | P59: 33.84 | Q59: 603194.SH | R59: 中力股份 | S59: 59.1021 | T59: 19.49 | U59: 301279.SZ | V59: 金道科技 | W59: 10.907 | X59: 3.6
A60: CI005548.CI | B60: 消费电子组件指数 | C60: 91 | D60: =IFERROR(([1]!thsiFinD("ths_close_price_index",$A60,$AE$2,"","")/[1]!thsiFinD("ths_close_price_index",$A60,$AE$5,"","")-1)*100,"") -> 48.694095 | E60: =IFERROR(([1]!thsiFinD("ths_close_price_index",$A60,$AE$2,"","")/[1]!thsiFinD("ths_close_price_index",$A60,$AE$3,"","")-1)*100,"") -> 2.1752303 | F60: =IFERROR(([1]!thsiFinD("ths_close_price_index",$A60,$AE$2,"","")/[1]!thsiFinD("ths_close_price_index",$A60,$AE$4,"","")-1)*100,"") -> 7.1069762 | G60: =IFERROR(E60/5-F60/20,"") -> 0.079697255 | H60: 60.15 | I60: 002384.SZ | J60: 东山精密 | K60: 3304.4222 | L60: 21.57 | M60: 002475.SZ | N60: 立讯精密 | O60: 3103.8119 | P60: 20.26 | Q60: 300857.SZ | R60: 协创数据 | S60: 1021.0415 | T60: 6.67 | U60: 300433.SZ | V60: 蓝思科技 | W60: 1012.201 | X60: 6.61 | Y60: 002938.SZ | Z60: 鹏鼎控股 | AA60: 771.4252 | AB60: 5.04
A61: CI005388.CI | B61: 印染指数 | C61: 5 | D61: =IFERROR(([1]!thsiFinD("ths_close_price_index",$A61,$AE$2,"","")/[1]!thsiFinD("ths_close_price_index",$A61,$AE$5,"","")-1)*100,"") -> -9.1295131 | E61: =IFERROR(([1]!thsiFinD("ths_close_price_index",$A61,$AE$2,"","")/[1]!thsiFinD("ths_close_price_index",$A61,$AE$3,"","")-1)*100,"") -> -2.2880362 | F61: =IFERROR(([1]!thsiFinD("ths_close_price_index",$A61,$AE$2,"","")/[1]!thsiFinD("ths_close_price_index",$A61,$AE$4,"","")-1)*100,"") -> -13.077638 | G61: =IFERROR(E61/5-F61/20,"") -> 0.19627465 | H61: 100 | I61: 600987.SH | J61: 航民股份 | K61: 30.282 | L61: 35.05 | M61: 605055.SH | N61: 迎丰股份 | O61: 14.2936 | P61: 16.54 | Q61: 605189.SH | R61: 富春染织 | S61: 14.1962 | T61: 16.43 | U61: 600448.SH | V61: 华纺股份 | W61: 13.99 | X61: 16.19 | Y61: 002144.SZ | Z61: 宏达高科 | AA61: 13.6408 | AB61: 15.79
A62: CI005540.CI | B62: 半导体材料指数 | C62: 22 | D62: =IFERROR(([1]!thsiFinD("ths_close_price_index",$A62,$AE$2,"","")/[1]!thsiFinD("ths_close_price_index",$A62,$AE$5,"","")-1)*100,"") -> 132.09258 | E62: =IFERROR(([1]!thsiFinD("ths_close_price_index",$A62,$AE$2,"","")/[1]!thsiFinD("ths_close_price_index",$A62,$AE$3,"","")-1)*100,"") -> 10.235065 | F62: =IFERROR(([1]!thsiFinD("ths_close_price_index",$A62,$AE$2,"","")/[1]!thsiFinD("ths_close_price_index",$A62,$AE$4,"","")-1)*100,"") -> 36.674855 | G62: =IFERROR(E62/5-F62/20,"") -> 0.21327028 | H62: 54.76 | I62: 300666.SZ | J62: 江丰电子 | K62: 638.8789 | L62: 13.21 | M62: 688126.SH | N62: 沪硅产业 | O62: 600.2852 | P62: 12.41 | Q62: 688146.SH | R62: 中船特气 | S62: 565.3718 | T62: 11.69 | U62: 002409.SZ | V62: 雅克科技 | W62: 439.4687 | X62: 9.09 | Y62: 300346.SZ | Z62: 南大光电 | AA62: 404.2595 | AB62: 8.36
A63: CI005469.CI | B63: 激光加工设备指数 | C63: 10 | D63: =IFERROR(([1]!thsiFinD("ths_close_price_index",$A63,$AE$2,"","")/[1]!thsiFinD("ths_close_price_index",$A63,$AE$5,"","")-1)*100,"") -> 198.24216 | E63: =IFERROR(([1]!thsiFinD("ths_close_price_index",$A63,$AE$2,"","")/[1]!thsiFinD("ths_close_price_index",$A63,$AE$3,"","")-1)*100,"") -> 10.215833 | F63: =IFERROR(([1]!thsiFinD("ths_close_price_index",$A63,$AE$2,"","")/[1]!thsiFinD("ths_close_price_index",$A63,$AE$4,"","")-1)*100,"") -> 14.02073 | G63: =IFERROR(E63/5-F63/20,"") -> 1.34213 | H63: 89.2 | I63: 002008.SZ | J63: 大族激光 | K63: 1030.1521 | L63: 49.72 | M63: 688025.SH | N63: 杰普特 | O63: 273.465 | P63: 13.2 | Q63: 300776.SZ | R63: 帝尔激光 | S63: 253.0384 | T63: 12.21 | U63: 300747.SZ | V63: 锐科激光 | W63: 171.5275 | X63: 8.28 | Y63: 301021.SZ | Z63: 英诺激光 | AA63: 119.8984 | AB63: 5.79
A64: CI005514.CI | B64: 其他食品指数 | C64: 13 | D64: =IFERROR(([1]!thsiFinD("ths_close_price_index",$A64,$AE$2,"","")/[1]!thsiFinD("ths_close_price_index",$A64,$AE$5,"","")-1)*100,"") -> -20.313556 | E64: =IFERROR(([1]!thsiFinD("ths_close_price_index",$A64,$AE$2,"","")/[1]!thsiFinD("ths_close_price_index",$A64,$AE$3,"","")-1)*100,"") -> 1.0843792 | F64: =IFERROR(([1]!thsiFinD("ths_close_price_index",$A64,$AE$2,"","")/[1]!thsiFinD("ths_close_price_index",$A64,$AE$4,"","")-1)*100,"") -> -2.8042912 | G64: =IFERROR(E64/5-F64/20,"") -> 0.35709041 | H64: 75.62 | I64: 600298.SH | J64: 安琪酵母 | K64: 187.8874 | L64: 37.7 | M64: 300146.SZ | N64: 汤臣倍健 | O64: 96.9437 | P64: 19.45 | Q64: 002626.SZ | R64: 金达威 | S64: 40.2741 | T64: 8.08 | U64: 002481.SZ | V64: 双塔食品 | W64: 26.777 | X64: 5.37 | Y64: 300858.SZ | Z64: 科拓生物 | AA64: 25.0053 | AB64: 5.02
A65: CI005444.CI | B65: 纸包装指数 | C65: 22 | D65: =IFERROR(([1]!thsiFinD("ths_close_price_index",$A65,$AE$2,"","")/[1]!thsiFinD("ths_close_price_index",$A65,$AE$5,"","")-1)*100,"") -> -0.37324883 | E65: =IFERROR(([1]!thsiFinD("ths_close_price_index",$A65,$AE$2,"","")/[1]!thsiFinD("ths_close_price_index",$A65,$AE$3,"","")-1)*100,"") -> -0.085813083 | F65: =IFERROR(([1]!thsiFinD("ths_close_price_index",$A65,$AE$2,"","")/[1]!thsiFinD("ths_close_price_index",$A65,$AE$4,"","")-1)*100,"") -> -0.10793798 | G65: =IFERROR(E65/5-F65/20,"") -> -0.011765717 | H65: 60.26 | I65: 002831.SZ | J65: 裕同科技 | K65: 167.1 | L65: 24.93 | M65: 002565.SZ | N65: 顺灏股份 | O65: 102.1006 | P65: 15.23 | Q65: 603687.SH | R65: 大胜达 | S65: 54.3544 | T65: 8.11 | U65: 002191.SZ | V65: 劲嘉股份 | W65: 45.3138 | X65: 6.76 | Y65: 601515.SH | Z65: 衢州东峰 | AA65: 35.051 | AB65: 5.23
A66: CI005445.CI | B66: 金属包装指数 | C66: 5 | D66: =IFERROR(([1]!thsiFinD("ths_close_price_index",$A66,$AE$2,"","")/[1]!thsiFinD("ths_close_price_index",$A66,$AE$5,"","")-1)*100,"") -> -16.298509 | E66: =IFERROR(([1]!thsiFinD("ths_close_price_index",$A66,$AE$2,"","")/[1]!thsiFinD("ths_close_price_index",$A66,$AE$3,"","")-1)*100,"") -> -4.7827773 | F66: =IFERROR(([1]!thsiFinD("ths_close_price_index",$A66,$AE$2,"","")/[1]!thsiFinD("ths_close_price_index",$A66,$AE$4,"","")-1)*100,"") -> -16.753057 | G66: =IFERROR(E66/5-F66/20,"") -> -0.1189026 | H66: 100.01 | I66: 002969.SZ | J66: 嘉美包装 | K66: 90.6384 | L66: 38.6 | M66: 002701.SZ | N66: 奥瑞金 | O66: 76.129 | P66: 32.42 | Q66: 601968.SH | R66: 宝钢包装 | S66: 24.7871 | T66: 10.55 | U66: 002846.SZ | V66: 英联股份 | W66: 21.7345 | X66: 9.26 | Y66: 002752.SZ | Z66: 昇兴股份 | AA66: 21.5491 | AB66: 9.18
A67: CI005559.CI | B67: 网络规划设计和工程施工指数 | C67: 8 | D67: =IFERROR(([1]!thsiFinD("ths_close_price_index",$A67,$AE$2,"","")/[1]!thsiFinD("ths_close_price_index",$A67,$AE$5,"","")-1)*100,"") -> -15.21327 | E67: =IFERROR(([1]!thsiFinD("ths_close_price_index",$A67,$AE$2,"","")/[1]!thsiFinD("ths_close_price_index",$A67,$AE$3,"","")-1)*100,"") -> -2.9639123 | F67: =IFERROR(([1]!thsiFinD("ths_close_price_index",$A67,$AE$2,"","")/[1]!thsiFinD("ths_close_price_index",$A67,$AE$4,"","")-1)*100,"") -> -13.237973 | G67: =IFERROR(E67/5-F67/20,"") -> 0.069116211 | H67: 84.54 | I67: 002929.SZ | J67: 润建股份 | K67: 104.0253 | L67: 25.76 | M67: 002544.SZ | N67: 普天科技 | O67: 84.568 | P67: 20.94 | Q67: 603220.SH | R67: 中贝通信 | S67: 80.0884 | T67: 19.83 | U67: 603322.SH | V67: 超讯科技 | W67: 39.2876 | X67: 9.73 | Y67: 002093.SZ | Z67: 国脉科技 | AA67: 33.4532 | AB67: 8.28
A68: CI005457.CI | B68: 油气装备指数 | C68: 13 | D68: =IFERROR(([1]!thsiFinD("ths_close_price_index",$A68,$AE$2,"","")/[1]!thsiFinD("ths_close_price_index",$A68,$AE$5,"","")-1)*100,"") -> 61.047146 | E68: =IFERROR(([1]!thsiFinD("ths_close_price_index",$A68,$AE$2,"","")/[1]!thsiFinD("ths_close_price_index",$A68,$AE$3,"","")-1)*100,"") -> -1.8947478 | F68: =IFERROR(([1]!thsiFinD("ths_close_price_index",$A68,$AE$2,"","")/[1]!thsiFinD("ths_close_price_index",$A68,$AE$4,"","")-1)*100,"") -> 3.1869601 | G68: =IFERROR(E68/5-F68/20,"") -> -0.53829756 | H68: 87.51 | I68: 002353.SZ | J68: 杰瑞股份 | K68: 997.6909 | L68: 75.23 | M68: 300164.SZ | N68: 通源石油 | O68: 47.1856 | P68: 3.56 | Q68: 300228.SZ | R68: 富瑞特装 | S68: 42.0129 | T68: 3.17 | U68: 300084.SZ | V68: 海默科技 | W68: 37.3796 | X68: 2.82 | Y68: 688377.SH | Z68: 迪威尔 | AA68: 36.2419 | AB68: 2.73
A69: CI005463.CI | B69: 起重运输设备指数 | C69: 7 | D69: =IFERROR(([1]!thsiFinD("ths_close_price_index",$A69,$AE$2,"","")/[1]!thsiFinD("ths_close_price_index",$A69,$AE$5,"","")-1)*100,"") -> -19.270593 | E69: =IFERROR(([1]!thsiFinD("ths_close_price_index",$A69,$AE$2,"","")/[1]!thsiFinD("ths_close_price_index",$A69,$AE$3,"","")-1)*100,"") -> -6.8028734 | F69: =IFERROR(([1]!thsiFinD("ths_close_price_index",$A69,$AE$2,"","")/[1]!thsiFinD("ths_close_price_index",$A69,$AE$4,"","")-1)*100,"") -> -14.187836 | G69: =IFERROR(E69/5-F69/20,"") -> -0.65118289 | H69: 88.56 | I69: 600320.SH | J69: 振华重工 | K69: 80.6148 | L69: 34.54 | M69: 600169.SH | N69: ST太重 | O69: 33.0182 | P69: 14.15 | Q69: 002483.SZ | R69: 润邦股份 | S69: 31.189 | T69: 13.36 | U69: 002523.SZ | V69: 天桥起重 | W69: 31.0867 | X69: 13.32 | Y69: 603966.SH | Z69: 法兰泰克 | AA69: 30.7784 | AB69: 13.19
A70: CI005296.CI | B70: 汽车销售及服务Ⅲ指数 | C70: 5 | D70: =IFERROR(([1]!thsiFinD("ths_close_price_index",$A70,$AE$2,"","")/[1]!thsiFinD("ths_close_price_index",$A70,$AE$5,"","")-1)*100,"") -> -20.923228 | E70: =IFERROR(([1]!thsiFinD("ths_close_price_index",$A70,$AE$2,"","")/[1]!thsiFinD("ths_close_price_index",$A70,$AE$3,"","")-1)*100,"") -> -2.3057969 | F70: =IFERROR(([1]!thsiFinD("ths_close_price_index",$A70,$AE$2,"","")/[1]!thsiFinD("ths_close_price_index",$A70,$AE$4,"","")-1)*100,"") -> -11.072734 | G70: =IFERROR(E70/5-F70/20,"") -> 0.092477335 | H70: 100 | I70: 600335.SH | J70: 国机汽车 | K70: 23.8202 | L70: 25.81 | M70: 600653.SH | N70: 申华控股 | O70: 22.4586 | P70: 24.34 | Q70: 301215.SZ | R70: 中汽股份 | S70: 20.2826 | T70: 21.98 | U70: 000757.SZ | V70: 浩物股份 | W70: 17.3664 | X70: 18.82 | Y70: 605151.SH | Z70: 西上海 | AA70: 8.3491 | AB70: 9.05
A71: CI005353.CI | B71: 公路指数 | C71: 19 | D71: =IFERROR(([1]!thsiFinD("ths_close_price_index",$A71,$AE$2,"","")/[1]!thsiFinD("ths_close_price_index",$A71,$AE$5,"","")-1)*100,"") -> -6.152555 | E71: =IFERROR(([1]!thsiFinD("ths_close_price_index",$A71,$AE$2,"","")/[1]!thsiFinD("ths_close_price_index",$A71,$AE$3,"","")-1)*100,"") -> -1.0044199 | F71: =IFERROR(([1]!thsiFinD("ths_close_price_index",$A71,$AE$2,"","")/[1]!thsiFinD("ths_close_price_index",$A71,$AE$4,"","")-1)*100,"") -> -5.1727322 | G71: =IFERROR(E71/5-F71/20,"") -> 0.05775263 | H71: 52.46 | I71: 001965.SZ | J71: 招商公路 | K71: 180.8845 | L71: 22.63 | M71: 000429.SZ | N71: 粤高速A | O71: 68.1543 | P71: 8.53 | Q71: 600350.SH | R71: 山东高速 | S71: 64.3806 | T71: 8.05 | U71: 600377.SH | V71: 宁沪高速 | W71: 56.0728 | X71: 7.02 | Y71: 600269.SH | Z71: 赣粤高速 | AA71: 49.7607 | AB71: 6.23
... A75: CI005577.CI | B75: 游戏指数 | C75: 23 | D75: =IFERROR(([1]!thsiFinD("ths_close_price_index",$A75,$AE$2,"","")/[1]!thsiFinD("ths_close_price_index",$A75,$AE$5,"","")-1)*100,"") -> -20.726341 | E75: =IFERROR(([1]!thsiFinD("ths_close_price_index",$A75,$AE$2,"","")/[1]!thsiFinD("ths_close_price_index",$A75,$AE$3,"","")-1)*100,"") -> 5.4308486 | F75: =IFERROR(([1]!thsiFinD("ths_close_price_index",$A75,$AE$2,"","")/[1]!thsiFinD("ths_close_price_index",$A75,$AE$4,"","")-1)*100,"") -> -3.8390224 | G75: =IFERROR(E75/5-F75/20,"") -> 1.2781208 | H75: 60.46 | I75: 002602.SZ | J75: 世纪华通 | K75: 745.5625 | L75: 26.31 | M75: 002558.SZ | N75: 巨人网络 | O75: 293.6373 | P75: 10.36 | Q75: 002517.SZ | R75: 恺英网络 | S75: 257.0812 | T75: 9.07 | U75: 002555.SZ | V75: 三七互娱 | W75: 254.6419 | X75: 8.99 | Y75: 002624.SZ | Z75: 完美世界 | AA75: 162.3442 | AB75: 5.73
A76: CI005409.CI | B76: 钢铁耗材指数 | C76: 4 | D76: =IFERROR(([1]!thsiFinD("ths_close_price_index",$A76,$AE$2,"","")/[1]!thsiFinD("ths_close_price_index",$A76,$AE$5,"","")-1)*100,"") -> 7.9103392 | E76: =IFERROR(([1]!thsiFinD("ths_close_price_index",$A76,$AE$2,"","")/[1]!thsiFinD("ths_close_price_index",$A76,$AE$3,"","")-1)*100,"") -> 6.4347356 | F76: =IFERROR(([1]!thsiFinD("ths_close_price_index",$A76,$AE$2,"","")/[1]!thsiFinD("ths_close_price_index",$A76,$AE$4,"","")-1)*100,"") -> 6.7624818 | G76: =IFERROR(E76/5-F76/20,"") -> 0.94882303 | H76: 100 | I76: 000629.SZ | J76: 钒钛股份 | K76: 143.708 | L76: 77.33 | M76: 688119.SH | N76: 中钢洛耐 | O76: 31.2147 | P76: 16.8 | Q76: 300930.SZ | R76: 屹通新材 | S76: 10.9121 | T76: 5.87
A77: CI005571.CI | B77: 产业互联网综合服务指数 | C77: 2 | D77: =IFERROR(([1]!thsiFinD("ths_close_price_index",$A77,$AE$2,"","")/[1]!thsiFinD("ths_close_price_index",$A77,$AE$5,"","")-1)*100,"") -> -10.423608 | E77: =IFERROR(([1]!thsiFinD("ths_close_price_index",$A77,$AE$2,"","")/[1]!thsiFinD("ths_close_price_index",$A77,$AE$3,"","")-1)*100,"") -> -3.6863552 | F77: =IFERROR(([1]!thsiFinD("ths_close_price_index",$A77,$AE$2,"","")/[1]!thsiFinD("ths_close_price_index",$A77,$AE$4,"","")-1)*100,"") -> -11.913334 | G77: =IFERROR(E77/5-F77/20,"") -> -0.14160432 | H77: 100 | I77: 002195.SZ | J77: 岩山科技 | K77: 363.4451 | L77: 56.83 | M77: 601360.SH | N77: 三六零 | O77: 276.0508 | P77: 43.17
A78: CI005429.CI | B78: 其他塑料制品指数 | C78: 22 | D78: =IFERROR(([1]!thsiFinD("ths_close_price_index",$A78,$AE$2,"","")/[1]!thsiFinD("ths_close_price_index",$A78,$AE$5,"","")-1)*100,"") -> 21.293126 | E78: =IFERROR(([1]!thsiFinD("ths_close_price_index",$A78,$AE$2,"","")/[1]!thsiFinD("ths_close_price_index",$A78,$AE$3,"","")-1)*100,"") -> -1.8715974 | F78: =IFERROR(([1]!thsiFinD("ths_close_price_index",$A78,$AE$2,"","")/[1]!thsiFinD("ths_close_price_index",$A78,$AE$4,"","")-1)*100,"") -> 1.356477 | G78: =IFERROR(E78/5-F78/20,"") -> -0.44214333 | H78: 69.21 | I78: 603002.SH | J78: 宏昌电子 | K78: 137.9089 | L78: 28.47 | M78: 301216.SZ | N78: 万凯新材 | O78: 85.8616 | P78: 17.73 | Q78: 300180.SZ | R78: 华峰超纤 | S78: 56.142 | T78: 11.59 | U78: 300920.SZ | V78: 润阳科技 | W78: 30.3896 | X78: 6.27 | Y78: 300230.SZ | Z78: 永利股份 | AA78: 24.9626 | AB78: 5.15
A79: CI005509.CI | B79: 儿童品牌指数 | C79: 4 | D79: =IFERROR(([1]!thsiFinD("ths_close_price_index",$A79,$AE$2,"","")/[1]!thsiFinD("ths_close_price_index",$A79,$AE$5,"","")-1)*100,"") -> 10.305338 | E79: =IFERROR(([1]!thsiFinD("ths_close_price_index",$A79,$AE$2,"","")/[1]!thsiFinD("ths_close_price_index",$A79,$AE$3,"","")-1)*100,"") -> -2.7135273 | F79: =IFERROR(([1]!thsiFinD("ths_close_price_index",$A79,$AE$2,"","")/[1]!thsiFinD("ths_close_price_index",$A79,$AE$4,"","")-1)*100,"") -> -15.824877 | G79: =IFERROR(E79/5-F79/20,"") -> 0.2485384 | H79: 100.01 | I79: 002875.SZ | J79: 安奈儿 | K79: 22.2813 | L79: 33.87 | M79: 603557.SH | N79: *ST起步 | O79: 19.2024 | P79: 29.19 | Q79: 002762.SZ | R79: 金发拉比 | S79: 13.8462 | T79: 21.05 | U79: 301276.SZ | V79: 嘉曼服饰 | W79: 10.4626 | X79: 15.9
A80: CI005568.CI | B80: 咨询实施及其他服务指数 | C80: 21 | D80: =IFERROR(([1]!thsiFinD("ths_close_price_index",$A80,$AE$2,"","")/[1]!thsiFinD("ths_close_price_index",$A80,$AE$5,"","")-1)*100,"") -> -8.9780908 | E80: =IFERROR(([1]!thsiFinD("ths_close_price_index",$A80,$AE$2,"","")/[1]!thsiFinD("ths_close_price_index",$A80,$AE$3,"","")-1)*100,"") -> -2.9533878 | F80: =IFERROR(([1]!thsiFinD("ths_close_price_index",$A80,$AE$2,"","")/[1]!thsiFinD("ths_close_price_index",$A80,$AE$4,"","")-1)*100,"") -> -5.1535683 | G80: =IFERROR(E80/5-F80/20,"") -> -0.33299914 | H80: 60.13 | I80: 301236.SZ | J80: 软通动力 | K80: 251.1993 | L80: 14.39 | M80: 600410.SH | N80: 华胜天成 | O80: 211.6235 | P80: 12.12 | Q80: 000034.SZ | R80: 神州数码 | S80: 208.7606 | T80: 11.96 | U80: 688343.SH | V80: 云天励飞 | W80: 198.6348 | X80: 11.38 | Y80: 300170.SZ | Z80: 汉得信息 | AA80: 179.4303 | AB80: 10.28
A81: CI005504.CI | B81: 其他家电指数 | C81: 17 | D81: =IFERROR(([1]!thsiFinD("ths_close_price_index",$A81,$AE$2,"","")/[1]!thsiFinD("ths_close_price_index",$A81,$AE$5,"","")-1)*100,"") -> -13.482064 | E81: =IFERROR(([1]!thsiFinD("ths_close_price_index",$A81,$AE$2,"","")/[1]!thsiFinD("ths_close_price_index",$A81,$AE$3,"","")-1)*100,"") -> -3.9366798 | F81: =IFERROR(([1]!thsiFinD("ths_close_price_index",$A81,$AE$2,"","")/[1]!thsiFinD("ths_close_price_index",$A81,$AE$4,"","")-1)*100,"") -> -11.418133 | G81: =IFERROR(E81/5-F81/20,"") -> -0.2164293 | H81: 98.65 | I81: 002050.SZ | J81: 三花智控 | K81: 936.8649 | L81: 65.23 | M81: 002032.SZ | N81: 苏泊尔 | O81: 250 | P81: 17.41 | Q81: 603355.SH | R81: 莱克电气 | S81: 100 | T81: 6.96 | U81: 002959.SZ | V81: 小熊电器 | W81: 80 | X81: 5.57 | Y81: 600336.SH | Z81: 澳柯玛 | AA81: 50 | AB81: 3.48
A82: CI005472.CI | B82: 输变电设备指数 | C82: 75 | D82: =IFERROR(([1]!thsiFinD("ths_close_price_index",$A82,$AE$2,"","")/[1]!thsiFinD("ths_close_price_index",$A82,$AE$5,"","")-1)*100,"") -> 16.169911 | E82: =IFERROR(([1]!thsiFinD("ths_close_price_index",$A82,$AE$2,"","")/[1]!thsiFinD("ths_close_price_index",$A82,$AE$3,"","")-1)*100,"") -> -1.0471866 | F82: =IFERROR(([1]!thsiFinD("ths_close_price_index",$A82,$AE$2,"","")/[1]!thsiFinD("ths_close_price_index",$A82,$AE$4,"","")-1)*100,"") -> -9.540015 | G82: =IFERROR(E82/5-F82/20,"") -> 0.26756344 | H82: 72.59 | I82: 002028.SZ | J82: 思源电气 | K82: 1114.0975 | L82: 25.05 | M82: 600089.SH | N82: 特变电工 | O82: 1038.6379 | P82: 23.35 | Q82: 600869.SH | R82: 远东股份 | S82: 441.0476 | T82: 9.91 | U82: 601179.SH | V82: 中国西电 | W82: 414.2039 | X82: 9.31 | Y82: 600577.SH | Z82: 精达股份 | AA82: 221.1621 | AB82: 4.97
A83: CI005406.CI | B83: 环保及水务指数 | C83: 111 | D83: =IFERROR(([1]!thsiFinD("ths_close_price_index",$A83,$AE$2,"","")/[1]!thsiFinD("ths_close_price_index",$A83,$AE$5,"","")-1)*100,"") -> 0.84728381 | E83: =IFERROR(([1]!thsiFinD("ths_close_price_index",$A83,$AE$2,"","")/[1]!thsiFinD("ths_close_price_index",$A83,$AE$3,"","")-1)*100,"") -> -0.97761711 | F83: =IFERROR(([1]!thsiFinD("ths_close_price_index",$A83,$AE$2,"","")/[1]!thsiFinD("ths_close_price_index",$A83,$AE$4,"","")-1)*100,"") -> -5.760693 | G83: =IFERROR(E83/5-F83/20,"") -> 0.092511229 | H83: 27.27 | I83: 603588.SH | J83: 高能环境 | K83: 228.6788 | L83: 8.77 | M83: 600388.SH | N83: 龙净环保 | O83: 136.5163 | P83: 5.24 | Q83: 600323.SH | R83: 瀚蓝环境 | S83: 123.8712 | T83: 4.75 | U83: 600008.SH | V83: 首创环保 | W83: 116.5184 | X83: 4.47 | Y83: 603568.SH | Z83: 伟明环保 | AA83: 105.3536 | AB83: 4.04
A84: CI005322.CI | B84: 医疗器械指数 | C84: 115 | D84: =IFERROR(([1]!thsiFinD("ths_close_price_index",$A84,$AE$2,"","")/[1]!thsiFinD("ths_close_price_index",$A84,$AE$5,"","")-1)*100,"") -> -9.8614139 | E84: =IFERROR(([1]!thsiFinD("ths_close_price_index",$A84,$AE$2,"","")/[1]!thsiFinD("ths_close_price_index",$A84,$AE$3,"","")-1)*100,"") -> -1.5751358 | F84: =IFERROR(([1]!thsiFinD("ths_close_price_index",$A84,$AE$2,"","")/[1]!thsiFinD("ths_close_price_index",$A84,$AE$4,"","")-1)*100,"") -> -8.0269835 | G84: =IFERROR(E84/5-F84/20,"") -> 0.086322018 | H84: 42.54 | I84: 300760.SZ | J84: 迈瑞医疗 | K84: 831.7666 | L84: 18.02 | M84: 688271.SH | N84: 联影医疗 | O84: 480.7772 | P84: 10.41 | Q84: 002432.SZ | R84: 九安医疗 | S84: 254.1528 | T84: 5.5 | U84: 688301.SH | V84: 奕瑞科技 | W84: 239.1471 | X84: 5.18 | Y84: 300677.SZ | Z84: 英科医疗 | AA84: 158.3866 | AB84: 3.43
A85: CI005412.CI | B85: 磷肥及磷化工指数 | C85: 9 | D85: =IFERROR(([1]!thsiFinD("ths_close_price_index",$A85,$AE$2,"","")/[1]!thsiFinD("ths_close_price_index",$A85,$AE$5,"","")-1)*100,"") -> 9.9029401 | E85: =IFERROR(([1]!thsiFinD("ths_close_price_index",$A85,$AE$2,"","")/[1]!thsiFinD("ths_close_price_index",$A85,$AE$3,"","")-1)*100,"") -> 13.043545 | F85: =IFERROR(([1]!thsiFinD("ths_close_price_index",$A85,$AE$2,"","")/[1]!thsiFinD("ths_close_price_index",$A85,$AE$4,"","")-1)*100,"") -> 11.124112 | G85: =IFERROR(E85/5-F85/20,"") -> 2.0525034 | H85: 89.62 | I85: 600096.SH | J85: 云天化 | K85: 365.5515 | L85: 29.88 | M85: 600141.SH | N85: 兴发集团 | O85: 336.7417 | P85: 27.52 | Q85: 600331.SH | R85: 宏达股份 | S85: 195.3365 | T85: 15.96 | U85: 002895.SZ | V85: 川恒股份 | W85: 100.9817 | X85: 8.25 | Y85: 002312.SZ | Z85: 川发龙蟒 | AA85: 98.0126 | AB85: 8.01
A86: CI005576.CI | B86: 动漫指数 | C86: 1 | D86: =IFERROR(([1]!thsiFinD("ths_close_price_index",$A86,$AE$2,"","")/[1]!thsiFinD("ths_close_price_index",$A86,$AE$5,"","")-1)*100,"") -> -27.570725 | E86: =IFERROR(([1]!thsiFinD("ths_close_price_index",$A86,$AE$2,"","")/[1]!thsiFinD("ths_close_price_index",$A86,$AE$3,"","")-1)*100,"") -> -1.5361117 | F86: =IFERROR(([1]!thsiFinD("ths_close_price_index",$A86,$AE$2,"","")/[1]!thsiFinD("ths_close_price_index",$A86,$AE$4,"","")-1)*100,"") -> -14.760818 | G86: =IFERROR(E86/5-F86/20,"") -> 0.43081858 | H86: 100 | I86: 002292.SZ | J86: 奥飞娱乐 | K86: 56.3362 | L86: 100
A87: CI005511.CI | B87: 其他时尚品指数 | C87: 6 | D87: =IFERROR(([1]!thsiFinD("ths_close_price_index",$A87,$AE$2,"","")/[1]!thsiFinD("ths_close_price_index",$A87,$AE$5,"","")-1)*100,"") -> -19.407418 | E87: =IFERROR(([1]!thsiFinD("ths_close_price_index",$A87,$AE$2,"","")/[1]!thsiFinD("ths_close_price_index",$A87,$AE$3,"","")-1)*100,"") -> -5.7997538 | F87: =IFERROR(([1]!thsiFinD("ths_close_price_index",$A87,$AE$2,"","")/[1]!thsiFinD("ths_close_price_index",$A87,$AE$4,"","")-1)*100,"") -> -14.127823 | G87: =IFERROR(E87/5-F87/20,"") -> -0.45355961 | H87: 99.99 | I87: 300591.SZ | J87: 万里马 | K87: 23.0955 | L87: 28.24 | M87: 300901.SZ | N87: 中胤时尚 | O87: 17.5136 | P87: 21.42 | Q87: 300577.SZ | R87: 开润股份 | S87: 17.289 | T87: 21.14 | U87: 600439.SH | V87: 瑞贝卡 | W87: 16.2097 | X87: 19.82 | Y87: 600137.SH | Z87: 浪莎股份 | AA87: 7.6621 | AB87: 9.37
A88: CI005330.CI | B88: 调味品指数 | C88: 13 | D88: =IFERROR(([1]!thsiFinD("ths_close_price_index",$A88,$AE$2,"","")/[1]!thsiFinD("ths_close_price_index",$A88,$AE$5,"","")-1)*100,"") -> 4.9744719 | E88: =IFERROR(([1]!thsiFinD("ths_close_price_index",$A88,$AE$2,"","")/[1]!thsiFinD("ths_close_price_index",$A88,$AE$3,"","")-1)*100,"") -> 2.6233097 | F88: =IFERROR(([1]!thsiFinD("ths_close_price_index",$A88,$AE$2,"","")/[1]!thsiFinD("ths_close_price_index",$A88,$AE$4,"","")-1)*100,"") -> 2.0443193 | G88: =IFERROR(E88/5-F88/20,"") -> 0.42244597 | H88: 82.32 | I88: 603288.SH | J88: 海天味业 | K88: 471.4195 | L88: 42.28 | M88: 600186.SH | N88: 莲花控股 | O88: 210.1983 | P88: 18.85 | Q88: 600872.SH | R88: 中炬高新 | S88: 102.2055 | T88: 9.17 | U88: 002507.SZ | V88: 涪陵榨菜 | W88: 84.4654 | X88: 7.58 | Y88: 603317.SH | Z88: 天味食品 | AA88: 49.5027 | AB88: 4.44
A89: CI005242.CI | B89: 绵纶指数 | C89: 4 | D89: =IFERROR(([1]!thsiFinD("ths_close_price_index",$A89,$AE$2,"","")/[1]!thsiFinD("ths_close_price_index",$A89,$AE$5,"","")-1)*100,"") -> -2.7145934 | E89: =IFERROR(([1]!thsiFinD("ths_close_price_index",$A89,$AE$2,"","")/[1]!thsiFinD("ths_close_price_index",$A89,$AE$3,"","")-1)*100,"") -> 1.8055389 | F89: =IFERROR(([1]!thsiFinD("ths_close_price_index",$A89,$AE$2,"","")/[1]!thsiFinD("ths_close_price_index",$A89,$AE$4,"","")-1)*100,"") -> 0.52102575 | G89: =IFERROR(E89/5-F89/20,"") -> 0.33505649 | H89: 100 | I89: 000782.SZ | J89: 恒申新材 | K89: 35.9588 | L89: 34.53 | M89: 600810.SH | N89: 神马股份 | O89: 30.7547 | P89: 29.53 | Q89: 605166.SH | R89: 聚合顺 | S89: 22.3939 | T89: 21.5 | U89: 603382.SH | V89: 海阳科技 | W89: 15.0396 | X89: 14.44
A90: CI005475.CI | B90: 电机指数 | C90: 14 | D90: =IFERROR(([1]!thsiFinD("ths_close_price_index",$A90,$AE$2,"","")/[1]!thsiFinD("ths_close_price_index",$A90,$AE$5,"","")-1)*100,"") -> -8.0418695 | E90: =IFERROR(([1]!thsiFinD("ths_close_price_index",$A90,$AE$2,"","")/[1]!thsiFinD("ths_close_price_index",$A90,$AE$3,"","")-1)*100,"") -> -4.8138015 | F90: =IFERROR(([1]!thsiFinD("ths_close_price_index",$A90,$AE$2,"","")/[1]!thsiFinD("ths_close_price_index",$A90,$AE$4,"","")-1)*100,"") -> -13.360915 | G90: =IFERROR(E90/5-F90/20,"") -> -0.29471454 | H90: 75.01 | I90: 603728.SH | J90: 鸣志电器 | K90: 107.7214 | L90: 27.03 | M90: 000922.SZ | N90: 佳电股份 | O90: 65.7454 | P90: 16.49 | Q90: 300660.SZ | R90: 江苏雷利 | S90: 61.9259 | T90: 15.54 | U90: 002892.SZ | V90: 科力尔 | W90: 42.2266 | X90: 10.59 | Y90: 603988.SH | Z90: 中电电机 | AA90: 21.3827 | AB90: 5.36
A91: CI005477.CI | B91: 储能指数 | C91: 12 | D91: =IFERROR(([1]!thsiFinD("ths_close_price_index",$A91,$AE$2,"","")/[1]!thsiFinD("ths_close_price_index",$A91,$AE$5,"","")-1)*100,"") -> 1.2360782 | E91: =IFERROR(([1]!thsiFinD("ths_close_price_index",$A91,$AE$2,"","")/[1]!thsiFinD("ths_close_price_index",$A91,$AE$3,"","")-1)*100,"") -> 0.10720697 | F91: =IFERROR(([1]!thsiFinD("ths_close_price_index",$A91,$AE$2,"","")/[1]!thsiFinD("ths_close_price_index",$A91,$AE$4,"","")-1)*100,"") -> -9.4414739 | G91: =IFERROR(E91/5-F91/20,"") -> 0.49351509 | H91: 100.01 | I91: 300001.SZ | J91: 特锐德 | K91: 278.5882 | L91: 52.45 | M91: 688063.SH | N91: 派能科技 | O91: 102.6818 | P91: 19.33 | Q91: 688717.SH | R91: 艾罗能源 | S91: 90.9856 | T91: 17.13 | U91: 300068.SZ | V91: ST南都 | W91: 33.3 | X91: 6.27 | Y91: 301327.SZ | Z91: 华宝新能 | AA91: 25.6405 | AB91: 4.83
A92: CI005215.CI | B92: 铅锌指数 | C92: 13 | D92: =IFERROR(([1]!thsiFinD("ths_close_price_index",$A92,$AE$2,"","")/[1]!thsiFinD("ths_close_price_index",$A92,$AE$5,"","")-1)*100,"") -> 20.939079 | E92: =IFERROR(([1]!thsiFinD("ths_close_price_index",$A92,$AE$2,"","")/[1]!thsiFinD("ths_close_price_index",$A92,$AE$3,"","")-1)*100,"") -> 1.6329874 | F92: =IFERROR(([1]!thsiFinD("ths_close_price_index",$A92,$AE$2,"","")/[1]!thsiFinD("ths_close_price_index",$A92,$AE$4,"","")-1)*100,"") -> 0.4275119 | G92: =IFERROR(E92/5-F92/20,"") -> 0.30522189 | H92: 66.35 | I92: 000426.SZ | J92: 兴业银锡 | K92: 554.814 | L92: 24.52 | M92: 600497.SH | N92: 驰宏锌锗 | O92: 338.8767 | P92: 14.98 | Q92: 000060.SZ | R92: 中金岭南 | S92: 273.6435 | T92: 12.09 | U92: 601020.SH | V92: 华钰矿业 | W92: 167.3538 | X92: 7.4 | Y92: 600961.SH | Z92: 株冶集团 | AA92: 166.4911 | AB92: 7.36
A93: CI005481.CI | B93: 车用电机电控指数 | C93: 15 | D93: =IFERROR(([1]!thsiFinD("ths_close_price_index",$A93,$AE$2,"","")/[1]!thsiFinD("ths_close_price_index",$A93,$AE$5,"","")-1)*100,"") -> -11.411403 | E93: =IFERROR(([1]!thsiFinD("ths_close_price_index",$A93,$AE$2,"","")/[1]!thsiFinD("ths_close_price_index",$A93,$AE$3,"","")-1)*100,"") -> -4.9640395 | F93: =IFERROR(([1]!thsiFinD("ths_close_price_index",$A93,$AE$2,"","")/[1]!thsiFinD("ths_close_price_index",$A93,$AE$4,"","")-1)*100,"") -> -13.198301 | G93: =IFERROR(E93/5-F93/20,"") -> -0.33289283 | H93: 100 | I93: 600580.SH | J93: 卧龙电驱 | K93: 340.7864 | L93: 46.69 | M93: 002176.SZ | N93: 江特电机 | O93: 159.3662 | P93: 21.83 | Q93: 002249.SZ | R93: 大洋电机 | S93: 131.2686 | T93: 17.98 | U93: 002196.SZ | V93: 方正电机 | W93: 54.3224 | X93: 7.44 | Y93: 300626.SZ | Z93: 华瑞股份 | AA93: 44.2078 | AB93: 6.06
A94: CI005420.CI | B94: 锂电化学品指数 | C94: 30 | D94: =IFERROR(([1]!thsiFinD("ths_close_price_index",$A94,$AE$2,"","")/[1]!thsiFinD("ths_close_price_index",$A94,$AE$5,"","")-1)*100,"") -> 18.978371 | E94: =IFERROR(([1]!thsiFinD("ths_close_price_index",$A94,$AE$2,"","")/[1]!thsiFinD("ths_close_price_index",$A94,$AE$3,"","")-1)*100,"") -> 1.7882459 | F94: =IFERROR(([1]!thsiFinD("ths_close_price_index",$A94,$AE$2,"","")/[1]!thsiFinD("ths_close_price_index",$A94,$AE$4,"","")-1)*100,"") -> 0.31704007 | G94: =IFERROR(E94/5-F94/20,"") -> 0.34179717 | H94: 59.18 | I94: 002709.SZ | J94: 天赐材料 | K94: 746.1652 | L94: 17.78 | M94: 300390.SZ | N94: 天华新能 | O94: 471.636 | P94: 11.24 | Q94: 301358.SZ | R94: 湖南裕能 | S94: 437.3801 | T94: 10.42 | U94: 300037.SZ | V94: 新宙邦 | W94: 421.4966 | X94: 10.04 | Y94: 002812.SZ | Z94: 恩捷股份 | AA94: 406.9923 | AB94: 9.7
A95: CI005441.CI | B95: 玻璃纤维指数 | C95: 6 | D95: =IFERROR(([1]!thsiFinD("ths_close_price_index",$A95,$AE$2,"","")/[1]!thsiFinD("ths_close_price_index",$A95,$AE$5,"","")-1)*100,"") -> 266.17091 | E95: =IFERROR(([1]!thsiFinD("ths_close_price_index",$A95,$AE$2,"","")/[1]!thsiFinD("ths_close_price_index",$A95,$AE$3,"","")-1)*100,"") -> 23.198454 | F95: =IFERROR(([1]!thsiFinD("ths_close_price_index",$A95,$AE$2,"","")/[1]!thsiFinD("ths_close_price_index",$A95,$AE$4,"","")-1)*100,"") -> 52.748444 | G95: =IFERROR(E95/5-F95/20,"") -> 2.0022686 | H95: 100 | I95: 600176.SH | J95: 中国巨石 | K95: 1218.3989 | L95: 62.72 | M95: 002080.SZ | N95: 中材科技 | O95: 562.6243 | P95: 28.96 | Q95: 300196.SZ | R95: 长海股份 | S95: 63.8381 | T95: 3.29 | U95: 002201.SZ | V95: 九鼎新材 | W95: 52.3386 | X95: 2.69 | Y95: 605006.SH | Z95: 山东玻纤 | AA95: 45.5259 | AB95: 2.34
A96: CI005439.CI | B96: 其他结构材料指数 | C96: 8 | D96: =IFERROR(([1]!thsiFinD("ths_close_price_index",$A96,$AE$2,"","")/[1]!thsiFinD("ths_close_price_index",$A96,$AE$5,"","")-1)*100,"") -> 4.7747768 | E96: =IFERROR(([1]!thsiFinD("ths_close_price_index",$A96,$AE$2,"","")/[1]!thsiFinD("ths_close_price_index",$A96,$AE$3,"","")-1)*100,"") -> -3.310468 | F96: =IFERROR(([1]!thsiFinD("ths_close_price_index",$A96,$AE$2,"","")/[1]!thsiFinD("ths_close_price_index",$A96,$AE$4,"","")-1)*100,"") -> -5.3885864 | G96: =IFERROR(E96/5-F96/20,"") -> -0.39266429 | H96: 81.1 | I96: 300986.SZ | J96: 志特新材 | K96: 45.3206 | L96: 30.3 | M96: 002457.SZ | N96: 青龙管业 | O96: 32.5587 | P96: 21.77 | Q96: 603616.SH | R96: 韩建河山 | S96: 16.1235 | T96: 10.78 | U96: 002205.SZ | V96: 国统股份 | W96: 14.4361 | X96: 9.65 | Y96: 002671.SZ | Z96: 龙泉股份 | AA96: 12.8579 | AB96: 8.6
A97: CI005528.CI | B97: 物业经纪服务指数 | C97: 4 | D97: =IFERROR(([1]!thsiFinD("ths_close_price_index",$A97,$AE$2,"","")/[1]!thsiFinD("ths_close_price_index",$A97,$AE$5,"","")-1)*100,"") -> -12.013243 | E97: =IFERROR(([1]!thsiFinD("ths_close_price_index",$A97,$AE$2,"","")/[1]!thsiFinD("ths_close_price_index",$A97,$AE$3,"","")-1)*100,"") -> -4.1411661 | F97: =IFERROR(([1]!thsiFinD("ths_close_price_index",$A97,$AE$2,"","")/[1]!thsiFinD("ths_close_price_index",$A97,$AE$4,"","")-1)*100,"") -> -14.920294 | G97: =IFERROR(E97/5-F97/20,"") -> -0.082218522 | H97: 100 | I97: 000560.SZ | J97: 我爱我家 | K97: 42.403 | L97: 50.26 | M97: 002285.SZ | N97: 世联行 | O97: 23.1623 | P97: 27.46 | Q97: 002377.SZ | R97: 国创高新 | S97: 18.7958 | T97: 22.28
A98: CI005572.CI | B98: 广播电视指数 | C98: 12 | D98: =IFERROR(([1]!thsiFinD("ths_close_price_index",$A98,$AE$2,"","")/[1]!thsiFinD("ths_close_price_index",$A98,$AE$5,"","")-1)*100,"") -> -17.820203 | E98: =IFERROR(([1]!thsiFinD("ths_close_price_index",$A98,$AE$2,"","")/[1]!thsiFinD("ths_close_price_index",$A98,$AE$3,"","")-1)*100,"") -> -3.4538984 | F98: =IFERROR(([1]!thsiFinD("ths_close_price_index",$A98,$AE$2,"","")/[1]!thsiFinD("ths_close_price_index",$A98,$AE$4,"","")-1)*100,"") -> -14.699385 | G98: =IFERROR(E98/5-F98/20,"") -> 0.044189589 | H98: 61.68 | I98: 600637.SH | J98: 东方明珠 | K98: 158.0605 | L98: 23.63 | M98: 600959.SH | N98: 江苏有线 | O98: 73.5646 | P98: 11 | Q98: 000810.SZ | R98: 创维数字 | S98: 65.5413 | T98: 9.8 | U98: 600037.SH | V98: 歌华有线 | W98: 57.8983 | X98: 8.65 | Y98: 600996.SH | Z98: 贵广网络 | AA98: 57.527 | AB98: 8.6
A99: CI005465.CI | B99: 其他通用机械指数 | C99: 48 | D99: =IFERROR(([1]!thsiFinD("ths_close_price_index",$A99,$AE$2,"","")/[1]!thsiFinD("ths_close_price_index",$A99,$AE$5,"","")-1)*100,"") -> 23.823346 | E99: =IFERROR(([1]!thsiFinD("ths_close_price_index",$A99,$AE$2,"","")/[1]!thsiFinD("ths_close_price_index",$A99,$AE$3,"","")-1)*100,"") -> -2.280407 | F99: =IFERROR(([1]!thsiFinD("ths_close_price_index",$A99,$AE$2,"","")/[1]!thsiFinD("ths_close_price_index",$A99,$AE$4,"","")-1)*100,"") -> 6.6702821 | G99: =IFERROR(E99/5-F99/20,"") -> -0.7895955 | H99: 63.76 | I99: 688017.SH | J99: 绿的谐波 | K99: 471.6212 | L99: 23.43 | M99: 688308.SH | N99: 欧科亿 | O99: 241.4085 | P99: 11.99 | Q99: 688333.SH | R99: 铂力特 | S99: 206.3582 | T99: 10.25 | U99: 002444.SZ | V99: 巨星科技 | W99: 196.6358 | X99: 9.77 | Y99: 001696.SZ | Z99: 宗申动力 | AA99: 167.5844 | AB99: 8.32
A100: CI005321.CI | B100: 医药流通指数 | C100: 31 | D100: =IFERROR(([1]!thsiFinD("ths_close_price_index",$A100,$AE$2,"","")/[1]!thsiFinD("ths_close_price_index",$A100,$AE$5,"","")-1)*100,"") -> -19.530796 | E100: =IFERROR(([1]!thsiFinD("ths_close_price_index",$A100,$AE$2,"","")/[1]!thsiFinD("ths_close_price_index",$A100,$AE$3,"","")-1)*100,"") -> -2.1185569 | F100: =IFERROR(([1]!thsiFinD("ths_close_price_index",$A100,$AE$2,"","")/[1]!thsiFinD("ths_close_price_index",$A100,$AE$4,"","")-1)*100,"") -> -4.9167816 | G100: =IFERROR(E100/5-F100/20,"") -> -0.17787229 | H100: 57.13 | I100: 601607.SH | J100: 上海医药 | K100: 159.243 | L100: 19.4 | M100: 600998.SH | N100: 九州通 | O100: 107.1214 | P100: 13.05 | Q100: 600511.SH | R100: 国药股份 | S100: 92.5902 | T100: 11.28 | U100: 600056.SH | V100: 中国医药 | W100: 63.9997 | X100: 7.8 | Y100: 603368.SH | Z100: 柳药集团 | AA100: 45.9669 | AB100: 5.6
A101: CI005424.CI | B101: 食品及饲料添加剂指数 | C101: 19 | D101: =IFERROR(([1]!thsiFinD("ths_close_price_index",$A101,$AE$2,"","")/[1]!thsiFinD("ths_close_price_index",$A101,$AE$5,"","")-1)*100,"") -> -16.609275 | E101: =IFERROR(([1]!thsiFinD("ths_close_price_index",$A101,$AE$2,"","")/[1]!thsiFinD("ths_close_price_index",$A101,$AE$3,"","")-1)*100,"") -> -4.5537994 | F101: =IFERROR(([1]!thsiFinD("ths_close_price_index",$A101,$AE$2,"","")/[1]!thsiFinD("ths_close_price_index",$A101,$AE$4,"","")-1)*100,"") -> -13.635578 | G101: =IFERROR(E101/5-F101/20,"") -> -0.22898099 | H101: 89.42 | I101: 600873.SH | J101: 梅花生物 | K101: 151.2577 | L101: 42.67 | M101: 002597.SZ | N101: 金禾实业 | O101: 67.3921 | P101: 19.01 | Q101: 600866.SH | R101: 星湖科技 | S101: 44.2155 | T101: 12.47 | U101: 600929.SH | V101: 雪天盐业 | W101: 30.2753 | X101: 8.54 | Y101: 002053.SZ | Z101: 云南能投 | AA101: 23.8402 | AB101: 6.73
A102: CI005450.CI | B102: 其他轻工Ⅲ指数 | C102: 19 | D102: =IFERROR(([1]!thsiFinD("ths_close_price_index",$A102,$AE$2,"","")/[1]!thsiFinD("ths_close_price_index",$A102,$AE$5,"","")-1)*100,"") -> -14.909737 | E102: =IFERROR(([1]!thsiFinD("ths_close_price_index",$A102,$AE$2,"","")/[1]!thsiFinD("ths_close_price_index",$A102,$AE$3,"","")-1)*100,"") -> 0.96269827 | F102: =IFERROR(([1]!thsiFinD("ths_close_price_index",$A102,$AE$2,"","")/[1]!thsiFinD("ths_close_price_index",$A102,$AE$4,"","")-1)*100,"") -> -9.0279325 | G102: =IFERROR(E102/5-F102/20,"") -> 0.64393628 | H102: 50.42 | I102: 000833.SZ | J102: 粤桂股份 | K102: 89.464 | L102: 24.87 | M102: 301193.SZ | N102: 家联科技 | O102: 24.1381 | P102: 6.71 | Q102: 301101.SZ | R102: 明月镜片 | S102: 23.1371 | T102: 6.43 | U102: 002899.SZ | V102: 英派斯 | W102: 23.0423 | X102: 6.41 | Y102: 002571.SZ | Z102: 德力股份 | AA102: 21.5769 | AB102: 6
A103: CI005529.CI | B103: 物业管理服务指数 | C103: 6 | D103: =IFERROR(([1]!thsiFinD("ths_close_price_index",$A103,$AE$2,"","")/[1]!thsiFinD("ths_close_price_index",$A103,$AE$5,"","")-1)*100,"") -> -26.408797 | E103: =IFERROR(([1]!thsiFinD("ths_close_price_index",$A103,$AE$2,"","")/[1]!thsiFinD("ths_close_price_index",$A103,$AE$3,"","")-1)*100,"") -> -3.6555789 | F103: =IFERROR(([1]!thsiFinD("ths_close_price_index",$A103,$AE$2,"","")/[1]!thsiFinD("ths_close_price_index",$A103,$AE$4,"","")-1)*100,"") -> -14.727033 | G103: =IFERROR(E103/5-F103/20,"") -> 0.0052358792 | H103: 92.62 | I103: 001914.SZ | J103: 招商积余 | K103: 34.4681 | L103: 34.34 | M103: 300917.SZ | N103: 特发服务 | O103: 19.6586 | P103: 19.59 | Q103: 600684.SH | R103: 珠江股份 | S103: 18.7588 | T103: 18.69 | U103: 002188.SZ | V103: 中天服务 | W103: 10.499 | X103: 10.46 | Y103: 002968.SZ | Z103: 新大正 | AA103: 9.5757 | AB103: 9.54
A104: CI005579.CI | B104: 信息搜索与聚合指数 | C104: 6 | D104: =IFERROR(([1]!thsiFinD("ths_close_price_index",$A104,$AE$2,"","")/[1]!thsiFinD("ths_close_price_index",$A104,$AE$5,"","")-1)*100,"") -> -18.238815 | E104: =IFERROR(([1]!thsiFinD("ths_close_price_index",$A104,$AE$2,"","")/[1]!thsiFinD("ths_close_price_index",$A104,$AE$3,"","")-1)*100,"") -> -3.8904647 | F104: =IFERROR(([1]!thsiFinD("ths_close_price_index",$A104,$AE$2,"","")/[1]!thsiFinD("ths_close_price_index",$A104,$AE$4,"","")-1)*100,"") -> -4.8281063 | G104: =IFERROR(E104/5-F104/20,"") -> -0.53668763 | H104: 95.28 | I104: 000681.SZ | J104: 视觉中国 | K104: 116.7963 | L104: 34.86 | M104: 603000.SH | N104: 人民网 | O104: 78.2615 | P104: 23.36 | Q104: 002315.SZ | R104: 焦点科技 | S104: 54.5049 | T104: 16.27 | U104: 603888.SH | V104: 新华网 | W104: 49.3857 | X104: 14.74 | Y104: 002095.SZ | Z104: 生意宝 | AA104: 20.273 | AB104: 6.05
A105: CI005467.CI | B105: 服务机器人指数 | C105: 3 | D105: =IFERROR(([1]!thsiFinD("ths_close_price_index",$A105,$AE$2,"","")/[1]!thsiFinD("ths_close_price_index",$A105,$AE$5,"","")-1)*100,"") -> -34.599901 | E105: =IFERROR(([1]!thsiFinD("ths_close_price_index",$A105,$AE$2,"","")/[1]!thsiFinD("ths_close_price_index",$A105,$AE$3,"","")-1)*100,"") -> -2.0360908 | F105: =IFERROR(([1]!thsiFinD("ths_close_price_index",$A105,$AE$2,"","")/[1]!thsiFinD("ths_close_price_index",$A105,$AE$4,"","")-1)*100,"") -> -15.063737 | G105: =IFERROR(E105/5-F105/20,"") -> 0.34596869 | H105: 100 | I105: 688169.SH | J105: 石头科技 | K105: 201.7491 | L105: 66.55 | M105: 603486.SH | N105: 科沃斯 | O105: 101.3939 | P105: 33.45
A106: CI005575.CI | B106: 影视指数 | C106: 18 | D106: =IFERROR(([1]!thsiFinD("ths_close_price_index",$A106,$AE$2,"","")/[1]!thsiFinD("ths_close_price_index",$A106,$AE$5,"","")-1)*100,"") -> -23.193223 | E106: =IFERROR(([1]!thsiFinD("ths_close_price_index",$A106,$AE$2,"","")/[1]!thsiFinD("ths_close_price_index",$A106,$AE$3,"","")-1)*100,"") -> -1.8508264 | F106: =IFERROR(([1]!thsiFinD("ths_close_price_index",$A106,$AE$2,"","")/[1]!thsiFinD("ths_close_price_index",$A106,$AE$4,"","")-1)*100,"") -> -13.968836 | G106: =IFERROR(E106/5-F106/20,"") -> 0.32827653 | H106: 63.67 | I106: 300251.SZ | J106: 光线传媒 | K106: 154.3567 | L106: 16.94 | M106: 300182.SZ | N106: 捷成股份 | O106: 121.4992 | P106: 13.33 | Q106: 002739.SZ | R106: 儒意电影 | S106: 119.3167 | T106: 13.09 | U106: 300133.SZ | V106: 华策影视 | W106: 98.4196 | X106: 10.8 | Y106: 600977.SH | Z106: 中国电影 | AA106: 86.6449 | AB106: 9.51
A107: CI005253.CI | B107: 民爆用品指数 | C107: 11 | D107: =IFERROR(([1]!thsiFinD("ths_close_price_index",$A107,$AE$2,"","")/[1]!thsiFinD("ths_close_price_index",$A107,$AE$5,"","")-1)*100,"") -> -29.030431 | E107: =IFERROR(([1]!thsiFinD("ths_close_price_index",$A107,$AE$2,"","")/[1]!thsiFinD("ths_close_price_index",$A107,$AE$3,"","")-1)*100,"") -> -5.4890528 | F107: =IFERROR(([1]!thsiFinD("ths_close_price_index",$A107,$AE$2,"","")/[1]!thsiFinD("ths_close_price_index",$A107,$AE$4,"","")-1)*100,"") -> -15.262582 | G107: =IFERROR(E107/5-F107/20,"") -> -0.33468148 | H107: 71.61 | I107: 002683.SZ | J107: 广东宏大 | K107: 130.8595 | L107: 28.2 | M107: 002226.SZ | N107: 江南化工 | O107: 66.3841 | P107: 14.31 | Q107: 603977.SH | R107: 国泰集团 | S107: 47.0803 | T107: 10.15 | U107: 002096.SZ | V107: 易普力 | W107: 44.8449 | X107: 9.66 | Y107: 603227.SH | Z107: 雪峰科技 | AA107: 43.1122 | AB107: 9.29
A108: CI005349.CI | B108: 住宅物业开发指数 | C108: 68 | D108: =IFERROR(([1]!thsiFinD("ths_close_price_index",$A108,$AE$2,"","")/[1]!thsiFinD("ths_close_price_index",$A108,$AE$5,"","")-1)*100,"") -> -11.544515 | E108: =IFERROR(([1]!thsiFinD("ths_close_price_index",$A108,$AE$2,"","")/[1]!thsiFinD("ths_close_price_index",$A108,$AE$3,"","")-1)*100,"") -> -2.5388852 | F108: =IFERROR(([1]!thsiFinD("ths_close_price_index",$A108,$AE$2,"","")/[1]!thsiFinD("ths_close_price_index",$A108,$AE$4,"","")-1)*100,"") -> -7.9913025 | G108: =IFERROR(E108/5-F108/20,"") -> -0.10821192 | H108: 41.3 | I108: 600048.SH | J108: 保利发展 | K108: 354.775 | L108: 12.23 | M108: 600246.SH | N108: 万通发展 | O108: 271.2252 | P108: 9.35 | Q108: 600641.SH | R108: 先导基电 | S108: 253.7846 | T108: 8.75 | U108: 000002.SZ | V108: 万科A | W108: 201.3453 | X108: 6.94 | Y108: 600208.SH | Z108: 衢州发展 | AA108: 116.8166 | AB108: 4.03
A109: CI005437.CI | B109: 建筑设计及服务Ⅲ指数 | C109: 33 | D109: =IFERROR(([1]!thsiFinD("ths_close_price_index",$A109,$AE$2,"","")/[1]!thsiFinD("ths_close_price_index",$A109,$AE$5,"","")-1)*100,"") -> -17.716392 | E109: =IFERROR(([1]!thsiFinD("ths_close_price_index",$A109,$AE$2,"","")/[1]!thsiFinD("ths_close_price_index",$A109,$AE$3,"","")-1)*100,"") -> -3.0802052 | F109: =IFERROR(([1]!thsiFinD("ths_close_price_index",$A109,$AE$2,"","")/[1]!thsiFinD("ths_close_price_index",$A109,$AE$4,"","")-1)*100,"") -> -9.6743499 | G109: =IFERROR(E109/5-F109/20,"") -> -0.13232355 | H109: 36.27 | I109: 600629.SH | J109: 华建集团 | K109: 77.0057 | L109: 11.87 | M109: 603018.SH | N109: 华设集团 | O109: 44.857 | P109: 6.91 | Q109: 603458.SH | R109: 勘设股份 | S109: 40.3549 | T109: 6.22 | U109: 300284.SZ | V109: 苏交科 | W109: 39.3589 | X109: 6.07 | Y109: 301115.SZ | Z109: 联检科技 | AA109: 33.7458 | AB109: 5.2
A110: CI005456.CI | B110: 其他专用机械指数 | C110: 217 | D110: =IFERROR(([1]!thsiFinD("ths_close_price_index",$A110,$AE$2,"","")/[1]!thsiFinD("ths_close_price_index",$A110,$AE$5,"","")-1)*100,"") -> 18.49559 | E110: =IFERROR(([1]!thsiFinD("ths_close_price_index",$A110,$AE$2,"","")/[1]!thsiFinD("ths_close_price_index",$A110,$AE$3,"","")-1)*100,"") -> -0.03290472 | F110: =IFERROR(([1]!thsiFinD("ths_close_price_index",$A110,$AE$2,"","")/[1]!thsiFinD("ths_close_price_index",$A110,$AE$4,"","")-1)*100,"") -> 3.8089791 | G110: =IFERROR(E110/5-F110/20,"") -> -0.1970299 | H110: 31.3 | I110: 688257.SH | J110: 新锐股份 | K110: 292.072 | L110: 8.54 | M110: 002595.SZ | N110: 豪迈科技 | O110: 282.2022 | P110: 8.26 | Q110: 301018.SZ | R110: 申菱环境 | S110: 185.9142 | T110: 5.44 | U110: 002975.SZ | V110: 博杰股份 | W110: 164.3069 | X110: 4.81 | Y110: 002645.SZ | Z110: 华宏科技 | AA110: 145.2334 | AB110: 4.25
A111: CI005464.CI | B111: 基础件指数 | C111: 56 | D111: =IFERROR(([1]!thsiFinD("ths_close_price_index",$A111,$AE$2,"","")/[1]!thsiFinD("ths_close_price_index",$A111,$AE$5,"","")-1)*100,"") -> 2.6601743 | E111: =IFERROR(([1]!thsiFinD("ths_close_price_index",$A111,$AE$2,"","")/[1]!thsiFinD("ths_close_price_index",$A111,$AE$3,"","")-1)*100,"") -> -4.5566997 | F111: =IFERROR(([1]!thsiFinD("ths_close_price_index",$A111,$AE$2,"","")/[1]!thsiFinD("ths_close_price_index",$A111,$AE$4,"","")-1)*100,"") -> -4.9291404 | G111: =IFERROR(E111/5-F111/20,"") -> -0.66488292 | H111: 47.66 | I111: 601100.SH | J111: 恒立液压 | K111: 550.2995 | L111: 17.37 | M111: 603308.SH | N111: 应流股份 | O111: 306.932 | P111: 9.69 | Q111: 002472.SZ | R111: 双环传动 | S111: 269.568 | T111: 8.51 | U111: 603699.SH | V111: 纽威股份 | W111: 199.1775 | X111: 6.29 | Y111: 002046.SZ | Z111: 国机精工 | AA111: 183.7934 | AB111: 5.8
A112: CI005468.CI | B112: 塑料加工机械指数 | C112: 5 | D112: =IFERROR(([1]!thsiFinD("ths_close_price_index",$A112,$AE$2,"","")/[1]!thsiFinD("ths_close_price_index",$A112,$AE$5,"","")-1)*100,"") -> -6.8807743 | E112: =IFERROR(([1]!thsiFinD("ths_close_price_index",$A112,$AE$2,"","")/[1]!thsiFinD("ths_close_price_index",$A112,$AE$3,"","")-1)*100,"") -> -4.0763878 | F112: =IFERROR(([1]!thsiFinD("ths_close_price_index",$A112,$AE$2,"","")/[1]!thsiFinD("ths_close_price_index",$A112,$AE$4,"","")-1)*100,"") -> -4.8134532 | G112: =IFERROR(E112/5-F112/20,"") -> -0.57460489 | H112: 100 | I112: 300415.SZ | J112: 伊之密 | K112: 61.9366 | L112: 46.88 | M112: 688419.SH | N112: 耐科装备 | O112: 32.9418 | P112: 24.93 | Q112: 300281.SZ | R112: 金明精机 | S112: 14.3313 | T112: 10.85 | U112: 600579.SH | V112: 中化装备 | W112: 13.4932 | X112: 10.21 | Y112: 603289.SH | Z112: 泰瑞机器 | AA112: 9.4249 | AB112: 7.13
A113: CI005358.CI | B113: 港口指数 | C113: 18 | D113: =IFERROR(([1]!thsiFinD("ths_close_price_index",$A113,$AE$2,"","")/[1]!thsiFinD("ths_close_price_index",$A113,$AE$5,"","")-1)*100,"") -> -6.6536576 | E113: =IFERROR(([1]!thsiFinD("ths_close_price_index",$A113,$AE$2,"","")/[1]!thsiFinD("ths_close_price_index",$A113,$AE$3,"","")-1)*100,"") -> -2.092177 | F113: =IFERROR(([1]!thsiFinD("ths_close_price_index",$A113,$AE$2,"","")/[1]!thsiFinD("ths_close_price_index",$A113,$AE$4,"","")-1)*100,"") -> -7.8173255 | G113: =IFERROR(E113/5-F113/20,"") -> -0.027569129 | H113: 54.28 | I113: 600018.SH | J113: 上港集团 | K113: 138.2342 | L113: 13.84 | M113: 000582.SZ | N113: 北部湾港 | O113: 108.5913 | P113: 10.87 | Q113: 601000.SH | R113: 唐山港 | S113: 104.485 | T113: 10.46 | U113: 601018.SH | V113: 宁波港 | W113: 100.6322 | X113: 10.08 | Y113: 601880.SH | Z113: 辽港股份 | AA113: 90.1481 | AB113: 9.03
A114: CI005507.CI | B114: 中高端成人品牌服饰指数 | C114: 14 | D114: =IFERROR(([1]!thsiFinD("ths_close_price_index",$A114,$AE$2,"","")/[1]!thsiFinD("ths_close_price_index",$A114,$AE$5,"","")-1)*100,"") -> -15.963394 | E114: =IFERROR(([1]!thsiFinD("ths_close_price_index",$A114,$AE$2,"","")/[1]!thsiFinD("ths_close_price_index",$A114,$AE$3,"","")-1)*100,"") -> -5.5389857 | F114: =IFERROR(([1]!thsiFinD("ths_close_price_index",$A114,$AE$2,"","")/[1]!thsiFinD("ths_close_price_index",$A114,$AE$4,"","")-1)*100,"") -> -10.705087 | G114: =IFERROR(E114/5-F114/20,"") -> -0.57254277 | H114: 56.28 | I114: 002154.SZ | J114: 报喜鸟 | K114: 34.7372 | L114: 13.89 | M114: 002029.SZ | N114: 七匹狼 | O114: 32.9822 | P114: 13.19 | Q114: 300840.SZ | R114: 酷特智能 | S114: 32.1152 | T114: 12.84 | U114: 002612.SZ | V114: 朗姿股份 | W114: 23.0782 | X114: 9.23 | Y114: 603518.SH | Z114: 锦泓集团 | AA114: 17.8299 | AB114: 7.13
A115: CI005421.CI | B115: 涂料油墨颜料指数 | C115: 23 | D115: =IFERROR(([1]!thsiFinD("ths_close_price_index",$A115,$AE$2,"","")/[1]!thsiFinD("ths_close_price_index",$A115,$AE$5,"","")-1)*100,"") -> 4.3894879 | E115: =IFERROR(([1]!thsiFinD("ths_close_price_index",$A115,$AE$2,"","")/[1]!thsiFinD("ths_close_price_index",$A115,$AE$3,"","")-1)*100,"") -> -0.80681619 | F115: =IFERROR(([1]!thsiFinD("ths_close_price_index",$A115,$AE$2,"","")/[1]!thsiFinD("ths_close_price_index",$A115,$AE$4,"","")-1)*100,"") -> -2.6284842 | G115: =IFERROR(E115/5-F115/20,"") -> -0.02993903 | H115: 50.02 | I115: 603737.SH | J115: 三棵树 | K115: 76.9516 | L115: 13.82 | M115: 603823.SH | N115: 百合花 | O115: 68.0559 | P115: 12.22 | Q115: 603826.SH | R115: 坤彩科技 | S115: 59.4618 | T115: 10.68 | U115: 603110.SH | V115: 东方材料 | W115: 40.7131 | X115: 7.31 | Y115: 300225.SZ | Z115: 金力泰 | AA115: 33.3405 | AB115: 5.99
...

Sheet 热点热力图
B1: 中信三级行业指数 · 短期热点热力图
B2: 瓦片按【指数自由流通市值】从大到小、从左上到右下排列(市值大→越靠前越显眼)；颜色按【近一周涨跌幅】红涨绿跌、幅度越大越深。数据随上一页(中信三级行业指数热度)iFinD公式自动刷新。 | AG2: =IFERROR(中信三级行业指数热度!G2+ROW()*0.0000000001,-9999) -> 1.0114438
B3: =中信三级行业指数热度!B17&CHAR(10)&TEXT(中信三级行业指数热度!E17,"0.0")&"%" -> 棉纺制品指数 2.3% | C3: =中信三级行业指数热度!B8&CHAR(10)&TEXT(中信三级行业指数热度!E8,"0.0")&"%" -> 医疗服务指数 8.0% | D3: =中信三级行业指数热度!B176&CHAR(10)&TEXT(中信三级行业指数热度!E176,"0.0")&"%" -> 兵器兵装Ⅲ指数 -2.6% | E3: =中信三级行业指数热度!B22&CHAR(10)&TEXT(中信三级行业指数热度!E22,"0.0")&"%" -> 出版指数 1.1% | F3: =中信三级行业指数热度!B75&CHAR(10)&TEXT(中信三级行业指数热度!E75,"0.0")&"%" -> 游戏指数 5.4% | G3: =中信三级行业指数热度!B11&CHAR(10)&TEXT(中信三级行业指数热度!E11,"0.0")&"%" -> 航运指数 6.9% | H3: =中信三级行业指数热度!B10&CHAR(10)&TEXT(中信三级行业指数热度!E10,"0.0")&"%" -> 燃料电池指数 11.0% | I3: =中信三级行业指数热度!B162&CHAR(10)&TEXT(中信三级行业指数热度!E162,"0.0")&"%" -> 农药指数 -1.3% | J3: =中信三级行业指数热度!B212&CHAR(10)&TEXT(中信三级行业指数热度!E212,"0.0")&"%" -> 大众成人品牌服饰指数 -1.1% | K3: =中信三级行业指数热度!B42&CHAR(10)&TEXT(中信三级行业指数热度!E42,"0.0")&"%" -> 综合能源设备指数 -3.2% | L3: =中信三级行业指数热度!B136&CHAR(10)&TEXT(中信三级行业指数热度!E136,"0.0")&"%" -> 其他装饰材料指数 -1.8% | M3: =中信三级行业指数热度!B244&CHAR(10)&TEXT(中信三级行业指数热度!E244,"0.0")&"%" -> 锂指数 0.4% | N3: =中信三级行业指数热度!B122&CHAR(10)&TEXT(中信三级行业指数热度!E122,"0.0")&"%" -> 非乳饮料指数 -4.1% | O3: =中信三级行业指数热度!B18&CHAR(10)&TEXT(中信三级行业指数热度!E18,"0.0")&"%" -> 聚氨酯指数 6.3% | R3: =中信三级行业指数热度!E17 -> 2.2547549 | S3: =中信三级行业指数热度!E8 -> 8.0227067 | T3: =中信三级行业指数热度!E176 -> -2.6072184 | U3: =中信三级行业指数热度!E22 -> 1.1078919 | V3: =中信三级行业指数热度!E75 -> 5.4308486 | W3: =中信三级行业指数热度!E11 -> 6.9384061 | X3: =中信三级行业指数热度!E10 -> 10.99687 | Y3: =中信三级行业指数热度!E162 -> -1.2689345 | Z3: =中信三级行业指数热度!E212 -> -1.1407558 | AA3: =中信三级行业指数热度!E42 -> -3.2413678 | AB3: =中信三级行业指数热度!E136 -> -1.8132384 | AC3: =中信三级行业指数热度!E244 -> 0.41439451 | AD3: =中信三级行业指数热度!E122 -> -4.0586634 | AE3: =中信三级行业指数热度!E18 -> 6.3281788 | AG3: =IFERROR(中信三级行业指数热度!G3+ROW()*0.0000000001,-9999) -> 1.4432608
B4: =中信三级行业指数热度!B121&CHAR(10)&TEXT(中信三级行业指数热度!E121,"0.0")&"%" -> 专业工程及其他指数 -0.4% | C4: =中信三级行业指数热度!B2&CHAR(10)&TEXT(中信三级行业指数热度!E2,"0.0")&"%" -> 半导体设备指数 12.8% | D4: =中信三级行业指数热度!B119&CHAR(10)&TEXT(中信三级行业指数热度!E119,"0.0")&"%" -> 家纺指数 -2.7% | E4: =中信三级行业指数热度!B90&CHAR(10)&TEXT(中信三级行业指数热度!E90,"0.0")&"%" -> 电机指数 -4.8% | F4: =中信三级行业指数热度!B107&CHAR(10)&TEXT(中信三级行业指数热度!E107,"0.0")&"%" -> 民爆用品指数 -5.5% | G4: =中信三级行业指数热度!B157&CHAR(10)&TEXT(中信三级行业指数热度!E157,"0.0")&"%" -> 粘胶指数 3.3% | H4: =中信三级行业指数热度!B9&CHAR(10)&TEXT(中信三级行业指数热度!E9,"0.0")&"%" -> 显示零组指数 4.5% | I4: =中信三级行业指数热度!B139&CHAR(10)&TEXT(中信三级行业指数热度!E139,"0.0")&"%" -> 中成药指数 -1.6% | J4: =中信三级行业指数热度!B51&CHAR(10)&TEXT(中信三级行业指数热度!E51,"0.0")&"%" -> 建筑装修Ⅲ指数 0.6% | K4: =中信三级行业指数热度!B151&CHAR(10)&TEXT(中信三级行业指数热度!E151,"0.0")&"%" -> 贸易Ⅲ指数 -2.2% | L4: =中信三级行业指数热度!B3&CHAR(10)&TEXT(中信三级行业指数热度!E3,"0.0")&"%" -> 分立器件指数 10.7% | M4: =中信三级行业指数热度!B231&CHAR(10)&TEXT(中信三级行业指数热度!E231,"0.0")&"%" -> 其他发电指数 -4.6% | N4: =中信三级行业指数热度!B52&CHAR(10)&TEXT(中信三级行业指数热度!E52,"0.0")&"%" -> 非棉纺织品指数 -2.4% | O4: =中信三级行业指数热度!B179&CHAR(10)&TEXT(中信三级行业指数热度!E179,"0.0")&"%" -> 其他广告营销指数 -3.4% | R4: =中信三级行业指数热度!E121 -> -0.42343967 | S4: =中信三级行业指数热度!E2 -> 12.773946 | T4: =中信三级行业指数热度!E119 -> -2.7194189 | U4: =中信三级行业指数热度!E90 -> -4.8138015 | V4: =中信三级行业指数热度!E107 -> -5.4890528 | W4: =中信三级行业指数热度!E157 -> 3.3241071 | X4: =中信三级行业指数热度!E9 -> 4.5272635 | Y4: =中信三级行业指数热度!E139 -> -1.562442 | Z4: =中信三级行业指数热度!E51 -> 0.62448854 | AA4: =中信三级行业指数热度!E151 -> -2.2082612 | AB4: =中信三级行业指数热度!E3 -> 10.727 | AC4: =中信三级行业指数热度!E231 -> -4.5923337 | AD4: =中信三级行业指数热度!E52 -> -2.3782433 | AE4: =中信三级行业指数热度!E179 -> -3.3590513 | AG4: =IFERROR(中信三级行业指数热度!G4+ROW()*0.0000000001,-9999) -> -1.7374558
B5: =中信三级行业指数热度!B246&CHAR(10)&TEXT(中信三级行业指数热度!E246,"0.0")&"%" -> 日用化学品指数 -7.3% | C5: =中信三级行业指数热度!B146&CHAR(10)&TEXT(中信三级行业指数热度!E146,"0.0")&"%" -> 综合业态指数 -3.0% | D5: =中信三级行业指数热度!B94&CHAR(10)&TEXT(中信三级行业指数热度!E94,"0.0")&"%" -> 锂电化学品指数 1.8% | E5: =中信三级行业指数热度!B12&CHAR(10)&TEXT(中信三级行业指数热度!E12,"0.0")&"%" -> 面板指数 11.9% | F5: =中信三级行业指数热度!B32&CHAR(10)&TEXT(中信三级行业指数热度!E32,"0.0")&"%" -> 行业应用软件指数 -1.6% | G5: =中信三级行业指数热度!B31&CHAR(10)&TEXT(中信三级行业指数热度!E31,"0.0")&"%" -> 电商及服务Ⅲ指数 0.0% | H5: =中信三级行业指数热度!B49&CHAR(10)&TEXT(中信三级行业指数热度!E49,"0.0")&"%" -> 专用汽车指数 -3.0% | I5: =中信三级行业指数热度!B27&CHAR(10)&TEXT(中信三级行业指数热度!E27,"0.0")&"%" -> 云基础设施服务指数 -3.2% | J5: =中信三级行业指数热度!B103&CHAR(10)&TEXT(中信三级行业指数热度!E103,"0.0")&"%" -> 物业管理服务指数 -3.7% | K5: =中信三级行业指数热度!B79&CHAR(10)&TEXT(中信三级行业指数热度!E79,"0.0")&"%" -> 儿童品牌指数 -2.7% | L5: =中信三级行业指数热度!B196&CHAR(10)&TEXT(中信三级行业指数热度!E196,"0.0")&"%" -> 合成树脂指数 0.2% | M5: =中信三级行业指数热度!B144&CHAR(10)&TEXT(中信三级行业指数热度!E144,"0.0")&"%" -> 综合Ⅲ指数 -3.1% | N5: =中信三级行业指数热度!B59&CHAR(10)&TEXT(中信三级行业指数热度!E59,"0.0")&"%" -> 叉车指数 -4.9% | O5: =中信三级行业指数热度!B240&CHAR(10)&TEXT(中信三级行业指数热度!E240,"0.0")&"%" -> 电网指数 -6.4% | R5: =中信三级行业指数热度!E246 -> -7.3117274 | S5: =中信三级行业指数热度!E146 -> -3.0313633 | T5: =中信三级行业指数热度!E94 -> 1.7882459 | U5: =中信三级行业指数热度!E12 -> 11.871478 | V5: =中信三级行业指数热度!E32 -> -1.6087978 | W5: =中信三级行业指数热度!E31 -> 0.04780603 | X5: =中信三级行业指数热度!E49 -> -3.004264 | Y5: =中信三级行业指数热度!E27 -> -3.2396427 | Z5: =中信三级行业指数热度!E103 -> -3.6555789 | AA5: =中信三级行业指数热度!E79 -> -2.7135273 | AB5: =中信三级行业指数热度!E196 -> 0.20972669 | AC5: =中信三级行业指数热度!E144 -> -3.1086603 | AD5: =中信三级行业指数热度!E59 -> -4.9300912 | AE5: =中信三级行业指数热度!E240 -> -6.4487407 | AG5: =IFERROR(中信三级行业指数热度!G5+ROW()*0.0000000001,-9999) -> 1.3061596
B6: =中信三级行业指数热度!B40&CHAR(10)&TEXT(中信三级行业指数热度!E40,"0.0")&"%" -> 其他文化娱乐指数 -2.3% | C6: =中信三级行业指数热度!B173&CHAR(10)&TEXT(中信三级行业指数热度!E173,"0.0")&"%" -> K12培训指数 -3.3% | D6: =中信三级行业指数热度!B91&CHAR(10)&TEXT(中信三级行业指数热度!E91,"0.0")&"%" -> 储能指数 0.1% | E6: =中信三级行业指数热度!B210&CHAR(10)&TEXT(中信三级行业指数热度!E210,"0.0")&"%" -> 酒店指数 -3.9% | F6: =中信三级行业指数热度!B181&CHAR(10)&TEXT(中信三级行业指数热度!E181,"0.0")&"%" -> 造纸Ⅲ指数 -3.5% | G6: =中信三级行业指数热度!B152&CHAR(10)&TEXT(中信三级行业指数热度!E152,"0.0")&"%" -> 水产养殖指数 -3.9% | H6: =中信三级行业指数热度!B108&CHAR(10)&TEXT(中信三级行业指数热度!E108,"0.0")&"%" -> 住宅物业开发指数 -2.5% | I6: =中信三级行业指数热度!B21&CHAR(10)&TEXT(中信三级行业指数热度!E21,"0.0")&"%" -> 油品销售及仓储指数 -0.6% | J6: =中信三级行业指数热度!B189&CHAR(10)&TEXT(中信三级行业指数热度!E189,"0.0")&"%" -> 其他运输设备指数 0.1% | K6: =中信三级行业指数热度!B77&CHAR(10)&TEXT(中信三级行业指数热度!E77,"0.0")&"%" -> 产业互联网综合服务指数 -3.7% | L6: =中信三级行业指数热度!B53&CHAR(10)&TEXT(中信三级行业指数热度!E53,"0.0")&"%" -> 信托指数 1.0% | M6: =中信三级行业指数热度!B20&CHAR(10)&TEXT(中信三级行业指数热度!E20,"0.0")&"%" -> 供热或其他指数 4.8% | N6: =中信三级行业指数热度!B46&CHAR(10)&TEXT(中信三级行业指数热度!E46,"0.0")&"%" -> 消费电子设备指数 -1.9% | O6: =中信三级行业指数热度!B48&CHAR(10)&TEXT(中信三级行业指数热度!E48,"0.0")&"%" -> LED指数 5.5% | R6: =中信三级行业指数热度!E40 -> -2.3298733 | S6: =中信三级行业指数热度!E173 -> -3.2914106 | T6: =中信三级行业指数热度!E91 -> 0.10720697 | U6: =中信三级行业指数热度!E210 -> -3.9462635 | V6: =中信三级行业指数热度!E181 -> -3.5052281 | W6: =中信三级行业指数热度!E152 -> -3.922558 | X6: =中信三级行业指数热度!E108 -> -2.5388852 | Y6: =中信三级行业指数热度!E21 -> -0.58729821 | Z6: =中信三级行业指数热度!E189 -> 0.1142829 | AA6: =中信三级行业指数热度!E77 -> -3.6863552 | AB6: =中信三级行业指数热度!E53 -> 1.0053474 | AC6: =中信三级行业指数热度!E20 -> 4.7657774 | AD6: =中信三级行业指数热度!E46 -> -1.8528563 | AE6: =中信三级行业指数热度!E48 -> 5.5178131 | AG6: =IFERROR(中信三级行业指数热度!G6+ROW()*0.0000000001,-9999) -> 2.0023683
B7: =中信三级行业指数热度!B6&CHAR(10)&TEXT(中信三级行业指数热度!E6,"0.0")&"%" -> 橡胶助剂指数 17.0% | C7: =中信三级行业指数热度!B47&CHAR(10)&TEXT(中信三级行业指数热度!E47,"0.0")&"%" -> 证券Ⅲ指数 9.5% | D7: =中信三级行业指数热度!B62&CHAR(10)&TEXT(中信三级行业指数热度!E62,"0.0")&"%" -> 半导体材料指数 10.2% | E7: =中信三级行业指数热度!B80&CHAR(10)&TEXT(中信三级行业指数热度!E80,"0.0")&"%" -> 咨询实施及其他服务指数 -3.0% | F7: =中信三级行业指数热度!B5&CHAR(10)&TEXT(中信三级行业指数热度!E5,"0.0")&"%" -> 集成电路指数 10.9% | G7: =中信三级行业指数热度!B74&CHAR(10)&TEXT(中信三级行业指数热度!E74,"0.0")&"%" -> 工程服务指数 1.7% | H7: =中信三级行业指数热度!B23&CHAR(10)&TEXT(中信三级行业指数热度!E23,"0.0")&"%" -> 生物医药Ⅲ指数 1.6% | I7: =中信三级行业指数热度!B35&CHAR(10)&TEXT(中信三级行业指数热度!E35,"0.0")&"%" -> 电子化学品指数 6.2% | J7: =中信三级行业指数热度!B71&CHAR(10)&TEXT(中信三级行业指数热度!E71,"0.0")&"%" -> 公路指数 -1.0% | K7: =中信三级行业指数热度!B88&CHAR(10)&TEXT(中信三级行业指数热度!E88,"0.0")&"%" -> 调味品指数 2.6% | L7: =中信三级行业指数热度!B4&CHAR(10)&TEXT(中信三级行业指数热度!E4,"0.0")&"%" -> 碳纤维指数 -0.9% | M7: =中信三级行业指数热度!B245&CHAR(10)&TEXT(中信三级行业指数热度!E245,"0.0")&"%" -> PCB指数 0.9% | N7: =中信三级行业指数热度!B16&CHAR(10)&TEXT(中信三级行业指数热度!E16,"0.0")&"%" -> 其他专用材料指数 6.7% | O7: =中信三级行业指数热度!B66&CHAR(10)&TEXT(中信三级行业指数热度!E66,"0.0")&"%" -> 金属包装指数 -4.8% | R7: =中信三级行业指数热度!E6 -> 16.97181 | S7: =中信三级行业指数热度!E47 -> 9.4874126 | T7: =中信三级行业指数热度!E62 -> 10.235065 | U7: =中信三级行业指数热度!E80 -> -2.9533878 | V7: =中信三级行业指数热度!E5 -> 10.902559 | W7: =中信三级行业指数热度!E74 -> 1.7380063 | X7: =中信三级行业指数热度!E23 -> 1.6050567 | Y7: =中信三级行业指数热度!E35 -> 6.1844263 | Z7: =中信三级行业指数热度!E71 -> -1.0044199 | AA7: =中信三级行业指数热度!E88 -> 2.6233097 | AB7: =中信三级行业指数热度!E4 -> -0.93914612 | AC7: =中信三级行业指数热度!E245 -> 0.85090171 | AD7: =中信三级行业指数热度!E16 -> 6.7269618 | AE7: =中信三级行业指数热度!E66 -> -4.7827773 | AG7: =IFERROR(中信三级行业指数热度!G7+ROW()*0.0000000001,-9999) -> -0.059352781
B8: =中信三级行业指数热度!B184&CHAR(10)&TEXT(中信三级行业指数热度!E184,"0.0")&"%" -> 高等及职业教育指数 -5.4% | C8: =中信三级行业指数热度!B99&CHAR(10)&TEXT(中信三级行业指数热度!E99,"0.0")&"%" -> 其他通用机械指数 -2.3% | D8: =中信三级行业指数热度!B123&CHAR(10)&TEXT(中信三级行业指数热度!E123,"0.0")&"%" -> 照明电工指数 -2.4% | E8: =中信三级行业指数热度!B142&CHAR(10)&TEXT(中信三级行业指数热度!E142,"0.0")&"%" -> 工业机器人及工控系统指数 -4.2% | F8: =中信三级行业指数热度!B182&CHAR(10)&TEXT(中信三级行业指数热度!E182,"0.0")&"%" -> 动物疫苗及兽药指数 0.9% | G8: =中信三级行业指数热度!B43&CHAR(10)&TEXT(中信三级行业指数热度!E43,"0.0")&"%" -> 其他化学制品Ⅲ指数 4.7% | H8: =中信三级行业指数热度!B67&CHAR(10)&TEXT(中信三级行业指数热度!E67,"0.0")&"%" -> 网络规划设计和工程施工指数 -3.0% | I8: =中信三级行业指数热度!B124&CHAR(10)&TEXT(中信三级行业指数热度!E124,"0.0")&"%" -> 复合肥指数 2.5% | J8: =中信三级行业指数热度!B25&CHAR(10)&TEXT(中信三级行业指数热度!E25,"0.0")&"%" -> 电梯指数 -3.1% | K8: =中信三级行业指数热度!B56&CHAR(10)&TEXT(中信三级行业指数热度!E56,"0.0")&"%" -> 风电指数 -3.9% | L8: =中信三级行业指数热度!B60&CHAR(10)&TEXT(中信三级行业指数热度!E60,"0.0")&"%" -> 消费电子组件指数 2.2% | M8: =中信三级行业指数热度!B253&CHAR(10)&TEXT(中信三级行业指数热度!E253,"0.0")&"%" -> 钨指数 3.9% | N8: =中信三级行业指数热度!B140&CHAR(10)&TEXT(中信三级行业指数热度!E140,"0.0")&"%" -> 互联网广告营销指数 -6.0% | O8: =中信三级行业指数热度!B205&CHAR(10)&TEXT(中信三级行业指数热度!E205,"0.0")&"%" -> 锂电池指数 1.9% | R8: =中信三级行业指数热度!E184 -> -5.3761573 | S8: =中信三级行业指数热度!E99 -> -2.280407 | T8: =中信三级行业指数热度!E123 -> -2.4003137 | U8: =中信三级行业指数热度!E142 -> -4.2265309 | V8: =中信三级行业指数热度!E182 -> 0.89582655 | W8: =中信三级行业指数热度!E43 -> 4.6832542 | X8: =中信三级行业指数热度!E67 -> -2.9639123 | Y8: =中信三级行业指数热度!E124 -> 2.5221256 | Z8: =中信三级行业指数热度!E25 -> -3.0996064 | AA8: =中信三级行业指数热度!E56 -> -3.942318 | AB8: =中信三级行业指数热度!E60 -> 2.1752303 | AC8: =中信三级行业指数热度!E253 -> 3.9172175 | AD8: =中信三级行业指数热度!E140 -> -6.0497267 | AE8: =中信三级行业指数热度!E205 -> 1.8665407 | AG8: =IFERROR(中信三级行业指数热度!G8+ROW()*0.0000000001,-9999) -> 1.3538775
B9: =中信三级行业指数热度!B150&CHAR(10)&TEXT(中信三级行业指数热度!E150,"0.0")&"%" -> 其他通信设备指数 -1.9% | C9: =中信三级行业指数热度!B34&CHAR(10)&TEXT(中信三级行业指数热度!E34,"0.0")&"%" -> 客车指数 0.3% | D9: =中信三级行业指数热度!B137&CHAR(10)&TEXT(中信三级行业指数热度!E137,"0.0")&"%" -> 其他石化指数 7.7% | E9: =中信三级行业指数热度!B19&CHAR(10)&TEXT(中信三级行业指数热度!E19,"0.0")&"%" -> 钛白粉指数 9.5% | F9: =中信三级行业指数热度!B165&CHAR(10)&TEXT(中信三级行业指数热度!E165,"0.0")&"%" -> 无机盐指数 9.5% | G9: =中信三级行业指数热度!B82&CHAR(10)&TEXT(中信三级行业指数热度!E82,"0.0")&"%" -> 输变电设备指数 -1.0% | H9: =中信三级行业指数热度!B69&CHAR(10)&TEXT(中信三级行业指数热度!E69,"0.0")&"%" -> 起重运输设备指数 -6.8% | I9: =中信三级行业指数热度!B101&CHAR(10)&TEXT(中信三级行业指数热度!E101,"0.0")&"%" -> 食品及饲料添加剂指数 -4.6% | J9: =中信三级行业指数热度!B28&CHAR(10)&TEXT(中信三级行业指数热度!E28,"0.0")&"%" -> 贸易流通指数 5.7% | K9: =中信三级行业指数热度!B131&CHAR(10)&TEXT(中信三级行业指数热度!E131,"0.0")&"%" -> 基建建设指数 -3.2% | L9: =中信三级行业指数热度!B37&CHAR(10)&TEXT(中信三级行业指数热度!E37,"0.0")&"%" -> 新兴计算机软件指数 -4.3% | M9: =中信三级行业指数热度!B61&CHAR(10)&TEXT(中信三级行业指数热度!E61,"0.0")&"%" -> 印染指数 -2.3% | N9: =中信三级行业指数热度!B57&CHAR(10)&TEXT(中信三级行业指数热度!E57,"0.0")&"%" -> 陶瓷指数 -6.1% | O9: =中信三级行业指数热度!B166&CHAR(10)&TEXT(中信三级行业指数热度!E166,"0.0")&"%" -> 种业指数 -5.1% | R9: =中信三级行业指数热度!E150 -> -1.9073685 | S9: =中信三级行业指数热度!E34 -> 0.34433546 | T9: =中信三级行业指数热度!E137 -> 7.7417234 | U9: =中信三级行业指数热度!E19 -> 9.5045087 | V9: =中信三级行业指数热度!E165 -> 9.4669789 | W9: =中信三级行业指数热度!E82 -> -1.0471866 | X9: =中信三级行业指数热度!E69 -> -6.8028734 | Y9: =中信三级行业指数热度!E101 -> -4.5537994 | Z9: =中信三级行业指数热度!E28 -> 5.7422695 | AA9: =中信三级行业指数热度!E131 -> -3.205189 | AB9: =中信三级行业指数热度!E37 -> -4.3115381 | AC9: =中信三级行业指数热度!E61 -> -2.2880362 | AD9: =中信三级行业指数热度!E57 -> -6.070654 | AE9: =中信三级行业指数热度!E166 -> -5.1153833 | AG9: =IFERROR(中信三级行业指数热度!G9+ROW()*0.0000000001,-9999) -> 0.49754206
B10: =中信三级行业指数热度!B172&CHAR(10)&TEXT(中信三级行业指数热度!E172,"0.0")&"%" -> 氮肥指数 0.7% | C10: =中信三级行业指数热度!B158&CHAR(10)&TEXT(中信三级行业指数热度!E158,"0.0")&"%" -> 汽车零部件Ⅲ指数 -5.3% | D10: =中信三级行业指数热度!B87&CHAR(10)&TEXT(中信三级行业指数热度!E87,"0.0")&"%" -> 其他时尚品指数 -5.8% | E10: =中信三级行业指数热度!B86&CHAR(10)&TEXT(中信三级行业指数热度!E86,"0.0")&"%" -> 动漫指数 -1.5% | F10: =中信三级行业指数热度!B147&CHAR(10)&TEXT(中信三级行业指数热度!E147,"0.0")&"%" -> 涤纶指数 -2.0% | G10: =中信三级行业指数热度!B145&CHAR(10)&TEXT(中信三级行业指数热度!E145,"0.0")&"%" -> 家具指数 -2.6% | H10: =中信三级行业指数热度!B81&CHAR(10)&TEXT(中信三级行业指数热度!E81,"0.0")&"%" -> 其他家电指数 -3.9% | I10: =中信三级行业指数热度!B63&CHAR(10)&TEXT(中信三级行业指数热度!E63,"0.0")&"%" -> 激光加工设备指数 10.2% | J10: =中信三级行业指数热度!B116&CHAR(10)&TEXT(中信三级行业指数热度!E116,"0.0")&"%" -> 互联网影视音频指数 -3.9% | K10: =中信三级行业指数热度!B45&CHAR(10)&TEXT(中信三级行业指数热度!E45,"0.0")&"%" -> 专用计算机设备指数 -3.9% | L10: =中信三级行业指数热度!B237&CHAR(10)&TEXT(中信三级行业指数热度!E237,"0.0")&"%" -> 专业市场经营Ⅲ指数 -4.8% | M10: =中信三级行业指数热度!B104&CHAR(10)&TEXT(中信三级行业指数热度!E104,"0.0")&"%" -> 信息搜索与聚合指数 -3.9% | N10: =中信三级行业指数热度!B185&CHAR(10)&TEXT(中信三级行业指数热度!E185,"0.0")&"%" -> 黑色家电Ⅲ指数 -2.4% | O10: =中信三级行业指数热度!B7&CHAR(10)&TEXT(中信三级行业指数热度!E7,"0.0")&"%" -> 卡车指数 -4.0% | R10: =中信三级行业指数热度!E172 -> 0.72417155 | S10: =中信三级行业指数热度!E158 -> -5.309339 | T10: =中信三级行业指数热度!E87 -> -5.7997538 | U10: =中信三级行业指数热度!E86 -> -1.5361117 | V10: =中信三级行业指数热度!E147 -> -2.0492156 | W10: =中信三级行业指数热度!E145 -> -2.6004325 | X10: =中信三级行业指数热度!E81 -> -3.9366798 | Y10: =中信三级行业指数热度!E63 -> 10.215833 | Z10: =中信三级行业指数热度!E116 -> -3.9141197 | AA10: =中信三级行业指数热度!E45 -> -3.8965396 | AB10: =中信三级行业指数热度!E237 -> -4.810784 | AC10: =中信三级行业指数热度!E104 -> -3.8904647 | AD10: =中信三级行业指数热度!E185 -> -2.4318222 | AE10: =中信三级行业指数热度!E7 -> -4.0003812 | AG10: =IFERROR(中信三级行业指数热度!G10+ROW()*0.0000000001,-9999) -> 1.53834
B11: =中信三级行业指数热度!B84&CHAR(10)&TEXT(中信三级行业指数热度!E84,"0.0")&"%" -> 医疗器械指数 -1.6% | C11: =中信三级行业指数热度!B225&CHAR(10)&TEXT(中信三级行业指数热度!E225,"0.0")&"%" -> 航空指数 3.0% | D11: =中信三级行业指数热度!B15&CHAR(10)&TEXT(中信三级行业指数热度!E15,"0.0")&"%" -> 特钢指数 -1.9% | E11: =中信三级行业指数热度!B128&CHAR(10)&TEXT(中信三级行业指数热度!E128,"0.0")&"%" -> 教育信息化及在线教育指数 -6.6% | F11: =中信三级行业指数热度!B200&CHAR(10)&TEXT(中信三级行业指数热度!E200,"0.0")&"%" -> 水电指数 -2.3% | G11: =中信三级行业指数热度!B141&CHAR(10)&TEXT(中信三级行业指数热度!E141,"0.0")&"%" -> 厨房电器Ⅲ指数 -2.3% | H11: =中信三级行业指数热度!B251&CHAR(10)&TEXT(中信三级行业指数热度!E251,"0.0")&"%" -> 服务综合指数 -8.0% | I11: =中信三级行业指数热度!B206&CHAR(10)&TEXT(中信三级行业指数热度!E206,"0.0")&"%" -> 百货指数 -4.0% | J11: =中信三级行业指数热度!B215&CHAR(10)&TEXT(中信三级行业指数热度!E215,"0.0")&"%" -> 石油开采Ⅲ指数 -7.0% | K11: =中信三级行业指数热度!B129&CHAR(10)&TEXT(中信三级行业指数热度!E129,"0.0")&"%" -> 线缆指数 15.7% | L11: =中信三级行业指数热度!B252&CHAR(10)&TEXT(中信三级行业指数热度!E252,"0.0")&"%" -> 有机硅指数 -0.6% | M11: =中信三级行业指数热度!B202&CHAR(10)&TEXT(中信三级行业指数热度!E202,"0.0")&"%" -> 休闲食品指数 -1.5% | N11: =中信三级行业指数热度!B118&CHAR(10)&TEXT(中信三级行业指数热度!E118,"0.0")&"%" -> 其他纺织指数 0.0% | O11: =中信三级行业指数热度!B207&CHAR(10)&TEXT(中信三级行业指数热度!E207,"0.0")&"%" -> 其他电子零组件Ⅲ指数 1.1% | R11: =中信三级行业指数热度!E84 -> -1.5751358 | S11: =中信三级行业指数热度!E225 -> 3.0282445 | T11: =中信三级行业指数热度!E15 -> -1.8536246 | U11: =中信三级行业指数热度!E128 -> -6.6274644 | V11: =中信三级行业指数热度!E200 -> -2.3319551 | W11: =中信三级行业指数热度!E141 -> -2.3229648 | X11: =中信三级行业指数热度!E251 -> -7.9524702 | Y11: =中信三级行业指数热度!E206 -> -3.9966181 | Z11: =中信三级行业指数热度!E215 -> -6.9647159 | AA11: =中信三级行业指数热度!E129 -> 15.676661 | AB11: =中信三级行业指数热度!E252 -> -0.64215108 | AC11: =中信三级行业指数热度!E202 -> -1.524849 | AD11: =中信三级行业指数热度!E118 -> 0.047723483 | AE11: =中信三级行业指数热度!E207 -> 1.0998687 | AG11: =IFERROR(中信三级行业指数热度!G11+ROW()*0.0000000001,-9999) -> 1.1188516
B12: =中信三级行业指数热度!B218&CHAR(10)&TEXT(中信三级行业指数热度!E218,"0.0")&"%" -> 超市及便利店指数 -2.9% | C12: =中信三级行业指数热度!B198&CHAR(10)&TEXT(中信三级行业指数热度!E198,"0.0")&"%" -> 板材指数 -3.2% | D12: =中信三级行业指数热度!B203&CHAR(10)&TEXT(中信三级行业指数热度!E203,"0.0")&"%" -> 其他军工Ⅲ指数 -3.2% | E12: =中信三级行业指数热度!B155&CHAR(10)&TEXT(中信三级行业指数热度!E155,"0.0")&"%" -> 基础软件及管理办公软件指数 -7.2% | F12: =中信三级行业指数热度!B125&CHAR(10)&TEXT(中信三级行业指数热度!E125,"0.0")&"%" -> 电力电子及自动化指数 -3.2% | G12: =中信三级行业指数热度!B178&CHAR(10)&TEXT(中信三级行业指数热度!E178,"0.0")&"%" -> 印刷指数 -9.1% | H12: =中信三级行业指数热度!B156&CHAR(10)&TEXT(中信三级行业指数热度!E156,"0.0")&"%" -> 乳制品指数 0.4% | I12: =中信三级行业指数热度!B96&CHAR(10)&TEXT(中信三级行业指数热度!E96,"0.0")&"%" -> 其他结构材料指数 -3.3% | J12: =中信三级行业指数热度!B186&CHAR(10)&TEXT(中信三级行业指数热度!E186,"0.0")&"%" -> 园林工程指数 -5.3% | K12: =中信三级行业指数热度!B54&CHAR(10)&TEXT(中信三级行业指数热度!E54,"0.0")&"%" -> 中药饮片指数 -8.8% | L12: =中信三级行业指数热度!B190&CHAR(10)&TEXT(中信三级行业指数热度!E190,"0.0")&"%" -> 珠宝首饰及钟表指数 -3.6% | M12: =中信三级行业指数热度!B68&CHAR(10)&TEXT(中信三级行业指数热度!E68,"0.0")&"%" -> 油气装备指数 -1.9% | N12: =中信三级行业指数热度!B126&CHAR(10)&TEXT(中信三级行业指数热度!E126,"0.0")&"%" -> 铝指数 -2.4% | O12: =中信三级行业指数热度!B233&CHAR(10)&TEXT(中信三级行业指数热度!E233,"0.0")&"%" -> 全国性股份制银行Ⅲ指数 -2.2% | R12: =中信三级行业指数热度!E218 -> -2.9449684 | S12: =中信三级行业指数热度!E198 -> -3.1920895 | T12: =中信三级行业指数热度!E203 -> -3.1636281 | U12: =中信三级行业指数热度!E155 -> -7.2124035 | V12: =中信三级行业指数热度!E125 -> -3.2124474 | W12: =中信三级行业指数热度!E178 -> -9.0793174 | X12: =中信三级行业指数热度!E156 -> 0.37709553 | Y12: =中信三级行业指数热度!E96 -> -3.310468 | Z12: =中信三级行业指数热度!E186 -> -5.3413633 | AA12: =中信三级行业指数热度!E54 -> -8.8269993 | AB12: =中信三级行业指数热度!E190 -> -3.5500377 | AC12: =中信三级行业指数热度!E68 -> -1.8947478 | AD12: =中信三级行业指数热度!E126 -> -2.4044909 | AE12: =中信三级行业指数热度!E233 -> -2.2401415 | AG12: =IFERROR(中信三级行业指数热度!G12+ROW()*0.0000000001,-9999) -> 1.0921849
B13: =中信三级行业指数热度!B38&CHAR(10)&TEXT(中信三级行业指数热度!E38,"0.0")&"%" -> 增值服务Ⅲ指数 -4.5% | C13: =中信三级行业指数热度!B106&CHAR(10)&TEXT(中信三级行业指数热度!E106,"0.0")&"%" -> 影视指数 -1.9% | D13: =中信三级行业指数热度!B29&CHAR(10)&TEXT(中信三级行业指数热度!E29,"0.0")&"%" -> 其他化学原料指数 7.0% | E13: =中信三级行业指数热度!B192&CHAR(10)&TEXT(中信三级行业指数热度!E192,"0.0")&"%" -> 畜牧养殖指数 -3.9% | F13: =中信三级行业指数热度!B113&CHAR(10)&TEXT(中信三级行业指数热度!E113,"0.0")&"%" -> 港口指数 -2.1% | G13: =中信三级行业指数热度!B223&CHAR(10)&TEXT(中信三级行业指数热度!E223,"0.0")&"%" -> 乘用车Ⅲ指数 -6.1% | H13: =中信三级行业指数热度!B256&CHAR(10)&TEXT(中信三级行业指数热度!E256,"0.0")&"%" -> 火电指数 -4.6% | I13: =中信三级行业指数热度!B14&CHAR(10)&TEXT(中信三级行业指数热度!E14,"0.0")&"%" -> 化学原料药指数 4.6% | J13: =中信三级行业指数热度!B110&CHAR(10)&TEXT(中信三级行业指数热度!E110,"0.0")&"%" -> 其他专用机械指数 0.0% | K13: =中信三级行业指数热度!B64&CHAR(10)&TEXT(中信三级行业指数热度!E64,"0.0")&"%" -> 其他食品指数 1.1% | L13: =中信三级行业指数热度!B238&CHAR(10)&TEXT(中信三级行业指数热度!E238,"0.0")&"%" -> 玻璃指数 -0.7% | M13: =中信三级行业指数热度!B194&CHAR(10)&TEXT(中信三级行业指数热度!E194,"0.0")&"%" -> 氯碱指数 3.2% | N13: =中信三级行业指数热度!B97&CHAR(10)&TEXT(中信三级行业指数热度!E97,"0.0")&"%" -> 物业经纪服务指数 -4.1% | O13: =中信三级行业指数热度!B85&CHAR(10)&TEXT(中信三级行业指数热度!E85,"0.0")&"%" -> 磷肥及磷化工指数 13.0% | R13: =中信三级行业指数热度!E38 -> -4.4966796 | S13: =中信三级行业指数热度!E106 -> -1.8508264 | T13: =中信三级行业指数热度!E29 -> 6.963528 | U13: =中信三级行业指数热度!E192 -> -3.8910515 | V13: =中信三级行业指数热度!E113 -> -2.092177 | W13: =中信三级行业指数热度!E223 -> -6.0856247 | X13: =中信三级行业指数热度!E256 -> -4.5993776 | Y13: =中信三级行业指数热度!E14 -> 4.6023343 | Z13: =中信三级行业指数热度!E110 -> -0.03290472 | AA13: =中信三级行业指数热度!E64 -> 1.0843792 | AB13: =中信三级行业指数热度!E238 -> -0.74502543 | AC13: =中信三级行业指数热度!E194 -> 3.2324587 | AD13: =中信三级行业指数热度!E97 -> -4.1411661 | AE13: =中信三级行业指数热度!E85 -> 13.043545 | AG13: =IFERROR(中信三级行业指数热度!G13+ROW()*0.0000000001,-9999) -> 1.4421281
B14: =中信三级行业指数热度!B72&CHAR(10)&TEXT(中信三级行业指数热度!E72,"0.0")&"%" -> 其他家居指数 -2.5% | C14: =中信三级行业指数热度!B257&CHAR(10)&TEXT(中信三级行业指数热度!E257,"0.0")&"%" -> 其他酒指数 -6.5% | D14: =中信三级行业指数热度!B213&CHAR(10)&TEXT(中信三级行业指数热度!E213,"0.0")&"%" -> 金属制品Ⅲ指数 -7.0% | E14: =中信三级行业指数热度!B78&CHAR(10)&TEXT(中信三级行业指数热度!E78,"0.0")&"%" -> 其他塑料制品指数 -1.9% | F14: =中信三级行业指数热度!B89&CHAR(10)&TEXT(中信三级行业指数热度!E89,"0.0")&"%" -> 绵纶指数 1.8% | G14: =中信三级行业指数热度!B167&CHAR(10)&TEXT(中信三级行业指数热度!E167,"0.0")&"%" -> 非住宅物业开发和运营指数 -1.5% | H14: =中信三级行业指数热度!B93&CHAR(10)&TEXT(中信三级行业指数热度!E93,"0.0")&"%" -> 车用电机电控指数 -5.0% | I14: =中信三级行业指数热度!B133&CHAR(10)&TEXT(中信三级行业指数热度!E133,"0.0")&"%" -> 物流综合指数 -1.6% | J14: =中信三级行业指数热度!B50&CHAR(10)&TEXT(中信三级行业指数热度!E50,"0.0")&"%" -> 摩托车及其他Ⅲ指数 1.4% | K14: =中信三级行业指数热度!B209&CHAR(10)&TEXT(中信三级行业指数热度!E209,"0.0")&"%" -> 其他连锁指数 -6.7% | L14: =中信三级行业指数热度!B65&CHAR(10)&TEXT(中信三级行业指数热度!E65,"0.0")&"%" -> 纸包装指数 -0.1% | M14: =中信三级行业指数热度!B195&CHAR(10)&TEXT(中信三级行业指数热度!E195,"0.0")&"%" -> 小家电Ⅲ指数 -6.2% | N14: =中信三级行业指数热度!B222&CHAR(10)&TEXT(中信三级行业指数热度!E222,"0.0")&"%" -> 工程机械Ⅲ指数 -4.9% | O14: =中信三级行业指数热度!B33&CHAR(10)&TEXT(中信三级行业指数热度!E33,"0.0")&"%" -> 化学制剂指数 3.3% | R14: =中信三级行业指数热度!E72 -> -2.5007458 | S14: =中信三级行业指数热度!E257 -> -6.5213846 | T14: =中信三级行业指数热度!E213 -> -6.9945085 | U14: =中信三级行业指数热度!E78 -> -1.8715974 | V14: =中信三级行业指数热度!E89 -> 1.8055389 | W14: =中信三级行业指数热度!E167 -> -1.5240746 | X14: =中信三级行业指数热度!E93 -> -4.9640395 | Y14: =中信三级行业指数热度!E133 -> -1.605378 | Z14: =中信三级行业指数热度!E50 -> 1.4120549 | AA14: =中信三级行业指数热度!E209 -> -6.7355539 | AB14: =中信三级行业指数热度!E65 -> -0.085813083 | AC14: =中信三级行业指数热度!E195 -> -6.2436943 | AD14: =中信三级行业指数热度!E222 -> -4.8703734 | AE14: =中信三级行业指数热度!E33 -> 3.2798066 | AG14: =IFERROR(中信三级行业指数热度!G14+ROW()*0.0000000001,-9999) -> 0.90345549
B15: =中信三级行业指数热度!B120&CHAR(10)&TEXT(中信三级行业指数热度!E120,"0.0")&"%" -> 其他包装指数 0.5% | C15: =中信三级行业指数热度!B39&CHAR(10)&TEXT(中信三级行业指数热度!E39,"0.0")&"%" -> 通信终端及配件指数 4.3% | D15: =中信三级行业指数热度!B241&CHAR(10)&TEXT(中信三级行业指数热度!E241,"0.0")&"%" -> 保险Ⅲ指数 1.8% | E15: =中信三级行业指数热度!B169&CHAR(10)&TEXT(中信三级行业指数热度!E169,"0.0")&"%" -> 人力资源服务指数 -3.4% | F15: =中信三级行业指数热度!B115&CHAR(10)&TEXT(中信三级行业指数热度!E115,"0.0")&"%" -> 涂料油墨颜料指数 -0.8% | G15: =中信三级行业指数热度!B180&CHAR(10)&TEXT(中信三级行业指数热度!E180,"0.0")&"%" -> 纯碱指数 -0.4% | H15: =中信三级行业指数热度!B208&CHAR(10)&TEXT(中信三级行业指数热度!E208,"0.0")&"%" -> 宠物食品指数 -3.5% | I15: =中信三级行业指数热度!B211&CHAR(10)&TEXT(中信三级行业指数热度!E211,"0.0")&"%" -> 农产品加工Ⅲ指数 -6.0% | J15: =中信三级行业指数热度!B255&CHAR(10)&TEXT(中信三级行业指数热度!E255,"0.0")&"%" -> 黄金指数 -11.4% | K15: =中信三级行业指数热度!B148&CHAR(10)&TEXT(中信三级行业指数热度!E148,"0.0")&"%" -> 系统设备指数 1.9% | L15: =中信三级行业指数热度!B164&CHAR(10)&TEXT(中信三级行业指数热度!E164,"0.0")&"%" -> 改性塑料指数 -3.9% | M15: =中信三级行业指数热度!B55&CHAR(10)&TEXT(中信三级行业指数热度!E55,"0.0")&"%" -> 其他非银金融指数 2.4% | N15: =中信三级行业指数热度!B111&CHAR(10)&TEXT(中信三级行业指数热度!E111,"0.0")&"%" -> 基础件指数 -4.6% | O15: =中信三级行业指数热度!B44&CHAR(10)&TEXT(中信三级行业指数热度!E44,"0.0")&"%" -> 多领域控股Ⅲ指数 0.1% | R15: =中信三级行业指数热度!E120 -> 0.48185541 | S15: =中信三级行业指数热度!E39 -> 4.2681039 | T15: =中信三级行业指数热度!E241 -> 1.8232594 | U15: =中信三级行业指数热度!E169 -> -3.4183568 | V15: =中信三级行业指数热度!E115 -> -0.80681619 | W15: =中信三级行业指数热度!E180 -> -0.42091993 | X15: =中信三级行业指数热度!E208 -> -3.5365171 | Y15: =中信三级行业指数热度!E211 -> -6.0062537 | Z15: =中信三级行业指数热度!E255 -> -11.447703 | AA15: =中信三级行业指数热度!E148 -> 1.9445069 | AB15: =中信三级行业指数热度!E164 -> -3.9264122 | AC15: =中信三级行业指数热度!E55 -> 2.4142643 | AD15: =中信三级行业指数热度!E111 -> -4.5566997 | AE15: =中信三级行业指数热度!E44 -> 0.13312361 | AG15: =IFERROR(中信三级行业指数热度!G15+ROW()*0.0000000001,-9999) -> -0.20884913
B16: =中信三级行业指数热度!B130&CHAR(10)&TEXT(中信三级行业指数热度!E130,"0.0")&"%" -> 电池综合服务指数 -3.1% | C16: =中信三级行业指数热度!B95&CHAR(10)&TEXT(中信三级行业指数热度!E95,"0.0")&"%" -> 玻璃纤维指数 23.2% | D16: =中信三级行业指数热度!B174&CHAR(10)&TEXT(中信三级行业指数热度!E174,"0.0")&"%" -> 体育及户外品牌指数 19.2% | E16: =中信三级行业指数热度!B105&CHAR(10)&TEXT(中信三级行业指数热度!E105,"0.0")&"%" -> 服务机器人指数 -2.0% | F16: =中信三级行业指数热度!B132&CHAR(10)&TEXT(中信三级行业指数热度!E132,"0.0")&"%" -> 餐饮指数 -3.0% | G16: =中信三级行业指数热度!B100&CHAR(10)&TEXT(中信三级行业指数热度!E100,"0.0")&"%" -> 医药流通指数 -2.1% | H16: =中信三级行业指数热度!B249&CHAR(10)&TEXT(中信三级行业指数热度!E249,"0.0")&"%" -> 家电3C指数 -7.8% | I16: =中信三级行业指数热度!B153&CHAR(10)&TEXT(中信三级行业指数热度!E153,"0.0")&"%" -> 太阳能指数 -0.9% | J16: =中信三级行业指数热度!B193&CHAR(10)&TEXT(中信三级行业指数热度!E193,"0.0")&"%" -> 配电设备指数 -4.4% | K16: =中信三级行业指数热度!B175&CHAR(10)&TEXT(中信三级行业指数热度!E175,"0.0")&"%" -> 水泥指数 -1.3% | L16: =中信三级行业指数热度!B187&CHAR(10)&TEXT(中信三级行业指数热度!E187,"0.0")&"%" -> 景区指数 -3.3% | M16: =中信三级行业指数热度!B30&CHAR(10)&TEXT(中信三级行业指数热度!E30,"0.0")&"%" -> 网络覆盖优化与运维指数 -2.8% | N16: =中信三级行业指数热度!B70&CHAR(10)&TEXT(中信三级行业指数热度!E70,"0.0")&"%" -> 汽车销售及服务Ⅲ指数 -2.3% | O16: =中信三级行业指数热度!B161&CHAR(10)&TEXT(中信三级行业指数热度!E161,"0.0")&"%" -> 船舶制造指数 -2.6% | R16: =中信三级行业指数热度!E130 -> -3.0787083 | S16: =中信三级行业指数热度!E95 -> 23.198454 | T16: =中信三级行业指数热度!E174 -> 19.238437 | U16: =中信三级行业指数热度!E105 -> -2.0360908 | V16: =中信三级行业指数热度!E132 -> -2.9720068 | W16: =中信三级行业指数热度!E100 -> -2.1185569 | X16: =中信三级行业指数热度!E249 -> -7.7515031 | Y16: =中信三级行业指数热度!E153 -> -0.90229483 | Z16: =中信三级行业指数热度!E193 -> -4.3823399 | AA16: =中信三级行业指数热度!E175 -> -1.3169824 | AB16: =中信三级行业指数热度!E187 -> -3.2632248 | AC16: =中信三级行业指数热度!E30 -> -2.8461825 | AD16: =中信三级行业指数热度!E70 -> -2.3057969 | AE16: =中信三级行业指数热度!E161 -> -2.5982194 | AG16: =IFERROR(中信三级行业指数热度!G16+ROW()*0.0000000001,-9999) -> 0.82467338
B17: =中信三级行业指数热度!B143&CHAR(10)&TEXT(中信三级行业指数热度!E143,"0.0")&"%" -> 肉制品指数 3.9% | C17: =中信三级行业指数热度!B258&CHAR(10)&TEXT(中信三级行业指数热度!E258,"0.0")&"%" -> 锂电设备指数 -6.4% | D17: =中信三级行业指数热度!B197&CHAR(10)&TEXT(中信三级行业指数热度!E197,"0.0")&"%" -> 安防指数 1.5% | E17: =中信三级行业指数热度!B135&CHAR(10)&TEXT(中信三级行业指数热度!E135,"0.0")&"%" -> 铁路交通设备指数 -3.1% | F17: =中信三级行业指数热度!B36&CHAR(10)&TEXT(中信三级行业指数热度!E36,"0.0")&"%" -> 通用计算机设备指数 5.0% | G17: =中信三级行业指数热度!B112&CHAR(10)&TEXT(中信三级行业指数热度!E112,"0.0")&"%" -> 塑料加工机械指数 -4.1% | H17: =中信三级行业指数热度!B232&CHAR(10)&TEXT(中信三级行业指数热度!E232,"0.0")&"%" -> 油田服务指数 -3.8% | I17: =中信三级行业指数热度!B219&CHAR(10)&TEXT(中信三级行业指数热度!E219,"0.0")&"%" -> 城商行指数 -1.4% | J17: =中信三级行业指数热度!B159&CHAR(10)&TEXT(中信三级行业指数热度!E159,"0.0")&"%" -> 航天军工指数 -3.8% | K17: =中信三级行业指数热度!B134&CHAR(10)&TEXT(中信三级行业指数热度!E134,"0.0")&"%" -> 航空军工指数 -3.4% | L17: =中信三级行业指数热度!B199&CHAR(10)&TEXT(中信三级行业指数热度!E199,"0.0")&"%" -> 休闲综合指数 -4.2% | M17: =中信三级行业指数热度!B188&CHAR(10)&TEXT(中信三级行业指数热度!E188,"0.0")&"%" -> 农商行指数 -1.5% | N17: =中信三级行业指数热度!B217&CHAR(10)&TEXT(中信三级行业指数热度!E217,"0.0")&"%" -> 房建建设指数 -4.1% | O17: =中信三级行业指数热度!B83&CHAR(10)&TEXT(中信三级行业指数热度!E83,"0.0")&"%" -> 环保及水务指数 -1.0% | R17: =中信三级行业指数热度!E143 -> 3.9368365 | S17: =中信三级行业指数热度!E258 -> -6.4372903 | T17: =中信三级行业指数热度!E197 -> 1.4525424 | U17: =中信三级行业指数热度!E135 -> -3.1370846 | V17: =中信三级行业指数热度!E36 -> 5.0357421 | W17: =中信三级行业指数热度!E112 -> -4.0763878 | X17: =中信三级行业指数热度!E232 -> -3.7955606 | Y17: =中信三级行业指数热度!E219 -> -1.3944542 | Z17: =中信三级行业指数热度!E159 -> -3.773255 | AA17: =中信三级行业指数热度!E134 -> -3.4467939 | AB17: =中信三级行业指数热度!E199 -> -4.2416758 | AC17: =中信三级行业指数热度!E188 -> -1.4503282 | AD17: =中信三级行业指数热度!E217 -> -4.1394512 | AE17: =中信三级行业指数热度!E83 -> -0.97761711 | AG17: =IFERROR(中信三级行业指数热度!G17+ROW()*0.0000000001,-9999) -> 0.56285423
B18: =中信三级行业指数热度!B160&CHAR(10)&TEXT(中信三级行业指数热度!E160,"0.0")&"%" -> 林木及加工指数 -5.9% | C18: =中信三级行业指数热度!B163&CHAR(10)&TEXT(中信三级行业指数热度!E163,"0.0")&"%" -> 矿山冶金机械指数 -4.6% | D18: =中信三级行业指数热度!B239&CHAR(10)&TEXT(中信三级行业指数热度!E239,"0.0")&"%" -> 氟化工指数 10.7% | E18: =中信三级行业指数热度!B73&CHAR(10)&TEXT(中信三级行业指数热度!E73,"0.0")&"%" -> 燃气指数 -4.0% | F18: =中信三级行业指数热度!B41&CHAR(10)&TEXT(中信三级行业指数热度!E41,"0.0")&"%" -> 饲料加工指数 2.1% | G18: =中信三级行业指数热度!B171&CHAR(10)&TEXT(中信三级行业指数热度!E171,"0.0")&"%" -> 其他稀有金属指数 9.3% | H18: =中信三级行业指数热度!B177&CHAR(10)&TEXT(中信三级行业指数热度!E177,"0.0")&"%" -> 铁路指数 -1.7% | I18: =中信三级行业指数热度!B26&CHAR(10)&TEXT(中信三级行业指数热度!E26,"0.0")&"%" -> 公交指数 -5.9% | J18: =中信三级行业指数热度!B224&CHAR(10)&TEXT(中信三级行业指数热度!E224,"0.0")&"%" -> 旅游服务指数 -4.1% | K18: =中信三级行业指数热度!B220&CHAR(10)&TEXT(中信三级行业指数热度!E220,"0.0")&"%" -> 炼油指数 -3.1% | L18: =中信三级行业指数热度!B154&CHAR(10)&TEXT(中信三级行业指数热度!E154,"0.0")&"%" -> 园区综合开发指数 -4.1% | M18: =中信三级行业指数热度!B228&CHAR(10)&TEXT(中信三级行业指数热度!E228,"0.0")&"%" -> 动力煤指数 -3.3% | N18: =中信三级行业指数热度!B227&CHAR(10)&TEXT(中信三级行业指数热度!E227,"0.0")&"%" -> 光伏设备指数 0.5% | O18: =中信三级行业指数热度!B109&CHAR(10)&TEXT(中信三级行业指数热度!E109,"0.0")&"%" -> 建筑设计及服务Ⅲ指数 -3.1% | R18: =中信三级行业指数热度!E160 -> -5.9133491 | S18: =中信三级行业指数热度!E163 -> -4.5767158 | T18: =中信三级行业指数热度!E239 -> 10.655347 | U18: =中信三级行业指数热度!E73 -> -4.0426162 | V18: =中信三级行业指数热度!E41 -> 2.1297964 | W18: =中信三级行业指数热度!E171 -> 9.3400709 | X18: =中信三级行业指数热度!E177 -> -1.6660782 | Y18: =中信三级行业指数热度!E26 -> -5.922553 | Z18: =中信三级行业指数热度!E224 -> -4.1055732 | AA18: =中信三级行业指数热度!E220 -> -3.1366922 | AB18: =中信三级行业指数热度!E154 -> -4.0950253 | AC18: =中信三级行业指数热度!E228 -> -3.2567954 | AD18: =中信三级行业指数热度!E227 -> 0.45400684 | AE18: =中信三级行业指数热度!E109 -> -3.0802052 | AG18: =IFERROR(中信三级行业指数热度!G18+ROW()*0.0000000001,-9999) -> 1.2790469
B19: =中信三级行业指数热度!B13&CHAR(10)&TEXT(中信三级行业指数热度!E13,"0.0")&"%" -> 印染化学品指数 9.6% | C19: =中信三级行业指数热度!B191&CHAR(10)&TEXT(中信三级行业指数热度!E191,"0.0")&"%" -> 国有大型银行Ⅲ指数 -0.7% | D19: =中信三级行业指数热度!B92&CHAR(10)&TEXT(中信三级行业指数热度!E92,"0.0")&"%" -> 铅锌指数 1.6% | E19: =中信三级行业指数热度!B242&CHAR(10)&TEXT(中信三级行业指数热度!E242,"0.0")&"%" -> 纺织服装机械指数 -5.9% | F19: =中信三级行业指数热度!B168&CHAR(10)&TEXT(中信三级行业指数热度!E168,"0.0")&"%" -> 长材指数 -3.6% | G19: =中信三级行业指数热度!B234&CHAR(10)&TEXT(中信三级行业指数热度!E234,"0.0")&"%" -> 电信运营Ⅲ指数 -4.6% | H19: =中信三级行业指数热度!B254&CHAR(10)&TEXT(中信三级行业指数热度!E254,"0.0")&"%" -> 膜材料指数 2.8% | I19: =中信三级行业指数热度!B229&CHAR(10)&TEXT(中信三级行业指数热度!E229,"0.0")&"%" -> 钾肥指数 -0.9% | J19: =中信三级行业指数热度!B76&CHAR(10)&TEXT(中信三级行业指数热度!E76,"0.0")&"%" -> 钢铁耗材指数 6.4% | K19: =中信三级行业指数热度!B262&CHAR(10)&TEXT(中信三级行业指数热度!E262,"0.0")&"%" -> 被动元件指数 4.0% | L19: =中信三级行业指数热度!B102&CHAR(10)&TEXT(中信三级行业指数热度!E102,"0.0")&"%" -> 其他轻工Ⅲ指数 1.0% | M19: =中信三级行业指数热度!B149&CHAR(10)&TEXT(中信三级行业指数热度!E149,"0.0")&"%" -> 3C设备指数 8.2% | N19: =中信三级行业指数热度!B236&CHAR(10)&TEXT(中信三级行业指数热度!E236,"0.0")&"%" -> 文娱轻工Ⅲ指数 -2.5% | O19: =中信三级行业指数热度!B204&CHAR(10)&TEXT(中信三级行业指数热度!E204,"0.0")&"%" -> 白酒指数 -0.7% | R19: =中信三级行业指数热度!E13 -> 9.5575775 | S19: =中信三级行业指数热度!E191 -> -0.66821903 | T19: =中信三级行业指数热度!E92 -> 1.6329874 | U19: =中信三级行业指数热度!E242 -> -5.8533688 | V19: =中信三级行业指数热度!E168 -> -3.6369307 | W19: =中信三级行业指数热度!E234 -> -4.6007582 | X19: =中信三级行业指数热度!E254 -> 2.8281898 | Y19: =中信三级行业指数热度!E229 -> -0.90432899 | Z19: =中信三级行业指数热度!E76 -> 6.4347356 | AA19: =中信三级行业指数热度!E262 -> 4.0355352 | AB19: =中信三级行业指数热度!E102 -> 0.96269827 | AC19: =中信三级行业指数热度!E149 -> 8.1546194 | AD19: =中信三级行业指数热度!E236 -> -2.5075074 | AE19: =中信三级行业指数热度!E204 -> -0.66575342 | AG19: =IFERROR(中信三级行业指数热度!G19+ROW()*0.0000000001,-9999) -> 1.2602125
B20: =中信三级行业指数热度!B117&CHAR(10)&TEXT(中信三级行业指数热度!E117,"0.0")&"%" -> 速冻食品指数 -0.2% | C20: =中信三级行业指数热度!B261&CHAR(10)&TEXT(中信三级行业指数热度!E261,"0.0")&"%" -> 铁矿石指数 -5.6% | D20: =中信三级行业指数热度!B170&CHAR(10)&TEXT(中信三级行业指数热度!E170,"0.0")&"%" -> 白色家电Ⅲ指数 -0.6% | E20: =中信三级行业指数热度!B114&CHAR(10)&TEXT(中信三级行业指数热度!E114,"0.0")&"%" -> 中高端成人品牌服饰指数 -5.5% | F20: =中信三级行业指数热度!B201&CHAR(10)&TEXT(中信三级行业指数热度!E201,"0.0")&"%" -> 镍钴锡锑指数 -1.6% | G20: =中信三级行业指数热度!B235&CHAR(10)&TEXT(中信三级行业指数热度!E235,"0.0")&"%" -> 焦炭指数 -2.7% | H20: =中信三级行业指数热度!B221&CHAR(10)&TEXT(中信三级行业指数热度!E221,"0.0")&"%" -> 种植指数 -9.5% | I20: =中信三级行业指数热度!B260&CHAR(10)&TEXT(中信三级行业指数热度!E260,"0.0")&"%" -> 橡胶制品指数 -3.7% | J20: =中信三级行业指数热度!B243&CHAR(10)&TEXT(中信三级行业指数热度!E243,"0.0")&"%" -> 铜指数 -11.5% | K20: =中信三级行业指数热度!B214&CHAR(10)&TEXT(中信三级行业指数热度!E214,"0.0")&"%" -> 轮胎指数 0.5% | L20: =中信三级行业指数热度!B127&CHAR(10)&TEXT(中信三级行业指数热度!E127,"0.0")&"%" -> 仪器仪表Ⅲ指数 2.6% | M20: =中信三级行业指数热度!B230&CHAR(10)&TEXT(中信三级行业指数热度!E230,"0.0")&"%" -> 稀土及磁性材料指数 -1.7% | N20: =中信三级行业指数热度!B138&CHAR(10)&TEXT(中信三级行业指数热度!E138,"0.0")&"%" -> 快递指数 -0.5% | O20: =中信三级行业指数热度!B216&CHAR(10)&TEXT(中信三级行业指数热度!E216,"0.0")&"%" -> 机场指数 0.0% | R20: =中信三级行业指数热度!E117 -> -0.24885511 | S20: =中信三级行业指数热度!E261 -> -5.5897634 | T20: =中信三级行业指数热度!E170 -> -0.64144773 | U20: =中信三级行业指数热度!E114 -> -5.5389857 | V20: =中信三级行业指数热度!E201 -> -1.6466987 | W20: =中信三级行业指数热度!E235 -> -2.7159017 | X20: =中信三级行业指数热度!E221 -> -9.4758169 | Y20: =中信三级行业指数热度!E260 -> -3.7006007 | Z20: =中信三级行业指数热度!E243 -> -11.541406 | AA20: =中信三级行业指数热度!E214 -> 0.52027398 | AB20: =中信三级行业指数热度!E127 -> 2.5717674 | AC20: =中信三级行业指数热度!E230 -> -1.6910097 | AD20: =中信三级行业指数热度!E138 -> -0.51159502 | AE20: =中信三级行业指数热度!E216 -> 0.02683421 | AG20: =IFERROR(中信三级行业指数热度!G20+ROW()*0.0000000001,-9999) -> 0.45883474
B21: =中信三级行业指数热度!B98&CHAR(10)&TEXT(中信三级行业指数热度!E98,"0.0")&"%" -> 广播电视指数 -3.5% | C21: =中信三级行业指数热度!B183&CHAR(10)&TEXT(中信三级行业指数热度!E183,"0.0")&"%" -> 网络接配及塔设指数 -0.3% | D21: =中信三级行业指数热度!B250&CHAR(10)&TEXT(中信三级行业指数热度!E250,"0.0")&"%" -> 炼焦煤指数 -3.9% | E21: =中信三级行业指数热度!B24&CHAR(10)&TEXT(中信三级行业指数热度!E24,"0.0")&"%" -> 数字金融服务指数 -3.5% | F21: =中信三级行业指数热度!B259&CHAR(10)&TEXT(中信三级行业指数热度!E259,"0.0")&"%" -> 核电指数 -10.7% | G21: =中信三级行业指数热度!B58&CHAR(10)&TEXT(中信三级行业指数热度!E58,"0.0")&"%" -> 云软件服务指数 -3.3% | H21: =中信三级行业指数热度!B247&CHAR(10)&TEXT(中信三级行业指数热度!E247,"0.0")&"%" -> 无烟煤指数 -0.8% | I21: =中信三级行业指数热度!B226&CHAR(10)&TEXT(中信三级行业指数热度!E226,"0.0")&"%" -> 机床设备指数 -2.9% | J21: =中信三级行业指数热度!B248&CHAR(10)&TEXT(中信三级行业指数热度!E248,"0.0")&"%" -> 啤酒指数 -3.0% | R21: =中信三级行业指数热度!E98 -> -3.4538984 | S21: =中信三级行业指数热度!E183 -> -0.33990381 | T21: =中信三级行业指数热度!E250 -> -3.8884129 | U21: =中信三级行业指数热度!E24 -> -3.4811007 | V21: =中信三级行业指数热度!E259 -> -10.706623 | W21: =中信三级行业指数热度!E58 -> -3.2543881 | X21: =中信三级行业指数热度!E247 -> -0.82069941 | Y21: =中信三级行业指数热度!E226 -> -2.9103441 | Z21: =中信三级行业指数热度!E248 -> -2.9595863 | AG21: =IFERROR(中信三级行业指数热度!G21+ROW()*0.0000000001,-9999) -> 0.22109404
AG22: =IFERROR(中信三级行业指数热度!G22+ROW()*0.0000000001,-9999) -> 0.46354522
B23: 图例(近一周涨跌幅): | D23: ≤-7% | E23: -7~-3% | F23: -3~-1% | G23: -1~1% | H23: 1~3% | I23: 3~7% | J23: ≥7% | AG23: =IFERROR(中信三级行业指数热度!G23+ROW()*0.0000000001,-9999) -> 0.67721979
AG24: =IFERROR(中信三级行业指数热度!G24+ROW()*0.0000000001,-9999) -> -0.22359984
AG25: =IFERROR(中信三级行业指数热度!G25+ROW()*0.0000000001,-9999) -> -0.31091614
B26: 短期热点 TOP20（按动量加速度自动排名，随刷新更新） | AG26: =IFERROR(中信三级行业指数热度!G26+ROW()*0.0000000001,-9999) -> -0.34970065
B27: 排名 | C27: 指数名称 | D27: 近一周(%) | E27: 近一月(%) | F27: 动量加速度 | G27: YTD(%) | AG27: =IFERROR(中信三级行业指数热度!G27+ROW()*0.0000000001,-9999) -> -0.18576884
B28: 1 | C28: =IFERROR(INDEX(中信三级行业指数热度!$B$2:$B$262,MATCH(LARGE($AG$2:$AG$262,1),$AG$2:$AG$262,0)),"") -> 体育及户外品牌指数 | D28: =IFERROR(INDEX(中信三级行业指数热度!$E$2:$E$262,MATCH(LARGE($AG$2:$AG$262,1),$AG$2:$AG$262,0)),"") -> 19.238437 | E28: =IFERROR(INDEX(中信三级行业指数热度!$F$2:$F$262,MATCH(LARGE($AG$2:$AG$262,1),$AG$2:$AG$262,0)),"") -> 29.453079 | F28: =IFERROR(INDEX(中信三级行业指数热度!$G$2:$G$262,MATCH(LARGE($AG$2:$AG$262,1),$AG$2:$AG$262,0)),"") -> 2.3750335 | G28: =IFERROR(INDEX(中信三级行业指数热度!$D$2:$D$262,MATCH(LARGE($AG$2:$AG$262,1),$AG$2:$AG$262,0)),"") -> 67.503389 | AG28: =IFERROR(中信三级行业指数热度!G28+ROW()*0.0000000001,-9999) -> 1.4032429
B29: 2 | C29: =IFERROR(INDEX(中信三级行业指数热度!$B$2:$B$262,MATCH(LARGE($AG$2:$AG$262,2),$AG$2:$AG$262,0)),"") -> 磷肥及磷化工指数 | D29: =IFERROR(INDEX(中信三级行业指数热度!$E$2:$E$262,MATCH(LARGE($AG$2:$AG$262,2),$AG$2:$AG$262,0)),"") -> 13.043545 | E29: =IFERROR(INDEX(中信三级行业指数热度!$F$2:$F$262,MATCH(LARGE($AG$2:$AG$262,2),$AG$2:$AG$262,0)),"") -> 11.124112 | F29: =IFERROR(INDEX(中信三级行业指数热度!$G$2:$G$262,MATCH(LARGE($AG$2:$AG$262,2),$AG$2:$AG$262,0)),"") -> 2.0525034 | G29: =IFERROR(INDEX(中信三级行业指数热度!$D$2:$D$262,MATCH(LARGE($AG$2:$AG$262,2),$AG$2:$AG$262,0)),"") -> 9.9029401 | AG29: =IFERROR(中信三级行业指数热度!G29+ROW()*0.0000000001,-9999) -> 0.75782513
B30: 3 | C30: =IFERROR(INDEX(中信三级行业指数热度!$B$2:$B$262,MATCH(LARGE($AG$2:$AG$262,3),$AG$2:$AG$262,0)),"") -> 橡胶助剂指数 | D30: =IFERROR(INDEX(中信三级行业指数热度!$E$2:$E$262,MATCH(LARGE($AG$2:$AG$262,3),$AG$2:$AG$262,0)),"") -> 16.97181 | E30: =IFERROR(INDEX(中信三级行业指数热度!$F$2:$F$262,MATCH(LARGE($AG$2:$AG$262,3),$AG$2:$AG$262,0)),"") -> 27.839876 | F30: =IFERROR(INDEX(中信三级行业指数热度!$G$2:$G$262,MATCH(LARGE($AG$2:$AG$262,3),$AG$2:$AG$262,0)),"") -> 2.0023683 | G30: =IFERROR(INDEX(中信三级行业指数热度!$D$2:$D$262,MATCH(LARGE($AG$2:$AG$262,3),$AG$2:$AG$262,0)),"") -> 47.346122 | AG30: =IFERROR(中信三级行业指数热度!G30+ROW()*0.0000000001,-9999) -> -0.016405574
B31: 4 | C31: =IFERROR(INDEX(中信三级行业指数热度!$B$2:$B$262,MATCH(LARGE($AG$2:$AG$262,4),$AG$2:$AG$262,0)),"") -> 玻璃纤维指数 | D31: =IFERROR(INDEX(中信三级行业指数热度!$E$2:$E$262,MATCH(LARGE($AG$2:$AG$262,4),$AG$2:$AG$262,0)),"") -> 23.198454 | E31: =IFERROR(INDEX(中信三级行业指数热度!$F$2:$F$262,MATCH(LARGE($AG$2:$AG$262,4),$AG$2:$AG$262,0)),"") -> 52.748444 | F31: =IFERROR(INDEX(中信三级行业指数热度!$G$2:$G$262,MATCH(LARGE($AG$2:$AG$262,4),$AG$2:$AG$262,0)),"") -> 2.0022686 | G31: =IFERROR(INDEX(中信三级行业指数热度!$D$2:$D$262,MATCH(LARGE($AG$2:$AG$262,4),$AG$2:$AG$262,0)),"") -> 266.17091 | AG31: =IFERROR(中信三级行业指数热度!G31+ROW()*0.0000000001,-9999) -> 0.22622638
B32: 5 | C32: =IFERROR(INDEX(中信三级行业指数热度!$B$2:$B$262,MATCH(LARGE($AG$2:$AG$262,5),$AG$2:$AG$262,0)),"") -> 燃料电池指数 | D32: =IFERROR(INDEX(中信三级行业指数热度!$E$2:$E$262,MATCH(LARGE($AG$2:$AG$262,5),$AG$2:$AG$262,0)),"") -> 10.99687 | E32: =IFERROR(INDEX(中信三级行业指数热度!$F$2:$F$262,MATCH(LARGE($AG$2:$AG$262,5),$AG$2:$AG$262,0)),"") -> 13.220679 | F32: =IFERROR(INDEX(中信三级行业指数热度!$G$2:$G$262,MATCH(LARGE($AG$2:$AG$262,5),$AG$2:$AG$262,0)),"") -> 1.53834 | G32: =IFERROR(INDEX(中信三级行业指数热度!$D$2:$D$262,MATCH(LARGE($AG$2:$AG$262,5),$AG$2:$AG$262,0)),"") -> 37.50765 | AG32: =IFERROR(中信三级行业指数热度!G32+ROW()*0.0000000001,-9999) -> -0.022405872
B33: 6 | C33: =IFERROR(INDEX(中信三级行业指数热度!$B$2:$B$262,MATCH(LARGE($AG$2:$AG$262,6),$AG$2:$AG$262,0)),"") -> 分立器件指数 | D33: =IFERROR(INDEX(中信三级行业指数热度!$E$2:$E$262,MATCH(LARGE($AG$2:$AG$262,6),$AG$2:$AG$262,0)),"") -> 10.727 | E33: =IFERROR(INDEX(中信三级行业指数热度!$F$2:$F$262,MATCH(LARGE($AG$2:$AG$262,6),$AG$2:$AG$262,0)),"") -> 14.042782 | F33: =IFERROR(INDEX(中信三级行业指数热度!$G$2:$G$262,MATCH(LARGE($AG$2:$AG$262,6),$AG$2:$AG$262,0)),"") -> 1.4432608 | G33: =IFERROR(INDEX(中信三级行业指数热度!$D$2:$D$262,MATCH(LARGE($AG$2:$AG$262,6),$AG$2:$AG$262,0)),"") -> 63.771828 | AG33: =IFERROR(中信三级行业指数热度!G33+ROW()*0.0000000001,-9999) -> 0.65410445
B34: 7 | C34: =IFERROR(INDEX(中信三级行业指数热度!$B$2:$B$262,MATCH(LARGE($AG$2:$AG$262,7),$AG$2:$AG$262,0)),"") -> 印染化学品指数 | D34: =IFERROR(INDEX(中信三级行业指数热度!$E$2:$E$262,MATCH(LARGE($AG$2:$AG$262,7),$AG$2:$AG$262,0)),"") -> 9.5575775 | E34: =IFERROR(INDEX(中信三级行业指数热度!$F$2:$F$262,MATCH(LARGE($AG$2:$AG$262,7),$AG$2:$AG$262,0)),"") -> 9.3877472 | F34: =IFERROR(INDEX(中信三级行业指数热度!$G$2:$G$262,MATCH(LARGE($AG$2:$AG$262,7),$AG$2:$AG$262,0)),"") -> 1.4421281 | G34: =IFERROR(INDEX(中信三级行业指数热度!$D$2:$D$262,MATCH(LARGE($AG$2:$AG$262,7),$AG$2:$AG$262,0)),"") -> 25.606664 | AG34: =IFERROR(中信三级行业指数热度!G34+ROW()*0.0000000001,-9999) -> 0.86117279
B35: 8 | C35: =IFERROR(INDEX(中信三级行业指数热度!$B$2:$B$262,MATCH(LARGE($AG$2:$AG$262,8),$AG$2:$AG$262,0)),"") -> 贸易流通指数 | D35: =IFERROR(INDEX(中信三级行业指数热度!$E$2:$E$262,MATCH(LARGE($AG$2:$AG$262,8),$AG$2:$AG$262,0)),"") -> 5.7422695 | E35: =IFERROR(INDEX(中信三级行业指数热度!$F$2:$F$262,MATCH(LARGE($AG$2:$AG$262,8),$AG$2:$AG$262,0)),"") -> -5.0957807 | F35: =IFERROR(INDEX(中信三级行业指数热度!$G$2:$G$262,MATCH(LARGE($AG$2:$AG$262,8),$AG$2:$AG$262,0)),"") -> 1.4032429 | G35: =IFERROR(INDEX(中信三级行业指数热度!$D$2:$D$262,MATCH(LARGE($AG$2:$AG$262,8),$AG$2:$AG$262,0)),"") -> -15.250729 | AG35: =IFERROR(中信三级行业指数热度!G35+ROW()*0.0000000001,-9999) -> -0.25464709
B36: 9 | C36: =IFERROR(INDEX(中信三级行业指数热度!$B$2:$B$262,MATCH(LARGE($AG$2:$AG$262,9),$AG$2:$AG$262,0)),"") -> 医疗服务指数 | D36: =IFERROR(INDEX(中信三级行业指数热度!$E$2:$E$262,MATCH(LARGE($AG$2:$AG$262,9),$AG$2:$AG$262,0)),"") -> 8.0227067 | E36: =IFERROR(INDEX(中信三级行业指数热度!$F$2:$F$262,MATCH(LARGE($AG$2:$AG$262,9),$AG$2:$AG$262,0)),"") -> 5.0132767 | F36: =IFERROR(INDEX(中信三级行业指数热度!$G$2:$G$262,MATCH(LARGE($AG$2:$AG$262,9),$AG$2:$AG$262,0)),"") -> 1.3538775 | G36: =IFERROR(INDEX(中信三级行业指数热度!$D$2:$D$262,MATCH(LARGE($AG$2:$AG$262,9),$AG$2:$AG$262,0)),"") -> 4.0206399 | AG36: =IFERROR(中信三级行业指数热度!G36+ROW()*0.0000000001,-9999) -> 0.70687964
B37: 10 | C37: =IFERROR(INDEX(中信三级行业指数热度!$B$2:$B$262,MATCH(LARGE($AG$2:$AG$262,10),$AG$2:$AG$262,0)),"") -> 激光加工设备指数 | D37: =IFERROR(INDEX(中信三级行业指数热度!$E$2:$E$262,MATCH(LARGE($AG$2:$AG$262,10),$AG$2:$AG$262,0)),"") -> 10.215833 | E37: =IFERROR(INDEX(中信三级行业指数热度!$F$2:$F$262,MATCH(LARGE($AG$2:$AG$262,10),$AG$2:$AG$262,0)),"") -> 14.02073 | F37: =IFERROR(INDEX(中信三级行业指数热度!$G$2:$G$262,MATCH(LARGE($AG$2:$AG$262,10),$AG$2:$AG$262,0)),"") -> 1.34213 | G37: =IFERROR(INDEX(中信三级行业指数热度!$D$2:$D$262,MATCH(LARGE($AG$2:$AG$262,10),$AG$2:$AG$262,0)),"") -> 198.24216 | AG37: =IFERROR(中信三级行业指数热度!G37+ROW()*0.0000000001,-9999) -> -0.23456244
B38: 11 | C38: =IFERROR(INDEX(中信三级行业指数热度!$B$2:$B$262,MATCH(LARGE($AG$2:$AG$262,11),$AG$2:$AG$262,0)),"") -> 集成电路指数 | D38: =IFERROR(INDEX(中信三级行业指数热度!$E$2:$E$262,MATCH(LARGE($AG$2:$AG$262,11),$AG$2:$AG$262,0)),"") -> 10.902559 | E38: =IFERROR(INDEX(中信三级行业指数热度!$F$2:$F$262,MATCH(LARGE($AG$2:$AG$262,11),$AG$2:$AG$262,0)),"") -> 17.487046 | F38: =IFERROR(INDEX(中信三级行业指数热度!$G$2:$G$262,MATCH(LARGE($AG$2:$AG$262,11),$AG$2:$AG$262,0)),"") -> 1.3061596 | G38: =IFERROR(INDEX(中信三级行业指数热度!$D$2:$D$262,MATCH(LARGE($AG$2:$AG$262,11),$AG$2:$AG$262,0)),"") -> 84.306331 | AG38: =IFERROR(中信三级行业指数热度!G38+ROW()*0.0000000001,-9999) -> -0.36104983
B39: 12 | C39: =IFERROR(INDEX(中信三级行业指数热度!$B$2:$B$262,MATCH(LARGE($AG$2:$AG$262,12),$AG$2:$AG$262,0)),"") -> 其他稀有金属指数 | D39: =IFERROR(INDEX(中信三级行业指数热度!$E$2:$E$262,MATCH(LARGE($AG$2:$AG$262,12),$AG$2:$AG$262,0)),"") -> 9.3400709 | E39: =IFERROR(INDEX(中信三级行业指数热度!$F$2:$F$262,MATCH(LARGE($AG$2:$AG$262,12),$AG$2:$AG$262,0)),"") -> 11.478197 | F39: =IFERROR(INDEX(中信三级行业指数热度!$G$2:$G$262,MATCH(LARGE($AG$2:$AG$262,12),$AG$2:$AG$262,0)),"") -> 1.2941043 | G39: =IFERROR(INDEX(中信三级行业指数热度!$D$2:$D$262,MATCH(LARGE($AG$2:$AG$262,12),$AG$2:$AG$262,0)),"") -> 63.130382 | AG39: =IFERROR(中信三级行业指数热度!G39+ROW()*0.0000000001,-9999) -> 0.78081415
B40: 13 | C40: =IFERROR(INDEX(中信三级行业指数热度!$B$2:$B$262,MATCH(LARGE($AG$2:$AG$262,13),$AG$2:$AG$262,0)),"") -> 聚氨酯指数 | D40: =IFERROR(INDEX(中信三级行业指数热度!$E$2:$E$262,MATCH(LARGE($AG$2:$AG$262,13),$AG$2:$AG$262,0)),"") -> 6.3281788 | E40: =IFERROR(INDEX(中信三级行业指数热度!$F$2:$F$262,MATCH(LARGE($AG$2:$AG$262,13),$AG$2:$AG$262,0)),"") -> -0.26822226 | F40: =IFERROR(INDEX(中信三级行业指数热度!$G$2:$G$262,MATCH(LARGE($AG$2:$AG$262,13),$AG$2:$AG$262,0)),"") -> 1.2790469 | G40: =IFERROR(INDEX(中信三级行业指数热度!$D$2:$D$262,MATCH(LARGE($AG$2:$AG$262,13),$AG$2:$AG$262,0)),"") -> -2.8696267 | AG40: =IFERROR(中信三级行业指数热度!G40+ROW()*0.0000000001,-9999) -> 0.54143885
B41: 14 | C41: =IFERROR(INDEX(中信三级行业指数热度!$B$2:$B$262,MATCH(LARGE($AG$2:$AG$262,14),$AG$2:$AG$262,0)),"") -> 游戏指数 | D41: =IFERROR(INDEX(中信三级行业指数热度!$E$2:$E$262,MATCH(LARGE($AG$2:$AG$262,14),$AG$2:$AG$262,0)),"") -> 5.4308486 | E41: =IFERROR(INDEX(中信三级行业指数热度!$F$2:$F$262,MATCH(LARGE($AG$2:$AG$262,14),$AG$2:$AG$262,0)),"") -> -3.8390224 | F41: =IFERROR(INDEX(中信三级行业指数热度!$G$2:$G$262,MATCH(LARGE($AG$2:$AG$262,14),$AG$2:$AG$262,0)),"") -> 1.2781208 | G41: =IFERROR(INDEX(中信三级行业指数热度!$D$2:$D$262,MATCH(LARGE($AG$2:$AG$262,14),$AG$2:$AG$262,0)),"") -> -20.726341 | AG41: =IFERROR(中信三级行业指数热度!G41+ROW()*0.0000000001,-9999) -> 0.67707747
B42: 15 | C42: =IFERROR(INDEX(中信三级行业指数热度!$B$2:$B$262,MATCH(LARGE($AG$2:$AG$262,15),$AG$2:$AG$262,0)),"") -> 证券Ⅲ指数 | D42: =IFERROR(INDEX(中信三级行业指数热度!$E$2:$E$262,MATCH(LARGE($AG$2:$AG$262,15),$AG$2:$AG$262,0)),"") -> 9.4874126 | E42: =IFERROR(INDEX(中信三级行业指数热度!$F$2:$F$262,MATCH(LARGE($AG$2:$AG$262,15),$AG$2:$AG$262,0)),"") -> 12.574281 | F42: =IFERROR(INDEX(中信三级行业指数热度!$G$2:$G$262,MATCH(LARGE($AG$2:$AG$262,15),$AG$2:$AG$262,0)),"") -> 1.2687685 | G42: =IFERROR(INDEX(中信三级行业指数热度!$D$2:$D$262,MATCH(LARGE($AG$2:$AG$262,15),$AG$2:$AG$262,0)),"") -> -4.9994751 | AG42: =IFERROR(中信三级行业指数热度!G42+ROW()*0.0000000001,-9999) -> 0.042847331
B43: 16 | C43: =IFERROR(INDEX(中信三级行业指数热度!$B$2:$B$262,MATCH(LARGE($AG$2:$AG$262,16),$AG$2:$AG$262,0)),"") -> 钛白粉指数 | D43: =IFERROR(INDEX(中信三级行业指数热度!$E$2:$E$262,MATCH(LARGE($AG$2:$AG$262,16),$AG$2:$AG$262,0)),"") -> 9.5045087 | E43: =IFERROR(INDEX(中信三级行业指数热度!$F$2:$F$262,MATCH(LARGE($AG$2:$AG$262,16),$AG$2:$AG$262,0)),"") -> 12.813784 | F43: =IFERROR(INDEX(中信三级行业指数热度!$G$2:$G$262,MATCH(LARGE($AG$2:$AG$262,16),$AG$2:$AG$262,0)),"") -> 1.2602125 | G43: =IFERROR(INDEX(中信三级行业指数热度!$D$2:$D$262,MATCH(LARGE($AG$2:$AG$262,16),$AG$2:$AG$262,0)),"") -> -6.0961378 | AG43: =IFERROR(中信三级行业指数热度!G43+ROW()*0.0000000001,-9999) -> 0.39896285
B44: 17 | C44: =IFERROR(INDEX(中信三级行业指数热度!$B$2:$B$262,MATCH(LARGE($AG$2:$AG$262,17),$AG$2:$AG$262,0)),"") -> 其他石化指数 | D44: =IFERROR(INDEX(中信三级行业指数热度!$E$2:$E$262,MATCH(LARGE($AG$2:$AG$262,17),$AG$2:$AG$262,0)),"") -> 7.7417234 | E44: =IFERROR(INDEX(中信三级行业指数热度!$F$2:$F$262,MATCH(LARGE($AG$2:$AG$262,17),$AG$2:$AG$262,0)),"") -> 6.8469842 | F44: =IFERROR(INDEX(中信三级行业指数热度!$G$2:$G$262,MATCH(LARGE($AG$2:$AG$262,17),$AG$2:$AG$262,0)),"") -> 1.2059955 | G44: =IFERROR(INDEX(中信三级行业指数热度!$D$2:$D$262,MATCH(LARGE($AG$2:$AG$262,17),$AG$2:$AG$262,0)),"") -> 3.7845098 | AG44: =IFERROR(中信三级行业指数热度!G44+ROW()*0.0000000001,-9999) -> 0.28167707
B45: 18 | C45: =IFERROR(INDEX(中信三级行业指数热度!$B$2:$B$262,MATCH(LARGE($AG$2:$AG$262,18),$AG$2:$AG$262,0)),"") -> 航运指数 | D45: =IFERROR(INDEX(中信三级行业指数热度!$E$2:$E$262,MATCH(LARGE($AG$2:$AG$262,18),$AG$2:$AG$262,0)),"") -> 6.9384061 | E45: =IFERROR(INDEX(中信三级行业指数热度!$F$2:$F$262,MATCH(LARGE($AG$2:$AG$262,18),$AG$2:$AG$262,0)),"") -> 5.376593 | F45: =IFERROR(INDEX(中信三级行业指数热度!$G$2:$G$262,MATCH(LARGE($AG$2:$AG$262,18),$AG$2:$AG$262,0)),"") -> 1.1188516 | G45: =IFERROR(INDEX(中信三级行业指数热度!$D$2:$D$262,MATCH(LARGE($AG$2:$AG$262,18),$AG$2:$AG$262,0)),"") -> 20.034214 | AG45: =IFERROR(中信三级行业指数热度!G45+ROW()*0.0000000001,-9999) -> -0.30594974
B46: 19 | C46: =IFERROR(INDEX(中信三级行业指数热度!$B$2:$B$262,MATCH(LARGE($AG$2:$AG$262,19),$AG$2:$AG$262,0)),"") -> 面板指数 | D46: =IFERROR(INDEX(中信三级行业指数热度!$E$2:$E$262,MATCH(LARGE($AG$2:$AG$262,19),$AG$2:$AG$262,0)),"") -> 11.871478 | E46: =IFERROR(INDEX(中信三级行业指数热度!$F$2:$F$262,MATCH(LARGE($AG$2:$AG$262,19),$AG$2:$AG$262,0)),"") -> 25.642215 | F46: =IFERROR(INDEX(中信三级行业指数热度!$G$2:$G$262,MATCH(LARGE($AG$2:$AG$262,19),$AG$2:$AG$262,0)),"") -> 1.0921849 | G46: =IFERROR(INDEX(中信三级行业指数热度!$D$2:$D$262,MATCH(LARGE($AG$2:$AG$262,19),$AG$2:$AG$262,0)),"") -> 50.277387 | AG46: =IFERROR(中信三级行业指数热度!G46+ROW()*0.0000000001,-9999) -> -0.28323298
B47: 20 | C47: =IFERROR(INDEX(中信三级行业指数热度!$B$2:$B$262,MATCH(LARGE($AG$2:$AG$262,20),$AG$2:$AG$262,0)),"") -> 半导体设备指数 | D47: =IFERROR(INDEX(中信三级行业指数热度!$E$2:$E$262,MATCH(LARGE($AG$2:$AG$262,20),$AG$2:$AG$262,0)),"") -> 12.773946 | E47: =IFERROR(INDEX(中信三级行业指数热度!$F$2:$F$262,MATCH(LARGE($AG$2:$AG$262,20),$AG$2:$AG$262,0)),"") -> 30.866909 | F47: =IFERROR(INDEX(中信三级行业指数热度!$G$2:$G$262,MATCH(LARGE($AG$2:$AG$262,20),$AG$2:$AG$262,0)),"") -> 1.0114438 | G47: =IFERROR(INDEX(中信三级行业指数热度!$D$2:$D$262,MATCH(LARGE($AG$2:$AG$262,20),$AG$2:$AG$262,0)),"") -> 118.03563 | AG47: =IFERROR(中信三级行业指数热度!G47+ROW()*0.0000000001,-9999) -> 1.2687685
AG48: =IFERROR(中信三级行业指数热度!G48+ROW()*0.0000000001,-9999) -> 0.82037274
AG49: =IFERROR(中信三级行业指数热度!G49+ROW()*0.0000000001,-9999) -> 0.020059682
AG50: =IFERROR(中信三级行业指数热度!G50+ROW()*0.0000000001,-9999) -> 0.65350882
AG51: =IFERROR(中信三级行业指数热度!G51+ROW()*0.0000000001,-9999) -> 0.38716009
AG52: =IFERROR(中信三级行业指数热度!G52+ROW()*0.0000000001,-9999) -> 0.058183798
AG53: =IFERROR(中信三级行业指数热度!G53+ROW()*0.0000000001,-9999) -> 0.64794974
AG54: =IFERROR(中信三级行业指数热度!G54+ROW()*0.0000000001,-9999) -> -1.0421845
AG55: =IFERROR(中信三级行业指数热度!G55+ROW()*0.0000000001,-9999) -> 0.70572738
AG56: =IFERROR(中信三级行业指数热度!G56+ROW()*0.0000000001,-9999) -> 0.14980623
AG57: =IFERROR(中信三级行业指数热度!G57+ROW()*0.0000000001,-9999) -> -0.48538454
AG58: =IFERROR(中信三级行业指数热度!G58+ROW()*0.0000000001,-9999) -> -0.10361754
AG59: =IFERROR(中信三级行业指数热度!G59+ROW()*0.0000000001,-9999) -> -0.74501159
... AG262: =IFERROR(中信三级行业指数热度!G262+ROW()*0.0000000001,-9999) -> -0.91476835

Sheet 动量加速度计算逻辑
B1: 短期动量加速度 · 计算逻辑说明
B3: 目的：在 261 个中信三级行业指数中，刻画“短期资金正在加速追捧”的热点。核心思想——不只看“涨没涨”，更看“近期涨速是否比中期更快”（动量的二阶变化 / 加速度）。
B5: 一、数据口径
B6: • 数据源：同花顺 iFinD Excel 插件函数，全部为活公式，打开并登录 iFinD 后自动刷新。
B7: • 价格：指数收盘价 ths_close_price_index（指数无复权问题）。
B8: • 基准日：一律截止【前一交易日 T-1】，由原生Excel WORKDAY/TODAY 推算(工作日近似)，跨周末/节假日自动顺延。
B9: • 三个回看锚点：T0=前一交易日(≈WORKDAY(今天,-1))、T0-5(近一周)、T0-20(近一月)、上年末(YTD基准)。锚点用原生Excel WORKDAY算,不依赖插件,见‘热度’页右侧 AD:AE。
B11: 二、三个区间涨跌幅（D/E/F列）
B12: 用两个交易日的收盘价相除得到区间涨跌幅（避免依赖各版本不一的“区间涨跌幅”字段，自证正确、跨版本通用）：
B13: 近一周涨跌幅% = (收盘价[T-1] / 收盘价[T-5] - 1) × 100
B14: 近一月涨跌幅% = (收盘价[T-1] / 收盘价[T-20] - 1) × 100
B15: YTD涨幅% = (收盘价[T-1] / 收盘价[上年末] - 1) × 100
B16: 对应 iFinD 公式（E列示例，A列为指数代码，$AE$2/$AE$3 为日期锚点）：
B17: =([1]!thsiFinD("ths_close_price_index",$A2,$AE$2,"","")/[1]!thsiFinD("ths_close_price_index",$A2,$AE$3,"","")-1)*100 -> #DIV/0!
B19: 三、动量加速度（G列）—— 本表核心
B20: 定义为“近一周日均涨速”减“近一月日均涨速”，即短期相对中期的提速：
B21: 动量加速度 = 近一周涨幅/5 − 近一月涨幅/20 （单位：% / 交易日）
B22: 对应公式： =E2/5 - F2/20
B23: 解读：
B24: • 加速度 > 0：近一周的涨速高于近一月平均，动量在【加速】——典型的资金短期追捧、趋势刚启动或正在强化。
B25: • 加速度 < 0：近一周涨速低于近一月平均，动量在【减速】——可能见顶钝化或退潮。
B26: • 越大越靠前：把 261 个指数按 G 列降序，最靠前的就是“短期加速最猛”的热点（见‘热点热力图’页 TOP20 自动榜单）。
B27: 为什么用‘速度差’而不是直接看涨幅：同样近一周涨10%，若近一月才涨12%（早已在涨）说明动量在衰减；若近一月仅涨3%说明本周突然提速、资金新进场——加速度能区分这两种，单看涨幅不能。
B29: 四、为什么是‘简单二阶导’而非回归斜率
B30: 主流金工（如趋势强度 TS=β×R²、动量改善 momentum acceleration）常用对 log 价格做时序 OLS 回归取斜率、再差分得加速度。本表按需求用“速度差”这一最简形式近似二阶导：
B31: • 一阶（速度/动量）：区间涨幅本身 ≈ 一阶导；
... B44: • 若 iFinD 账号有单次取数上限：D/E/F 每格各调用 2 次 thsiFinD（约 1500 次/全表），可改为先用辅助列取 T-1/T-5/T-20/年初收盘各一次再做四则运算以减少调用。
